Workbook

Sheet Table of Contents
A1: Table of Contents
A2: Section | B2: Open | C2: Description
A3: Primary workflow
A4: =HYPERLINK("#'Executive Briefing'!A1","Executive Briefing") | B4: =HYPERLINK("#'Executive Briefing'!A1","Open") | C4: Primary executive landing: KPI cards, charts, owner triage, and navigation.
A5: =HYPERLINK("#'Summary'!A1","Summary") | B5: =HYPERLINK("#'Summary'!A1","Open") | C5: Aggregated issue counts, AEO opportunities, and top critical URLs from the run.
A6: =HYPERLINK("#'Priority URLs'!A1","Priority URLs") | B6: =HYPERLINK("#'Priority URLs'!A1","Open") | C6: High-value pages requiring immediate attention based on business risk.
A7: =HYPERLINK("#'FixPlan'!A1","FixPlan") | B7: =HYPERLINK("#'FixPlan'!A1","Open") | C7: Prioritized list of technical and content fixes with estimated effort.
A8: =HYPERLINK("#'Quick Wins'!A1","Quick Wins") | B8: =HYPERLINK("#'Quick Wins'!A1","Open") | C8: Top 15 high-impact, low-effort fixes ranked by traffic and business risk.
A9: =HYPERLINK("#'Content Optimisation Hub'!A1","Content Optimisation Hub") | B9: =HYPERLINK("#'Content Optimisation Hub'!A1","Open") | C9: Diagnostic command center: live title, meta, and H1–H6 health plus on-page score.
A10: =HYPERLINK("#'Content Planner'!A1","Content Planner") | B10: =HYPERLINK("#'Content Planner'!A1","Open") | C10: Page-level workflow tracker: nav/footer site structure with copywriting, design, and client sign-off status columns.
A11: =HYPERLINK("#'Content Hub Metrics'!A1","Content Hub Metrics") | B11: =HYPERLINK("#'Content Hub Metrics'!A1","Open") | C11: Per-URL crawl metrics (JS/rendered words, field CWV), anchor diversity, and executive ROI estimates aligned with the Content Hub URL set.
A12: =HYPERLINK("#'Main'!A1","Main") | B12: =HYPERLINK("#'Main'!A1","Open") | C12: Primary URL inventory with titles, meta descriptions, and crawl signals.
A13: =HYPERLINK("#'AIOSEO Recommendations'!A1","AIOSEO Recommendations") | B13: =HYPERLINK("#'AIOSEO Recommendations'!A1","Open") | C13: Plugin-aligned recommendations and edit links for AIOSEO users.
A14: =HYPERLINK("#'Link Inventory'!A1","Link Inventory") | B14: =HYPERLINK("#'Link Inventory'!A1","Open") | C14: Every anchor-level outbound link with type, rel attributes, status codes, and generic-anchor flags.
A15: =HYPERLINK("#'Broken Link Impact'!A1","Broken Link Impact") | B15: =HYPERLINK("#'Broken Link Impact'!A1","Open") | C15: Broken destinations ranked by inbound link count and source-page GSC clicks.
A16: =HYPERLINK("#'SitemapQA'!A1","SitemapQA") | B16: =HYPERLINK("#'SitemapQA'!A1","Open") | C16: Sitemap coverage, URL membership checks, and sitemap metadata QA.
A17: =HYPERLINK("#'Template & Duplication Risks'!A1","Template & Duplication Risks") | B17: =HYPERLINK("#'Template & Duplication Risks'!A1","Open") | C17: Duplicate titles/meta, draft/copy pages, and folder-level template pattern risks.
A18: =HYPERLINK("#'Playbook'!A1","Playbook") | B18: =HYPERLINK("#'Playbook'!A1","Open") | C18: Client education reference: editorial standards plus per-issue playbooks with what/why/fix/verify guidance.
A19: Technical & Historical (Advanced) — tabs hidden; use Open links or right-click tab bar → Unhide Sheet
A20: =HYPERLINK("#'Issue Register'!A1","Issue Register") | B20: =HYPERLINK("#'Issue Register'!A1","Open") | C20: Tracked issue backlog with first-seen dates, days open, assignment fields, and client notes. Unified rollups from Summary plus per-URL issue rows.
A21: =HYPERLINK("#'Technical Diagnostics'!A1","Technical Diagnostics") | B21: =HYPERLINK("#'Technical Diagnostics'!A1","Open") | C21: Per-URL technical, indexability, redirect, security, PSI, and Search Console signals.
A22: =HYPERLINK("#'Content & AI Readiness'!A1","Content & AI Readiness") | B22: =HYPERLINK("#'Content & AI Readiness'!A1","Open") | C22: Per-URL content depth, schema, media, and answer-engine readiness metrics.
A23: =HYPERLINK("#'Link Intelligence'!A1","Link Intelligence") | B23: =HYPERLINK("#'Link Intelligence'!A1","Open") | C23: Per-URL internal link summary rows plus anchor-level detail for broken-link triage.
A24: =HYPERLINK("#'CMS Action URLs'!A1","CMS Action URLs") | B24: =HYPERLINK("#'CMS Action URLs'!A1","Open") | C24: WooCommerce and other CMS action-parameter URLs discovered during the crawl (for example add-to-cart) that were withheld from the crawl queue.
A25: =HYPERLINK("#'Redirects'!A1","Redirects") | B25: =HYPERLINK("#'Redirects'!A1","Open") | C25: Redirect chains, hop lists, HTTPS upgrades, and loop detection.
A26: =HYPERLINK("#'Redirect Map'!A1","Redirect Map") | B26: =HYPERLINK("#'Redirect Map'!A1","Open") | C26: Per-source redirect chains with hop status codes, 302 flags, and SEO risk notes.
A27: =HYPERLINK("#'Robots.txt Analysis'!A1","Robots.txt Analysis") | B27: =HYPERLINK("#'Robots.txt Analysis'!A1","Open") | C27: Parsed robots.txt content, user-agent rules, blocked URLs, and sitemap conflicts.
A28: =HYPERLINK("#'Crawl Log'!A1","Crawl Log") | B28: =HYPERLINK("#'Crawl Log'!A1","Open") | C28: Errors and warnings from fetch, render, PSI, and GSC phases for this audit run.
A29: =HYPERLINK("#'Link Equity Map'!A1","Link Equity Map") | B29: =HYPERLINK("#'Link Equity Map'!A1","Open") | C29: Internal PageRank distribution: inlink/outlink counts and equity flow per URL.
A30: =HYPERLINK("#'Anchor Text Audit'!A1","Anchor Text Audit") | B30: =HYPERLINK("#'Anchor Text Audit'!A1","Open") | C30: Anchor-text profile per destination: distribution, generic-anchor share, and diversity.
A31: =HYPERLINK("#'Snippet Opportunities'!A1","Snippet Opportunities") | B31: =HYPERLINK("#'Snippet Opportunities'!A1","Open") | C31: Pages with answer-block potential for featured snippets and AI answer extraction.
A32: =HYPERLINK("#'Script Inventory'!A1","Script Inventory") | B32: =HYPERLINK("#'Script Inventory'!A1","Open") | C32: Third-party and first-party scripts per URL with blocking and privacy implications.
A33: =HYPERLINK("#'Image Inventory'!A1","Image Inventory") | B33: =HYPERLINK("#'Image Inventory'!A1","Open") | C33: Every image with alt-text coverage, filename quality, dimensions, and mixed-content flags.
A34: =HYPERLINK("#'ResolvedIssues'!A1","ResolvedIssues") | B34: =HYPERLINK("#'ResolvedIssues'!A1","Open") | C34: Issues marked resolved when compared to the previous export. First runs show a baseline note when no previous export was supplied.
A35: =HYPERLINK("#'DeltaFromPreviousRun'!A1","DeltaFromPreviousRun") | B35: =HYPERLINK("#'DeltaFromPreviousRun'!A1","Open") | C35: New, resolved, and persistent issues compared to a prior audit workbook or delta JSON. Sections: summary counts, new issues, resolved issues, metric changes, and SEO health trend. First runs show a baseline note when no previous export was supplied.
A36: =HYPERLINK("#'Audit Run Details'!A1","Audit Run Details") | B36: =HYPERLINK("#'Audit Run Details'!A1","Open") | C36: Run configuration, timestamps, and environment notes.

Sheet Executive Briefing
A1: 🐸 HYPE FROG: SEO & AEO Intelligence Report
A2: SEO health is 61% across 83 crawled URLs. 80 URL(s) (96%) carry Critical or Warning badges. If those were cleared, blended SEO health could reach ~95% (+34 pts) — an illustrative ceiling from the export model (90% of remaining headroom × open-issue share). Technical, PSI, and AEO components use the same conservative formula in the chart below; they are not guaranteed to move in lockstep. Source tables: row 114+.
A3: =IFERROR(INDEX('Audit Run Details'!$B:$B,MATCH("Total URLs",'Audit Run Details'!$A:$A,0)),"") & " URLs crawled"
A4: Audit Run Details | B4: Value
A5: Run Date | B5: =IFERROR(INDEX('Audit Run Details'!$B:$B,MATCH("Run Timestamp",'Audit Run Details'!$A:$A,0)),"")
A7: SEO Health (now) | C7: SEO Health (illustrative projected) | E7: AEO Readiness | G7: Critical URLs | I7: Traffic Lift (est.) | K7: Performance (PSI)
A8: 61% | C8: 95% | E8: 92% | G8: 17 | I8: 0 | K8: 88
A9: Key insights: 17 URL(s) carry a Critical badge and need urgent attention. | 63 URL(s) are in Warning state — schedule fixes before they escalate. | Largest theme: "Render Blocking Resources" touches 83 URL(s) (see Fix Plan). | 6 URL(s) returned 4xx/5xx during the crawl.
A10: Health & illustrative projection
A29: Issue distribution — unique URLs vs issue instances (see source row 60+)
A48: Priority pages & content readiness
A67: Top issues to fix first (by affected URLs)
G88: OWNER ISSUE SUMMARY | M88: Quick Navigation | N88: Open
G89: Owner | H89: Issue Rows | I89: Affected URLs | J89: Critical | K89: Warning | M89: Issue Summary | N89: =HYPERLINK("#Summary!A1","Open")
G90: =HYPERLINK("#'FixPlan'!A1","Copy Writer") | H90: =COUNTIF(OFFSET('FixPlan'!$A$1,2,MATCH("Owner",'FixPlan'!$2:$2,0)-1,99998,1),"Copy Writer") | I90: =SUMIF(OFFSET('FixPlan'!$A$1,2,MATCH("Owner",'FixPlan'!$2:$2,0)-1,99998,1),"Copy Writer",OFFSET('FixPlan'!$A$1,2,MATCH("Affected Count",'FixPlan'!$2:$2,0)-1,99998,1)) | J90: =COUNTIFS(OFFSET('FixPlan'!$A$1,2,MATCH("Owner",'FixPlan'!$2:$2,0)-1,99998,1),"Copy Writer",OFFSET('FixPlan'!$A$1,2,MATCH("Severity",'FixPlan'!$2:$2,0)-1,99998,1),"Critical") | K90: =COUNTIFS(OFFSET('FixPlan'!$A$1,2,MATCH("Owner",'FixPlan'!$2:$2,0)-1,99998,1),"Copy Writer",OFFSET('FixPlan'!$A$1,2,MATCH("Severity",'FixPlan'!$2:$2,0)-1,99998,1),"Warning")+COUNTIFS(OFFSET('FixPlan'!$A$1,2,MATCH("Owner",'FixPlan'!$2:$2,0)-1,99998,1),"Copy Writer",OFFSET('FixPlan'!$A$1,2,MATCH("Severity",'FixPlan'!$2:$2,0)-1,99998,1),"Needs Work") | M90: Fix Plan | N90: =HYPERLINK("#FixPlan!A1","Open")
G91: =HYPERLINK("#'FixPlan'!A1","Dev") | H91: =COUNTIF(OFFSET('FixPlan'!$A$1,2,MATCH("Owner",'FixPlan'!$2:$2,0)-1,99998,1),"Dev") | I91: =SUMIF(OFFSET('FixPlan'!$A$1,2,MATCH("Owner",'FixPlan'!$2:$2,0)-1,99998,1),"Dev",OFFSET('FixPlan'!$A$1,2,MATCH("Affected Count",'FixPlan'!$2:$2,0)-1,99998,1)) | J91: =COUNTIFS(OFFSET('FixPlan'!$A$1,2,MATCH("Owner",'FixPlan'!$2:$2,0)-1,99998,1),"Dev",OFFSET('FixPlan'!$A$1,2,MATCH("Severity",'FixPlan'!$2:$2,0)-1,99998,1),"Critical") | K91: =COUNTIFS(OFFSET('FixPlan'!$A$1,2,MATCH("Owner",'FixPlan'!$2:$2,0)-1,99998,1),"Dev",OFFSET('FixPlan'!$A$1,2,MATCH("Severity",'FixPlan'!$2:$2,0)-1,99998,1),"Warning")+COUNTIFS(OFFSET('FixPlan'!$A$1,2,MATCH("Owner",'FixPlan'!$2:$2,0)-1,99998,1),"Dev",OFFSET('FixPlan'!$A$1,2,MATCH("Severity",'FixPlan'!$2:$2,0)-1,99998,1),"Needs Work") | M91: Main URL Data | N91: =HYPERLINK("#Main!A1","Open")
G92: =HYPERLINK("#'FixPlan'!A1","Server/Host") | H92: =COUNTIF(OFFSET('FixPlan'!$A$1,2,MATCH("Owner",'FixPlan'!$2:$2,0)-1,99998,1),"Server/Host") | I92: =SUMIF(OFFSET('FixPlan'!$A$1,2,MATCH("Owner",'FixPlan'!$2:$2,0)-1,99998,1),"Server/Host",OFFSET('FixPlan'!$A$1,2,MATCH("Affected Count",'FixPlan'!$2:$2,0)-1,99998,1)) | J92: =COUNTIFS(OFFSET('FixPlan'!$A$1,2,MATCH("Owner",'FixPlan'!$2:$2,0)-1,99998,1),"Server/Host",OFFSET('FixPlan'!$A$1,2,MATCH("Severity",'FixPlan'!$2:$2,0)-1,99998,1),"Critical") | K92: =COUNTIFS(OFFSET('FixPlan'!$A$1,2,MATCH("Owner",'FixPlan'!$2:$2,0)-1,99998,1),"Server/Host",OFFSET('FixPlan'!$A$1,2,MATCH("Severity",'FixPlan'!$2:$2,0)-1,99998,1),"Warning")+COUNTIFS(OFFSET('FixPlan'!$A$1,2,MATCH("Owner",'FixPlan'!$2:$2,0)-1,99998,1),"Server/Host",OFFSET('FixPlan'!$A$1,2,MATCH("Severity",'FixPlan'!$2:$2,0)-1,99998,1),"Needs Work") | M92: Technical Diagnostics | N92: =HYPERLINK("#'Technical Diagnostics'!A1","Open")
M93: Indexability | N93: =HYPERLINK("#'Technical Diagnostics'!A1","Open")
M94: AEO Opportunities | N94: =HYPERLINK("#'Content & AI Readiness'!A1","Open")
M95: AIOSEO Recommendations | N95: =HYPERLINK("#'AIOSEO Recommendations'!A1","Open")
M96: Content Hub | N96: =HYPERLINK("#'Content Optimisation Hub'!A1","Open")
M98: Advanced Sheets
M99: Technical & historical tabs are hidden to reduce clutter. Use the links below or Home → Format → Hide & Unhide → Unhide Sheet.
M101: Issue Register (canonical backlog) | N101: =HYPERLINK("#'Issue Register'!A1","Open")
M102: Technical Diagnostics | N102: =HYPERLINK("#'Technical Diagnostics'!A1","Open")
M103: Content & AI Readiness | N103: =HYPERLINK("#'Content & AI Readiness'!A1","Open")
M104: Link Intelligence | N104: =HYPERLINK("#'Link Intelligence'!A1","Open")
M105: CMS Action URLs | N105: =HYPERLINK("#'CMS Action URLs'!A1","Open")
M106: Redirects | N106: =HYPERLINK("#'Redirects'!A1","Open")
M107: Redirect Map | N107: =HYPERLINK("#'Redirect Map'!A1","Open")
M108: Robots.txt Analysis | N108: =HYPERLINK("#'Robots.txt Analysis'!A1","Open")
M109: Crawl Log | N109: =HYPERLINK("#'Crawl Log'!A1","Open")
M110: Audit Run Details | N110: =HYPERLINK("#'Audit Run Details'!A1","Open")
M111: Resolved Issues | N111: =HYPERLINK("#'ResolvedIssues'!A1","Open")
A112: ▼ Chart source data begins row 114 (columns A–C) | M112: Delta From Previous Run | N112: =HYPERLINK("#'DeltaFromPreviousRun'!A1","Open")
A114: Chart source data (scroll down — used by charts above)
A115: Health comparison
A116: Metric | B116: Current | C116: Illustrative projected
A117: SEO Health | B117: 61.3 | C117: 94.9
A118: Technical Health | B118: 61.3 | C118: 94.9
A119: Performance (PSI) | B119: 88 | C119: 98.4
A120: LCP (Lab Mobile avg) | B120: 2.4 | C120: 2.5
A121: Accessibility (avg) | B121: 85 | C121: 90
A122: AEO Readiness | B122: 92.4 | C122: 99
A123: Severity — unique URLs vs issue instances
A124: Severity | B124: Unique URLs | C124: Issue instances
A125: Critical | B125: 17 | C125: 17
A126: Warning | B126: 63 | C126: 135
A127: Observation | B127: 3 | C127: 370
A130: Owner workload — unique URLs vs issue instances
A131: Owner | B131: Unique URLs | C131: Issue instances
A132: Copy Writer | B132: 66 | C132: 256
A133: Server/Host | B133: 11 | C133: 11
A134: Dev | B134: 6 | C134: 255
A139: Top business risk URLs (chart excludes cart/checkout/thank-you pages)
A140: Page | B140: Business Risk Score
A141: africanmarketingconfederation.org | B141: 130
A142: smoke-archive/page-13 | B142: 130
A143: smoke-archive/page-17 | B143: 130
A144: smoke-archive/page-26 | B144: 130
A145: smoke-archive/page-34 | B145: 130
A146: smoke-archive/page-39 | B146: 130
A147: smoke-archive/page-51 | B147: 130
A148: smoke-archive/page-52 | B148: 130
A151: Content readiness
A152: Metric | B152: Percent
A153: Good H1 | B153: 100
A154: Meta description | B154: 81.9
A155: Answer paragraphs | B155: 89.2
A156: Schema present | B156: 0
A157: Image alt ≥80% | B157: 84.3
A158: Question headings | B158: 89.2
A159: SEO health — export projection model
A160: Metric | B160: Percent
A161: Current SEO Health | B161: 61.3
A162: Illustrative projected SEO Health | B162: 94.9
A163: Model: current + (100-current) × open-issue share × 0.9 (matches export_flow)
A164: Top issues by URL impact
A165: Issue | B165: Affected URLs
A166: No Consent Manager Detected | B166: 83
A167: Lab TBT 150ms–300ms (Mobile) | B167: 83
A168: Moderate Lighthouse Performance Mobile … | B168: 83
A169: Render Blocking Resources | B169: 83
A170: Missing OG Image | B170: 63
A171: Missing Meta Description | B171: 15
A172: Missing OG Description | B172: 15
A173: Low Image Alt Coverage | B173: 13

Sheet Summary
A1: ← Return to Executive Briefing | C1: =IFERROR(INDEX('Audit Run Details'!$B:$B,MATCH("Target Site",'Audit Run Details'!$A:$A,0)),"") & " — " & IFERROR(INDEX('Audit Run Details'!$B:$B,MATCH("Total URLs",'Audit Run Details'!$A:$A,0)),"") & " URLs crawled — " & LEFT(IFERROR(INDEX('Audit Run Details'!$B:$B,MATCH("Run Timestamp",'Audit Run Details'!$A:$A,0)),""),10)
A2: Section | B2: Severity | C2: Issue | D2: Affected URL Count | E2: Reference Tab | F2: Affected URLs (sample)
A3: AEO Opportunities | B3: Warning | C3: Low AEO Readiness Score | D3: 9 | E3: Content & AI Readiness | F3: https://africanmarketingconfederation.org/smoke-archive/page-9 | https://africanmarketingconfederation.org/smoke-archive/page-18 | https://africanmarketingconfederation.org/smoke-archive/page-27 | https://africanmarketingconfederation.org/smoke-archive/page-36 | https://africanmarketingconfederation.org/smoke-archive/page-45 | https://africanmarketingconfederation.org/smoke-archive/page-54 | https://africanmarketingconfederation.org/smoke-archive/page-63 | https://africanmarketingconfederation.org/smoke-archive/page-72 | https://africanmarketingconfederation.org/discovered-via-bfs-1 || Full list: see Content & AI Readiness tab
A4: AEO Opportunities | B4: Warning | C4: Missing FAQ/QA Schema | D4: 0 | E4: Content & AI Readiness | F4: || Full list: see Content & AI Readiness tab
A5: AEO Opportunities | B5: Observation | C5: No 40-60 Word Answer Paragraphs | D5: 9 | E5: Content & AI Readiness | F5: https://africanmarketingconfederation.org/smoke-archive/page-9 | https://africanmarketingconfederation.org/smoke-archive/page-18 | https://africanmarketingconfederation.org/smoke-archive/page-27 | https://africanmarketingconfederation.org/smoke-archive/page-36 | https://africanmarketingconfederation.org/smoke-archive/page-45 | https://africanmarketingconfederation.org/smoke-archive/page-54 | https://africanmarketingconfederation.org/smoke-archive/page-63 | https://africanmarketingconfederation.org/smoke-archive/page-72 | https://africanmarketingconfederation.org/discovered-via-bfs-1 || Full list: see Content & AI Readiness tab
A6: AEO Opportunities | B6: Observation | C6: No Answer-Friendly Structure | D6: 9 | E6: Content & AI Readiness | F6: https://africanmarketingconfederation.org/smoke-archive/page-9 | https://africanmarketingconfederation.org/smoke-archive/page-18 | https://africanmarketingconfederation.org/smoke-archive/page-27 | https://africanmarketingconfederation.org/smoke-archive/page-36 | https://africanmarketingconfederation.org/smoke-archive/page-45 | https://africanmarketingconfederation.org/smoke-archive/page-54 | https://africanmarketingconfederation.org/smoke-archive/page-63 | https://africanmarketingconfederation.org/smoke-archive/page-72 | https://africanmarketingconfederation.org/discovered-via-bfs-1 || Full list: see Content & AI Readiness tab
A7: AEO Opportunities | B7: Observation | C7: No Question Headings | D7: 9 | E7: Content & AI Readiness | F7: https://africanmarketingconfederation.org/smoke-archive/page-9 | https://africanmarketingconfederation.org/smoke-archive/page-18 | https://africanmarketingconfederation.org/smoke-archive/page-27 | https://africanmarketingconfederation.org/smoke-archive/page-36 | https://africanmarketingconfederation.org/smoke-archive/page-45 | https://africanmarketingconfederation.org/smoke-archive/page-54 | https://africanmarketingconfederation.org/smoke-archive/page-63 | https://africanmarketingconfederation.org/smoke-archive/page-72 | https://africanmarketingconfederation.org/discovered-via-bfs-1 || Full list: see Content & AI Readiness tab
A8: AEO Opportunities | F8: Detailed rows: see Content & AI Readiness tab
A9: Issue Counts | B9: Critical | C9: Non-200 Status | D9: 11 | E9: Technical Diagnostics | F9: https://africanmarketingconfederation.org/ | https://africanmarketingconfederation.org/smoke-archive/page-13 | https://africanmarketingconfederation.org/smoke-archive/page-17 | https://africanmarketingconfederation.org/smoke-archive/page-26 | https://africanmarketingconfederation.org/smoke-archive/page-34 | https://africanmarketingconfederation.org/smoke-archive/page-39 | https://africanmarketingconfederation.org/smoke-archive/page-51 | https://africanmarketingconfederation.org/smoke-archive/page-52 | https://africanmarketingconfederation.org/smoke-archive/page-65 | https://africanmarketingconfederation.org/smoke-archive/page-68 | https://africanmarketingconfederation.org/smoke-archive/page-78 || Full list: see Technical Diagnostics / Link Intelligence tabs
A10: Issue Counts | B10: Critical | C10: No Schema Markup | D10: 6 | E10: Technical Diagnostics | F10: https://africanmarketingconfederation.org/smoke-archive/page-12 | https://africanmarketingconfederation.org/smoke-archive/page-24 | https://africanmarketingconfederation.org/smoke-archive/page-36 | https://africanmarketingconfederation.org/smoke-archive/page-48 | https://africanmarketingconfederation.org/smoke-archive/page-60 | https://africanmarketingconfederation.org/smoke-archive/page-72 || Full list: see Technical Diagnostics / Link Intelligence tabs
A11: Issue Counts | B11: Critical | C11: Blocked by Googlebot | D11: 0 | E11: Technical Diagnostics | F11: || Full list: see Technical Diagnostics / Link Intelligence tabs
A12: Issue Counts | B12: Critical | C12: Broken Internal Links | D12: 0 | E12: Link Intelligence | F12: || Full list: see Technical Diagnostics / Link Intelligence tabs
A13: Issue Counts | B13: Critical | C13: CWV LCP Above 4.0s (Field Data) | D13: 0 | E13: Technical Diagnostics | F13: || Full list: see Technical Diagnostics / Link Intelligence tabs
A14: Issue Counts | B14: Critical | C14: Canonical Loop | D14: 0 | E14: Technical Diagnostics | F14: || Full list: see Technical Diagnostics / Link Intelligence tabs
A15: Issue Counts | B15: Critical | C15: Canonical Points Elsewhere | D15: 0 | E15: Technical Diagnostics | F15: || Full list: see Technical Diagnostics / Link Intelligence tabs
A16: Issue Counts | B16: Critical | C16: Canonical Points to Broken URL | D16: 0 | E16: Technical Diagnostics | F16: || Full list: see Technical Diagnostics / Link Intelligence tabs
A17: Issue Counts | B17: Critical | C17: High Broken Image Count (>3) | D17: 0 | E17: Technical Diagnostics | F17: || Full list: see Technical Diagnostics / Link Intelligence tabs
A18: Issue Counts | B18: Critical | C18: In Sitemap but Blocked by Googlebot | D18: 0 | E18: Technical Diagnostics | F18: || Full list: see Technical Diagnostics / Link Intelligence tabs
A19: Issue Counts | B19: Critical | C19: Lab LCP Above 4.0s (Mobile) | D19: 0 | E19: Technical Diagnostics | F19: || Full list: see Technical Diagnostics / Link Intelligence tabs
A20: Issue Counts | B20: Critical | C20: Missing Title | D20: 0 | E20: Technical Diagnostics | F20: || Full list: see Technical Diagnostics / Link Intelligence tabs
... A107: Issue Counts | B107: Observation | C107: llms.txt Missing | D107: 0 | E107: Technical Diagnostics | F107: || Full list: see Technical Diagnostics / Link Intelligence tabs
A108: Issue Counts
A109: Top 10 Critical URLs
A110: Top 10 Critical URLs | B110: Critical | C110: #1 https://africanmarketingconfederation.org/ | D110: 1 | E110: Priority URLs | F110: Non-200 Status
A111: Top 10 Critical URLs | B111: Critical | C111: #2 https://africanmarketingconfederation.org/smoke-archive/page-13 | D111: 1 | E111: Priority URLs | F111: Non-200 Status
A112: Top 10 Critical URLs | B112: Critical | C112: #3 https://africanmarketingconfederation.org/smoke-archive/page-17 | D112: 1 | E112: Priority URLs | F112: Non-200 Status
A113: Top 10 Critical URLs | B113: Critical | C113: #4 https://africanmarketingconfederation.org/smoke-archive/page-26 | D113: 1 | E113: Priority URLs | F113: Non-200 Status
A114: Top 10 Critical URLs | B114: Critical | C114: #5 https://africanmarketingconfederation.org/smoke-archive/page-34 | D114: 1 | E114: Priority URLs | F114: Non-200 Status
A115: Top 10 Critical URLs | B115: Critical | C115: #6 https://africanmarketingconfederation.org/smoke-archive/page-39 | D115: 1 | E115: Priority URLs | F115: Non-200 Status
A116: Top 10 Critical URLs | B116: Critical | C116: #7 https://africanmarketingconfederation.org/smoke-archive/page-51 | D116: 1 | E116: Priority URLs | F116: Non-200 Status
A117: Top 10 Critical URLs | B117: Critical | C117: #8 https://africanmarketingconfederation.org/smoke-archive/page-52 | D117: 1 | E117: Priority URLs | F117: Non-200 Status
A118: Top 10 Critical URLs | B118: Critical | C118: #9 https://africanmarketingconfederation.org/smoke-archive/page-65 | D118: 1 | E118: Priority URLs | F118: Non-200 Status
A119: Top 10 Critical URLs | B119: Critical | C119: #10 https://africanmarketingconfederation.org/smoke-archive/page-68 | D119: 1 | E119: Priority URLs | F119: Non-200 Status
A120: Top Issues by Template
A121: Top Issues by Template | B121: Observation | C121: /smoke-archive/ -> No Consent Manager Detected | D121: 69 | E121: Template & Duplication Risks
A122: Top Issues by Template | B122: Observation | C122: /smoke-archive/ -> Lab TBT 150ms–300ms (Mobile) | D122: 69 | E122: Template & Duplication Risks
A123: Top Issues by Template | B123: Observation | C123: /smoke-archive/ -> Moderate Lighthouse Performance Mobile (50–89) | D123: 69 | E123: Template & Duplication Risks
A124: Top Issues by Template | B124: Observation | C124: /smoke-archive/ -> Render Blocking Resources | D124: 69 | E124: Template & Duplication Risks
A125: Top Issues by Template | B125: Observation | C125: /smoke-archive/ -> Missing OG Image | D125: 52 | E125: Template & Duplication Risks
A126: Top Issues by Template | B126: Observation | C126: /smoke-archive/ -> Missing Meta Description | D126: 14 | E126: Template & Duplication Risks
A127: Top Issues by Template | B127: Observation | C127: /smoke-archive/ -> Missing OG Description | D127: 14 | E127: Template & Duplication Risks
A128: Top Issues by Template | B128: Observation | C128: /smoke-archive/ -> Low Image Alt Coverage | D128: 12 | E128: Template & Duplication Risks
A129: Top Issues by Template | B129: Observation | C129: /smoke-archive/ -> Low E-E-A-T Signal Score (<3) | D129: 11 | E129: Template & Duplication Risks
A130: Top Issues by Template | B130: Observation | C130: /smoke-archive/ -> No Author Attribution | D130: 11 | E130: Template & Duplication Risks
A131: Top Issues by Template | B131: Observation | C131: /smoke-archive/ -> Non-200 Status | D131: 10 | E131: Template & Duplication Risks
A132: Top Issues by Template | B132: Observation | C132: /smoke-archive/ -> Missing OG Title | D132: 9 | E132: Template & Duplication Risks
... A140: Top Issues by Template | B140: Observation | C140: /discovered-via-bfs-1/ -> Low AEO Readiness Score | D140: 1 | E140: Template & Duplication Risks

Sheet Priority URLs
A1: ← Return to Executive Briefing | C1: =IFERROR(INDEX('Audit Run Details'!$B:$B,MATCH("Target Site",'Audit Run Details'!$A:$A,0)),"") & " — " & IFERROR(INDEX('Audit Run Details'!$B:$B,MATCH("Total URLs",'Audit Run Details'!$A:$A,0)),"") & " URLs crawled — " & LEFT(IFERROR(INDEX('Audit Run Details'!$B:$B,MATCH("Run Timestamp",'Audit Run Details'!$A:$A,0)),""),10)
A2: URL | B2: Business Risk Score | C2: Severity Badge | D2: SEO Health Score | E2: GSC Impressions | F2: GSC CTR | G2: GSC Data Freshness | H2: GSC Coverage Note | I2: Revenue Intent | J2: Critical Issues Count | K2: Warning Issues Count | L2: Action Needed | M2: Why Prioritized | N2: Owner | O2: Status | P2: Sprint | Q2: Indexability Reason | R2: Broken Internal Links Count | S2: Canonical Type | T2: Open in Main | U2: Open in Technical
A3: https://africanmarketingconfederation.org/ | B3: 130 | C3: Critical | D3: 0 | E3: 1524 | F3: 0.0341 | G3: 2026-06-01 to 2026-06-30 (30-day window; excludes today; typical GSC lag ~48h) | H3: Matched in GSC — Search Analytics (30-day window) | I3: Standard | J3: 1 | K3: 0 | L3: Yes | M3: Has critical issues | N3: Dev | O3: Open | R3: 0 | T3: =IFERROR(HYPERLINK("#'Main'!B"&MATCH(TRIM(A3),'Main'!B:B,0),"Open"),HYPERLINK("#'Main'!B1","Open")) | U3: =IFERROR(HYPERLINK("#'Technical Diagnostics'!A"&MATCH(A3,'Technical Diagnostics'!A:A,0),"Open"),HYPERLINK("#'Technical Diagnostics'!A1","Open"))
A4: https://africanmarketingconfederation.org/smoke-archive/page-13 | B4: 130 | C4: Critical | D4: 0 | F4: 0 | G4: 2026-06-01 to 2026-06-30 (30-day window; excludes today; typical GSC lag ~48h) | H4: No Search Analytics row matched this URL in the 30-day export (compare Final URL with the page URL shown in GSC) | I4: Standard | J4: 1 | K4: 0 | L4: Yes | M4: Has critical issues | N4: Dev | O4: Open | R4: 0 | T4: =IFERROR(HYPERLINK("#'Main'!B"&MATCH(TRIM(A4),'Main'!B:B,0),"Open"),HYPERLINK("#'Main'!B1","Open")) | U4: =IFERROR(HYPERLINK("#'Technical Diagnostics'!A"&MATCH(A4,'Technical Diagnostics'!A:A,0),"Open"),HYPERLINK("#'Technical Diagnostics'!A1","Open"))
A5: https://africanmarketingconfederation.org/smoke-archive/page-17 | B5: 130 | C5: Critical | D5: 0 | F5: 0 | G5: 2026-06-01 to 2026-06-30 (30-day window; excludes today; typical GSC lag ~48h) | H5: No Search Analytics row matched this URL in the 30-day export (compare Final URL with the page URL shown in GSC) | I5: Standard | J5: 1 | K5: 0 | L5: Yes | M5: Has critical issues | N5: Dev | O5: Open | R5: 0 | T5: =IFERROR(HYPERLINK("#'Main'!B"&MATCH(TRIM(A5),'Main'!B:B,0),"Open"),HYPERLINK("#'Main'!B1","Open")) | U5: =IFERROR(HYPERLINK("#'Technical Diagnostics'!A"&MATCH(A5,'Technical Diagnostics'!A:A,0),"Open"),HYPERLINK("#'Technical Diagnostics'!A1","Open"))
A6: https://africanmarketingconfederation.org/smoke-archive/page-26 | B6: 130 | C6: Critical | D6: 0 | F6: 0 | G6: 2026-06-01 to 2026-06-30 (30-day window; excludes today; typical GSC lag ~48h) | H6: No Search Analytics row matched this URL in the 30-day export (compare Final URL with the page URL shown in GSC) | I6: Standard | J6: 1 | K6: 0 | L6: Yes | M6: Has critical issues | N6: Dev | O6: Open | R6: 0 | T6: =IFERROR(HYPERLINK("#'Main'!B"&MATCH(TRIM(A6),'Main'!B:B,0),"Open"),HYPERLINK("#'Main'!B1","Open")) | U6: =IFERROR(HYPERLINK("#'Technical Diagnostics'!A"&MATCH(A6,'Technical Diagnostics'!A:A,0),"Open"),HYPERLINK("#'Technical Diagnostics'!A1","Open"))
A7: https://africanmarketingconfederation.org/smoke-archive/page-34 | B7: 130 | C7: Critical | D7: 0 | F7: 0 | G7: 2026-06-01 to 2026-06-30 (30-day window; excludes today; typical GSC lag ~48h) | H7: No Search Analytics row matched this URL in the 30-day export (compare Final URL with the page URL shown in GSC) | I7: Standard | J7: 1 | K7: 0 | L7: Yes | M7: Has critical issues | N7: Dev | O7: Open | R7: 0 | T7: =IFERROR(HYPERLINK("#'Main'!B"&MATCH(TRIM(A7),'Main'!B:B,0),"Open"),HYPERLINK("#'Main'!B1","Open")) | U7: =IFERROR(HYPERLINK("#'Technical Diagnostics'!A"&MATCH(A7,'Technical Diagnostics'!A:A,0),"Open"),HYPERLINK("#'Technical Diagnostics'!A1","Open"))
A8: https://africanmarketingconfederation.org/smoke-archive/page-39 | B8: 130 | C8: Critical | D8: 0 | F8: 0 | G8: 2026-06-01 to 2026-06-30 (30-day window; excludes today; typical GSC lag ~48h) | H8: No Search Analytics row matched this URL in the 30-day export (compare Final URL with the page URL shown in GSC) | I8: Standard | J8: 1 | K8: 0 | L8: Yes | M8: Has critical issues | N8: Dev | O8: Open | R8: 0 | T8: =IFERROR(HYPERLINK("#'Main'!B"&MATCH(TRIM(A8),'Main'!B:B,0),"Open"),HYPERLINK("#'Main'!B1","Open")) | U8: =IFERROR(HYPERLINK("#'Technical Diagnostics'!A"&MATCH(A8,'Technical Diagnostics'!A:A,0),"Open"),HYPERLINK("#'Technical Diagnostics'!A1","Open"))
A9: https://africanmarketingconfederation.org/smoke-archive/page-51 | B9: 130 | C9: Critical | D9: 0 | F9: 0 | G9: 2026-06-01 to 2026-06-30 (30-day window; excludes today; typical GSC lag ~48h) | H9: No Search Analytics row matched this URL in the 30-day export (compare Final URL with the page URL shown in GSC) | I9: Standard | J9: 1 | K9: 0 | L9: Yes | M9: Has critical issues | N9: Dev | O9: Open | R9: 0 | T9: =IFERROR(HYPERLINK("#'Main'!B"&MATCH(TRIM(A9),'Main'!B:B,0),"Open"),HYPERLINK("#'Main'!B1","Open")) | U9: =IFERROR(HYPERLINK("#'Technical Diagnostics'!A"&MATCH(A9,'Technical Diagnostics'!A:A,0),"Open"),HYPERLINK("#'Technical Diagnostics'!A1","Open"))
A10: https://africanmarketingconfederation.org/smoke-archive/page-52 | B10: 130 | C10: Critical | D10: 0 | F10: 0 | G10: 2026-06-01 to 2026-06-30 (30-day window; excludes today; typical GSC lag ~48h) | H10: No Search Analytics row matched this URL in the 30-day export (compare Final URL with the page URL shown in GSC) | I10: Standard | J10: 1 | K10: 0 | L10: Yes | M10: Has critical issues | N10: Dev | O10: Open | R10: 0 | T10: =IFERROR(HYPERLINK("#'Main'!B"&MATCH(TRIM(A10),'Main'!B:B,0),"Open"),HYPERLINK("#'Main'!B1","Open")) | U10: =IFERROR(HYPERLINK("#'Technical Diagnostics'!A"&MATCH(A10,'Technical Diagnostics'!A:A,0),"Open"),HYPERLINK("#'Technical Diagnostics'!A1","Open"))
A11: https://africanmarketingconfederation.org/smoke-archive/page-65 | B11: 130 | C11: Critical | D11: 0 | F11: 0 | G11: 2026-06-01 to 2026-06-30 (30-day window; excludes today; typical GSC lag ~48h) | H11: No Search Analytics row matched this URL in the 30-day export (compare Final URL with the page URL shown in GSC) | I11: Standard | J11: 1 | K11: 0 | L11: Yes | M11: Has critical issues | N11: Dev | O11: Open | R11: 0 | T11: =IFERROR(HYPERLINK("#'Main'!B"&MATCH(TRIM(A11),'Main'!B:B,0),"Open"),HYPERLINK("#'Main'!B1","Open")) | U11: =IFERROR(HYPERLINK("#'Technical Diagnostics'!A"&MATCH(A11,'Technical Diagnostics'!A:A,0),"Open"),HYPERLINK("#'Technical Diagnostics'!A1","Open"))
A12: https://africanmarketingconfederation.org/smoke-archive/page-68 | B12: 130 | C12: Critical | D12: 0 | F12: 0 | G12: 2026-06-01 to 2026-06-30 (30-day window; excludes today; typical GSC lag ~48h) | H12: No Search Analytics row matched this URL in the 30-day export (compare Final URL with the page URL shown in GSC) | I12: Standard | J12: 1 | K12: 0 | L12: Yes | M12: Has critical issues | N12: Dev | O12: Open | R12: 0 | T12: =IFERROR(HYPERLINK("#'Main'!B"&MATCH(TRIM(A12),'Main'!B:B,0),"Open"),HYPERLINK("#'Main'!B1","Open")) | U12: =IFERROR(HYPERLINK("#'Technical Diagnostics'!A"&MATCH(A12,'Technical Diagnostics'!A:A,0),"Open"),HYPERLINK("#'Technical Diagnostics'!A1","Open"))
A13: https://africanmarketingconfederation.org/smoke-archive/page-78 | B13: 130 | C13: Critical | D13: 0 | F13: 0 | G13: 2026-06-01 to 2026-06-30 (30-day window; excludes today; typical GSC lag ~48h) | H13: No Search Analytics row matched this URL in the 30-day export (compare Final URL with the page URL shown in GSC) | I13: Standard | J13: 1 | K13: 0 | L13: Yes | M13: Has critical issues | N13: Dev | O13: Open | R13: 0 | T13: =IFERROR(HYPERLINK("#'Main'!B"&MATCH(TRIM(A13),'Main'!B:B,0),"Open"),HYPERLINK("#'Main'!B1","Open")) | U13: =IFERROR(HYPERLINK("#'Technical Diagnostics'!A"&MATCH(A13,'Technical Diagnostics'!A:A,0),"Open"),HYPERLINK("#'Technical Diagnostics'!A1","Open"))
A14: https://africanmarketingconfederation.org/smoke-archive/page-60 | B14: 125 | C14: Critical | D14: 35 | F14: 0 | G14: 2026-06-01 to 2026-06-30 (30-day window; excludes today; typical GSC lag ~48h) | H14: No Search Analytics row matched this URL in the 30-day export (compare Final URL with the page URL shown in GSC) | I14: Standard | J14: 1 | K14: 3 | L14: Yes | M14: Has critical issues | N14: Dev | O14: Open | R14: 0 | S14: self | T14: =IFERROR(HYPERLINK("#'Main'!B"&MATCH(TRIM(A14),'Main'!B:B,0),"Open"),HYPERLINK("#'Main'!B1","Open")) | U14: =IFERROR(HYPERLINK("#'Technical Diagnostics'!A"&MATCH(A14,'Technical Diagnostics'!A:A,0),"Open"),HYPERLINK("#'Technical Diagnostics'!A1","Open"))
A15: https://africanmarketingconfederation.org/smoke-archive/page-72 | B15: 125 | C15: Critical | D15: 35 | F15: 0 | G15: 2026-06-01 to 2026-06-30 (30-day window; excludes today; typical GSC lag ~48h) | H15: No Search Analytics row matched this URL in the 30-day export (compare Final URL with the page URL shown in GSC) | I15: Standard | J15: 1 | K15: 3 | L15: Yes | M15: Has critical issues | N15: Dev | O15: Open | R15: 0 | S15: self | T15: =IFERROR(HYPERLINK("#'Main'!B"&MATCH(TRIM(A15),'Main'!B:B,0),"Open"),HYPERLINK("#'Main'!B1","Open")) | U15: =IFERROR(HYPERLINK("#'Technical Diagnostics'!A"&MATCH(A15,'Technical Diagnostics'!A:A,0),"Open"),HYPERLINK("#'Technical Diagnostics'!A1","Open"))
A16: https://africanmarketingconfederation.org/smoke-archive/page-24 | B16: 105 | C16: Critical | D16: 45 | F16: 0 | G16: 2026-06-01 to 2026-06-30 (30-day window; excludes today; typical GSC lag ~48h) | H16: No Search Analytics row matched this URL in the 30-day export (compare Final URL with the page URL shown in GSC) | I16: Standard | J16: 1 | K16: 2 | L16: Yes | M16: Has critical issues | N16: Dev | O16: Open | R16: 0 | S16: self | T16: =IFERROR(HYPERLINK("#'Main'!B"&MATCH(TRIM(A16),'Main'!B:B,0),"Open"),HYPERLINK("#'Main'!B1","Open")) | U16: =IFERROR(HYPERLINK("#'Technical Diagnostics'!A"&MATCH(A16,'Technical Diagnostics'!A:A,0),"Open"),HYPERLINK("#'Technical Diagnostics'!A1","Open"))
A17: https://africanmarketingconfederation.org/smoke-archive/page-36 | B17: 105 | C17: Critical | D17: 45 | F17: 0 | G17: 2026-06-01 to 2026-06-30 (30-day window; excludes today; typical GSC lag ~48h) | H17: No Search Analytics row matched this URL in the 30-day export (compare Final URL with the page URL shown in GSC) | I17: Standard | J17: 1 | K17: 2 | L17: Yes | M17: Has critical issues | N17: Dev | O17: Open | R17: 0 | S17: self | T17: =IFERROR(HYPERLINK("#'Main'!B"&MATCH(TRIM(A17),'Main'!B:B,0),"Open"),HYPERLINK("#'Main'!B1","Open")) | U17: =IFERROR(HYPERLINK("#'Technical Diagnostics'!A"&MATCH(A17,'Technical Diagnostics'!A:A,0),"Open"),HYPERLINK("#'Technical Diagnostics'!A1","Open"))
A18: https://africanmarketingconfederation.org/smoke-archive/page-48 | B18: 105 | C18: Critical | D18: 45 | F18: 0 | G18: 2026-06-01 to 2026-06-30 (30-day window; excludes today; typical GSC lag ~48h) | H18: No Search Analytics row matched this URL in the 30-day export (compare Final URL with the page URL shown in GSC) | I18: Standard | J18: 1 | K18: 2 | L18: Yes | M18: Has critical issues | N18: Dev | O18: Open | R18: 0 | S18: self | T18: =IFERROR(HYPERLINK("#'Main'!B"&MATCH(TRIM(A18),'Main'!B:B,0),"Open"),HYPERLINK("#'Main'!B1","Open")) | U18: =IFERROR(HYPERLINK("#'Technical Diagnostics'!A"&MATCH(A18,'Technical Diagnostics'!A:A,0),"Open"),HYPERLINK("#'Technical Diagnostics'!A1","Open"))
A19: https://africanmarketingconfederation.org/smoke-archive/page-30 | B19: 90 | C19: Warning | D19: 50 | F19: 0 | G19: 2026-06-01 to 2026-06-30 (30-day window; excludes today; typical GSC lag ~48h) | H19: No Search Analytics row matched this URL in the 30-day export (compare Final URL with the page URL shown in GSC) | I19: Standard | J19: 0 | K19: 4 | L19: Yes | M19: Monitor | N19: Copy Writer | O19: Open | R19: 0 | S19: self | T19: =IFERROR(HYPERLINK("#'Main'!B"&MATCH(TRIM(A19),'Main'!B:B,0),"Open"),HYPERLINK("#'Main'!B1","Open")) | U19: =IFERROR(HYPERLINK("#'Technical Diagnostics'!A"&MATCH(A19,'Technical Diagnostics'!A:A,0),"Open"),HYPERLINK("#'Technical Diagnostics'!A1","Open"))
A20: https://africanmarketingconfederation.org/smoke-archive/page-35 | B20: 90 | C20: Warning | D20: 50 | F20: 0 | G20: 2026-06-01 to 2026-06-30 (30-day window; excludes today; typical GSC lag ~48h) | H20: No Search Analytics row matched this URL in the 30-day export (compare Final URL with the page URL shown in GSC) | I20: Standard | J20: 0 | K20: 4 | L20: Yes | M20: Monitor | N20: Copy Writer | O20: Open | R20: 0 | S20: self | T20: =IFERROR(HYPERLINK("#'Main'!B"&MATCH(TRIM(A20),'Main'!B:B,0),"Open"),HYPERLINK("#'Main'!B1","Open")) | U20: =IFERROR(HYPERLINK("#'Technical Diagnostics'!A"&MATCH(A20,'Technical Diagnostics'!A:A,0),"Open"),HYPERLINK("#'Technical Diagnostics'!A1","Open"))
A21: https://africanmarketingconfederation.org/smoke-archive/page-45 | B21: 90 | C21: Warning | D21: 50 | F21: 0 | G21: 2026-06-01 to 2026-06-30 (30-day window; excludes today; typical GSC lag ~48h) | H21: No Search Analytics row matched this URL in the 30-day export (compare Final URL with the page URL shown in GSC) | I21: Standard | J21: 0 | K21: 4 | L21: Yes | M21: Monitor | N21: Copy Writer | O21: Open | R21: 0 | S21: self | T21: =IFERROR(HYPERLINK("#'Main'!B"&MATCH(TRIM(A21),'Main'!B:B,0),"Open"),HYPERLINK("#'Main'!B1","Open")) | U21: =IFERROR(HYPERLINK("#'Technical Diagnostics'!A"&MATCH(A21,'Technical Diagnostics'!A:A,0),"Open"),HYPERLINK("#'Technical Diagnostics'!A1","Open"))
A22: https://africanmarketingconfederation.org/smoke-archive/page-70 | B22: 90 | C22: Warning | D22: 50 | F22: 0 | G22: 2026-06-01 to 2026-06-30 (30-day window; excludes today; typical GSC lag ~48h) | H22: No Search Analytics row matched this URL in the 30-day export (compare Final URL with the page URL shown in GSC) | I22: Standard | J22: 0 | K22: 4 | L22: Yes | M22: Monitor | N22: Copy Writer | O22: Open | R22: 0 | S22: self | T22: =IFERROR(HYPERLINK("#'Main'!B"&MATCH(TRIM(A22),'Main'!B:B,0),"Open"),HYPERLINK("#'Main'!B1","Open")) | U22: =IFERROR(HYPERLINK("#'Technical Diagnostics'!A"&MATCH(A22,'Technical Diagnostics'!A:A,0),"Open"),HYPERLINK("#'Technical Diagnostics'!A1","Open"))
A23: https://africanmarketingconfederation.org/smoke-archive/page-12 | B23: 85 | C23: Critical | D23: 55 | F23: 0 | G23: 2026-06-01 to 2026-06-30 (30-day window; excludes today; typical GSC lag ~48h) | H23: No Search Analytics row matched this URL in the 30-day export (compare Final URL with the page URL shown in GSC) | I23: Standard | J23: 1 | K23: 1 | L23: Yes | M23: Has critical issues | N23: Dev | O23: Open | R23: 0 | S23: self | T23: =IFERROR(HYPERLINK("#'Main'!B"&MATCH(TRIM(A23),'Main'!B:B,0),"Open"),HYPERLINK("#'Main'!B1","Open")) | U23: =IFERROR(HYPERLINK("#'Technical Diagnostics'!A"&MATCH(A23,'Technical Diagnostics'!A:A,0),"Open"),HYPERLINK("#'Technical Diagnostics'!A1","Open"))
A24: https://africanmarketingconfederation.org/smoke-archive/page-5 | B24: 70 | C24: Warning | D24: 60 | F24: 0 | G24: 2026-06-01 to 2026-06-30 (30-day window; excludes today; typical GSC lag ~48h) | H24: No Search Analytics row matched this URL in the 30-day export (compare Final URL with the page URL shown in GSC) | I24: Standard | J24: 0 | K24: 3 | L24: Yes | M24: Monitor | N24: Copy Writer | O24: Open | R24: 0 | S24: self | T24: =IFERROR(HYPERLINK("#'Main'!B"&MATCH(TRIM(A24),'Main'!B:B,0),"Open"),HYPERLINK("#'Main'!B1","Open")) | U24: =IFERROR(HYPERLINK("#'Technical Diagnostics'!A"&MATCH(A24,'Technical Diagnostics'!A:A,0),"Open"),HYPERLINK("#'Technical Diagnostics'!A1","Open"))
A25: https://africanmarketingconfederation.org/smoke-archive/page-10 | B25: 70 | C25: Warning | D25: 60 | F25: 0 | G25: 2026-06-01 to 2026-06-30 (30-day window; excludes today; typical GSC lag ~48h) | H25: No Search Analytics row matched this URL in the 30-day export (compare Final URL with the page URL shown in GSC) | I25: Standard | J25: 0 | K25: 3 | L25: Yes | M25: Monitor | N25: Copy Writer | O25: Open | R25: 0 | S25: self | T25: =IFERROR(HYPERLINK("#'Main'!B"&MATCH(TRIM(A25),'Main'!B:B,0),"Open"),HYPERLINK("#'Main'!B1","Open")) | U25: =IFERROR(HYPERLINK("#'Technical Diagnostics'!A"&MATCH(A25,'Technical Diagnostics'!A:A,0),"Open"),HYPERLINK("#'Technical Diagnostics'!A1","Open"))
... A32: https://africanmarketingconfederation.org/smoke-archive/page-54 | B32: 70 | C32: Warning | D32: 60 | F32: 0 | G32: 2026-06-01 to 2026-06-30 (30-day window; excludes today; typical GSC lag ~48h) | H32: No Search Analytics row matched this URL in the 30-day export (compare Final URL with the page URL shown in GSC) | I32: Standard | J32: 0 | K32: 3 | L32: Yes | M32: Monitor | N32: Copy Writer | O32: Open | R32: 0 | S32: self | T32: =IFERROR(HYPERLINK("#'Main'!B"&MATCH(TRIM(A32),'Main'!B:B,0),"Open"),HYPERLINK("#'Main'!B1","Open")) | U32: =IFERROR(HYPERLINK("#'Technical Diagnostics'!A"&MATCH(A32,'Technical Diagnostics'!A:A,0),"Open"),HYPERLINK("#'Technical Diagnostics'!A1","Open"))
A33: https://africanmarketingconfederation.org/smoke-archive/page-55 | B33: 70 | C33: Warning | D33: 60 | F33: 0 | G33: 2026-06-01 to 2026-06-30 (30-day window; excludes today; typical GSC lag ~48h) | H33: No Search Analytics row matched this URL in the 30-day export (compare Final URL with the page URL shown in GSC) | I33: Standard | J33: 0 | K33: 3 | L33: Yes | M33: Monitor | N33: Copy Writer | O33: Open | R33: 0 | T33: =IFERROR(HYPERLINK("#'Main'!B"&MATCH(TRIM(A33),'Main'!B:B,0),"Open"),HYPERLINK("#'Main'!B1","Open")) | U33: =IFERROR(HYPERLINK("#'Technical Diagnostics'!A"&MATCH(A33,'Technical Diagnostics'!A:A,0),"Open"),HYPERLINK("#'Technical Diagnostics'!A1","Open"))
A34: https://africanmarketingconfederation.org/smoke-archive/page-63 | B34: 70 | C34: Warning | D34: 60 | F34: 0 | G34: 2026-06-01 to 2026-06-30 (30-day window; excludes today; typical GSC lag ~48h) | H34: No Search Analytics row matched this URL in the 30-day export (compare Final URL with the page URL shown in GSC) | I34: Standard | J34: 0 | K34: 3 | L34: Yes | M34: Monitor | N34: Copy Writer | O34: Open | R34: 0 | S34: self | T34: =IFERROR(HYPERLINK("#'Main'!B"&MATCH(TRIM(A34),'Main'!B:B,0),"Open"),HYPERLINK("#'Main'!B1","Open")) | U34: =IFERROR(HYPERLINK("#'Technical Diagnostics'!A"&MATCH(A34,'Technical Diagnostics'!A:A,0),"Open"),HYPERLINK("#'Technical Diagnostics'!A1","Open"))
A35: https://africanmarketingconfederation.org/smoke-archive/page-75 | B35: 70 | C35: Warning | D35: 60 | F35: 0 | G35: 2026-06-01 to 2026-06-30 (30-day window; excludes today; typical GSC lag ~48h) | H35: No Search Analytics row matched this URL in the 30-day export (compare Final URL with the page URL shown in GSC) | I35: Standard | J35: 0 | K35: 3 | L35: Yes | M35: Monitor | N35: Copy Writer | O35: Open | R35: 0 | S35: self | T35: =IFERROR(HYPERLINK("#'Main'!B"&MATCH(TRIM(A35),'Main'!B:B,0),"Open"),HYPERLINK("#'Main'!B1","Open")) | U35: =IFERROR(HYPERLINK("#'Technical Diagnostics'!A"&MATCH(A35,'Technical Diagnostics'!A:A,0),"Open"),HYPERLINK("#'Technical Diagnostics'!A1","Open"))
A36: https://africanmarketingconfederation.org/smoke-archive/page-6 | B36: 50 | C36: Warning | D36: 70 | F36: 0 | G36: 2026-06-01 to 2026-06-30 (30-day window; excludes today; typical GSC lag ~48h) | H36: No Search Analytics row matched this URL in the 30-day export (compare Final URL with the page URL shown in GSC) | I36: Standard | J36: 0 | K36: 2 | L36: Yes | M36: Monitor | N36: Copy Writer | O36: Open | R36: 0 | S36: self | T36: =IFERROR(HYPERLINK("#'Main'!B"&MATCH(TRIM(A36),'Main'!B:B,0),"Open"),HYPERLINK("#'Main'!B1","Open")) | U36: =IFERROR(HYPERLINK("#'Technical Diagnostics'!A"&MATCH(A36,'Technical Diagnostics'!A:A,0),"Open"),HYPERLINK("#'Technical Diagnostics'!A1","Open"))
A37: https://africanmarketingconfederation.org/smoke-archive/page-7 | B37: 50 | C37: Warning | D37: 70 | F37: 0 | G37: 2026-06-01 to 2026-06-30 (30-day window; excludes today; typical GSC lag ~48h) | H37: No Search Analytics row matched this URL in the 30-day export (compare Final URL with the page URL shown in GSC) | I37: Standard | J37: 0 | K37: 2 | L37: Yes | M37: Monitor | N37: Copy Writer | O37: Open | R37: 0 | S37: self | T37: =IFERROR(HYPERLINK("#'Main'!B"&MATCH(TRIM(A37),'Main'!B:B,0),"Open"),HYPERLINK("#'Main'!B1","Open")) | U37: =IFERROR(HYPERLINK("#'Technical Diagnostics'!A"&MATCH(A37,'Technical Diagnostics'!A:A,0),"Open"),HYPERLINK("#'Technical Diagnostics'!A1","Open"))
A38: https://africanmarketingconfederation.org/smoke-archive/page-9 | B38: 50 | C38: Warning | D38: 70 | F38: 0 | G38: 2026-06-01 to 2026-06-30 (30-day window; excludes today; typical GSC lag ~48h) | H38: No Search Analytics row matched this URL in the 30-day export (compare Final URL with the page URL shown in GSC) | I38: Standard | J38: 0 | K38: 2 | L38: Yes | M38: Monitor | N38: Copy Writer | O38: Open | R38: 0 | S38: self | T38: =IFERROR(HYPERLINK("#'Main'!B"&MATCH(TRIM(A38),'Main'!B:B,0),"Open"),HYPERLINK("#'Main'!B1","Open")) | U38: =IFERROR(HYPERLINK("#'Technical Diagnostics'!A"&MATCH(A38,'Technical Diagnostics'!A:A,0),"Open"),HYPERLINK("#'Technical Diagnostics'!A1","Open"))
A39: https://africanmarketingconfederation.org/smoke-archive/page-14 | B39: 50 | C39: Warning | D39: 70 | F39: 0 | G39: 2026-06-01 to 2026-06-30 (30-day window; excludes today; typical GSC lag ~48h) | H39: No Search Analytics row matched this URL in the 30-day export (compare Final URL with the page URL shown in GSC) | I39: Standard | J39: 0 | K39: 2 | L39: Yes | M39: Monitor | N39: Copy Writer | O39: Open | R39: 0 | S39: self | T39: =IFERROR(HYPERLINK("#'Main'!B"&MATCH(TRIM(A39),'Main'!B:B,0),"Open"),HYPERLINK("#'Main'!B1","Open")) | U39: =IFERROR(HYPERLINK("#'Technical Diagnostics'!A"&MATCH(A39,'Technical Diagnostics'!A:A,0),"Open"),HYPERLINK("#'Technical Diagnostics'!A1","Open"))
A40: https://africanmarketingconfederation.org/smoke-archive/page-20 | B40: 50 | C40: Warning | D40: 70 | F40: 0 | G40: 2026-06-01 to 2026-06-30 (30-day window; excludes today; typical GSC lag ~48h) | H40: No Search Analytics row matched this URL in the 30-day export (compare Final URL with the page URL shown in GSC) | I40: Standard | J40: 0 | K40: 2 | L40: Yes | M40: Monitor | N40: Copy Writer | O40: Open | R40: 0 | S40: self | T40: =IFERROR(HYPERLINK("#'Main'!B"&MATCH(TRIM(A40),'Main'!B:B,0),"Open"),HYPERLINK("#'Main'!B1","Open")) | U40: =IFERROR(HYPERLINK("#'Technical Diagnostics'!A"&MATCH(A40,'Technical Diagnostics'!A:A,0),"Open"),HYPERLINK("#'Technical Diagnostics'!A1","Open"))
A41: https://africanmarketingconfederation.org/smoke-archive/page-21 | B41: 50 | C41: Warning | D41: 70 | F41: 0 | G41: 2026-06-01 to 2026-06-30 (30-day window; excludes today; typical GSC lag ~48h) | H41: No Search Analytics row matched this URL in the 30-day export (compare Final URL with the page URL shown in GSC) | I41: Standard | J41: 0 | K41: 2 | L41: Yes | M41: Monitor | N41: Copy Writer | O41: Open | R41: 0 | S41: self | T41: =IFERROR(HYPERLINK("#'Main'!B"&MATCH(TRIM(A41),'Main'!B:B,0),"Open"),HYPERLINK("#'Main'!B1","Open")) | U41: =IFERROR(HYPERLINK("#'Technical Diagnostics'!A"&MATCH(A41,'Technical Diagnostics'!A:A,0),"Open"),HYPERLINK("#'Technical Diagnostics'!A1","Open"))
A42: https://africanmarketingconfederation.org/smoke-archive/page-27 | B42: 50 | C42: Warning | D42: 70 | F42: 0 | G42: 2026-06-01 to 2026-06-30 (30-day window; excludes today; typical GSC lag ~48h) | H42: No Search Analytics row matched this URL in the 30-day export (compare Final URL with the page URL shown in GSC) | I42: Standard | J42: 0 | K42: 2 | L42: Yes | M42: Monitor | N42: Copy Writer | O42: Open | R42: 0 | S42: self | T42: =IFERROR(HYPERLINK("#'Main'!B"&MATCH(TRIM(A42),'Main'!B:B,0),"Open"),HYPERLINK("#'Main'!B1","Open")) | U42: =IFERROR(HYPERLINK("#'Technical Diagnostics'!A"&MATCH(A42,'Technical Diagnostics'!A:A,0),"Open"),HYPERLINK("#'Technical Diagnostics'!A1","Open"))
A43: https://africanmarketingconfederation.org/smoke-archive/page-49 | B43: 50 | C43: Warning | D43: 70 | F43: 0 | G43: 2026-06-01 to 2026-06-30 (30-day window; excludes today; typical GSC lag ~48h) | H43: No Search Analytics row matched this URL in the 30-day export (compare Final URL with the page URL shown in GSC) | I43: Standard | J43: 0 | K43: 2 | L43: Yes | M43: Monitor | N43: Copy Writer | O43: Open | R43: 0 | S43: self | T43: =IFERROR(HYPERLINK("#'Main'!B"&MATCH(TRIM(A43),'Main'!B:B,0),"Open"),HYPERLINK("#'Main'!B1","Open")) | U43: =IFERROR(HYPERLINK("#'Technical Diagnostics'!A"&MATCH(A43,'Technical Diagnostics'!A:A,0),"Open"),HYPERLINK("#'Technical Diagnostics'!A1","Open"))
A44: https://africanmarketingconfederation.org/smoke-archive/page-56 | B44: 50 | C44: Warning | D44: 70 | F44: 0 | G44: 2026-06-01 to 2026-06-30 (30-day window; excludes today; typical GSC lag ~48h) | H44: No Search Analytics row matched this URL in the 30-day export (compare Final URL with the page URL shown in GSC) | I44: Standard | J44: 0 | K44: 2 | L44: Yes | M44: Monitor | N44: Copy Writer | O44: Open | R44: 0 | S44: self | T44: =IFERROR(HYPERLINK("#'Main'!B"&MATCH(TRIM(A44),'Main'!B:B,0),"Open"),HYPERLINK("#'Main'!B1","Open")) | U44: =IFERROR(HYPERLINK("#'Technical Diagnostics'!A"&MATCH(A44,'Technical Diagnostics'!A:A,0),"Open"),HYPERLINK("#'Technical Diagnostics'!A1","Open"))
A45: https://africanmarketingconfederation.org/smoke-archive/page-66 | B45: 50 | C45: Warning | D45: 70 | F45: 0 | G45: 2026-06-01 to 2026-06-30 (30-day window; excludes today; typical GSC lag ~48h) | H45: No Search Analytics row matched this URL in the 30-day export (compare Final URL with the page URL shown in GSC) | I45: Standard | J45: 0 | K45: 2 | L45: Yes | M45: Monitor | N45: Copy Writer | O45: Open | R45: 0 | T45: =IFERROR(HYPERLINK("#'Main'!B"&MATCH(TRIM(A45),'Main'!B:B,0),"Open"),HYPERLINK("#'Main'!B1","Open")) | U45: =IFERROR(HYPERLINK("#'Technical Diagnostics'!A"&MATCH(A45,'Technical Diagnostics'!A:A,0),"Open"),HYPERLINK("#'Technical Diagnostics'!A1","Open"))
A46: https://africanmarketingconfederation.org/smoke-archive/page-77 | B46: 50 | C46: Warning | D46: 70 | F46: 0 | G46: 2026-06-01 to 2026-06-30 (30-day window; excludes today; typical GSC lag ~48h) | H46: No Search Analytics row matched this URL in the 30-day export (compare Final URL with the page URL shown in GSC) | I46: Standard | J46: 0 | K46: 2 | L46: Yes | M46: Monitor | N46: Copy Writer | O46: Open | R46: 0 | T46: =IFERROR(HYPERLINK("#'Main'!B"&MATCH(TRIM(A46),'Main'!B:B,0),"Open"),HYPERLINK("#'Main'!B1","Open")) | U46: =IFERROR(HYPERLINK("#'Technical Diagnostics'!A"&MATCH(A46,'Technical Diagnostics'!A:A,0),"Open"),HYPERLINK("#'Technical Diagnostics'!A1","Open"))
A47: https://africanmarketingconfederation.org/discovered-via-bfs-1 | B47: 50 | C47: Warning | D47: 70 | F47: 0 | G47: 2026-06-01 to 2026-06-30 (30-day window; excludes today; typical GSC lag ~48h) | H47: No Search Analytics row matched this URL in the 30-day export (compare Final URL with the page URL shown in GSC) | I47: Standard | J47: 0 | K47: 2 | L47: Yes | M47: Monitor | N47: Copy Writer | O47: Open | R47: 0 | S47: self | T47: =IFERROR(HYPERLINK("#'Main'!B"&MATCH(TRIM(A47),'Main'!B:B,0),"Open"),HYPERLINK("#'Main'!B1","Open")) | U47: =IFERROR(HYPERLINK("#'Technical Diagnostics'!A"&MATCH(A47,'Technical Diagnostics'!A:A,0),"Open"),HYPERLINK("#'Technical Diagnostics'!A1","Open"))
A48: https://africanmarketingconfederation.org/smoke-archive/page-1 | B48: 30 | C48: Warning | D48: 80 | F48: 0 | G48: 2026-06-01 to 2026-06-30 (30-day window; excludes today; typical GSC lag ~48h) | H48: No Search Analytics row matched this URL in the 30-day export (compare Final URL with the page URL shown in GSC) | I48: Standard | J48: 0 | K48: 1 | L48: Yes | M48: Monitor | N48: Copy Writer | O48: Open | R48: 0 | S48: self | T48: =IFERROR(HYPERLINK("#'Main'!B"&MATCH(TRIM(A48),'Main'!B:B,0),"Open"),HYPERLINK("#'Main'!B1","Open")) | U48: =IFERROR(HYPERLINK("#'Technical Diagnostics'!A"&MATCH(A48,'Technical Diagnostics'!A:A,0),"Open"),HYPERLINK("#'Technical Diagnostics'!A1","Open"))
A49: https://africanmarketingconfederation.org/smoke-archive/page-2 | B49: 30 | C49: Warning | D49: 80 | F49: 0 | G49: 2026-06-01 to 2026-06-30 (30-day window; excludes today; typical GSC lag ~48h) | H49: No Search Analytics row matched this URL in the 30-day export (compare Final URL with the page URL shown in GSC) | I49: Standard | J49: 0 | K49: 1 | L49: Yes | M49: Monitor | N49: Copy Writer | O49: Open | R49: 0 | S49: self | T49: =IFERROR(HYPERLINK("#'Main'!B"&MATCH(TRIM(A49),'Main'!B:B,0),"Open"),HYPERLINK("#'Main'!B1","Open")) | U49: =IFERROR(HYPERLINK("#'Technical Diagnostics'!A"&MATCH(A49,'Technical Diagnostics'!A:A,0),"Open"),HYPERLINK("#'Technical Diagnostics'!A1","Open"))
A50: https://africanmarketingconfederation.org/smoke-archive/page-3 | B50: 30 | C50: Warning | D50: 80 | F50: 0 | G50: 2026-06-01 to 2026-06-30 (30-day window; excludes today; typical GSC lag ~48h) | H50: No Search Analytics row matched this URL in the 30-day export (compare Final URL with the page URL shown in GSC) | I50: Standard | J50: 0 | K50: 1 | L50: Yes | M50: Monitor | N50: Copy Writer | O50: Open | R50: 0 | S50: self | T50: =IFERROR(HYPERLINK("#'Main'!B"&MATCH(TRIM(A50),'Main'!B:B,0),"Open"),HYPERLINK("#'Main'!B1","Open")) | U50: =IFERROR(HYPERLINK("#'Technical Diagnostics'!A"&MATCH(A50,'Technical Diagnostics'!A:A,0),"Open"),HYPERLINK("#'Technical Diagnostics'!A1","Open"))
A51: https://africanmarketingconfederation.org/smoke-archive/page-8 | B51: 30 | C51: Warning | D51: 80 | F51: 0 | G51: 2026-06-01 to 2026-06-30 (30-day window; excludes today; typical GSC lag ~48h) | H51: No Search Analytics row matched this URL in the 30-day export (compare Final URL with the page URL shown in GSC) | I51: Standard | J51: 0 | K51: 1 | L51: Yes | M51: Monitor | N51: Copy Writer | O51: Open | R51: 0 | S51: self | T51: =IFERROR(HYPERLINK("#'Main'!B"&MATCH(TRIM(A51),'Main'!B:B,0),"Open"),HYPERLINK("#'Main'!B1","Open")) | U51: =IFERROR(HYPERLINK("#'Technical Diagnostics'!A"&MATCH(A51,'Technical Diagnostics'!A:A,0),"Open"),HYPERLINK("#'Technical Diagnostics'!A1","Open"))
A52: https://africanmarketingconfederation.org/smoke-archive/page-11 | B52: 30 | C52: Warning | D52: 80 | F52: 0 | G52: 2026-06-01 to 2026-06-30 (30-day window; excludes today; typical GSC lag ~48h) | H52: No Search Analytics row matched this URL in the 30-day export (compare Final URL with the page URL shown in GSC) | I52: Standard | J52: 0 | K52: 1 | L52: Yes | M52: Monitor | N52: Copy Writer | O52: Open | R52: 0 | T52: =IFERROR(HYPERLINK("#'Main'!B"&MATCH(TRIM(A52),'Main'!B:B,0),"Open"),HYPERLINK("#'Main'!B1","Open")) | U52: =IFERROR(HYPERLINK("#'Technical Diagnostics'!A"&MATCH(A52,'Technical Diagnostics'!A:A,0),"Open"),HYPERLINK("#'Technical Diagnostics'!A1","Open"))
A53: https://africanmarketingconfederation.org/smoke-archive/page-16 | B53: 30 | C53: Warning | D53: 80 | F53: 0 | G53: 2026-06-01 to 2026-06-30 (30-day window; excludes today; typical GSC lag ~48h) | H53: No Search Analytics row matched this URL in the 30-day export (compare Final URL with the page URL shown in GSC) | I53: Standard | J53: 0 | K53: 1 | L53: Yes | M53: Monitor | N53: Copy Writer | O53: Open | R53: 0 | S53: self | T53: =IFERROR(HYPERLINK("#'Main'!B"&MATCH(TRIM(A53),'Main'!B:B,0),"Open"),HYPERLINK("#'Main'!B1","Open")) | U53: =IFERROR(HYPERLINK("#'Technical Diagnostics'!A"&MATCH(A53,'Technical Diagnostics'!A:A,0),"Open"),HYPERLINK("#'Technical Diagnostics'!A1","Open"))
A54: https://africanmarketingconfederation.org/smoke-archive/page-19 | B54: 30 | C54: Warning | D54: 80 | F54: 0 | G54: 2026-06-01 to 2026-06-30 (30-day window; excludes today; typical GSC lag ~48h) | H54: No Search Analytics row matched this URL in the 30-day export (compare Final URL with the page URL shown in GSC) | I54: Standard | J54: 0 | K54: 1 | L54: Yes | M54: Monitor | N54: Copy Writer | O54: Open | R54: 0 | S54: self | T54: =IFERROR(HYPERLINK("#'Main'!B"&MATCH(TRIM(A54),'Main'!B:B,0),"Open"),HYPERLINK("#'Main'!B1","Open")) | U54: =IFERROR(HYPERLINK("#'Technical Diagnostics'!A"&MATCH(A54,'Technical Diagnostics'!A:A,0),"Open"),HYPERLINK("#'Technical Diagnostics'!A1","Open"))
A55: https://africanmarketingconfederation.org/smoke-archive/page-22 | B55: 30 | C55: Warning | D55: 80 | F55: 0 | G55: 2026-06-01 to 2026-06-30 (30-day window; excludes today; typical GSC lag ~48h) | H55: No Search Analytics row matched this URL in the 30-day export (compare Final URL with the page URL shown in GSC) | I55: Standard | J55: 0 | K55: 1 | L55: Yes | M55: Monitor | N55: Copy Writer | O55: Open | R55: 0 | T55: =IFERROR(HYPERLINK("#'Main'!B"&MATCH(TRIM(A55),'Main'!B:B,0),"Open"),HYPERLINK("#'Main'!B1","Open")) | U55: =IFERROR(HYPERLINK("#'Technical Diagnostics'!A"&MATCH(A55,'Technical Diagnostics'!A:A,0),"Open"),HYPERLINK("#'Technical Diagnostics'!A1","Open"))
A56: https://africanmarketingconfederation.org/smoke-archive/page-23 | B56: 30 | C56: Warning | D56: 80 | F56: 0 | G56: 2026-06-01 to 2026-06-30 (30-day window; excludes today; typical GSC lag ~48h) | H56: No Search Analytics row matched this URL in the 30-day export (compare Final URL with the page URL shown in GSC) | I56: Standard | J56: 0 | K56: 1 | L56: Yes | M56: Monitor | N56: Copy Writer | O56: Open | R56: 0 | S56: self | T56: =IFERROR(HYPERLINK("#'Main'!B"&MATCH(TRIM(A56),'Main'!B:B,0),"Open"),HYPERLINK("#'Main'!B1","Open")) | U56: =IFERROR(HYPERLINK("#'Technical Diagnostics'!A"&MATCH(A56,'Technical Diagnostics'!A:A,0),"Open"),HYPERLINK("#'Technical Diagnostics'!A1","Open"))
A57: https://africanmarketingconfederation.org/smoke-archive/page-28 | B57: 30 | C57: Warning | D57: 80 | F57: 0 | G57: 2026-06-01 to 2026-06-30 (30-day window; excludes today; typical GSC lag ~48h) | H57: No Search Analytics row matched this URL in the 30-day export (compare Final URL with the page URL shown in GSC) | I57: Standard | J57: 0 | K57: 1 | L57: Yes | M57: Monitor | N57: Copy Writer | O57: Open | R57: 0 | S57: self | T57: =IFERROR(HYPERLINK("#'Main'!B"&MATCH(TRIM(A57),'Main'!B:B,0),"Open"),HYPERLINK("#'Main'!B1","Open")) | U57: =IFERROR(HYPERLINK("#'Technical Diagnostics'!A"&MATCH(A57,'Technical Diagnostics'!A:A,0),"Open"),HYPERLINK("#'Technical Diagnostics'!A1","Open"))
A58: https://africanmarketingconfederation.org/smoke-archive/page-29 | B58: 30 | C58: Warning | D58: 80 | F58: 0 | G58: 2026-06-01 to 2026-06-30 (30-day window; excludes today; typical GSC lag ~48h) | H58: No Search Analytics row matched this URL in the 30-day export (compare Final URL with the page URL shown in GSC) | I58: Standard | J58: 0 | K58: 1 | L58: Yes | M58: Monitor | N58: Copy Writer | O58: Open | R58: 0 | S58: self | T58: =IFERROR(HYPERLINK("#'Main'!B"&MATCH(TRIM(A58),'Main'!B:B,0),"Open"),HYPERLINK("#'Main'!B1","Open")) | U58: =IFERROR(HYPERLINK("#'Technical Diagnostics'!A"&MATCH(A58,'Technical Diagnostics'!A:A,0),"Open"),HYPERLINK("#'Technical Diagnostics'!A1","Open"))
A59: https://africanmarketingconfederation.org/smoke-archive/page-31 | B59: 30 | C59: Warning | D59: 80 | F59: 0 | G59: 2026-06-01 to 2026-06-30 (30-day window; excludes today; typical GSC lag ~48h) | H59: No Search Analytics row matched this URL in the 30-day export (compare Final URL with the page URL shown in GSC) | I59: Standard | J59: 0 | K59: 1 | L59: Yes | M59: Monitor | N59: Copy Writer | O59: Open | R59: 0 | S59: self | T59: =IFERROR(HYPERLINK("#'Main'!B"&MATCH(TRIM(A59),'Main'!B:B,0),"Open"),HYPERLINK("#'Main'!B1","Open")) | U59: =IFERROR(HYPERLINK("#'Technical Diagnostics'!A"&MATCH(A59,'Technical Diagnostics'!A:A,0),"Open"),HYPERLINK("#'Technical Diagnostics'!A1","Open"))
A60: https://africanmarketingconfederation.org/smoke-archive/page-32 | B60: 30 | C60: Warning | D60: 80 | F60: 0 | G60: 2026-06-01 to 2026-06-30 (30-day window; excludes today; typical GSC lag ~48h) | H60: No Search Analytics row matched this URL in the 30-day export (compare Final URL with the page URL shown in GSC) | I60: Standard | J60: 0 | K60: 1 | L60: Yes | M60: Monitor | N60: Copy Writer | O60: Open | R60: 0 | S60: self | T60: =IFERROR(HYPERLINK("#'Main'!B"&MATCH(TRIM(A60),'Main'!B:B,0),"Open"),HYPERLINK("#'Main'!B1","Open")) | U60: =IFERROR(HYPERLINK("#'Technical Diagnostics'!A"&MATCH(A60,'Technical Diagnostics'!A:A,0),"Open"),HYPERLINK("#'Technical Diagnostics'!A1","Open"))
A61: https://africanmarketingconfederation.org/smoke-archive/page-33 | B61: 30 | C61: Warning | D61: 80 | F61: 0 | G61: 2026-06-01 to 2026-06-30 (30-day window; excludes today; typical GSC lag ~48h) | H61: No Search Analytics row matched this URL in the 30-day export (compare Final URL with the page URL shown in GSC) | I61: Standard | J61: 0 | K61: 1 | L61: Yes | M61: Monitor | N61: Copy Writer | O61: Open | R61: 0 | T61: =IFERROR(HYPERLINK("#'Main'!B"&MATCH(TRIM(A61),'Main'!B:B,0),"Open"),HYPERLINK("#'Main'!B1","Open")) | U61: =IFERROR(HYPERLINK("#'Technical Diagnostics'!A"&MATCH(A61,'Technical Diagnostics'!A:A,0),"Open"),HYPERLINK("#'Technical Diagnostics'!A1","Open"))
A62: https://africanmarketingconfederation.org/smoke-archive/page-37 | B62: 30 | C62: Warning | D62: 80 | F62: 0 | G62: 2026-06-01 to 2026-06-30 (30-day window; excludes today; typical GSC lag ~48h) | H62: No Search Analytics row matched this URL in the 30-day export (compare Final URL with the page URL shown in GSC) | I62: Standard | J62: 0 | K62: 1 | L62: Yes | M62: Monitor | N62: Copy Writer | O62: Open | R62: 0 | S62: self | T62: =IFERROR(HYPERLINK("#'Main'!B"&MATCH(TRIM(A62),'Main'!B:B,0),"Open"),HYPERLINK("#'Main'!B1","Open")) | U62: =IFERROR(HYPERLINK("#'Technical Diagnostics'!A"&MATCH(A62,'Technical Diagnostics'!A:A,0),"Open"),HYPERLINK("#'Technical Diagnostics'!A1","Open"))
A63: https://africanmarketingconfederation.org/smoke-archive/page-38 | B63: 30 | C63: Warning | D63: 80 | F63: 0 | G63: 2026-06-01 to 2026-06-30 (30-day window; excludes today; typical GSC lag ~48h) | H63: No Search Analytics row matched this URL in the 30-day export (compare Final URL with the page URL shown in GSC) | I63: Standard | J63: 0 | K63: 1 | L63: Yes | M63: Monitor | N63: Copy Writer | O63: Open | R63: 0 | S63: self | T63: =IFERROR(HYPERLINK("#'Main'!B"&MATCH(TRIM(A63),'Main'!B:B,0),"Open"),HYPERLINK("#'Main'!B1","Open")) | U63: =IFERROR(HYPERLINK("#'Technical Diagnostics'!A"&MATCH(A63,'Technical Diagnostics'!A:A,0),"Open"),HYPERLINK("#'Technical Diagnostics'!A1","Open"))
A64: https://africanmarketingconfederation.org/smoke-archive/page-41 | B64: 30 | C64: Warning | D64: 80 | F64: 0 | G64: 2026-06-01 to 2026-06-30 (30-day window; excludes today; typical GSC lag ~48h) | H64: No Search Analytics row matched this URL in the 30-day export (compare Final URL with the page URL shown in GSC) | I64: Standard | J64: 0 | K64: 1 | L64: Yes | M64: Monitor | N64: Copy Writer | O64: Open | R64: 0 | S64: self | T64: =IFERROR(HYPERLINK("#'Main'!B"&MATCH(TRIM(A64),'Main'!B:B,0),"Open"),HYPERLINK("#'Main'!B1","Open")) | U64: =IFERROR(HYPERLINK("#'Technical Diagnostics'!A"&MATCH(A64,'Technical Diagnostics'!A:A,0),"Open"),HYPERLINK("#'Technical Diagnostics'!A1","Open"))
A65: https://africanmarketingconfederation.org/smoke-archive/page-43 | B65: 30 | C65: Warning | D65: 80 | F65: 0 | G65: 2026-06-01 to 2026-06-30 (30-day window; excludes today; typical GSC lag ~48h) | H65: No Search Analytics row matched this URL in the 30-day export (compare Final URL with the page URL shown in GSC) | I65: Standard | J65: 0 | K65: 1 | L65: Yes | M65: Monitor | N65: Copy Writer | O65: Open | R65: 0 | S65: self | T65: =IFERROR(HYPERLINK("#'Main'!B"&MATCH(TRIM(A65),'Main'!B:B,0),"Open"),HYPERLINK("#'Main'!B1","Open")) | U65: =IFERROR(HYPERLINK("#'Technical Diagnostics'!A"&MATCH(A65,'Technical Diagnostics'!A:A,0),"Open"),HYPERLINK("#'Technical Diagnostics'!A1","Open"))
A66: https://africanmarketingconfederation.org/smoke-archive/page-46 | B66: 30 | C66: Warning | D66: 80 | F66: 0 | G66: 2026-06-01 to 2026-06-30 (30-day window; excludes today; typical GSC lag ~48h) | H66: No Search Analytics row matched this URL in the 30-day export (compare Final URL with the page URL shown in GSC) | I66: Standard | J66: 0 | K66: 1 | L66: Yes | M66: Monitor | N66: Copy Writer | O66: Open | R66: 0 | S66: self | T66: =IFERROR(HYPERLINK("#'Main'!B"&MATCH(TRIM(A66),'Main'!B:B,0),"Open"),HYPERLINK("#'Main'!B1","Open")) | U66: =IFERROR(HYPERLINK("#'Technical Diagnostics'!A"&MATCH(A66,'Technical Diagnostics'!A:A,0),"Open"),HYPERLINK("#'Technical Diagnostics'!A1","Open"))
A67: https://africanmarketingconfederation.org/smoke-archive/page-47 | B67: 30 | C67: Warning | D67: 80 | F67: 0 | G67: 2026-06-01 to 2026-06-30 (30-day window; excludes today; typical GSC lag ~48h) | H67: No Search Analytics row matched this URL in the 30-day export (compare Final URL with the page URL shown in GSC) | I67: Standard | J67: 0 | K67: 1 | L67: Yes | M67: Monitor | N67: Copy Writer | O67: Open | R67: 0 | S67: self | T67: =IFERROR(HYPERLINK("#'Main'!B"&MATCH(TRIM(A67),'Main'!B:B,0),"Open"),HYPERLINK("#'Main'!B1","Open")) | U67: =IFERROR(HYPERLINK("#'Technical Diagnostics'!A"&MATCH(A67,'Technical Diagnostics'!A:A,0),"Open"),HYPERLINK("#'Technical Diagnostics'!A1","Open"))
A68: https://africanmarketingconfederation.org/smoke-archive/page-53 | B68: 30 | C68: Warning | D68: 80 | F68: 0 | G68: 2026-06-01 to 2026-06-30 (30-day window; excludes today; typical GSC lag ~48h) | H68: No Search Analytics row matched this URL in the 30-day export (compare Final URL with the page URL shown in GSC) | I68: Standard | J68: 0 | K68: 1 | L68: Yes | M68: Monitor | N68: Copy Writer | O68: Open | R68: 0 | S68: self | T68: =IFERROR(HYPERLINK("#'Main'!B"&MATCH(TRIM(A68),'Main'!B:B,0),"Open"),HYPERLINK("#'Main'!B1","Open")) | U68: =IFERROR(HYPERLINK("#'Technical Diagnostics'!A"&MATCH(A68,'Technical Diagnostics'!A:A,0),"Open"),HYPERLINK("#'Technical Diagnostics'!A1","Open"))
A69: https://africanmarketingconfederation.org/smoke-archive/page-57 | B69: 30 | C69: Warning | D69: 80 | F69: 0 | G69: 2026-06-01 to 2026-06-30 (30-day window; excludes today; typical GSC lag ~48h) | H69: No Search Analytics row matched this URL in the 30-day export (compare Final URL with the page URL shown in GSC) | I69: Standard | J69: 0 | K69: 1 | L69: Yes | M69: Monitor | N69: Copy Writer | O69: Open | R69: 0 | S69: self | T69: =IFERROR(HYPERLINK("#'Main'!B"&MATCH(TRIM(A69),'Main'!B:B,0),"Open"),HYPERLINK("#'Main'!B1","Open")) | U69: =IFERROR(HYPERLINK("#'Technical Diagnostics'!A"&MATCH(A69,'Technical Diagnostics'!A:A,0),"Open"),HYPERLINK("#'Technical Diagnostics'!A1","Open"))
A70: https://africanmarketingconfederation.org/smoke-archive/page-58 | B70: 30 | C70: Warning | D70: 80 | F70: 0 | G70: 2026-06-01 to 2026-06-30 (30-day window; excludes today; typical GSC lag ~48h) | H70: No Search Analytics row matched this URL in the 30-day export (compare Final URL with the page URL shown in GSC) | I70: Standard | J70: 0 | K70: 1 | L70: Yes | M70: Monitor | N70: Copy Writer | O70: Open | R70: 0 | S70: self | T70: =IFERROR(HYPERLINK("#'Main'!B"&MATCH(TRIM(A70),'Main'!B:B,0),"Open"),HYPERLINK("#'Main'!B1","Open")) | U70: =IFERROR(HYPERLINK("#'Technical Diagnostics'!A"&MATCH(A70,'Technical Diagnostics'!A:A,0),"Open"),HYPERLINK("#'Technical Diagnostics'!A1","Open"))
A71: https://africanmarketingconfederation.org/smoke-archive/page-59 | B71: 30 | C71: Warning | D71: 80 | F71: 0 | G71: 2026-06-01 to 2026-06-30 (30-day window; excludes today; typical GSC lag ~48h) | H71: No Search Analytics row matched this URL in the 30-day export (compare Final URL with the page URL shown in GSC) | I71: Standard | J71: 0 | K71: 1 | L71: Yes | M71: Monitor | N71: Copy Writer | O71: Open | R71: 0 | S71: self | T71: =IFERROR(HYPERLINK("#'Main'!B"&MATCH(TRIM(A71),'Main'!B:B,0),"Open"),HYPERLINK("#'Main'!B1","Open")) | U71: =IFERROR(HYPERLINK("#'Technical Diagnostics'!A"&MATCH(A71,'Technical Diagnostics'!A:A,0),"Open"),HYPERLINK("#'Technical Diagnostics'!A1","Open"))
A72: https://africanmarketingconfederation.org/smoke-archive/page-61 | B72: 30 | C72: Warning | D72: 80 | F72: 0 | G72: 2026-06-01 to 2026-06-30 (30-day window; excludes today; typical GSC lag ~48h) | H72: No Search Analytics row matched this URL in the 30-day export (compare Final URL with the page URL shown in GSC) | I72: Standard | J72: 0 | K72: 1 | L72: Yes | M72: Monitor | N72: Copy Writer | O72: Open | R72: 0 | S72: self | T72: =IFERROR(HYPERLINK("#'Main'!B"&MATCH(TRIM(A72),'Main'!B:B,0),"Open"),HYPERLINK("#'Main'!B1","Open")) | U72: =IFERROR(HYPERLINK("#'Technical Diagnostics'!A"&MATCH(A72,'Technical Diagnostics'!A:A,0),"Open"),HYPERLINK("#'Technical Diagnostics'!A1","Open"))
A73: https://africanmarketingconfederation.org/smoke-archive/page-62 | B73: 30 | C73: Warning | D73: 80 | F73: 0 | G73: 2026-06-01 to 2026-06-30 (30-day window; excludes today; typical GSC lag ~48h) | H73: No Search Analytics row matched this URL in the 30-day export (compare Final URL with the page URL shown in GSC) | I73: Standard | J73: 0 | K73: 1 | L73: Yes | M73: Monitor | N73: Copy Writer | O73: Open | R73: 0 | S73: self | T73: =IFERROR(HYPERLINK("#'Main'!B"&MATCH(TRIM(A73),'Main'!B:B,0),"Open"),HYPERLINK("#'Main'!B1","Open")) | U73: =IFERROR(HYPERLINK("#'Technical Diagnostics'!A"&MATCH(A73,'Technical Diagnostics'!A:A,0),"Open"),HYPERLINK("#'Technical Diagnostics'!A1","Open"))
... A83: https://africanmarketingconfederation.org/smoke-archive/page-4 | B83: 10 | C83: Observation | D83: 90 | F83: 0 | G83: 2026-06-01 to 2026-06-30 (30-day window; excludes today; typical GSC lag ~48h) | H83: No Search Analytics row matched this URL in the 30-day export (compare Final URL with the page URL shown in GSC) | I83: Standard | J83: 0 | K83: 0 | L83: No | M83: Monitor | N83: Copy Writer | O83: Open | R83: 0 | S83: self | T83: =IFERROR(HYPERLINK("#'Main'!B"&MATCH(TRIM(A83),'Main'!B:B,0),"Open"),HYPERLINK("#'Main'!B1","Open")) | U83: =IFERROR(HYPERLINK("#'Technical Diagnostics'!A"&MATCH(A83,'Technical Diagnostics'!A:A,0),"Open"),HYPERLINK("#'Technical Diagnostics'!A1","Open"))
A84: https://africanmarketingconfederation.org/smoke-archive/page-44 | B84: 10 | C84: Observation | D84: 90 | F84: 0 | G84: 2026-06-01 to 2026-06-30 (30-day window; excludes today; typical GSC lag ~48h) | H84: No Search Analytics row matched this URL in the 30-day export (compare Final URL with the page URL shown in GSC) | I84: Standard | J84: 0 | K84: 0 | L84: No | M84: Monitor | N84: Copy Writer | O84: Open | R84: 0 | T84: =IFERROR(HYPERLINK("#'Main'!B"&MATCH(TRIM(A84),'Main'!B:B,0),"Open"),HYPERLINK("#'Main'!B1","Open")) | U84: =IFERROR(HYPERLINK("#'Technical Diagnostics'!A"&MATCH(A84,'Technical Diagnostics'!A:A,0),"Open"),HYPERLINK("#'Technical Diagnostics'!A1","Open"))
A85: https://africanmarketingconfederation.org/smoke-archive/page-76 | B85: 10 | C85: Observation | D85: 90 | F85: 0 | G85: 2026-06-01 to 2026-06-30 (30-day window; excludes today; typical GSC lag ~48h) | H85: No Search Analytics row matched this URL in the 30-day export (compare Final URL with the page URL shown in GSC) | I85: Standard | J85: 0 | K85: 0 | L85: No | M85: Monitor | N85: Copy Writer | O85: Open | R85: 0 | S85: self | T85: =IFERROR(HYPERLINK("#'Main'!B"&MATCH(TRIM(A85),'Main'!B:B,0),"Open"),HYPERLINK("#'Main'!B1","Open")) | U85: =IFERROR(HYPERLINK("#'Technical Diagnostics'!A"&MATCH(A85,'Technical Diagnostics'!A:A,0),"Open"),HYPERLINK("#'Technical Diagnostics'!A1","Open"))

Sheet FixPlan
A1: ← Return to Executive Briefing | C1: =IFERROR(INDEX('Audit Run Details'!$B:$B,MATCH("Target Site",'Audit Run Details'!$A:$A,0)),"") & " — " & IFERROR(INDEX('Audit Run Details'!$B:$B,MATCH("Total URLs",'Audit Run Details'!$A:$A,0)),"") & " URLs crawled — " & LEFT(IFERROR(INDEX('Audit Run Details'!$B:$B,MATCH("Run Timestamp",'Audit Run Details'!$A:$A,0)),""),10)
A2: Issue Type | B2: Severity | C2: Priority Score | D2: Affected Count | E2: Affected URLs | F2: Detail Reference Tab | G2: Resolution Type | H2: URL | I2: Recommended Fix | J2: Likely Root Cause | K2: Owner | L2: Agency Owner | M2: Effort | N2: Est. Hours | O2: Est. Sprint Points | P2: Aging/Priority | Q2: Status | R2: Verified By | S2: Date Resolved | T2: Revenue Risk | U2: Action Needed | V2: Jump to Details | W2: Sprint | X2: Category | Y2: Open in Main | Z2: Hub Status (Content Hub)
A3: No Consent Manager Detected | B3: Observation | C3: 37 | D3: 83 | E3: SEE DETAILS IN Technical Diagnostics | F3: Technical Diagnostics | G3: Site Config | H3: https://africanmarketingconfederation.org/ | I3: Apply fix based on issue type and re-run audit. | J3: Template/technical implementation quality issue. | K3: Copy Writer | L3: Agency SEO | M3: S | N3: 4 | O3: 2 | P3: Backlog | Q3: In Review | T3: Monitor | U3: No | V3: Open in Main Tab | X3: SEO | Y3: =IFERROR(HYPERLINK("#'Main'!B"&MATCH(TRIM(H3),'Main'!B:B,0),"Open"),HYPERLINK("#'Main'!B1","Open")) | Z3: =IFERROR(INDEX('Content Optimisation Hub'!F3:F10000,MATCH(H3,'Content Optimisation Hub'!I3:I10000,0)),"Not in Hub")
A4: Lab TBT 150ms–300ms (Mobile) | B4: Observation | C4: 40 | D4: 83 | E4: SEE DETAILS IN Technical Diagnostics | F4: Technical Diagnostics | G4: Global Template | H4: https://africanmarketingconfederation.org/ | I4: Apply fix based on issue type and re-run audit. | J4: Template/technical implementation quality issue. | K4: Dev | L4: Agency Dev | M4: M | N4: 10 | O4: 5 | P4: Backlog | Q4: In Review | T4: Monitor | U4: No | V4: Open in Main Tab | X4: SEO | Y4: =IFERROR(HYPERLINK("#'Main'!B"&MATCH(TRIM(H4),'Main'!B:B,0),"Open"),HYPERLINK("#'Main'!B1","Open")) | Z4: =IFERROR(INDEX('Content Optimisation Hub'!F3:F10000,MATCH(H4,'Content Optimisation Hub'!I3:I10000,0)),"Not in Hub")
A5: Moderate Lighthouse Performance Mobile (50–89) | B5: Observation | C5: 40 | D5: 83 | E5: SEE DETAILS IN Technical Diagnostics | F5: Technical Diagnostics | G5: Global Template | H5: https://africanmarketingconfederation.org/ | I5: Apply fix based on issue type and re-run audit. | J5: Template/technical implementation quality issue. | K5: Dev | L5: Agency Dev | M5: M | N5: 10 | O5: 5 | P5: Backlog | Q5: In Review | T5: Monitor | U5: No | V5: Open in Main Tab | X5: SEO | Y5: =IFERROR(HYPERLINK("#'Main'!B"&MATCH(TRIM(H5),'Main'!B:B,0),"Open"),HYPERLINK("#'Main'!B1","Open")) | Z5: =IFERROR(INDEX('Content Optimisation Hub'!F3:F10000,MATCH(H5,'Content Optimisation Hub'!I3:I10000,0)),"Not in Hub")
A6: Render Blocking Resources | B6: Observation | C6: 40 | D6: 83 | E6: SEE DETAILS IN Technical Diagnostics | F6: Technical Diagnostics | G6: Global Template | H6: https://africanmarketingconfederation.org/ | I6: Apply fix based on issue type and re-run audit. | J6: Template/technical implementation quality issue. | K6: Dev | L6: Agency Dev | M6: M | N6: 10 | O6: 5 | P6: Backlog | Q6: In Review | T6: Monitor | U6: No | V6: Open in Main Tab | X6: SEO | Y6: =IFERROR(HYPERLINK("#'Main'!B"&MATCH(TRIM(H6),'Main'!B:B,0),"Open"),HYPERLINK("#'Main'!B1","Open")) | Z6: =IFERROR(INDEX('Content Optimisation Hub'!F3:F10000,MATCH(H6,'Content Optimisation Hub'!I3:I10000,0)),"Not in Hub")
A7: Missing OG Image | B7: Warning | C7: 73 | D7: 63 | E7: SEE DETAILS IN Technical Diagnostics | F7: Technical Diagnostics | G7: Global Template | H7: https://africanmarketingconfederation.org/smoke-archive/page-1 | I7: Apply fix based on issue type and re-run audit. | J7: Template/technical implementation quality issue. | K7: Copy Writer | L7: Agency SEO | M7: L | N7: 16 | O7: 8 | P7: Next Sprint | Q7: To Do | T7: Medium Risk | U7: Yes | V7: Open in Main Tab | X7: SEO | Y7: =IFERROR(HYPERLINK("#'Main'!B"&MATCH(TRIM(H7),'Main'!B:B,0),"Open"),HYPERLINK("#'Main'!B1","Open")) | Z7: =IFERROR(INDEX('Content Optimisation Hub'!F3:F10000,MATCH(H7,'Content Optimisation Hub'!I3:I10000,0)),"Not in Hub")
A8: Missing Meta Description | B8: Warning | C8: 70 | D8: 15 | E8: SEE DETAILS IN Technical Diagnostics | F8: Technical Diagnostics | G8: Global Template | H8: https://africanmarketingconfederation.org/smoke-archive/page-5 | I8: Add concise unique description aligned with user intent. | J8: Meta description missing or empty. | K8: Copy Writer | L8: Agency SEO | M8: M | N8: 10 | O8: 5 | P8: Next Sprint | Q8: To Do | T8: Medium Risk | U8: Yes | V8: Open in Main Tab | X8: SEO | Y8: =IFERROR(HYPERLINK("#'Main'!B"&MATCH(TRIM(H8),'Main'!B:B,0),"Open"),HYPERLINK("#'Main'!B1","Open")) | Z8: =IFERROR(INDEX('Content Optimisation Hub'!F3:F10000,MATCH(H8,'Content Optimisation Hub'!I3:I10000,0)),"Not in Hub")
A9: Missing OG Description | B9: Warning | C9: 70 | D9: 15 | E9: SEE DETAILS IN Technical Diagnostics | F9: Technical Diagnostics | G9: Global Template | H9: https://africanmarketingconfederation.org/smoke-archive/page-5 | I9: Apply fix based on issue type and re-run audit. | J9: Template/technical implementation quality issue. | K9: Copy Writer | L9: Agency SEO | M9: M | N9: 10 | O9: 5 | P9: Next Sprint | Q9: To Do | T9: Medium Risk | U9: Yes | V9: Open in Main Tab | X9: SEO | Y9: =IFERROR(HYPERLINK("#'Main'!B"&MATCH(TRIM(H9),'Main'!B:B,0),"Open"),HYPERLINK("#'Main'!B1","Open")) | Z9: =IFERROR(INDEX('Content Optimisation Hub'!F3:F10000,MATCH(H9,'Content Optimisation Hub'!I3:I10000,0)),"Not in Hub")
A10: Low Image Alt Coverage | B10: Warning | C10: 70 | D10: 13 | E10: SEE DETAILS IN Technical Diagnostics | F10: Technical Diagnostics | G10: Global Template | H10: https://africanmarketingconfederation.org/smoke-archive/page-6 | I10: Apply fix based on issue type and re-run audit. | J10: Template/technical implementation quality issue. | K10: Copy Writer | L10: Agency SEO | M10: M | N10: 10 | O10: 5 | P10: Next Sprint | Q10: To Do | T10: Medium Risk | U10: Yes | V10: Open in Main Tab | X10: SEO | Y10: =IFERROR(HYPERLINK("#'Main'!B"&MATCH(TRIM(H10),'Main'!B:B,0),"Open"),HYPERLINK("#'Main'!B1","Open")) | Z10: =IFERROR(INDEX('Content Optimisation Hub'!F3:F10000,MATCH(H10,'Content Optimisation Hub'!I3:I10000,0)),"Not in Hub")
A11: Non-200 Status | B11: Critical | C11: 102 | D11: 11 | E11: SEE DETAILS IN Technical Diagnostics | F11: Technical Diagnostics | G11: Global Template | H11: https://africanmarketingconfederation.org/ | I11: Fix status code, restore page, or implement correct redirect to canonical destination. | J11: URL returns 4xx/5xx or equivalent failure. | K11: Server/Host | L11: Agency Dev | M11: S | N11: 4 | O11: 2 | P11: Immediate (Current Sprint) | Q11: To Do | T11: High Risk | U11: Yes | V11: Open in Main Tab | X11: SEO | Y11: =IFERROR(HYPERLINK("#'Main'!B"&MATCH(TRIM(H11),'Main'!B:B,0),"Open"),HYPERLINK("#'Main'!B1","Open")) | Z11: =IFERROR(INDEX('Content Optimisation Hub'!F3:F10000,MATCH(H11,'Content Optimisation Hub'!I3:I10000,0)),"Not in Hub")
A12: No Author Attribution | B12: Observation | C12: 37 | D12: 11 | E12: SEE DETAILS IN Technical Diagnostics | F12: Technical Diagnostics | G12: Global Template | H12: https://africanmarketingconfederation.org/smoke-archive/page-7 | I12: Apply fix based on issue type and re-run audit. | J12: Template/technical implementation quality issue. | K12: Copy Writer | L12: Agency SEO | M12: S | N12: 4 | O12: 2 | P12: Backlog | Q12: In Review | T12: Monitor | U12: No | V12: Open in Main Tab | X12: SEO | Y12: =IFERROR(HYPERLINK("#'Main'!B"&MATCH(TRIM(H12),'Main'!B:B,0),"Open"),HYPERLINK("#'Main'!B1","Open")) | Z12: =IFERROR(INDEX('Content Optimisation Hub'!F3:F10000,MATCH(H12,'Content Optimisation Hub'!I3:I10000,0)),"Not in Hub")
A13: Low E-E-A-T Signal Score (<3) | B13: Warning | C13: 67 | D13: 11 | E13: SEE DETAILS IN Technical Diagnostics | F13: Technical Diagnostics | G13: Global Template | H13: https://africanmarketingconfederation.org/smoke-archive/page-7 | I13: Apply fix based on issue type and re-run audit. | J13: Template/technical implementation quality issue. | K13: Copy Writer | L13: Agency SEO | M13: S | N13: 4 | O13: 2 | P13: Next Sprint | Q13: To Do | T13: Medium Risk | U13: Yes | V13: Open in Main Tab | X13: SEO | Y13: =IFERROR(HYPERLINK("#'Main'!B"&MATCH(TRIM(H13),'Main'!B:B,0),"Open"),HYPERLINK("#'Main'!B1","Open")) | Z13: =IFERROR(INDEX('Content Optimisation Hub'!F3:F10000,MATCH(H13,'Content Optimisation Hub'!I3:I10000,0)),"Not in Hub")
A14: No Question Headings | B14: Observation | C14: 37 | D14: 9 | E14: https://africanmarketingconfederation.org/smoke-archive/page-9 https://africanmarketingconfederation.org/smoke-archive/page-18 https://africanmarketingconfederation.org/smoke-archive/page-27 https://africanmarketingconfederation.org/smoke-archive/page-36 https://africanmarketingconfederation.org/smoke-archive/page-45 https://africanmarketingconfederation.org/smoke-archive/page-54 https://africanmarketingconfederation.org/smoke-archive/page-63 https://africanmarketingconfederation.org/smoke-archive/page-72 https://africanmarketingconfederation.org/discovered-via-bfs-1 | F14: Content & AI Readiness | G14: Manual Content | H14: https://africanmarketingconfederation.org/smoke-archive/page-9 | I14: Rewrite priority H2/H3 headings into natural-language questions (Who/What/How) so the following paragraph can serve as a direct extractable answer. | J14: Headings are not phrased as user questions. | K14: Copy Writer | L14: Agency SEO | M14: S | N14: 4 | O14: 2 | P14: Backlog | Q14: In Review | T14: Monitor | U14: No | V14: Open in Main Tab | X14: AEO | Y14: =IFERROR(HYPERLINK("#'Main'!B"&MATCH(TRIM(H14),'Main'!B:B,0),"Open"),HYPERLINK("#'Main'!B1","Open")) | Z14: =IFERROR(INDEX('Content Optimisation Hub'!F3:F10000,MATCH(H14,'Content Optimisation Hub'!I3:I10000,0)),"Not in Hub")
A15: No Answer-Friendly Structure | B15: Observation | C15: 37 | D15: 9 | E15: https://africanmarketingconfederation.org/smoke-archive/page-9 https://africanmarketingconfederation.org/smoke-archive/page-18 https://africanmarketingconfederation.org/smoke-archive/page-27 https://africanmarketingconfederation.org/smoke-archive/page-36 https://africanmarketingconfederation.org/smoke-archive/page-45 https://africanmarketingconfederation.org/smoke-archive/page-54 https://africanmarketingconfederation.org/smoke-archive/page-63 https://africanmarketingconfederation.org/smoke-archive/page-72 https://africanmarketingconfederation.org/discovered-via-bfs-1 | F15: Content & AI Readiness | G15: Manual Content | H15: https://africanmarketingconfederation.org/smoke-archive/page-9 | I15: Break data-heavy explanations into ul/ol steps or a comparison table so LLMs can cite discrete facts without re-parsing long paragraphs. | J15: Dense prose without lists or tables where facts could be chunked. | K15: Copy Writer | L15: Agency SEO | M15: S | N15: 4 | O15: 2 | P15: Backlog | Q15: In Review | T15: Monitor | U15: No | V15: Open in Main Tab | X15: AEO | Y15: =IFERROR(HYPERLINK("#'Main'!B"&MATCH(TRIM(H15),'Main'!B:B,0),"Open"),HYPERLINK("#'Main'!B1","Open")) | Z15: =IFERROR(INDEX('Content Optimisation Hub'!F3:F10000,MATCH(H15,'Content Optimisation Hub'!I3:I10000,0)),"Not in Hub")
A16: No 40-60 Word Answer Paragraphs | B16: Observation | C16: 37 | D16: 9 | E16: https://africanmarketingconfederation.org/smoke-archive/page-9 https://africanmarketingconfederation.org/smoke-archive/page-18 https://africanmarketingconfederation.org/smoke-archive/page-27 https://africanmarketingconfederation.org/smoke-archive/page-36 https://africanmarketingconfederation.org/smoke-archive/page-45 https://africanmarketingconfederation.org/smoke-archive/page-54 https://africanmarketingconfederation.org/smoke-archive/page-63 https://africanmarketingconfederation.org/smoke-archive/page-72 https://africanmarketingconfederation.org/discovered-via-bfs-1 | F16: Content & AI Readiness | G16: Manual Content | H16: https://africanmarketingconfederation.org/smoke-archive/page-9 | I16: Refactor each target section to lead with a ~45-word factual definition (no fluff) immediately under the question heading to improve LLM Position Zero retrieval. | J16: No 40–60 word definitional paragraph directly under a question-style H2/H3. | K16: Copy Writer | L16: Agency SEO | M16: S | N16: 4 | O16: 2 | P16: Backlog | Q16: In Review | T16: Monitor | U16: No | V16: Open in Main Tab | X16: AEO | Y16: =IFERROR(HYPERLINK("#'Main'!B"&MATCH(TRIM(H16),'Main'!B:B,0),"Open"),HYPERLINK("#'Main'!B1","Open")) | Z16: =IFERROR(INDEX('Content Optimisation Hub'!F3:F10000,MATCH(H16,'Content Optimisation Hub'!I3:I10000,0)),"Not in Hub")
A17: Missing OG Title | B17: Warning | C17: 67 | D17: 9 | E17: https://africanmarketingconfederation.org/smoke-archive/page-8 https://africanmarketingconfederation.org/smoke-archive/page-16 https://africanmarketingconfederation.org/smoke-archive/page-24 https://africanmarketingconfederation.org/smoke-archive/page-32 https://africanmarketingconfederation.org/smoke-archive/page-40 https://africanmarketingconfederation.org/smoke-archive/page-48 https://africanmarketingconfederation.org/smoke-archive/page-56 https://africanmarketingconfederation.org/smoke-archive/page-64 https://africanmarketingconfederation.org/smoke-archive/page-72 | F17: Technical Diagnostics | G17: Manual Content | H17: https://africanmarketingconfederation.org/smoke-archive/page-8 | I17: Apply fix based on issue type and re-run audit. | J17: Template/technical implementation quality issue. | K17: Copy Writer | L17: Agency SEO | M17: S | N17: 4 | O17: 2 | P17: Next Sprint | Q17: To Do | T17: Medium Risk | U17: Yes | V17: Open in Main Tab | X17: SEO | Y17: =IFERROR(HYPERLINK("#'Main'!B"&MATCH(TRIM(H17),'Main'!B:B,0),"Open"),HYPERLINK("#'Main'!B1","Open")) | Z17: =IFERROR(INDEX('Content Optimisation Hub'!F3:F10000,MATCH(H17,'Content Optimisation Hub'!I3:I10000,0)),"Not in Hub")
A18: Low AEO Readiness Score | B18: Warning | C18: 67 | D18: 9 | E18: https://africanmarketingconfederation.org/smoke-archive/page-9 https://africanmarketingconfederation.org/smoke-archive/page-18 https://africanmarketingconfederation.org/smoke-archive/page-27 https://africanmarketingconfederation.org/smoke-archive/page-36 https://africanmarketingconfederation.org/smoke-archive/page-45 https://africanmarketingconfederation.org/smoke-archive/page-54 https://africanmarketingconfederation.org/smoke-archive/page-63 https://africanmarketingconfederation.org/smoke-archive/page-72 https://africanmarketingconfederation.org/discovered-via-bfs-1 | F18: Content & AI Readiness | G18: Manual Content | H18: https://africanmarketingconfederation.org/smoke-archive/page-9 | I18: Raise the weighted mix: add a 40–60 word factual paragraph under each question H2/H3, add FAQPage/HowTo/Speakable JSON-LD, tune copy to FK grade 7–10, add ul/ol/table for key facts, and ensure robots.txt explicitly allows GPTBot, PerplexityBot, and CCBot. | J18: Weighted AEO score is below the 70-point extraction-confidence band. | K18: Copy Writer | L18: Agency SEO | M18: S | N18: 4 | O18: 2 | P18: Next Sprint | Q18: To Do | T18: Medium Risk | U18: Yes | V18: Open in Main Tab | X18: AEO | Y18: =IFERROR(HYPERLINK("#'Main'!B"&MATCH(TRIM(H18),'Main'!B:B,0),"Open"),HYPERLINK("#'Main'!B1","Open")) | Z18: =IFERROR(INDEX('Content Optimisation Hub'!F3:F10000,MATCH(H18,'Content Optimisation Hub'!I3:I10000,0)),"Not in Hub")
A19: No Schema Markup | B19: Critical | C19: 105 | D19: 6 | E19: https://africanmarketingconfederation.org/smoke-archive/page-12 https://africanmarketingconfederation.org/smoke-archive/page-24 https://africanmarketingconfederation.org/smoke-archive/page-36 https://africanmarketingconfederation.org/smoke-archive/page-48 https://africanmarketingconfederation.org/smoke-archive/page-60 https://africanmarketingconfederation.org/smoke-archive/page-72 | F19: Technical Diagnostics | G19: Global Template | H19: https://africanmarketingconfederation.org/smoke-archive/page-12 | I19: Apply fix based on issue type and re-run audit. | J19: Template/technical implementation quality issue. | K19: Dev | L19: Agency Dev | M19: M | N19: 10 | O19: 5 | P19: Immediate (Current Sprint) | Q19: To Do | T19: High Risk | U19: Yes | V19: Open in Main Tab | X19: SEO | Y19: =IFERROR(HYPERLINK("#'Main'!B"&MATCH(TRIM(H19),'Main'!B:B,0),"Open"),HYPERLINK("#'Main'!B1","Open")) | Z19: =IFERROR(INDEX('Content Optimisation Hub'!F3:F10000,MATCH(H19,'Content Optimisation Hub'!I3:I10000,0)),"Not in Hub")

Sheet Quick Wins
A1: ← Return to Executive Briefing | C1: =IFERROR(INDEX('Audit Run Details'!$B:$B,MATCH("Target Site",'Audit Run Details'!$A:$A,0)),"") & " — " & IFERROR(INDEX('Audit Run Details'!$B:$B,MATCH("Total URLs",'Audit Run Details'!$A:$A,0)),"") & " URLs crawled — " & LEFT(IFERROR(INDEX('Audit Run Details'!$B:$B,MATCH("Run Timestamp",'Audit Run Details'!$A:$A,0)),""),10)
A2: Priority Score | B2: URL | C2: Issue | D2: Severity | E2: Effort (hrs) | F2: Owner | G2: GSC Clicks (30d) | H2: Business Risk Score | I2: Recommended Fix | J2: Sprint | K2: Revenue Risk | L2: Jump to FixPlan | M2: Open in Main
A3: 30.2 | B3: https://africanmarketingconfederation.org/ | C3: Non-200 Status | D3: Critical | E3: 4 | F3: Server/Host | G3: 52 | H3: 0 | I3: Fix status code, restore page, or implement correct redirect to canonical destination. | J3: Immediate (Current Sprint) | K3: High Risk | L3: =IFERROR(HYPERLINK("#'FixPlan'!A"&MATCH("Non-200 Status",'FixPlan'!B:B,0),"Open in FixPlan"),HYPERLINK("#'FixPlan'!A1","Open in FixPlan")) | M3: =IFERROR(HYPERLINK("#'Main'!B"&MATCH(TRIM(B3),'Main'!B:B,0),"Open"),HYPERLINK("#'Main'!B1","Open"))
A4: 7.7 | B4: https://africanmarketingconfederation.org/ | C4: No Consent Manager Detected | D4: Observation | E4: 4 | F4: Copy Writer | G4: 52 | H4: 0 | I4: Apply fix based on issue type and re-run audit. | J4: Backlog | K4: Monitor | L4: =IFERROR(HYPERLINK("#'FixPlan'!A"&MATCH("No Consent Manager Detected",'FixPlan'!B:B,0),"Open in FixPlan"),HYPERLINK("#'FixPlan'!A1","Open in FixPlan")) | M4: =IFERROR(HYPERLINK("#'Main'!B"&MATCH(TRIM(B4),'Main'!B:B,0),"Open"),HYPERLINK("#'Main'!B1","Open"))

Sheet Content Optimisation Hub
A1: ← Return to Executive Briefing | E1: CONTENT HUB (DIAGNOSTIC): Edit Title, Meta, and H1-H6 in-place; health columns and On-Page score update live. | Use Elementor link for CMS edits. | Set Status to Done when changes are live in the CMS. | AA1: NOTE: If images show '#BLOCKED!', enable external content in Excel security.
A2: Action Required | B2: On-Page Optimisation Score | C2: SEO Score | D2: Technical Health | E2: Copy Score | F2: Status | G2: Assigned Owner | H2: URL Slug Normalization | I2: URL | J2: Proposed URL Slug | K2: Current Title | L2: Title Health | M2: Current Meta Desc | N2: Meta Health | O2: H1 | P2: H1 Health | Q2: H2 | R2: H2 Health | S2: H3 | T2: H3 Health | U2: H4 | V2: H4 Health | W2: H5 | X2: H5 Health | Y2: H6 | Z2: H6 Health | AA2: Elementor Builder Link | AB2: Current OG-Image URL | AC2: OG Image Health | AD2: OG Image Preview | AE2: Open in Main | AF2: Recommended Action | AG2: Priority Reason | AH2: Entity Density (%) | AI2: Top Entities | AJ2: Citation Candidate Count | AK2: Semantic AEO Score
A3: =IF(B3>=85,"Complete","Needs Copy") | B3: =MIN(100,ROUND(0.30*(IF(L3="",0,IF(LEFT(L3,7)="MISSING",0,IF(ISNUMBER(SEARCH("OK",L3)),100,IF(ISNUMBER(SEARCH("SHORT",L3)),65,IF(ISNUMBER(SEARCH("LONG",L3)),50,70))))))+0.25*(IF(N3="",0,IF(LEFT(N3,7)="MISSING",0,IF(ISNUMBER(SEARCH("OK",N3)),100,IF(ISNUMBER(SEARCH("SHORT",N3)),65,IF(ISNUMBER(SEARCH("LONG",N3)),50,70))))))+0.20*(IF(P3="",0,IF(LEFT(P3,2)="OK",100,0)))+0.08*(IF(R3="",0,IF(LEFT(R3,2)="OK",100,0)))+0.06*(IF(T3="",0,IF(LEFT(T3,2)="OK",100,0)))+0.05*(IF(V3="",0,IF(LEFT(V3,2)="OK",100,0)))+0.03*(IF(X3="",0,IF(LEFT(X3,2)="OK",100,0)))+0.03*(IF(Z3="",0,IF(LEFT(Z3,2)="OK",100,0))),0)) | C3: =IFERROR(INDEX(OFFSET('Main'!$A$1,2,MATCH("SEO Score",'Main'!$2:$2,0)-1,99998,1),MATCH(TRIM(I3),OFFSET('Main'!$A$1,2,MATCH("URL",'Main'!$2:$2,0)-1,99998,1),0)),"") | D3: =IFERROR(INDEX(OFFSET('Main'!$A$1,2,MATCH("Technical Health",'Main'!$2:$2,0)-1,99998,1),MATCH(TRIM(I3),OFFSET('Main'!$A$1,2,MATCH("URL",'Main'!$2:$2,0)-1,99998,1),0)),"") | E3: =IFERROR(INDEX(OFFSET('Main'!$A$1,2,MATCH("Copy Score",'Main'!$2:$2,0)-1,99998,1),MATCH(TRIM(I3),OFFSET('Main'!$A$1,2,MATCH("URL",'Main'!$2:$2,0)-1,99998,1),0)),"") | F3: To Do | G3: Copy Writer | H3: =HYPERLINK("https://africanmarketingconfederation.org/discovered-via-bfs-1","Discovered Via Bfs 1") | I3: =HYPERLINK("https://africanmarketingconfederation.org/discovered-via-bfs-1","https://africanmarketingconfederation.org/discovered-via-bfs-1") | J3: discovered-via-bfs-1 | K3: Smoke title 81 | L3: =IF(K3="","MISSING",IF(AND(LEN(K3)>=50,LEN(K3)<=60),"OK 50-60 chars",IF(LEN(K3)<50,"SHORT: "&LEN(K3),"LONG: "&LEN(K3)))) | M3: Smoke meta description for page 81. | N3: =IF(M3="","MISSING",IF(AND(LEN(M3)>=120,LEN(M3)<=160),"OK 120-160 chars",IF(LEN(M3)<120,"SHORT: "&LEN(M3),"LONG: "&LEN(M3)))) | O3: Smoke heading | P3: OK | R3: =IF(ISBLANK(Q3),"MISSING","OK") | T3: =IF(ISBLANK(S3),"MISSING","OK") | V3: =IF(ISBLANK(U3),"MISSING","OK") | X3: =IF(ISBLANK(W3),"MISSING","OK") | Z3: =IF(ISBLANK(Y3),"MISSING","OK") | AC3: Missing OG image | AE3: =IFERROR(HYPERLINK("#'Main'!B"&MATCH(TRIM(I3),'Main'!B:B,0),"Open in Main"),IFERROR(HYPERLINK("#'Technical Diagnostics'!A"&MATCH(TRIM(I3),'Technical Diagnostics'!A:A,0),"Open in Technical"),"Not Found")) | AF3: Add a concise 40–60 word answer paragraph directly under a question-style heading to improve AEO extractability for: Smoke title 81. | AG3: Prioritised because of missing answer paragraphs + search intent: Informational + 9 open content/SEO issue(s). | AH3: 0 | AJ3: 0 | AK3: 0
A4: =IF(B4>=85,"Complete","Needs Copy") | B4: =MIN(100,ROUND(0.30*(IF(L4="",0,IF(LEFT(L4,7)="MISSING",0,IF(ISNUMBER(SEARCH("OK",L4)),100,IF(ISNUMBER(SEARCH("SHORT",L4)),65,IF(ISNUMBER(SEARCH("LONG",L4)),50,70))))))+0.25*(IF(N4="",0,IF(LEFT(N4,7)="MISSING",0,IF(ISNUMBER(SEARCH("OK",N4)),100,IF(ISNUMBER(SEARCH("SHORT",N4)),65,IF(ISNUMBER(SEARCH("LONG",N4)),50,70))))))+0.20*(IF(P4="",0,IF(LEFT(P4,2)="OK",100,0)))+0.08*(IF(R4="",0,IF(LEFT(R4,2)="OK",100,0)))+0.06*(IF(T4="",0,IF(LEFT(T4,2)="OK",100,0)))+0.05*(IF(V4="",0,IF(LEFT(V4,2)="OK",100,0)))+0.03*(IF(X4="",0,IF(LEFT(X4,2)="OK",100,0)))+0.03*(IF(Z4="",0,IF(LEFT(Z4,2)="OK",100,0))),0)) | C4: =IFERROR(INDEX(OFFSET('Main'!$A$1,2,MATCH("SEO Score",'Main'!$2:$2,0)-1,99998,1),MATCH(TRIM(I4),OFFSET('Main'!$A$1,2,MATCH("URL",'Main'!$2:$2,0)-1,99998,1),0)),"") | D4: =IFERROR(INDEX(OFFSET('Main'!$A$1,2,MATCH("Technical Health",'Main'!$2:$2,0)-1,99998,1),MATCH(TRIM(I4),OFFSET('Main'!$A$1,2,MATCH("URL",'Main'!$2:$2,0)-1,99998,1),0)),"") | E4: =IFERROR(INDEX(OFFSET('Main'!$A$1,2,MATCH("Copy Score",'Main'!$2:$2,0)-1,99998,1),MATCH(TRIM(I4),OFFSET('Main'!$A$1,2,MATCH("URL",'Main'!$2:$2,0)-1,99998,1),0)),"") | F4: To Do | G4: Copy Writer | H4: =HYPERLINK("https://africanmarketingconfederation.org/smoke-archive/page-10","Page 10") | I4: =HYPERLINK("https://africanmarketingconfederation.org/smoke-archive/page-10","https://africanmarketingconfederation.org/smoke-archive/page-10") | J4: page-10 | K4: Smoke title 10 | L4: =IF(K4="","MISSING",IF(AND(LEN(K4)>=50,LEN(K4)<=60),"OK 50-60 chars",IF(LEN(K4)<50,"SHORT: "&LEN(K4),"LONG: "&LEN(K4)))) | M4: MISSING DESCRIPTION | N4: =IF(M4="","MISSING",IF(AND(LEN(M4)>=120,LEN(M4)<=160),"OK 120-160 chars",IF(LEN(M4)<120,"SHORT: "&LEN(M4),"LONG: "&LEN(M4)))) | O4: Smoke heading | P4: OK | R4: =IF(ISBLANK(Q4),"MISSING","OK") | T4: =IF(ISBLANK(S4),"MISSING","OK") | V4: =IF(ISBLANK(U4),"MISSING","OK") | X4: =IF(ISBLANK(W4),"MISSING","OK") | Z4: =IF(ISBLANK(Y4),"MISSING","OK") | AC4: Missing OG image | AE4: =IFERROR(HYPERLINK("#'Main'!B"&MATCH(TRIM(I4),'Main'!B:B,0),"Open in Main"),IFERROR(HYPERLINK("#'Technical Diagnostics'!A"&MATCH(TRIM(I4),'Technical Diagnostics'!A:A,0),"Open in Technical"),"Not Found")) | AF4: Add a meta description (currently missing). Aim for 120–155 characters summarising: Smoke title 10. | AG4: Prioritised because of search intent: Informational + 7 open content/SEO issue(s). | AH4: 0 | AJ4: 0 | AK4: 0
A5: =IF(B5>=85,"Complete","Needs Copy") | B5: =MIN(100,ROUND(0.30*(IF(L5="",0,IF(LEFT(L5,7)="MISSING",0,IF(ISNUMBER(SEARCH("OK",L5)),100,IF(ISNUMBER(SEARCH("SHORT",L5)),65,IF(ISNUMBER(SEARCH("LONG",L5)),50,70))))))+0.25*(IF(N5="",0,IF(LEFT(N5,7)="MISSING",0,IF(ISNUMBER(SEARCH("OK",N5)),100,IF(ISNUMBER(SEARCH("SHORT",N5)),65,IF(ISNUMBER(SEARCH("LONG",N5)),50,70))))))+0.20*(IF(P5="",0,IF(LEFT(P5,2)="OK",100,0)))+0.08*(IF(R5="",0,IF(LEFT(R5,2)="OK",100,0)))+0.06*(IF(T5="",0,IF(LEFT(T5,2)="OK",100,0)))+0.05*(IF(V5="",0,IF(LEFT(V5,2)="OK",100,0)))+0.03*(IF(X5="",0,IF(LEFT(X5,2)="OK",100,0)))+0.03*(IF(Z5="",0,IF(LEFT(Z5,2)="OK",100,0))),0)) | C5: =IFERROR(INDEX(OFFSET('Main'!$A$1,2,MATCH("SEO Score",'Main'!$2:$2,0)-1,99998,1),MATCH(TRIM(I5),OFFSET('Main'!$A$1,2,MATCH("URL",'Main'!$2:$2,0)-1,99998,1),0)),"") | D5: =IFERROR(INDEX(OFFSET('Main'!$A$1,2,MATCH("Technical Health",'Main'!$2:$2,0)-1,99998,1),MATCH(TRIM(I5),OFFSET('Main'!$A$1,2,MATCH("URL",'Main'!$2:$2,0)-1,99998,1),0)),"") | E5: =IFERROR(INDEX(OFFSET('Main'!$A$1,2,MATCH("Copy Score",'Main'!$2:$2,0)-1,99998,1),MATCH(TRIM(I5),OFFSET('Main'!$A$1,2,MATCH("URL",'Main'!$2:$2,0)-1,99998,1),0)),"") | F5: To Do | G5: Copy Writer | H5: =HYPERLINK("https://africanmarketingconfederation.org/smoke-archive/page-12","Page 12") | I5: =HYPERLINK("https://africanmarketingconfederation.org/smoke-archive/page-12","https://africanmarketingconfederation.org/smoke-archive/page-12") | J5: page-12 | K5: Smoke title 12 | L5: =IF(K5="","MISSING",IF(AND(LEN(K5)>=50,LEN(K5)<=60),"OK 50-60 chars",IF(LEN(K5)<50,"SHORT: "&LEN(K5),"LONG: "&LEN(K5)))) | M5: Smoke meta description for page 12. | N5: =IF(M5="","MISSING",IF(AND(LEN(M5)>=120,LEN(M5)<=160),"OK 120-160 chars",IF(LEN(M5)<120,"SHORT: "&LEN(M5),"LONG: "&LEN(M5)))) | O5: Smoke heading | P5: OK | R5: =IF(ISBLANK(Q5),"MISSING","OK") | T5: =IF(ISBLANK(S5),"MISSING","OK") | V5: =IF(ISBLANK(U5),"MISSING","OK") | X5: =IF(ISBLANK(W5),"MISSING","OK") | Z5: =IF(ISBLANK(Y5),"MISSING","OK") | AB5: =HYPERLINK("https://africanmarketingconfederation.org/og-12.jpg","View Image") | AC5: Present — mixed OG images across site | AD5: =IF(LEN("https://africanmarketingconfederation.org/og-12.jpg")>0,IFERROR(_xlfn.IMAGE("https://africanmarketingconfederation.org/og-12.jpg"),"https://africanmarketingconfederation.org/og-12.jpg"),"") | AE5: =IFERROR(HYPERLINK("#'Main'!B"&MATCH(TRIM(I5),'Main'!B:B,0),"Open in Main"),IFERROR(HYPERLINK("#'Technical Diagnostics'!A"&MATCH(TRIM(I5),'Technical Diagnostics'!A:A,0),"Open in Technical"),"Not Found")) | AF5: Restructure content for a faq featured snippet: use a direct answer block, scannable list, or FAQ schema as appropriate for “Smoke title 12”. | AG5: Prioritised because of search intent: Informational + 6 open content/SEO issue(s). | AH5: 0 | AJ5: 0 | AK5: 0
A6: =IF(B6>=85,"Complete","Needs Copy") | B6: =MIN(100,ROUND(0.30*(IF(L6="",0,IF(LEFT(L6,7)="MISSING",0,IF(ISNUMBER(SEARCH("OK",L6)),100,IF(ISNUMBER(SEARCH("SHORT",L6)),65,IF(ISNUMBER(SEARCH("LONG",L6)),50,70))))))+0.25*(IF(N6="",0,IF(LEFT(N6,7)="MISSING",0,IF(ISNUMBER(SEARCH("OK",N6)),100,IF(ISNUMBER(SEARCH("SHORT",N6)),65,IF(ISNUMBER(SEARCH("LONG",N6)),50,70))))))+0.20*(IF(P6="",0,IF(LEFT(P6,2)="OK",100,0)))+0.08*(IF(R6="",0,IF(LEFT(R6,2)="OK",100,0)))+0.06*(IF(T6="",0,IF(LEFT(T6,2)="OK",100,0)))+0.05*(IF(V6="",0,IF(LEFT(V6,2)="OK",100,0)))+0.03*(IF(X6="",0,IF(LEFT(X6,2)="OK",100,0)))+0.03*(IF(Z6="",0,IF(LEFT(Z6,2)="OK",100,0))),0)) | C6: =IFERROR(INDEX(OFFSET('Main'!$A$1,2,MATCH("SEO Score",'Main'!$2:$2,0)-1,99998,1),MATCH(TRIM(I6),OFFSET('Main'!$A$1,2,MATCH("URL",'Main'!$2:$2,0)-1,99998,1),0)),"") | D6: =IFERROR(INDEX(OFFSET('Main'!$A$1,2,MATCH("Technical Health",'Main'!$2:$2,0)-1,99998,1),MATCH(TRIM(I6),OFFSET('Main'!$A$1,2,MATCH("URL",'Main'!$2:$2,0)-1,99998,1),0)),"") | E6: =IFERROR(INDEX(OFFSET('Main'!$A$1,2,MATCH("Copy Score",'Main'!$2:$2,0)-1,99998,1),MATCH(TRIM(I6),OFFSET('Main'!$A$1,2,MATCH("URL",'Main'!$2:$2,0)-1,99998,1),0)),"") | F6: To Do | G6: Copy Writer | H6: =HYPERLINK("https://africanmarketingconfederation.org/smoke-archive/page-15","Page 15") | I6: =HYPERLINK("https://africanmarketingconfederation.org/smoke-archive/page-15","https://africanmarketingconfederation.org/smoke-archive/page-15") | J6: page-15 | K6: Smoke title 15 | L6: =IF(K6="","MISSING",IF(AND(LEN(K6)>=50,LEN(K6)<=60),"OK 50-60 chars",IF(LEN(K6)<50,"SHORT: "&LEN(K6),"LONG: "&LEN(K6)))) | M6: MISSING DESCRIPTION | N6: =IF(M6="","MISSING",IF(AND(LEN(M6)>=120,LEN(M6)<=160),"OK 120-160 chars",IF(LEN(M6)<120,"SHORT: "&LEN(M6),"LONG: "&LEN(M6)))) | O6: Smoke heading | P6: OK | R6: =IF(ISBLANK(Q6),"MISSING","OK") | T6: =IF(ISBLANK(S6),"MISSING","OK") | V6: =IF(ISBLANK(U6),"MISSING","OK") | X6: =IF(ISBLANK(W6),"MISSING","OK") | Z6: =IF(ISBLANK(Y6),"MISSING","OK") | AC6: Missing OG image | AE6: =IFERROR(HYPERLINK("#'Main'!B"&MATCH(TRIM(I6),'Main'!B:B,0),"Open in Main"),IFERROR(HYPERLINK("#'Technical Diagnostics'!A"&MATCH(TRIM(I6),'Technical Diagnostics'!A:A,0),"Open in Technical"),"Not Found")) | AF6: Add a meta description (currently missing). Aim for 120–155 characters summarising: Smoke title 15. | AG6: Prioritised because of search intent: Informational + 7 open content/SEO issue(s). | AH6: 0 | AJ6: 0 | AK6: 0
A7: =IF(B7>=85,"Complete","Needs Copy") | B7: =MIN(100,ROUND(0.30*(IF(L7="",0,IF(LEFT(L7,7)="MISSING",0,IF(ISNUMBER(SEARCH("OK",L7)),100,IF(ISNUMBER(SEARCH("SHORT",L7)),65,IF(ISNUMBER(SEARCH("LONG",L7)),50,70))))))+0.25*(IF(N7="",0,IF(LEFT(N7,7)="MISSING",0,IF(ISNUMBER(SEARCH("OK",N7)),100,IF(ISNUMBER(SEARCH("SHORT",N7)),65,IF(ISNUMBER(SEARCH("LONG",N7)),50,70))))))+0.20*(IF(P7="",0,IF(LEFT(P7,2)="OK",100,0)))+0.08*(IF(R7="",0,IF(LEFT(R7,2)="OK",100,0)))+0.06*(IF(T7="",0,IF(LEFT(T7,2)="OK",100,0)))+0.05*(IF(V7="",0,IF(LEFT(V7,2)="OK",100,0)))+0.03*(IF(X7="",0,IF(LEFT(X7,2)="OK",100,0)))+0.03*(IF(Z7="",0,IF(LEFT(Z7,2)="OK",100,0))),0)) | C7: =IFERROR(INDEX(OFFSET('Main'!$A$1,2,MATCH("SEO Score",'Main'!$2:$2,0)-1,99998,1),MATCH(TRIM(I7),OFFSET('Main'!$A$1,2,MATCH("URL",'Main'!$2:$2,0)-1,99998,1),0)),"") | D7: =IFERROR(INDEX(OFFSET('Main'!$A$1,2,MATCH("Technical Health",'Main'!$2:$2,0)-1,99998,1),MATCH(TRIM(I7),OFFSET('Main'!$A$1,2,MATCH("URL",'Main'!$2:$2,0)-1,99998,1),0)),"") | E7: =IFERROR(INDEX(OFFSET('Main'!$A$1,2,MATCH("Copy Score",'Main'!$2:$2,0)-1,99998,1),MATCH(TRIM(I7),OFFSET('Main'!$A$1,2,MATCH("URL",'Main'!$2:$2,0)-1,99998,1),0)),"") | F7: To Do | G7: Copy Writer | H7: =HYPERLINK("https://africanmarketingconfederation.org/smoke-archive/page-16","Page 16") | I7: =HYPERLINK("https://africanmarketingconfederation.org/smoke-archive/page-16","https://africanmarketingconfederation.org/smoke-archive/page-16") | J7: page-16 | K7: Smoke title 16 | L7: =IF(K7="","MISSING",IF(AND(LEN(K7)>=50,LEN(K7)<=60),"OK 50-60 chars",IF(LEN(K7)<50,"SHORT: "&LEN(K7),"LONG: "&LEN(K7)))) | M7: Smoke meta description for page 16. | N7: =IF(M7="","MISSING",IF(AND(LEN(M7)>=120,LEN(M7)<=160),"OK 120-160 chars",IF(LEN(M7)<120,"SHORT: "&LEN(M7),"LONG: "&LEN(M7)))) | O7: Smoke heading | P7: OK | R7: =IF(ISBLANK(Q7),"MISSING","OK") | T7: =IF(ISBLANK(S7),"MISSING","OK") | V7: =IF(ISBLANK(U7),"MISSING","OK") | X7: =IF(ISBLANK(W7),"MISSING","OK") | Z7: =IF(ISBLANK(Y7),"MISSING","OK") | AB7: =HYPERLINK("https://africanmarketingconfederation.org/og-16.jpg","View Image") | AC7: Present — mixed OG images across site | AD7: =IF(LEN("https://africanmarketingconfederation.org/og-16.jpg")>0,IFERROR(_xlfn.IMAGE("https://africanmarketingconfederation.org/og-16.jpg"),"https://africanmarketingconfederation.org/og-16.jpg"),"") | AE7: =IFERROR(HYPERLINK("#'Main'!B"&MATCH(TRIM(I7),'Main'!B:B,0),"Open in Main"),IFERROR(HYPERLINK("#'Technical Diagnostics'!A"&MATCH(TRIM(I7),'Technical Diagnostics'!A:A,0),"Open in Technical"),"Not Found")) | AF7: Restructure content for a faq featured snippet: use a direct answer block, scannable list, or FAQ schema as appropriate for “Smoke title 16”. | AG7: Prioritised because of search intent: Informational + 5 open content/SEO issue(s). | AH7: 0 | AJ7: 0 | AK7: 0
A8: =IF(B8>=85,"Complete","Needs Copy") | B8: =MIN(100,ROUND(0.30*(IF(L8="",0,IF(LEFT(L8,7)="MISSING",0,IF(ISNUMBER(SEARCH("OK",L8)),100,IF(ISNUMBER(SEARCH("SHORT",L8)),65,IF(ISNUMBER(SEARCH("LONG",L8)),50,70))))))+0.25*(IF(N8="",0,IF(LEFT(N8,7)="MISSING",0,IF(ISNUMBER(SEARCH("OK",N8)),100,IF(ISNUMBER(SEARCH("SHORT",N8)),65,IF(ISNUMBER(SEARCH("LONG",N8)),50,70))))))+0.20*(IF(P8="",0,IF(LEFT(P8,2)="OK",100,0)))+0.08*(IF(R8="",0,IF(LEFT(R8,2)="OK",100,0)))+0.06*(IF(T8="",0,IF(LEFT(T8,2)="OK",100,0)))+0.05*(IF(V8="",0,IF(LEFT(V8,2)="OK",100,0)))+0.03*(IF(X8="",0,IF(LEFT(X8,2)="OK",100,0)))+0.03*(IF(Z8="",0,IF(LEFT(Z8,2)="OK",100,0))),0)) | C8: =IFERROR(INDEX(OFFSET('Main'!$A$1,2,MATCH("SEO Score",'Main'!$2:$2,0)-1,99998,1),MATCH(TRIM(I8),OFFSET('Main'!$A$1,2,MATCH("URL",'Main'!$2:$2,0)-1,99998,1),0)),"") | D8: =IFERROR(INDEX(OFFSET('Main'!$A$1,2,MATCH("Technical Health",'Main'!$2:$2,0)-1,99998,1),MATCH(TRIM(I8),OFFSET('Main'!$A$1,2,MATCH("URL",'Main'!$2:$2,0)-1,99998,1),0)),"") | E8: =IFERROR(INDEX(OFFSET('Main'!$A$1,2,MATCH("Copy Score",'Main'!$2:$2,0)-1,99998,1),MATCH(TRIM(I8),OFFSET('Main'!$A$1,2,MATCH("URL",'Main'!$2:$2,0)-1,99998,1),0)),"") | F8: To Do | G8: Copy Writer | H8: =HYPERLINK("https://africanmarketingconfederation.org/smoke-archive/page-18","Page 18") | I8: =HYPERLINK("https://africanmarketingconfederation.org/smoke-archive/page-18","https://africanmarketingconfederation.org/smoke-archive/page-18") | J8: page-18 | K8: Smoke title 18 | L8: =IF(K8="","MISSING",IF(AND(LEN(K8)>=50,LEN(K8)<=60),"OK 50-60 chars",IF(LEN(K8)<50,"SHORT: "&LEN(K8),"LONG: "&LEN(K8)))) | M8: Smoke meta description for page 18. | N8: =IF(M8="","MISSING",IF(AND(LEN(M8)>=120,LEN(M8)<=160),"OK 120-160 chars",IF(LEN(M8)<120,"SHORT: "&LEN(M8),"LONG: "&LEN(M8)))) | O8: Smoke heading | P8: OK | R8: =IF(ISBLANK(Q8),"MISSING","OK") | T8: =IF(ISBLANK(S8),"MISSING","OK") | V8: =IF(ISBLANK(U8),"MISSING","OK") | X8: =IF(ISBLANK(W8),"MISSING","OK") | Z8: =IF(ISBLANK(Y8),"MISSING","OK") | AC8: Missing OG image | AE8: =IFERROR(HYPERLINK("#'Main'!B"&MATCH(TRIM(I8),'Main'!B:B,0),"Open in Main"),IFERROR(HYPERLINK("#'Technical Diagnostics'!A"&MATCH(TRIM(I8),'Technical Diagnostics'!A:A,0),"Open in Technical"),"Not Found")) | AF8: Add a concise 40–60 word answer paragraph directly under a question-style heading to improve AEO extractability for: Smoke title 18. | AG8: Prioritised because of missing answer paragraphs + search intent: Informational + 10 open content/SEO issue(s). | AH8: 0 | AJ8: 0 | AK8: 0
A9: =IF(B9>=85,"Complete","Needs Copy") | B9: =MIN(100,ROUND(0.30*(IF(L9="",0,IF(LEFT(L9,7)="MISSING",0,IF(ISNUMBER(SEARCH("OK",L9)),100,IF(ISNUMBER(SEARCH("SHORT",L9)),65,IF(ISNUMBER(SEARCH("LONG",L9)),50,70))))))+0.25*(IF(N9="",0,IF(LEFT(N9,7)="MISSING",0,IF(ISNUMBER(SEARCH("OK",N9)),100,IF(ISNUMBER(SEARCH("SHORT",N9)),65,IF(ISNUMBER(SEARCH("LONG",N9)),50,70))))))+0.20*(IF(P9="",0,IF(LEFT(P9,2)="OK",100,0)))+0.08*(IF(R9="",0,IF(LEFT(R9,2)="OK",100,0)))+0.06*(IF(T9="",0,IF(LEFT(T9,2)="OK",100,0)))+0.05*(IF(V9="",0,IF(LEFT(V9,2)="OK",100,0)))+0.03*(IF(X9="",0,IF(LEFT(X9,2)="OK",100,0)))+0.03*(IF(Z9="",0,IF(LEFT(Z9,2)="OK",100,0))),0)) | C9: =IFERROR(INDEX(OFFSET('Main'!$A$1,2,MATCH("SEO Score",'Main'!$2:$2,0)-1,99998,1),MATCH(TRIM(I9),OFFSET('Main'!$A$1,2,MATCH("URL",'Main'!$2:$2,0)-1,99998,1),0)),"") | D9: =IFERROR(INDEX(OFFSET('Main'!$A$1,2,MATCH("Technical Health",'Main'!$2:$2,0)-1,99998,1),MATCH(TRIM(I9),OFFSET('Main'!$A$1,2,MATCH("URL",'Main'!$2:$2,0)-1,99998,1),0)),"") | E9: =IFERROR(INDEX(OFFSET('Main'!$A$1,2,MATCH("Copy Score",'Main'!$2:$2,0)-1,99998,1),MATCH(TRIM(I9),OFFSET('Main'!$A$1,2,MATCH("URL",'Main'!$2:$2,0)-1,99998,1),0)),"") | F9: To Do | G9: Copy Writer | H9: =HYPERLINK("https://africanmarketingconfederation.org/smoke-archive/page-20","Page 20") | I9: =HYPERLINK("https://africanmarketingconfederation.org/smoke-archive/page-20","https://africanmarketingconfederation.org/smoke-archive/page-20") | J9: page-20 | K9: Smoke title 20 | L9: =IF(K9="","MISSING",IF(AND(LEN(K9)>=50,LEN(K9)<=60),"OK 50-60 chars",IF(LEN(K9)<50,"SHORT: "&LEN(K9),"LONG: "&LEN(K9)))) | M9: MISSING DESCRIPTION | N9: =IF(M9="","MISSING",IF(AND(LEN(M9)>=120,LEN(M9)<=160),"OK 120-160 chars",IF(LEN(M9)<120,"SHORT: "&LEN(M9),"LONG: "&LEN(M9)))) | O9: Smoke heading | P9: OK | R9: =IF(ISBLANK(Q9),"MISSING","OK") | T9: =IF(ISBLANK(S9),"MISSING","OK") | V9: =IF(ISBLANK(U9),"MISSING","OK") | X9: =IF(ISBLANK(W9),"MISSING","OK") | Z9: =IF(ISBLANK(Y9),"MISSING","OK") | AB9: =HYPERLINK("https://africanmarketingconfederation.org/og-20.jpg","View Image") | AC9: Present — mixed OG images across site | AD9: =IF(LEN("https://africanmarketingconfederation.org/og-20.jpg")>0,IFERROR(_xlfn.IMAGE("https://africanmarketingconfederation.org/og-20.jpg"),"https://africanmarketingconfederation.org/og-20.jpg"),"") | AE9: =IFERROR(HYPERLINK("#'Main'!B"&MATCH(TRIM(I9),'Main'!B:B,0),"Open in Main"),IFERROR(HYPERLINK("#'Technical Diagnostics'!A"&MATCH(TRIM(I9),'Technical Diagnostics'!A:A,0),"Open in Technical"),"Not Found")) | AF9: Add a meta description (currently missing). Aim for 120–155 characters summarising: Smoke title 20. | AG9: Prioritised because of search intent: Informational + 6 open content/SEO issue(s). | AH9: 0 | AJ9: 0 | AK9: 0
A10: =IF(B10>=85,"Complete","Needs Copy") | B10: =MIN(100,ROUND(0.30*(IF(L10="",0,IF(LEFT(L10,7)="MISSING",0,IF(ISNUMBER(SEARCH("OK",L10)),100,IF(ISNUMBER(SEARCH("SHORT",L10)),65,IF(ISNUMBER(SEARCH("LONG",L10)),50,70))))))+0.25*(IF(N10="",0,IF(LEFT(N10,7)="MISSING",0,IF(ISNUMBER(SEARCH("OK",N10)),100,IF(ISNUMBER(SEARCH("SHORT",N10)),65,IF(ISNUMBER(SEARCH("LONG",N10)),50,70))))))+0.20*(IF(P10="",0,IF(LEFT(P10,2)="OK",100,0)))+0.08*(IF(R10="",0,IF(LEFT(R10,2)="OK",100,0)))+0.06*(IF(T10="",0,IF(LEFT(T10,2)="OK",100,0)))+0.05*(IF(V10="",0,IF(LEFT(V10,2)="OK",100,0)))+0.03*(IF(X10="",0,IF(LEFT(X10,2)="OK",100,0)))+0.03*(IF(Z10="",0,IF(LEFT(Z10,2)="OK",100,0))),0)) | C10: =IFERROR(INDEX(OFFSET('Main'!$A$1,2,MATCH("SEO Score",'Main'!$2:$2,0)-1,99998,1),MATCH(TRIM(I10),OFFSET('Main'!$A$1,2,MATCH("URL",'Main'!$2:$2,0)-1,99998,1),0)),"") | D10: =IFERROR(INDEX(OFFSET('Main'!$A$1,2,MATCH("Technical Health",'Main'!$2:$2,0)-1,99998,1),MATCH(TRIM(I10),OFFSET('Main'!$A$1,2,MATCH("URL",'Main'!$2:$2,0)-1,99998,1),0)),"") | E10: =IFERROR(INDEX(OFFSET('Main'!$A$1,2,MATCH("Copy Score",'Main'!$2:$2,0)-1,99998,1),MATCH(TRIM(I10),OFFSET('Main'!$A$1,2,MATCH("URL",'Main'!$2:$2,0)-1,99998,1),0)),"") | F10: To Do | G10: Copy Writer | H10: =HYPERLINK("https://africanmarketingconfederation.org/smoke-archive/page-24","Page 24") | I10: =HYPERLINK("https://africanmarketingconfederation.org/smoke-archive/page-24","https://africanmarketingconfederation.org/smoke-archive/page-24") | J10: page-24 | K10: Smoke title 24 | L10: =IF(K10="","MISSING",IF(AND(LEN(K10)>=50,LEN(K10)<=60),"OK 50-60 chars",IF(LEN(K10)<50,"SHORT: "&LEN(K10),"LONG: "&LEN(K10)))) | M10: Smoke meta description for page 24. | N10: =IF(M10="","MISSING",IF(AND(LEN(M10)>=120,LEN(M10)<=160),"OK 120-160 chars",IF(LEN(M10)<120,"SHORT: "&LEN(M10),"LONG: "&LEN(M10)))) | O10: Smoke heading | P10: OK | R10: =IF(ISBLANK(Q10),"MISSING","OK") | T10: =IF(ISBLANK(S10),"MISSING","OK") | V10: =IF(ISBLANK(U10),"MISSING","OK") | X10: =IF(ISBLANK(W10),"MISSING","OK") | Z10: =IF(ISBLANK(Y10),"MISSING","OK") | AB10: =HYPERLINK("https://africanmarketingconfederation.org/og-24.jpg","View Image") | AC10: Present — mixed OG images across site | AD10: =IF(LEN("https://africanmarketingconfederation.org/og-24.jpg")>0,IFERROR(_xlfn.IMAGE("https://africanmarketingconfederation.org/og-24.jpg"),"https://africanmarketingconfederation.org/og-24.jpg"),"") | AE10: =IFERROR(HYPERLINK("#'Main'!B"&MATCH(TRIM(I10),'Main'!B:B,0),"Open in Main"),IFERROR(HYPERLINK("#'Technical Diagnostics'!A"&MATCH(TRIM(I10),'Technical Diagnostics'!A:A,0),"Open in Technical"),"Not Found")) | AF10: Restructure content for a faq featured snippet: use a direct answer block, scannable list, or FAQ schema as appropriate for “Smoke title 24”. | AG10: Prioritised because of search intent: Informational + 7 open content/SEO issue(s). | AH10: 0 | AJ10: 0 | AK10: 0
A11: =IF(B11>=85,"Complete","Needs Copy") | B11: =MIN(100,ROUND(0.30*(IF(L11="",0,IF(LEFT(L11,7)="MISSING",0,IF(ISNUMBER(SEARCH("OK",L11)),100,IF(ISNUMBER(SEARCH("SHORT",L11)),65,IF(ISNUMBER(SEARCH("LONG",L11)),50,70))))))+0.25*(IF(N11="",0,IF(LEFT(N11,7)="MISSING",0,IF(ISNUMBER(SEARCH("OK",N11)),100,IF(ISNUMBER(SEARCH("SHORT",N11)),65,IF(ISNUMBER(SEARCH("LONG",N11)),50,70))))))+0.20*(IF(P11="",0,IF(LEFT(P11,2)="OK",100,0)))+0.08*(IF(R11="",0,IF(LEFT(R11,2)="OK",100,0)))+0.06*(IF(T11="",0,IF(LEFT(T11,2)="OK",100,0)))+0.05*(IF(V11="",0,IF(LEFT(V11,2)="OK",100,0)))+0.03*(IF(X11="",0,IF(LEFT(X11,2)="OK",100,0)))+0.03*(IF(Z11="",0,IF(LEFT(Z11,2)="OK",100,0))),0)) | C11: =IFERROR(INDEX(OFFSET('Main'!$A$1,2,MATCH("SEO Score",'Main'!$2:$2,0)-1,99998,1),MATCH(TRIM(I11),OFFSET('Main'!$A$1,2,MATCH("URL",'Main'!$2:$2,0)-1,99998,1),0)),"") | D11: =IFERROR(INDEX(OFFSET('Main'!$A$1,2,MATCH("Technical Health",'Main'!$2:$2,0)-1,99998,1),MATCH(TRIM(I11),OFFSET('Main'!$A$1,2,MATCH("URL",'Main'!$2:$2,0)-1,99998,1),0)),"") | E11: =IFERROR(INDEX(OFFSET('Main'!$A$1,2,MATCH("Copy Score",'Main'!$2:$2,0)-1,99998,1),MATCH(TRIM(I11),OFFSET('Main'!$A$1,2,MATCH("URL",'Main'!$2:$2,0)-1,99998,1),0)),"") | F11: To Do | G11: Copy Writer | H11: =HYPERLINK("https://africanmarketingconfederation.org/smoke-archive/page-25","Page 25") | I11: =HYPERLINK("https://africanmarketingconfederation.org/smoke-archive/page-25","https://africanmarketingconfederation.org/smoke-archive/page-25") | J11: page-25 | K11: Smoke title 25 | L11: =IF(K11="","MISSING",IF(AND(LEN(K11)>=50,LEN(K11)<=60),"OK 50-60 chars",IF(LEN(K11)<50,"SHORT: "&LEN(K11),"LONG: "&LEN(K11)))) | M11: MISSING DESCRIPTION | N11: =IF(M11="","MISSING",IF(AND(LEN(M11)>=120,LEN(M11)<=160),"OK 120-160 chars",IF(LEN(M11)<120,"SHORT: "&LEN(M11),"LONG: "&LEN(M11)))) | O11: Smoke heading | P11: OK | R11: =IF(ISBLANK(Q11),"MISSING","OK") | T11: =IF(ISBLANK(S11),"MISSING","OK") | V11: =IF(ISBLANK(U11),"MISSING","OK") | X11: =IF(ISBLANK(W11),"MISSING","OK") | Z11: =IF(ISBLANK(Y11),"MISSING","OK") | AC11: Missing OG image | AE11: =IFERROR(HYPERLINK("#'Main'!B"&MATCH(TRIM(I11),'Main'!B:B,0),"Open in Main"),IFERROR(HYPERLINK("#'Technical Diagnostics'!A"&MATCH(TRIM(I11),'Technical Diagnostics'!A:A,0),"Open in Technical"),"Not Found")) | AF11: Add a meta description (currently missing). Aim for 120–155 characters summarising: Smoke title 25. | AG11: Prioritised because of search intent: Informational + 7 open content/SEO issue(s). | AH11: 0 | AJ11: 0 | AK11: 0
A12: =IF(B12>=85,"Complete","Needs Copy") | B12: =MIN(100,ROUND(0.30*(IF(L12="",0,IF(LEFT(L12,7)="MISSING",0,IF(ISNUMBER(SEARCH("OK",L12)),100,IF(ISNUMBER(SEARCH("SHORT",L12)),65,IF(ISNUMBER(SEARCH("LONG",L12)),50,70))))))+0.25*(IF(N12="",0,IF(LEFT(N12,7)="MISSING",0,IF(ISNUMBER(SEARCH("OK",N12)),100,IF(ISNUMBER(SEARCH("SHORT",N12)),65,IF(ISNUMBER(SEARCH("LONG",N12)),50,70))))))+0.20*(IF(P12="",0,IF(LEFT(P12,2)="OK",100,0)))+0.08*(IF(R12="",0,IF(LEFT(R12,2)="OK",100,0)))+0.06*(IF(T12="",0,IF(LEFT(T12,2)="OK",100,0)))+0.05*(IF(V12="",0,IF(LEFT(V12,2)="OK",100,0)))+0.03*(IF(X12="",0,IF(LEFT(X12,2)="OK",100,0)))+0.03*(IF(Z12="",0,IF(LEFT(Z12,2)="OK",100,0))),0)) | C12: =IFERROR(INDEX(OFFSET('Main'!$A$1,2,MATCH("SEO Score",'Main'!$2:$2,0)-1,99998,1),MATCH(TRIM(I12),OFFSET('Main'!$A$1,2,MATCH("URL",'Main'!$2:$2,0)-1,99998,1),0)),"") | D12: =IFERROR(INDEX(OFFSET('Main'!$A$1,2,MATCH("Technical Health",'Main'!$2:$2,0)-1,99998,1),MATCH(TRIM(I12),OFFSET('Main'!$A$1,2,MATCH("URL",'Main'!$2:$2,0)-1,99998,1),0)),"") | E12: =IFERROR(INDEX(OFFSET('Main'!$A$1,2,MATCH("Copy Score",'Main'!$2:$2,0)-1,99998,1),MATCH(TRIM(I12),OFFSET('Main'!$A$1,2,MATCH("URL",'Main'!$2:$2,0)-1,99998,1),0)),"") | F12: To Do | G12: Copy Writer | H12: =HYPERLINK("https://africanmarketingconfederation.org/smoke-archive/page-27","Page 27") | I12: =HYPERLINK("https://africanmarketingconfederation.org/smoke-archive/page-27","https://africanmarketingconfederation.org/smoke-archive/page-27") | J12: page-27 | K12: Smoke title 27 | L12: =IF(K12="","MISSING",IF(AND(LEN(K12)>=50,LEN(K12)<=60),"OK 50-60 chars",IF(LEN(K12)<50,"SHORT: "&LEN(K12),"LONG: "&LEN(K12)))) | M12: Smoke meta description for page 27. | N12: =IF(M12="","MISSING",IF(AND(LEN(M12)>=120,LEN(M12)<=160),"OK 120-160 chars",IF(LEN(M12)<120,"SHORT: "&LEN(M12),"LONG: "&LEN(M12)))) | O12: Smoke heading | P12: OK | R12: =IF(ISBLANK(Q12),"MISSING","OK") | T12: =IF(ISBLANK(S12),"MISSING","OK") | V12: =IF(ISBLANK(U12),"MISSING","OK") | X12: =IF(ISBLANK(W12),"MISSING","OK") | Z12: =IF(ISBLANK(Y12),"MISSING","OK") | AC12: Missing OG image | AE12: =IFERROR(HYPERLINK("#'Main'!B"&MATCH(TRIM(I12),'Main'!B:B,0),"Open in Main"),IFERROR(HYPERLINK("#'Technical Diagnostics'!A"&MATCH(TRIM(I12),'Technical Diagnostics'!A:A,0),"Open in Technical"),"Not Found")) | AF12: Add a concise 40–60 word answer paragraph directly under a question-style heading to improve AEO extractability for: Smoke title 27. | AG12: Prioritised because of missing answer paragraphs + search intent: Informational + 9 open content/SEO issue(s). | AH12: 0 | AJ12: 0 | AK12: 0
A13: =IF(B13>=85,"Complete","Needs Copy") | B13: =MIN(100,ROUND(0.30*(IF(L13="",0,IF(LEFT(L13,7)="MISSING",0,IF(ISNUMBER(SEARCH("OK",L13)),100,IF(ISNUMBER(SEARCH("SHORT",L13)),65,IF(ISNUMBER(SEARCH("LONG",L13)),50,70))))))+0.25*(IF(N13="",0,IF(LEFT(N13,7)="MISSING",0,IF(ISNUMBER(SEARCH("OK",N13)),100,IF(ISNUMBER(SEARCH("SHORT",N13)),65,IF(ISNUMBER(SEARCH("LONG",N13)),50,70))))))+0.20*(IF(P13="",0,IF(LEFT(P13,2)="OK",100,0)))+0.08*(IF(R13="",0,IF(LEFT(R13,2)="OK",100,0)))+0.06*(IF(T13="",0,IF(LEFT(T13,2)="OK",100,0)))+0.05*(IF(V13="",0,IF(LEFT(V13,2)="OK",100,0)))+0.03*(IF(X13="",0,IF(LEFT(X13,2)="OK",100,0)))+0.03*(IF(Z13="",0,IF(LEFT(Z13,2)="OK",100,0))),0)) | C13: =IFERROR(INDEX(OFFSET('Main'!$A$1,2,MATCH("SEO Score",'Main'!$2:$2,0)-1,99998,1),MATCH(TRIM(I13),OFFSET('Main'!$A$1,2,MATCH("URL",'Main'!$2:$2,0)-1,99998,1),0)),"") | D13: =IFERROR(INDEX(OFFSET('Main'!$A$1,2,MATCH("Technical Health",'Main'!$2:$2,0)-1,99998,1),MATCH(TRIM(I13),OFFSET('Main'!$A$1,2,MATCH("URL",'Main'!$2:$2,0)-1,99998,1),0)),"") | E13: =IFERROR(INDEX(OFFSET('Main'!$A$1,2,MATCH("Copy Score",'Main'!$2:$2,0)-1,99998,1),MATCH(TRIM(I13),OFFSET('Main'!$A$1,2,MATCH("URL",'Main'!$2:$2,0)-1,99998,1),0)),"") | F13: To Do | G13: Copy Writer | H13: =HYPERLINK("https://africanmarketingconfederation.org/smoke-archive/page-30","Page 30") | I13: =HYPERLINK("https://africanmarketingconfederation.org/smoke-archive/page-30","https://africanmarketingconfederation.org/smoke-archive/page-30") | J13: page-30 | K13: Smoke title 30 | L13: =IF(K13="","MISSING",IF(AND(LEN(K13)>=50,LEN(K13)<=60),"OK 50-60 chars",IF(LEN(K13)<50,"SHORT: "&LEN(K13),"LONG: "&LEN(K13)))) | M13: MISSING DESCRIPTION | N13: =IF(M13="","MISSING",IF(AND(LEN(M13)>=120,LEN(M13)<=160),"OK 120-160 chars",IF(LEN(M13)<120,"SHORT: "&LEN(M13),"LONG: "&LEN(M13)))) | O13: Smoke heading | P13: OK | R13: =IF(ISBLANK(Q13),"MISSING","OK") | T13: =IF(ISBLANK(S13),"MISSING","OK") | V13: =IF(ISBLANK(U13),"MISSING","OK") | X13: =IF(ISBLANK(W13),"MISSING","OK") | Z13: =IF(ISBLANK(Y13),"MISSING","OK") | AC13: Missing OG image | AE13: =IFERROR(HYPERLINK("#'Main'!B"&MATCH(TRIM(I13),'Main'!B:B,0),"Open in Main"),IFERROR(HYPERLINK("#'Technical Diagnostics'!A"&MATCH(TRIM(I13),'Technical Diagnostics'!A:A,0),"Open in Technical"),"Not Found")) | AF13: Add a meta description (currently missing). Aim for 120–155 characters summarising: Smoke title 30. | AG13: Prioritised because of search intent: Informational + 8 open content/SEO issue(s). | AH13: 0 | AJ13: 0 | AK13: 0
A14: =IF(B14>=85,"Complete","Needs Copy") | B14: =MIN(100,ROUND(0.30*(IF(L14="",0,IF(LEFT(L14,7)="MISSING",0,IF(ISNUMBER(SEARCH("OK",L14)),100,IF(ISNUMBER(SEARCH("SHORT",L14)),65,IF(ISNUMBER(SEARCH("LONG",L14)),50,70))))))+0.25*(IF(N14="",0,IF(LEFT(N14,7)="MISSING",0,IF(ISNUMBER(SEARCH("OK",N14)),100,IF(ISNUMBER(SEARCH("SHORT",N14)),65,IF(ISNUMBER(SEARCH("LONG",N14)),50,70))))))+0.20*(IF(P14="",0,IF(LEFT(P14,2)="OK",100,0)))+0.08*(IF(R14="",0,IF(LEFT(R14,2)="OK",100,0)))+0.06*(IF(T14="",0,IF(LEFT(T14,2)="OK",100,0)))+0.05*(IF(V14="",0,IF(LEFT(V14,2)="OK",100,0)))+0.03*(IF(X14="",0,IF(LEFT(X14,2)="OK",100,0)))+0.03*(IF(Z14="",0,IF(LEFT(Z14,2)="OK",100,0))),0)) | C14: =IFERROR(INDEX(OFFSET('Main'!$A$1,2,MATCH("SEO Score",'Main'!$2:$2,0)-1,99998,1),MATCH(TRIM(I14),OFFSET('Main'!$A$1,2,MATCH("URL",'Main'!$2:$2,0)-1,99998,1),0)),"") | D14: =IFERROR(INDEX(OFFSET('Main'!$A$1,2,MATCH("Technical Health",'Main'!$2:$2,0)-1,99998,1),MATCH(TRIM(I14),OFFSET('Main'!$A$1,2,MATCH("URL",'Main'!$2:$2,0)-1,99998,1),0)),"") | E14: =IFERROR(INDEX(OFFSET('Main'!$A$1,2,MATCH("Copy Score",'Main'!$2:$2,0)-1,99998,1),MATCH(TRIM(I14),OFFSET('Main'!$A$1,2,MATCH("URL",'Main'!$2:$2,0)-1,99998,1),0)),"") | F14: To Do | G14: Copy Writer | H14: =HYPERLINK("https://africanmarketingconfederation.org/smoke-archive/page-32","Page 32") | I14: =HYPERLINK("https://africanmarketingconfederation.org/smoke-archive/page-32","https://africanmarketingconfederation.org/smoke-archive/page-32") | J14: page-32 | K14: Smoke title 32 | L14: =IF(K14="","MISSING",IF(AND(LEN(K14)>=50,LEN(K14)<=60),"OK 50-60 chars",IF(LEN(K14)<50,"SHORT: "&LEN(K14),"LONG: "&LEN(K14)))) | M14: Smoke meta description for page 32. | N14: =IF(M14="","MISSING",IF(AND(LEN(M14)>=120,LEN(M14)<=160),"OK 120-160 chars",IF(LEN(M14)<120,"SHORT: "&LEN(M14),"LONG: "&LEN(M14)))) | O14: Smoke heading | P14: OK | R14: =IF(ISBLANK(Q14),"MISSING","OK") | T14: =IF(ISBLANK(S14),"MISSING","OK") | V14: =IF(ISBLANK(U14),"MISSING","OK") | X14: =IF(ISBLANK(W14),"MISSING","OK") | Z14: =IF(ISBLANK(Y14),"MISSING","OK") | AB14: =HYPERLINK("https://africanmarketingconfederation.org/og-32.jpg","View Image") | AC14: Present — mixed OG images across site | AD14: =IF(LEN("https://africanmarketingconfederation.org/og-32.jpg")>0,IFERROR(_xlfn.IMAGE("https://africanmarketingconfederation.org/og-32.jpg"),"https://africanmarketingconfederation.org/og-32.jpg"),"") | AE14: =IFERROR(HYPERLINK("#'Main'!B"&MATCH(TRIM(I14),'Main'!B:B,0),"Open in Main"),IFERROR(HYPERLINK("#'Technical Diagnostics'!A"&MATCH(TRIM(I14),'Technical Diagnostics'!A:A,0),"Open in Technical"),"Not Found")) | AF14: Restructure content for a faq featured snippet: use a direct answer block, scannable list, or FAQ schema as appropriate for “Smoke title 32”. | AG14: Prioritised because of search intent: Informational + 5 open content/SEO issue(s). | AH14: 0 | AJ14: 0 | AK14: 0
A15: =IF(B15>=85,"Complete","Needs Copy") | B15: =MIN(100,ROUND(0.30*(IF(L15="",0,IF(LEFT(L15,7)="MISSING",0,IF(ISNUMBER(SEARCH("OK",L15)),100,IF(ISNUMBER(SEARCH("SHORT",L15)),65,IF(ISNUMBER(SEARCH("LONG",L15)),50,70))))))+0.25*(IF(N15="",0,IF(LEFT(N15,7)="MISSING",0,IF(ISNUMBER(SEARCH("OK",N15)),100,IF(ISNUMBER(SEARCH("SHORT",N15)),65,IF(ISNUMBER(SEARCH("LONG",N15)),50,70))))))+0.20*(IF(P15="",0,IF(LEFT(P15,2)="OK",100,0)))+0.08*(IF(R15="",0,IF(LEFT(R15,2)="OK",100,0)))+0.06*(IF(T15="",0,IF(LEFT(T15,2)="OK",100,0)))+0.05*(IF(V15="",0,IF(LEFT(V15,2)="OK",100,0)))+0.03*(IF(X15="",0,IF(LEFT(X15,2)="OK",100,0)))+0.03*(IF(Z15="",0,IF(LEFT(Z15,2)="OK",100,0))),0)) | C15: =IFERROR(INDEX(OFFSET('Main'!$A$1,2,MATCH("SEO Score",'Main'!$2:$2,0)-1,99998,1),MATCH(TRIM(I15),OFFSET('Main'!$A$1,2,MATCH("URL",'Main'!$2:$2,0)-1,99998,1),0)),"") | D15: =IFERROR(INDEX(OFFSET('Main'!$A$1,2,MATCH("Technical Health",'Main'!$2:$2,0)-1,99998,1),MATCH(TRIM(I15),OFFSET('Main'!$A$1,2,MATCH("URL",'Main'!$2:$2,0)-1,99998,1),0)),"") | E15: =IFERROR(INDEX(OFFSET('Main'!$A$1,2,MATCH("Copy Score",'Main'!$2:$2,0)-1,99998,1),MATCH(TRIM(I15),OFFSET('Main'!$A$1,2,MATCH("URL",'Main'!$2:$2,0)-1,99998,1),0)),"") | F15: To Do | G15: Copy Writer | H15: =HYPERLINK("https://africanmarketingconfederation.org/smoke-archive/page-35","Page 35") | I15: =HYPERLINK("https://africanmarketingconfederation.org/smoke-archive/page-35","https://africanmarketingconfederation.org/smoke-archive/page-35") | J15: page-35 | K15: Smoke title 35 | L15: =IF(K15="","MISSING",IF(AND(LEN(K15)>=50,LEN(K15)<=60),"OK 50-60 chars",IF(LEN(K15)<50,"SHORT: "&LEN(K15),"LONG: "&LEN(K15)))) | M15: MISSING DESCRIPTION | N15: =IF(M15="","MISSING",IF(AND(LEN(M15)>=120,LEN(M15)<=160),"OK 120-160 chars",IF(LEN(M15)<120,"SHORT: "&LEN(M15),"LONG: "&LEN(M15)))) | O15: Smoke heading | P15: OK | R15: =IF(ISBLANK(Q15),"MISSING","OK") | T15: =IF(ISBLANK(S15),"MISSING","OK") | V15: =IF(ISBLANK(U15),"MISSING","OK") | X15: =IF(ISBLANK(W15),"MISSING","OK") | Z15: =IF(ISBLANK(Y15),"MISSING","OK") | AC15: Missing OG image | AE15: =IFERROR(HYPERLINK("#'Main'!B"&MATCH(TRIM(I15),'Main'!B:B,0),"Open in Main"),IFERROR(HYPERLINK("#'Technical Diagnostics'!A"&MATCH(TRIM(I15),'Technical Diagnostics'!A:A,0),"Open in Technical"),"Not Found")) | AF15: Add a meta description (currently missing). Aim for 120–155 characters summarising: Smoke title 35. | AG15: Prioritised because of search intent: Informational + 9 open content/SEO issue(s). | AH15: 0 | AJ15: 0 | AK15: 0
A16: =IF(B16>=85,"Complete","Needs Copy") | B16: =MIN(100,ROUND(0.30*(IF(L16="",0,IF(LEFT(L16,7)="MISSING",0,IF(ISNUMBER(SEARCH("OK",L16)),100,IF(ISNUMBER(SEARCH("SHORT",L16)),65,IF(ISNUMBER(SEARCH("LONG",L16)),50,70))))))+0.25*(IF(N16="",0,IF(LEFT(N16,7)="MISSING",0,IF(ISNUMBER(SEARCH("OK",N16)),100,IF(ISNUMBER(SEARCH("SHORT",N16)),65,IF(ISNUMBER(SEARCH("LONG",N16)),50,70))))))+0.20*(IF(P16="",0,IF(LEFT(P16,2)="OK",100,0)))+0.08*(IF(R16="",0,IF(LEFT(R16,2)="OK",100,0)))+0.06*(IF(T16="",0,IF(LEFT(T16,2)="OK",100,0)))+0.05*(IF(V16="",0,IF(LEFT(V16,2)="OK",100,0)))+0.03*(IF(X16="",0,IF(LEFT(X16,2)="OK",100,0)))+0.03*(IF(Z16="",0,IF(LEFT(Z16,2)="OK",100,0))),0)) | C16: =IFERROR(INDEX(OFFSET('Main'!$A$1,2,MATCH("SEO Score",'Main'!$2:$2,0)-1,99998,1),MATCH(TRIM(I16),OFFSET('Main'!$A$1,2,MATCH("URL",'Main'!$2:$2,0)-1,99998,1),0)),"") | D16: =IFERROR(INDEX(OFFSET('Main'!$A$1,2,MATCH("Technical Health",'Main'!$2:$2,0)-1,99998,1),MATCH(TRIM(I16),OFFSET('Main'!$A$1,2,MATCH("URL",'Main'!$2:$2,0)-1,99998,1),0)),"") | E16: =IFERROR(INDEX(OFFSET('Main'!$A$1,2,MATCH("Copy Score",'Main'!$2:$2,0)-1,99998,1),MATCH(TRIM(I16),OFFSET('Main'!$A$1,2,MATCH("URL",'Main'!$2:$2,0)-1,99998,1),0)),"") | F16: To Do | G16: Copy Writer | H16: =HYPERLINK("https://africanmarketingconfederation.org/smoke-archive/page-36","Page 36") | I16: =HYPERLINK("https://africanmarketingconfederation.org/smoke-archive/page-36","https://africanmarketingconfederation.org/smoke-archive/page-36") | J16: page-36 | K16: Smoke title 36 | L16: =IF(K16="","MISSING",IF(AND(LEN(K16)>=50,LEN(K16)<=60),"OK 50-60 chars",IF(LEN(K16)<50,"SHORT: "&LEN(K16),"LONG: "&LEN(K16)))) | M16: Smoke meta description for page 36. | N16: =IF(M16="","MISSING",IF(AND(LEN(M16)>=120,LEN(M16)<=160),"OK 120-160 chars",IF(LEN(M16)<120,"SHORT: "&LEN(M16),"LONG: "&LEN(M16)))) | O16: Smoke heading | P16: OK | R16: =IF(ISBLANK(Q16),"MISSING","OK") | T16: =IF(ISBLANK(S16),"MISSING","OK") | V16: =IF(ISBLANK(U16),"MISSING","OK") | X16: =IF(ISBLANK(W16),"MISSING","OK") | Z16: =IF(ISBLANK(Y16),"MISSING","OK") | AB16: =HYPERLINK("https://africanmarketingconfederation.org/og-36.jpg","View Image") | AC16: Present — mixed OG images across site | AD16: =IF(LEN("https://africanmarketingconfederation.org/og-36.jpg")>0,IFERROR(_xlfn.IMAGE("https://africanmarketingconfederation.org/og-36.jpg"),"https://africanmarketingconfederation.org/og-36.jpg"),"") | AE16: =IFERROR(HYPERLINK("#'Main'!B"&MATCH(TRIM(I16),'Main'!B:B,0),"Open in Main"),IFERROR(HYPERLINK("#'Technical Diagnostics'!A"&MATCH(TRIM(I16),'Technical Diagnostics'!A:A,0),"Open in Technical"),"Not Found")) | AF16: Add a concise 40–60 word answer paragraph directly under a question-style heading to improve AEO extractability for: Smoke title 36. | AG16: Prioritised because of missing answer paragraphs + search intent: Informational + 10 open content/SEO issue(s). | AH16: 0 | AJ16: 0 | AK16: 0
A17: =IF(B17>=85,"Complete","Needs Copy") | B17: =MIN(100,ROUND(0.30*(IF(L17="",0,IF(LEFT(L17,7)="MISSING",0,IF(ISNUMBER(SEARCH("OK",L17)),100,IF(ISNUMBER(SEARCH("SHORT",L17)),65,IF(ISNUMBER(SEARCH("LONG",L17)),50,70))))))+0.25*(IF(N17="",0,IF(LEFT(N17,7)="MISSING",0,IF(ISNUMBER(SEARCH("OK",N17)),100,IF(ISNUMBER(SEARCH("SHORT",N17)),65,IF(ISNUMBER(SEARCH("LONG",N17)),50,70))))))+0.20*(IF(P17="",0,IF(LEFT(P17,2)="OK",100,0)))+0.08*(IF(R17="",0,IF(LEFT(R17,2)="OK",100,0)))+0.06*(IF(T17="",0,IF(LEFT(T17,2)="OK",100,0)))+0.05*(IF(V17="",0,IF(LEFT(V17,2)="OK",100,0)))+0.03*(IF(X17="",0,IF(LEFT(X17,2)="OK",100,0)))+0.03*(IF(Z17="",0,IF(LEFT(Z17,2)="OK",100,0))),0)) | C17: =IFERROR(INDEX(OFFSET('Main'!$A$1,2,MATCH("SEO Score",'Main'!$2:$2,0)-1,99998,1),MATCH(TRIM(I17),OFFSET('Main'!$A$1,2,MATCH("URL",'Main'!$2:$2,0)-1,99998,1),0)),"") | D17: =IFERROR(INDEX(OFFSET('Main'!$A$1,2,MATCH("Technical Health",'Main'!$2:$2,0)-1,99998,1),MATCH(TRIM(I17),OFFSET('Main'!$A$1,2,MATCH("URL",'Main'!$2:$2,0)-1,99998,1),0)),"") | E17: =IFERROR(INDEX(OFFSET('Main'!$A$1,2,MATCH("Copy Score",'Main'!$2:$2,0)-1,99998,1),MATCH(TRIM(I17),OFFSET('Main'!$A$1,2,MATCH("URL",'Main'!$2:$2,0)-1,99998,1),0)),"") | F17: To Do | G17: Copy Writer | H17: =HYPERLINK("https://africanmarketingconfederation.org/smoke-archive/page-40","Page 40") | I17: =HYPERLINK("https://africanmarketingconfederation.org/smoke-archive/page-40","https://africanmarketingconfederation.org/smoke-archive/page-40") | J17: page-40 | K17: Smoke title 40 | L17: =IF(K17="","MISSING",IF(AND(LEN(K17)>=50,LEN(K17)<=60),"OK 50-60 chars",IF(LEN(K17)<50,"SHORT: "&LEN(K17),"LONG: "&LEN(K17)))) | M17: MISSING DESCRIPTION | N17: =IF(M17="","MISSING",IF(AND(LEN(M17)>=120,LEN(M17)<=160),"OK 120-160 chars",IF(LEN(M17)<120,"SHORT: "&LEN(M17),"LONG: "&LEN(M17)))) | O17: Smoke heading | P17: OK | R17: =IF(ISBLANK(Q17),"MISSING","OK") | T17: =IF(ISBLANK(S17),"MISSING","OK") | V17: =IF(ISBLANK(U17),"MISSING","OK") | X17: =IF(ISBLANK(W17),"MISSING","OK") | Z17: =IF(ISBLANK(Y17),"MISSING","OK") | AB17: =HYPERLINK("https://africanmarketingconfederation.org/og-40.jpg","View Image") | AC17: Present — mixed OG images across site | AD17: =IF(LEN("https://africanmarketingconfederation.org/og-40.jpg")>0,IFERROR(_xlfn.IMAGE("https://africanmarketingconfederation.org/og-40.jpg"),"https://africanmarketingconfederation.org/og-40.jpg"),"") | AE17: =IFERROR(HYPERLINK("#'Main'!B"&MATCH(TRIM(I17),'Main'!B:B,0),"Open in Main"),IFERROR(HYPERLINK("#'Technical Diagnostics'!A"&MATCH(TRIM(I17),'Technical Diagnostics'!A:A,0),"Open in Technical"),"Not Found")) | AF17: Add a meta description (currently missing). Aim for 120–155 characters summarising: Smoke title 40. | AG17: Prioritised because of search intent: Informational + 7 open content/SEO issue(s). | AH17: 0 | AJ17: 0 | AK17: 0
A18: =IF(B18>=85,"Complete","Needs Copy") | B18: =MIN(100,ROUND(0.30*(IF(L18="",0,IF(LEFT(L18,7)="MISSING",0,IF(ISNUMBER(SEARCH("OK",L18)),100,IF(ISNUMBER(SEARCH("SHORT",L18)),65,IF(ISNUMBER(SEARCH("LONG",L18)),50,70))))))+0.25*(IF(N18="",0,IF(LEFT(N18,7)="MISSING",0,IF(ISNUMBER(SEARCH("OK",N18)),100,IF(ISNUMBER(SEARCH("SHORT",N18)),65,IF(ISNUMBER(SEARCH("LONG",N18)),50,70))))))+0.20*(IF(P18="",0,IF(LEFT(P18,2)="OK",100,0)))+0.08*(IF(R18="",0,IF(LEFT(R18,2)="OK",100,0)))+0.06*(IF(T18="",0,IF(LEFT(T18,2)="OK",100,0)))+0.05*(IF(V18="",0,IF(LEFT(V18,2)="OK",100,0)))+0.03*(IF(X18="",0,IF(LEFT(X18,2)="OK",100,0)))+0.03*(IF(Z18="",0,IF(LEFT(Z18,2)="OK",100,0))),0)) | C18: =IFERROR(INDEX(OFFSET('Main'!$A$1,2,MATCH("SEO Score",'Main'!$2:$2,0)-1,99998,1),MATCH(TRIM(I18),OFFSET('Main'!$A$1,2,MATCH("URL",'Main'!$2:$2,0)-1,99998,1),0)),"") | D18: =IFERROR(INDEX(OFFSET('Main'!$A$1,2,MATCH("Technical Health",'Main'!$2:$2,0)-1,99998,1),MATCH(TRIM(I18),OFFSET('Main'!$A$1,2,MATCH("URL",'Main'!$2:$2,0)-1,99998,1),0)),"") | E18: =IFERROR(INDEX(OFFSET('Main'!$A$1,2,MATCH("Copy Score",'Main'!$2:$2,0)-1,99998,1),MATCH(TRIM(I18),OFFSET('Main'!$A$1,2,MATCH("URL",'Main'!$2:$2,0)-1,99998,1),0)),"") | F18: To Do | G18: Copy Writer | H18: =HYPERLINK("https://africanmarketingconfederation.org/smoke-archive/page-42","Page 42") | I18: =HYPERLINK("https://africanmarketingconfederation.org/smoke-archive/page-42","https://africanmarketingconfederation.org/smoke-archive/page-42") | J18: page-42 | K18: Smoke title 42 | L18: =IF(K18="","MISSING",IF(AND(LEN(K18)>=50,LEN(K18)<=60),"OK 50-60 chars",IF(LEN(K18)<50,"SHORT: "&LEN(K18),"LONG: "&LEN(K18)))) | M18: Smoke meta description for page 42. | N18: =IF(M18="","MISSING",IF(AND(LEN(M18)>=120,LEN(M18)<=160),"OK 120-160 chars",IF(LEN(M18)<120,"SHORT: "&LEN(M18),"LONG: "&LEN(M18)))) | O18: Smoke heading | P18: OK | R18: =IF(ISBLANK(Q18),"MISSING","OK") | T18: =IF(ISBLANK(S18),"MISSING","OK") | V18: =IF(ISBLANK(U18),"MISSING","OK") | X18: =IF(ISBLANK(W18),"MISSING","OK") | Z18: =IF(ISBLANK(Y18),"MISSING","OK") | AC18: Missing OG image | AE18: =IFERROR(HYPERLINK("#'Main'!B"&MATCH(TRIM(I18),'Main'!B:B,0),"Open in Main"),IFERROR(HYPERLINK("#'Technical Diagnostics'!A"&MATCH(TRIM(I18),'Technical Diagnostics'!A:A,0),"Open in Technical"),"Not Found")) | AF18: Restructure content for a faq featured snippet: use a direct answer block, scannable list, or FAQ schema as appropriate for “Smoke title 42”. | AG18: Prioritised because of search intent: Informational + 8 open content/SEO issue(s). | AH18: 0 | AJ18: 0 | AK18: 0
A19: =IF(B19>=85,"Complete","Needs Copy") | B19: =MIN(100,ROUND(0.30*(IF(L19="",0,IF(LEFT(L19,7)="MISSING",0,IF(ISNUMBER(SEARCH("OK",L19)),100,IF(ISNUMBER(SEARCH("SHORT",L19)),65,IF(ISNUMBER(SEARCH("LONG",L19)),50,70))))))+0.25*(IF(N19="",0,IF(LEFT(N19,7)="MISSING",0,IF(ISNUMBER(SEARCH("OK",N19)),100,IF(ISNUMBER(SEARCH("SHORT",N19)),65,IF(ISNUMBER(SEARCH("LONG",N19)),50,70))))))+0.20*(IF(P19="",0,IF(LEFT(P19,2)="OK",100,0)))+0.08*(IF(R19="",0,IF(LEFT(R19,2)="OK",100,0)))+0.06*(IF(T19="",0,IF(LEFT(T19,2)="OK",100,0)))+0.05*(IF(V19="",0,IF(LEFT(V19,2)="OK",100,0)))+0.03*(IF(X19="",0,IF(LEFT(X19,2)="OK",100,0)))+0.03*(IF(Z19="",0,IF(LEFT(Z19,2)="OK",100,0))),0)) | C19: =IFERROR(INDEX(OFFSET('Main'!$A$1,2,MATCH("SEO Score",'Main'!$2:$2,0)-1,99998,1),MATCH(TRIM(I19),OFFSET('Main'!$A$1,2,MATCH("URL",'Main'!$2:$2,0)-1,99998,1),0)),"") | D19: =IFERROR(INDEX(OFFSET('Main'!$A$1,2,MATCH("Technical Health",'Main'!$2:$2,0)-1,99998,1),MATCH(TRIM(I19),OFFSET('Main'!$A$1,2,MATCH("URL",'Main'!$2:$2,0)-1,99998,1),0)),"") | E19: =IFERROR(INDEX(OFFSET('Main'!$A$1,2,MATCH("Copy Score",'Main'!$2:$2,0)-1,99998,1),MATCH(TRIM(I19),OFFSET('Main'!$A$1,2,MATCH("URL",'Main'!$2:$2,0)-1,99998,1),0)),"") | F19: To Do | G19: Copy Writer | H19: =HYPERLINK("https://africanmarketingconfederation.org/smoke-archive/page-45","Page 45") | I19: =HYPERLINK("https://africanmarketingconfederation.org/smoke-archive/page-45","https://africanmarketingconfederation.org/smoke-archive/page-45") | J19: page-45 | K19: Smoke title 45 | L19: =IF(K19="","MISSING",IF(AND(LEN(K19)>=50,LEN(K19)<=60),"OK 50-60 chars",IF(LEN(K19)<50,"SHORT: "&LEN(K19),"LONG: "&LEN(K19)))) | M19: MISSING DESCRIPTION | N19: =IF(M19="","MISSING",IF(AND(LEN(M19)>=120,LEN(M19)<=160),"OK 120-160 chars",IF(LEN(M19)<120,"SHORT: "&LEN(M19),"LONG: "&LEN(M19)))) | O19: Smoke heading | P19: OK | R19: =IF(ISBLANK(Q19),"MISSING","OK") | T19: =IF(ISBLANK(S19),"MISSING","OK") | V19: =IF(ISBLANK(U19),"MISSING","OK") | X19: =IF(ISBLANK(W19),"MISSING","OK") | Z19: =IF(ISBLANK(Y19),"MISSING","OK") | AC19: Missing OG image | AE19: =IFERROR(HYPERLINK("#'Main'!B"&MATCH(TRIM(I19),'Main'!B:B,0),"Open in Main"),IFERROR(HYPERLINK("#'Technical Diagnostics'!A"&MATCH(TRIM(I19),'Technical Diagnostics'!A:A,0),"Open in Technical"),"Not Found")) | AF19: Add a meta description (currently missing). Aim for 120–155 characters summarising: Smoke title 45. | AG19: Prioritised because of missing answer paragraphs + search intent: Informational + 11 open content/SEO issue(s). | AH19: 0 | AJ19: 0 | AK19: 0
A20: =IF(B20>=85,"Complete","Needs Copy") | B20: =MIN(100,ROUND(0.30*(IF(L20="",0,IF(LEFT(L20,7)="MISSING",0,IF(ISNUMBER(SEARCH("OK",L20)),100,IF(ISNUMBER(SEARCH("SHORT",L20)),65,IF(ISNUMBER(SEARCH("LONG",L20)),50,70))))))+0.25*(IF(N20="",0,IF(LEFT(N20,7)="MISSING",0,IF(ISNUMBER(SEARCH("OK",N20)),100,IF(ISNUMBER(SEARCH("SHORT",N20)),65,IF(ISNUMBER(SEARCH("LONG",N20)),50,70))))))+0.20*(IF(P20="",0,IF(LEFT(P20,2)="OK",100,0)))+0.08*(IF(R20="",0,IF(LEFT(R20,2)="OK",100,0)))+0.06*(IF(T20="",0,IF(LEFT(T20,2)="OK",100,0)))+0.05*(IF(V20="",0,IF(LEFT(V20,2)="OK",100,0)))+0.03*(IF(X20="",0,IF(LEFT(X20,2)="OK",100,0)))+0.03*(IF(Z20="",0,IF(LEFT(Z20,2)="OK",100,0))),0)) | C20: =IFERROR(INDEX(OFFSET('Main'!$A$1,2,MATCH("SEO Score",'Main'!$2:$2,0)-1,99998,1),MATCH(TRIM(I20),OFFSET('Main'!$A$1,2,MATCH("URL",'Main'!$2:$2,0)-1,99998,1),0)),"") | D20: =IFERROR(INDEX(OFFSET('Main'!$A$1,2,MATCH("Technical Health",'Main'!$2:$2,0)-1,99998,1),MATCH(TRIM(I20),OFFSET('Main'!$A$1,2,MATCH("URL",'Main'!$2:$2,0)-1,99998,1),0)),"") | E20: =IFERROR(INDEX(OFFSET('Main'!$A$1,2,MATCH("Copy Score",'Main'!$2:$2,0)-1,99998,1),MATCH(TRIM(I20),OFFSET('Main'!$A$1,2,MATCH("URL",'Main'!$2:$2,0)-1,99998,1),0)),"") | F20: To Do | G20: Copy Writer | H20: =HYPERLINK("https://africanmarketingconfederation.org/smoke-archive/page-48","Page 48") | I20: =HYPERLINK("https://africanmarketingconfederation.org/smoke-archive/page-48","https://africanmarketingconfederation.org/smoke-archive/page-48") | J20: page-48 | K20: Smoke title 48 | L20: =IF(K20="","MISSING",IF(AND(LEN(K20)>=50,LEN(K20)<=60),"OK 50-60 chars",IF(LEN(K20)<50,"SHORT: "&LEN(K20),"LONG: "&LEN(K20)))) | M20: Smoke meta description for page 48. | N20: =IF(M20="","MISSING",IF(AND(LEN(M20)>=120,LEN(M20)<=160),"OK 120-160 chars",IF(LEN(M20)<120,"SHORT: "&LEN(M20),"LONG: "&LEN(M20)))) | O20: Smoke heading | P20: OK | R20: =IF(ISBLANK(Q20),"MISSING","OK") | T20: =IF(ISBLANK(S20),"MISSING","OK") | V20: =IF(ISBLANK(U20),"MISSING","OK") | X20: =IF(ISBLANK(W20),"MISSING","OK") | Z20: =IF(ISBLANK(Y20),"MISSING","OK") | AB20: =HYPERLINK("https://africanmarketingconfederation.org/og-48.jpg","View Image") | AC20: Present — mixed OG images across site | AD20: =IF(LEN("https://africanmarketingconfederation.org/og-48.jpg")>0,IFERROR(_xlfn.IMAGE("https://africanmarketingconfederation.org/og-48.jpg"),"https://africanmarketingconfederation.org/og-48.jpg"),"") | AE20: =IFERROR(HYPERLINK("#'Main'!B"&MATCH(TRIM(I20),'Main'!B:B,0),"Open in Main"),IFERROR(HYPERLINK("#'Technical Diagnostics'!A"&MATCH(TRIM(I20),'Technical Diagnostics'!A:A,0),"Open in Technical"),"Not Found")) | AF20: Restructure content for a faq featured snippet: use a direct answer block, scannable list, or FAQ schema as appropriate for “Smoke title 48”. | AG20: Prioritised because of search intent: Informational + 7 open content/SEO issue(s). | AH20: 0 | AJ20: 0 | AK20: 0
A21: =IF(B21>=85,"Complete","Needs Copy") | B21: =MIN(100,ROUND(0.30*(IF(L21="",0,IF(LEFT(L21,7)="MISSING",0,IF(ISNUMBER(SEARCH("OK",L21)),100,IF(ISNUMBER(SEARCH("SHORT",L21)),65,IF(ISNUMBER(SEARCH("LONG",L21)),50,70))))))+0.25*(IF(N21="",0,IF(LEFT(N21,7)="MISSING",0,IF(ISNUMBER(SEARCH("OK",N21)),100,IF(ISNUMBER(SEARCH("SHORT",N21)),65,IF(ISNUMBER(SEARCH("LONG",N21)),50,70))))))+0.20*(IF(P21="",0,IF(LEFT(P21,2)="OK",100,0)))+0.08*(IF(R21="",0,IF(LEFT(R21,2)="OK",100,0)))+0.06*(IF(T21="",0,IF(LEFT(T21,2)="OK",100,0)))+0.05*(IF(V21="",0,IF(LEFT(V21,2)="OK",100,0)))+0.03*(IF(X21="",0,IF(LEFT(X21,2)="OK",100,0)))+0.03*(IF(Z21="",0,IF(LEFT(Z21,2)="OK",100,0))),0)) | C21: =IFERROR(INDEX(OFFSET('Main'!$A$1,2,MATCH("SEO Score",'Main'!$2:$2,0)-1,99998,1),MATCH(TRIM(I21),OFFSET('Main'!$A$1,2,MATCH("URL",'Main'!$2:$2,0)-1,99998,1),0)),"") | D21: =IFERROR(INDEX(OFFSET('Main'!$A$1,2,MATCH("Technical Health",'Main'!$2:$2,0)-1,99998,1),MATCH(TRIM(I21),OFFSET('Main'!$A$1,2,MATCH("URL",'Main'!$2:$2,0)-1,99998,1),0)),"") | E21: =IFERROR(INDEX(OFFSET('Main'!$A$1,2,MATCH("Copy Score",'Main'!$2:$2,0)-1,99998,1),MATCH(TRIM(I21),OFFSET('Main'!$A$1,2,MATCH("URL",'Main'!$2:$2,0)-1,99998,1),0)),"") | F21: To Do | G21: Copy Writer | H21: =HYPERLINK("https://africanmarketingconfederation.org/smoke-archive/page-5","Page 5") | I21: =HYPERLINK("https://africanmarketingconfederation.org/smoke-archive/page-5","https://africanmarketingconfederation.org/smoke-archive/page-5") | J21: page-5 | K21: Smoke title 5 | L21: =IF(K21="","MISSING",IF(AND(LEN(K21)>=50,LEN(K21)<=60),"OK 50-60 chars",IF(LEN(K21)<50,"SHORT: "&LEN(K21),"LONG: "&LEN(K21)))) | M21: MISSING DESCRIPTION | N21: =IF(M21="","MISSING",IF(AND(LEN(M21)>=120,LEN(M21)<=160),"OK 120-160 chars",IF(LEN(M21)<120,"SHORT: "&LEN(M21),"LONG: "&LEN(M21)))) | O21: Smoke heading | P21: OK | R21: =IF(ISBLANK(Q21),"MISSING","OK") | T21: =IF(ISBLANK(S21),"MISSING","OK") | V21: =IF(ISBLANK(U21),"MISSING","OK") | X21: =IF(ISBLANK(W21),"MISSING","OK") | Z21: =IF(ISBLANK(Y21),"MISSING","OK") | AC21: Missing OG image | AE21: =IFERROR(HYPERLINK("#'Main'!B"&MATCH(TRIM(I21),'Main'!B:B,0),"Open in Main"),IFERROR(HYPERLINK("#'Technical Diagnostics'!A"&MATCH(TRIM(I21),'Technical Diagnostics'!A:A,0),"Open in Technical"),"Not Found")) | AF21: Add a meta description (currently missing). Aim for 120–155 characters summarising: Smoke title 5. | AG21: Prioritised because of search intent: Informational + 7 open content/SEO issue(s). | AH21: 0 | AJ21: 0 | AK21: 0
A22: =IF(B22>=85,"Complete","Needs Copy") | B22: =MIN(100,ROUND(0.30*(IF(L22="",0,IF(LEFT(L22,7)="MISSING",0,IF(ISNUMBER(SEARCH("OK",L22)),100,IF(ISNUMBER(SEARCH("SHORT",L22)),65,IF(ISNUMBER(SEARCH("LONG",L22)),50,70))))))+0.25*(IF(N22="",0,IF(LEFT(N22,7)="MISSING",0,IF(ISNUMBER(SEARCH("OK",N22)),100,IF(ISNUMBER(SEARCH("SHORT",N22)),65,IF(ISNUMBER(SEARCH("LONG",N22)),50,70))))))+0.20*(IF(P22="",0,IF(LEFT(P22,2)="OK",100,0)))+0.08*(IF(R22="",0,IF(LEFT(R22,2)="OK",100,0)))+0.06*(IF(T22="",0,IF(LEFT(T22,2)="OK",100,0)))+0.05*(IF(V22="",0,IF(LEFT(V22,2)="OK",100,0)))+0.03*(IF(X22="",0,IF(LEFT(X22,2)="OK",100,0)))+0.03*(IF(Z22="",0,IF(LEFT(Z22,2)="OK",100,0))),0)) | C22: =IFERROR(INDEX(OFFSET('Main'!$A$1,2,MATCH("SEO Score",'Main'!$2:$2,0)-1,99998,1),MATCH(TRIM(I22),OFFSET('Main'!$A$1,2,MATCH("URL",'Main'!$2:$2,0)-1,99998,1),0)),"") | D22: =IFERROR(INDEX(OFFSET('Main'!$A$1,2,MATCH("Technical Health",'Main'!$2:$2,0)-1,99998,1),MATCH(TRIM(I22),OFFSET('Main'!$A$1,2,MATCH("URL",'Main'!$2:$2,0)-1,99998,1),0)),"") | E22: =IFERROR(INDEX(OFFSET('Main'!$A$1,2,MATCH("Copy Score",'Main'!$2:$2,0)-1,99998,1),MATCH(TRIM(I22),OFFSET('Main'!$A$1,2,MATCH("URL",'Main'!$2:$2,0)-1,99998,1),0)),"") | F22: To Do | G22: Copy Writer | H22: =HYPERLINK("https://africanmarketingconfederation.org/smoke-archive/page-50","Page 50") | I22: =HYPERLINK("https://africanmarketingconfederation.org/smoke-archive/page-50","https://africanmarketingconfederation.org/smoke-archive/page-50") | J22: page-50 | K22: Smoke title 50 | L22: =IF(K22="","MISSING",IF(AND(LEN(K22)>=50,LEN(K22)<=60),"OK 50-60 chars",IF(LEN(K22)<50,"SHORT: "&LEN(K22),"LONG: "&LEN(K22)))) | M22: MISSING DESCRIPTION | N22: =IF(M22="","MISSING",IF(AND(LEN(M22)>=120,LEN(M22)<=160),"OK 120-160 chars",IF(LEN(M22)<120,"SHORT: "&LEN(M22),"LONG: "&LEN(M22)))) | O22: Smoke heading | P22: OK | R22: =IF(ISBLANK(Q22),"MISSING","OK") | T22: =IF(ISBLANK(S22),"MISSING","OK") | V22: =IF(ISBLANK(U22),"MISSING","OK") | X22: =IF(ISBLANK(W22),"MISSING","OK") | Z22: =IF(ISBLANK(Y22),"MISSING","OK") | AC22: Missing OG image | AE22: =IFERROR(HYPERLINK("#'Main'!B"&MATCH(TRIM(I22),'Main'!B:B,0),"Open in Main"),IFERROR(HYPERLINK("#'Technical Diagnostics'!A"&MATCH(TRIM(I22),'Technical Diagnostics'!A:A,0),"Open in Technical"),"Not Found")) | AF22: Add a meta description (currently missing). Aim for 120–155 characters summarising: Smoke title 50. | AG22: Prioritised because of search intent: Informational + 7 open content/SEO issue(s). | AH22: 0 | AJ22: 0 | AK22: 0
A23: =IF(B23>=85,"Complete","Needs Copy") | B23: =MIN(100,ROUND(0.30*(IF(L23="",0,IF(LEFT(L23,7)="MISSING",0,IF(ISNUMBER(SEARCH("OK",L23)),100,IF(ISNUMBER(SEARCH("SHORT",L23)),65,IF(ISNUMBER(SEARCH("LONG",L23)),50,70))))))+0.25*(IF(N23="",0,IF(LEFT(N23,7)="MISSING",0,IF(ISNUMBER(SEARCH("OK",N23)),100,IF(ISNUMBER(SEARCH("SHORT",N23)),65,IF(ISNUMBER(SEARCH("LONG",N23)),50,70))))))+0.20*(IF(P23="",0,IF(LEFT(P23,2)="OK",100,0)))+0.08*(IF(R23="",0,IF(LEFT(R23,2)="OK",100,0)))+0.06*(IF(T23="",0,IF(LEFT(T23,2)="OK",100,0)))+0.05*(IF(V23="",0,IF(LEFT(V23,2)="OK",100,0)))+0.03*(IF(X23="",0,IF(LEFT(X23,2)="OK",100,0)))+0.03*(IF(Z23="",0,IF(LEFT(Z23,2)="OK",100,0))),0)) | C23: =IFERROR(INDEX(OFFSET('Main'!$A$1,2,MATCH("SEO Score",'Main'!$2:$2,0)-1,99998,1),MATCH(TRIM(I23),OFFSET('Main'!$A$1,2,MATCH("URL",'Main'!$2:$2,0)-1,99998,1),0)),"") | D23: =IFERROR(INDEX(OFFSET('Main'!$A$1,2,MATCH("Technical Health",'Main'!$2:$2,0)-1,99998,1),MATCH(TRIM(I23),OFFSET('Main'!$A$1,2,MATCH("URL",'Main'!$2:$2,0)-1,99998,1),0)),"") | E23: =IFERROR(INDEX(OFFSET('Main'!$A$1,2,MATCH("Copy Score",'Main'!$2:$2,0)-1,99998,1),MATCH(TRIM(I23),OFFSET('Main'!$A$1,2,MATCH("URL",'Main'!$2:$2,0)-1,99998,1),0)),"") | F23: To Do | G23: Copy Writer | H23: =HYPERLINK("https://africanmarketingconfederation.org/smoke-archive/page-54","Page 54") | I23: =HYPERLINK("https://africanmarketingconfederation.org/smoke-archive/page-54","https://africanmarketingconfederation.org/smoke-archive/page-54") | J23: page-54 | K23: Smoke title 54 | L23: =IF(K23="","MISSING",IF(AND(LEN(K23)>=50,LEN(K23)<=60),"OK 50-60 chars",IF(LEN(K23)<50,"SHORT: "&LEN(K23),"LONG: "&LEN(K23)))) | M23: Smoke meta description for page 54. | N23: =IF(M23="","MISSING",IF(AND(LEN(M23)>=120,LEN(M23)<=160),"OK 120-160 chars",IF(LEN(M23)<120,"SHORT: "&LEN(M23),"LONG: "&LEN(M23)))) | O23: Smoke heading | P23: OK | R23: =IF(ISBLANK(Q23),"MISSING","OK") | T23: =IF(ISBLANK(S23),"MISSING","OK") | V23: =IF(ISBLANK(U23),"MISSING","OK") | X23: =IF(ISBLANK(W23),"MISSING","OK") | Z23: =IF(ISBLANK(Y23),"MISSING","OK") | AC23: Missing OG image | AE23: =IFERROR(HYPERLINK("#'Main'!B"&MATCH(TRIM(I23),'Main'!B:B,0),"Open in Main"),IFERROR(HYPERLINK("#'Technical Diagnostics'!A"&MATCH(TRIM(I23),'Technical Diagnostics'!A:A,0),"Open in Technical"),"Not Found")) | AF23: Add a concise 40–60 word answer paragraph directly under a question-style heading to improve AEO extractability for: Smoke title 54. | AG23: Prioritised because of missing answer paragraphs + search intent: Informational + 10 open content/SEO issue(s). | AH23: 0 | AJ23: 0 | AK23: 0
A24: =IF(B24>=85,"Complete","Needs Copy") | B24: =MIN(100,ROUND(0.30*(IF(L24="",0,IF(LEFT(L24,7)="MISSING",0,IF(ISNUMBER(SEARCH("OK",L24)),100,IF(ISNUMBER(SEARCH("SHORT",L24)),65,IF(ISNUMBER(SEARCH("LONG",L24)),50,70))))))+0.25*(IF(N24="",0,IF(LEFT(N24,7)="MISSING",0,IF(ISNUMBER(SEARCH("OK",N24)),100,IF(ISNUMBER(SEARCH("SHORT",N24)),65,IF(ISNUMBER(SEARCH("LONG",N24)),50,70))))))+0.20*(IF(P24="",0,IF(LEFT(P24,2)="OK",100,0)))+0.08*(IF(R24="",0,IF(LEFT(R24,2)="OK",100,0)))+0.06*(IF(T24="",0,IF(LEFT(T24,2)="OK",100,0)))+0.05*(IF(V24="",0,IF(LEFT(V24,2)="OK",100,0)))+0.03*(IF(X24="",0,IF(LEFT(X24,2)="OK",100,0)))+0.03*(IF(Z24="",0,IF(LEFT(Z24,2)="OK",100,0))),0)) | C24: =IFERROR(INDEX(OFFSET('Main'!$A$1,2,MATCH("SEO Score",'Main'!$2:$2,0)-1,99998,1),MATCH(TRIM(I24),OFFSET('Main'!$A$1,2,MATCH("URL",'Main'!$2:$2,0)-1,99998,1),0)),"") | D24: =IFERROR(INDEX(OFFSET('Main'!$A$1,2,MATCH("Technical Health",'Main'!$2:$2,0)-1,99998,1),MATCH(TRIM(I24),OFFSET('Main'!$A$1,2,MATCH("URL",'Main'!$2:$2,0)-1,99998,1),0)),"") | E24: =IFERROR(INDEX(OFFSET('Main'!$A$1,2,MATCH("Copy Score",'Main'!$2:$2,0)-1,99998,1),MATCH(TRIM(I24),OFFSET('Main'!$A$1,2,MATCH("URL",'Main'!$2:$2,0)-1,99998,1),0)),"") | F24: To Do | G24: Copy Writer | H24: =HYPERLINK("https://africanmarketingconfederation.org/smoke-archive/page-55","Page 55") | I24: =HYPERLINK("https://africanmarketingconfederation.org/smoke-archive/page-55","https://africanmarketingconfederation.org/smoke-archive/page-55") | J24: page-55 | K24: Smoke title 55 | L24: =IF(K24="","MISSING",IF(AND(LEN(K24)>=50,LEN(K24)<=60),"OK 50-60 chars",IF(LEN(K24)<50,"SHORT: "&LEN(K24),"LONG: "&LEN(K24)))) | M24: MISSING DESCRIPTION | N24: =IF(M24="","MISSING",IF(AND(LEN(M24)>=120,LEN(M24)<=160),"OK 120-160 chars",IF(LEN(M24)<120,"SHORT: "&LEN(M24),"LONG: "&LEN(M24)))) | O24: Smoke heading | P24: OK | R24: =IF(ISBLANK(Q24),"MISSING","OK") | T24: =IF(ISBLANK(S24),"MISSING","OK") | V24: =IF(ISBLANK(U24),"MISSING","OK") | X24: =IF(ISBLANK(W24),"MISSING","OK") | Z24: =IF(ISBLANK(Y24),"MISSING","OK") | AC24: Missing OG image | AE24: =IFERROR(HYPERLINK("#'Main'!B"&MATCH(TRIM(I24),'Main'!B:B,0),"Open in Main"),IFERROR(HYPERLINK("#'Technical Diagnostics'!A"&MATCH(TRIM(I24),'Technical Diagnostics'!A:A,0),"Open in Technical"),"Not Found")) | AF24: Add a meta description (currently missing). Aim for 120–155 characters summarising: Smoke title 55. | AG24: Prioritised because of search intent: Informational + 7 open content/SEO issue(s). | AH24: 0 | AJ24: 0 | AK24: 0
A25: =IF(B25>=85,"Complete","Needs Copy") | B25: =MIN(100,ROUND(0.30*(IF(L25="",0,IF(LEFT(L25,7)="MISSING",0,IF(ISNUMBER(SEARCH("OK",L25)),100,IF(ISNUMBER(SEARCH("SHORT",L25)),65,IF(ISNUMBER(SEARCH("LONG",L25)),50,70))))))+0.25*(IF(N25="",0,IF(LEFT(N25,7)="MISSING",0,IF(ISNUMBER(SEARCH("OK",N25)),100,IF(ISNUMBER(SEARCH("SHORT",N25)),65,IF(ISNUMBER(SEARCH("LONG",N25)),50,70))))))+0.20*(IF(P25="",0,IF(LEFT(P25,2)="OK",100,0)))+0.08*(IF(R25="",0,IF(LEFT(R25,2)="OK",100,0)))+0.06*(IF(T25="",0,IF(LEFT(T25,2)="OK",100,0)))+0.05*(IF(V25="",0,IF(LEFT(V25,2)="OK",100,0)))+0.03*(IF(X25="",0,IF(LEFT(X25,2)="OK",100,0)))+0.03*(IF(Z25="",0,IF(LEFT(Z25,2)="OK",100,0))),0)) | C25: =IFERROR(INDEX(OFFSET('Main'!$A$1,2,MATCH("SEO Score",'Main'!$2:$2,0)-1,99998,1),MATCH(TRIM(I25),OFFSET('Main'!$A$1,2,MATCH("URL",'Main'!$2:$2,0)-1,99998,1),0)),"") | D25: =IFERROR(INDEX(OFFSET('Main'!$A$1,2,MATCH("Technical Health",'Main'!$2:$2,0)-1,99998,1),MATCH(TRIM(I25),OFFSET('Main'!$A$1,2,MATCH("URL",'Main'!$2:$2,0)-1,99998,1),0)),"") | E25: =IFERROR(INDEX(OFFSET('Main'!$A$1,2,MATCH("Copy Score",'Main'!$2:$2,0)-1,99998,1),MATCH(TRIM(I25),OFFSET('Main'!$A$1,2,MATCH("URL",'Main'!$2:$2,0)-1,99998,1),0)),"") | F25: To Do | G25: Copy Writer | H25: =HYPERLINK("https://africanmarketingconfederation.org/smoke-archive/page-56","Page 56") | I25: =HYPERLINK("https://africanmarketingconfederation.org/smoke-archive/page-56","https://africanmarketingconfederation.org/smoke-archive/page-56") | J25: page-56 | K25: Smoke title 56 | L25: =IF(K25="","MISSING",IF(AND(LEN(K25)>=50,LEN(K25)<=60),"OK 50-60 chars",IF(LEN(K25)<50,"SHORT: "&LEN(K25),"LONG: "&LEN(K25)))) | M25: Smoke meta description for page 56. | N25: =IF(M25="","MISSING",IF(AND(LEN(M25)>=120,LEN(M25)<=160),"OK 120-160 chars",IF(LEN(M25)<120,"SHORT: "&LEN(M25),"LONG: "&LEN(M25)))) | O25: Smoke heading | P25: OK | R25: =IF(ISBLANK(Q25),"MISSING","OK") | T25: =IF(ISBLANK(S25),"MISSING","OK") | V25: =IF(ISBLANK(U25),"MISSING","OK") | X25: =IF(ISBLANK(W25),"MISSING","OK") | Z25: =IF(ISBLANK(Y25),"MISSING","OK") | AB25: =HYPERLINK("https://africanmarketingconfederation.org/og-56.jpg","View Image") | AC25: Present — mixed OG images across site | AD25: =IF(LEN("https://africanmarketingconfederation.org/og-56.jpg")>0,IFERROR(_xlfn.IMAGE("https://africanmarketingconfederation.org/og-56.jpg"),"https://africanmarketingconfederation.org/og-56.jpg"),"") | AE25: =IFERROR(HYPERLINK("#'Main'!B"&MATCH(TRIM(I25),'Main'!B:B,0),"Open in Main"),IFERROR(HYPERLINK("#'Technical Diagnostics'!A"&MATCH(TRIM(I25),'Technical Diagnostics'!A:A,0),"Open in Technical"),"Not Found")) | AF25: Restructure content for a faq featured snippet: use a direct answer block, scannable list, or FAQ schema as appropriate for “Smoke title 56”. | AG25: Prioritised because of search intent: Informational + 7 open content/SEO issue(s). | AH25: 0 | AJ25: 0 | AK25: 0
A26: =IF(B26>=85,"Complete","Needs Copy") | B26: =MIN(100,ROUND(0.30*(IF(L26="",0,IF(LEFT(L26,7)="MISSING",0,IF(ISNUMBER(SEARCH("OK",L26)),100,IF(ISNUMBER(SEARCH("SHORT",L26)),65,IF(ISNUMBER(SEARCH("LONG",L26)),50,70))))))+0.25*(IF(N26="",0,IF(LEFT(N26,7)="MISSING",0,IF(ISNUMBER(SEARCH("OK",N26)),100,IF(ISNUMBER(SEARCH("SHORT",N26)),65,IF(ISNUMBER(SEARCH("LONG",N26)),50,70))))))+0.20*(IF(P26="",0,IF(LEFT(P26,2)="OK",100,0)))+0.08*(IF(R26="",0,IF(LEFT(R26,2)="OK",100,0)))+0.06*(IF(T26="",0,IF(LEFT(T26,2)="OK",100,0)))+0.05*(IF(V26="",0,IF(LEFT(V26,2)="OK",100,0)))+0.03*(IF(X26="",0,IF(LEFT(X26,2)="OK",100,0)))+0.03*(IF(Z26="",0,IF(LEFT(Z26,2)="OK",100,0))),0)) | C26: =IFERROR(INDEX(OFFSET('Main'!$A$1,2,MATCH("SEO Score",'Main'!$2:$2,0)-1,99998,1),MATCH(TRIM(I26),OFFSET('Main'!$A$1,2,MATCH("URL",'Main'!$2:$2,0)-1,99998,1),0)),"") | D26: =IFERROR(INDEX(OFFSET('Main'!$A$1,2,MATCH("Technical Health",'Main'!$2:$2,0)-1,99998,1),MATCH(TRIM(I26),OFFSET('Main'!$A$1,2,MATCH("URL",'Main'!$2:$2,0)-1,99998,1),0)),"") | E26: =IFERROR(INDEX(OFFSET('Main'!$A$1,2,MATCH("Copy Score",'Main'!$2:$2,0)-1,99998,1),MATCH(TRIM(I26),OFFSET('Main'!$A$1,2,MATCH("URL",'Main'!$2:$2,0)-1,99998,1),0)),"") | F26: To Do | G26: Copy Writer | H26: =HYPERLINK("https://africanmarketingconfederation.org/smoke-archive/page-6","Page 6") | I26: =HYPERLINK("https://africanmarketingconfederation.org/smoke-archive/page-6","https://africanmarketingconfederation.org/smoke-archive/page-6") | J26: page-6 | K26: Smoke title 6 | L26: =IF(K26="","MISSING",IF(AND(LEN(K26)>=50,LEN(K26)<=60),"OK 50-60 chars",IF(LEN(K26)<50,"SHORT: "&LEN(K26),"LONG: "&LEN(K26)))) | M26: Smoke meta description for page 6. | N26: =IF(M26="","MISSING",IF(AND(LEN(M26)>=120,LEN(M26)<=160),"OK 120-160 chars",IF(LEN(M26)<120,"SHORT: "&LEN(M26),"LONG: "&LEN(M26)))) | O26: Smoke heading | P26: OK | R26: =IF(ISBLANK(Q26),"MISSING","OK") | T26: =IF(ISBLANK(S26),"MISSING","OK") | V26: =IF(ISBLANK(U26),"MISSING","OK") | X26: =IF(ISBLANK(W26),"MISSING","OK") | Z26: =IF(ISBLANK(Y26),"MISSING","OK") | AC26: Missing OG image | AE26: =IFERROR(HYPERLINK("#'Main'!B"&MATCH(TRIM(I26),'Main'!B:B,0),"Open in Main"),IFERROR(HYPERLINK("#'Technical Diagnostics'!A"&MATCH(TRIM(I26),'Technical Diagnostics'!A:A,0),"Open in Technical"),"Not Found")) | AF26: Restructure content for a faq featured snippet: use a direct answer block, scannable list, or FAQ schema as appropriate for “Smoke title 6”. | AG26: Prioritised because of search intent: Informational + 6 open content/SEO issue(s). | AH26: 0 | AJ26: 0 | AK26: 0
A27: =IF(B27>=85,"Complete","Needs Copy") | B27: =MIN(100,ROUND(0.30*(IF(L27="",0,IF(LEFT(L27,7)="MISSING",0,IF(ISNUMBER(SEARCH("OK",L27)),100,IF(ISNUMBER(SEARCH("SHORT",L27)),65,IF(ISNUMBER(SEARCH("LONG",L27)),50,70))))))+0.25*(IF(N27="",0,IF(LEFT(N27,7)="MISSING",0,IF(ISNUMBER(SEARCH("OK",N27)),100,IF(ISNUMBER(SEARCH("SHORT",N27)),65,IF(ISNUMBER(SEARCH("LONG",N27)),50,70))))))+0.20*(IF(P27="",0,IF(LEFT(P27,2)="OK",100,0)))+0.08*(IF(R27="",0,IF(LEFT(R27,2)="OK",100,0)))+0.06*(IF(T27="",0,IF(LEFT(T27,2)="OK",100,0)))+0.05*(IF(V27="",0,IF(LEFT(V27,2)="OK",100,0)))+0.03*(IF(X27="",0,IF(LEFT(X27,2)="OK",100,0)))+0.03*(IF(Z27="",0,IF(LEFT(Z27,2)="OK",100,0))),0)) | C27: =IFERROR(INDEX(OFFSET('Main'!$A$1,2,MATCH("SEO Score",'Main'!$2:$2,0)-1,99998,1),MATCH(TRIM(I27),OFFSET('Main'!$A$1,2,MATCH("URL",'Main'!$2:$2,0)-1,99998,1),0)),"") | D27: =IFERROR(INDEX(OFFSET('Main'!$A$1,2,MATCH("Technical Health",'Main'!$2:$2,0)-1,99998,1),MATCH(TRIM(I27),OFFSET('Main'!$A$1,2,MATCH("URL",'Main'!$2:$2,0)-1,99998,1),0)),"") | E27: =IFERROR(INDEX(OFFSET('Main'!$A$1,2,MATCH("Copy Score",'Main'!$2:$2,0)-1,99998,1),MATCH(TRIM(I27),OFFSET('Main'!$A$1,2,MATCH("URL",'Main'!$2:$2,0)-1,99998,1),0)),"") | F27: To Do | G27: Copy Writer | H27: =HYPERLINK("https://africanmarketingconfederation.org/smoke-archive/page-60","Page 60") | I27: =HYPERLINK("https://africanmarketingconfederation.org/smoke-archive/page-60","https://africanmarketingconfederation.org/smoke-archive/page-60") | J27: page-60 | K27: Smoke title 60 | L27: =IF(K27="","MISSING",IF(AND(LEN(K27)>=50,LEN(K27)<=60),"OK 50-60 chars",IF(LEN(K27)<50,"SHORT: "&LEN(K27),"LONG: "&LEN(K27)))) | M27: MISSING DESCRIPTION | N27: =IF(M27="","MISSING",IF(AND(LEN(M27)>=120,LEN(M27)<=160),"OK 120-160 chars",IF(LEN(M27)<120,"SHORT: "&LEN(M27),"LONG: "&LEN(M27)))) | O27: Smoke heading | P27: OK | R27: =IF(ISBLANK(Q27),"MISSING","OK") | T27: =IF(ISBLANK(S27),"MISSING","OK") | V27: =IF(ISBLANK(U27),"MISSING","OK") | X27: =IF(ISBLANK(W27),"MISSING","OK") | Z27: =IF(ISBLANK(Y27),"MISSING","OK") | AB27: =HYPERLINK("https://africanmarketingconfederation.org/og-60.jpg","View Image") | AC27: Present — mixed OG images across site | AD27: =IF(LEN("https://africanmarketingconfederation.org/og-60.jpg")>0,IFERROR(_xlfn.IMAGE("https://africanmarketingconfederation.org/og-60.jpg"),"https://africanmarketingconfederation.org/og-60.jpg"),"") | AE27: =IFERROR(HYPERLINK("#'Main'!B"&MATCH(TRIM(I27),'Main'!B:B,0),"Open in Main"),IFERROR(HYPERLINK("#'Technical Diagnostics'!A"&MATCH(TRIM(I27),'Technical Diagnostics'!A:A,0),"Open in Technical"),"Not Found")) | AF27: Add a meta description (currently missing). Aim for 120–155 characters summarising: Smoke title 60. | AG27: Prioritised because of search intent: Informational + 8 open content/SEO issue(s). | AH27: 0 | AJ27: 0 | AK27: 0
A28: =IF(B28>=85,"Complete","Needs Copy") | B28: =MIN(100,ROUND(0.30*(IF(L28="",0,IF(LEFT(L28,7)="MISSING",0,IF(ISNUMBER(SEARCH("OK",L28)),100,IF(ISNUMBER(SEARCH("SHORT",L28)),65,IF(ISNUMBER(SEARCH("LONG",L28)),50,70))))))+0.25*(IF(N28="",0,IF(LEFT(N28,7)="MISSING",0,IF(ISNUMBER(SEARCH("OK",N28)),100,IF(ISNUMBER(SEARCH("SHORT",N28)),65,IF(ISNUMBER(SEARCH("LONG",N28)),50,70))))))+0.20*(IF(P28="",0,IF(LEFT(P28,2)="OK",100,0)))+0.08*(IF(R28="",0,IF(LEFT(R28,2)="OK",100,0)))+0.06*(IF(T28="",0,IF(LEFT(T28,2)="OK",100,0)))+0.05*(IF(V28="",0,IF(LEFT(V28,2)="OK",100,0)))+0.03*(IF(X28="",0,IF(LEFT(X28,2)="OK",100,0)))+0.03*(IF(Z28="",0,IF(LEFT(Z28,2)="OK",100,0))),0)) | C28: =IFERROR(INDEX(OFFSET('Main'!$A$1,2,MATCH("SEO Score",'Main'!$2:$2,0)-1,99998,1),MATCH(TRIM(I28),OFFSET('Main'!$A$1,2,MATCH("URL",'Main'!$2:$2,0)-1,99998,1),0)),"") | D28: =IFERROR(INDEX(OFFSET('Main'!$A$1,2,MATCH("Technical Health",'Main'!$2:$2,0)-1,99998,1),MATCH(TRIM(I28),OFFSET('Main'!$A$1,2,MATCH("URL",'Main'!$2:$2,0)-1,99998,1),0)),"") | E28: =IFERROR(INDEX(OFFSET('Main'!$A$1,2,MATCH("Copy Score",'Main'!$2:$2,0)-1,99998,1),MATCH(TRIM(I28),OFFSET('Main'!$A$1,2,MATCH("URL",'Main'!$2:$2,0)-1,99998,1),0)),"") | F28: To Do | G28: Copy Writer | H28: =HYPERLINK("https://africanmarketingconfederation.org/smoke-archive/page-63","Page 63") | I28: =HYPERLINK("https://africanmarketingconfederation.org/smoke-archive/page-63","https://africanmarketingconfederation.org/smoke-archive/page-63") | J28: page-63 | K28: Smoke title 63 | L28: =IF(K28="","MISSING",IF(AND(LEN(K28)>=50,LEN(K28)<=60),"OK 50-60 chars",IF(LEN(K28)<50,"SHORT: "&LEN(K28),"LONG: "&LEN(K28)))) | M28: Smoke meta description for page 63. | N28: =IF(M28="","MISSING",IF(AND(LEN(M28)>=120,LEN(M28)<=160),"OK 120-160 chars",IF(LEN(M28)<120,"SHORT: "&LEN(M28),"LONG: "&LEN(M28)))) | O28: Smoke heading | P28: OK | R28: =IF(ISBLANK(Q28),"MISSING","OK") | T28: =IF(ISBLANK(S28),"MISSING","OK") | V28: =IF(ISBLANK(U28),"MISSING","OK") | X28: =IF(ISBLANK(W28),"MISSING","OK") | Z28: =IF(ISBLANK(Y28),"MISSING","OK") | AC28: Missing OG image | AE28: =IFERROR(HYPERLINK("#'Main'!B"&MATCH(TRIM(I28),'Main'!B:B,0),"Open in Main"),IFERROR(HYPERLINK("#'Technical Diagnostics'!A"&MATCH(TRIM(I28),'Technical Diagnostics'!A:A,0),"Open in Technical"),"Not Found")) | AF28: Add a concise 40–60 word answer paragraph directly under a question-style heading to improve AEO extractability for: Smoke title 63. | AG28: Prioritised because of missing answer paragraphs + search intent: Informational + 11 open content/SEO issue(s). | AH28: 0 | AJ28: 0 | AK28: 0
A29: =IF(B29>=85,"Complete","Needs Copy") | B29: =MIN(100,ROUND(0.30*(IF(L29="",0,IF(LEFT(L29,7)="MISSING",0,IF(ISNUMBER(SEARCH("OK",L29)),100,IF(ISNUMBER(SEARCH("SHORT",L29)),65,IF(ISNUMBER(SEARCH("LONG",L29)),50,70))))))+0.25*(IF(N29="",0,IF(LEFT(N29,7)="MISSING",0,IF(ISNUMBER(SEARCH("OK",N29)),100,IF(ISNUMBER(SEARCH("SHORT",N29)),65,IF(ISNUMBER(SEARCH("LONG",N29)),50,70))))))+0.20*(IF(P29="",0,IF(LEFT(P29,2)="OK",100,0)))+0.08*(IF(R29="",0,IF(LEFT(R29,2)="OK",100,0)))+0.06*(IF(T29="",0,IF(LEFT(T29,2)="OK",100,0)))+0.05*(IF(V29="",0,IF(LEFT(V29,2)="OK",100,0)))+0.03*(IF(X29="",0,IF(LEFT(X29,2)="OK",100,0)))+0.03*(IF(Z29="",0,IF(LEFT(Z29,2)="OK",100,0))),0)) | C29: =IFERROR(INDEX(OFFSET('Main'!$A$1,2,MATCH("SEO Score",'Main'!$2:$2,0)-1,99998,1),MATCH(TRIM(I29),OFFSET('Main'!$A$1,2,MATCH("URL",'Main'!$2:$2,0)-1,99998,1),0)),"") | D29: =IFERROR(INDEX(OFFSET('Main'!$A$1,2,MATCH("Technical Health",'Main'!$2:$2,0)-1,99998,1),MATCH(TRIM(I29),OFFSET('Main'!$A$1,2,MATCH("URL",'Main'!$2:$2,0)-1,99998,1),0)),"") | E29: =IFERROR(INDEX(OFFSET('Main'!$A$1,2,MATCH("Copy Score",'Main'!$2:$2,0)-1,99998,1),MATCH(TRIM(I29),OFFSET('Main'!$A$1,2,MATCH("URL",'Main'!$2:$2,0)-1,99998,1),0)),"") | F29: To Do | G29: Copy Writer | H29: =HYPERLINK("https://africanmarketingconfederation.org/smoke-archive/page-64","Page 64") | I29: =HYPERLINK("https://africanmarketingconfederation.org/smoke-archive/page-64","https://africanmarketingconfederation.org/smoke-archive/page-64") | J29: page-64 | K29: Smoke title 64 | L29: =IF(K29="","MISSING",IF(AND(LEN(K29)>=50,LEN(K29)<=60),"OK 50-60 chars",IF(LEN(K29)<50,"SHORT: "&LEN(K29),"LONG: "&LEN(K29)))) | M29: Smoke meta description for page 64. | N29: =IF(M29="","MISSING",IF(AND(LEN(M29)>=120,LEN(M29)<=160),"OK 120-160 chars",IF(LEN(M29)<120,"SHORT: "&LEN(M29),"LONG: "&LEN(M29)))) | O29: Smoke heading | P29: OK | R29: =IF(ISBLANK(Q29),"MISSING","OK") | T29: =IF(ISBLANK(S29),"MISSING","OK") | V29: =IF(ISBLANK(U29),"MISSING","OK") | X29: =IF(ISBLANK(W29),"MISSING","OK") | Z29: =IF(ISBLANK(Y29),"MISSING","OK") | AB29: =HYPERLINK("https://africanmarketingconfederation.org/og-64.jpg","View Image") | AC29: Present — mixed OG images across site | AD29: =IF(LEN("https://africanmarketingconfederation.org/og-64.jpg")>0,IFERROR(_xlfn.IMAGE("https://africanmarketingconfederation.org/og-64.jpg"),"https://africanmarketingconfederation.org/og-64.jpg"),"") | AE29: =IFERROR(HYPERLINK("#'Main'!B"&MATCH(TRIM(I29),'Main'!B:B,0),"Open in Main"),IFERROR(HYPERLINK("#'Technical Diagnostics'!A"&MATCH(TRIM(I29),'Technical Diagnostics'!A:A,0),"Open in Technical"),"Not Found")) | AF29: Restructure content for a faq featured snippet: use a direct answer block, scannable list, or FAQ schema as appropriate for “Smoke title 64”. | AG29: Prioritised because of search intent: Informational + 5 open content/SEO issue(s). | AH29: 0 | AJ29: 0 | AK29: 0
A30: =IF(B30>=85,"Complete","Needs Copy") | B30: =MIN(100,ROUND(0.30*(IF(L30="",0,IF(LEFT(L30,7)="MISSING",0,IF(ISNUMBER(SEARCH("OK",L30)),100,IF(ISNUMBER(SEARCH("SHORT",L30)),65,IF(ISNUMBER(SEARCH("LONG",L30)),50,70))))))+0.25*(IF(N30="",0,IF(LEFT(N30,7)="MISSING",0,IF(ISNUMBER(SEARCH("OK",N30)),100,IF(ISNUMBER(SEARCH("SHORT",N30)),65,IF(ISNUMBER(SEARCH("LONG",N30)),50,70))))))+0.20*(IF(P30="",0,IF(LEFT(P30,2)="OK",100,0)))+0.08*(IF(R30="",0,IF(LEFT(R30,2)="OK",100,0)))+0.06*(IF(T30="",0,IF(LEFT(T30,2)="OK",100,0)))+0.05*(IF(V30="",0,IF(LEFT(V30,2)="OK",100,0)))+0.03*(IF(X30="",0,IF(LEFT(X30,2)="OK",100,0)))+0.03*(IF(Z30="",0,IF(LEFT(Z30,2)="OK",100,0))),0)) | C30: =IFERROR(INDEX(OFFSET('Main'!$A$1,2,MATCH("SEO Score",'Main'!$2:$2,0)-1,99998,1),MATCH(TRIM(I30),OFFSET('Main'!$A$1,2,MATCH("URL",'Main'!$2:$2,0)-1,99998,1),0)),"") | D30: =IFERROR(INDEX(OFFSET('Main'!$A$1,2,MATCH("Technical Health",'Main'!$2:$2,0)-1,99998,1),MATCH(TRIM(I30),OFFSET('Main'!$A$1,2,MATCH("URL",'Main'!$2:$2,0)-1,99998,1),0)),"") | E30: =IFERROR(INDEX(OFFSET('Main'!$A$1,2,MATCH("Copy Score",'Main'!$2:$2,0)-1,99998,1),MATCH(TRIM(I30),OFFSET('Main'!$A$1,2,MATCH("URL",'Main'!$2:$2,0)-1,99998,1),0)),"") | F30: To Do | G30: Copy Writer | H30: =HYPERLINK("https://africanmarketingconfederation.org/smoke-archive/page-66","Page 66") | I30: =HYPERLINK("https://africanmarketingconfederation.org/smoke-archive/page-66","https://africanmarketingconfederation.org/smoke-archive/page-66") | J30: page-66 | K30: Smoke title 66 | L30: =IF(K30="","MISSING",IF(AND(LEN(K30)>=50,LEN(K30)<=60),"OK 50-60 chars",IF(LEN(K30)<50,"SHORT: "&LEN(K30),"LONG: "&LEN(K30)))) | M30: Smoke meta description for page 66. | N30: =IF(M30="","MISSING",IF(AND(LEN(M30)>=120,LEN(M30)<=160),"OK 120-160 chars",IF(LEN(M30)<120,"SHORT: "&LEN(M30),"LONG: "&LEN(M30)))) | O30: Smoke heading | P30: OK | R30: =IF(ISBLANK(Q30),"MISSING","OK") | T30: =IF(ISBLANK(S30),"MISSING","OK") | V30: =IF(ISBLANK(U30),"MISSING","OK") | X30: =IF(ISBLANK(W30),"MISSING","OK") | Z30: =IF(ISBLANK(Y30),"MISSING","OK") | AC30: Missing OG image | AE30: =IFERROR(HYPERLINK("#'Main'!B"&MATCH(TRIM(I30),'Main'!B:B,0),"Open in Main"),IFERROR(HYPERLINK("#'Technical Diagnostics'!A"&MATCH(TRIM(I30),'Technical Diagnostics'!A:A,0),"Open in Technical"),"Not Found")) | AF30: Restructure content for a faq featured snippet: use a direct answer block, scannable list, or FAQ schema as appropriate for “Smoke title 66”. | AG30: Prioritised because of search intent: Informational + 6 open content/SEO issue(s). | AH30: 0 | AJ30: 0 | AK30: 0
A31: =IF(B31>=85,"Complete","Needs Copy") | B31: =MIN(100,ROUND(0.30*(IF(L31="",0,IF(LEFT(L31,7)="MISSING",0,IF(ISNUMBER(SEARCH("OK",L31)),100,IF(ISNUMBER(SEARCH("SHORT",L31)),65,IF(ISNUMBER(SEARCH("LONG",L31)),50,70))))))+0.25*(IF(N31="",0,IF(LEFT(N31,7)="MISSING",0,IF(ISNUMBER(SEARCH("OK",N31)),100,IF(ISNUMBER(SEARCH("SHORT",N31)),65,IF(ISNUMBER(SEARCH("LONG",N31)),50,70))))))+0.20*(IF(P31="",0,IF(LEFT(P31,2)="OK",100,0)))+0.08*(IF(R31="",0,IF(LEFT(R31,2)="OK",100,0)))+0.06*(IF(T31="",0,IF(LEFT(T31,2)="OK",100,0)))+0.05*(IF(V31="",0,IF(LEFT(V31,2)="OK",100,0)))+0.03*(IF(X31="",0,IF(LEFT(X31,2)="OK",100,0)))+0.03*(IF(Z31="",0,IF(LEFT(Z31,2)="OK",100,0))),0)) | C31: =IFERROR(INDEX(OFFSET('Main'!$A$1,2,MATCH("SEO Score",'Main'!$2:$2,0)-1,99998,1),MATCH(TRIM(I31),OFFSET('Main'!$A$1,2,MATCH("URL",'Main'!$2:$2,0)-1,99998,1),0)),"") | D31: =IFERROR(INDEX(OFFSET('Main'!$A$1,2,MATCH("Technical Health",'Main'!$2:$2,0)-1,99998,1),MATCH(TRIM(I31),OFFSET('Main'!$A$1,2,MATCH("URL",'Main'!$2:$2,0)-1,99998,1),0)),"") | E31: =IFERROR(INDEX(OFFSET('Main'!$A$1,2,MATCH("Copy Score",'Main'!$2:$2,0)-1,99998,1),MATCH(TRIM(I31),OFFSET('Main'!$A$1,2,MATCH("URL",'Main'!$2:$2,0)-1,99998,1),0)),"") | F31: To Do | G31: Copy Writer | H31: =HYPERLINK("https://africanmarketingconfederation.org/smoke-archive/page-70","Page 70") | I31: =HYPERLINK("https://africanmarketingconfederation.org/smoke-archive/page-70","https://africanmarketingconfederation.org/smoke-archive/page-70") | J31: page-70 | K31: Smoke title 70 | L31: =IF(K31="","MISSING",IF(AND(LEN(K31)>=50,LEN(K31)<=60),"OK 50-60 chars",IF(LEN(K31)<50,"SHORT: "&LEN(K31),"LONG: "&LEN(K31)))) | M31: MISSING DESCRIPTION | N31: =IF(M31="","MISSING",IF(AND(LEN(M31)>=120,LEN(M31)<=160),"OK 120-160 chars",IF(LEN(M31)<120,"SHORT: "&LEN(M31),"LONG: "&LEN(M31)))) | O31: Smoke heading | P31: OK | R31: =IF(ISBLANK(Q31),"MISSING","OK") | T31: =IF(ISBLANK(S31),"MISSING","OK") | V31: =IF(ISBLANK(U31),"MISSING","OK") | X31: =IF(ISBLANK(W31),"MISSING","OK") | Z31: =IF(ISBLANK(Y31),"MISSING","OK") | AC31: Missing OG image | AE31: =IFERROR(HYPERLINK("#'Main'!B"&MATCH(TRIM(I31),'Main'!B:B,0),"Open in Main"),IFERROR(HYPERLINK("#'Technical Diagnostics'!A"&MATCH(TRIM(I31),'Technical Diagnostics'!A:A,0),"Open in Technical"),"Not Found")) | AF31: Add a meta description (currently missing). Aim for 120–155 characters summarising: Smoke title 70. | AG31: Prioritised because of search intent: Informational + 9 open content/SEO issue(s). | AH31: 0 | AJ31: 0 | AK31: 0
A32: =IF(B32>=85,"Complete","Needs Copy") | B32: =MIN(100,ROUND(0.30*(IF(L32="",0,IF(LEFT(L32,7)="MISSING",0,IF(ISNUMBER(SEARCH("OK",L32)),100,IF(ISNUMBER(SEARCH("SHORT",L32)),65,IF(ISNUMBER(SEARCH("LONG",L32)),50,70))))))+0.25*(IF(N32="",0,IF(LEFT(N32,7)="MISSING",0,IF(ISNUMBER(SEARCH("OK",N32)),100,IF(ISNUMBER(SEARCH("SHORT",N32)),65,IF(ISNUMBER(SEARCH("LONG",N32)),50,70))))))+0.20*(IF(P32="",0,IF(LEFT(P32,2)="OK",100,0)))+0.08*(IF(R32="",0,IF(LEFT(R32,2)="OK",100,0)))+0.06*(IF(T32="",0,IF(LEFT(T32,2)="OK",100,0)))+0.05*(IF(V32="",0,IF(LEFT(V32,2)="OK",100,0)))+0.03*(IF(X32="",0,IF(LEFT(X32,2)="OK",100,0)))+0.03*(IF(Z32="",0,IF(LEFT(Z32,2)="OK",100,0))),0)) | C32: =IFERROR(INDEX(OFFSET('Main'!$A$1,2,MATCH("SEO Score",'Main'!$2:$2,0)-1,99998,1),MATCH(TRIM(I32),OFFSET('Main'!$A$1,2,MATCH("URL",'Main'!$2:$2,0)-1,99998,1),0)),"") | D32: =IFERROR(INDEX(OFFSET('Main'!$A$1,2,MATCH("Technical Health",'Main'!$2:$2,0)-1,99998,1),MATCH(TRIM(I32),OFFSET('Main'!$A$1,2,MATCH("URL",'Main'!$2:$2,0)-1,99998,1),0)),"") | E32: =IFERROR(INDEX(OFFSET('Main'!$A$1,2,MATCH("Copy Score",'Main'!$2:$2,0)-1,99998,1),MATCH(TRIM(I32),OFFSET('Main'!$A$1,2,MATCH("URL",'Main'!$2:$2,0)-1,99998,1),0)),"") | F32: To Do | G32: Copy Writer | H32: =HYPERLINK("https://africanmarketingconfederation.org/smoke-archive/page-72","Page 72") | I32: =HYPERLINK("https://africanmarketingconfederation.org/smoke-archive/page-72","https://africanmarketingconfederation.org/smoke-archive/page-72") | J32: page-72 | K32: Smoke title 72 | L32: =IF(K32="","MISSING",IF(AND(LEN(K32)>=50,LEN(K32)<=60),"OK 50-60 chars",IF(LEN(K32)<50,"SHORT: "&LEN(K32),"LONG: "&LEN(K32)))) | M32: Smoke meta description for page 72. | N32: =IF(M32="","MISSING",IF(AND(LEN(M32)>=120,LEN(M32)<=160),"OK 120-160 chars",IF(LEN(M32)<120,"SHORT: "&LEN(M32),"LONG: "&LEN(M32)))) | O32: Smoke heading | P32: OK | R32: =IF(ISBLANK(Q32),"MISSING","OK") | T32: =IF(ISBLANK(S32),"MISSING","OK") | V32: =IF(ISBLANK(U32),"MISSING","OK") | X32: =IF(ISBLANK(W32),"MISSING","OK") | Z32: =IF(ISBLANK(Y32),"MISSING","OK") | AB32: =HYPERLINK("https://africanmarketingconfederation.org/og-72.jpg","View Image") | AC32: Present — mixed OG images across site | AD32: =IF(LEN("https://africanmarketingconfederation.org/og-72.jpg")>0,IFERROR(_xlfn.IMAGE("https://africanmarketingconfederation.org/og-72.jpg"),"https://africanmarketingconfederation.org/og-72.jpg"),"") | AE32: =IFERROR(HYPERLINK("#'Main'!B"&MATCH(TRIM(I32),'Main'!B:B,0),"Open in Main"),IFERROR(HYPERLINK("#'Technical Diagnostics'!A"&MATCH(TRIM(I32),'Technical Diagnostics'!A:A,0),"Open in Technical"),"Not Found")) | AF32: Add a concise 40–60 word answer paragraph directly under a question-style heading to improve AEO extractability for: Smoke title 72. | AG32: Prioritised because of missing answer paragraphs + search intent: Informational + 11 open content/SEO issue(s). | AH32: 0 | AJ32: 0 | AK32: 0
A33: =IF(B33>=85,"Complete","Needs Copy") | B33: =MIN(100,ROUND(0.30*(IF(L33="",0,IF(LEFT(L33,7)="MISSING",0,IF(ISNUMBER(SEARCH("OK",L33)),100,IF(ISNUMBER(SEARCH("SHORT",L33)),65,IF(ISNUMBER(SEARCH("LONG",L33)),50,70))))))+0.25*(IF(N33="",0,IF(LEFT(N33,7)="MISSING",0,IF(ISNUMBER(SEARCH("OK",N33)),100,IF(ISNUMBER(SEARCH("SHORT",N33)),65,IF(ISNUMBER(SEARCH("LONG",N33)),50,70))))))+0.20*(IF(P33="",0,IF(LEFT(P33,2)="OK",100,0)))+0.08*(IF(R33="",0,IF(LEFT(R33,2)="OK",100,0)))+0.06*(IF(T33="",0,IF(LEFT(T33,2)="OK",100,0)))+0.05*(IF(V33="",0,IF(LEFT(V33,2)="OK",100,0)))+0.03*(IF(X33="",0,IF(LEFT(X33,2)="OK",100,0)))+0.03*(IF(Z33="",0,IF(LEFT(Z33,2)="OK",100,0))),0)) | C33: =IFERROR(INDEX(OFFSET('Main'!$A$1,2,MATCH("SEO Score",'Main'!$2:$2,0)-1,99998,1),MATCH(TRIM(I33),OFFSET('Main'!$A$1,2,MATCH("URL",'Main'!$2:$2,0)-1,99998,1),0)),"") | D33: =IFERROR(INDEX(OFFSET('Main'!$A$1,2,MATCH("Technical Health",'Main'!$2:$2,0)-1,99998,1),MATCH(TRIM(I33),OFFSET('Main'!$A$1,2,MATCH("URL",'Main'!$2:$2,0)-1,99998,1),0)),"") | E33: =IFERROR(INDEX(OFFSET('Main'!$A$1,2,MATCH("Copy Score",'Main'!$2:$2,0)-1,99998,1),MATCH(TRIM(I33),OFFSET('Main'!$A$1,2,MATCH("URL",'Main'!$2:$2,0)-1,99998,1),0)),"") | F33: To Do | G33: Copy Writer | H33: =HYPERLINK("https://africanmarketingconfederation.org/smoke-archive/page-75","Page 75") | I33: =HYPERLINK("https://africanmarketingconfederation.org/smoke-archive/page-75","https://africanmarketingconfederation.org/smoke-archive/page-75") | J33: page-75 | K33: Smoke title 75 | L33: =IF(K33="","MISSING",IF(AND(LEN(K33)>=50,LEN(K33)<=60),"OK 50-60 chars",IF(LEN(K33)<50,"SHORT: "&LEN(K33),"LONG: "&LEN(K33)))) | M33: MISSING DESCRIPTION | N33: =IF(M33="","MISSING",IF(AND(LEN(M33)>=120,LEN(M33)<=160),"OK 120-160 chars",IF(LEN(M33)<120,"SHORT: "&LEN(M33),"LONG: "&LEN(M33)))) | O33: Smoke heading | P33: OK | R33: =IF(ISBLANK(Q33),"MISSING","OK") | T33: =IF(ISBLANK(S33),"MISSING","OK") | V33: =IF(ISBLANK(U33),"MISSING","OK") | X33: =IF(ISBLANK(W33),"MISSING","OK") | Z33: =IF(ISBLANK(Y33),"MISSING","OK") | AC33: Missing OG image | AE33: =IFERROR(HYPERLINK("#'Main'!B"&MATCH(TRIM(I33),'Main'!B:B,0),"Open in Main"),IFERROR(HYPERLINK("#'Technical Diagnostics'!A"&MATCH(TRIM(I33),'Technical Diagnostics'!A:A,0),"Open in Technical"),"Not Found")) | AF33: Add a meta description (currently missing). Aim for 120–155 characters summarising: Smoke title 75. | AG33: Prioritised because of search intent: Informational + 7 open content/SEO issue(s). | AH33: 0 | AJ33: 0 | AK33: 0
A34: =IF(B34>=85,"Complete","Needs Copy") | B34: =MIN(100,ROUND(0.30*(IF(L34="",0,IF(LEFT(L34,7)="MISSING",0,IF(ISNUMBER(SEARCH("OK",L34)),100,IF(ISNUMBER(SEARCH("SHORT",L34)),65,IF(ISNUMBER(SEARCH("LONG",L34)),50,70))))))+0.25*(IF(N34="",0,IF(LEFT(N34,7)="MISSING",0,IF(ISNUMBER(SEARCH("OK",N34)),100,IF(ISNUMBER(SEARCH("SHORT",N34)),65,IF(ISNUMBER(SEARCH("LONG",N34)),50,70))))))+0.20*(IF(P34="",0,IF(LEFT(P34,2)="OK",100,0)))+0.08*(IF(R34="",0,IF(LEFT(R34,2)="OK",100,0)))+0.06*(IF(T34="",0,IF(LEFT(T34,2)="OK",100,0)))+0.05*(IF(V34="",0,IF(LEFT(V34,2)="OK",100,0)))+0.03*(IF(X34="",0,IF(LEFT(X34,2)="OK",100,0)))+0.03*(IF(Z34="",0,IF(LEFT(Z34,2)="OK",100,0))),0)) | C34: =IFERROR(INDEX(OFFSET('Main'!$A$1,2,MATCH("SEO Score",'Main'!$2:$2,0)-1,99998,1),MATCH(TRIM(I34),OFFSET('Main'!$A$1,2,MATCH("URL",'Main'!$2:$2,0)-1,99998,1),0)),"") | D34: =IFERROR(INDEX(OFFSET('Main'!$A$1,2,MATCH("Technical Health",'Main'!$2:$2,0)-1,99998,1),MATCH(TRIM(I34),OFFSET('Main'!$A$1,2,MATCH("URL",'Main'!$2:$2,0)-1,99998,1),0)),"") | E34: =IFERROR(INDEX(OFFSET('Main'!$A$1,2,MATCH("Copy Score",'Main'!$2:$2,0)-1,99998,1),MATCH(TRIM(I34),OFFSET('Main'!$A$1,2,MATCH("URL",'Main'!$2:$2,0)-1,99998,1),0)),"") | F34: To Do | G34: Copy Writer | H34: =HYPERLINK("https://africanmarketingconfederation.org/smoke-archive/page-8","Page 8") | I34: =HYPERLINK("https://africanmarketingconfederation.org/smoke-archive/page-8","https://africanmarketingconfederation.org/smoke-archive/page-8") | J34: page-8 | K34: Smoke title 8 | L34: =IF(K34="","MISSING",IF(AND(LEN(K34)>=50,LEN(K34)<=60),"OK 50-60 chars",IF(LEN(K34)<50,"SHORT: "&LEN(K34),"LONG: "&LEN(K34)))) | M34: Smoke meta description for page 8. | N34: =IF(M34="","MISSING",IF(AND(LEN(M34)>=120,LEN(M34)<=160),"OK 120-160 chars",IF(LEN(M34)<120,"SHORT: "&LEN(M34),"LONG: "&LEN(M34)))) | O34: Smoke heading | P34: OK | R34: =IF(ISBLANK(Q34),"MISSING","OK") | T34: =IF(ISBLANK(S34),"MISSING","OK") | V34: =IF(ISBLANK(U34),"MISSING","OK") | X34: =IF(ISBLANK(W34),"MISSING","OK") | Z34: =IF(ISBLANK(Y34),"MISSING","OK") | AB34: =HYPERLINK("https://africanmarketingconfederation.org/og-8.jpg","View Image") | AC34: Present — mixed OG images across site | AD34: =IF(LEN("https://africanmarketingconfederation.org/og-8.jpg")>0,IFERROR(_xlfn.IMAGE("https://africanmarketingconfederation.org/og-8.jpg"),"https://africanmarketingconfederation.org/og-8.jpg"),"") | AE34: =IFERROR(HYPERLINK("#'Main'!B"&MATCH(TRIM(I34),'Main'!B:B,0),"Open in Main"),IFERROR(HYPERLINK("#'Technical Diagnostics'!A"&MATCH(TRIM(I34),'Technical Diagnostics'!A:A,0),"Open in Technical"),"Not Found")) | AF34: Restructure content for a faq featured snippet: use a direct answer block, scannable list, or FAQ schema as appropriate for “Smoke title 8”. | AG34: Prioritised because of search intent: Informational + 5 open content/SEO issue(s). | AH34: 0 | AJ34: 0 | AK34: 0
A35: =IF(B35>=85,"Complete","Needs Copy") | B35: =MIN(100,ROUND(0.30*(IF(L35="",0,IF(LEFT(L35,7)="MISSING",0,IF(ISNUMBER(SEARCH("OK",L35)),100,IF(ISNUMBER(SEARCH("SHORT",L35)),65,IF(ISNUMBER(SEARCH("LONG",L35)),50,70))))))+0.25*(IF(N35="",0,IF(LEFT(N35,7)="MISSING",0,IF(ISNUMBER(SEARCH("OK",N35)),100,IF(ISNUMBER(SEARCH("SHORT",N35)),65,IF(ISNUMBER(SEARCH("LONG",N35)),50,70))))))+0.20*(IF(P35="",0,IF(LEFT(P35,2)="OK",100,0)))+0.08*(IF(R35="",0,IF(LEFT(R35,2)="OK",100,0)))+0.06*(IF(T35="",0,IF(LEFT(T35,2)="OK",100,0)))+0.05*(IF(V35="",0,IF(LEFT(V35,2)="OK",100,0)))+0.03*(IF(X35="",0,IF(LEFT(X35,2)="OK",100,0)))+0.03*(IF(Z35="",0,IF(LEFT(Z35,2)="OK",100,0))),0)) | C35: =IFERROR(INDEX(OFFSET('Main'!$A$1,2,MATCH("SEO Score",'Main'!$2:$2,0)-1,99998,1),MATCH(TRIM(I35),OFFSET('Main'!$A$1,2,MATCH("URL",'Main'!$2:$2,0)-1,99998,1),0)),"") | D35: =IFERROR(INDEX(OFFSET('Main'!$A$1,2,MATCH("Technical Health",'Main'!$2:$2,0)-1,99998,1),MATCH(TRIM(I35),OFFSET('Main'!$A$1,2,MATCH("URL",'Main'!$2:$2,0)-1,99998,1),0)),"") | E35: =IFERROR(INDEX(OFFSET('Main'!$A$1,2,MATCH("Copy Score",'Main'!$2:$2,0)-1,99998,1),MATCH(TRIM(I35),OFFSET('Main'!$A$1,2,MATCH("URL",'Main'!$2:$2,0)-1,99998,1),0)),"") | F35: To Do | G35: Copy Writer | H35: =HYPERLINK("https://africanmarketingconfederation.org/smoke-archive/page-9","Page 9") | I35: =HYPERLINK("https://africanmarketingconfederation.org/smoke-archive/page-9","https://africanmarketingconfederation.org/smoke-archive/page-9") | J35: page-9 | K35: Smoke title 9 | L35: =IF(K35="","MISSING",IF(AND(LEN(K35)>=50,LEN(K35)<=60),"OK 50-60 chars",IF(LEN(K35)<50,"SHORT: "&LEN(K35),"LONG: "&LEN(K35)))) | M35: Smoke meta description for page 9. | N35: =IF(M35="","MISSING",IF(AND(LEN(M35)>=120,LEN(M35)<=160),"OK 120-160 chars",IF(LEN(M35)<120,"SHORT: "&LEN(M35),"LONG: "&LEN(M35)))) | O35: Smoke heading | P35: OK | R35: =IF(ISBLANK(Q35),"MISSING","OK") | T35: =IF(ISBLANK(S35),"MISSING","OK") | V35: =IF(ISBLANK(U35),"MISSING","OK") | X35: =IF(ISBLANK(W35),"MISSING","OK") | Z35: =IF(ISBLANK(Y35),"MISSING","OK") | AC35: Missing OG image | AE35: =IFERROR(HYPERLINK("#'Main'!B"&MATCH(TRIM(I35),'Main'!B:B,0),"Open in Main"),IFERROR(HYPERLINK("#'Technical Diagnostics'!A"&MATCH(TRIM(I35),'Technical Diagnostics'!A:A,0),"Open in Technical"),"Not Found")) | AF35: Add a concise 40–60 word answer paragraph directly under a question-style heading to improve AEO extractability for: Smoke title 9. | AG35: Prioritised because of missing answer paragraphs + search intent: Informational + 9 open content/SEO issue(s). | AH35: 0 | AJ35: 0 | AK35: 0

Sheet Content Planner
A1: ← Return to Executive Briefing | C1: =IFERROR(INDEX('Audit Run Details'!$B:$B,MATCH("Target Site",'Audit Run Details'!$A:$A,0)),"") & " — " & IFERROR(INDEX('Audit Run Details'!$B:$B,MATCH("Total URLs",'Audit Run Details'!$A:$A,0)),"") & " URLs crawled — " & LEFT(IFERROR(INDEX('Audit Run Details'!$B:$B,MATCH("Run Timestamp",'Audit Run Details'!$A:$A,0)),""),10)
A2: Primary | B2: Secondary | C2: Tertiary | D2: Page link | E2: Copy Doc | F2: Copywriter Sign off | G2: Copy First Check | H2: 2nd Revisions | I2: Client copy sign off | J2: Web design off | K2: UXI sign off | L2: Visual Design sign off | M2: Client final sign off | N2: Optimisations | O2: Desktop | P2: Tablet | Q2: Mobile | R2: SEO | S2: Performance
A3: Home | D3: https://africanmarketingconfederation.org/ | F3: Not signed off | G3: Not signed off | H3: Not signed off | I3: Not signed off | J3: Not signed off | K3: Not signed off | L3: Not signed off | M3: Not signed off | N3: Not signed off | O3: Not signed off | P3: Not signed off | Q3: Not signed off | R3: Not signed off | S3: Not signed off
A4: discovered-via-bfs-1 | D4: https://africanmarketingconfederation.org/discovered-via-bfs-1 | F4: Not signed off | G4: Not signed off | H4: Not signed off | I4: Not signed off | J4: Not signed off | K4: Not signed off | L4: Not signed off | M4: Not signed off | N4: Not signed off | O4: Not signed off | P4: Not signed off | Q4: Not signed off | R4: Not signed off | S4: Not signed off
A5: discovered-via-bfs-2 | D5: https://africanmarketingconfederation.org/discovered-via-bfs-2 | F5: Not signed off | G5: Not signed off | H5: Not signed off | I5: Not signed off | J5: Not signed off | K5: Not signed off | L5: Not signed off | M5: Not signed off | N5: Not signed off | O5: Not signed off | P5: Not signed off | Q5: Not signed off | R5: Not signed off | S5: Not signed off
A6: discovered-via-bfs-3 | D6: https://africanmarketingconfederation.org/discovered-via-bfs-3 | F6: Not signed off | G6: Not signed off | H6: Not signed off | I6: Not signed off | J6: Not signed off | K6: Not signed off | L6: Not signed off | M6: Not signed off | N6: Not signed off | O6: Not signed off | P6: Not signed off | Q6: Not signed off | R6: Not signed off | S6: Not signed off
B7: page-1 | D7: https://africanmarketingconfederation.org/smoke-archive/page-1 | F7: Not signed off | G7: Not signed off | H7: Not signed off | I7: Not signed off | J7: Not signed off | K7: Not signed off | L7: Not signed off | M7: Not signed off | N7: Not signed off | O7: Not signed off | P7: Not signed off | Q7: Not signed off | R7: Not signed off | S7: Not signed off
B8: page-10 | D8: https://africanmarketingconfederation.org/smoke-archive/page-10 | F8: Not signed off | G8: Not signed off | H8: Not signed off | I8: Not signed off | J8: Not signed off | K8: Not signed off | L8: Not signed off | M8: Not signed off | N8: Not signed off | O8: Not signed off | P8: Not signed off | Q8: Not signed off | R8: Not signed off | S8: Not signed off
B9: page-11 | D9: https://africanmarketingconfederation.org/smoke-archive/page-11 | F9: Not signed off | G9: Not signed off | H9: Not signed off | I9: Not signed off | J9: Not signed off | K9: Not signed off | L9: Not signed off | M9: Not signed off | N9: Not signed off | O9: Not signed off | P9: Not signed off | Q9: Not signed off | R9: Not signed off | S9: Not signed off
B10: page-12 | D10: https://africanmarketingconfederation.org/smoke-archive/page-12 | F10: Not signed off | G10: Not signed off | H10: Not signed off | I10: Not signed off | J10: Not signed off | K10: Not signed off | L10: Not signed off | M10: Not signed off | N10: Not signed off | O10: Not signed off | P10: Not signed off | Q10: Not signed off | R10: Not signed off | S10: Not signed off
B11: page-13 | D11: https://africanmarketingconfederation.org/smoke-archive/page-13 | F11: Not signed off | G11: Not signed off | H11: Not signed off | I11: Not signed off | J11: Not signed off | K11: Not signed off | L11: Not signed off | M11: Not signed off | N11: Not signed off | O11: Not signed off | P11: Not signed off | Q11: Not signed off | R11: Not signed off | S11: Not signed off
B12: page-14 | D12: https://africanmarketingconfederation.org/smoke-archive/page-14 | F12: Not signed off | G12: Not signed off | H12: Not signed off | I12: Not signed off | J12: Not signed off | K12: Not signed off | L12: Not signed off | M12: Not signed off | N12: Not signed off | O12: Not signed off | P12: Not signed off | Q12: Not signed off | R12: Not signed off | S12: Not signed off
B13: page-15 | D13: https://africanmarketingconfederation.org/smoke-archive/page-15 | F13: Not signed off | G13: Not signed off | H13: Not signed off | I13: Not signed off | J13: Not signed off | K13: Not signed off | L13: Not signed off | M13: Not signed off | N13: Not signed off | O13: Not signed off | P13: Not signed off | Q13: Not signed off | R13: Not signed off | S13: Not signed off
B14: page-16 | D14: https://africanmarketingconfederation.org/smoke-archive/page-16 | F14: Not signed off | G14: Not signed off | H14: Not signed off | I14: Not signed off | J14: Not signed off | K14: Not signed off | L14: Not signed off | M14: Not signed off | N14: Not signed off | O14: Not signed off | P14: Not signed off | Q14: Not signed off | R14: Not signed off | S14: Not signed off
B15: page-17 | D15: https://africanmarketingconfederation.org/smoke-archive/page-17 | F15: Not signed off | G15: Not signed off | H15: Not signed off | I15: Not signed off | J15: Not signed off | K15: Not signed off | L15: Not signed off | M15: Not signed off | N15: Not signed off | O15: Not signed off | P15: Not signed off | Q15: Not signed off | R15: Not signed off | S15: Not signed off
B16: page-18 | D16: https://africanmarketingconfederation.org/smoke-archive/page-18 | F16: Not signed off | G16: Not signed off | H16: Not signed off | I16: Not signed off | J16: Not signed off | K16: Not signed off | L16: Not signed off | M16: Not signed off | N16: Not signed off | O16: Not signed off | P16: Not signed off | Q16: Not signed off | R16: Not signed off | S16: Not signed off
B17: page-19 | D17: https://africanmarketingconfederation.org/smoke-archive/page-19 | F17: Not signed off | G17: Not signed off | H17: Not signed off | I17: Not signed off | J17: Not signed off | K17: Not signed off | L17: Not signed off | M17: Not signed off | N17: Not signed off | O17: Not signed off | P17: Not signed off | Q17: Not signed off | R17: Not signed off | S17: Not signed off
B18: page-2 | D18: https://africanmarketingconfederation.org/smoke-archive/page-2 | F18: Not signed off | G18: Not signed off | H18: Not signed off | I18: Not signed off | J18: Not signed off | K18: Not signed off | L18: Not signed off | M18: Not signed off | N18: Not signed off | O18: Not signed off | P18: Not signed off | Q18: Not signed off | R18: Not signed off | S18: Not signed off
... B85: page-9 | D85: https://africanmarketingconfederation.org/smoke-archive/page-9 | F85: Not signed off | G85: Not signed off | H85: Not signed off | I85: Not signed off | J85: Not signed off | K85: Not signed off | L85: Not signed off | M85: Not signed off | N85: Not signed off | O85: Not signed off | P85: Not signed off | Q85: Not signed off | R85: Not signed off | S85: Not signed off

Sheet Content Hub Metrics
A1: ← Return to Executive Briefing | C1: =IFERROR(INDEX('Audit Run Details'!$B:$B,MATCH("Target Site",'Audit Run Details'!$A:$A,0)),"") & " — " & IFERROR(INDEX('Audit Run Details'!$B:$B,MATCH("Total URLs",'Audit Run Details'!$A:$A,0)),"") & " URLs crawled — " & LEFT(IFERROR(INDEX('Audit Run Details'!$B:$B,MATCH("Run Timestamp",'Audit Run Details'!$A:$A,0)),""),10)
A2: URL | B2: JS Dependent | C2: Raw Words | D2: Rendered Words | E2: Field LCP (ms) | F2: Field CLS | G2: Anchor Text Diversity | H2: Potential Traffic Lift | I2: AEO Visibility Gain | J2: Instant Priority | K2: Search Intent | L2: Open in Main
A3: https://africanmarketingconfederation.org/discovered-via-bfs-1 | B3: FALSE | C3: 351 | D3: 351 | E3: 2400 | F3: 0.04 | H3: 0 | I3: 0 | J3: Standard | K3: Informational | L3: =IFERROR(HYPERLINK("#'Main'!B"&MATCH(TRIM(A3),'Main'!B:B,0),"Open"),HYPERLINK("#'Main'!B1","Open"))
A4: https://africanmarketingconfederation.org/smoke-archive/page-10 | B4: FALSE | C4: 330 | D4: 330 | E4: 2400 | F4: 0.04 | H4: 0 | I4: 0 | J4: Standard | K4: Informational | L4: =IFERROR(HYPERLINK("#'Main'!B"&MATCH(TRIM(A4),'Main'!B:B,0),"Open"),HYPERLINK("#'Main'!B1","Open"))
A5: https://africanmarketingconfederation.org/smoke-archive/page-12 | B5: FALSE | C5: 332 | D5: 332 | E5: 2400 | F5: 0.04 | H5: 0 | I5: 0 | J5: Standard | K5: Informational | L5: =IFERROR(HYPERLINK("#'Main'!B"&MATCH(TRIM(A5),'Main'!B:B,0),"Open"),HYPERLINK("#'Main'!B1","Open"))
A6: https://africanmarketingconfederation.org/smoke-archive/page-15 | B6: FALSE | C6: 335 | D6: 335 | E6: 2400 | F6: 0.04 | H6: 0 | I6: 0 | J6: Standard | K6: Informational | L6: =IFERROR(HYPERLINK("#'Main'!B"&MATCH(TRIM(A6),'Main'!B:B,0),"Open"),HYPERLINK("#'Main'!B1","Open"))
A7: https://africanmarketingconfederation.org/smoke-archive/page-16 | B7: FALSE | C7: 336 | D7: 336 | E7: 2400 | F7: 0.04 | H7: 0 | I7: 0 | J7: Standard | K7: Informational | L7: =IFERROR(HYPERLINK("#'Main'!B"&MATCH(TRIM(A7),'Main'!B:B,0),"Open"),HYPERLINK("#'Main'!B1","Open"))
A8: https://africanmarketingconfederation.org/smoke-archive/page-18 | B8: FALSE | C8: 338 | D8: 338 | E8: 2400 | F8: 0.04 | H8: 0 | I8: 0 | J8: Standard | K8: Informational | L8: =IFERROR(HYPERLINK("#'Main'!B"&MATCH(TRIM(A8),'Main'!B:B,0),"Open"),HYPERLINK("#'Main'!B1","Open"))
A9: https://africanmarketingconfederation.org/smoke-archive/page-20 | B9: FALSE | C9: 340 | D9: 340 | E9: 2400 | F9: 0.04 | H9: 0 | I9: 0 | J9: Standard | K9: Informational | L9: =IFERROR(HYPERLINK("#'Main'!B"&MATCH(TRIM(A9),'Main'!B:B,0),"Open"),HYPERLINK("#'Main'!B1","Open"))
A10: https://africanmarketingconfederation.org/smoke-archive/page-24 | B10: FALSE | C10: 344 | D10: 344 | E10: 2400 | F10: 0.04 | H10: 0 | I10: 0 | J10: Standard | K10: Informational | L10: =IFERROR(HYPERLINK("#'Main'!B"&MATCH(TRIM(A10),'Main'!B:B,0),"Open"),HYPERLINK("#'Main'!B1","Open"))
A11: https://africanmarketingconfederation.org/smoke-archive/page-25 | B11: FALSE | C11: 345 | D11: 345 | E11: 2400 | F11: 0.04 | H11: 0 | I11: 0 | J11: Standard | K11: Informational | L11: =IFERROR(HYPERLINK("#'Main'!B"&MATCH(TRIM(A11),'Main'!B:B,0),"Open"),HYPERLINK("#'Main'!B1","Open"))
A12: https://africanmarketingconfederation.org/smoke-archive/page-27 | B12: FALSE | C12: 347 | D12: 347 | E12: 2400 | F12: 0.04 | H12: 0 | I12: 0 | J12: Standard | K12: Informational | L12: =IFERROR(HYPERLINK("#'Main'!B"&MATCH(TRIM(A12),'Main'!B:B,0),"Open"),HYPERLINK("#'Main'!B1","Open"))
A13: https://africanmarketingconfederation.org/smoke-archive/page-30 | B13: FALSE | C13: 350 | D13: 350 | E13: 2400 | F13: 0.04 | H13: 0 | I13: 0 | J13: Standard | K13: Informational | L13: =IFERROR(HYPERLINK("#'Main'!B"&MATCH(TRIM(A13),'Main'!B:B,0),"Open"),HYPERLINK("#'Main'!B1","Open"))
A14: https://africanmarketingconfederation.org/smoke-archive/page-32 | B14: FALSE | C14: 352 | D14: 352 | E14: 2400 | F14: 0.04 | H14: 0 | I14: 0 | J14: Standard | K14: Informational | L14: =IFERROR(HYPERLINK("#'Main'!B"&MATCH(TRIM(A14),'Main'!B:B,0),"Open"),HYPERLINK("#'Main'!B1","Open"))
... A35: https://africanmarketingconfederation.org/smoke-archive/page-9 | B35: FALSE | C35: 329 | D35: 329 | E35: 2400 | F35: 0.04 | H35: 0 | I35: 0 | J35: Standard | K35: Informational | L35: =IFERROR(HYPERLINK("#'Main'!B"&MATCH(TRIM(A35),'Main'!B:B,0),"Open"),HYPERLINK("#'Main'!B1","Open"))

Sheet Main
A1: ← Return to Executive Briefing | C1: =IFERROR(INDEX('Audit Run Details'!$B:$B,MATCH("Target Site",'Audit Run Details'!$A:$A,0)),"") & " — " & IFERROR(INDEX('Audit Run Details'!$B:$B,MATCH("Total URLs",'Audit Run Details'!$A:$A,0)),"") & " URLs crawled — " & LEFT(IFERROR(INDEX('Audit Run Details'!$B:$B,MATCH("Run Timestamp",'Audit Run Details'!$A:$A,0)),""),10)
A2: Health Icon | B2: URL | C2: Status Code | D2: Indexability | E2: Load Time (s) | F2: Title | G2: Meta Description | H2: Word Count (Body) | I2: SEO Health Score | J2: Severity Badge | K2: Action Needed | L2: CWV LCP (s) | M2: CWV CLS | N2: Field vs Lab | O2: CWV Data Source | P2: PSI Data Status | Q2: CrUX Level | R2: CWV INP (ms) | S2: CWV FCP (ms) | T2: CWV TTFB (ms) | U2: CrUX LCP Category | V2: CrUX CLS Category | W2: CrUX INP Category | X2: Origin CrUX LCP (s) | Y2: Origin CrUX CLS | Z2: Origin CrUX INP (ms) | AA2: Desktop PSI Score | AB2: Mobile PSI Score | AC2: Lighthouse Performance (Mobile) | AD2: Lighthouse Accessibility (Mobile) | AE2: Lighthouse Best Practices (Mobile) | AF2: Lighthouse SEO Score (Mobile) | AG2: Mobile LCP (s) | AH2: Mobile CLS | AI2: Mobile TTFB (s) | AJ2: Lab LCP (Mobile) (s) | AK2: Lab CLS (Mobile) | AL2: Lab TBT (Mobile) (ms) | AM2: Lab INP (Mobile) (ms) | AN2: Lab FCP (Mobile) (s) | AO2: Lab Speed Index (Mobile) (s) | AP2: Lab TTI (Mobile) (s) | AQ2: Lab TTFB (Mobile) (ms) | AR2: Lighthouse Performance (Desktop) | AS2: Lighthouse Accessibility (Desktop) | AT2: Lighthouse Best Practices (Desktop) | AU2: Lighthouse SEO Score (Desktop) | AV2: Lab LCP (Desktop) (s) | AW2: Lab CLS (Desktop) | AX2: Lab TBT (Desktop) (ms) | AY2: Lab INP (Desktop) (ms) | AZ2: Lab FCP (Desktop) (s) | BA2: Lab Speed Index (Desktop) (s) | BB2: Lab TTI (Desktop) (s) | BC2: Lab TTFB (Desktop) (ms) | BD2: Page Size (KB) | BE2: DOM Size (nodes) | BF2: JS Execution (ms) | BG2: Network Request Count | BH2: Has Text Compression | BI2: Has Long Cache TTL Issues | BJ2: Has Render Blocking Resources | BK2: Uses Modern Image Formats | BL2: Reachable from Homepage | BM2: Regional Authority Score | BN2: Extraction State | BO2: Extraction Source | BP2: Extraction Source Fallback | BQ2: Title Length | BR2: Meta Desc Length | BS2: OG-Image | BT2: Has Valid JSON-LD | BU2: Meta Keywords | BV2: H1 Content | BW2: H1 Length | BX2: H2 Content | BY2: H2 Length | BZ2: H3 Content | CA2: H3 Length | CB2: H4 Content | CC2: H4 Length | CD2: H5 Content | CE2: H5 Length | CF2: H6 Content | CG2: H6 Length | CH2: GSC Clicks | CI2: GSC Impressions | CJ2: GSC CTR | CK2: GSC Avg Position | CL2: GSC Data Freshness | CM2: GSC Coverage Note | CN2: Click Depth | CO2: Orphan Pages | CP2: Internal PageRank | CQ2: Found via Sitemap | CR2: Found via Crawl | CS2: Discovery Source | CT2: Discovered On URL | CU2: Discovery Rank | CV2: Technical Health | CW2: Copy Score | CX2: SEO Score | CY2: Schema Present | CZ2: Schema Valid | DA2: Schema Types Found | DB2: Schema Types Valid | DC2: Schema Types With Errors | DD2: Schema Error Count | DE2: Schema Warning Count | DF2: Schema Parse Error Detail | DG2: Schema Validation Summary | DH2: Schema Issues Detail | DI2: E-E-A-T Signal Score | DJ2: Schema Author Name | DK2: Meta Author | DL2: Has Byline Element | DM2: Byline Text | DN2: Schema Published Date | DO2: Schema Modified Date | DP2: OG Published Time | DQ2: OG Modified Time | DR2: Has Time Element | DS2: Has Privacy Policy Link | DT2: Has Terms Link | DU2: Has Social Links | DV2: Social Profile Link Count | DW2: Has Phone Number | DX2: Has Email Address | DY2: Links to About Page | DZ2: Has Authority External Links | EA2: Is Thin Content | EB2: Is Near Duplicate | EC2: Near Duplicate Of | ED2: Content Similarity Score | EE2: Is Draft or Test Page | EF2: Draft Signal | EG2: Published Date | EH2: Last Modified Date | EI2: HTTP Last-Modified | EJ2: Content Age (days) | EK2: Freshness Status | EL2: OG Title | EM2: OG Description | EN2: OG Type | EO2: OG URL | EP2: OG Image URL | EQ2: OG Image Width | ER2: OG Image Height | ES2: OG Image OK | ET2: OG Image Dimensions OK | EU2: OG URL Mismatch | EV2: Twitter Card Type | EW2: Twitter Title | EX2: Twitter Description | EY2: Twitter Image | EZ2: OG Completeness Score | FA2: Open Graph Complete | FB2: Final URL | FC2: Redirect Chain | FD2: Redirect Chain Length | FE2: Redirect Chain Hops | FF2: Has 302 in Chain | FG2: Has Mixed Redirect Types | FH2: Redirect Loop Flag | FI2: Canonical Chain Depth | FJ2: Canonical Chain Final | FK2: Canonical Chain | FL2: Canonical Loop Detected | FM2: Canonical Points to Redirect | FN2: Canonical Points to Non-200 | FO2: GSC Index Status | FP2: GSC Last Crawl Date | FQ2: GSC Mobile Usability | FR2: GSC Rich Result Status | FS2: GSC Coverage Reason | FT2: Days Since Last Crawl | FU2: Robots.txt: Googlebot | FV2: Robots.txt: Bingbot | FW2: Robots.txt: GPTBot | FX2: Robots.txt: ClaudeBot | FY2: Robots.txt: PerplexityBot | FZ2: Crawl-Delay Applies | GA2: Third Party Script Count | GB2: Third Party Scripts | GC2: Third Party Total Size (KB) | GD2: Has Google Analytics | GE2: Has Tag Manager | GF2: Has Meta Pixel | GG2: Has Chat Widget | GH2: Has Consent Manager | GI2: Third Party JS Blocking | GJ2: Image Count | GK2: Broken Image Count | GL2: Large Image Count | GM2: Broken Image URLs | GN2: Oversized Image URLs | GO2: Has Broken Images | GP2: Hreflang Declared Languages | GQ2: Hreflang Alternate URLs | GR2: Hreflang Reciprocal Status | GS2: Hreflang Code Valid | GT2: PageRank Percentile | GU2: Equity Tier | GV2: Inbound Internal Link Count | GW2: Generic Inbound Anchor % | GX2: Generic Anchor Dominance | GY2: Featured Snippet Type | GZ2: Featured Snippet Readiness | HA2: GSC Position Opportunity | HB2: Top TF-IDF Terms | HC2: Keyword in Title | HD2: Keyword in H1 | HE2: Keyword in First Paragraph | HF2: Keyword Density (%) | HG2: Has Rel Author Link | HH2: Has HTML Table | HI2: Technical View
