Workbook

Sheet Table of Contents
A1: Table of Contents | B1: Unnamed: 1 | C1: Unnamed: 2
A2: Section | B2: Open | C2: Description
A3: Dashboard | B3: Open | C3: Primary columns: Executive SEO & AEO Performance Report, Unnamed: 1, Unnamed: 2, Unnamed: 3, Unnamed: 4, Unnamed: 5, Unnamed: 6, Unnamed: 7, Unnamed: 8, Unnamed: 9
A4: Content Optimization Hub | B4: Open | C4: Primary columns: CONTENT HUB INSTRUCTIONS: 1. Draft in 'Proposed' columns. | 2. Watch 'Count' for Green. | 3. Click 'Elementor' link. | 4. Mark 'Status' as 'Completed'. | NOTE: If images show '#BLOCKED!', click the 'Sec…
A5: Quick Reference Guide | B5: Open | C5: Primary columns: Section, Item, Guideline, Why It Matters, BACK TO DASHBOARD, BACK TO DASHBOARD_1
A6: FixPlan | B6: Open | C6: Primary columns: Issue Type, Severity, Priority Score, Affected Count, Affected URLs, Detail Reference Tab, Resolution Type, URL, Recommended Fix, Likely Root Cause
A7: Main | B7: Open | C7: Primary columns: Health Icon, URL, Status Code, Indexability, Load Time (s), Title, Meta Description, Word Count (Body), SEO Health Score, Severity Badge
A8: Technical | B8: Open | C8: Primary columns: URL, Status Code, Status Class, SEO Health Score, Severity Badge, Action Needed, Indexability Reason, TTFB (ms), Total Request Time (ms), Final URL
A9: PSI Performance | B9: Open | C9: Primary columns: URL, Desktop Score, Mobile Score, Mobile LCP, Mobile CLS, Mobile TTFB, Open in Main, BACK TO DASHBOARD, BACK TO DASHBOARD_1
A10: Content | B10: Open | C10: Primary columns: URL, Word Count, Word Count Band, Readability (Rough Flesch), H1 Count, Missing H1 Flag, Multiple H1 Flag, Title Missing, Meta Description Missing, Thin Content Flag
A11: AEO | B11: Open | C11: Primary columns: URL, AEO Readiness Score, AEO Badge, Why It Matters, FAQ Section Count, Question Heading Count, Paragraphs 40-60 Words Count, QAPage/FAQ Schema Present, Speakable Schema Present, HowTo Signal
A12: Schema & Metadata | B12: Open | C12: Primary columns: URL, Schema Types Found, Schema Types Count, Schema Parse Errors, OG Title, OG Description, OG Image, Open Graph Complete, Twitter Card Type, Open in Main
... A30: SitemapQA | B30: Open | C30: Primary columns: Sitemap URL, Final URL, Status Code, Found via Crawl, Found via Sitemap, Discovery Source, In Sitemap but Non-200, Sitemap URL Redirects, In Sitemap but Canonicalized Elsewhere, Missing <lastmod>

Sheet Dashboard
A1: Executive SEO & AEO Performance Report | B1: Unnamed: 1 | C1: Unnamed: 2 | D1: Unnamed: 3 | E1: Unnamed: 4 | F1: Unnamed: 5 | G1: Unnamed: 6 | H1: Unnamed: 7 | I1: Unnamed: 8 | J1: Unnamed: 9 | K1: Unnamed: 10
A2: Executive SEO & AEO Dashboard
A4: EXECUTIVE METRICS | B4: Value | D4: Status | E4: Count | G4: OWNER ISSUE SUMMARY
A5: Total URLs | B5: 10 | D5: 200 OK | E5: 10 | G5: Owner | H5: Issue Rows | I5: Affected URLs | J5: Critical | K5: Warning
A6: Overall Health Score | B6: =IFERROR(100.0/100,0) | D6: 3xx Redirects | E6: 0 | G6: =HYPERLINK("#'FixPlan'!A1","Dev") | H6: 9 | I6: 0 | J6: 4 | K6: 4
A7: SEO Pass Rate % | B7: =IFERROR(10/10,0) | D7: 4xx Errors | E7: 0 | G7: =HYPERLINK("#'FixPlan'!A1","Server/Host") | H7: 5 | I7: 0 | J7: 2 | K7: 0
A8: Pass URLs | B8: 10 | D8: 5xx Errors | E8: 0 | G8: =HYPERLINK("#'FixPlan'!A1","Copy Writer") | H8: 20 | I8: 0 | J8: 1 | K8: 8
A9: Critical URLs | B9: 0 | D9: Other | E9: 0
A10: Warning URLs | B10: 0
A11: Error Rate % (4xx/5xx) | B11: =IFERROR(0/10,0)
A12: Crawl Success Rate % (2xx) | B12: =IFERROR(10/10,0) | D12: Severity | E12: Count | J12: Quick Navigation | K12: Open
A13: Critical URL Rate % | B13: =IFERROR(0/10,0) | D13: Critical | E13: 7 | J13: Fix Plan | K13: =HYPERLINK("#FixPlan!A1","Open")
A14: Warning URL Rate % | B14: =IFERROR(0/10,0) | D14: Warning | E14: 12 | J14: Main URL Data | K14: =HYPERLINK("#Main!A1","Open")
A15: Projected Health Score % (if all To Do done) | B15: 1 | D15: Medium | E15: 0 | J15: Technical Diagnostics | K15: =HYPERLINK("#Technical!A1","Open")
A16: Projected Pass Rate % (if all To Do done) | B16: 1 | D16: Low | E16: 15 | J16: Indexability | K16: =HYPERLINK("#Indexability!A1","Open")
A17: Content Hub Readiness (%) | B17: 0 | J17: AEO Opportunities | K17: =HYPERLINK("#AEO!A1","Open")
A18: URLs with Schema | B18: 0 | J18: AIOSEO Action Queue | K18: =HYPERLINK("#AIOSEO!A1","Open")
A19: Broken Internal Links | B19: 0
E20: Traditional SEO vs. 2026 AEO Readiness | J20: BUSINESS IMPACT SUMMARY
E21: Dimension | F21: Score | J21: 0 error URLs detected (0 4xx / 0 5xx). Critical issue volume is 0 URLs and warning volume is 0. Top blocker: N/A affecting 0 URLs.
E22: Traditional SEO | F22: 1
E23: 2026 AEO Readiness | F23: 0
E24: Strategic Narrative
E25: High SEO / Low AEO suggests the site is visible to humans but invisible to AI answer engines.
B44: TOP ISSUES TO FIX FIRST | C44: Affected URLs
B45: =HYPERLINK("#FixPlan!A8","Broken Internal Links") | C45: 0
B46: =HYPERLINK("#FixPlan!A7","CWV LCP Above 4.0s") | C46: 0
B47: =HYPERLINK("#FixPlan!A5","Canonical Points Elsewhere") | C47: 0
B48: =HYPERLINK("#FixPlan!A3","Missing Title") | C48: 0
B49: =HYPERLINK("#FixPlan!A4","Noindex Directive") | C49: 0

Sheet Content Optimization Hub
A1: CONTENT HUB INSTRUCTIONS: 1. Draft in 'Proposed' columns. | 2. Watch 'Count' for Green. | 3. Click 'Elementor' link. | 4. Mark 'Status' as 'Completed'. | NOTE: If images show '#BLOCKED!', click the 'Security Warning' bar at the top of Excel and select 'Enable Content'.
A2: CONTENT HUB INSTRUCTIONS: 1. Draft in 'Proposed' columns. | 2. Watch 'Count' for Green. | 3. Click 'Elementor' link. | 4. Mark 'Status' as 'Completed'. | NOTE: If images show '#BLOCKED!', click the 'Security Warning' bar at the top of Excel and select 'En | B2: Unnamed: 1 | C2: Unnamed: 2 | D2: Unnamed: 3 | E2: Unnamed: 4 | F2: Unnamed: 5 | G2: Unnamed: 6 | H2: Unnamed: 7 | I2: Unnamed: 8 | J2: Unnamed: 9 | K2: Unnamed: 10 | L2: Unnamed: 11 | M2: Unnamed: 12 | N2: Unnamed: 13 | O2: Unnamed: 14 | P2: Unnamed: 15 | Q2: Unnamed: 16 | R2: Unnamed: 17 | S2: Unnamed: 18 | T2: Unnamed: 19 | U2: Unnamed: 20 | V2: Unnamed: 21 | W2: Unnamed: 22 | X2: Unnamed: 23 | Y2: Unnamed: 24
A3: Action Required | B3: Status | C3: Assigned Owner | D3: Content Cluster ID | E3: URL | F3: Elementor Builder Link | G3: Target Keywords | H3: Current Page Copy Snippet | I3: Current Title | J3: Proposed Title (50-60 Chars) | K3: Title Count | L3: Current Meta Desc | M3: Proposed Meta Desc (120-160 Chars) | N3: Desc Count | O3: Current H-Tag Structure | P3: Proposed H-Tag Fixes | Q3: AEO Answer Block Draft | R3: FAQ/QA Draft | S3: Current OG-Image URL | T3: OG Image Preview | U3: Social Share Note | V3: SEO Score | W3: Technical Health | X3: Copy Score | Y3: Open in Main
A4: Needs Copy | B4: To Do | C4: Unassigned | D4: home-african-marketing-confed | E4: https://africanmarketingconfederation.org/ | F4: https://africanmarketingconfederation.org/wp-admin/post.php?post=8&action=elementor | H4: European marketers gather to choose their top achievers for 2026 Marketing associations from across Europe nominated national champions, with 10 finalists competing for the Marketer of the Year title. Read More » April 30, 2026 | I4: African Marketing Confederation - Uniting Marketers for Excellence | L4: The African Marketing Confederation is the ground-breaking Pan-African body driving the development of top marketing standards across Africa and beyond. | O4: H1: ABOUT The African Marketing Confederation H2: The 2026 AMC Conference H2: Meets the Mighty Victoria Falls H2: 23-25 September | Livingstone, Zambia H2: The 2026 AMC Conference H2: Meets the Mighty Victoria Falls | S4: https://africanmarketingconfederation.org/wp-content/uploads/2026/03/og-image.png | V4: 18.75 | W4: 0 | X4: 75 | Y4: Open
A5: Needs Copy | B5: To Do | C5: Unassigned | D5: about-us-african-marketing-confed | E5: https://africanmarketingconfederation.org/about-us | F5: https://africanmarketingconfederation.org/wp-admin/post.php?post=84&action=elementor | G5: About Us | H5: Skip to content ABOUT The African Marketing Confederation The African Marketing Confederation is the ground-breaking Pan African body of marketing professionals spearheading the ongoing development of the highest possible standards of marketing acro... | I5: African Marketing Confederation – The Leading Marketing Professional Body – African Marketing Confederation | L5: ABOUT The African Marketing Confederation The African Marketing Confederation is the ground-breaking Pan African body of marketing professionals spearheading the ongoing development of the highest possible standards of marketing across Africa. Founded in 2011, the AMC is a collaboration between the African national marketing bodies and associations to exchange expertise and information, and to promote | O5: H1: ABOUT The African Marketing Confederation H3: African Marketing Confederation PRESIDENT’S COUNCIL H2: Helen McIntee H2: President and Co-founder H2: David Balikuddembe H2: Secretary General | S5: https://africanmarketingconfederation.org/wp-content/uploads/2026/03/og-image.png | V5: 18.75 | W5: 0 | X5: 75 | Y5: Open
A6: Needs Copy | B6: To Do | C6: Unassigned | D6: african-marketing-confederation-tourism-chapter-african-marketing-confed | E6: https://africanmarketingconfederation.org/african-marketing-confederation-tourism-chapter | F6: https://africanmarketingconfederation.org/wp-admin/post.php?post=28165&action=elementor | G6: African Marketing Confederation Tourism Chapter | H6: Skip to content African Marketing Confederation Tourism Chapter Shaping Africa’s Tourism Narrative Through Strategic Marketing Tourism is one of Africa’s most powerful economic engines – generating jobs, stimulating investment, and fostering cultural... | I6: African Marketing Confederation Tourism Chapter – African Marketing Confederation | L6: African Marketing Confederation Tourism Chapter Shaping Africa’s Tourism Narrative Through Strategic Marketing Tourism is one of Africa’s most powerful economic engines - generating jobs, stimulating investment, and fostering cultural exchange.The African Marketing Confederation is proud to launch the Tourism Chapter, a bold initiative to elevate African tourism through the lens of world-class marketing. Launched at the | O6: H1: African Marketing Confederation Tourism Chapter H3: Shaping Africa’s Tourism Narrative Through Strategic Marketing H2: Charting the Course: Purpose, Mission & Vision for Africa’s Tourism Future H2: Our Goals and Objectives: | S6: https://africanmarketingconfederation.org/wp-content/uploads/2026/03/og-image.png | V6: 25 | W6: 0 | X6: 100 | Y6: Open
A7: Needs Copy | B7: To Do | C7: Unassigned | D7: amc-awards-2024-amc-awards-{n}-–-african | E7: https://africanmarketingconfederation.org/amc-awards-2024 | F7: https://africanmarketingconfederation.org/wp-admin/post.php?post=16125&action=elementor | G7: Amc Awards 2024 | H7: English Français Português Español Igbo Deutsch Kiswahili ພາສາລາວ العربية Afsoomaali Sesotho 简体中文 Русский Zulu en NOMINATIONS are Open ! AMC Awards The African Marketing Confederation Awards event is held annually as part of the African Marketing Con... | I7: AMC Awards 2024 – African Marketing Confederation | L7: NOMINATIONS are Open ! AMC Awards The African Marketing Confederation Awards event is held annually as part of the African Marketing Confederation Forum. This distinguished event celebrates and acknowledges outstanding marketing campaigns and the visionary individuals behind them. The awards presented honor not only the groundbreaking strategies and creative brilliance that set these campaigns apart but | O7: H1: NOMINATIONS are Open ! H2: Awards Categories H2: Tourism & Destination Marketing Campaign H2: of the Year H2: Best Social Media Campaign of the Year H2: Best Social Media Campaign | S7: https://africanmarketingconfederation.org/wp-content/uploads/2021/08/amc_faw.png | V7: 25 | W7: 0 | X7: 100 | Y7: Open
A8: Needs Copy | B8: To Do | C8: Unassigned | D8: amc-conference-2022-amc-conference-{n}-–-afr | E8: https://africanmarketingconfederation.org/amc-conference-2022 | F8: https://africanmarketingconfederation.org/wp-admin/post.php?post=4494&action=elementor | G8: Amc Conference 2022 | H8: AMC officially welcomes new member associations into the fold October 8, 2024 No Comments Angola, Botswana, Ethiopia, Mozambique and Tanzania receive their membership certificates. AMC now has 16 members. Read More » | I8: AMC Conference 2022 – African Marketing Confederation | L8: corinna kopf onlyfans leaks AMC Conference 2022 Thank you for attending19 - 22 October 2022 The African Marketing Confederation's Annual Conference brought together the best collection of marketing leaders from top companies, marketing bodies and associations to share tactics and best practices on how to build the next generation of marketing. Event Highlights Thank you for Attending! | O8: H2: AMC Conference 2022 H2: Event Highlights H3: AMC officially welcomes new member associations into the fold H3: Marketers are placing the ads where consumers don’t want to see them H3: Time for Africa to control its own narrative and image, delegates told H3: Excitement as Ghana announced as host of 2025 AMC marketing conference | S8: https://africanmarketingconfederation.org/wp-content/uploads/2026/03/og-image.png | V8: 11.25 | W8: 0 | X8: 45 | Y8: Open
A9: Needs Copy | B9: To Do | C9: Unassigned | D9: amc-conference-2022-prospectus-amc-conference-{n}-–-pro | E9: https://africanmarketingconfederation.org/amc-conference-2022-prospectus | F9: https://africanmarketingconfederation.org/wp-admin/post.php?post=5619&action=elementor | G9: Amc Conference 2022 Prospectus | H9: Skip to content AMC Conference 2022 23 - 24 March 2022 Navigating Africa’s Unique Marketing Mix BOOK NOW 00 Days 00 Hours 00 Minutes 00 Seconds download prospectus To download the AMC 2022 Conference Prospectus please complete the form below: First ... | I9: AMC Conference 2022 – Prospectus – African Marketing Confederation | L9: AMC Conference 2022 23 - 24 March 2022 Navigating Africa's Unique Marketing Mix BOOK NOW Days Hours Minutes Seconds download prospectus To download the AMC 2022 Conference Prospectus please complete the form below: First Name Last Name Email Mobile Company I've read and agree to the Privacy Policy BOOK NOW FOR THE AMC CONFERENCE 2022 | O9: H2: AMC Conference 2022 H2: download prospectus H2: BOOK NOW FOR THE AMC CONFERENCE 2022 | S9: https://africanmarketingconfederation.org/wp-content/uploads/2026/03/og-image.png | V9: 11.25 | W9: 0 | X9: 45 | Y9: Open
A10: Needs Copy | B10: To Do | C10: Unassigned | D10: amc-conference-2022-thank-you-amc-conference-{n}-–-tha | E10: https://africanmarketingconfederation.org/amc-conference-2022-thank-you | F10: https://africanmarketingconfederation.org/wp-admin/post.php?post=4941&action=elementor | G10: Amc Conference 2022 Thank You | H10: Skip to content AMC Conference 2022 23 - 24 March 2022 Navigating Africa’s Unique Marketing Mix ENQUIRE NOW 00 Days 00 Hours 00 Minutes 00 Seconds Success! Thank you for completing the enquiry form. Our team will contact you shortly! × The AMC Confer... | I10: AMC Conference 2022 – Thank You – African Marketing Confederation | L10: AMC Conference 2022 23 - 24 March 2022 Navigating Africa's Unique Marketing Mix ENQUIRE NOW Days Hours Minutes Seconds Success! Thank you for completing the enquiry form. Our team will contact you shortly! × Dismiss alert The AMC Conference is the must attend Pan African event for marketing professionals. It will focus on solutions for | O10: H2: AMC Conference 2022 H2: WHO SHOULD ATTEND H2: Countries Participating H3: South Africa H3: Nigeria H3: Morocco | S10: https://africanmarketingconfederation.org/wp-content/uploads/2026/03/og-image.png | V10: 17.5 | W10: 0 | X10: 70 | Y10: Open
A11: Needs Copy | B11: To Do | C11: Unassigned | D11: amc-conference-2023-amc-conference-{n}-–-afr | E11: https://africanmarketingconfederation.org/amc-conference-2023 | F11: https://africanmarketingconfederation.org/wp-admin/post.php?post=12371&action=elementor | G11: Amc Conference 2023 | H11: AMC Conference 6 - 9 September 2023 Imperial Botanical Beach Hotel, Entebbe, Uganda Thank you for joining us! View Presentations 2nd Annual African Marketing Confederation Conference Africa's $3.4 trillion Economy: Opportunities for Marketers Welcome... | I11: AMC Conference 2023 – African Marketing Confederation | L11: AMC Conference 6 - 9 September 2023 Imperial Botanical Beach Hotel, Entebbe, Uganda Thank you for joining us! View Presentations 2nd Annual African Marketing Confederation Conference Africa's $3.4 trillion Economy: Opportunities for Marketers Welcome to the Recap of the 2nd Annual African Marketing Conference: Unveiling Africa's $3.4 Trillion EconomyOur conference was a remarkable exploration of | O11: H1: AMC Conference H2: Africa's $3.4 trillion Economy: Opportunities for Marketers H2: Thank you for joining us! H2: Topics covered H3: Africa Free Trade Area H3: Business Intelligence | S11: https://africanmarketingconfederation.org/wp-content/uploads/2021/08/amc_faw.png | V11: 25 | W11: 0 | X11: 100 | Y11: Open
A12: Needs Copy | B12: To Do | C12: Unassigned | D12: amc-conference-2023-amc-awards-–-african-mar | E12: https://africanmarketingconfederation.org/amc-conference-2023/amc-awards | F12: https://africanmarketingconfederation.org/wp-admin/post.php?post=12954&action=elementor | G12: Amc Awards | H12: Skip to content AMC Awards Welcome to the prestigious African Marketing Confederation Awards, a distinguished event that celebrates and acknowledges the remarkable achievements, cutting-edge innovations, and exceptional leadership demonstrated by out... | I12: AMC Awards – African Marketing Confederation | L12: AMC Awards Welcome to the prestigious African Marketing Confederation Awards, a distinguished event that celebrates and acknowledges the remarkable achievements, cutting-edge innovations, and exceptional leadership demonstrated by outstanding individuals within the dynamic realm of marketing across the expansive African region.During the 2nd Annual African Marketing Confederation Conference, held from 6th to 9th September at the | O12: H1: AMC Awards H2: AMC AWARD Winners | S12: https://africanmarketingconfederation.org/wp-content/uploads/2021/08/amc_faw.png | V12: 25 | W12: 0 | X12: 100 | Y12: Open
A13: Needs Copy | B13: To Do | C13: Unassigned | D13: amc-conference-2023-amc-awards-|-book-now-–- | E13: https://africanmarketingconfederation.org/amc-conference-2023/amc-awards-book-now | F13: https://africanmarketingconfederation.org/wp-admin/post.php?post=13164&action=elementor | G13: Amc Awards Book Now | H13: Skip to content English Français Português Español Igbo Deutsch Kiswahili ພາສາລາວ العربية Afsoomaali Sesotho 简体中文 Русский Zulu en 0 Your Cart Your cart is empty Return to Shop Continue Shopping Notifications | I13: AMC Awards | Book Now – African Marketing Confederation | L13: MISSING DESCRIPTION | S13: https://africanmarketingconfederation.org/wp-content/uploads/2021/08/amc_faw.png | V13: 6.25 | W13: 0 | X13: 25 | Y13: Open

Sheet Quick Reference Guide
A1: Section | B1: Item | C1: Guideline | D1: Why It Matters | E1: BACK TO DASHBOARD | F1: BACK TO DASHBOARD_1
A2: [Meta Data Standards]
B3: Meta Title | C3: 50-60 characters. Place primary keyword at the front. Avoid brand repetition unless there is space. | D3: Improves clarity and reduces SERP truncation risk.
B4: Meta Description | C4: 120-160 characters. Must contain a clear Call-To-Action (CTA) and active verbs. | D4: Supports stronger click-through and intent alignment.
B5: Target Keywords | C5: 1 Primary, 2 Secondary per page. Do not keyword stuff; focus on user intent. | D5: Keeps copy focused on topical relevance over keyword density.
A7: [On-Page Structure (H-Tags)]
B8: H1 Tag | C8: Exactly ONE per page. Must contain the primary topic/keyword. Think of it as the 'Book Title'. | D8: Provides the clearest top-level topical signal.
B9: H2 Tags | C9: Main sections. Use question formats (Who, What, How) to trigger Answer Engine extraction. | D9: Improves structured scannability for users and LLMs.
B10: H3 Tags | C10: Sub-sections under H2s. Use for lists, steps, or detailed breakdowns. | D10: Strengthens hierarchy and supports extraction-ready formatting.
B11: H4-H6 Tags | C11: Use sparingly. Only for granular formatting within complex H3 topics. | D11: Avoids over-nesting while preserving semantic structure.
A13: [AEO (Answer Engine Optimization) & Content]
B14: AEO Answer Blocks | C14: 40-60 words. Placed directly beneath an H2 question. Must be factual, objective, and devoid of marketing fluff (e.g., 'The best way to...'). | D14: Optimizes direct extraction for answer engines and voice search.
B15: FAQ Schema | C15: Minimum 2-3 questions per informational page. Answers must be direct and stand alone without needing the rest of the page for context. | D15: Improves machine readability and rich-answer eligibility.
B16: Content Readability | C16: Keep sentences under 20 words. Use bullet points for any list of 3 or more items. | D16: Increases comprehension and snippet usability.
A18: [Visual & Social Branding]
B19: OG Image | C19: 1200 x 630 pixels. Keep text centered (safe zone) so it isn't cropped by mobile devices on LinkedIn/X. | D19: Ensures consistent social card presentation.
B20: Social Share Note | C20: Customize the message for the platform. LinkedIn = Professional insight. X (Twitter) = Quick hook. Facebook = Conversational. | D20: Improves engagement by matching platform context.

Sheet FixPlan
A1: Issue Type | B1: Severity | C1: Priority Score | D1: Affected Count | E1: Affected URLs | F1: Detail Reference Tab | G1: Resolution Type | H1: URL | I1: Recommended Fix | J1: Likely Root Cause | K1: Owner | L1: Agency Owner | M1: Effort | N1: Est. Hours | O1: Est. Sprint Points | P1: Aging/Priority | Q1: Status | R1: Verified By | S1: Date Resolved | T1: Revenue Risk | U1: Action Needed | V1: Jump to Details | W1: Sprint | X1: Category | Y1: Fix Type | Z1: Estimated Traffic Impact | AA1: Fix Effort | AB1: ROI Score | AC1: Exact Action | AD1: Open in Main | AE1: Hub Status (Content Hub) | AF1: BACK TO DASHBOARD | AG1: BACK TO DASHBOARD_1
A2: Non-200 Status | B2: Critical | C2: 105 | D2: 0 | F2: Technical | G2: Manual Content | I2: Fix status code, restore page, or implement correct redirect to canonical destination. | J2: URL returns 4xx/5xx or equivalent failure. | K2: Server/Host | L2: Server/Host | M2: M | N2: 10 | O2: 5 | P2: Immediate (Current Sprint) | Q2: To Do | T2: High Risk | U2: Yes | V2: Open in Main Tab | X2: SEO | Y2: Technical | Z2: Low | AA2: 10 | AB2: 0 | AC2: Resolve 'Non-200 Status' using technical best practices and validate in the related detail tab. | AD2: Open | AE2: =IFERROR(INDEX('Content Optimization Hub'!A:A,MATCH(H2,'Content Optimization Hub'!C:C,0)),"Not in Hub")
A3: Missing Title | B3: Critical | C3: 105 | D3: 0 | F3: Technical | G3: Manual Content | I3: Add unique descriptive title on affected template/page type. | J3: Template/page missing title tag. | K3: Copy Writer | L3: Copy Writer | M3: M | N3: 10 | O3: 5 | P3: Immediate (Current Sprint) | Q3: To Do | T3: High Risk | U3: Yes | V3: Open in Main Tab | X3: SEO | Y3: Content | Z3: Low | AA3: 10 | AB3: 0 | AC3: Resolve 'Missing Title' using content best practices and validate in the related detail tab. | AD3: Open | AE3: =IFERROR(INDEX('Content Optimization Hub'!A:A,MATCH(H3,'Content Optimization Hub'!C:C,0)),"Not in Hub")
A4: Noindex Directive | B4: Critical | C4: 105 | D4: 0 | F4: Indexability | G4: Manual Content | I4: Remove unintended noindex directives on index-worthy URLs. | J4: Meta robots or X-Robots-Tag contains noindex. | K4: Dev | L4: Dev | M4: M | N4: 10 | O4: 5 | P4: Immediate (Current Sprint) | Q4: To Do | T4: High Risk | U4: Yes | V4: Open in Main Tab | X4: SEO | Y4: Technical | Z4: Low | AA4: 10 | AB4: 0 | AC4: Resolve 'Noindex Directive' using technical best practices and validate in the related detail tab. | AD4: Open | AE4: =IFERROR(INDEX('Content Optimization Hub'!A:A,MATCH(H4,'Content Optimization Hub'!C:C,0)),"Not in Hub")
A5: Canonical Points Elsewhere | B5: Critical | C5: 105 | D5: 0 | F5: Indexability | G5: Global Template | I5: Align canonical to preferred final URL and ensure internal links use canonical target. | J5: Canonical targets a different URL variant. | K5: Dev | L5: Dev | M5: M | N5: 10 | O5: 5 | P5: Immediate (Current Sprint) | Q5: To Do | T5: High Risk | U5: Yes | V5: Open in Main Tab | X5: SEO | Y5: Technical | Z5: Low | AA5: 10 | AB5: 0 | AC5: Resolve 'Canonical Points Elsewhere' using technical best practices and validate in the related detail tab. | AD5: Open | AE5: =IFERROR(INDEX('Content Optimization Hub'!A:A,MATCH(H5,'Content Optimization Hub'!C:C,0)),"Not in Hub")
A6: Robots.txt Disallow Root | B6: Critical | C6: 105 | D6: 0 | F6: Technical | G6: Global Template | I6: Apply fix based on issue type and re-run audit. | J6: Template/technical implementation quality issue. | K6: Server/Host | L6: Server/Host | M6: M | N6: 10 | O6: 5 | P6: Immediate (Current Sprint) | Q6: To Do | T6: High Risk | U6: Yes | V6: Open in Main Tab | X6: SEO | Y6: Content | Z6: Low | AA6: 10 | AB6: 0 | AC6: Resolve 'Robots.txt Disallow Root' using content best practices and validate in the related detail tab. | AD6: Open | AE6: =IFERROR(INDEX('Content Optimization Hub'!A:A,MATCH(H6,'Content Optimization Hub'!C:C,0)),"Not in Hub")
A7: CWV LCP Above 4.0s | B7: Critical | C7: 105 | D7: 0 | F7: Technical | G7: Global Template | I7: Apply fix based on issue type and re-run audit. | J7: Template/technical implementation quality issue. | K7: Dev | L7: Dev | M7: M | N7: 10 | O7: 5 | P7: Immediate (Current Sprint) | Q7: To Do | T7: High Risk | U7: Yes | V7: Open in Main Tab | X7: SEO | Y7: Content | Z7: Low | AA7: 10 | AB7: 0 | AC7: Resolve 'CWV LCP Above 4.0s' using content best practices and validate in the related detail tab. | AD7: Open | AE7: =IFERROR(INDEX('Content Optimization Hub'!A:A,MATCH(H7,'Content Optimization Hub'!C:C,0)),"Not in Hub")
A8: Broken Internal Links | B8: Critical | C8: 105 | D8: 0 | F8: Links | G8: Manual Content | I8: Update internal links to valid URLs and remove dead references. | J8: Internal links resolve to missing or error pages. | K8: Dev | L8: Dev | M8: M | N8: 10 | O8: 5 | P8: Immediate (Current Sprint) | Q8: To Do | T8: High Risk | U8: Yes | V8: Open in Main Tab | X8: SEO | Y8: Content | Z8: Low | AA8: 10 | AB8: 0 | AC8: Resolve 'Broken Internal Links' using content best practices and validate in the related detail tab. | AD8: Open | AE8: =IFERROR(INDEX('Content Optimization Hub'!A:A,MATCH(H8,'Content Optimization Hub'!C:C,0)),"Not in Hub")
A9: Redirect Chains | B9: Warning | C9: 67 | D9: 0 | F9: Technical | G9: Global Template | I9: Apply fix based on issue type and re-run audit. | J9: Template/technical implementation quality issue. | K9: Dev | L9: Dev | M9: S | N9: 4 | O9: 2 | P9: Next Sprint | Q9: To Do | T9: Medium Risk | U9: Yes | V9: Open in Main Tab | X9: SEO | Y9: Technical | Z9: Low | AA9: 4 | AB9: 0 | AC9: Resolve 'Redirect Chains' using technical best practices and validate in the related detail tab. | AD9: Open | AE9: =IFERROR(INDEX('Content Optimization Hub'!A:A,MATCH(H9,'Content Optimization Hub'!C:C,0)),"Not in Hub")
A10: Missing Meta Description | B10: Warning | C10: 67 | D10: 0 | F10: Technical | G10: Manual Content | I10: Add concise unique description aligned with user intent. | J10: Meta description missing or empty. | K10: Copy Writer | L10: Copy Writer | M10: S | N10: 4 | O10: 2 | P10: Next Sprint | Q10: To Do | T10: Medium Risk | U10: Yes | V10: Open in Main Tab | X10: SEO | Y10: Content | Z10: Low | AA10: 4 | AB10: 0 | AC10: Resolve 'Missing Meta Description' using content best practices and validate in the related detail tab. | AD10: Open | AE10: =IFERROR(INDEX('Content Optimization Hub'!A:A,MATCH(H10,'Content Optimization Hub'!C:C,0)),"Not in Hub")
A11: Missing H1 | B11: Warning | C11: 67 | D11: 0 | F11: Technical | G11: Manual Content | I11: Apply fix based on issue type and re-run audit. | J11: Template/technical implementation quality issue. | K11: Copy Writer | L11: Copy Writer | M11: S | N11: 4 | O11: 2 | P11: Next Sprint | Q11: To Do | T11: Medium Risk | U11: Yes | V11: Open in Main Tab | X11: SEO | Y11: Content | Z11: Low | AA11: 4 | AB11: 0 | AC11: Resolve 'Missing H1' using content best practices and validate in the related detail tab. | AD11: Open | AE11: =IFERROR(INDEX('Content Optimization Hub'!A:A,MATCH(H11,'Content Optimization Hub'!C:C,0)),"Not in Hub")
A12: Multiple H1 | B12: Warning | C12: 67 | D12: 0 | F12: Technical | G12: Manual Content | I12: Apply fix based on issue type and re-run audit. | J12: Template/technical implementation quality issue. | K12: Copy Writer | L12: Copy Writer | M12: S | N12: 4 | O12: 2 | P12: Next Sprint | Q12: To Do | T12: Medium Risk | U12: Yes | V12: Open in Main Tab | X12: SEO | Y12: Content | Z12: Low | AA12: 4 | AB12: 0 | AC12: Resolve 'Multiple H1' using content best practices and validate in the related detail tab. | AD12: Open | AE12: =IFERROR(INDEX('Content Optimization Hub'!A:A,MATCH(H12,'Content Optimization Hub'!C:C,0)),"Not in Hub")
A13: CWV LCP Needs Improvement (2.5-4.0s) | B13: Warning | C13: 67 | D13: 0 | F13: Technical | G13: Global Template | I13: Apply fix based on issue type and re-run audit. | J13: Template/technical implementation quality issue. | K13: Copy Writer | L13: Copy Writer | M13: S | N13: 4 | O13: 2 | P13: Next Sprint | Q13: To Do | T13: Medium Risk | U13: Yes | V13: Open in Main Tab | X13: SEO | Y13: Content | Z13: Low | AA13: 4 | AB13: 0 | AC13: Resolve 'CWV LCP Needs Improvement (2.5-4.0s)' using content best practices and validate in the related detail tab. | AD13: Open | AE13: =IFERROR(INDEX('Content Optimization Hub'!A:A,MATCH(H13,'Content Optimization Hub'!C:C,0)),"Not in Hub")
... A35: AI Crawlers Not Explicitly Allowed | B35: Observation | C35: 37 | D35: 0 | F35: Technical | G35: Manual Content | I35: Apply fix based on issue type and re-run audit. | J35: Template/technical implementation quality issue. | K35: Copy Writer | L35: Copy Writer | M35: S | N35: 4 | O35: 2 | P35: Backlog | Q35: In Review | T35: Monitor | U35: No | V35: Open in Main Tab | X35: SEO | Y35: Content | Z35: Low | AA35: 4 | AB35: 0 | AC35: Resolve 'AI Crawlers Not Explicitly Allowed' using content best practices and validate in the related detail tab. | AD35: Open | AE35: =IFERROR(INDEX('Content Optimization Hub'!A:A,MATCH(H35,'Content Optimization Hub'!C:C,0)),"Not in Hub")

Sheet Main
A1: Health Icon | B1: URL | C1: Status Code | D1: Indexability | E1: Load Time (s) | F1: Title | G1: Meta Description | H1: Word Count (Body) | I1: SEO Health Score | J1: Severity Badge | K1: Extraction State | L1: Extraction Source | M1: Title Length | N1: Meta Desc Length | O1: OG-Image | P1: Has Valid JSON-LD | Q1: H1 Content | R1: H1 Length | S1: H2 Content | T1: H2 Length | U1: H3 Content | V1: H3 Length | W1: H4 Content | X1: H4 Length | Y1: H5 Content | Z1: H5 Length | AA1: H6 Content | AB1: H6 Length | AC1: CWV LCP (s) | AD1: CWV CLS | AE1: Field vs Lab | AF1: Regional Authority Score | AG1: Desktop PSI Score | AH1: Mobile PSI Score | AI1: Mobile LCP (s) | AJ1: Mobile CLS | AK1: Mobile TTFB (s) | AL1: GSC Clicks | AM1: GSC Impressions | AN1: GSC CTR | AO1: GSC Avg Position | AP1: Click Depth | AQ1: Orphan Pages | AR1: Internal PageRank | AS1: Found via Sitemap | AT1: Found via Crawl | AU1: Discovery Source | AV1: Technical Health | AW1: Copy Score | AX1: SEO Score | AY1: Technical View | AZ1: BACK TO DASHBOARD | BA1: Technical View_1 | BB1: BACK TO DASHBOARD_1
A2: UNMEASURED | B2: https://africanmarketingconfederation.org/ | C2: 200 | D2: Indexable | E2: 2.214 | F2: African Marketing Confederation - Uniting Marketers for Excellence | G2: The African Marketing Confederation is the ground-breaking Pan-African body driving the development of top marketing standards across Africa and beyond. | H2: 35 | J2: Unmeasured | K2: partial | L2: rendered_browser | M2: 66 | N2: 152 | O2: https://africanmarketingconfederation.org/wp-content/uploads/2026/03/og-image.png | P2: FALSE | R2: 0 | T2: 0 | V2: 0 | X2: 0 | Z2: 0 | AB2: 0 | AC2: 0 | AE2: Lab | AF2: 100 | AG2: 0 | AH2: 0 | AI2: 0 | AJ2: 0 | AK2: 0 | AL2: 60 | AM2: 1108 | AN2: 0.054151625 | AO2: 5.9296029 | AP2: 0 | AQ2: FALSE | AR2: 0.287449 | AS2: TRUE | AT2: TRUE | AU2: Both | AV2: 0 | AW2: 75 | AX2: 18.75 | AY2: Open Technical | BA2: =IFERROR(HYPERLINK("#Technical!A"&MATCH(B2,Technical!A:A,0),"Open Technical"),HYPERLINK("#Technical!A1","Open Technical"))
A3: UNMEASURED | B3: https://africanmarketingconfederation.org/about-us | C3: 200 | D3: Indexable | E3: 0.085 | F3: African Marketing Confederation – The Leading Marketing Professional Body – African Marketing Confederation | G3: ABOUT The African Marketing Confederation The African Marketing Confederation is the ground-breaking Pan African body of marketing professionals spearheading the ongoing development of the highest possible standards of marketing across Africa. Founded in 2011, the AMC is a collaboration between the African national marketing bodies and associations to exchange expertise and information, and to promote | H3: 235 | J3: Unmeasured | K3: partial | L3: rendered_browser | M3: 107 | N3: 405 | O3: https://africanmarketingconfederation.org/wp-content/uploads/2026/03/og-image.png | P3: FALSE | R3: 0 | T3: 0 | V3: 0 | X3: 0 | Z3: 0 | AB3: 0 | AC3: 0 | AE3: Lab | AF3: 70 | AG3: 0 | AH3: 0 | AI3: 0 | AJ3: 0 | AK3: 0 | AL3: 7 | AM3: 200 | AN3: 0.035 | AO3: 3.255 | AP3: 1 | AQ3: FALSE | AR3: 0.271899 | AS3: TRUE | AT3: TRUE | AU3: Both | AV3: 0 | AW3: 75 | AX3: 18.75 | AY3: Open Technical | BA3: =IFERROR(HYPERLINK("#Technical!A"&MATCH(B3,Technical!A:A,0),"Open Technical"),HYPERLINK("#Technical!A1","Open Technical"))
A4: UNMEASURED | B4: https://africanmarketingconfederation.org/african-marketing-confederation-tourism-chapter | C4: 200 | D4: Indexable | E4: 0.086 | F4: African Marketing Confederation Tourism Chapter – African Marketing Confederation | G4: African Marketing Confederation Tourism Chapter Shaping Africa’s Tourism Narrative Through Strategic Marketing Tourism is one of Africa’s most powerful economic engines - generating jobs, stimulating investment, and fostering cultural exchange.The African Marketing Confederation is proud to launch the Tourism Chapter, a bold initiative to elevate African tourism through the lens of world-class marketing. Launched at the | H4: 355 | J4: Unmeasured | K4: partial | L4: rendered_browser | M4: 81 | N4: 423 | O4: https://africanmarketingconfederation.org/wp-content/uploads/2026/03/og-image.png | P4: FALSE | R4: 0 | T4: 0 | V4: 0 | X4: 0 | Z4: 0 | AB4: 0 | AC4: 0 | AE4: Lab | AF4: 60 | AG4: 0 | AH4: 0 | AI4: 0 | AJ4: 0 | AK4: 0 | AL4: 0 | AM4: 8 | AN4: 0 | AO4: 5 | AP4: 1 | AQ4: FALSE | AR4: 0.271899 | AS4: TRUE | AT4: TRUE | AU4: Both | AV4: 0 | AW4: 100 | AX4: 25 | AY4: Open Technical | BA4: =IFERROR(HYPERLINK("#Technical!A"&MATCH(B4,Technical!A:A,0),"Open Technical"),HYPERLINK("#Technical!A1","Open Technical"))
A5: UNMEASURED | B5: https://africanmarketingconfederation.org/amc-awards-2024 | C5: 200 | D5: Indexable | E5: 0.078 | F5: AMC Awards 2024 – African Marketing Confederation | G5: NOMINATIONS are Open ! AMC Awards The African Marketing Confederation Awards event is held annually as part of the African Marketing Confederation Forum. This distinguished event celebrates and acknowledges outstanding marketing campaigns and the visionary individuals behind them. The awards presented honor not only the groundbreaking strategies and creative brilliance that set these campaigns apart but | H5: 1668 | J5: Unmeasured | K5: partial | L5: rendered_browser | M5: 49 | N5: 406 | O5: https://africanmarketingconfederation.org/wp-content/uploads/2021/08/amc_faw.png | P5: FALSE | R5: 0 | T5: 0 | V5: 0 | X5: 0 | Z5: 0 | AB5: 0 | AC5: 0 | AE5: Lab | AF5: 100 | AG5: 0 | AH5: 0 | AI5: 0 | AJ5: 0 | AK5: 0 | AL5: 0 | AM5: 0 | AN5: 0 | AO5: 0 | AQ5: TRUE | AR5: 0.019665 | AS5: TRUE | AT5: TRUE | AU5: Both | AV5: 0 | AW5: 100 | AX5: 25 | AY5: Open Technical | BA5: =IFERROR(HYPERLINK("#Technical!A"&MATCH(B5,Technical!A:A,0),"Open Technical"),HYPERLINK("#Technical!A1","Open Technical"))
A6: UNMEASURED | B6: https://africanmarketingconfederation.org/amc-conference-2022 | C6: 200 | D6: Indexable | E6: 2.318 | F6: AMC Conference 2022 – African Marketing Confederation | G6: corinna kopf onlyfans leaks AMC Conference 2022 Thank you for attending19 - 22 October 2022 The African Marketing Confederation's Annual Conference brought together the best collection of marketing leaders from top companies, marketing bodies and associations to share tactics and best practices on how to build the next generation of marketing. Event Highlights Thank you for Attending! | H6: 32 | J6: Unmeasured | K6: partial | L6: rendered_browser | M6: 53 | N6: 387 | O6: https://africanmarketingconfederation.org/wp-content/uploads/2026/03/og-image.png | P6: FALSE | R6: 0 | T6: 0 | V6: 0 | X6: 0 | Z6: 0 | AB6: 0 | AC6: 0 | AE6: Lab | AF6: 100 | AG6: 0 | AH6: 0 | AI6: 0 | AJ6: 0 | AK6: 0 | AL6: 0 | AM6: 10 | AN6: 0 | AO6: 6.1 | AQ6: TRUE | AR6: 0.019665 | AS6: TRUE | AT6: TRUE | AU6: Both | AV6: 0 | AW6: 45 | AX6: 11.25 | AY6: Open Technical | BA6: =IFERROR(HYPERLINK("#Technical!A"&MATCH(B6,Technical!A:A,0),"Open Technical"),HYPERLINK("#Technical!A1","Open Technical"))
A7: UNMEASURED | B7: https://africanmarketingconfederation.org/amc-conference-2022-prospectus | C7: 200 | D7: Indexable | E7: 3.629 | F7: AMC Conference 2022 – Prospectus – African Marketing Confederation | G7: AMC Conference 2022 23 - 24 March 2022 Navigating Africa's Unique Marketing Mix BOOK NOW Days Hours Minutes Seconds download prospectus To download the AMC 2022 Conference Prospectus please complete the form below: First Name Last Name Email Mobile Company I've read and agree to the Privacy Policy BOOK NOW FOR THE AMC CONFERENCE 2022 | H7: 120 | J7: Unmeasured | K7: partial | L7: rendered_browser | M7: 66 | N7: 335 | O7: https://africanmarketingconfederation.org/wp-content/uploads/2026/03/og-image.png | P7: FALSE | R7: 0 | T7: 0 | V7: 0 | X7: 0 | Z7: 0 | AB7: 0 | AC7: 0 | AE7: Lab | AF7: 30 | AG7: 0 | AH7: 0 | AI7: 0 | AJ7: 0 | AK7: 0 | AL7: 0 | AM7: 0 | AN7: 0 | AO7: 0 | AQ7: TRUE | AR7: 0.019665 | AS7: TRUE | AT7: TRUE | AU7: Both | AV7: 0 | AW7: 45 | AX7: 11.25 | AY7: Open Technical | BA7: =IFERROR(HYPERLINK("#Technical!A"&MATCH(B7,Technical!A:A,0),"Open Technical"),HYPERLINK("#Technical!A1","Open Technical"))
A8: UNMEASURED | B8: https://africanmarketingconfederation.org/amc-conference-2022-thank-you | C8: 200 | D8: Indexable | E8: 3.88 | F8: AMC Conference 2022 – Thank You – African Marketing Confederation | G8: AMC Conference 2022 23 - 24 March 2022 Navigating Africa's Unique Marketing Mix ENQUIRE NOW Days Hours Minutes Seconds Success! Thank you for completing the enquiry form. Our team will contact you shortly! × Dismiss alert The AMC Conference is the must attend Pan African event for marketing professionals. It will focus on solutions for | H8: 367 | J8: Unmeasured | K8: partial | L8: rendered_browser | M8: 65 | N8: 337 | O8: https://africanmarketingconfederation.org/wp-content/uploads/2026/03/og-image.png | P8: FALSE | R8: 0 | T8: 0 | V8: 0 | X8: 0 | Z8: 0 | AB8: 0 | AC8: 0 | AE8: Lab | AF8: 100 | AG8: 0 | AH8: 0 | AI8: 0 | AJ8: 0 | AK8: 0 | AL8: 0 | AM8: 0 | AN8: 0 | AO8: 0 | AQ8: TRUE | AR8: 0.019665 | AS8: TRUE | AT8: TRUE | AU8: Both | AV8: 0 | AW8: 70 | AX8: 17.5 | AY8: Open Technical | BA8: =IFERROR(HYPERLINK("#Technical!A"&MATCH(B8,Technical!A:A,0),"Open Technical"),HYPERLINK("#Technical!A1","Open Technical"))
A9: UNMEASURED | B9: https://africanmarketingconfederation.org/amc-conference-2023 | C9: 200 | D9: Indexable | E9: 3.016 | F9: AMC Conference 2023 – African Marketing Confederation | G9: AMC Conference 6 - 9 September 2023 Imperial Botanical Beach Hotel, Entebbe, Uganda Thank you for joining us! View Presentations 2nd Annual African Marketing Confederation Conference Africa's $3.4 trillion Economy: Opportunities for Marketers Welcome to the Recap of the 2nd Annual African Marketing Conference: Unveiling Africa's $3.4 Trillion EconomyOur conference was a remarkable exploration of | H9: 415 | J9: Unmeasured | K9: partial | L9: rendered_browser | M9: 53 | N9: 398 | O9: https://africanmarketingconfederation.org/wp-content/uploads/2021/08/amc_faw.png | P9: FALSE | R9: 0 | T9: 0 | V9: 0 | X9: 0 | Z9: 0 | AB9: 0 | AC9: 0 | AE9: Lab | AF9: 80 | AG9: 0 | AH9: 0 | AI9: 0 | AJ9: 0 | AK9: 0 | AL9: 1 | AM9: 24 | AN9: 0.041666667 | AO9: 14.583333 | AQ9: FALSE | AR9: 0.035214 | AS9: TRUE | AT9: TRUE | AU9: Both | AV9: 0 | AW9: 100 | AX9: 25 | AY9: Open Technical | BA9: =IFERROR(HYPERLINK("#Technical!A"&MATCH(B9,Technical!A:A,0),"Open Technical"),HYPERLINK("#Technical!A1","Open Technical"))
A10: UNMEASURED | B10: https://africanmarketingconfederation.org/amc-conference-2023/amc-awards | C10: 200 | D10: Indexable | E10: 2.673 | F10: AMC Awards – African Marketing Confederation | G10: AMC Awards Welcome to the prestigious African Marketing Confederation Awards, a distinguished event that celebrates and acknowledges the remarkable achievements, cutting-edge innovations, and exceptional leadership demonstrated by outstanding individuals within the dynamic realm of marketing across the expansive African region.During the 2nd Annual African Marketing Confederation Conference, held from 6th to 9th September at the | H10: 326 | J10: Unmeasured | K10: partial | L10: rendered_browser | M10: 44 | N10: 432 | O10: https://africanmarketingconfederation.org/wp-content/uploads/2021/08/amc_faw.png | P10: FALSE | R10: 0 | T10: 0 | V10: 0 | X10: 0 | Z10: 0 | AB10: 0 | AC10: 0 | AE10: Lab | AF10: 40 | AG10: 0 | AH10: 0 | AI10: 0 | AJ10: 0 | AK10: 0 | AL10: 2 | AM10: 34 | AN10: 0.058823529 | AO10: 4.2352941 | AQ10: FALSE | AR10: 0.035214 | AS10: TRUE | AT10: TRUE | AU10: Both | AV10: 0 | AW10: 100 | AX10: 25 | AY10: Open Technical | BA10: =IFERROR(HYPERLINK("#Technical!A"&MATCH(B10,Technical!A:A,0),"Open Technical"),HYPERLINK("#Technical!A1","Open Technical"))
A11: UNMEASURED | B11: https://africanmarketingconfederation.org/amc-conference-2023/amc-awards-book-now | C11: 200 | D11: Indexable | E11: 2.668 | F11: AMC Awards | Book Now – African Marketing Confederation | H11: 31 | J11: Unmeasured | K11: partial | L11: rendered_browser | M11: 55 | N11: 0 | O11: https://africanmarketingconfederation.org/wp-content/uploads/2021/08/amc_faw.png | P11: FALSE | R11: 0 | T11: 0 | V11: 0 | X11: 0 | Z11: 0 | AB11: 0 | AC11: 0 | AE11: Lab | AF11: 30 | AG11: 0 | AH11: 0 | AI11: 0 | AJ11: 0 | AK11: 0 | AL11: 0 | AM11: 0 | AN11: 0 | AO11: 0 | AQ11: TRUE | AR11: 0.019665 | AS11: TRUE | AT11: TRUE | AU11: Both | AV11: 0 | AW11: 25 | AX11: 6.25 | AY11: Open Technical | BA11: =IFERROR(HYPERLINK("#Technical!A"&MATCH(B11,Technical!A:A,0),"Open Technical"),HYPERLINK("#Technical!A1","Open Technical"))

Sheet Technical
A1: URL | B1: Status Code | C1: Status Class | D1: SEO Health Score | E1: Severity Badge | F1: Action Needed | G1: Indexability Reason | H1: TTFB (ms) | I1: Total Request Time (ms) | J1: Final URL | K1: Canonical URL | L1: Canonical Type | M1: Owner | N1: Status | O1: Sprint | P1: Extraction State | Q1: Extraction Source | R1: Health Icon | S1: SEO Score | T1: Technical Health | U1: Copy Score | V1: Protocol | W1: Redirect Chain Length | X1: Redirect Target | Y1: Redirect Hops | Z1: HTTP->HTTPS Redirect | AA1: Content-Type | AB1: HTTP Version | AC1: HTML Size (KB) | AD1: Compression Enabled | AE1: Cache-Control | AF1: ETag | AG1: X-Robots-Tag | AH1: Meta Robots Raw | AI1: Canonical Matches Final URL | AJ1: Canonical Absolute URL | AK1: Canonical in Sitemap Match | AL1: Hreflang Present | AM1: Hreflang Count | AN1: Hreflang Self Reference | AO1: Hreflang Reciprocal Check | AP1: Hreflang Canonical Consistency | AQ1: x-default Present | AR1: Pagination rel=next | AS1: Pagination rel=prev | AT1: Last-Modified | AU1: Published Date | AV1: Modified Date | AW1: Last Updated | AX1: Change Frequency | AY1: Priority | AZ1: Schema Types Count | BA1: Schema Types Found | BB1: Internal Links Count | BC1: Unique Internal Links Count | BD1: External Links Count | BE1: AI Crawlers Allowed (GPTBot/ClaudeBot/PerplexityBot) | BF1: llms.txt Present | BG1: Desktop PSI Score | BH1: Mobile PSI Score | BI1: Mobile LCP (s) | BJ1: Mobile CLS | BK1: Mobile TTFB (s) | BL1: CWV LCP (s) | BM1: CWV CLS | BN1: CWV Data Source | BO1: Field vs Lab | BP1: GSC Clicks | BQ1: GSC Impressions | BR1: GSC CTR | BS1: GSC Avg Position | BT1: Click Depth | BU1: Internal Inlinks | BV1: Orphan Pages | BW1: Internal PageRank | BX1: Regional Authority Score | BY1: Regional Entity Hits | BZ1: Answer Block Detected (First 60 Words) | CA1: AEO Extractability Score | CB1: Critical Issues Count | CC1: Warning Issues Count | CD1: Observation Issues Count | CE1: Inlinks Bucket | CF1: Important But Underlinked | CG1: SERP Title Truncation Risk | CH1: SERP Meta Truncation Risk | CI1: SERP Title Pixel Approx | CJ1: SERP Meta Pixel Approx | CK1: Cannibalization Hint | CL1: Stable Issue IDs | CM1: URL Depth | CN1: Param URL Flag | CO1: Open in Main | CP1: BACK TO DASHBOARD | CQ1: BACK TO DASHBOARD_1
A2: https://africanmarketingconfederation.org/ | B2: 200 | C2: 2xx | E2: Unmeasured | G2: Indexable | H2: 34.75 | I2: 36971.04 | J2: https://africanmarketingconfederation.org/ | K2: https://africanmarketingconfederation.org/ | L2: self | M2: Dev | N2: Open | P2: partial | Q2: rendered_browser | R2: UNMEASURED | S2: 18.75 | T2: 0 | U2: 75 | V2: https | W2: 0 | Z2: FALSE | AA2: text/html; charset=UTF-8 | AB2: HTTP/1.1 | AC2: 558.4 | AD2: TRUE | AE2: max-age=0 | AH2: max-image-preview:large | AI2: TRUE | AJ2: https://africanmarketingconfederation.org/ | AK2: TRUE | AL2: FALSE | AM2: 0 | AN2: FALSE | AQ2: FALSE | AR2: FALSE | AS2: FALSE | AW2: 2026-04-29T08:23:06+00:00 | AX2: always | AY2: 1 | AZ2: 0 | BB2: 63 | BC2: 22 | BD2: 2 | BE2: FALSE | BF2: TRUE | BG2: 0 | BH2: 0 | BI2: 0 | BJ2: 0 | BK2: 0 | BL2: 0 | BN2: Lab | BO2: Lab | BP2: 60 | BQ2: 1108 | BR2: 0.054151625 | BS2: 5.9296029 | BT2: 0 | BU2: 8 | BV2: FALSE | BW2: 0.287449 | BX2: 100 | BY2: 16 | BZ2: FALSE | CA2: Medium | CE2: 3-10 | CG2: FALSE | CH2: FALSE | CI2: 475 | CJ2: 942 | CM2: 0 | CN2: FALSE | CO2: Open
A3: https://africanmarketingconfederation.org/about-us | B3: 200 | C3: 2xx | E3: Unmeasured | G3: Indexable | H3: 84.99 | I3: 39053.33 | J3: https://africanmarketingconfederation.org/about-us | K3: https://africanmarketingconfederation.org/about-us | L3: self | M3: Dev | N3: Open | P3: partial | Q3: rendered_browser | R3: UNMEASURED | S3: 18.75 | T3: 0 | U3: 75 | V3: https | W3: 0 | Z3: FALSE | AA3: text/html; charset=UTF-8 | AB3: HTTP/1.1 | AC3: 321.92 | AD3: TRUE | AE3: max-age=0 | AH3: max-image-preview:large | AI3: TRUE | AJ3: https://africanmarketingconfederation.org/about-us | AK3: TRUE | AL3: FALSE | AM3: 0 | AN3: FALSE | AQ3: FALSE | AR3: FALSE | AS3: FALSE | AW3: 2026-04-17T08:53:24+00:00 | AX3: weekly | AY3: 0.7 | AZ3: 0 | BB3: 32 | BC3: 14 | BD3: 7 | BE3: FALSE | BF3: TRUE | BG3: 0 | BH3: 0 | BI3: 0 | BJ3: 0 | BK3: 0 | BL3: 0 | BN3: Lab | BO3: Lab | BP3: 7 | BQ3: 200 | BR3: 0.035 | BS3: 3.255 | BT3: 1 | BU3: 6 | BV3: FALSE | BW3: 0.271899 | BX3: 70 | BY3: 5 | BZ3: FALSE | CA3: Medium | CE3: 3-10 | CG3: FALSE | CH3: FALSE | CI3: 770 | CJ3: 2511 | CM3: 1 | CN3: FALSE | CO3: Open
A4: https://africanmarketingconfederation.org/african-marketing-confederation-tourism-chapter | B4: 200 | C4: 2xx | E4: Unmeasured | G4: Indexable | H4: 86 | I4: 39506.96 | J4: https://africanmarketingconfederation.org/african-marketing-confederation-tourism-chapter | K4: https://africanmarketingconfederation.org/african-marketing-confederation-tourism-chapter | L4: self | M4: Dev | N4: Open | P4: partial | Q4: rendered_browser | R4: UNMEASURED | S4: 25 | T4: 0 | U4: 100 | V4: https | W4: 0 | Z4: FALSE | AA4: text/html; charset=UTF-8 | AB4: HTTP/1.1 | AC4: 337.63 | AD4: TRUE | AE4: max-age=0 | AH4: max-image-preview:large | AI4: TRUE | AJ4: https://africanmarketingconfederation.org/african-marketing-confederation-tourism-chapter | AK4: TRUE | AL4: FALSE | AM4: 0 | AN4: FALSE | AQ4: FALSE | AR4: FALSE | AS4: FALSE | AW4: 2026-04-17T08:55:48+00:00 | AX4: weekly | AY4: 0.7 | AZ4: 0 | BB4: 58 | BC4: 15 | BD4: 3 | BE4: FALSE | BF4: TRUE | BG4: 0 | BH4: 0 | BI4: 0 | BJ4: 0 | BK4: 0 | BL4: 0 | BN4: Lab | BO4: Lab | BP4: 0 | BQ4: 8 | BR4: 0 | BS4: 5 | BT4: 1 | BU4: 6 | BV4: FALSE | BW4: 0.271899 | BX4: 60 | BY4: 4 | BZ4: FALSE | CA4: Medium | CE4: 3-10 | CG4: FALSE | CH4: FALSE | CI4: 583 | CJ4: 2622 | CM4: 1 | CN4: FALSE | CO4: Open
A5: https://africanmarketingconfederation.org/amc-awards-2024 | B5: 200 | C5: 2xx | E5: Unmeasured | G5: Indexable | H5: 78.4 | I5: 18282.83 | J5: https://africanmarketingconfederation.org/amc-awards-2024 | K5: https://africanmarketingconfederation.org/amc-awards-2024 | L5: self | M5: Dev | N5: Open | P5: partial | Q5: rendered_browser | R5: UNMEASURED | S5: 25 | T5: 0 | U5: 100 | V5: https | W5: 0 | Z5: FALSE | AA5: text/html; charset=UTF-8 | AB5: HTTP/1.1 | AC5: 513.32 | AD5: TRUE | AE5: max-age=0 | AH5: max-image-preview:large | AI5: TRUE | AJ5: https://africanmarketingconfederation.org/amc-awards-2024 | AK5: TRUE | AL5: FALSE | AM5: 0 | AN5: FALSE | AQ5: FALSE | AR5: FALSE | AS5: FALSE | AW5: 2025-04-24T13:54:46+00:00 | AX5: weekly | AY5: 0.7 | AZ5: 0 | BB5: 16 | BC5: 9 | BD5: 4 | BE5: FALSE | BF5: TRUE | BG5: 0 | BH5: 0 | BI5: 0 | BJ5: 0 | BK5: 0 | BL5: 0 | BN5: Lab | BO5: Lab | BP5: 0 | BQ5: 0 | BR5: 0 | BS5: 0 | BU5: 0 | BV5: TRUE | BW5: 0.019665 | BX5: 100 | BY5: 16 | BZ5: TRUE | CA5: Medium | CE5: 0 | CG5: FALSE | CH5: FALSE | CI5: 352 | CJ5: 2517 | CM5: 1 | CN5: FALSE | CO5: Open
A6: https://africanmarketingconfederation.org/amc-conference-2022 | B6: 200 | C6: 2xx | E6: Unmeasured | G6: Indexable | H6: 2317.69 | I6: 20124.52 | J6: https://africanmarketingconfederation.org/amc-conference-2022 | K6: https://africanmarketingconfederation.org/amc-conference-2022 | L6: self | M6: Dev | N6: Open | P6: partial | Q6: rendered_browser | R6: UNMEASURED | S6: 11.25 | T6: 0 | U6: 45 | V6: https | W6: 0 | Z6: FALSE | AA6: text/html; charset=UTF-8 | AB6: HTTP/1.1 | AC6: 341.93 | AD6: TRUE | AE6: max-age=0 | AH6: max-image-preview:large | AI6: TRUE | AJ6: https://africanmarketingconfederation.org/amc-conference-2022 | AK6: TRUE | AL6: FALSE | AM6: 0 | AN6: FALSE | AQ6: FALSE | AR6: FALSE | AS6: FALSE | AW6: 2026-01-21T00:07:32+00:00 | AX6: weekly | AY6: 0.7 | AZ6: 0 | BB6: 99 | BC6: 64 | BD6: 3 | BE6: FALSE | BF6: TRUE | BG6: 0 | BH6: 0 | BI6: 0 | BJ6: 0 | BK6: 0 | BL6: 0 | BN6: Lab | BO6: Lab | BP6: 0 | BQ6: 10 | BR6: 0 | BS6: 6.1 | BU6: 0 | BV6: TRUE | BW6: 0.019665 | BX6: 100 | BY6: 9 | BZ6: FALSE | CA6: Medium | CE6: 0 | CG6: FALSE | CH6: FALSE | CI6: 381 | CJ6: 2399 | CM6: 1 | CN6: FALSE | CO6: Open
A7: https://africanmarketingconfederation.org/amc-conference-2022-prospectus | B7: 200 | C7: 2xx | E7: Unmeasured | G7: Indexable | H7: 3628.71 | I7: 21740.58 | J7: https://africanmarketingconfederation.org/amc-conference-2022-prospectus | K7: https://africanmarketingconfederation.org/amc-conference-2022-prospectus | L7: self | M7: Dev | N7: Open | P7: partial | Q7: rendered_browser | R7: UNMEASURED | S7: 11.25 | T7: 0 | U7: 45 | V7: https | W7: 0 | Z7: FALSE | AA7: text/html; charset=UTF-8 | AB7: HTTP/1.1 | AC7: 279.86 | AD7: TRUE | AE7: max-age=0 | AH7: max-image-preview:large | AI7: TRUE | AJ7: https://africanmarketingconfederation.org/amc-conference-2022-prospectus | AK7: TRUE | AL7: FALSE | AM7: 0 | AN7: FALSE | AQ7: FALSE | AR7: FALSE | AS7: FALSE | AW7: 2025-07-14T07:22:03+00:00 | AX7: weekly | AY7: 0.7 | AZ7: 0 | BB7: 32 | BC7: 14 | BD7: 4 | BE7: FALSE | BF7: TRUE | BG7: 0 | BH7: 0 | BI7: 0 | BJ7: 0 | BK7: 0 | BL7: 0 | BN7: Lab | BO7: Lab | BP7: 0 | BQ7: 0 | BR7: 0 | BS7: 0 | BU7: 0 | BV7: TRUE | BW7: 0.019665 | BX7: 30 | BY7: 3 | BZ7: FALSE | CA7: Medium | CE7: 0 | CG7: FALSE | CH7: FALSE | CI7: 475 | CJ7: 2077 | CM7: 1 | CN7: FALSE | CO7: Open
A8: https://africanmarketingconfederation.org/amc-conference-2022-thank-you | B8: 200 | C8: 2xx | E8: Unmeasured | G8: Indexable | H8: 3879.66 | I8: 22165.22 | J8: https://africanmarketingconfederation.org/amc-conference-2022-thank-you | K8: https://africanmarketingconfederation.org/amc-conference-2022-thank-you | L8: self | M8: Dev | N8: Open | P8: partial | Q8: rendered_browser | R8: UNMEASURED | S8: 17.5 | T8: 0 | U8: 70 | V8: https | W8: 0 | Z8: FALSE | AA8: text/html; charset=UTF-8 | AB8: HTTP/1.1 | AC8: 341.57 | AD8: TRUE | AE8: max-age=0 | AH8: max-image-preview:large | AI8: TRUE | AJ8: https://africanmarketingconfederation.org/amc-conference-2022-thank-you | AK8: TRUE | AL8: FALSE | AM8: 0 | AN8: FALSE | AQ8: FALSE | AR8: FALSE | AS8: FALSE | AW8: 2021-11-26T08:41:00+00:00 | AX8: weekly | AY8: 0.7 | AZ8: 0 | BB8: 32 | BC8: 15 | BD8: 2 | BE8: FALSE | BF8: TRUE | BG8: 0 | BH8: 0 | BI8: 0 | BJ8: 0 | BK8: 0 | BL8: 0 | BN8: Lab | BO8: Lab | BP8: 0 | BQ8: 0 | BR8: 0 | BS8: 0 | BU8: 0 | BV8: TRUE | BW8: 0.019665 | BX8: 100 | BY8: 8 | BZ8: FALSE | CA8: Medium | CE8: 0 | CG8: FALSE | CH8: FALSE | CI8: 468 | CJ8: 2089 | CM8: 1 | CN8: FALSE | CO8: Open
A9: https://africanmarketingconfederation.org/amc-conference-2023 | B9: 200 | C9: 2xx | E9: Unmeasured | G9: Indexable | H9: 3016.19 | I9: 20985.18 | J9: https://africanmarketingconfederation.org/amc-conference-2023 | K9: https://africanmarketingconfederation.org/amc-conference-2023 | L9: self | M9: Dev | N9: Open | P9: partial | Q9: rendered_browser | R9: UNMEASURED | S9: 25 | T9: 0 | U9: 100 | V9: https | W9: 0 | Z9: FALSE | AA9: text/html; charset=UTF-8 | AB9: HTTP/1.1 | AC9: 370.99 | AD9: TRUE | AE9: max-age=0 | AH9: max-image-preview:large | AI9: TRUE | AJ9: https://africanmarketingconfederation.org/amc-conference-2023 | AK9: TRUE | AL9: FALSE | AM9: 0 | AN9: FALSE | AQ9: FALSE | AR9: FALSE | AS9: FALSE | AW9: 2025-03-03T07:59:34+00:00 | AX9: weekly | AY9: 0.7 | AZ9: 0 | BB9: 41 | BC9: 33 | BD9: 13 | BE9: FALSE | BF9: TRUE | BG9: 0 | BH9: 0 | BI9: 0 | BJ9: 0 | BK9: 0 | BL9: 0 | BN9: Lab | BO9: Lab | BP9: 1 | BQ9: 24 | BR9: 0.041666667 | BS9: 14.583333 | BU9: 2 | BV9: FALSE | BW9: 0.035214 | BX9: 80 | BY9: 6 | BZ9: FALSE | CA9: Medium | CE9: 1-2 | CG9: FALSE | CH9: FALSE | CI9: 381 | CJ9: 2467 | CM9: 1 | CN9: FALSE | CO9: Open
A10: https://africanmarketingconfederation.org/amc-conference-2023/amc-awards | B10: 200 | C10: 2xx | E10: Unmeasured | G10: Indexable | H10: 2673.27 | I10: 20610.13 | J10: https://africanmarketingconfederation.org/amc-conference-2023/amc-awards | K10: https://africanmarketingconfederation.org/amc-conference-2023/amc-awards | L10: self | M10: Dev | N10: Open | P10: partial | Q10: rendered_browser | R10: UNMEASURED | S10: 25 | T10: 0 | U10: 100 | V10: https | W10: 0 | Z10: FALSE | AA10: text/html; charset=UTF-8 | AB10: HTTP/1.1 | AC10: 272.63 | AD10: TRUE | AE10: max-age=0 | AH10: max-image-preview:large | AI10: TRUE | AJ10: https://africanmarketingconfederation.org/amc-conference-2023/amc-awards | AK10: TRUE | AL10: FALSE | AM10: 0 | AN10: FALSE | AQ10: FALSE | AR10: FALSE | AS10: FALSE | AW10: 2023-11-23T11:51:22+00:00 | AX10: weekly | AY10: 0.7 | AZ10: 0 | BB10: 19 | BC10: 10 | BD10: 2 | BE10: FALSE | BF10: TRUE | BG10: 0 | BH10: 0 | BI10: 0 | BJ10: 0 | BK10: 0 | BL10: 0 | BN10: Lab | BO10: Lab | BP10: 2 | BQ10: 34 | BR10: 0.058823529 | BS10: 4.2352941 | BU10: 2 | BV10: FALSE | BW10: 0.035214 | BX10: 40 | BY10: 4 | BZ10: FALSE | CA10: Medium | CE10: 1-2 | CG10: FALSE | CH10: FALSE | CI10: 316 | CJ10: 2678 | CM10: 2 | CN10: FALSE | CO10: Open
A11: https://africanmarketingconfederation.org/amc-conference-2023/amc-awards-book-now | B11: 200 | C11: 2xx | E11: Unmeasured | G11: Indexable | H11: 2667.9 | I11: 20777.82 | J11: https://africanmarketingconfederation.org/amc-conference-2023/amc-awards-book-now | K11: https://africanmarketingconfederation.org/amc-conference-2023/amc-awards-book-now | L11: self | M11: Dev | N11: Open | P11: partial | Q11: rendered_browser | R11: UNMEASURED | S11: 6.25 | T11: 0 | U11: 25 | V11: https | W11: 0 | Z11: FALSE | AA11: text/html; charset=UTF-8 | AB11: HTTP/1.1 | AC11: 239.75 | AD11: TRUE | AE11: max-age=0 | AH11: max-image-preview:large | AI11: TRUE | AJ11: https://africanmarketingconfederation.org/amc-conference-2023/amc-awards-book-now | AK11: TRUE | AL11: FALSE | AM11: 0 | AN11: FALSE | AQ11: FALSE | AR11: FALSE | AS11: FALSE | AW11: 2023-08-22T14:14:41+00:00 | AX11: weekly | AY11: 0.7 | AZ11: 0 | BB11: 19 | BC11: 10 | BD11: 2 | BE11: FALSE | BF11: TRUE | BG11: 0 | BH11: 0 | BI11: 0 | BJ11: 0 | BK11: 0 | BL11: 0 | BN11: Lab | BO11: Lab | BP11: 0 | BQ11: 0 | BR11: 0 | BS11: 0 | BU11: 0 | BV11: TRUE | BW11: 0.019665 | BX11: 30 | BY11: 3 | BZ11: FALSE | CA11: Medium | CE11: 0 | CG11: FALSE | CH11: FALSE | CI11: 396 | CJ11: 0 | CM11: 2 | CN11: FALSE | CO11: Open

Sheet Content
A1: URL | B1: Word Count | C1: Word Count Band | D1: Readability (Rough Flesch) | E1: H1 Count | F1: Missing H1 Flag | G1: Multiple H1 Flag | H1: Title Missing | I1: Meta Description Missing | J1: Thin Content Flag | K1: Sentence Count | L1: Body Text-to-HTML Ratio | M1: Open in Main | N1: BACK TO DASHBOARD | O1: BACK TO DASHBOARD_1
A2: https://africanmarketingconfederation.org/about-us | B2: 235 | C2: Thin | D2: 172.76 | E2: 1 | F2: FALSE | G2: FALSE | H2: FALSE | I2: FALSE | J2: TRUE | K2: 7 | M2: Open
A3: https://africanmarketingconfederation.org/ | B3: 35 | C3: Thin | D3: 189.07 | E3: 5 | F3: FALSE | G3: TRUE | H3: FALSE | I3: FALSE | J3: TRUE | K3: 2 | M3: Open
A4: https://africanmarketingconfederation.org/african-marketing-confederation-tourism-chapter | B4: 355 | C4: OK | D4: 179.12 | E4: 2 | F4: FALSE | G4: TRUE | H4: FALSE | I4: FALSE | J4: FALSE | K4: 13 | M4: Open
A5: https://africanmarketingconfederation.org/amc-awards-2024 | B5: 1668 | C5: Strong | D5: 178.62 | E5: 2 | F5: FALSE | G5: TRUE | H5: FALSE | I5: FALSE | J5: FALSE | K5: 60 | M5: Open
A6: https://africanmarketingconfederation.org/amc-conference-2022-prospectus | B6: 120 | C6: Thin | D6: 145.94 | E6: 0 | F6: TRUE | G6: FALSE | H6: FALSE | I6: FALSE | J6: TRUE | K6: 2 | M6: Open
A7: https://africanmarketingconfederation.org/amc-conference-2022-thank-you | B7: 367 | C7: OK | D7: 178.18 | E7: 0 | F7: TRUE | G7: FALSE | H7: FALSE | I7: FALSE | J7: FALSE | K7: 13 | M7: Open
A8: https://africanmarketingconfederation.org/amc-conference-2022 | B8: 32 | C8: Thin | D8: 196.01 | E8: 0 | F8: TRUE | G8: FALSE | H8: FALSE | I8: FALSE | J8: TRUE | K8: 3 | M8: Open
A9: https://africanmarketingconfederation.org/amc-conference-2023 | B9: 415 | C9: OK | D9: 168.54 | E9: 1 | F9: FALSE | G9: FALSE | H9: FALSE | I9: FALSE | J9: FALSE | K9: 11 | M9: Open
A10: https://africanmarketingconfederation.org/amc-conference-2023/amc-awards-book-now | B10: 31 | C10: Thin | D10: 175.37 | E10: 0 | F10: TRUE | G10: FALSE | H10: FALSE | I10: TRUE | J10: TRUE | K10: 1 | M10: Open
A11: https://africanmarketingconfederation.org/amc-conference-2023/amc-awards | B11: 326 | C11: OK | D11: 176.75 | E11: 1 | F11: FALSE | G11: FALSE | H11: FALSE | I11: FALSE | J11: FALSE | K11: 11 | M11: Open

Sheet AEO
A1: URL | B1: AEO Readiness Score | C1: AEO Badge | D1: Why It Matters | E1: FAQ Section Count | F1: Question Heading Count | G1: Paragraphs 40-60 Words Count | H1: QAPage/FAQ Schema Present | I1: Speakable Schema Present | J1: HowTo Signal | K1: Definition Signal | L1: List/Table Answer Signal | M1: Answer Block Detected (First 60 Words) | N1: AEO Extractability Score | O1: Snippet Preview Mockup | P1: Title Missing | Q1: Meta Description Missing | R1: Open in Main | S1: BACK TO DASHBOARD | T1: BACK TO DASHBOARD_1
A2: https://africanmarketingconfederation.org/about-us | B2: 0 | C2: Needs Work | D2: Missing 30-60 word answer blocks reduces eligibility for featured snippets. Question-style headings help match conversational search and answer intent. FAQ/QA schema improves machine understanding for rich answer surfaces. Speakable markup can improve voice assistant readability of key answers. Answer-friendly structure (how-to, definitions, lists/tables) helps extraction by answer engines. | E2: 0 | F2: 0 | G2: 0 | H2: FALSE | I2: FALSE | J2: FALSE | K2: FALSE | L2: FALSE | M2: FALSE | N2: Medium | P2: FALSE | Q2: FALSE | R2: Open
A3: https://africanmarketingconfederation.org/ | B3: 0 | C3: Needs Work | D3: Missing 30-60 word answer blocks reduces eligibility for featured snippets. Question-style headings help match conversational search and answer intent. FAQ/QA schema improves machine understanding for rich answer surfaces. Speakable markup can improve voice assistant readability of key answers. Answer-friendly structure (how-to, definitions, lists/tables) helps extraction by answer engines. | E3: 0 | F3: 0 | G3: 0 | H3: FALSE | I3: FALSE | J3: FALSE | K3: FALSE | L3: FALSE | M3: FALSE | N3: Medium | P3: FALSE | Q3: FALSE | R3: Open
A4: https://africanmarketingconfederation.org/african-marketing-confederation-tourism-chapter | B4: 0 | C4: Needs Work | D4: Missing 30-60 word answer blocks reduces eligibility for featured snippets. Question-style headings help match conversational search and answer intent. FAQ/QA schema improves machine understanding for rich answer surfaces. Speakable markup can improve voice assistant readability of key answers. Answer-friendly structure (how-to, definitions, lists/tables) helps extraction by answer engines. | E4: 0 | F4: 0 | G4: 0 | H4: FALSE | I4: FALSE | J4: FALSE | K4: FALSE | L4: FALSE | M4: FALSE | N4: Medium | P4: FALSE | Q4: FALSE | R4: Open
A5: https://africanmarketingconfederation.org/amc-awards-2024 | B5: 0 | C5: Needs Work | D5: Missing 30-60 word answer blocks reduces eligibility for featured snippets. Question-style headings help match conversational search and answer intent. FAQ/QA schema improves machine understanding for rich answer surfaces. Speakable markup can improve voice assistant readability of key answers. Answer-friendly structure (how-to, definitions, lists/tables) helps extraction by answer engines. | E5: 0 | F5: 0 | G5: 0 | H5: FALSE | I5: FALSE | J5: FALSE | K5: FALSE | L5: FALSE | M5: TRUE | N5: Medium | P5: FALSE | Q5: FALSE | R5: Open
A6: https://africanmarketingconfederation.org/amc-conference-2022-prospectus | B6: 0 | C6: Needs Work | D6: Missing 30-60 word answer blocks reduces eligibility for featured snippets. Question-style headings help match conversational search and answer intent. FAQ/QA schema improves machine understanding for rich answer surfaces. Speakable markup can improve voice assistant readability of key answers. Answer-friendly structure (how-to, definitions, lists/tables) helps extraction by answer engines. | E6: 0 | F6: 0 | G6: 0 | H6: FALSE | I6: FALSE | J6: FALSE | K6: FALSE | L6: FALSE | M6: FALSE | N6: Medium | P6: FALSE | Q6: FALSE | R6: Open
A7: https://africanmarketingconfederation.org/amc-conference-2022-thank-you | B7: 0 | C7: Needs Work | D7: Missing 30-60 word answer blocks reduces eligibility for featured snippets. Question-style headings help match conversational search and answer intent. FAQ/QA schema improves machine understanding for rich answer surfaces. Speakable markup can improve voice assistant readability of key answers. Answer-friendly structure (how-to, definitions, lists/tables) helps extraction by answer engines. | E7: 0 | F7: 0 | G7: 0 | H7: FALSE | I7: FALSE | J7: FALSE | K7: FALSE | L7: FALSE | M7: FALSE | N7: Medium | P7: FALSE | Q7: FALSE | R7: Open
A8: https://africanmarketingconfederation.org/amc-conference-2022 | B8: 0 | C8: Needs Work | D8: Missing 30-60 word answer blocks reduces eligibility for featured snippets. Question-style headings help match conversational search and answer intent. FAQ/QA schema improves machine understanding for rich answer surfaces. Speakable markup can improve voice assistant readability of key answers. Answer-friendly structure (how-to, definitions, lists/tables) helps extraction by answer engines. | E8: 0 | F8: 0 | G8: 0 | H8: FALSE | I8: FALSE | J8: FALSE | K8: FALSE | L8: FALSE | M8: FALSE | N8: Medium | P8: FALSE | Q8: FALSE | R8: Open
A9: https://africanmarketingconfederation.org/amc-conference-2023 | B9: 0 | C9: Needs Work | D9: Missing 30-60 word answer blocks reduces eligibility for featured snippets. Question-style headings help match conversational search and answer intent. FAQ/QA schema improves machine understanding for rich answer surfaces. Speakable markup can improve voice assistant readability of key answers. Answer-friendly structure (how-to, definitions, lists/tables) helps extraction by answer engines. | E9: 0 | F9: 0 | G9: 0 | H9: FALSE | I9: FALSE | J9: FALSE | K9: FALSE | L9: FALSE | M9: FALSE | N9: Medium | P9: FALSE | Q9: FALSE | R9: Open
A10: https://africanmarketingconfederation.org/amc-conference-2023/amc-awards-book-now | B10: 0 | C10: Needs Work | D10: Missing 30-60 word answer blocks reduces eligibility for featured snippets. Question-style headings help match conversational search and answer intent. FAQ/QA schema improves machine understanding for rich answer surfaces. Speakable markup can improve voice assistant readability of key answers. Answer-friendly structure (how-to, definitions, lists/tables) helps extraction by answer engines. Missing title/meta weakens topical context and lowers snippet confidence. | E10: 0 | F10: 0 | G10: 0 | H10: FALSE | I10: FALSE | J10: FALSE | K10: FALSE | L10: FALSE | M10: FALSE | N10: Medium | P10: FALSE | Q10: TRUE | R10: Open
A11: https://africanmarketingconfederation.org/amc-conference-2023/amc-awards | B11: 0 | C11: Needs Work | D11: Missing 30-60 word answer blocks reduces eligibility for featured snippets. Question-style headings help match conversational search and answer intent. FAQ/QA schema improves machine understanding for rich answer surfaces. Speakable markup can improve voice assistant readability of key answers. Answer-friendly structure (how-to, definitions, lists/tables) helps extraction by answer engines. | E11: 0 | F11: 0 | G11: 0 | H11: FALSE | I11: FALSE | J11: FALSE | K11: FALSE | L11: FALSE | M11: FALSE | N11: Medium | P11: FALSE | Q11: FALSE | R11: Open

Sheet Schema & Metadata
A1: URL | B1: Schema Types Found | C1: Schema Types Count | D1: Schema Parse Errors | E1: OG Title | F1: OG Description | G1: OG Image | H1: Open Graph Complete | I1: Twitter Card Type | J1: Open in Main | K1: BACK TO DASHBOARD | L1: BACK TO DASHBOARD_1
A2: https://africanmarketingconfederation.org/about-us | C2: 0 | D2: 0 | E2: African Marketing Confederation – The Leading Marketing Professional Body – African Marketing Confederation | F2: ABOUT The African Marketing Confederation The African Marketing Confederation is the ground-breaking Pan African body of marketing professionals spearheading the ongoing development of the highest possible standards of marketing across Africa. Founded in 2011, the AMC is a collaboration between the African national marketing bodies and associations to exchange expertise and information, and to promote | G2: https://africanmarketingconfederation.org/wp-content/uploads/2026/03/og-image.png | H2: TRUE | I2: summary_large_image | J2: Open
A3: https://africanmarketingconfederation.org/ | C3: 0 | D3: 0 | E3: Home page of the african marketing confederation | F3: The 2026 AMC Conference Meets the Mighty Victoria Falls 23-25 September | Livingstone, Zambia Sign Up for Updates The 2026 AMC Conference Meets the Mighty Victoria Falls 23-25 September | Livingstone, Zambia Sign Up for Updates Certified Professional Marketer (Africa) - CPM(A) The designation where global marketing standards meet African realities Learn More ABOUT The | G3: https://africanmarketingconfederation.org/wp-content/uploads/2026/03/og-image.png | H3: TRUE | I3: summary_large_image | J3: Open
A4: https://africanmarketingconfederation.org/african-marketing-confederation-tourism-chapter | C4: 0 | D4: 0 | E4: African Marketing Confederation Tourism Chapter – African Marketing Confederation | F4: African Marketing Confederation Tourism Chapter Shaping Africa’s Tourism Narrative Through Strategic Marketing Tourism is one of Africa’s most powerful economic engines - generating jobs, stimulating investment, and fostering cultural exchange.The African Marketing Confederation is proud to launch the Tourism Chapter, a bold initiative to elevate African tourism through the lens of world-class marketing. Launched at the | G4: https://africanmarketingconfederation.org/wp-content/uploads/2026/03/og-image.png | H4: TRUE | I4: summary_large_image | J4: Open
A5: https://africanmarketingconfederation.org/amc-awards-2024 | C5: 0 | D5: 0 | E5: AMC Awards 2024 – African Marketing Confederation | F5: NOMINATIONS are Open ! AMC Awards The African Marketing Confederation Awards event is held annually as part of the African Marketing Confederation Forum. This distinguished event celebrates and acknowledges outstanding marketing campaigns and the visionary individuals behind them. The awards presented honor not only the groundbreaking strategies and creative brilliance that set these campaigns apart but | G5: https://africanmarketingconfederation.org/wp-content/uploads/2021/08/amc_faw.png | H5: TRUE | I5: summary_large_image | J5: Open
A6: https://africanmarketingconfederation.org/amc-conference-2022-prospectus | C6: 0 | D6: 0 | E6: AMC Conference 2022 – Prospectus – African Marketing Confederation | F6: AMC Conference 2022 23 - 24 March 2022 Navigating Africa's Unique Marketing Mix BOOK NOW Days Hours Minutes Seconds download prospectus To download the AMC 2022 Conference Prospectus please complete the form below: First Name Last Name Email Mobile Company I've read and agree to the Privacy Policy BOOK NOW FOR THE AMC CONFERENCE 2022 | G6: https://africanmarketingconfederation.org/wp-content/uploads/2026/03/og-image.png | H6: TRUE | I6: summary_large_image | J6: Open
A7: https://africanmarketingconfederation.org/amc-conference-2022-thank-you | C7: 0 | D7: 0 | E7: AMC Conference 2022 – Thank You – African Marketing Confederation | F7: AMC Conference 2022 23 - 24 March 2022 Navigating Africa's Unique Marketing Mix ENQUIRE NOW Days Hours Minutes Seconds Success! Thank you for completing the enquiry form. Our team will contact you shortly! × Dismiss alert The AMC Conference is the must attend Pan African event for marketing professionals. It will focus on solutions for | G7: https://africanmarketingconfederation.org/wp-content/uploads/2026/03/og-image.png | H7: TRUE | I7: summary_large_image | J7: Open
A8: https://africanmarketingconfederation.org/amc-conference-2022 | C8: 0 | D8: 0 | E8: AMC Conference 2022 – African Marketing Confederation | F8: corinna kopf onlyfans leaks AMC Conference 2022 Thank you for attending19 - 22 October 2022 The African Marketing Confederation's Annual Conference brought together the best collection of marketing leaders from top companies, marketing bodies and associations to share tactics and best practices on how to build the next generation of marketing. Event Highlights Thank you for Attending! | G8: https://africanmarketingconfederation.org/wp-content/uploads/2026/03/og-image.png | H8: TRUE | I8: summary_large_image | J8: Open
A9: https://africanmarketingconfederation.org/amc-conference-2023 | C9: 0 | D9: 0 | E9: AMC Conference 2023 – African Marketing Confederation | F9: AMC Conference 6 - 9 September 2023 Imperial Botanical Beach Hotel, Entebbe, Uganda Thank you for joining us! View Presentations 2nd Annual African Marketing Confederation Conference Africa's $3.4 trillion Economy: Opportunities for Marketers Welcome to the Recap of the 2nd Annual African Marketing Conference: Unveiling Africa's $3.4 Trillion EconomyOur conference was a remarkable exploration of | G9: https://africanmarketingconfederation.org/wp-content/uploads/2021/08/amc_faw.png | H9: TRUE | I9: summary_large_image | J9: Open
A10: https://africanmarketingconfederation.org/amc-conference-2023/amc-awards-book-now | C10: 0 | D10: 0 | E10: AMC Awards | Book Now – African Marketing Confederation | G10: https://africanmarketingconfederation.org/wp-content/uploads/2021/08/amc_faw.png | H10: FALSE | I10: summary_large_image | J10: Open
A11: https://africanmarketingconfederation.org/amc-conference-2023/amc-awards | C11: 0 | D11: 0 | E11: AMC Awards – African Marketing Confederation | F11: AMC Awards Welcome to the prestigious African Marketing Confederation Awards, a distinguished event that celebrates and acknowledges the remarkable achievements, cutting-edge innovations, and exceptional leadership demonstrated by outstanding individuals within the dynamic realm of marketing across the expansive African region.During the 2nd Annual African Marketing Confederation Conference, held from 6th to 9th September at the | G11: https://africanmarketingconfederation.org/wp-content/uploads/2021/08/amc_faw.png | H11: TRUE | I11: summary_large_image | J11: Open

Sheet Links
A1: URL | B1: Internal Links Count | C1: Unique Internal Links Count | D1: Broken Internal Links Count | E1: Unresolved Internal Links Count | F1: Generic Anchor Text Count | G1: External Links Count | H1: Nofollow Internal Links Count | I1: Nofollow External Links Count | J1: Internal Link Statuses | K1: Open in Main | L1: BACK TO DASHBOARD | M1: BACK TO DASHBOARD_1
A2: https://africanmarketingconfederation.org/about-us | B2: 32 | C2: 14 | D2: 1 | E2: 0 | F2: 0 | G2: 7 | H2: 0 | I2: 0 | J2: https://africanmarketingconfederation.org/ => 200 | https://africanmarketingconfederation.org/about-us => 200 | https://africanmarketingconfederation.org/african-marketing-confederation-tourism-chapter => 200 | https://africanmarketingconfederation.org/amc-conference-2025-delegate-packages => 404 | https://africanmarketingconfederation.org/amc-conference-2026 => 200 | https://africanmarketingconfederation.org/certified-professional-marketer-africa => 200 | https://africanmarketingconfederation.org/chartered-marketer-africa => 200 | https://africanmarketingconfederation.org/contact-us => 200 | https://africanmarketingconfederation.org/education => 200 | https://africanmarketingconfederation.org/members => 200 | https://africanmarketingconfederation.org/news-articles => 200 | https://africanmarketingconfederation.org/privacy-policy => 200 | https://africanmarketingconfederation.org/publications-2 => 200 | https://africanmarketingconfederation.org/sub-committees => 200 | K2: Open
A3: https://africanmarketingconfederation.org/ | B3: 63 | C3: 22 | D3: 1 | E3: 0 | F3: 3 | G3: 2 | H3: 0 | I3: 0 | J3: https://africanmarketingconfederation.org/ => 200 | https://africanmarketingconfederation.org/about-us => 200 | https://africanmarketingconfederation.org/african-marketing-confederation-tourism-chapter => 200 | https://africanmarketingconfederation.org/amc-conference-2025 => 200 | https://africanmarketingconfederation.org/amc-conference-2025-delegate-packages => 404 | https://africanmarketingconfederation.org/amc-conference-2026 => 200 | https://africanmarketingconfederation.org/certified-professional-marketer-africa => 200 | https://africanmarketingconfederation.org/chartered-marketer-africa => 200 | https://africanmarketingconfederation.org/chatgpt-ads-in-africa-a-game-changer-or-a-trust-gamble => 200 | https://africanmarketingconfederation.org/contact-us => 200 | https://africanmarketingconfederation.org/education => 200 | https://africanmarketingconfederation.org/european-marketers-gather-to-choose-their-top-achievers-for-2026 => 200 | https://africanmarketingconfederation.org/members => 200 | https://africanmarketingconfederation.org/namibia-bets-on-walvis-bay-port-as-increasingly-viable-alternative => 200 | https://africanmarketingconfederation.org/news-articles => 200 | https://africanmarketingconfederation.org/omnicom-media-study-warns-negative-reach-can-undermine-ad-campaigns => 200 | https://africanmarketingconfederation.org/out-now-new-issue-brings-latest-news-and-insights-for-africas-marketers => 200 | https://africanmarketingconfederation.org/privacy-policy => 200 | https://africanmarketingconfederation.org/publications-2 => 200 | https://africanmarketingconfederation.org/report-identifies-five-forces-influencing-global-purchasing-decisions => 200 | https://africanmarketingconfederation.org/sub-committees => 200 | https://africanmarketingconfederation.org/subscribe => 200 | K3: Open
A4: https://africanmarketingconfederation.org/african-marketing-confederation-tourism-chapter | B4: 58 | C4: 15 | D4: 1 | E4: 0 | F4: 0 | G4: 3 | H4: 0 | I4: 0 | J4: https://africanmarketingconfederation.org/ => 200 | https://africanmarketingconfederation.org/about-us => 200 | https://africanmarketingconfederation.org/african-marketing-confederation-tourism-chapter => 200 | https://africanmarketingconfederation.org/amc-conference-2025-delegate-packages => 404 | https://africanmarketingconfederation.org/amc-conference-2025-highlights => 200 | https://africanmarketingconfederation.org/amc-conference-2026 => 200 | https://africanmarketingconfederation.org/certified-professional-marketer-africa => 200 | https://africanmarketingconfederation.org/chartered-marketer-africa => 200 | https://africanmarketingconfederation.org/contact-us => 200 | https://africanmarketingconfederation.org/education => 200 | https://africanmarketingconfederation.org/members => 200 | https://africanmarketingconfederation.org/news-articles => 200 | https://africanmarketingconfederation.org/privacy-policy => 200 | https://africanmarketingconfederation.org/publications-2 => 200 | https://africanmarketingconfederation.org/sub-committees => 200 | K4: Open
A5: https://africanmarketingconfederation.org/amc-awards-2024 | B5: 16 | C5: 9 | D5: 1 | E5: 0 | F5: 0 | G5: 4 | H5: 0 | I5: 0 | J5: https://africanmarketingconfederation.org/amc-conference-2025 => 200 | https://africanmarketingconfederation.org/amc-conference-2025-delegate-packages => 404 | https://africanmarketingconfederation.org/amc-marketing-conference-2024/amc-programme-2025 => 200 | https://africanmarketingconfederation.org/amc-marketing-conference-2024/awards-2025 => 200 | https://africanmarketingconfederation.org/amc-sponsors-2025 => 200 | https://africanmarketingconfederation.org/conference-faq-2025 => 200 | https://africanmarketingconfederation.org/privacy-policy => 200 | https://africanmarketingconfederation.org/publications-2 => 200 | https://africanmarketingconfederation.org/speakers-2025 => 200 | K5: Open
A6: https://africanmarketingconfederation.org/amc-conference-2022-prospectus | B6: 32 | C6: 14 | D6: 1 | E6: 0 | F6: 0 | G6: 4 | H6: 0 | I6: 0 | J6: https://africanmarketingconfederation.org/ => 200 | https://africanmarketingconfederation.org/about-us => 200 | https://africanmarketingconfederation.org/african-marketing-confederation-tourism-chapter => 200 | https://africanmarketingconfederation.org/amc-conference-2025-delegate-packages => 404 | https://africanmarketingconfederation.org/amc-conference-2026 => 200 | https://africanmarketingconfederation.org/certified-professional-marketer-africa => 200 | https://africanmarketingconfederation.org/chartered-marketer-africa => 200 | https://africanmarketingconfederation.org/contact-us => 200 | https://africanmarketingconfederation.org/education => 200 | https://africanmarketingconfederation.org/members => 200 | https://africanmarketingconfederation.org/news-articles => 200 | https://africanmarketingconfederation.org/privacy-policy => 200 | https://africanmarketingconfederation.org/publications-2 => 200 | https://africanmarketingconfederation.org/sub-committees => 200 | K6: Open
A7: https://africanmarketingconfederation.org/amc-conference-2022-thank-you | B7: 32 | C7: 15 | D7: 2 | E7: 0 | F7: 0 | G7: 2 | H7: 0 | I7: 0 | J7: https://africanmarketingconfederation.org/ => 200 | https://africanmarketingconfederation.org/about-us => 200 | https://africanmarketingconfederation.org/african-marketing-confederation-tourism-chapter => 200 | https://africanmarketingconfederation.org/amc-conference-2025-delegate-packages => 404 | https://africanmarketingconfederation.org/amc-conference-2026 => 200 | https://africanmarketingconfederation.org/certified-professional-marketer-africa => 200 | https://africanmarketingconfederation.org/chartered-marketer-africa => 200 | https://africanmarketingconfederation.org/contact-us => 200 | https://africanmarketingconfederation.org/education => 200 | https://africanmarketingconfederation.org/members => 200 | https://africanmarketingconfederation.org/news-articles => 200 | https://africanmarketingconfederation.org/privacy-policy => 200 | https://africanmarketingconfederation.org/publications-2 => 200 | https://africanmarketingconfederation.org/sub-committees => 200 | https://africanmarketingconfederation.org/wp-content/uploads/2021/11/AMC-2022_Prospectus-low-res.pdf => 404 | K7: Open
A8: https://africanmarketingconfederation.org/amc-conference-2022 | B8: 99 | C8: 64 | D8: 1 | E8: 0 | F8: 0 | G8: 3 | H8: 0 | I8: 0 | J8: https://africanmarketingconfederation.org/ => 200 | https://africanmarketingconfederation.org/2024-amc-awards-recognise-marketing-excellence-from-the-continent => 200 | https://africanmarketingconfederation.org/about-us => 200 | https://africanmarketingconfederation.org/african-marketing-confederation-tourism-chapter => 200 | https://africanmarketingconfederation.org/amc-conference-2025 => 200 | https://africanmarketingconfederation.org/amc-conference-2025-delegate-packages => 404 | https://africanmarketingconfederation.org/amc-conference-2026 => 200 | https://africanmarketingconfederation.org/amc-marketing-conference-2024/amc-programme-2025 => 200 | https://africanmarketingconfederation.org/amc-marketing-conference-2024/awards-2025 => 200 | https://africanmarketingconfederation.org/amc-officially-welcomes-new-member-associations-into-the-fold => 200 | https://africanmarketingconfederation.org/amc-sponsors-2025 => 200 | https://africanmarketingconfederation.org/certified-professional-marketer-africa => 200 | https://africanmarketingconfederation.org/chartered-marketer-africa => 200 | https://africanmarketingconfederation.org/conference-faq-2025 => 200 | https://africanmarketingconfederation.org/contact-us => 200 | https://africanmarketingconfederation.org/education => 200 | https://africanmarketingconfederation.org/excitement-as-ghana-announced-as-host-of-2025-amc-marketing-conference => 200 | https://africanmarketingconfederation.org/how-a-bold-strategy-saved-kiwi-marketing-association-from-extinction => 200 | https://africanmarketingconfederation.org/marketers-are-placing-the-ads-where-consumers-dont-want-to-see-them => 200 | https://africanmarketingconfederation.org/members => 200 | https://africanmarketingconfederation.org/news-articles => 200 | https://africanmarketingconfederation.org/privacy-policy => 200 | https://africanmarketingconfederation.org/publications-2 => 200 | https://africanmarketingconfederation.org/speakers-2025 => 200 | https://africanmarketingconfederation.org/sub-committees => 200 | https://africanmarketingconfederation.org/time-for-africa-to-control-its-own-narrative-and-image-delegates-told => 200 | https://africanmarketingconfederation.org/wp-content/uploads/2022/10/EA2A2394-scaled.jpg => 200 | https://africanmarketingconfederation.org/wp-content/uploads/2022/10/EA2A2427-scaled.jpg => 200 | https://africanmarketingconfederation.org/wp-content/uploads/2022/10/EA2A2487-scaled.jpg => 200 | https://africanmarketingconfederation.org/wp-content/uploads/2022/10/EA2A2512-scaled.jpg => 200 | https://africanmarketingconfederation.org/wp-content/uploads/2022/10/EA2A2525-scaled.jpg => 200 | https://africanmarketingconfederation.org/wp-content/uploads/2022/10/EA2A2527-scaled.jpg => 200 | https://africanmarketingconfederation.org/wp-content/uploads/2022/10/EA2A2536-scaled.jpg => 200 | https://africanmarketingconfederation.org/wp-content/uploads/2022/10/EA2A2999-scaled.jpg => 200 | https://africanmarketingconfederation.org/wp-content/uploads/2022/10/EA2A3057-scaled.jpg => 200 | https://africanmarketingconfederation.org/wp-content/uploads/2022/10/EA2A3111-scaled.jpg => 200 | https://africanmarketingconfederation.org/wp-content/uploads/2022/10/EA2A3195-scaled.jpg => 200 | https://africanmarketingconfederation.org/wp-content/uploads/2022/10/EA2A3198-scaled.jpg => 200 | https://africanmarketingconfederation.org/wp-content/uploads/2022/10/EA2A3217-scaled.jpg => 200 | https://africanmarketingconfederation.org/wp-content/uploads/2022/10/EA2A3254-scaled.jpg => 200 | https://africanmarketingconfederation.org/wp-content/uploads/2022/10/EA2A3268-scaled.jpg => 200 | https://africanmarketingconfederation.org/wp-content/uploads/2022/10/EA2A3293-scaled.jpg => 200 | https://africanmarketingconfederation.org/wp-content/uploads/2022/10/EA2A3369-scaled.jpg => 200 | https://africanmarketingconfederation.org/wp-content/uploads/2022/10/EA2A3396-scaled.jpg => 200 | https://africanmarketingconfederation.org/wp-content/uploads/2022/10/EA2A3485-scaled.jpg => 200 | https://africanmarketingconfederation.org/wp-content/uploads/2022/10/EA2A3505-scaled.jpg => 200 | https://africanmarketingconfederation.org/wp-content/uploads/2022/10/EA2A3816-scaled.jpg => 200 | https://africanmarketingconfederation.org/wp-content/uploads/2022/10/EA2A3869-scaled.jpg => 200 | https://africanmarketingconfederation.org/wp-content/uploads/2022/10/EA2A3879-scaled.jpg => 200 | https://africanmarketingconfederation.org/wp-content/uploads/2022/10/EA2A3892-scaled.jpg => 200 | https://africanmarketingconfederation.org/wp-content/uploads/2022/10/EA2A3922-scaled.jpg => 200 | https://africanmarketingconfederation.org/wp-content/uploads/2022/10/EA2A3930-scaled.jpg => 200 | https://africanmarketingconfederation.org/wp-content/uploads/2022/10/EA2A3936-scaled.jpg => 200 | https://africanmarketingconfederation.org/wp-content/uploads/2022/10/EA2A4027-scaled.jpg => 200 | https://africanmarketingconfederation.org/wp-content/uploads/2022/10/EA2A4067-scaled.jpg => 200 | https://africanmarketingconfederation.org/wp-content/uploads/2022/10/EA2A4121-scaled.jpg => 200 | https://africanmarketingconfederation.org/wp-content/uploads/2022/10/EA2A4137-scaled.jpg => 200 | https://africanmarketingconfederation.org/wp-content/uploads/2022/10/IMG_0031-scaled.jpg => 200 | https://africanmarketingconfederation.org/wp-content/uploads/2022/10/IMG_9698-scaled.jpg => 200 | https://africanmarketingconfederation.org/wp-content/uploads/2022/10/IMG_9719-scaled.jpg => 200 | https://africanmarketingconfederation.org/wp-content/uploads/2022/10/IMG_9758-scaled.jpg => 200 | https://africanmarketingconfederation.org/wp-content/uploads/2022/10/IMG_9953-scaled.jpg => 200 | https://africanmarketingconfederation.org/wp-content/uploads/2022/10/IMG_9964-scaled.jpg => 200 | https://africanmarketingconfederation.org/wp-content/uploads/2022/10/IMG_9985-scaled.jpg => 200 | K8: Open
A9: https://africanmarketingconfederation.org/amc-conference-2023 | B9: 41 | C9: 33 | D9: 2 | E9: 0 | F9: 0 | G9: 13 | H9: 0 | I9: 0 | J9: https://africanmarketingconfederation.org/amc-conference-2023/gallery => 200 | https://africanmarketingconfederation.org/amc-conference-2023/programme => 200 | https://africanmarketingconfederation.org/amc-conference-2023/speakers => 200 | https://africanmarketingconfederation.org/amc-conference-2025 => 200 | https://africanmarketingconfederation.org/amc-conference-2025-delegate-packages => 404 | https://africanmarketingconfederation.org/amc-marketing-conference-2024/amc-programme-2025 => 200 | https://africanmarketingconfederation.org/amc-marketing-conference-2024/awards-2025 => 200 | https://africanmarketingconfederation.org/amc-sponsors-2025 => 200 | https://africanmarketingconfederation.org/calendar_events => 404 | https://africanmarketingconfederation.org/conference-faq-2025 => 200 | https://africanmarketingconfederation.org/privacy-policy => 200 | https://africanmarketingconfederation.org/publications-2 => 200 | https://africanmarketingconfederation.org/speakers-2025 => 200 | https://africanmarketingconfederation.org/wp-content/uploads/2023/09/AMC-TICON-0164.jpg => 200 | https://africanmarketingconfederation.org/wp-content/uploads/2023/09/AMC-TICON-1113.jpg => 200 | https://africanmarketingconfederation.org/wp-content/uploads/2023/09/AMC-TICON-1127.jpg => 200 | https://africanmarketingconfederation.org/wp-content/uploads/2023/09/AMC-Ticon-00246.jpg => 200 | https://africanmarketingconfederation.org/wp-content/uploads/2023/09/AMC-Ticon-00449.jpg => 200 | https://africanmarketingconfederation.org/wp-content/uploads/2023/09/AMC-Ticon-00481.jpg => 200 | https://africanmarketingconfederation.org/wp-content/uploads/2023/09/AMC-Ticon-00638.jpg => 200 | https://africanmarketingconfederation.org/wp-content/uploads/2023/09/AMC-Ticon-00682.jpg => 200 | https://africanmarketingconfederation.org/wp-content/uploads/2023/09/AMC-Ticon-00742.jpg => 200 | https://africanmarketingconfederation.org/wp-content/uploads/2023/09/AMC-Ticon-01128.jpg => 200 | https://africanmarketingconfederation.org/wp-content/uploads/2023/09/AMC-Ticon-01363.jpg => 200 | https://africanmarketingconfederation.org/wp-content/uploads/2023/09/AMC-Ticon-01409.jpg => 200 | https://africanmarketingconfederation.org/wp-content/uploads/2023/09/AMC-Ticon-01476.jpg => 200 | https://africanmarketingconfederation.org/wp-content/uploads/2023/09/AMC-Ticon-01530.jpg => 200 | https://africanmarketingconfederation.org/wp-content/uploads/2023/09/AMC-Ticon-01616.jpg => 200 | https://africanmarketingconfederation.org/wp-content/uploads/2023/09/AMC-Ticon-02950-1.jpg => 200 | https://africanmarketingconfederation.org/wp-content/uploads/2023/09/AMC-Ticon-03063.jpg => 200 | https://africanmarketingconfederation.org/wp-content/uploads/2023/09/AMC-Ticon-09823.jpg => 200 | https://africanmarketingconfederation.org/wp-content/uploads/2023/09/AMC-Ticon-09825.jpg => 200 | https://africanmarketingconfederation.org/wp-content/uploads/2023/09/AMC-Ticon-09953.jpg => 200 | K9: Open
A10: https://africanmarketingconfederation.org/amc-conference-2023/amc-awards-book-now | B10: 19 | C10: 10 | D10: 1 | E10: 0 | F10: 0 | G10: 2 | H10: 0 | I10: 0 | J10: https://africanmarketingconfederation.org/ => 200 | https://africanmarketingconfederation.org/amc-conference-2023 => 200 | https://africanmarketingconfederation.org/amc-conference-2023/amc-awards => 200 | https://africanmarketingconfederation.org/amc-conference-2023/gallery => 200 | https://africanmarketingconfederation.org/amc-conference-2023/partners => 200 | https://africanmarketingconfederation.org/amc-conference-2023/programme => 200 | https://africanmarketingconfederation.org/amc-conference-2023/speakers => 200 | https://africanmarketingconfederation.org/amc-conference-2025-delegate-packages => 404 | https://africanmarketingconfederation.org/privacy-policy => 200 | https://africanmarketingconfederation.org/publications-2 => 200 | K10: Open
A11: https://africanmarketingconfederation.org/amc-conference-2023/amc-awards | B11: 19 | C11: 10 | D11: 1 | E11: 0 | F11: 0 | G11: 2 | H11: 0 | I11: 0 | J11: https://africanmarketingconfederation.org/ => 200 | https://africanmarketingconfederation.org/amc-conference-2023 => 200 | https://africanmarketingconfederation.org/amc-conference-2023/amc-awards => 200 | https://africanmarketingconfederation.org/amc-conference-2023/gallery => 200 | https://africanmarketingconfederation.org/amc-conference-2023/partners => 200 | https://africanmarketingconfederation.org/amc-conference-2023/programme => 200 | https://africanmarketingconfederation.org/amc-conference-2023/speakers => 200 | https://africanmarketingconfederation.org/amc-conference-2025-delegate-packages => 404 | https://africanmarketingconfederation.org/privacy-policy => 200 | https://africanmarketingconfederation.org/publications-2 => 200 | K11: Open

Sheet Indexability
A1: URL | B1: Status Code | C1: Status Class | D1: Indexability Reason | E1: Canonical URL | F1: Canonical Type | G1: Canonical Matches Final URL | H1: Canonical in Sitemap Match | I1: Meta Robots Raw | J1: X-Robots-Tag | K1: Final URL | L1: Open in Main | M1: BACK TO DASHBOARD | N1: BACK TO DASHBOARD_1
A2: https://africanmarketingconfederation.org/about-us | B2: 200 | C2: 2xx | D2: Indexable | E2: https://africanmarketingconfederation.org/about-us | F2: self | G2: TRUE | H2: TRUE | I2: max-image-preview:large | K2: https://africanmarketingconfederation.org/about-us | L2: Open
A3: https://africanmarketingconfederation.org/ | B3: 200 | C3: 2xx | D3: Indexable | E3: https://africanmarketingconfederation.org/ | F3: self | G3: TRUE | H3: TRUE | I3: max-image-preview:large | K3: https://africanmarketingconfederation.org/ | L3: Open
A4: https://africanmarketingconfederation.org/african-marketing-confederation-tourism-chapter | B4: 200 | C4: 2xx | D4: Indexable | E4: https://africanmarketingconfederation.org/african-marketing-confederation-tourism-chapter | F4: self | G4: TRUE | H4: TRUE | I4: max-image-preview:large | K4: https://africanmarketingconfederation.org/african-marketing-confederation-tourism-chapter | L4: Open
A5: https://africanmarketingconfederation.org/amc-awards-2024 | B5: 200 | C5: 2xx | D5: Indexable | E5: https://africanmarketingconfederation.org/amc-awards-2024 | F5: self | G5: TRUE | H5: TRUE | I5: max-image-preview:large | K5: https://africanmarketingconfederation.org/amc-awards-2024 | L5: Open
A6: https://africanmarketingconfederation.org/amc-conference-2022-prospectus | B6: 200 | C6: 2xx | D6: Indexable | E6: https://africanmarketingconfederation.org/amc-conference-2022-prospectus | F6: self | G6: TRUE | H6: TRUE | I6: max-image-preview:large | K6: https://africanmarketingconfederation.org/amc-conference-2022-prospectus | L6: Open
A7: https://africanmarketingconfederation.org/amc-conference-2022-thank-you | B7: 200 | C7: 2xx | D7: Indexable | E7: https://africanmarketingconfederation.org/amc-conference-2022-thank-you | F7: self | G7: TRUE | H7: TRUE | I7: max-image-preview:large | K7: https://africanmarketingconfederation.org/amc-conference-2022-thank-you | L7: Open
A8: https://africanmarketingconfederation.org/amc-conference-2022 | B8: 200 | C8: 2xx | D8: Indexable | E8: https://africanmarketingconfederation.org/amc-conference-2022 | F8: self | G8: TRUE | H8: TRUE | I8: max-image-preview:large | K8: https://africanmarketingconfederation.org/amc-conference-2022 | L8: Open
A9: https://africanmarketingconfederation.org/amc-conference-2023 | B9: 200 | C9: 2xx | D9: Indexable | E9: https://africanmarketingconfederation.org/amc-conference-2023 | F9: self | G9: TRUE | H9: TRUE | I9: max-image-preview:large | K9: https://africanmarketingconfederation.org/amc-conference-2023 | L9: Open
A10: https://africanmarketingconfederation.org/amc-conference-2023/amc-awards-book-now | B10: 200 | C10: 2xx | D10: Indexable | E10: https://africanmarketingconfederation.org/amc-conference-2023/amc-awards-book-now | F10: self | G10: TRUE | H10: TRUE | I10: max-image-preview:large | K10: https://africanmarketingconfederation.org/amc-conference-2023/amc-awards-book-now | L10: Open
A11: https://africanmarketingconfederation.org/amc-conference-2023/amc-awards | B11: 200 | C11: 2xx | D11: Indexable | E11: https://africanmarketingconfederation.org/amc-conference-2023/amc-awards | F11: self | G11: TRUE | H11: TRUE | I11: max-image-preview:large | K11: https://africanmarketingconfederation.org/amc-conference-2023/amc-awards | L11: Open

Sheet Redirects
A1: URL | B1: Status Code | C1: Final URL | D1: Redirect Chain Length | E1: Redirect Target | F1: Redirect Hops | G1: HTTP->HTTPS Redirect | H1: Redirect Loop Flag | I1: Open in Main | J1: BACK TO DASHBOARD | K1: BACK TO DASHBOARD_1
A2: https://africanmarketingconfederation.org/about-us | B2: 200 | C2: https://africanmarketingconfederation.org/about-us | D2: 0 | G2: FALSE | H2: FALSE | I2: Open
A3: https://africanmarketingconfederation.org/ | B3: 200 | C3: https://africanmarketingconfederation.org/ | D3: 0 | G3: FALSE | H3: FALSE | I3: Open
A4: https://africanmarketingconfederation.org/african-marketing-confederation-tourism-chapter | B4: 200 | C4: https://africanmarketingconfederation.org/african-marketing-confederation-tourism-chapter | D4: 0 | G4: FALSE | H4: FALSE | I4: Open
A5: https://africanmarketingconfederation.org/amc-awards-2024 | B5: 200 | C5: https://africanmarketingconfederation.org/amc-awards-2024 | D5: 0 | G5: FALSE | H5: FALSE | I5: Open
A6: https://africanmarketingconfederation.org/amc-conference-2022-prospectus | B6: 200 | C6: https://africanmarketingconfederation.org/amc-conference-2022-prospectus | D6: 0 | G6: FALSE | H6: FALSE | I6: Open
A7: https://africanmarketingconfederation.org/amc-conference-2022-thank-you | B7: 200 | C7: https://africanmarketingconfederation.org/amc-conference-2022-thank-you | D7: 0 | G7: FALSE | H7: FALSE | I7: Open
A8: https://africanmarketingconfederation.org/amc-conference-2022 | B8: 200 | C8: https://africanmarketingconfederation.org/amc-conference-2022 | D8: 0 | G8: FALSE | H8: FALSE | I8: Open
A9: https://africanmarketingconfederation.org/amc-conference-2023 | B9: 200 | C9: https://africanmarketingconfederation.org/amc-conference-2023 | D9: 0 | G9: FALSE | H9: FALSE | I9: Open
A10: https://africanmarketingconfederation.org/amc-conference-2023/amc-awards-book-now | B10: 200 | C10: https://africanmarketingconfederation.org/amc-conference-2023/amc-awards-book-now | D10: 0 | G10: FALSE | H10: FALSE | I10: Open
A11: https://africanmarketingconfederation.org/amc-conference-2023/amc-awards | B11: 200 | C11: https://africanmarketingconfederation.org/amc-conference-2023/amc-awards | D11: 0 | G11: FALSE | H11: FALSE | I11: Open

Sheet Priority URLs
A1: URL | B1: Business Risk Score | C1: Severity Badge | D1: SEO Health Score | E1: GSC Impressions | F1: GSC CTR | G1: Revenue Intent | H1: Critical Issues Count | I1: Warning Issues Count | J1: Action Needed | K1: Why Prioritized | L1: Owner | M1: Status | N1: Sprint | O1: Indexability Reason | P1: Broken Internal Links Count | Q1: Canonical Type | R1: Open in Main | S1: Open in Technical | T1: BACK TO DASHBOARD | U1: BACK TO DASHBOARD_1
A2: https://africanmarketingconfederation.org/about-us | B2: 0 | C2: Unmeasured | E2: 200 | F2: 0.035 | G2: Standard | J2: No | K2: Broken internal links | L2: Dev | M2: Open | O2: Indexable | P2: 1 | Q2: self | R2: Open | S2: =IFERROR(HYPERLINK("#Technical!A"&MATCH(A2,Technical!A:A,0),"Open"),HYPERLINK("#Technical!A1","Open"))
A3: https://africanmarketingconfederation.org/ | B3: 0 | C3: Unmeasured | E3: 1108 | F3: 0.054151625 | G3: Standard | J3: No | K3: Broken internal links | L3: Dev | M3: Open | O3: Indexable | P3: 1 | Q3: self | R3: Open | S3: =IFERROR(HYPERLINK("#Technical!A"&MATCH(A3,Technical!A:A,0),"Open"),HYPERLINK("#Technical!A1","Open"))
A4: https://africanmarketingconfederation.org/african-marketing-confederation-tourism-chapter | B4: 0 | C4: Unmeasured | E4: 8 | F4: 0 | G4: Standard | J4: No | K4: Broken internal links | L4: Dev | M4: Open | O4: Indexable | P4: 1 | Q4: self | R4: Open | S4: =IFERROR(HYPERLINK("#Technical!A"&MATCH(A4,Technical!A:A,0),"Open"),HYPERLINK("#Technical!A1","Open"))
A5: https://africanmarketingconfederation.org/amc-awards-2024 | B5: 0 | C5: Unmeasured | E5: 0 | F5: 0 | G5: Standard | J5: No | K5: Broken internal links | L5: Dev | M5: Open | O5: Indexable | P5: 1 | Q5: self | R5: Open | S5: =IFERROR(HYPERLINK("#Technical!A"&MATCH(A5,Technical!A:A,0),"Open"),HYPERLINK("#Technical!A1","Open"))
A6: https://africanmarketingconfederation.org/amc-conference-2022-prospectus | B6: 0 | C6: Unmeasured | E6: 0 | F6: 0 | G6: Standard | J6: No | K6: Broken internal links | L6: Dev | M6: Open | O6: Indexable | P6: 1 | Q6: self | R6: Open | S6: =IFERROR(HYPERLINK("#Technical!A"&MATCH(A6,Technical!A:A,0),"Open"),HYPERLINK("#Technical!A1","Open"))
A7: https://africanmarketingconfederation.org/amc-conference-2022-thank-you | B7: 0 | C7: Unmeasured | E7: 0 | F7: 0 | G7: Standard | J7: No | K7: Broken internal links | L7: Dev | M7: Open | O7: Indexable | P7: 2 | Q7: self | R7: Open | S7: =IFERROR(HYPERLINK("#Technical!A"&MATCH(A7,Technical!A:A,0),"Open"),HYPERLINK("#Technical!A1","Open"))
A8: https://africanmarketingconfederation.org/amc-conference-2022 | B8: 0 | C8: Unmeasured | E8: 10 | F8: 0 | G8: Standard | J8: No | K8: Broken internal links | L8: Dev | M8: Open | O8: Indexable | P8: 1 | Q8: self | R8: Open | S8: =IFERROR(HYPERLINK("#Technical!A"&MATCH(A8,Technical!A:A,0),"Open"),HYPERLINK("#Technical!A1","Open"))
A9: https://africanmarketingconfederation.org/amc-conference-2023 | B9: 0 | C9: Unmeasured | E9: 24 | F9: 0.041666667 | G9: Standard | J9: No | K9: Broken internal links | L9: Dev | M9: Open | O9: Indexable | P9: 2 | Q9: self | R9: Open | S9: =IFERROR(HYPERLINK("#Technical!A"&MATCH(A9,Technical!A:A,0),"Open"),HYPERLINK("#Technical!A1","Open"))
A10: https://africanmarketingconfederation.org/amc-conference-2023/amc-awards-book-now | B10: 0 | C10: Unmeasured | E10: 0 | F10: 0 | G10: Standard | J10: No | K10: Broken internal links | L10: Dev | M10: Open | O10: Indexable | P10: 1 | Q10: self | R10: Open | S10: =IFERROR(HYPERLINK("#Technical!A"&MATCH(A10,Technical!A:A,0),"Open"),HYPERLINK("#Technical!A1","Open"))
A11: https://africanmarketingconfederation.org/amc-conference-2023/amc-awards | B11: 0 | C11: Unmeasured | E11: 34 | F11: 0.058823529 | G11: Standard | J11: No | K11: Broken internal links | L11: Dev | M11: Open | O11: Indexable | P11: 1 | Q11: self | R11: Open | S11: =IFERROR(HYPERLINK("#Technical!A"&MATCH(A11,Technical!A:A,0),"Open"),HYPERLINK("#Technical!A1","Open"))

Sheet AIOSEO
A1: URL | B1: WordPress Post ID | C1: Direct Edit Link | D1: AIOSEO Panel | E1: Severity | F1: Issue | G1: Priority Score | H1: Current Value | I1: Recommended Target | J1: How to Fix in AIOSEO | K1: Reference Tab | L1: Reference Field | M1: Action Needed | N1: Owner | O1: Status | P1: Est. Hours | Q1: Stable Issue ID | R1: Why It Matters | S1: Open in Main | T1: Open in Technical | U1: BACK TO DASHBOARD | V1: BACK TO DASHBOARD_1
A2: https://africanmarketingconfederation.org/ | B2: 8 | C2: https://africanmarketingconfederation.org/wp-admin/post.php?post=8&action=edit | D2: Links | E2: Critical | F2: Broken internal links | G2: 105 | H2: 1 | I2: 0 | J2: Replace dead links with live targets, or remove them in the page editor. | K2: Links | L2: Broken Internal Links Count | M2: Yes | N2: Dev | O2: Open | P2: 10 | Q2: https://africanmarketingconfederation.org/::aioseo_broken_internal_links | R2: Broken links waste crawl budget and degrade user experience. | S2: Open | T2: =IFERROR(HYPERLINK("#Technical!A"&MATCH(A2,Technical!A:A,0),"Open"),HYPERLINK("#Technical!A1","Open"))
A3: https://africanmarketingconfederation.org/about-us | B3: 84 | C3: https://africanmarketingconfederation.org/wp-admin/post.php?post=84&action=edit | D3: Links | E3: Critical | F3: Broken internal links | G3: 105 | H3: 1 | I3: 0 | J3: Replace dead links with live targets, or remove them in the page editor. | K3: Links | L3: Broken Internal Links Count | M3: Yes | N3: Dev | O3: Open | P3: 10 | Q3: https://africanmarketingconfederation.org/about-us::aioseo_broken_internal_links | R3: Broken links waste crawl budget and degrade user experience. | S3: Open | T3: =IFERROR(HYPERLINK("#Technical!A"&MATCH(A3,Technical!A:A,0),"Open"),HYPERLINK("#Technical!A1","Open"))
A4: https://africanmarketingconfederation.org/african-marketing-confederation-tourism-chapter | B4: 28165 | C4: https://africanmarketingconfederation.org/wp-admin/post.php?post=28165&action=edit | D4: Links | E4: Critical | F4: Broken internal links | G4: 105 | H4: 1 | I4: 0 | J4: Replace dead links with live targets, or remove them in the page editor. | K4: Links | L4: Broken Internal Links Count | M4: Yes | N4: Dev | O4: Open | P4: 10 | Q4: https://africanmarketingconfederation.org/african-marketing-confederation-tourism-chapter::aioseo_broken_internal_links | R4: Broken links waste crawl budget and degrade user experience. | S4: Open | T4: =IFERROR(HYPERLINK("#Technical!A"&MATCH(A4,Technical!A:A,0),"Open"),HYPERLINK("#Technical!A1","Open"))
A5: https://africanmarketingconfederation.org/amc-awards-2024 | B5: 16125 | C5: https://africanmarketingconfederation.org/wp-admin/post.php?post=16125&action=edit | D5: Links | E5: Critical | F5: Broken internal links | G5: 105 | H5: 1 | I5: 0 | J5: Replace dead links with live targets, or remove them in the page editor. | K5: Links | L5: Broken Internal Links Count | M5: Yes | N5: Dev | O5: Open | P5: 10 | Q5: https://africanmarketingconfederation.org/amc-awards-2024::aioseo_broken_internal_links | R5: Broken links waste crawl budget and degrade user experience. | S5: Open | T5: =IFERROR(HYPERLINK("#Technical!A"&MATCH(A5,Technical!A:A,0),"Open"),HYPERLINK("#Technical!A1","Open"))
A6: https://africanmarketingconfederation.org/amc-conference-2022 | B6: 4494 | C6: https://africanmarketingconfederation.org/wp-admin/post.php?post=4494&action=edit | D6: Links | E6: Critical | F6: Broken internal links | G6: 105 | H6: 1 | I6: 0 | J6: Replace dead links with live targets, or remove them in the page editor. | K6: Links | L6: Broken Internal Links Count | M6: Yes | N6: Dev | O6: Open | P6: 10 | Q6: https://africanmarketingconfederation.org/amc-conference-2022::aioseo_broken_internal_links | R6: Broken links waste crawl budget and degrade user experience. | S6: Open | T6: =IFERROR(HYPERLINK("#Technical!A"&MATCH(A6,Technical!A:A,0),"Open"),HYPERLINK("#Technical!A1","Open"))
A7: https://africanmarketingconfederation.org/amc-conference-2022-prospectus | B7: 5619 | C7: https://africanmarketingconfederation.org/wp-admin/post.php?post=5619&action=edit | D7: Links | E7: Critical | F7: Broken internal links | G7: 105 | H7: 1 | I7: 0 | J7: Replace dead links with live targets, or remove them in the page editor. | K7: Links | L7: Broken Internal Links Count | M7: Yes | N7: Dev | O7: Open | P7: 10 | Q7: https://africanmarketingconfederation.org/amc-conference-2022-prospectus::aioseo_broken_internal_links | R7: Broken links waste crawl budget and degrade user experience. | S7: Open | T7: =IFERROR(HYPERLINK("#Technical!A"&MATCH(A7,Technical!A:A,0),"Open"),HYPERLINK("#Technical!A1","Open"))
A8: https://africanmarketingconfederation.org/amc-conference-2022-thank-you | B8: 4941 | C8: https://africanmarketingconfederation.org/wp-admin/post.php?post=4941&action=edit | D8: Links | E8: Critical | F8: Broken internal links | G8: 105 | H8: 2 | I8: 0 | J8: Replace dead links with live targets, or remove them in the page editor. | K8: Links | L8: Broken Internal Links Count | M8: Yes | N8: Dev | O8: Open | P8: 10 | Q8: https://africanmarketingconfederation.org/amc-conference-2022-thank-you::aioseo_broken_internal_links | R8: Broken links waste crawl budget and degrade user experience. | S8: Open | T8: =IFERROR(HYPERLINK("#Technical!A"&MATCH(A8,Technical!A:A,0),"Open"),HYPERLINK("#Technical!A1","Open"))
A9: https://africanmarketingconfederation.org/amc-conference-2023 | B9: 12371 | C9: https://africanmarketingconfederation.org/wp-admin/post.php?post=12371&action=edit | D9: Links | E9: Critical | F9: Broken internal links | G9: 105 | H9: 2 | I9: 0 | J9: Replace dead links with live targets, or remove them in the page editor. | K9: Links | L9: Broken Internal Links Count | M9: Yes | N9: Dev | O9: Open | P9: 10 | Q9: https://africanmarketingconfederation.org/amc-conference-2023::aioseo_broken_internal_links | R9: Broken links waste crawl budget and degrade user experience. | S9: Open | T9: =IFERROR(HYPERLINK("#Technical!A"&MATCH(A9,Technical!A:A,0),"Open"),HYPERLINK("#Technical!A1","Open"))
A10: https://africanmarketingconfederation.org/amc-conference-2023/amc-awards | B10: 12954 | C10: https://africanmarketingconfederation.org/wp-admin/post.php?post=12954&action=edit | D10: Links | E10: Critical | F10: Broken internal links | G10: 105 | H10: 1 | I10: 0 | J10: Replace dead links with live targets, or remove them in the page editor. | K10: Links | L10: Broken Internal Links Count | M10: Yes | N10: Dev | O10: Open | P10: 10 | Q10: https://africanmarketingconfederation.org/amc-conference-2023/amc-awards::aioseo_broken_internal_links | R10: Broken links waste crawl budget and degrade user experience. | S10: Open | T10: =IFERROR(HYPERLINK("#Technical!A"&MATCH(A10,Technical!A:A,0),"Open"),HYPERLINK("#Technical!A1","Open"))
A11: https://africanmarketingconfederation.org/amc-conference-2023/amc-awards-book-now | B11: 13164 | C11: https://africanmarketingconfederation.org/wp-admin/post.php?post=13164&action=edit | D11: Links | E11: Critical | F11: Broken internal links | G11: 105 | H11: 1 | I11: 0 | J11: Replace dead links with live targets, or remove them in the page editor. | K11: Links | L11: Broken Internal Links Count | M11: Yes | N11: Dev | O11: Open | P11: 10 | Q11: https://africanmarketingconfederation.org/amc-conference-2023/amc-awards-book-now::aioseo_broken_internal_links | R11: Broken links waste crawl budget and degrade user experience. | S11: Open | T11: =IFERROR(HYPERLINK("#Technical!A"&MATCH(A11,Technical!A:A,0),"Open"),HYPERLINK("#Technical!A1","Open"))
A12: https://africanmarketingconfederation.org/amc-conference-2023/amc-awards-book-now | B12: 13164 | C12: https://africanmarketingconfederation.org/wp-admin/post.php?post=13164&action=edit | D12: Basic SEO | E12: Warning | F12: Missing meta description | G12: 67 | H12: Missing | I12: 120-160 characters | J12: In AIOSEO snippet settings, add a concise, unique meta description aligned to page intent. | K12: Main | L12: Meta Description | M12: Yes | N12: Copy Writer | O12: Open | P12: 4 | Q12: https://africanmarketingconfederation.org/amc-conference-2023/amc-awards-book-now::aioseo_missing_meta_description | R12: Missing descriptions reduce control over search snippet messaging. | S12: Open | T12: =IFERROR(HYPERLINK("#Technical!A"&MATCH(A12,Technical!A:A,0),"Open"),HYPERLINK("#Technical!A1","Open"))
A13: https://africanmarketingconfederation.org/ | B13: 8 | C13: https://africanmarketingconfederation.org/wp-admin/post.php?post=8&action=edit | D13: Content | E13: Warning | F13: Low AEO readiness score | G13: 67 | H13: 0 | I13: >=60 | J13: Add concise answer blocks, question-led subheadings, and clear structured sections. | K13: AEO | L13: AEO Readiness Score | M13: Yes | N13: Copy Writer | O13: Open | P13: 4 | Q13: https://africanmarketingconfederation.org/::aioseo_low_aeo_readiness_score | R13: Weak answer-style structure lowers AI/answer-engine retrieval potential. | S13: Open | T13: =IFERROR(HYPERLINK("#Technical!A"&MATCH(A13,Technical!A:A,0),"Open"),HYPERLINK("#Technical!A1","Open"))
A14: https://africanmarketingconfederation.org/about-us | B14: 84 | C14: https://africanmarketingconfederation.org/wp-admin/post.php?post=84&action=edit | D14: Content | E14: Warning | F14: Low AEO readiness score | G14: 67 | H14: 0 | I14: >=60 | J14: Add concise answer blocks, question-led subheadings, and clear structured sections. | K14: AEO | L14: AEO Readiness Score | M14: Yes | N14: Copy Writer | O14: Open | P14: 4 | Q14: https://africanmarketingconfederation.org/about-us::aioseo_low_aeo_readiness_score | R14: Weak answer-style structure lowers AI/answer-engine retrieval potential. | S14: Open | T14: =IFERROR(HYPERLINK("#Technical!A"&MATCH(A14,Technical!A:A,0),"Open"),HYPERLINK("#Technical!A1","Open"))
A15: https://africanmarketingconfederation.org/african-marketing-confederation-tourism-chapter | B15: 28165 | C15: https://africanmarketingconfederation.org/wp-admin/post.php?post=28165&action=edit | D15: Content | E15: Warning | F15: Low AEO readiness score | G15: 67 | H15: 0 | I15: >=60 | J15: Add concise answer blocks, question-led subheadings, and clear structured sections. | K15: AEO | L15: AEO Readiness Score | M15: Yes | N15: Copy Writer | O15: Open | P15: 4 | Q15: https://africanmarketingconfederation.org/african-marketing-confederation-tourism-chapter::aioseo_low_aeo_readiness_score | R15: Weak answer-style structure lowers AI/answer-engine retrieval potential. | S15: Open | T15: =IFERROR(HYPERLINK("#Technical!A"&MATCH(A15,Technical!A:A,0),"Open"),HYPERLINK("#Technical!A1","Open"))
A16: https://africanmarketingconfederation.org/amc-awards-2024 | B16: 16125 | C16: https://africanmarketingconfederation.org/wp-admin/post.php?post=16125&action=edit | D16: Content | E16: Warning | F16: Low AEO readiness score | G16: 67 | H16: 0 | I16: >=60 | J16: Add concise answer blocks, question-led subheadings, and clear structured sections. | K16: AEO | L16: AEO Readiness Score | M16: Yes | N16: Copy Writer | O16: Open | P16: 4 | Q16: https://africanmarketingconfederation.org/amc-awards-2024::aioseo_low_aeo_readiness_score | R16: Weak answer-style structure lowers AI/answer-engine retrieval potential. | S16: Open | T16: =IFERROR(HYPERLINK("#Technical!A"&MATCH(A16,Technical!A:A,0),"Open"),HYPERLINK("#Technical!A1","Open"))
A17: https://africanmarketingconfederation.org/amc-conference-2022 | B17: 4494 | C17: https://africanmarketingconfederation.org/wp-admin/post.php?post=4494&action=edit | D17: Content | E17: Warning | F17: Low AEO readiness score | G17: 67 | H17: 0 | I17: >=60 | J17: Add concise answer blocks, question-led subheadings, and clear structured sections. | K17: AEO | L17: AEO Readiness Score | M17: Yes | N17: Copy Writer | O17: Open | P17: 4 | Q17: https://africanmarketingconfederation.org/amc-conference-2022::aioseo_low_aeo_readiness_score | R17: Weak answer-style structure lowers AI/answer-engine retrieval potential. | S17: Open | T17: =IFERROR(HYPERLINK("#Technical!A"&MATCH(A17,Technical!A:A,0),"Open"),HYPERLINK("#Technical!A1","Open"))
A18: https://africanmarketingconfederation.org/amc-conference-2022-prospectus | B18: 5619 | C18: https://africanmarketingconfederation.org/wp-admin/post.php?post=5619&action=edit | D18: Content | E18: Warning | F18: Low AEO readiness score | G18: 67 | H18: 0 | I18: >=60 | J18: Add concise answer blocks, question-led subheadings, and clear structured sections. | K18: AEO | L18: AEO Readiness Score | M18: Yes | N18: Copy Writer | O18: Open | P18: 4 | Q18: https://africanmarketingconfederation.org/amc-conference-2022-prospectus::aioseo_low_aeo_readiness_score | R18: Weak answer-style structure lowers AI/answer-engine retrieval potential. | S18: Open | T18: =IFERROR(HYPERLINK("#Technical!A"&MATCH(A18,Technical!A:A,0),"Open"),HYPERLINK("#Technical!A1","Open"))
A19: https://africanmarketingconfederation.org/amc-conference-2022-thank-you | B19: 4941 | C19: https://africanmarketingconfederation.org/wp-admin/post.php?post=4941&action=edit | D19: Content | E19: Warning | F19: Low AEO readiness score | G19: 67 | H19: 0 | I19: >=60 | J19: Add concise answer blocks, question-led subheadings, and clear structured sections. | K19: AEO | L19: AEO Readiness Score | M19: Yes | N19: Copy Writer | O19: Open | P19: 4 | Q19: https://africanmarketingconfederation.org/amc-conference-2022-thank-you::aioseo_low_aeo_readiness_score | R19: Weak answer-style structure lowers AI/answer-engine retrieval potential. | S19: Open | T19: =IFERROR(HYPERLINK("#Technical!A"&MATCH(A19,Technical!A:A,0),"Open"),HYPERLINK("#Technical!A1","Open"))
A20: https://africanmarketingconfederation.org/amc-conference-2023 | B20: 12371 | C20: https://africanmarketingconfederation.org/wp-admin/post.php?post=12371&action=edit | D20: Content | E20: Warning | F20: Low AEO readiness score | G20: 67 | H20: 0 | I20: >=60 | J20: Add concise answer blocks, question-led subheadings, and clear structured sections. | K20: AEO | L20: AEO Readiness Score | M20: Yes | N20: Copy Writer | O20: Open | P20: 4 | Q20: https://africanmarketingconfederation.org/amc-conference-2023::aioseo_low_aeo_readiness_score | R20: Weak answer-style structure lowers AI/answer-engine retrieval potential. | S20: Open | T20: =IFERROR(HYPERLINK("#Technical!A"&MATCH(A20,Technical!A:A,0),"Open"),HYPERLINK("#Technical!A1","Open"))
A21: https://africanmarketingconfederation.org/amc-conference-2023/amc-awards | B21: 12954 | C21: https://africanmarketingconfederation.org/wp-admin/post.php?post=12954&action=edit | D21: Content | E21: Warning | F21: Low AEO readiness score | G21: 67 | H21: 0 | I21: >=60 | J21: Add concise answer blocks, question-led subheadings, and clear structured sections. | K21: AEO | L21: AEO Readiness Score | M21: Yes | N21: Copy Writer | O21: Open | P21: 4 | Q21: https://africanmarketingconfederation.org/amc-conference-2023/amc-awards::aioseo_low_aeo_readiness_score | R21: Weak answer-style structure lowers AI/answer-engine retrieval potential. | S21: Open | T21: =IFERROR(HYPERLINK("#Technical!A"&MATCH(A21,Technical!A:A,0),"Open"),HYPERLINK("#Technical!A1","Open"))
A22: https://africanmarketingconfederation.org/amc-conference-2023/amc-awards-book-now | B22: 13164 | C22: https://africanmarketingconfederation.org/wp-admin/post.php?post=13164&action=edit | D22: Content | E22: Warning | F22: Low AEO readiness score | G22: 67 | H22: 0 | I22: >=60 | J22: Add concise answer blocks, question-led subheadings, and clear structured sections. | K22: AEO | L22: AEO Readiness Score | M22: Yes | N22: Copy Writer | O22: Open | P22: 4 | Q22: https://africanmarketingconfederation.org/amc-conference-2023/amc-awards-book-now::aioseo_low_aeo_readiness_score | R22: Weak answer-style structure lowers AI/answer-engine retrieval potential. | S22: Open | T22: =IFERROR(HYPERLINK("#Technical!A"&MATCH(A22,Technical!A:A,0),"Open"),HYPERLINK("#Technical!A1","Open"))
A23: https://africanmarketingconfederation.org/ | B23: 8 | C23: https://africanmarketingconfederation.org/wp-admin/post.php?post=8&action=edit | D23: Readability | E23: Warning | F23: Low image alt coverage | G23: 67 | H23: 79.03 | I23: >=80% | J23: Add descriptive alt text to meaningful images in the page editor/media fields. | K23: Media | L23: Image Alt Coverage (%) | M23: Yes | N23: Copy Writer | O23: Open | P23: 4 | Q23: https://africanmarketingconfederation.org/::aioseo_low_image_alt_coverage | R23: Missing alt text reduces accessibility and weakens image context signals. | S23: Open | T23: =IFERROR(HYPERLINK("#Technical!A"&MATCH(A23,Technical!A:A,0),"Open"),HYPERLINK("#Technical!A1","Open"))
A24: https://africanmarketingconfederation.org/ | B24: 8 | C24: https://africanmarketingconfederation.org/wp-admin/post.php?post=8&action=edit | D24: Readability | E24: Warning | F24: Thin content | G24: 67 | H24: 35 | I24: >=300 words (quality first) | J24: Expand page copy with useful, unique sections that answer key user questions. | K24: Content | L24: Word Count | M24: Yes | N24: Copy Writer | O24: Open | P24: 4 | Q24: https://africanmarketingconfederation.org/::aioseo_thin_content | R24: Low-content pages can struggle to satisfy intent and rank competitively. | S24: Open | T24: =IFERROR(HYPERLINK("#Technical!A"&MATCH(A24,Technical!A:A,0),"Open"),HYPERLINK("#Technical!A1","Open"))
... A96: https://africanmarketingconfederation.org/amc-conference-2022-thank-you | B96: 4941 | C96: https://africanmarketingconfederation.org/wp-admin/post.php?post=4941&action=edit | D96: Title | E96: Observation | F96: SEO title too long | G96: 37 | H96: 65 | I96: 40-60 characters | J96: Shorten title in AIOSEO snippet editor and keep key terms in the first 55-60 characters. | K96: Main | L96: Title | M96: No | N96: Copy Writer | O96: Open | P96: 4 | Q96: https://africanmarketingconfederation.org/amc-conference-2022-thank-you::aioseo_seo_title_too_long | R96: Long titles are more likely to truncate in SERPs. | S96: Open | T96: =IFERROR(HYPERLINK("#Technical!A"&MATCH(A96,Technical!A:A,0),"Open"),HYPERLINK("#Technical!A1","Open"))

Sheet Security
A1: URL | B1: Strict-Transport-Security | C1: Content-Security-Policy | D1: X-Content-Type-Options | E1: X-Frame-Options | F1: Referrer-Policy | G1: Permissions-Policy | H1: Robots.txt Accessible | I1: Sitemap in Robots.txt | J1: Robots.txt Crawl-Delay | K1: Robots.txt Disallow / | L1: Open in Main | M1: BACK TO DASHBOARD | N1: BACK TO DASHBOARD_1
A2: https://africanmarketingconfederation.org/about-us | L2: Open
A3: https://africanmarketingconfederation.org/ | L3: Open
A4: https://africanmarketingconfederation.org/african-marketing-confederation-tourism-chapter | L4: Open
A5: https://africanmarketingconfederation.org/amc-awards-2024 | L5: Open
A6: https://africanmarketingconfederation.org/amc-conference-2022-prospectus | L6: Open
A7: https://africanmarketingconfederation.org/amc-conference-2022-thank-you | L7: Open
A8: https://africanmarketingconfederation.org/amc-conference-2022 | L8: Open
A9: https://africanmarketingconfederation.org/amc-conference-2023 | L9: Open
A10: https://africanmarketingconfederation.org/amc-conference-2023/amc-awards-book-now | L10: Open
A11: https://africanmarketingconfederation.org/amc-conference-2023/amc-awards | L11: Open

Sheet Summary
A1: Section | B1: Severity | C1: Issue | D1: Affected URL Count | E1: Reference Tab | F1: Affected URLs (sample) | G1: BACK TO DASHBOARD | H1: BACK TO DASHBOARD_1
A2: AEO Opportunities | B2: Warning | C2: Low AEO Readiness Score | D2: 10 | E2: AEO | F2: https://africanmarketingconfederation.org/about-us | https://africanmarketingconfederation.org/ | https://africanmarketingconfederation.org/african-marketing-confederation-tourism-chapter | https://africanmarketingconfederation.org/amc-awards-2024 | https://africanmarketingconfederation.org/amc-conference-2022-prospectus | https://africanmarketingconfederation.org/amc-conference-2022-thank-you | https://africanmarketingconfederation.org/amc-conference-2022 | https://africanmarketingconfederation.org/amc-conference-2023 | https://africanmarketingconfederation.org/amc-conference-2023/amc-awards-book-now | https://africanmarketingconfederation.org/amc-conference-2023/amc-awards || Full list: see AEO tab
A3: AEO Opportunities | B3: Warning | C3: Missing FAQ/QA Schema | D3: 0 | E3: AEO | F3: || Full list: see AEO tab
A4: AEO Opportunities | B4: Observation | C4: No 40-60 Word Answer Paragraphs | D4: 10 | E4: AEO | F4: https://africanmarketingconfederation.org/about-us | https://africanmarketingconfederation.org/ | https://africanmarketingconfederation.org/african-marketing-confederation-tourism-chapter | https://africanmarketingconfederation.org/amc-awards-2024 | https://africanmarketingconfederation.org/amc-conference-2022-prospectus | https://africanmarketingconfederation.org/amc-conference-2022-thank-you | https://africanmarketingconfederation.org/amc-conference-2022 | https://africanmarketingconfederation.org/amc-conference-2023 | https://africanmarketingconfederation.org/amc-conference-2023/amc-awards-book-now | https://africanmarketingconfederation.org/amc-conference-2023/amc-awards || Full list: see AEO tab
A5: AEO Opportunities | B5: Observation | C5: No Answer-Friendly Structure | D5: 10 | E5: AEO | F5: https://africanmarketingconfederation.org/about-us | https://africanmarketingconfederation.org/ | https://africanmarketingconfederation.org/african-marketing-confederation-tourism-chapter | https://africanmarketingconfederation.org/amc-awards-2024 | https://africanmarketingconfederation.org/amc-conference-2022-prospectus | https://africanmarketingconfederation.org/amc-conference-2022-thank-you | https://africanmarketingconfederation.org/amc-conference-2022 | https://africanmarketingconfederation.org/amc-conference-2023 | https://africanmarketingconfederation.org/amc-conference-2023/amc-awards-book-now | https://africanmarketingconfederation.org/amc-conference-2023/amc-awards || Full list: see AEO tab
A6: AEO Opportunities | B6: Observation | C6: No Question Headings | D6: 10 | E6: AEO | F6: https://africanmarketingconfederation.org/about-us | https://africanmarketingconfederation.org/ | https://africanmarketingconfederation.org/african-marketing-confederation-tourism-chapter | https://africanmarketingconfederation.org/amc-awards-2024 | https://africanmarketingconfederation.org/amc-conference-2022-prospectus | https://africanmarketingconfederation.org/amc-conference-2022-thank-you | https://africanmarketingconfederation.org/amc-conference-2022 | https://africanmarketingconfederation.org/amc-conference-2023 | https://africanmarketingconfederation.org/amc-conference-2023/amc-awards-book-now | https://africanmarketingconfederation.org/amc-conference-2023/amc-awards || Full list: see AEO tab
A7: AEO Opportunities | F7: Detailed rows: see AEO tab
A8: Issue Counts | B8: Critical | C8: Broken Internal Links | D8: 10 | E8: Links | F8: https://africanmarketingconfederation.org/about-us | https://africanmarketingconfederation.org/ | https://africanmarketingconfederation.org/african-marketing-confederation-tourism-chapter | https://africanmarketingconfederation.org/amc-awards-2024 | https://africanmarketingconfederation.org/amc-conference-2022-prospectus | https://africanmarketingconfederation.org/amc-conference-2022-thank-you | https://africanmarketingconfederation.org/amc-conference-2022 | https://africanmarketingconfederation.org/amc-conference-2023 | https://africanmarketingconfederation.org/amc-conference-2023/amc-awards-book-now | https://africanmarketingconfederation.org/amc-conference-2023/amc-awards || Full list: see Technical/Links/Indexability tabs
A9: Issue Counts | B9: Critical | C9: CWV LCP Above 4.0s | D9: 0 | E9: Technical | F9: || Full list: see Technical/Links/Indexability tabs
A10: Issue Counts | B10: Critical | C10: Canonical Points Elsewhere | D10: 0 | E10: Indexability | F10: || Full list: see Technical/Links/Indexability tabs
A11: Issue Counts | B11: Critical | C11: Missing Title | D11: 0 | E11: Technical | F11: || Full list: see Technical/Links/Indexability tabs
A12: Issue Counts | B12: Critical | C12: Noindex Directive | D12: 0 | E12: Indexability | F12: || Full list: see Technical/Links/Indexability tabs
A13: Issue Counts | B13: Critical | C13: Non-200 Status | D13: 0 | E13: Technical | F13: || Full list: see Technical/Links/Indexability tabs
A14: Issue Counts | B14: Critical | C14: Robots.txt Disallow Root | D14: 0 | E14: Technical | F14: || Full list: see Technical/Links/Indexability tabs
A15: Issue Counts | B15: Warning | C15: Low AEO Readiness Score | D15: 10 | E15: AEO | F15: https://africanmarketingconfederation.org/about-us | https://africanmarketingconfederation.org/ | https://africanmarketingconfederation.org/african-marketing-confederation-tourism-chapter | https://africanmarketingconfederation.org/amc-awards-2024 | https://africanmarketingconfederation.org/amc-conference-2022-prospectus | https://africanmarketingconfederation.org/amc-conference-2022-thank-you | https://africanmarketingconfederation.org/amc-conference-2022 | https://africanmarketingconfederation.org/amc-conference-2023 | https://africanmarketingconfederation.org/amc-conference-2023/amc-awards-book-now | https://africanmarketingconfederation.org/amc-conference-2023/amc-awards || Full list: see Technical/Links/Indexability tabs
A16: Issue Counts | B16: Warning | C16: Low Image Alt Coverage | D16: 9 | E16: Technical | F16: https://africanmarketingconfederation.org/about-us | https://africanmarketingconfederation.org/ | https://africanmarketingconfederation.org/amc-awards-2024 | https://africanmarketingconfederation.org/amc-conference-2022-prospectus | https://africanmarketingconfederation.org/amc-conference-2022-thank-you | https://africanmarketingconfederation.org/amc-conference-2022 | https://africanmarketingconfederation.org/amc-conference-2023 | https://africanmarketingconfederation.org/amc-conference-2023/amc-awards-book-now | https://africanmarketingconfederation.org/amc-conference-2023/amc-awards || Full list: see Technical/Links/Indexability tabs
A17: Issue Counts | B17: Warning | C17: Missing H1 | D17: 4 | E17: Technical | F17: https://africanmarketingconfederation.org/amc-conference-2022-prospectus | https://africanmarketingconfederation.org/amc-conference-2022-thank-you | https://africanmarketingconfederation.org/amc-conference-2022 | https://africanmarketingconfederation.org/amc-conference-2023/amc-awards-book-now || Full list: see Technical/Links/Indexability tabs
A18: Issue Counts | B18: Warning | C18: Multiple H1 | D18: 3 | E18: Technical | F18: https://africanmarketingconfederation.org/ | https://africanmarketingconfederation.org/african-marketing-confederation-tourism-chapter | https://africanmarketingconfederation.org/amc-awards-2024 || Full list: see Technical/Links/Indexability tabs
A19: Issue Counts | B19: Warning | C19: Missing Meta Description | D19: 1 | E19: Technical | F19: https://africanmarketingconfederation.org/amc-conference-2023/amc-awards-book-now || Full list: see Technical/Links/Indexability tabs
... A41: Issue Counts | B41: Observation | C41: llms.txt Missing | D41: 0 | E41: Technical | F41: || Full list: see Technical/Links/Indexability tabs
A42: Issue Counts
A43: Top 10 Critical URLs
A44: Top Issues by Template
A45: Top Issues by Template | B45: Observation | C45: /amc-conference-2023/ -> Unmeasured | D45: 3 | E45: Pattern and Template Issues
A46: Top Issues by Template | B46: Observation | C46: /about-us/ -> Unmeasured | D46: 1 | E46: Pattern and Template Issues
A47: Top Issues by Template | B47: Observation | C47: / -> Unmeasured | D47: 1 | E47: Pattern and Template Issues
A48: Top Issues by Template | B48: Observation | C48: /african-marketing-confederation-tourism-chapter/ -> Unmeasured | D48: 1 | E48: Pattern and Template Issues
A49: Top Issues by Template | B49: Observation | C49: /amc-awards-2024/ -> Unmeasured | D49: 1 | E49: Pattern and Template Issues
A50: Top Issues by Template | B50: Observation | C50: /amc-conference-2022-prospectus/ -> Unmeasured | D50: 1 | E50: Pattern and Template Issues
A51: Top Issues by Template | B51: Observation | C51: /amc-conference-2022-thank-you/ -> Unmeasured | D51: 1 | E51: Pattern and Template Issues
A52: Top Issues by Template | B52: Observation | C52: /amc-conference-2022/ -> Unmeasured | D52: 1 | E52: Pattern and Template Issues

Sheet LinksDetail
A1: Source URL | B1: Target URL | C1: Anchor Text | D1: Rel | E1: Link Type | F1: Nofollow | G1: Target Status (if crawled) | H1: Crawlable | I1: BACK TO DASHBOARD | J1: BACK TO DASHBOARD_1
A2: https://africanmarketingconfederation.org/about-us | B2: https://africanmarketingconfederation.org/ | E2: Internal | F2: FALSE | G2: 200 | H2: TRUE
A3: https://africanmarketingconfederation.org/about-us | B3: https://africanmarketingconfederation.org/ | C3: HOME | E3: Internal | F3: FALSE | G3: 200 | H3: TRUE
A4: https://africanmarketingconfederation.org/about-us | B4: https://africanmarketingconfederation.org/about-us | C4: ABOUT US | E4: Internal | F4: FALSE | G4: 200 | H4: TRUE
A5: https://africanmarketingconfederation.org/about-us | B5: https://africanmarketingconfederation.org/sub-committees | C5: AMC COMMITTEES | E5: Internal | F5: FALSE | G5: 200 | H5: TRUE
A6: https://africanmarketingconfederation.org/about-us | B6: https://africanmarketingconfederation.org/members | C6: MEMBERS | E6: Internal | F6: FALSE | G6: 200 | H6: TRUE
A7: https://africanmarketingconfederation.org/about-us | B7: https://africanmarketingconfederation.org/african-marketing-confederation-tourism-chapter | C7: TOURISM CHAPTER | E7: Internal | F7: FALSE | G7: 200 | H7: TRUE
A8: https://africanmarketingconfederation.org/about-us | B8: https://africanmarketingconfederation.org/education | C8: EDUCATION | E8: Internal | F8: FALSE | G8: 200 | H8: TRUE
A9: https://africanmarketingconfederation.org/about-us | B9: https://africanmarketingconfederation.org/chartered-marketer-africa | C9: CHARTERED MARKETER (AFRICA) | E9: Internal | F9: FALSE | G9: 200 | H9: TRUE
A10: https://africanmarketingconfederation.org/about-us | B10: https://africanmarketingconfederation.org/certified-professional-marketer-africa | C10: CPM(A) | E10: Internal | F10: FALSE | G10: 200 | H10: TRUE
A11: https://africanmarketingconfederation.org/about-us | B11: https://africanmarketingconfederation.org/news-articles | C11: NEWS & PUBLICATIONS | E11: Internal | F11: FALSE | G11: 200 | H11: TRUE
A12: https://africanmarketingconfederation.org/about-us | B12: https://africanmarketingconfederation.org/news-articles | C12: NEWS ARTICLES | E12: Internal | F12: FALSE | G12: 200 | H12: TRUE
A13: https://africanmarketingconfederation.org/about-us | B13: https://africanmarketingconfederation.org/publications-2 | C13: PUBLICATIONS | E13: Internal | F13: FALSE | G13: 200 | H13: TRUE
A14: https://africanmarketingconfederation.org/about-us | B14: https://africanmarketingconfederation.org/amc-conference-2026 | C14: AMC Conference | E14: Internal | F14: FALSE | G14: 200 | H14: TRUE
... A28: https://africanmarketingconfederation.org/about-us | B28: https://africanmarketingconfederation.org/contact-us | C28: CONTACT US | E28: Internal | F28: FALSE | G28: 200 | H28: TRUE
A29: https://africanmarketingconfederation.org/about-us | B29: https://www.linkedin.com/in/helen-mcintee-780347a | C29: Linkedin | E29: External | F29: FALSE | H29: TRUE
A30: https://africanmarketingconfederation.org/about-us | B30: https://www.linkedin.com/in/david-balikuddembe-chartered-marketer-99899525?originalSubdomain=ug | C30: Linkedin | E30: External | F30: FALSE | H30: TRUE
A31: https://africanmarketingconfederation.org/about-us | B31: https://www.linkedin.com/in/nigel-tattersall-72a0771a8 | C31: Linkedin | E31: External | F31: FALSE | H31: TRUE
A32: https://africanmarketingconfederation.org/about-us | B32: https://www.linkedin.com/in/irene-gregory-aa058811 | C32: Linkedin | E32: External | F32: FALSE | H32: TRUE
A33: https://africanmarketingconfederation.org/about-us | B33: https://www.linkedin.com/in/kwabena-agyekum-60150832 | C33: Linkedin | E33: External | F33: FALSE | H33: TRUE
A34: https://africanmarketingconfederation.org/about-us | B34: https://africanmarketingconfederation.org/members | C34: Read More About Our Members | E34: Internal | F34: FALSE | G34: 200 | H34: TRUE
A35: https://africanmarketingconfederation.org/about-us | B35: https://africanmarketingconfederation.org/publications-2 | C35: Strategic Marketing for AfricaMagazine | E35: Internal | F35: FALSE | G35: 200 | H35: TRUE
A36: https://africanmarketingconfederation.org/about-us | B36: https://www.facebook.com/The-African-Marketing-Confederation-108980418182403 | E36: External | F36: FALSE | H36: TRUE
A37: https://africanmarketingconfederation.org/about-us | B37: https://www.linkedin.com/company/african-marketing-confederation | E37: External | F37: FALSE | H37: TRUE
A38: https://africanmarketingconfederation.org/about-us | B38: https://africanmarketingconfederation.org/privacy-policy | C38: © 2026 by African Marketing Confederation | Privacy Policy | E38: Internal | F38: FALSE | G38: 200 | H38: TRUE
A39: https://africanmarketingconfederation.org/about-us | B39: https://africanmarketingconfederation.org/amc-conference-2025-delegate-packages | C39: Return to Shop | E39: Internal | F39: FALSE | G39: 404 | H39: FALSE
A40: https://africanmarketingconfederation.org/about-us | B40: https://africanmarketingconfederation.org/amc-conference-2025-delegate-packages | C40: Continue Shopping | E40: Internal | F40: FALSE | G40: 404 | H40: FALSE
A41: https://africanmarketingconfederation.org/ | B41: https://africanmarketingconfederation.org/ | E41: Internal | F41: FALSE | G41: 200 | H41: TRUE
A42: https://africanmarketingconfederation.org/ | B42: https://africanmarketingconfederation.org/ | C42: HOME | E42: Internal | F42: FALSE | G42: 200 | H42: TRUE
A43: https://africanmarketingconfederation.org/ | B43: https://africanmarketingconfederation.org/about-us | C43: ABOUT US | E43: Internal | F43: FALSE | G43: 200 | H43: TRUE
A44: https://africanmarketingconfederation.org/ | B44: https://africanmarketingconfederation.org/sub-committees | C44: AMC COMMITTEES | E44: Internal | F44: FALSE | G44: 200 | H44: TRUE
A45: https://africanmarketingconfederation.org/ | B45: https://africanmarketingconfederation.org/members | C45: MEMBERS | E45: Internal | F45: FALSE | G45: 200 | H45: TRUE
A46: https://africanmarketingconfederation.org/ | B46: https://africanmarketingconfederation.org/african-marketing-confederation-tourism-chapter | C46: TOURISM CHAPTER | E46: Internal | F46: FALSE | G46: 200 | H46: TRUE
A47: https://africanmarketingconfederation.org/ | B47: https://africanmarketingconfederation.org/education | C47: EDUCATION | E47: Internal | F47: FALSE | G47: 200 | H47: TRUE
A48: https://africanmarketingconfederation.org/ | B48: https://africanmarketingconfederation.org/chartered-marketer-africa | C48: CHARTERED MARKETER (AFRICA) | E48: Internal | F48: FALSE | G48: 200 | H48: TRUE
A49: https://africanmarketingconfederation.org/ | B49: https://africanmarketingconfederation.org/certified-professional-marketer-africa | C49: CPM(A) | E49: Internal | F49: FALSE | G49: 200 | H49: TRUE
A50: https://africanmarketingconfederation.org/ | B50: https://africanmarketingconfederation.org/news-articles | C50: NEWS & PUBLICATIONS | E50: Internal | F50: FALSE | G50: 200 | H50: TRUE
A51: https://africanmarketingconfederation.org/ | B51: https://africanmarketingconfederation.org/news-articles | C51: NEWS ARTICLES | E51: Internal | F51: FALSE | G51: 200 | H51: TRUE
A52: https://africanmarketingconfederation.org/ | B52: https://africanmarketingconfederation.org/publications-2 | C52: PUBLICATIONS | E52: Internal | F52: FALSE | G52: 200 | H52: TRUE
A53: https://africanmarketingconfederation.org/ | B53: https://africanmarketingconfederation.org/amc-conference-2026 | C53: AMC Conference | E53: Internal | F53: FALSE | G53: 200 | H53: TRUE
... A80: https://africanmarketingconfederation.org/ | B80: https://africanmarketingconfederation.org/subscribe | C80: Subscribe | E80: Internal | F80: FALSE | G80: 200 | H80: TRUE
A81: https://africanmarketingconfederation.org/ | B81: https://africanmarketingconfederation.org/european-marketers-gather-to-choose-their-top-achievers-for-2026 | E81: Internal | F81: FALSE | G81: 200 | H81: TRUE
A82: https://africanmarketingconfederation.org/ | B82: https://africanmarketingconfederation.org/european-marketers-gather-to-choose-their-top-achievers-for-2026 | C82: European marketers gather to choose their top achievers for 2026 | E82: Internal | F82: FALSE | G82: 200 | H82: TRUE
A83: https://africanmarketingconfederation.org/ | B83: https://africanmarketingconfederation.org/european-marketers-gather-to-choose-their-top-achievers-for-2026 | C83: Read More » | E83: Internal | F83: FALSE | G83: 200 | H83: TRUE
A84: https://africanmarketingconfederation.org/ | B84: https://africanmarketingconfederation.org/namibia-bets-on-walvis-bay-port-as-increasingly-viable-alternative | E84: Internal | F84: FALSE | G84: 200 | H84: TRUE
A85: https://africanmarketingconfederation.org/ | B85: https://africanmarketingconfederation.org/namibia-bets-on-walvis-bay-port-as-increasingly-viable-alternative | C85: Namibia bets on Walvis Bay port as increasingly viable alternative | E85: Internal | F85: FALSE | G85: 200 | H85: TRUE
A86: https://africanmarketingconfederation.org/ | B86: https://africanmarketingconfederation.org/namibia-bets-on-walvis-bay-port-as-increasingly-viable-alternative | C86: Read More » | E86: Internal | F86: FALSE | G86: 200 | H86: TRUE
A87: https://africanmarketingconfederation.org/ | B87: https://africanmarketingconfederation.org/chatgpt-ads-in-africa-a-game-changer-or-a-trust-gamble | E87: Internal | F87: FALSE | G87: 200 | H87: TRUE
A88: https://africanmarketingconfederation.org/ | B88: https://africanmarketingconfederation.org/chatgpt-ads-in-africa-a-game-changer-or-a-trust-gamble | C88: ChatGPT ads in Africa: A game changer or a trust gamble? | E88: Internal | F88: FALSE | G88: 200 | H88: TRUE
A89: https://africanmarketingconfederation.org/ | B89: https://africanmarketingconfederation.org/chatgpt-ads-in-africa-a-game-changer-or-a-trust-gamble | C89: Read More » | E89: Internal | F89: FALSE | G89: 200 | H89: TRUE
A90: https://africanmarketingconfederation.org/ | B90: https://africanmarketingconfederation.org/report-identifies-five-forces-influencing-global-purchasing-decisions | E90: Internal | F90: FALSE | G90: 200 | H90: TRUE
A91: https://africanmarketingconfederation.org/ | B91: https://africanmarketingconfederation.org/report-identifies-five-forces-influencing-global-purchasing-decisions | C91: Report identifies five forces influencing global purchasing decisions | E91: Internal | F91: FALSE | G91: 200 | H91: TRUE
A92: https://africanmarketingconfederation.org/ | B92: https://africanmarketingconfederation.org/report-identifies-five-forces-influencing-global-purchasing-decisions | C92: Read More » | E92: Internal | F92: FALSE | G92: 200 | H92: TRUE
A93: https://africanmarketingconfederation.org/ | B93: https://africanmarketingconfederation.org/out-now-new-issue-brings-latest-news-and-insights-for-africas-marketers | E93: Internal | F93: FALSE | G93: 200 | H93: TRUE
A94: https://africanmarketingconfederation.org/ | B94: https://africanmarketingconfederation.org/out-now-new-issue-brings-latest-news-and-insights-for-africas-marketers | C94: Out now! New issue brings latest news and insights for Africa’s marketers | E94: Internal | F94: FALSE | G94: 200 | H94: TRUE
A95: https://africanmarketingconfederation.org/ | B95: https://africanmarketingconfederation.org/out-now-new-issue-brings-latest-news-and-insights-for-africas-marketers | C95: Read More » | E95: Internal | F95: FALSE | G95: 200 | H95: TRUE
A96: https://africanmarketingconfederation.org/ | B96: https://africanmarketingconfederation.org/omnicom-media-study-warns-negative-reach-can-undermine-ad-campaigns | E96: Internal | F96: FALSE | G96: 200 | H96: TRUE
A97: https://africanmarketingconfederation.org/ | B97: https://africanmarketingconfederation.org/omnicom-media-study-warns-negative-reach-can-undermine-ad-campaigns | C97: Omnicom Media study warns ‘negative reach’ can undermine ad campaigns | E97: Internal | F97: FALSE | G97: 200 | H97: TRUE
A98: https://africanmarketingconfederation.org/ | B98: https://africanmarketingconfederation.org/omnicom-media-study-warns-negative-reach-can-undermine-ad-campaigns | C98: Read More » | E98: Internal | F98: FALSE | G98: 200 | H98: TRUE
A99: https://africanmarketingconfederation.org/ | B99: https://africanmarketingconfederation.org/news-articles | C99: View all articles » | E99: Internal | F99: FALSE | G99: 200 | H99: TRUE
A100: https://africanmarketingconfederation.org/ | B100: https://africanmarketingconfederation.org/publications-2 | C100: Strategic Marketing for AfricaMagazine | E100: Internal | F100: FALSE | G100: 200 | H100: TRUE
A101: https://africanmarketingconfederation.org/ | B101: https://www.facebook.com/The-African-Marketing-Confederation-108980418182403 | E101: External | F101: FALSE | H101: TRUE
A102: https://africanmarketingconfederation.org/ | B102: https://www.linkedin.com/company/african-marketing-confederation | E102: External | F102: FALSE | H102: TRUE
A103: https://africanmarketingconfederation.org/ | B103: https://africanmarketingconfederation.org/privacy-policy | C103: © 2026 by African Marketing Confederation | Privacy Policy | E103: Internal | F103: FALSE | G103: 200 | H103: TRUE
A104: https://africanmarketingconfederation.org/ | B104: https://africanmarketingconfederation.org/amc-conference-2025-delegate-packages | C104: Return to Shop | E104: Internal | F104: FALSE | G104: 404 | H104: FALSE
A105: https://africanmarketingconfederation.org/ | B105: https://africanmarketingconfederation.org/amc-conference-2025-delegate-packages | C105: Continue Shopping | E105: Internal | F105: FALSE | G105: 404 | H105: FALSE
A106: https://africanmarketingconfederation.org/african-marketing-confederation-tourism-chapter | B106: https://africanmarketingconfederation.org/ | E106: Internal | F106: FALSE | G106: 200 | H106: TRUE
A107: https://africanmarketingconfederation.org/african-marketing-confederation-tourism-chapter | B107: https://africanmarketingconfederation.org/ | C107: HOME | E107: Internal | F107: FALSE | G107: 200 | H107: TRUE
A108: https://africanmarketingconfederation.org/african-marketing-confederation-tourism-chapter | B108: https://africanmarketingconfederation.org/about-us | C108: ABOUT US | E108: Internal | F108: FALSE | G108: 200 | H108: TRUE
A109: https://africanmarketingconfederation.org/african-marketing-confederation-tourism-chapter | B109: https://africanmarketingconfederation.org/sub-committees | C109: AMC COMMITTEES | E109: Internal | F109: FALSE | G109: 200 | H109: TRUE
A110: https://africanmarketingconfederation.org/african-marketing-confederation-tourism-chapter | B110: https://africanmarketingconfederation.org/members | C110: MEMBERS | E110: Internal | F110: FALSE | G110: 200 | H110: TRUE
A111: https://africanmarketingconfederation.org/african-marketing-confederation-tourism-chapter | B111: https://africanmarketingconfederation.org/african-marketing-confederation-tourism-chapter | C111: TOURISM CHAPTER | E111: Internal | F111: FALSE | G111: 200 | H111: TRUE
A112: https://africanmarketingconfederation.org/african-marketing-confederation-tourism-chapter | B112: https://africanmarketingconfederation.org/education | C112: EDUCATION | E112: Internal | F112: FALSE | G112: 200 | H112: TRUE
A113: https://africanmarketingconfederation.org/african-marketing-confederation-tourism-chapter | B113: https://africanmarketingconfederation.org/chartered-marketer-africa | C113: CHARTERED MARKETER (AFRICA) | E113: Internal | F113: FALSE | G113: 200 | H113: TRUE
A114: https://africanmarketingconfederation.org/african-marketing-confederation-tourism-chapter | B114: https://africanmarketingconfederation.org/certified-professional-marketer-africa | C114: CPM(A) | E114: Internal | F114: FALSE | G114: 200 | H114: TRUE
A115: https://africanmarketingconfederation.org/african-marketing-confederation-tourism-chapter | B115: https://africanmarketingconfederation.org/news-articles | C115: NEWS & PUBLICATIONS | E115: Internal | F115: FALSE | G115: 200 | H115: TRUE
A116: https://africanmarketingconfederation.org/african-marketing-confederation-tourism-chapter | B116: https://africanmarketingconfederation.org/news-articles | C116: NEWS ARTICLES | E116: Internal | F116: FALSE | G116: 200 | H116: TRUE
A117: https://africanmarketingconfederation.org/african-marketing-confederation-tourism-chapter | B117: https://africanmarketingconfederation.org/publications-2 | C117: PUBLICATIONS | E117: Internal | F117: FALSE | G117: 200 | H117: TRUE
A118: https://africanmarketingconfederation.org/african-marketing-confederation-tourism-chapter | B118: https://africanmarketingconfederation.org/amc-conference-2026 | C118: AMC Conference | E118: Internal | F118: FALSE | G118: 200 | H118: TRUE
... A132: https://africanmarketingconfederation.org/african-marketing-confederation-tourism-chapter | B132: https://africanmarketingconfederation.org/contact-us | C132: CONTACT US | E132: Internal | F132: FALSE | G132: 200 | H132: TRUE
A133: https://africanmarketingconfederation.org/african-marketing-confederation-tourism-chapter | B133: http://www.africanmarketingconfederation.org/ | E133: External | F133: FALSE | H133: TRUE
A134: https://africanmarketingconfederation.org/african-marketing-confederation-tourism-chapter | B134: https://africanmarketingconfederation.org/ | C134: HOME | E134: Internal | F134: FALSE | G134: 200 | H134: TRUE
A135: https://africanmarketingconfederation.org/african-marketing-confederation-tourism-chapter | B135: https://africanmarketingconfederation.org/about-us | C135: ABOUT US | E135: Internal | F135: FALSE | G135: 200 | H135: TRUE
A136: https://africanmarketingconfederation.org/african-marketing-confederation-tourism-chapter | B136: https://africanmarketingconfederation.org/sub-committees | C136: AMC COMMITTEES | E136: Internal | F136: FALSE | G136: 200 | H136: TRUE
A137: https://africanmarketingconfederation.org/african-marketing-confederation-tourism-chapter | B137: https://africanmarketingconfederation.org/members | C137: MEMBERS | E137: Internal | F137: FALSE | G137: 200 | H137: TRUE
A138: https://africanmarketingconfederation.org/african-marketing-confederation-tourism-chapter | B138: https://africanmarketingconfederation.org/african-marketing-confederation-tourism-chapter | C138: TOURISM CHAPTER | E138: Internal | F138: FALSE | G138: 200 | H138: TRUE
A139: https://africanmarketingconfederation.org/african-marketing-confederation-tourism-chapter | B139: https://africanmarketingconfederation.org/education | C139: EDUCATION | E139: Internal | F139: FALSE | G139: 200 | H139: TRUE
A140: https://africanmarketingconfederation.org/african-marketing-confederation-tourism-chapter | B140: https://africanmarketingconfederation.org/chartered-marketer-africa | C140: CHARTERED MARKETER (AFRICA) | E140: Internal | F140: FALSE | G140: 200 | H140: TRUE
A141: https://africanmarketingconfederation.org/african-marketing-confederation-tourism-chapter | B141: https://africanmarketingconfederation.org/certified-professional-marketer-africa | C141: CPM(A) | E141: Internal | F141: FALSE | G141: 200 | H141: TRUE
A142: https://africanmarketingconfederation.org/african-marketing-confederation-tourism-chapter | B142: https://africanmarketingconfederation.org/news-articles | C142: NEWS & PUBLICATIONS | E142: Internal | F142: FALSE | G142: 200 | H142: TRUE
A143: https://africanmarketingconfederation.org/african-marketing-confederation-tourism-chapter | B143: https://africanmarketingconfederation.org/news-articles | C143: NEWS ARTICLES | E143: Internal | F143: FALSE | G143: 200 | H143: TRUE
A144: https://africanmarketingconfederation.org/african-marketing-confederation-tourism-chapter | B144: https://africanmarketingconfederation.org/publications-2 | C144: PUBLICATIONS | E144: Internal | F144: FALSE | G144: 200 | H144: TRUE
A145: https://africanmarketingconfederation.org/african-marketing-confederation-tourism-chapter | B145: https://africanmarketingconfederation.org/amc-conference-2026 | C145: AMC Conference | E145: Internal | F145: FALSE | G145: 200 | H145: TRUE
... A161: https://africanmarketingconfederation.org/african-marketing-confederation-tourism-chapter | B161: https://africanmarketingconfederation.org/publications-2 | C161: Strategic Marketing for AfricaMagazine | E161: Internal | F161: FALSE | G161: 200 | H161: TRUE
A162: https://africanmarketingconfederation.org/african-marketing-confederation-tourism-chapter | B162: https://www.facebook.com/The-African-Marketing-Confederation-108980418182403 | E162: External | F162: FALSE | H162: TRUE
A163: https://africanmarketingconfederation.org/african-marketing-confederation-tourism-chapter | B163: https://www.linkedin.com/company/african-marketing-confederation | E163: External | F163: FALSE | H163: TRUE
A164: https://africanmarketingconfederation.org/african-marketing-confederation-tourism-chapter | B164: https://africanmarketingconfederation.org/privacy-policy | C164: © 2026 by African Marketing Confederation | Privacy Policy | E164: Internal | F164: FALSE | G164: 200 | H164: TRUE
A165: https://africanmarketingconfederation.org/african-marketing-confederation-tourism-chapter | B165: https://africanmarketingconfederation.org/amc-conference-2025-delegate-packages | C165: Return to Shop | E165: Internal | F165: FALSE | G165: 404 | H165: FALSE
A166: https://africanmarketingconfederation.org/african-marketing-confederation-tourism-chapter | B166: https://africanmarketingconfederation.org/amc-conference-2025-delegate-packages | C166: Continue Shopping | E166: Internal | F166: FALSE | G166: 404 | H166: FALSE
A167: https://africanmarketingconfederation.org/amc-awards-2024 | B167: http://www.africanmarketingconfederation.org/ | E167: External | F167: FALSE | H167: TRUE
...

Sheet Media
A1: URL | B1: Image Count | C1: Images | D1: Images Missing Alt | E1: Image Alt Coverage (%) | F1: Image Extension Distribution | G1: Likely Large Image Count | H1: Image Filename Quality Issues | I1: Image On Canonical Domain (%) | J1: Mixed Content Detected | K1: Open in Main | L1: BACK TO DASHBOARD | M1: BACK TO DASHBOARD_1
A2: https://africanmarketingconfederation.org/about-us | B2: 44 | C2: /wp-content/plugins/gtranslate/flags/svg/en.svg | https://africanmarketingconfederation.org/wp-content/uploads/2021/08/africa_map.png | https://africanmarketingconfederation.org/wp-content/uploads/2021/08/facebook.svg | https://africanmarketingconfederation.org/wp-content/uploads/2021/08/linkedin.svg | https://africanmarketingconfederation.org/wp-content/uploads/2024/03/Artboard-1-1024x1024.png | https://africanmarketingconfederation.org/wp-content/uploads/2024/03/Artboard-1.png | https://africanmarketingconfederation.org/wp-content/uploads/2024/03/Artboard-3-1-1024x1024.png | https://africanmarketingconfederation.org/wp-content/uploads/2024/03/Artboard-3-1.png | https://africanmarketingconfederation.org/wp-content/uploads/2024/03/Artboard-3-copy-1024x1024.png | https://africanmarketingconfederation.org/wp-content/uploads/2024/03/Artboard-3-copy.png | https://africanmarketingconfederation.org/wp-content/uploads/2024/03/Artboard-4-copy-2-1024x1024.png | https://africanmarketingconfederation.org/wp-content/uploads/2024/03/Artboard-4-copy-2.png | https://africanmarketingconfederation.org/wp-content/uploads/2024/03/Artboard-4-copy-4-1024x1024.png | https://africanmarketingconfederation.org/wp-content/uploads/2024/03/Artboard-4-copy-4.png | https://africanmarketingconfederation.org/wp-content/uploads/2024/03/Artboard-4-copy-6-1024x1024.png | https://africanmarketingconfederation.org/wp-content/uploads/2024/03/Artboard-4-copy-6.png | https://africanmarketingconfederation.org/wp-content/uploads/2024/04/AMC-Founders_0000_Group-1-copy-4-1024x1024.png | https://africanmarketingconfederation.org/wp-content/uploads/2024/04/AMC-Founders_0001_Group-1-copy-3-1024x1024.png | https://africanmarketingconfederation.org/wp-content/uploads/2024/04/Helen-1024x1024.png | https://africanmarketingconfederation.org/wp-content/uploads/2024/04/Nigel-1024x1024.png | https://africanmarketingconfederation.org/wp-content/uploads/2025/11/David-Balikuddembe.png | https://africanmarketingconfederation.org/wp-content/uploads/2026/03/og-image.png | https://www.facebook.com/tr?id=1795315120651843&ev=PageView&noscript=1 | https://www.facebook.com/tr?id=1795315120651843&ev=PageView&noscript=1&cd%5Bpage_title%5D=African+Marketing+Confederation+%E2%80%93+The+Leading+Marketing+Professional+Body&cd%5Bpost_type%5D=page&cd%5Bpost_id%5D=84&cd%5Bplugin%5D=PixelYourSite&cd%5Buser_role%5D=guest&cd%5Bevent_url%5D=africanmarketingconfederation.org%2Fabout-us%2F | D2: 12 | E2: 72.73 | F2: other:2, png:19, svg:3 | G2: 0 | H2: 0 | J2: FALSE | K2: Open
A3: https://africanmarketingconfederation.org/ | B3: 62 | C3: /wp-content/plugins/gtranslate/flags/svg/en.svg | https://africanmarketingconfederation.org/wp-content/uploads/2021/08/amc_aboutus_giraffes-1.png | https://africanmarketingconfederation.org/wp-content/uploads/2021/08/facebook.svg | https://africanmarketingconfederation.org/wp-content/uploads/2021/08/linkedin.svg | https://africanmarketingconfederation.org/wp-content/uploads/2024/03/Artboard-1.png | https://africanmarketingconfederation.org/wp-content/uploads/2024/03/Artboard-2-1.png | https://africanmarketingconfederation.org/wp-content/uploads/2024/03/Artboard-3-1.png | https://africanmarketingconfederation.org/wp-content/uploads/2024/03/Artboard-3-copy.png | https://africanmarketingconfederation.org/wp-content/uploads/2024/03/Artboard-4-copy-2.png | https://africanmarketingconfederation.org/wp-content/uploads/2024/03/Artboard-4-copy-3.png | https://africanmarketingconfederation.org/wp-content/uploads/2024/03/Artboard-4-copy-4.png | https://africanmarketingconfederation.org/wp-content/uploads/2024/03/Artboard-4-copy-6.png | https://africanmarketingconfederation.org/wp-content/uploads/2024/03/Artboard-4-copy.png | https://africanmarketingconfederation.org/wp-content/uploads/2024/03/Artboard-4.png | https://africanmarketingconfederation.org/wp-content/uploads/2024/05/Untitled-2.png | https://africanmarketingconfederation.org/wp-content/uploads/2024/08/SMA-Issue-1-2026-COVER.png | https://africanmarketingconfederation.org/wp-content/uploads/2024/09/Untitled-2-12.png | https://africanmarketingconfederation.org/wp-content/uploads/2024/09/Untitled-2-14.png | https://africanmarketingconfederation.org/wp-content/uploads/2024/09/Untitled-2-15.png | https://africanmarketingconfederation.org/wp-content/uploads/2025/05/The-Marketing-Association-of-Botswana-Logo-01-1.png | https://africanmarketingconfederation.org/wp-content/uploads/2025/07/thumbnail_atpmc-nouveau-1-1.jpg | https://africanmarketingconfederation.org/wp-content/uploads/2025/08/CPMA-Banner-Home-Page-989x1024.png | https://africanmarketingconfederation.org/wp-content/uploads/2025/08/Home-Page-CPMA-icons-989x1024.png | https://africanmarketingconfederation.org/wp-content/uploads/2026/01/AMC-2026-Mobile.png | https://africanmarketingconfederation.org/wp-content/uploads/2026/03/AMC-Logo-Dark-Horizontal.png | https://africanmarketingconfederation.org/wp-content/uploads/2026/03/ASCON-Logo-Dark.png | https://africanmarketingconfederation.org/wp-content/uploads/2026/03/Artwork1_a665a3a1-7845-44e5-b6df-752efd31cb90.png | https://africanmarketingconfederation.org/wp-content/uploads/2026/03/og-image.png | https://africanmarketingconfederation.org/wp-content/uploads/2026/04/28-April-Advertising-233x300.png | https://africanmarketingconfederation.org/wp-content/uploads/2026/04/29-April-Advertising-300x260.png | https://africanmarketingconfederation.org/wp-content/uploads/2026/04/29-April-Consumer-Trends-300x200.jpg | https://africanmarketingconfederation.org/wp-content/uploads/2026/04/30-April-Marketing-Awards-300x133.jpg | https://africanmarketingconfederation.org/wp-content/uploads/2026/04/30-April-Supply-Chain-300x200.jpg | https://africanmarketingconfederation.org/wp-content/uploads/2026/04/SMA-Issue-1-2026-BACKGROUND-300x106.webp | https://www.facebook.com/tr?id=1795315120651843&ev=PageView&noscript=1 | https://www.facebook.com/tr?id=1795315120651843&ev=PageView&noscript=1&cd%5Bpage_title%5D=Home+page+of+the+african+marketing+confederation&cd%5Bpost_type%5D=page&cd%5Bpost_id%5D=8&cd%5Bplugin%5D=PixelYourSite&cd%5Buser_role%5D=guest&cd%5Bevent_url%5D=africanmarketingconfederation.org%2F | D3: 13 | E3: 79.03 | F3: jpg:4, other:2, png:26, svg:3, webp:1 | G3: 0 | H3: 0 | J3: FALSE | K3: Open
A4: https://africanmarketingconfederation.org/african-marketing-confederation-tourism-chapter | B4: 48 | C4: /wp-content/plugins/gtranslate/flags/svg/en.svg | https://africanmarketingconfederation.org/wp-content/uploads/2021/08/facebook.svg | https://africanmarketingconfederation.org/wp-content/uploads/2021/08/linkedin.svg | https://africanmarketingconfederation.org/wp-content/uploads/2021/09/AMC-Logo-04-1024x449.png | https://africanmarketingconfederation.org/wp-content/uploads/2024/03/Artboard-1.png | https://africanmarketingconfederation.org/wp-content/uploads/2024/03/Artboard-2-1.png | https://africanmarketingconfederation.org/wp-content/uploads/2024/03/Artboard-3-1.png | https://africanmarketingconfederation.org/wp-content/uploads/2024/03/Artboard-3-copy.png | https://africanmarketingconfederation.org/wp-content/uploads/2024/03/Artboard-4-copy-2.png | https://africanmarketingconfederation.org/wp-content/uploads/2024/03/Artboard-4-copy-3.png | https://africanmarketingconfederation.org/wp-content/uploads/2024/03/Artboard-4-copy-4.png | https://africanmarketingconfederation.org/wp-content/uploads/2024/03/Artboard-4-copy-6.png | https://africanmarketingconfederation.org/wp-content/uploads/2024/03/Artboard-4-copy.png | https://africanmarketingconfederation.org/wp-content/uploads/2024/03/Artboard-4.png | https://africanmarketingconfederation.org/wp-content/uploads/2024/05/Untitled-2.png | https://africanmarketingconfederation.org/wp-content/uploads/2024/09/Untitled-2-12.png | https://africanmarketingconfederation.org/wp-content/uploads/2024/09/Untitled-2-14.png | https://africanmarketingconfederation.org/wp-content/uploads/2024/09/Untitled-2-15.png | https://africanmarketingconfederation.org/wp-content/uploads/2025/05/The-Marketing-Association-of-Botswana-Logo-01-1.png | https://africanmarketingconfederation.org/wp-content/uploads/2025/07/Shaping-Africas-Tourism-Narrative-Through-Strategic-Marketing-Figure.png | https://africanmarketingconfederation.org/wp-content/uploads/2025/07/thumbnail_atpmc-nouveau-1-1.jpg | https://africanmarketingconfederation.org/wp-content/uploads/2025/08/Dots.png | https://africanmarketingconfederation.org/wp-content/uploads/2025/08/People-Tourism-Chapter-Cover.png | https://africanmarketingconfederation.org/wp-content/uploads/2026/03/og-image.png | https://www.facebook.com/tr?id=1795315120651843&ev=PageView&noscript=1 | https://www.facebook.com/tr?id=1795315120651843&ev=PageView&noscript=1&cd%5Bpage_title%5D=African+Marketing+Confederation+Tourism+Chapter&cd%5Bpost_type%5D=page&cd%5Bpost_id%5D=28165&cd%5Bplugin%5D=PixelYourSite&cd%5Buser_role%5D=guest&cd%5Bevent_url%5D=africanmarketingconfederation.org%2Fafrican-marketing-confederation-tourism-chapter%2F | D4: 9 | E4: 81.25 | F4: jpg:1, other:2, png:20, svg:3 | G4: 0 | H4: 0 | J4: FALSE | K4: Open
A5: https://africanmarketingconfederation.org/amc-awards-2024 | B5: 93 | C5: /wp-content/plugins/gtranslate/flags/svg/en.svg | https://africanmarketingconfederation.org/wp-content/uploads/2021/08/facebook.svg | https://africanmarketingconfederation.org/wp-content/uploads/2021/08/linkedin.svg | https://africanmarketingconfederation.org/wp-content/uploads/2021/08/twitter.svg | https://africanmarketingconfederation.org/wp-content/uploads/2021/09/AMC-Logo-04-1024x449.png | https://africanmarketingconfederation.org/wp-content/uploads/2023/09/AMC-Ticon-01353.jpg | https://africanmarketingconfederation.org/wp-content/uploads/2023/09/AMC-Ticon-01363.jpg | https://africanmarketingconfederation.org/wp-content/uploads/2023/09/AMC-Ticon-01364.jpg | https://africanmarketingconfederation.org/wp-content/uploads/2023/09/AMC-Ticon-01380.jpg | https://africanmarketingconfederation.org/wp-content/uploads/2023/09/AMC-Ticon-01396.jpg | https://africanmarketingconfederation.org/wp-content/uploads/2023/09/AMC-Ticon-01399.jpg | https://africanmarketingconfederation.org/wp-content/uploads/2023/09/AMC-Ticon-01409.jpg | https://africanmarketingconfederation.org/wp-content/uploads/2023/09/AMC-Ticon-01415.jpg | https://africanmarketingconfederation.org/wp-content/uploads/2023/09/AMC-Ticon-01474.jpg | https://africanmarketingconfederation.org/wp-content/uploads/2023/09/AMC-Ticon-01497.jpg | https://africanmarketingconfederation.org/wp-content/uploads/2023/09/AMC-Ticon-01564.jpg | https://africanmarketingconfederation.org/wp-content/uploads/2024/03/AMC-Website-Elements-2-1-819x1024.png | https://africanmarketingconfederation.org/wp-content/uploads/2024/03/Artboard-1.png | https://africanmarketingconfederation.org/wp-content/uploads/2024/03/Artboard-2-1.png | https://africanmarketingconfederation.org/wp-content/uploads/2024/03/Artboard-3-1.png | https://africanmarketingconfederation.org/wp-content/uploads/2024/03/Artboard-3-copy.png | https://africanmarketingconfederation.org/wp-content/uploads/2024/03/Artboard-4-copy-2.png | https://africanmarketingconfederation.org/wp-content/uploads/2024/03/Artboard-4-copy-3.png | https://africanmarketingconfederation.org/wp-content/uploads/2024/03/Artboard-4-copy-4.png | https://africanmarketingconfederation.org/wp-content/uploads/2024/03/Artboard-4-copy-5.png | https://africanmarketingconfederation.org/wp-content/uploads/2024/03/Artboard-4-copy-6.png | https://africanmarketingconfederation.org/wp-content/uploads/2024/03/Artboard-4-copy.png | https://africanmarketingconfederation.org/wp-content/uploads/2024/03/Artboard-4.png | https://africanmarketingconfederation.org/wp-content/uploads/2024/08/1Best-Social-Media-Campaign-of-the-Year.png | https://africanmarketingconfederation.org/wp-content/uploads/2024/08/2Brand-of-the-Year.png | https://africanmarketingconfederation.org/wp-content/uploads/2024/08/3Most-Effective-Campaign-of-the-Year.png | https://africanmarketingconfederation.org/wp-content/uploads/2024/08/4Best-Use-of-Local-Insights.png | https://africanmarketingconfederation.org/wp-content/uploads/2024/08/5Campaign-of-the-Year.png | https://africanmarketingconfederation.org/wp-content/uploads/2024/08/7Best-Cause-Related-Campaign.png | https://africanmarketingconfederation.org/wp-content/uploads/2024/08/Brand-of-the-year-icon.png | https://africanmarketingconfederation.org/wp-content/uploads/2024/08/Campaign-of-the-year.png | https://africanmarketingconfederation.org/wp-content/uploads/2024/08/Local-insight-icon.png | https://africanmarketingconfederation.org/wp-content/uploads/2024/08/Most-effective-campaign.png | https://africanmarketingconfederation.org/wp-content/uploads/2024/08/Touris-icon.png | https://africanmarketingconfederation.org/wp-content/uploads/2024/08/Tourism-award.png | https://africanmarketingconfederation.org/wp-content/uploads/2024/08/best-related-Icon.png | https://africanmarketingconfederation.org/wp-content/uploads/2024/08/best-social-media-campaign-icon.png | https://www.facebook.com/tr?id=1795315120651843&ev=PageView&noscript=1 | https://www.facebook.com/tr?id=1795315120651843&ev=PageView&noscript=1&cd%5Bpage_title%5D=AMC+Awards+2024&cd%5Bpost_type%5D=page&cd%5Bpost_id%5D=16125&cd%5Bplugin%5D=PixelYourSite&cd%5Buser_role%5D=guest&cd%5Bevent_url%5D=africanmarketingconfederation.org%2Famc-awards-2024%2F | D5: 25 | E5: 73.12 | F5: jpg:11, other:2, png:27, svg:4 | G5: 0 | H5: 0 | J5: FALSE | K5: Open
A6: https://africanmarketingconfederation.org/amc-conference-2022-prospectus | B6: 23 | C6: /wp-content/plugins/gtranslate/flags/svg/en.svg | https://africanmarketingconfederation.org/wp-content/uploads/2021/08/facebook.svg | https://africanmarketingconfederation.org/wp-content/uploads/2021/08/linkedin.svg | https://africanmarketingconfederation.org/wp-content/uploads/2021/11/Navigating-768x164.png | https://africanmarketingconfederation.org/wp-content/uploads/2022/01/AMC-2022-Conference-Prospectus-Cover.png | https://africanmarketingconfederation.org/wp-content/uploads/2022/01/AMC-2022_Conference-Book-Now.png | https://africanmarketingconfederation.org/wp-content/uploads/2026/03/og-image.png | https://www.facebook.com/tr?id=1795315120651843&ev=PageView&noscript=1 | https://www.facebook.com/tr?id=1795315120651843&ev=PageView&noscript=1&cd%5Bpage_title%5D=AMC+Conference+2022+-+Prospectus&cd%5Bpost_type%5D=page&cd%5Bpost_id%5D=5619&cd%5Bplugin%5D=PixelYourSite&cd%5Buser_role%5D=guest&cd%5Bevent_url%5D=africanmarketingconfederation.org%2Famc-conference-2022-prospectus%2F | D6: 8 | E6: 65.22 | F6: other:2, png:4, svg:3 | G6: 0 | H6: 0 | J6: FALSE | K6: Open
A7: https://africanmarketingconfederation.org/amc-conference-2022-thank-you | B7: 30 | C7: /wp-content/plugins/gtranslate/flags/svg/en.svg | https://africanmarketingconfederation.org/wp-content/uploads/2021/08/facebook.svg | https://africanmarketingconfederation.org/wp-content/uploads/2021/08/linkedin.svg | https://africanmarketingconfederation.org/wp-content/uploads/2021/11/Ghana.png | https://africanmarketingconfederation.org/wp-content/uploads/2021/11/Kenya.png | https://africanmarketingconfederation.org/wp-content/uploads/2021/11/Malawi.png | https://africanmarketingconfederation.org/wp-content/uploads/2021/11/Marketing-Professionals-1024x1024.png | https://africanmarketingconfederation.org/wp-content/uploads/2021/11/Mauritius.png | https://africanmarketingconfederation.org/wp-content/uploads/2021/11/Morocco.png | https://africanmarketingconfederation.org/wp-content/uploads/2021/11/Navigating-768x164.png | https://africanmarketingconfederation.org/wp-content/uploads/2021/11/Nigeria.png | https://africanmarketingconfederation.org/wp-content/uploads/2021/11/South-Africa.png | https://africanmarketingconfederation.org/wp-content/uploads/2021/11/Zambia.png | https://africanmarketingconfederation.org/wp-content/uploads/2026/03/og-image.png | https://www.facebook.com/tr?id=1795315120651843&ev=PageView&noscript=1 | https://www.facebook.com/tr?id=1795315120651843&ev=PageView&noscript=1&cd%5Bpage_title%5D=AMC+Conference+2022+-+Thank+You&cd%5Bpost_type%5D=page&cd%5Bpost_id%5D=4941&cd%5Bplugin%5D=PixelYourSite&cd%5Buser_role%5D=guest&cd%5Bevent_url%5D=africanmarketingconfederation.org%2Famc-conference-2022-thank-you%2F | D7: 15 | E7: 50 | F7: other:2, png:11, svg:3 | G7: 0 | H7: 0 | J7: FALSE | K7: Open
A8: https://africanmarketingconfederation.org/amc-conference-2022 | B8: 28 | C8: /wp-content/plugins/gtranslate/flags/svg/en.svg | https://africanmarketingconfederation.org/wp-content/uploads/2021/08/facebook.svg | https://africanmarketingconfederation.org/wp-content/uploads/2021/08/linkedin.svg | https://africanmarketingconfederation.org/wp-content/uploads/2021/09/AMC-Logo-04-1024x449.png | https://africanmarketingconfederation.org/wp-content/uploads/2022/08/New-Theme-768x415.png | https://africanmarketingconfederation.org/wp-content/uploads/2024/09/26-September-Marketing-Forum-4-laptop-only-300x225.jpg | https://africanmarketingconfederation.org/wp-content/uploads/2024/09/27-September-Marketing-Forum-5-265x300.jpg | https://africanmarketingconfederation.org/wp-content/uploads/2024/09/27-September-Marketing-Forum-6-300x265.jpg | https://africanmarketingconfederation.org/wp-content/uploads/2024/10/1-October-Marketing-Forum-9-300x199.jpg | https://africanmarketingconfederation.org/wp-content/uploads/2024/10/30-September-Marketing-Forum-8-300x225.jpg | https://africanmarketingconfederation.org/wp-content/uploads/2024/10/8-October-Marketing-Forum.JPG | https://africanmarketingconfederation.org/wp-content/uploads/2026/03/og-image.png | https://www.facebook.com/tr?id=1795315120651843&ev=PageView&noscript=1 | https://www.facebook.com/tr?id=1795315120651843&ev=PageView&noscript=1&cd%5Bpage_title%5D=AMC+Conference+2022&cd%5Bpost_type%5D=page&cd%5Bpost_id%5D=4494&cd%5Bplugin%5D=PixelYourSite&cd%5Buser_role%5D=guest&cd%5Bevent_url%5D=africanmarketingconfederation.org%2Famc-conference-2022%2F | D8: 13 | E8: 53.57 | F8: jpg:6, other:2, png:3, svg:3 | G8: 0 | H8: 0 | J8: FALSE | K8: Open
A9: https://africanmarketingconfederation.org/amc-conference-2023 | B9: 56 | C9: /wp-content/plugins/gtranslate/flags/svg/en.svg | https://africanmarketingconfederation.org/wp-content/uploads/2021/08/facebook.svg | https://africanmarketingconfederation.org/wp-content/uploads/2021/08/linkedin.svg | https://africanmarketingconfederation.org/wp-content/uploads/2021/08/twitter.svg | https://africanmarketingconfederation.org/wp-content/uploads/2021/09/AMC-Logo-04-1024x449.png | https://africanmarketingconfederation.org/wp-content/uploads/2023/06/10.png | https://africanmarketingconfederation.org/wp-content/uploads/2023/06/2.png | https://africanmarketingconfederation.org/wp-content/uploads/2023/06/3.png | https://africanmarketingconfederation.org/wp-content/uploads/2023/06/4.png | https://africanmarketingconfederation.org/wp-content/uploads/2023/06/5.png | https://africanmarketingconfederation.org/wp-content/uploads/2023/06/6.png | https://africanmarketingconfederation.org/wp-content/uploads/2023/06/7.png | https://africanmarketingconfederation.org/wp-content/uploads/2023/06/9.png | https://africanmarketingconfederation.org/wp-content/uploads/2023/06/AMC-hosted-by-UMS-animation-circles-with-stroke-v4.gif | https://africanmarketingconfederation.org/wp-content/uploads/2023/06/IMM-Logo-2022_IMM_primary_horizontal.png | https://africanmarketingconfederation.org/wp-content/uploads/2023/06/Institute-of-Marketing-in-Malawi.png | https://africanmarketingconfederation.org/wp-content/uploads/2023/08/Ali-Hussein-Kassim-2.png | https://africanmarketingconfederation.org/wp-content/uploads/2023/08/Cathy-Adengo-1.jpg | https://africanmarketingconfederation.org/wp-content/uploads/2023/08/Doreen-Asaasira-Muhangizi.jpg | https://africanmarketingconfederation.org/wp-content/uploads/2023/08/James-Sutton-CIM.jpg | https://africanmarketingconfederation.org/wp-content/uploads/2023/09/AMC-TICON-0164-300x200.jpg | https://africanmarketingconfederation.org/wp-content/uploads/2023/09/AMC-TICON-1113-300x200.jpg | https://africanmarketingconfederation.org/wp-content/uploads/2023/09/AMC-TICON-1127-300x200.jpg | https://africanmarketingconfederation.org/wp-content/uploads/2023/09/AMC-Ticon-00246-300x200.jpg | https://africanmarketingconfederation.org/wp-content/uploads/2023/09/AMC-Ticon-00449-300x200.jpg | https://africanmarketingconfederation.org/wp-content/uploads/2023/09/AMC-Ticon-00481-300x200.jpg | https://africanmarketingconfederation.org/wp-content/uploads/2023/09/AMC-Ticon-00638-300x200.jpg | https://africanmarketingconfederation.org/wp-content/uploads/2023/09/AMC-Ticon-00682-300x200.jpg | https://africanmarketingconfederation.org/wp-content/uploads/2023/09/AMC-Ticon-00742-300x200.jpg | https://africanmarketingconfederation.org/wp-content/uploads/2023/09/AMC-Ticon-01128-300x200.jpg | https://africanmarketingconfederation.org/wp-content/uploads/2023/09/AMC-Ticon-01363-300x200.jpg | https://africanmarketingconfederation.org/wp-content/uploads/2023/09/AMC-Ticon-01409-300x200.jpg | https://africanmarketingconfederation.org/wp-content/uploads/2023/09/AMC-Ticon-01476-300x200.jpg | https://africanmarketingconfederation.org/wp-content/uploads/2023/09/AMC-Ticon-01530-300x200.jpg | https://africanmarketingconfederation.org/wp-content/uploads/2023/09/AMC-Ticon-01616-300x200.jpg | https://africanmarketingconfederation.org/wp-content/uploads/2023/09/AMC-Ticon-02950-1-300x200.jpg | https://africanmarketingconfederation.org/wp-content/uploads/2023/09/AMC-Ticon-03063-300x200.jpg | https://africanmarketingconfederation.org/wp-content/uploads/2023/09/AMC-Ticon-09823-300x169.jpg | https://africanmarketingconfederation.org/wp-content/uploads/2023/09/AMC-Ticon-09825-300x169.jpg | https://africanmarketingconfederation.org/wp-content/uploads/2023/09/AMC-Ticon-09953-300x200.jpg | https://www.facebook.com/tr?id=1795315120651843&ev=PageView&noscript=1 | https://www.facebook.com/tr?id=1795315120651843&ev=PageView&noscript=1&cd%5Bpage_title%5D=AMC+Conference+2023&cd%5Bpost_type%5D=page&cd%5Bpost_id%5D=12371&cd%5Bplugin%5D=PixelYourSite&cd%5Buser_role%5D=guest&cd%5Bevent_url%5D=africanmarketingconfederation.org%2Famc-conference-2023%2F | D9: 37 | E9: 33.93 | F9: gif:1, jpg:23, other:2, png:12, svg:4 | G9: 0 | H9: 0 | J9: FALSE | K9: Open
A10: https://africanmarketingconfederation.org/amc-conference-2023/amc-awards-book-now | B10: 20 | C10: /wp-content/plugins/gtranslate/flags/svg/en.svg | https://africanmarketingconfederation.org/wp-content/uploads/2021/08/facebook.svg | https://africanmarketingconfederation.org/wp-content/uploads/2021/08/linkedin.svg | https://africanmarketingconfederation.org/wp-content/uploads/2021/09/AMC-Logo-04-1024x449.png | https://www.facebook.com/tr?id=1795315120651843&ev=PageView&noscript=1 | https://www.facebook.com/tr?id=1795315120651843&ev=PageView&noscript=1&cd%5Bpage_title%5D=AMC+Awards+%7C+Book+Now&cd%5Bpost_type%5D=page&cd%5Bpost_id%5D=13164&cd%5Bplugin%5D=PixelYourSite&cd%5Buser_role%5D=guest&cd%5Bevent_url%5D=africanmarketingconfederation.org%2Famc-conference-2023%2Famc-awards-book-now%2F | D10: 5 | E10: 75 | F10: other:2, png:1, svg:3 | G10: 0 | H10: 0 | J10: FALSE | K10: Open
A11: https://africanmarketingconfederation.org/amc-conference-2023/amc-awards | B11: 25 | C11: /wp-content/plugins/gtranslate/flags/svg/en.svg | https://africanmarketingconfederation.org/wp-content/uploads/2021/08/facebook.svg | https://africanmarketingconfederation.org/wp-content/uploads/2021/08/linkedin.svg | https://africanmarketingconfederation.org/wp-content/uploads/2021/09/AMC-Logo-04-1024x449.png | https://africanmarketingconfederation.org/wp-content/uploads/2023/08/Awards-Brochure-Icon-02.png | https://africanmarketingconfederation.org/wp-content/uploads/2023/08/Young-Marketing-Professional.png | https://africanmarketingconfederation.org/wp-content/uploads/2023/11/Daniel-Ogong.jpg | https://africanmarketingconfederation.org/wp-content/uploads/2023/11/Honorary-Member.png | https://africanmarketingconfederation.org/wp-content/uploads/2023/11/Pic-13-Gillian-with-new-honorary-member.jpg | https://www.facebook.com/tr?id=1795315120651843&ev=PageView&noscript=1 | https://www.facebook.com/tr?id=1795315120651843&ev=PageView&noscript=1&cd%5Bpage_title%5D=AMC+Awards&cd%5Bpost_type%5D=page&cd%5Bpost_id%5D=12954&cd%5Bplugin%5D=PixelYourSite&cd%5Buser_role%5D=guest&cd%5Bevent_url%5D=africanmarketingconfederation.org%2Famc-conference-2023%2Famc-awards%2F | D11: 7 | E11: 72 | F11: jpg:2, other:2, png:4, svg:3 | G11: 0 | H11: 0 | J11: FALSE | K11: Open

Sheet Duplicates
A1: URL | B1: Title Duplicate Count | C1: Meta Description Duplicate Count | D1: Title Duplicate URLs | E1: Meta Duplicate URLs | F1: Open in Main | G1: BACK TO DASHBOARD | H1: BACK TO DASHBOARD_1
A2: https://africanmarketingconfederation.org/about-us | B2: 1 | C2: 1 | F2: Open
A3: https://africanmarketingconfederation.org/ | B3: 1 | C3: 1 | F3: Open
A4: https://africanmarketingconfederation.org/african-marketing-confederation-tourism-chapter | B4: 1 | C4: 1 | F4: Open
A5: https://africanmarketingconfederation.org/amc-awards-2024 | B5: 1 | C5: 1 | F5: Open
A6: https://africanmarketingconfederation.org/amc-conference-2022-prospectus | B6: 1 | C6: 1 | F6: Open
A7: https://africanmarketingconfederation.org/amc-conference-2022-thank-you | B7: 1 | C7: 1 | F7: Open
A8: https://africanmarketingconfederation.org/amc-conference-2022 | B8: 1 | C8: 1 | F8: Open
A9: https://africanmarketingconfederation.org/amc-conference-2023 | B9: 1 | C9: 1 | F9: Open
A10: https://africanmarketingconfederation.org/amc-conference-2023/amc-awards-book-now | B10: 1 | C10: 0 | F10: Open
A11: https://africanmarketingconfederation.org/amc-conference-2023/amc-awards | B11: 1 | C11: 1 | F11: Open

Sheet Pattern and Template Issues
A1: WHAT IS THIS? This tab detects structural flaws coded into your page templates. Fixing one template here can instantly fix hundreds of pages. | B1: Column_2 | C1: Column_3 | D1: Column_4 | E1: Column_5 | F1: BACK TO DASHBOARD | G1: BACK TO DASHBOARD_1
A2: Subfolder | B2: URL Count | C2: Systemic Issue | D2: Affected Ratio | E2: Exact Action
A3: /amc-conference-2022-prospectus/ | B3: 1 | C3: Missing H1 is template-wide | D3: 100 | E3: Update template to render exactly one descriptive H1 for each page based on page-specific title data.
A4: /amc-conference-2022-thank-you/ | B4: 1 | C4: Missing H1 is template-wide | D4: 100 | E4: Update template to render exactly one descriptive H1 for each page based on page-specific title data.
A5: /amc-conference-2022/ | B5: 1 | C5: Missing H1 is template-wide | D5: 100 | E5: Update template to render exactly one descriptive H1 for each page based on page-specific title data.

Sheet PSI Performance
A1: URL | B1: Desktop Score | C1: Mobile Score | D1: Mobile LCP | E1: Mobile CLS | F1: Mobile TTFB | G1: Open in Main | H1: BACK TO DASHBOARD | I1: BACK TO DASHBOARD_1
A2: https://africanmarketingconfederation.org/about-us | B2: 0 | C2: 0 | D2: 0 | E2: 0 | F2: 0 | G2: Open
A3: https://africanmarketingconfederation.org/ | B3: 0 | C3: 0 | D3: 0 | E3: 0 | F3: 0 | G3: Open
A4: https://africanmarketingconfederation.org/african-marketing-confederation-tourism-chapter | B4: 0 | C4: 0 | D4: 0 | E4: 0 | F4: 0 | G4: Open
A5: https://africanmarketingconfederation.org/amc-awards-2024 | B5: 0 | C5: 0 | D5: 0 | E5: 0 | F5: 0 | G5: Open
A6: https://africanmarketingconfederation.org/amc-conference-2022-prospectus | B6: 0 | C6: 0 | D6: 0 | E6: 0 | F6: 0 | G6: Open
A7: https://africanmarketingconfederation.org/amc-conference-2022-thank-you | B7: 0 | C7: 0 | D7: 0 | E7: 0 | F7: 0 | G7: Open
A8: https://africanmarketingconfederation.org/amc-conference-2022 | B8: 0 | C8: 0 | D8: 0 | E8: 0 | F8: 0 | G8: Open
A9: https://africanmarketingconfederation.org/amc-conference-2023 | B9: 0 | C9: 0 | D9: 0 | E9: 0 | F9: 0 | G9: Open
A10: https://africanmarketingconfederation.org/amc-conference-2023/amc-awards-book-now | B10: 0 | C10: 0 | D10: 0 | E10: 0 | F10: 0 | G10: Open
A11: https://africanmarketingconfederation.org/amc-conference-2023/amc-awards | B11: 0 | C11: 0 | D11: 0 | E11: 0 | F11: 0 | G11: Open

Sheet IssueInventory
A1: URL | B1: Issue | C1: Severity | D1: Reference Tab | E1: Stable Issue ID | F1: Owner | G1: Status | H1: Sprint | I1: Open in Main | J1: Open in Reference | K1: BACK TO DASHBOARD | L1: BACK TO DASHBOARD_1
A2: https://africanmarketingconfederation.org/about-us | B2: Unmeasured | C2: Observation | D2: Technical | E2: https://africanmarketingconfederation.org/about-us::unmeasured | F2: Copy Writer | G2: Open | I2: =IFERROR(HYPERLINK("#Main!A"&MATCH(A2,Main!A:A,0),"Open"),HYPERLINK("#Main!A1","Open")) | J2: =IFERROR(HYPERLINK("#"&D2&"!A"&MATCH(A2,INDIRECT("'"&D2&"'!A:A"),0),"Open"),HYPERLINK("#"&D2&"!A1","Open"))
A3: https://africanmarketingconfederation.org/ | B3: Unmeasured | C3: Observation | D3: Technical | E3: https://africanmarketingconfederation.org/::unmeasured | F3: Copy Writer | G3: Open | I3: =IFERROR(HYPERLINK("#Main!A"&MATCH(A3,Main!A:A,0),"Open"),HYPERLINK("#Main!A1","Open")) | J3: =IFERROR(HYPERLINK("#"&D3&"!A"&MATCH(A3,INDIRECT("'"&D3&"'!A:A"),0),"Open"),HYPERLINK("#"&D3&"!A1","Open"))
A4: https://africanmarketingconfederation.org/african-marketing-confederation-tourism-chapter | B4: Unmeasured | C4: Observation | D4: Technical | E4: https://africanmarketingconfederation.org/african-marketing-confederation-tourism-chapter::unmeasured | F4: Copy Writer | G4: Open | I4: =IFERROR(HYPERLINK("#Main!A"&MATCH(A4,Main!A:A,0),"Open"),HYPERLINK("#Main!A1","Open")) | J4: =IFERROR(HYPERLINK("#"&D4&"!A"&MATCH(A4,INDIRECT("'"&D4&"'!A:A"),0),"Open"),HYPERLINK("#"&D4&"!A1","Open"))
A5: https://africanmarketingconfederation.org/amc-awards-2024 | B5: Unmeasured | C5: Observation | D5: Technical | E5: https://africanmarketingconfederation.org/amc-awards-2024::unmeasured | F5: Copy Writer | G5: Open | I5: =IFERROR(HYPERLINK("#Main!A"&MATCH(A5,Main!A:A,0),"Open"),HYPERLINK("#Main!A1","Open")) | J5: =IFERROR(HYPERLINK("#"&D5&"!A"&MATCH(A5,INDIRECT("'"&D5&"'!A:A"),0),"Open"),HYPERLINK("#"&D5&"!A1","Open"))
A6: https://africanmarketingconfederation.org/amc-conference-2022-prospectus | B6: Unmeasured | C6: Observation | D6: Technical | E6: https://africanmarketingconfederation.org/amc-conference-2022-prospectus::unmeasured | F6: Copy Writer | G6: Open | I6: =IFERROR(HYPERLINK("#Main!A"&MATCH(A6,Main!A:A,0),"Open"),HYPERLINK("#Main!A1","Open")) | J6: =IFERROR(HYPERLINK("#"&D6&"!A"&MATCH(A6,INDIRECT("'"&D6&"'!A:A"),0),"Open"),HYPERLINK("#"&D6&"!A1","Open"))
A7: https://africanmarketingconfederation.org/amc-conference-2022-thank-you | B7: Unmeasured | C7: Observation | D7: Technical | E7: https://africanmarketingconfederation.org/amc-conference-2022-thank-you::unmeasured | F7: Copy Writer | G7: Open | I7: =IFERROR(HYPERLINK("#Main!A"&MATCH(A7,Main!A:A,0),"Open"),HYPERLINK("#Main!A1","Open")) | J7: =IFERROR(HYPERLINK("#"&D7&"!A"&MATCH(A7,INDIRECT("'"&D7&"'!A:A"),0),"Open"),HYPERLINK("#"&D7&"!A1","Open"))
A8: https://africanmarketingconfederation.org/amc-conference-2022 | B8: Unmeasured | C8: Observation | D8: Technical | E8: https://africanmarketingconfederation.org/amc-conference-2022::unmeasured | F8: Copy Writer | G8: Open | I8: =IFERROR(HYPERLINK("#Main!A"&MATCH(A8,Main!A:A,0),"Open"),HYPERLINK("#Main!A1","Open")) | J8: =IFERROR(HYPERLINK("#"&D8&"!A"&MATCH(A8,INDIRECT("'"&D8&"'!A:A"),0),"Open"),HYPERLINK("#"&D8&"!A1","Open"))
A9: https://africanmarketingconfederation.org/amc-conference-2023 | B9: Unmeasured | C9: Observation | D9: Technical | E9: https://africanmarketingconfederation.org/amc-conference-2023::unmeasured | F9: Copy Writer | G9: Open | I9: =IFERROR(HYPERLINK("#Main!A"&MATCH(A9,Main!A:A,0),"Open"),HYPERLINK("#Main!A1","Open")) | J9: =IFERROR(HYPERLINK("#"&D9&"!A"&MATCH(A9,INDIRECT("'"&D9&"'!A:A"),0),"Open"),HYPERLINK("#"&D9&"!A1","Open"))
A10: https://africanmarketingconfederation.org/amc-conference-2023/amc-awards-book-now | B10: Unmeasured | C10: Observation | D10: Technical | E10: https://africanmarketingconfederation.org/amc-conference-2023/amc-awards-book-now::unmeasured | F10: Copy Writer | G10: Open | I10: =IFERROR(HYPERLINK("#Main!A"&MATCH(A10,Main!A:A,0),"Open"),HYPERLINK("#Main!A1","Open")) | J10: =IFERROR(HYPERLINK("#"&D10&"!A"&MATCH(A10,INDIRECT("'"&D10&"'!A:A"),0),"Open"),HYPERLINK("#"&D10&"!A1","Open"))
A11: https://africanmarketingconfederation.org/amc-conference-2023/amc-awards | B11: Unmeasured | C11: Observation | D11: Technical | E11: https://africanmarketingconfederation.org/amc-conference-2023/amc-awards::unmeasured | F11: Copy Writer | G11: Open | I11: =IFERROR(HYPERLINK("#Main!A"&MATCH(A11,Main!A:A,0),"Open"),HYPERLINK("#Main!A1","Open")) | J11: =IFERROR(HYPERLINK("#"&D11&"!A"&MATCH(A11,INDIRECT("'"&D11&"'!A:A"),0),"Open"),HYPERLINK("#"&D11&"!A1","Open"))

Sheet CrawlGraph
A1: URL | B1: Inlinks Count | C1: Inlinks URLs | D1: Orphan Candidate | E1: Click Depth | F1: Internal PageRank | G1: Open in Main | H1: BACK TO DASHBOARD | I1: BACK TO DASHBOARD_1
A2: https://africanmarketingconfederation.org/about-us | B2: 6 | C2: https://africanmarketingconfederation.org/ | https://africanmarketingconfederation.org/about-us | https://africanmarketingconfederation.org/african-marketing-confederation-tourism-chapter | https://africanmarketingconfederation.org/amc-conference-2022 | https://africanmarketingconfederation.org/amc-conference-2022-prospectus | https://africanmarketingconfederation.org/amc-conference-2022-thank-you | D2: FALSE | E2: 1 | F2: 0.271899 | G2: Open
A3: https://africanmarketingconfederation.org/ | B3: 8 | C3: https://africanmarketingconfederation.org/ | https://africanmarketingconfederation.org/about-us | https://africanmarketingconfederation.org/african-marketing-confederation-tourism-chapter | https://africanmarketingconfederation.org/amc-conference-2022 | https://africanmarketingconfederation.org/amc-conference-2022-prospectus | https://africanmarketingconfederation.org/amc-conference-2022-thank-you | https://africanmarketingconfederation.org/amc-conference-2023/amc-awards | https://africanmarketingconfederation.org/amc-conference-2023/amc-awards-book-now | D3: FALSE | E3: 0 | F3: 0.287449 | G3: Open
A4: https://africanmarketingconfederation.org/african-marketing-confederation-tourism-chapter | B4: 6 | C4: https://africanmarketingconfederation.org/ | https://africanmarketingconfederation.org/about-us | https://africanmarketingconfederation.org/african-marketing-confederation-tourism-chapter | https://africanmarketingconfederation.org/amc-conference-2022 | https://africanmarketingconfederation.org/amc-conference-2022-prospectus | https://africanmarketingconfederation.org/amc-conference-2022-thank-you | D4: FALSE | E4: 1 | F4: 0.271899 | G4: Open
A5: https://africanmarketingconfederation.org/amc-awards-2024 | B5: 0 | D5: TRUE | F5: 0.019665 | G5: Open
A6: https://africanmarketingconfederation.org/amc-conference-2022-prospectus | B6: 0 | D6: TRUE | F6: 0.019665 | G6: Open
A7: https://africanmarketingconfederation.org/amc-conference-2022-thank-you | B7: 0 | D7: TRUE | F7: 0.019665 | G7: Open
A8: https://africanmarketingconfederation.org/amc-conference-2022 | B8: 0 | D8: TRUE | F8: 0.019665 | G8: Open
A9: https://africanmarketingconfederation.org/amc-conference-2023 | B9: 2 | C9: https://africanmarketingconfederation.org/amc-conference-2023/amc-awards | https://africanmarketingconfederation.org/amc-conference-2023/amc-awards-book-now | D9: FALSE | F9: 0.035214 | G9: Open
A10: https://africanmarketingconfederation.org/amc-conference-2023/amc-awards-book-now | B10: 0 | D10: TRUE | F10: 0.019665 | G10: Open
A11: https://africanmarketingconfederation.org/amc-conference-2023/amc-awards | B11: 2 | C11: https://africanmarketingconfederation.org/amc-conference-2023/amc-awards | https://africanmarketingconfederation.org/amc-conference-2023/amc-awards-book-now | D11: FALSE | F11: 0.035214 | G11: Open

Sheet SitemapQA
A1: Sitemap URL | B1: Final URL | C1: Status Code | D1: Found via Crawl | E1: Found via Sitemap | F1: Discovery Source | G1: In Sitemap but Non-200 | H1: Sitemap URL Redirects | I1: In Sitemap but Canonicalized Elsewhere | J1: Missing <lastmod> | K1: Missing <changefreq> | L1: Missing <priority> | M1: Sitemap <lastmod> | N1: Sitemap <changefreq> | O1: Sitemap <priority> | P1: Source Sitemap | Q1: BACK TO DASHBOARD | R1: BACK TO DASHBOARD_1
A2: https://africanmarketingconfederation.org/ | B2: https://africanmarketingconfederation.org/ | C2: 200 | D2: TRUE | E2: TRUE | F2: Both | G2: FALSE | H2: 0 | I2: 0 | J2: FALSE | K2: FALSE | L2: FALSE | M2: 2026-04-29 08:23:06 | N2: always | O2: 1 | P2: https://africanmarketingconfederation.org/page-sitemap.xml
A3: https://africanmarketingconfederation.org/publications-2/ | D3: FALSE | E3: TRUE | F3: Sitemap | G3: TRUE | J3: FALSE | K3: FALSE | L3: FALSE | M3: 2026-04-29 07:05:09 | N3: weekly | O3: 0.7 | P3: https://africanmarketingconfederation.org/page-sitemap.xml
A4: https://africanmarketingconfederation.org/publication-download-list/ | D4: FALSE | E4: TRUE | F4: Sitemap | G4: TRUE | J4: FALSE | K4: FALSE | L4: FALSE | M4: 2026-04-28 12:04:20 | N4: weekly | O4: 0.7 | P4: https://africanmarketingconfederation.org/page-sitemap.xml
A5: https://africanmarketingconfederation.org/launch-event-2026-amc-conference/ | D5: FALSE | E5: TRUE | F5: Sitemap | G5: TRUE | J5: FALSE | K5: FALSE | L5: FALSE | M5: 2026-04-24 07:07:22 | N5: weekly | O5: 0.7 | P5: https://africanmarketingconfederation.org/page-sitemap.xml
A6: https://africanmarketingconfederation.org/amc-conference-2026/ | D6: FALSE | E6: TRUE | F6: Sitemap | G6: TRUE | J6: FALSE | K6: FALSE | L6: FALSE | M6: 2026-04-24 06:54:40 | N6: weekly | O6: 0.7 | P6: https://africanmarketingconfederation.org/page-sitemap.xml
A7: https://africanmarketingconfederation.org/certified-professional-marketer-africa/ | D7: FALSE | E7: TRUE | F7: Sitemap | G7: TRUE | J7: FALSE | K7: FALSE | L7: FALSE | M7: 2026-04-20 08:17:50 | N7: weekly | O7: 0.7 | P7: https://africanmarketingconfederation.org/page-sitemap.xml
A8: https://africanmarketingconfederation.org/chartered-marketer-africa/ | D8: FALSE | E8: TRUE | F8: Sitemap | G8: TRUE | J8: FALSE | K8: FALSE | L8: FALSE | M8: 2026-04-20 07:58:07 | N8: weekly | O8: 0.7 | P8: https://africanmarketingconfederation.org/page-sitemap.xml
A9: https://africanmarketingconfederation.org/education/ | D9: FALSE | E9: TRUE | F9: Sitemap | G9: TRUE | J9: FALSE | K9: FALSE | L9: FALSE | M9: 2026-04-20 06:32:38 | N9: weekly | O9: 0.7 | P9: https://africanmarketingconfederation.org/page-sitemap.xml
A10: https://africanmarketingconfederation.org/awards-2026/ | D10: FALSE | E10: TRUE | F10: Sitemap | G10: TRUE | J10: FALSE | K10: FALSE | L10: FALSE | M10: 2026-04-17 09:26:48 | N10: weekly | O10: 0.7 | P10: https://africanmarketingconfederation.org/page-sitemap.xml
A11: https://africanmarketingconfederation.org/contact-us/ | D11: FALSE | E11: TRUE | F11: Sitemap | G11: TRUE | J11: FALSE | K11: FALSE | L11: FALSE | M11: 2026-04-17 08:58:32 | N11: weekly | O11: 0.7 | P11: https://africanmarketingconfederation.org/page-sitemap.xml
A12: https://africanmarketingconfederation.org/news-articles/ | D12: FALSE | E12: TRUE | F12: Sitemap | G12: TRUE | J12: FALSE | K12: FALSE | L12: FALSE | M12: 2026-04-17 08:58:00 | N12: weekly | O12: 0.7 | P12: https://africanmarketingconfederation.org/page-sitemap.xml
A13: https://africanmarketingconfederation.org/african-marketing-confederation-tourism-chapter/ | B13: https://africanmarketingconfederation.org/african-marketing-confederation-tourism-chapter | C13: 200 | D13: TRUE | E13: TRUE | F13: Both | G13: FALSE | H13: 0 | I13: 0 | J13: FALSE | K13: FALSE | L13: FALSE | M13: 2026-04-17 08:55:48 | N13: weekly | O13: 0.7 | P13: https://africanmarketingconfederation.org/page-sitemap.xml
A14: https://africanmarketingconfederation.org/members/ | D14: FALSE | E14: TRUE | F14: Sitemap | G14: TRUE | J14: FALSE | K14: FALSE | L14: FALSE | M14: 2026-04-17 08:55:31 | N14: weekly | O14: 0.7 | P14: https://africanmarketingconfederation.org/page-sitemap.xml
A15: https://africanmarketingconfederation.org/sub-committees/ | D15: FALSE | E15: TRUE | F15: Sitemap | G15: TRUE | J15: FALSE | K15: FALSE | L15: FALSE | M15: 2026-04-17 08:53:47 | N15: weekly | O15: 0.7 | P15: https://africanmarketingconfederation.org/page-sitemap.xml
A16: https://africanmarketingconfederation.org/about-us/ | B16: https://africanmarketingconfederation.org/about-us | C16: 200 | D16: TRUE | E16: TRUE | F16: Both | G16: FALSE | H16: 0 | I16: 0 | J16: FALSE | K16: FALSE | L16: FALSE | M16: 2026-04-17 08:53:24 | N16: weekly | O16: 0.7 | P16: https://africanmarketingconfederation.org/page-sitemap.xml
A17: https://africanmarketingconfederation.org/awards-2026-1/ | D17: FALSE | E17: TRUE | F17: Sitemap | G17: TRUE | J17: FALSE | K17: FALSE | L17: FALSE | M17: 2026-04-08 11:43:29 | N17: weekly | O17: 0.7 | P17: https://africanmarketingconfederation.org/page-sitemap.xml
A18: https://africanmarketingconfederation.org/awards-2026-test/ | D18: FALSE | E18: TRUE | F18: Sitemap | G18: TRUE | J18: FALSE | K18: FALSE | L18: FALSE | M18: 2026-04-08 09:47:58 | N18: weekly | O18: 0.7 | P18: https://africanmarketingconfederation.org/page-sitemap.xml
A19: https://africanmarketingconfederation.org/speakers-2025/ | D19: FALSE | E19: TRUE | F19: Sitemap | G19: TRUE | J19: FALSE | K19: FALSE | L19: FALSE | M19: 2026-03-26 12:27:48 | N19: weekly | O19: 0.7 | P19: https://africanmarketingconfederation.org/page-sitemap.xml
A20: https://africanmarketingconfederation.org/amc-conference-2026-awards-nominations-thank-you/ | D20: FALSE | E20: TRUE | F20: Sitemap | G20: TRUE | J20: FALSE | K20: FALSE | L20: FALSE | M20: 2026-03-04 07:14:00 | N20: weekly | O20: 0.7 | P20: https://africanmarketingconfederation.org/page-sitemap.xml
A21: https://africanmarketingconfederation.org/amc-conference-2026-zambia-thank-you/ | D21: FALSE | E21: TRUE | F21: Sitemap | G21: TRUE | J21: FALSE | K21: FALSE | L21: FALSE | M21: 2026-03-04 06:43:52 | N21: weekly | O21: 0.7 | P21: https://africanmarketingconfederation.org/page-sitemap.xml
A22: https://africanmarketingconfederation.org/amc-launch-event-zambia-thank-you-2026/ | D22: FALSE | E22: TRUE | F22: Sitemap | G22: TRUE | J22: FALSE | K22: FALSE | L22: FALSE | M22: 2026-03-04 06:43:51 | N22: weekly | O22: 0.7 | P22: https://africanmarketingconfederation.org/page-sitemap.xml
A23: https://africanmarketingconfederation.org/amc-marketing-conference-2024/awards-2025/ | D23: FALSE | E23: TRUE | F23: Sitemap | G23: TRUE | J23: FALSE | K23: FALSE | L23: FALSE | M23: 2026-02-05 07:09:45 | N23: weekly | O23: 0.7 | P23: https://africanmarketingconfederation.org/page-sitemap.xml
A24: https://africanmarketingconfederation.org/amc-conference-2025-highlights/ | D24: FALSE | E24: TRUE | F24: Sitemap | G24: TRUE | J24: FALSE | K24: FALSE | L24: FALSE | M24: 2026-01-28 11:37:11 | N24: weekly | O24: 0.7 | P24: https://africanmarketingconfederation.org/page-sitemap.xml
A25: https://africanmarketingconfederation.org/amc-conference-2022/ | B25: https://africanmarketingconfederation.org/amc-conference-2022 | C25: 200 | D25: TRUE | E25: TRUE | F25: Both | G25: FALSE | H25: 0 | I25: 0 | J25: FALSE | K25: FALSE | L25: FALSE | M25: 2026-01-21 00:07:32 | N25: weekly | O25: 0.7 | P25: https://africanmarketingconfederation.org/page-sitemap.xml
A26: https://africanmarketingconfederation.org/amc-conference-2023/gallery/ | D26: FALSE | E26: TRUE | F26: Sitemap | G26: TRUE | J26: FALSE | K26: FALSE | L26: FALSE | M26: 2026-01-09 00:06:37 | N26: weekly | O26: 0.7 | P26: https://africanmarketingconfederation.org/page-sitemap.xml
A27: https://africanmarketingconfederation.org/conference-registrations-2024/ | D27: FALSE | E27: TRUE | F27: Sitemap | G27: TRUE | J27: FALSE | K27: FALSE | L27: FALSE | M27: 2026-01-06 00:02:42 | N27: weekly | O27: 0.7 | P27: https://africanmarketingconfederation.org/page-sitemap.xml
A28: https://africanmarketingconfederation.org/elementor-31820/ | D28: FALSE | E28: TRUE | F28: Sitemap | G28: TRUE | J28: FALSE | K28: FALSE | L28: FALSE | M28: 2025-12-10 08:14:03 | N28: weekly | O28: 0.7 | P28: https://africanmarketingconfederation.org/page-sitemap.xml
A29: https://africanmarketingconfederation.org/amc-conference-2024-recap/ | D29: FALSE | E29: TRUE | F29: Sitemap | G29: TRUE | J29: FALSE | K29: FALSE | L29: FALSE | M29: 2025-09-04 11:53:34 | N29: weekly | O29: 0.7 | P29: https://africanmarketingconfederation.org/page-sitemap.xml
A30: https://africanmarketingconfederation.org/amc-marketing-conference-2024/amc-programme-2025/ | D30: FALSE | E30: TRUE | F30: Sitemap | G30: TRUE | J30: FALSE | K30: FALSE | L30: FALSE | M30: 2025-08-22 08:14:01 | N30: weekly | O30: 0.7 | P30: https://africanmarketingconfederation.org/page-sitemap.xml
A31: https://africanmarketingconfederation.org/amc-conference-2025/ | D31: FALSE | E31: TRUE | F31: Sitemap | G31: TRUE | J31: FALSE | K31: FALSE | L31: FALSE | M31: 2025-08-19 11:23:21 | N31: weekly | O31: 0.7 | P31: https://africanmarketingconfederation.org/page-sitemap.xml
A32: https://africanmarketingconfederation.org/amc-sponsors-2025/ | D32: FALSE | E32: TRUE | F32: Sitemap | G32: TRUE | J32: FALSE | K32: FALSE | L32: FALSE | M32: 2025-08-18 11:53:25 | N32: weekly | O32: 0.7 | P32: https://africanmarketingconfederation.org/page-sitemap.xml
A33: https://africanmarketingconfederation.org/amc-conference-2022-prospectus/ | B33: https://africanmarketingconfederation.org/amc-conference-2022-prospectus | C33: 200 | D33: TRUE | E33: TRUE | F33: Both | G33: FALSE | H33: 0 | I33: 0 | J33: FALSE | K33: FALSE | L33: FALSE | M33: 2025-07-14 07:22:03 | N33: weekly | O33: 0.7 | P33: https://africanmarketingconfederation.org/page-sitemap.xml
A34: https://africanmarketingconfederation.org/checkout/ | D34: FALSE | E34: TRUE | F34: Sitemap | G34: TRUE | J34: FALSE | K34: FALSE | L34: FALSE | M34: 2025-06-25 06:43:08 | N34: weekly | O34: 0.7 | P34: https://africanmarketingconfederation.org/page-sitemap.xml
A35: https://africanmarketingconfederation.org/test-payment-gate/ | D35: FALSE | E35: TRUE | F35: Sitemap | G35: TRUE | J35: FALSE | K35: FALSE | L35: FALSE | M35: 2025-06-24 13:09:52 | N35: weekly | O35: 0.7 | P35: https://africanmarketingconfederation.org/page-sitemap.xml
A36: https://africanmarketingconfederation.org/amc-marketing-conference-2024/amc-preregister-2025/ | D36: FALSE | E36: TRUE | F36: Sitemap | G36: TRUE | J36: FALSE | K36: FALSE | L36: FALSE | M36: 2025-05-21 07:15:39 | N36: weekly | O36: 0.7 | P36: https://africanmarketingconfederation.org/page-sitemap.xml
A37: https://africanmarketingconfederation.org/conference-faq-2025/ | D37: FALSE | E37: TRUE | F37: Sitemap | G37: TRUE | J37: FALSE | K37: FALSE | L37: FALSE | M37: 2025-05-16 09:55:10 | N37: weekly | O37: 0.7 | P37: https://africanmarketingconfederation.org/page-sitemap.xml
A38: https://africanmarketingconfederation.org/amc-marketing-conference-2024/amc-conference-2025-ghana-sponsors/ | D38: FALSE | E38: TRUE | F38: Sitemap | G38: TRUE | J38: FALSE | K38: FALSE | L38: FALSE | M38: 2025-05-15 13:46:52 | N38: weekly | O38: 0.7 | P38: https://africanmarketingconfederation.org/page-sitemap.xml
A39: https://africanmarketingconfederation.org/amc-forum-payments/ | D39: FALSE | E39: TRUE | F39: Sitemap | G39: TRUE | J39: FALSE | K39: FALSE | L39: FALSE | M39: 2025-05-14 06:45:46 | N39: weekly | O39: 0.7 | P39: https://africanmarketingconfederation.org/page-sitemap.xml
