Workbook

Sheet Table of Contents
A1: Table of Contents
A2: Section | B2: Open
A3: Dashboard | B3: =HYPERLINK("#Dashboard!A1","Open") -> Open
A4: Content Optimization Hub | B4: =HYPERLINK("#Content Optimization Hub!A1","Open") -> Open
A5: FixPlan | B5: =HYPERLINK("#FixPlan!A1","Open") -> Open
A6: Main | B6: =HYPERLINK("#Main!A1","Open") -> Open
A7: Technical | B7: =HYPERLINK("#Technical!A1","Open") -> Open
A8: Content | B8: =HYPERLINK("#Content!A1","Open") -> Open
A9: AEO | B9: =HYPERLINK("#AEO!A1","Open") -> Open
A10: Schema & Metadata | B10: =HYPERLINK("#Schema & Metadata!A1","Open") -> Open
A11: Links | B11: =HYPERLINK("#Links!A1","Open") -> Open
A12: Indexability | B12: =HYPERLINK("#Indexability!A1","Open") -> Open
A13: Redirects | B13: =HYPERLINK("#Redirects!A1","Open") -> Open
A14: Priority URLs | B14: =HYPERLINK("#Priority URLs!A1","Open") -> Open
A15: AIOSEO | B15: =HYPERLINK("#AIOSEO!A1","Open") -> Open
A16: Security | B16: =HYPERLINK("#Security!A1","Open") -> Open
A17: Summary | B17: =HYPERLINK("#Summary!A1","Open") -> Open
A18: Legend | B18: =HYPERLINK("#Legend!A1","Open") -> Open
A19: LinksDetail | B19: =HYPERLINK("#LinksDetail!A1","Open") -> Open
A20: Media | B20: =HYPERLINK("#Media!A1","Open") -> Open
A21: Duplicates | B21: =HYPERLINK("#Duplicates!A1","Open") -> Open
A22: TemplateClusters | B22: =HYPERLINK("#TemplateClusters!A1","Open") -> Open
A23: IssueInventory | B23: =HYPERLINK("#IssueInventory!A1","Open") -> Open
A24: RunMetadata | B24: =HYPERLINK("#RunMetadata!A1","Open") -> Open
A25: DeltaFromPreviousRun | B25: =HYPERLINK("#DeltaFromPreviousRun!A1","Open") -> Open
A26: ResolvedIssues | B26: =HYPERLINK("#ResolvedIssues!A1","Open") -> Open
A27: CrawlGraph | B27: =HYPERLINK("#CrawlGraph!A1","Open") -> Open
A28: SitemapQA | B28: =HYPERLINK("#SitemapQA!A1","Open") -> Open

Sheet Dashboard
A1: Metric | B1: Executive SEO & AEO Dashboard | C1: Column_3 | D1: Column_4 | E1: Column_5 | F1: Column_6 | G1: Column_7 | H1: Column_8 | I1: Column_9 | J1: Column_10 | K1: Column_11 | L1: Column_12 | M1: Column_13 | N1: Column_14 | O1: Column_15 | P1: Column_16 | Q1: Column_17 | R1: Column_18 | S1: Column_19 | T1: Column_20 | U1: Column_21 | V1: Column_22 | W1: Column_23 | X1: Column_24 | Y1: Column_25
A2: URLs Crawled | B2: Executive SEO & AEO Performance Report
A3: Pass Rate (%) | B3: 1970-01-01 00:00:00.000000000
A4: Critical URL Count | B4: EXECUTIVE METRICS | C4: Value | E4: OWNER ISSUE SUMMARY (PIVOT)
A5: Warning URL Count | B5: =HYPERLINK("#Main!A1","Total URLs") -> Total URLs | C5: 0 | E5: Owner | F5: Issue Rows | G5: Affected URLs | H5: Critical | I5: Warning | J5: Observation
A6: Status Distribution | B6: =HYPERLINK("#Summary!A1","Overall Health Score") -> Overall Health Score | C6: =IFERROR(59.66/100,0) -> 0.5966 | E6: =HYPERLINK("#FixPlan!A1","Copy Writer") -> Copy Writer | F6: 20 | G6: 530 | H6: 1 | I6: 8 | J6: 11
A7: Score Bands | B7: =HYPERLINK("#Summary!A1","SEO Pass Rate %") -> SEO Pass Rate % | C7: =IFERROR(0/85,0) -> 0 | E7: =HYPERLINK("#FixPlan!A1","Server/Host") -> Server/Host | F7: 5 | G7: 257 | H7: 2 | I7: 0 | J7: 3
B8: =HYPERLINK("#Technical!A1","Pass URLs") -> Pass URLs | C8: 0 | E8: =HYPERLINK("#FixPlan!A1","Dev") -> Dev | F8: 9 | G8: 0 | H8: 4 | I8: 4 | J8: 1
B9: =HYPERLINK("#FixPlan!A1","Critical URLs") -> Critical URLs | C9: 2
B10: =HYPERLINK("#Technical!A1","Warning URLs") -> Warning URLs | C10: 83
B11: =HYPERLINK("#Technical!A1","Error Rate % (4xx/5xx)") -> Error Rate % (4xx/5xx) | C11: =IFERROR(2/85,0) -> 0.023529412
B12: =HYPERLINK("#Technical!A1","Crawl Success Rate % (2xx)") -> Crawl Success Rate % (2xx) | C12: =IFERROR(83/85,0) -> 0.97647059
B13: =HYPERLINK("#Technical!A1","Critical URL Rate %") -> Critical URL Rate % | C13: =IFERROR(2/85,0) -> 0.023529412
B14: =HYPERLINK("#Technical!A1","Warning URL Rate %") -> Warning URL Rate % | C14: =IFERROR(83/85,0) -> 0.97647059
B15: Projected Health Score % (if all To Do done) | C15: 0.83863529
B16: Projected Pass Rate % (if all To Do done) | C16: 0.75588235
B18: Status | C18: Count
B19: 200 OK | C19: 83
B20: 3xx Redirects | C20: 0 | E20: Traditional SEO vs. 2026 AEO Readiness
B21: 4xx Errors | C21: 2 | E21: Dimension | F21: Score
B22: 5xx Errors | C22: 0 | E22: Traditional SEO | F22: 0.7485
B23: Other | C23: 0 | E23: 2026 AEO Readiness | F23: 0
A24: Immediate Actions | E24: Strategic Narrative
A25: Top 5 URLs by Business Risk Score | B25: Severity | C25: Count | E25: High SEO / Low AEO suggests the site is visible to humans but invisible to AI answer engines.
A26: Rank | B26: Critical | C26: 7 | D26: Why Prioritized | G26: Status
A27: 1 | B27: Warning | C27: 12 | D27: Has critical issues | G27: Open
A28: 2 | B28: Medium | C28: 0 | D28: Has critical issues | E28: Yes | F28: Dev | G28: Open
A29: 3 | B29: Low | C29: 15 | D29: Monitor | E29: Yes | F29: Copy Writer | G29: Open
A30: 4 | B30: https://africanmarketingconfederation.org/amc-conference-2023/amc-awards-book-now/ | C30: 84 | D30: Monitor | E30: Yes | F30: Copy Writer | G30: Open
A31: 5 | B31: PRIORITY SNAPSHOT | C31: Value | D31: Monitor | E31: Yes | F31: Copy Writer | G31: Open
B32: Top Blocking Issue | C32: No Compression Header
B33: Top Issue Affected URLs | C33: 85
B34: 4xx/5xx URLs | C34: 2
B35: Avg TTFB (ms) | C35: 250.29
B37: Quick Navigation | C37: Open
B38: Fix Plan | C38: =HYPERLINK("#FixPlan!A1","Open") -> Open
B39: Main URL Data | C39: =HYPERLINK("#Main!A1","Open") -> Open
B40: Technical Diagnostics | C40: =HYPERLINK("#Technical!A1","Open") -> Open
B41: Indexability | C41: =HYPERLINK("#Indexability!A1","Open") -> Open
B42: AEO Opportunities | C42: =HYPERLINK("#AEO!A1","Open") -> Open
B43: AIOSEO Action Queue | C43: =HYPERLINK("#AIOSEO!A1","Open") -> Open
B44: TOP ISSUES TO FIX FIRST | C44: Affected URLs
B45: =HYPERLINK("#FixPlan!A9","Low AEO Readiness Score") -> Low AEO Readiness Score | C45: 85
B46: =HYPERLINK("#FixPlan!A8","AI Crawlers Not Explicitly Allowed") -> AI Crawlers Not Explicitly Allowed | C46: 85
B47: =HYPERLINK("#FixPlan!A7","No 40-60 Word Answer Paragraphs") -> No 40-60 Word Answer Paragraphs | C47: 85
B48: =HYPERLINK("#FixPlan!A6","No Answer-Friendly Structure") -> No Answer-Friendly Structure | C48: 85
B49: =HYPERLINK("#FixPlan!A3","No Cache-Control Header") -> No Cache-Control Header | C49: 85
B51: BUSINESS IMPACT SUMMARY
B52: 2 error URLs detected (2 4xx / 0 5xx). Critical issue volume is 2 URLs and warning volume is 83. Top blocker: No Compression Header affecting 85 URLs.

Sheet Content Optimization Hub
A1: 🚀 CONTENT HUB INSTRUCTIONS: 1. Draft content in 'Proposed' columns. | 2. Ensure 'Count' columns are Green. | 3. Use 'Elementor' link for direct editing. | 4. Update 'Status' to 'Completed' when finished. | 5. Preview branding in 'OG Image Preview' column.
A2: Status | B2: Assigned Owner | C2: Content Cluster ID | D2: URL | E2: Elementor Builder Link | F2: Target Keywords | G2: Current Page Copy Snippet | H2: Current Title | I2: Proposed Title (50-60 Chars) | J2: Title Count | K2: Current Meta Desc | L2: Proposed Meta Desc (120-160 Chars) | M2: Desc Count | N2: Current H-Tag Structure | O2: Proposed H-Tag Fixes | P2: AEO Answer Block Draft | Q2: FAQ/QA Draft | R2: Current OG-Image URL | S2: OG Image Preview | T2: Social Share Note | U2: Open in Main | V2: BACK TO DASHBOARD
A3: To Do | B3: Unassigned | C3: home-african-marketing-confed | D3: https://africanmarketingconfederation.org/ | E3: https://africanmarketingconfederation.org/wp-admin/post.php?post=8&action=elementor | F3: [Auto]: H1 ABOUT The African Marketing Confederation H2 The 2026 AMC Conference H2 Meets the Mighty Victoria Falls H2 23 25 September Livingstone Zambia H2 The 2026 AMC Conference H2 Meets the Mighty Victoria Falls | G3: European marketers gather to choose their top achievers for 2026 Marketing associations from across Europe nominated national champions, with 10 finalists competing for the Marketer of the Year title. Read More » April 30, 2026 | H3: African Marketing Confederation - Uniting Marketers for Excellence | J3: =LEN(I3) -> 0 | K3: The African Marketing Confederation is the ground-breaking Pan-African body driving the development of top marketing standards across Africa and beyond. | M3: =LEN(L3) -> 0 | N3: H1: ABOUT The African Marketing Confederation H2: The 2026 AMC Conference H2: Meets the Mighty Victoria Falls H2: 23-25 September | Livingstone, Zambia H2: The 2026 AMC Conference H2: Meets the Mighty Victoria Falls | S3: =IF(LEN(R3)>0, _xludf.IMAGE(R3), "") | U3: =IFERROR(HYPERLINK("#Main!A"&MATCH(D2,Main!A:A,0),"Open"),HYPERLINK("#Main!A1","Open")) -> Open
A4: To Do | B4: Unassigned | C4: about-us-african-marketing-confed | D4: https://africanmarketingconfederation.org/about-us/ | E4: https://africanmarketingconfederation.org/wp-admin/post.php?post=84&action=elementor | F4: [Auto]: about us | G4: Skip to content ABOUT The African Marketing Confederation​ The African Marketing Confederation is the ground-breaking Pan African body of marketing professionals spearheading the ongoing development of the highest possible standards of marketing acro... | H4: African Marketing Confederation – The Leading Marketing Professional Body – African Marketing Confederation | J4: =LEN(I4) -> 0 | K4: ABOUT The African Marketing Confederation​ The African Marketing Confederation is the ground-breaking Pan African body of marketing professionals spearheading the ongoing development of the highest possible standards of marketing across Africa. Founded in 2011, the AMC is a collaboration between the African national marketing bodies and associations to exchange expertise and information, and to promote | M4: =LEN(L4) -> 0 | N4: H1: ABOUT The African Marketing Confederation​ H3: African Marketing Confederation ​ PRESIDENT’S COUNCIL H2: Helen McIntee H2: President and Co-founder H2: David Balikuddembe H2: Secretary General | S4: =IF(LEN(R4)>0, _xludf.IMAGE(R4), "") | U4: =IFERROR(HYPERLINK("#Main!A"&MATCH(D3,Main!A:A,0),"Open"),HYPERLINK("#Main!A1","Open")) -> Open
A5: To Do | B5: Unassigned | C5: african-marketing-confederation-tourism-chapter-african-marketing-confed | D5: https://africanmarketingconfederation.org/african-marketing-confederation-tourism-chapter/ | E5: https://africanmarketingconfederation.org/wp-admin/post.php?post=28165&action=elementor | F5: [Auto]: african marketing confederation tourism chapter | G5: Skip to content African Marketing Confederation Tourism Chapter Shaping Africa’s Tourism Narrative Through Strategic Marketing Tourism is one of Africa’s most powerful economic engines – generating jobs, stimulating investment, and fostering cultural... | H5: African Marketing Confederation Tourism Chapter – African Marketing Confederation | J5: =LEN(I5) -> 0 | K5: African Marketing Confederation Tourism Chapter Shaping Africa’s Tourism Narrative Through Strategic Marketing Tourism is one of Africa’s most powerful economic engines - generating jobs, stimulating investment, and fostering cultural exchange.The African Marketing Confederation is proud to launch the Tourism Chapter, a bold initiative to elevate African tourism through the lens of world-class marketing. Launched at the | M5: =LEN(L5) -> 0 | N5: H1: African Marketing Confederation Tourism Chapter H3: Shaping Africa’s Tourism Narrative Through Strategic Marketing H2: Charting the Course: Purpose, Mission & Vision for Africa’s Tourism Future H2: Our Goals and Objectives: | S5: =IF(LEN(R5)>0, _xludf.IMAGE(R5), "") | U5: =IFERROR(HYPERLINK("#Main!A"&MATCH(D4,Main!A:A,0),"Open"),HYPERLINK("#Main!A1","Open")) -> Open
A6: To Do | B6: Unassigned | C6: amc-awards-2024-amc-awards-{n}-–-african | D6: https://africanmarketingconfederation.org/amc-awards-2024/ | E6: https://africanmarketingconfederation.org/wp-admin/post.php?post=16125&action=elementor | F6: [Auto]: amc awards 2024 | G6: NOMINATIONS are Open ! AMC Awards The African Marketing Confederation Awards event is held annually as part of the African Marketing Confederation Forum. This distinguished event celebrates and acknowledges outstanding marketing campaigns and the vis... | H6: AMC Awards 2024 – African Marketing Confederation | J6: =LEN(I6) -> 0 | K6: NOMINATIONS are Open ! AMC Awards The African Marketing Confederation Awards event is held annually as part of the African Marketing Confederation Forum. This distinguished event celebrates and acknowledges outstanding marketing campaigns and the visionary individuals behind them. The awards presented honor not only the groundbreaking strategies and creative brilliance that set these campaigns apart but | M6: =LEN(L6) -> 0 | N6: H1: NOMINATIONS are Open ! H2: Awards Categories H2: Tourism & Destination Marketing Campaign H2: of the Year H2: Best Social Media Campaign of the Year H2: Best Social Media Campaign | S6: =IF(LEN(R6)>0, _xludf.IMAGE(R6), "") | U6: =IFERROR(HYPERLINK("#Main!A"&MATCH(D5,Main!A:A,0),"Open"),HYPERLINK("#Main!A1","Open")) -> Open
A7: To Do | B7: Unassigned | C7: amc-conference-2022-prospectus-amc-conference-{n}-–-pro | D7: https://africanmarketingconfederation.org/amc-conference-2022-prospectus/ | E7: https://africanmarketingconfederation.org/wp-admin/post.php?post=5619&action=elementor | F7: [Auto]: amc conference 2022 prospectus | G7: Skip to content AMC Conference 2022 23 - 24 March 2022 Navigating Africa’s Unique Marketing Mix BOOK NOW Days Hours Minutes Seconds download prospectus To download the AMC 2022 Conference Prospectus please complete the form below: First Name Last Na... | H7: AMC Conference 2022 – Prospectus – African Marketing Confederation | J7: =LEN(I7) -> 0 | K7: AMC Conference 2022 23 - 24 March 2022 Navigating Africa's Unique Marketing Mix BOOK NOW Days Hours Minutes Seconds download prospectus To download the AMC 2022 Conference Prospectus please complete the form below: First Name Last Name Email Mobile Company I've read and agree to the Privacy Policy BOOK NOW FOR THE AMC CONFERENCE 2022 | M7: =LEN(L7) -> 0 | N7: H2: AMC Conference 2022 H2: download prospectus H2: BOOK NOW FOR THE AMC CONFERENCE 2022 | S7: =IF(LEN(R7)>0, _xludf.IMAGE(R7), "") | U7: =IFERROR(HYPERLINK("#Main!A"&MATCH(D6,Main!A:A,0),"Open"),HYPERLINK("#Main!A1","Open")) -> Open
A8: To Do | B8: Unassigned | C8: amc-conference-2022-thank-you-amc-conference-{n}-–-tha | D8: https://africanmarketingconfederation.org/amc-conference-2022-thank-you/ | E8: https://africanmarketingconfederation.org/wp-admin/post.php?post=4941&action=elementor | F8: [Auto]: amc conference 2022 thank you | G8: Skip to content AMC Conference 2022 23 - 24 March 2022 Navigating Africa’s Unique Marketing Mix ENQUIRE NOW Days Hours Minutes Seconds Success! Thank you for completing the enquiry form. Our team will contact you shortly! × The AMC Conference is the ... | H8: AMC Conference 2022 – Thank You – African Marketing Confederation | J8: =LEN(I8) -> 0 | K8: AMC Conference 2022 23 - 24 March 2022 Navigating Africa's Unique Marketing Mix ENQUIRE NOW Days Hours Minutes Seconds Success! Thank you for completing the enquiry form. Our team will contact you shortly! × Dismiss alert The AMC Conference is the must attend Pan African event for marketing professionals. It will focus on solutions for | M8: =LEN(L8) -> 0 | N8: H2: AMC Conference 2022 H2: WHO SHOULD ATTEND H2: Countries Participating H3: South Africa H3: Nigeria H3: Morocco | S8: =IF(LEN(R8)>0, _xludf.IMAGE(R8), "") | U8: =IFERROR(HYPERLINK("#Main!A"&MATCH(D7,Main!A:A,0),"Open"),HYPERLINK("#Main!A1","Open")) -> Open
A9: To Do | B9: Unassigned | C9: amc-conference-2022-amc-conference-{n}-–-afr | D9: https://africanmarketingconfederation.org/amc-conference-2022/ | E9: https://africanmarketingconfederation.org/wp-admin/post.php?post=4494&action=elementor | F9: [Auto]: amc conference 2022 | G9: AMC officially welcomes new member associations into the fold October 8, 2024 No Comments Angola, Botswana, Ethiopia, Mozambique and Tanzania receive their membership certificates. AMC now has 16 members. Read More » | H9: AMC Conference 2022 – African Marketing Confederation | J9: =LEN(I9) -> 0 | K9: corinna kopf onlyfans leaks AMC Conference 2022 Thank you for attending19 - 22 October 2022 The African Marketing Confederation's Annual Conference brought together the best collection of marketing leaders from top companies, marketing bodies and associations to share tactics and best practices on how to build the next generation of marketing. Event Highlights Thank you for Attending! | M9: =LEN(L9) -> 0 | N9: H2: AMC Conference 2022 H2: Event Highlights H3: AMC officially welcomes new member associations into the fold H3: Marketers are placing the ads where consumers don’t want to see them H3: Time for Africa to control its own narrative and image, delegates told H3: Excitement as Ghana announced as host of 2025 AMC marketing conference | S9: =IF(LEN(R9)>0, _xludf.IMAGE(R9), "") | U9: =IFERROR(HYPERLINK("#Main!A"&MATCH(D8,Main!A:A,0),"Open"),HYPERLINK("#Main!A1","Open")) -> Open
A10: To Do | B10: Unassigned | C10: amc-conference-2023-amc-conference-{n}-–-afr | D10: https://africanmarketingconfederation.org/amc-conference-2023/ | E10: https://africanmarketingconfederation.org/wp-admin/post.php?post=12371&action=elementor | F10: [Auto]: amc conference 2023 | G10: AMC Conference 6 - 9 September 2023 Imperial Botanical Beach Hotel, Entebbe, Uganda Thank you for joining us! View Presentations 2nd Annual African Marketing Confederation Conference Africa's $3.4 trillion Economy: Opportunities for Marketers Welcome... | H10: AMC Conference 2023 – African Marketing Confederation | J10: =LEN(I10) -> 0 | K10: AMC Conference 6 - 9 September 2023 Imperial Botanical Beach Hotel, Entebbe, Uganda Thank you for joining us! View Presentations 2nd Annual African Marketing Confederation Conference Africa's $3.4 trillion Economy: Opportunities for Marketers Welcome to the Recap of the 2nd Annual African Marketing Conference: Unveiling Africa's $3.4 Trillion EconomyOur conference was a remarkable exploration of | M10: =LEN(L10) -> 0 | N10: H1: AMC Conference H2: Africa's $3.4 trillion Economy: Opportunities for Marketers H2: Thank you for joining us! H2: Topics covered H3: Africa Free Trade Area H3: Business Intelligence | S10: =IF(LEN(R10)>0, _xludf.IMAGE(R10), "") | U10: =IFERROR(HYPERLINK("#Main!A"&MATCH(D9,Main!A:A,0),"Open"),HYPERLINK("#Main!A1","Open")) -> Open
A11: To Do | B11: Unassigned | C11: amc-conference-2023-amc-awards-|-book-now-–- | D11: https://africanmarketingconfederation.org/amc-conference-2023/amc-awards-book-now/ | E11: https://africanmarketingconfederation.org/wp-admin/post.php?post=13164&action=elementor | F11: [Auto]: amc awards book now | G11: Skip to content 0 Your Cart Your cart is empty Return to Shop Continue Shopping | H11: AMC Awards | Book Now – African Marketing Confederation | J11: =LEN(I11) -> 0 | K11: MISSING DESCRIPTION | M11: =LEN(L11) -> 0 | S11: =IF(LEN(R11)>0, _xludf.IMAGE(R11), "") | U11: =IFERROR(HYPERLINK("#Main!A"&MATCH(D10,Main!A:A,0),"Open"),HYPERLINK("#Main!A1","Open")) -> Open
A12: To Do | B12: Unassigned | C12: amc-conference-2023-amc-awards-–-african-mar | D12: https://africanmarketingconfederation.org/amc-conference-2023/amc-awards/ | E12: https://africanmarketingconfederation.org/wp-admin/post.php?post=12954&action=elementor | F12: [Auto]: amc awards | G12: Skip to content AMC Awards Welcome to the prestigious African Marketing Confederation Awards, a distinguished event that celebrates and acknowledges the remarkable achievements, cutting-edge innovations, and exceptional leadership demonstrated by out... | H12: AMC Awards – African Marketing Confederation | J12: =LEN(I12) -> 0 | K12: AMC Awards Welcome to the prestigious African Marketing Confederation Awards, a distinguished event that celebrates and acknowledges the remarkable achievements, cutting-edge innovations, and exceptional leadership demonstrated by outstanding individuals within the dynamic realm of marketing across the expansive African region.During the 2nd Annual African Marketing Confederation Conference, held from 6th to 9th September at the | M12: =LEN(L12) -> 0 | N12: H1: AMC Awards H2: AMC AWARD Winners | S12: =IF(LEN(R12)>0, _xludf.IMAGE(R12), "") | U12: =IFERROR(HYPERLINK("#Main!A"&MATCH(D11,Main!A:A,0),"Open"),HYPERLINK("#Main!A1","Open")) -> Open
A13: To Do | B13: Unassigned | C13: amc-conference-2023-book-now-|-thank-you-–-a | D13: https://africanmarketingconfederation.org/amc-conference-2023/book-now-thank-you/ | E13: https://africanmarketingconfederation.org/wp-admin/post.php?post=12497&action=elementor | F13: [Auto]: book now thank you | G13: Thank you for completing your booking! Congratulations on booking your seat to the 2023 AfricaPro Conference presenting the 2nd Annual African Marketing Confederation Conference and Inaugural Technology Information Confederation Africa Conference! Yo... | H13: Book Now | Thank you – African Marketing Confederation | J13: =LEN(I13) -> 0 | K13: Thank you for completing your booking! Congratulations on booking your seat to the 2023 AfricaPro Conference presenting the 2nd Annual African Marketing Confederation Conference and Inaugural Technology Information Confederation Africa Conference! You will receive your email confirmation shortly with more event information. Be sure to keep an eye on the event website for up to | M13: =LEN(L13) -> 0 | N13: H2: Thank you for completing your booking! | S13: =IF(LEN(R13)>0, _xludf.IMAGE(R13), "") | U13: =IFERROR(HYPERLINK("#Main!A"&MATCH(D12,Main!A:A,0),"Open"),HYPERLINK("#Main!A1","Open")) -> Open
A14: To Do | B14: Unassigned | C14: amc-conference-2023-book-now-–-african-marke | D14: https://africanmarketingconfederation.org/amc-conference-2023/book-now/ | E14: https://africanmarketingconfederation.org/wp-admin/post.php?post=12407&action=elementor | F14: [Auto]: book now | G14: Skip to content Book Now Individual Booking Package Options 1: Full Conference + Accommodation 5 - 9 September 2023 890 USD 3 Day Conference Including Excursions: 5 Sept - Networking evening and light dinner 6 Sept - Official opening and barbecue din... | H14: Book Now – African Marketing Confederation | J14: =LEN(I14) -> 0 | K14: Book Now Individual Booking Package Options 1: Full Conference + Accommodation 5 - 9 September 2023 890 USD 3 Day Conference Including Excursions: 5 Sept - Networking evening and light dinner 6 Sept - Official opening and barbecue dinner 7 Sept - Sunset Cruise on Lake Victoria 8 Sept - Cultural Gala dinner at Ndere | M14: =LEN(L14) -> 0 | N14: H1: Book Now H3: Individual Booking H3: Group Bookings H3: Group Bookings | S14: =IF(LEN(R14)>0, _xludf.IMAGE(R14), "") | U14: =IFERROR(HYPERLINK("#Main!A"&MATCH(D13,Main!A:A,0),"Open"),HYPERLINK("#Main!A1","Open")) -> Open
A15: To Do | B15: Unassigned | C15: amc-conference-2023-download-prospectus-–-af | D15: https://africanmarketingconfederation.org/amc-conference-2023/download-prospectus/ | E15: https://africanmarketingconfederation.org/wp-admin/post.php?post=13098&action=elementor | F15: [Auto]: download prospectus | G15: BOOK NOW Prospectus Download the African Marketing Confederation Prospectus Learn more about the available sponsorship and exhibitor packages and how you can be a part of this exciting event First Name Last Name Email Position Are you a member of a c... | H15: Download Prospectus – African Marketing Confederation | J15: =LEN(I15) -> 0 | K15: BOOK NOW Prospectus Download the African Marketing Confederation Prospectus Learn more about the available sponsorship and exhibitor packages and how you can be a part of this exciting event First Name Last Name Email Position Are you a member of a country member body?--Select--Yes No I would like to receive monthly updates from AMCYes No | M15: =LEN(L15) -> 0 | N15: H1: Prospectus H2: Prospectus | S15: =IF(LEN(R15)>0, _xludf.IMAGE(R15), "") | U15: =IFERROR(HYPERLINK("#Main!A"&MATCH(D14,Main!A:A,0),"Open"),HYPERLINK("#Main!A1","Open")) -> Open
A16: To Do | B16: Unassigned | C16: amc-conference-2023-gallery-–-african-market | D16: https://africanmarketingconfederation.org/amc-conference-2023/gallery/ | E16: https://africanmarketingconfederation.org/wp-admin/post.php?post=13549&action=elementor | F16: [Auto]: gallery | G16: Skip to content Conference Gallery All Day 1 Day 2 Day 3 Night 1 Night 2 Night 3 0 Your Cart Your cart is empty Return to Shop Continue Shopping | H16: Gallery – African Marketing Confederation | J16: =LEN(I16) -> 0 | K16: Conference Gallery sydney sweeney met gala All Day 1 Day 2 Day 3 Night 1 Night 2 Night 3 | M16: =LEN(L16) -> 0 | N16: H1: Conference Gallery | S16: =IF(LEN(R16)>0, _xludf.IMAGE(R16), "") | U16: =IFERROR(HYPERLINK("#Main!A"&MATCH(D15,Main!A:A,0),"Open"),HYPERLINK("#Main!A1","Open")) -> Open
A17: To Do | B17: Unassigned | C17: amc-conference-2023-partners-–-african-marke | D17: https://africanmarketingconfederation.org/amc-conference-2023/partners/ | E17: https://africanmarketingconfederation.org/wp-admin/post.php?post=13282&action=elementor | F17: [Auto]: partners | G17: Skip to content Conference Partners AMC Member Bodies 0 Your Cart Your cart is empty Return to Shop Continue Shopping | H17: Partners – African Marketing Confederation | J17: =LEN(I17) -> 0 | K17: Conference Partners AMC Member Bodies | M17: =LEN(L17) -> 0 | N17: H1: Conference Partners | S17: =IF(LEN(R17)>0, _xludf.IMAGE(R17), "") | U17: =IFERROR(HYPERLINK("#Main!A"&MATCH(D16,Main!A:A,0),"Open"),HYPERLINK("#Main!A1","Open")) -> Open
A18: To Do | B18: Unassigned | C18: amc-conference-2023-programme-–-african-mark | D18: https://africanmarketingconfederation.org/amc-conference-2023/programme/ | E18: https://africanmarketingconfederation.org/wp-admin/post.php?post=12945&action=elementor | F18: [Auto]: programme | G18: Skip to content Programme Download Conference Presentations Are Marketers Intelligent Enough For AI - Fred Kithinzi Taking Africa to the world and bringing the world to Africa - Nondumiso Mabece| Next Media DGCEO Presentation Strategy and Technology:... | H18: Programme – African Marketing Confederation | J18: =LEN(I18) -> 0 | K18: Programme Download Conference Presentations Are Marketers Intelligent Enough For AI - Fred Kithinzi Taking Africa to the world and bringing the world to Africa - Nondumiso Mabece| Next Media DGCEO Presentation Strategy and Technology: Expanding the Success of Pan-African Brands - Prof. Robert Ebo Hinson Winning African Markets - Simon Harvey Culture as the New | M18: =LEN(L18) -> 0 | N18: H1: Programme H2: Download Conference Presentations H2: Conference Day 1 H3: WEDNESDAY | 6 SEPTEMBER 2023 H2: Conference Day 2 H3: THURSDAY | 7 SEPTEMBER 2023 | S18: =IF(LEN(R18)>0, _xludf.IMAGE(R18), "") | U18: =IFERROR(HYPERLINK("#Main!A"&MATCH(D17,Main!A:A,0),"Open"),HYPERLINK("#Main!A1","Open")) -> Open
A19: To Do | B19: Unassigned | C19: amc-conference-2023-speakers-–-african-marke | D19: https://africanmarketingconfederation.org/amc-conference-2023/speakers/ | E19: https://africanmarketingconfederation.org/wp-admin/post.php?post=13179&action=elementor | F19: [Auto]: speakers | G19: Skip to content Speakers Ali Hussein Kassim Kenya CEO - AHK Corp View Bio Cathy Adengo Uganda Head of Sustainability, Stanbic Bank Uganda View Bio Doreen Asaasira Muhangazi Uganda Chief Human Resource Officer View Bio James Sutton United Kingdom Stra... | H19: Speakers – African Marketing Confederation | J19: =LEN(I19) -> 0 | K19: Speakers Ali Hussein Kassim Kenya CEO - AHK Corp View Bio Cathy Adengo Uganda Head of Sustainability, Stanbic Bank Uganda View Bio Doreen Asaasira Muhangazi Uganda Chief Human Resource Officer View Bio James Sutton United Kingdom Strategy and Commercial Director - CIM-UK View Bio Juliet Ziswa Zimbabwe Marketing Director - OK Zimbabwe Limited Group View | M19: =LEN(L19) -> 0 | N19: H1: Speakers H2: Ali Hussein Kassim H3: Kenya H2: Cathy Adengo H3: Uganda H2: Doreen Asaasira Muhangazi | S19: =IF(LEN(R19)>0, _xludf.IMAGE(R19), "") | U19: =IFERROR(HYPERLINK("#Main!A"&MATCH(D18,Main!A:A,0),"Open"),HYPERLINK("#Main!A1","Open")) -> Open
A20: To Do | B20: Unassigned | C20: amc-conference-2024-recap-amc-conference-{n}-recap | D20: https://africanmarketingconfederation.org/amc-conference-2024-recap/ | E20: https://africanmarketingconfederation.org/wp-admin/post.php?post=22401&action=elementor | F20: [Auto]: amc conference 2024 recap | G20: Event Highlights AMC Marketing Conference 2024 Shaping the Future of African Marketing Get 2025 Conference Updates Share Your Experience Conference Day 1 The conference kicked off with insightful addresses, including a keynote from marketing expert ... | H20: AMC Conference 2024 Recap – African Marketing Confederation | J20: =LEN(I20) -> 0 | K20: Event Highlights AMC Marketing Conference 2024 Shaping the Future of African Marketing Get 2025 Conference Updates Share Your Experience Conference Day 1 The conference kicked off with insightful addresses, including a keynote from marketing expert Hermawan Kartajaya. Dr Philip Kotler, the Father of Modern Marketing, delivered a welcome address live from Chicago and we ended | M20: =LEN(L20) -> 0 | N20: H1: Event Highlights H3: Conference Day 1 H3: Conference Day 2 H3: Conference Day 3 H3: Did you attend the 2024 AMC Conference? We’d love to hear about your experience! H3: Countries Represented | S20: =IF(LEN(R20)>0, _xludf.IMAGE(R20), "") | U20: =IFERROR(HYPERLINK("#Main!A"&MATCH(D19,Main!A:A,0),"Open"),HYPERLINK("#Main!A1","Open")) -> Open
A21: To Do | B21: Unassigned | C21: amc-conference-2024-sponsors-packages-sponsors-packages-–-afri | D21: https://africanmarketingconfederation.org/amc-conference-2024-sponsors-packages/ | E21: https://africanmarketingconfederation.org/wp-admin/post.php?post=18318&action=elementor | F21: [Auto]: amc conference 2024 sponsors packages | G21: SPONSORSHIP PACKAGES AMC Full-Conference Package Labadi Beach Hotel Full-day conference attendance 4 nights’ accommodation All breakfasts, lunches, & 3 dinners $ 1550 View Product AMC Full-Conference Package La Palm Royal Beach Hotel Full-day confere... | H21: Sponsors Packages – African Marketing Confederation | J21: =LEN(I21) -> 0 | K21: SPONSORSHIP PACKAGES Diamond Package Overall Anchor and Title Sponsor $50000,00 View Product Platinum Package Industry Leader Sponsor / per Professional Body Stream $20000,00 View Product Silver Package Full Day (Option to Choose Day 1, 2, or 3) Provision of Delegates Apparel in the Form of Golf Shirts and Caps (Day 2 & 3) $12000,00 View | M21: =LEN(L21) -> 0 | N21: H1: SPONSORSHIP PACKAGES H2: AMC Full-Conference Package Labadi Beach Hotel H3: $ 1550 H2: AMC Full-Conference Package La Palm Royal Beach Hotel H3: $ 1330 H2: AMC Day Attendance Package | S21: =IF(LEN(R21)>0, _xludf.IMAGE(R21), "") | U21: =IFERROR(HYPERLINK("#Main!A"&MATCH(D20,Main!A:A,0),"Open"),HYPERLINK("#Main!A1","Open")) -> Open
A22: To Do | B22: Unassigned | C22: amc-conference-2025-highlights-amc-conference-{n}-highl | D22: https://africanmarketingconfederation.org/amc-conference-2025-highlights/ | E22: https://africanmarketingconfederation.org/wp-admin/post.php?post=30257&action=elementor | F22: [Auto]: amc conference 2025 highlights | G22: 2025 Event Highlights AMC Marketing Conference AMC Marketing Conference 250+ Delegates. 29 Countries. One Pan-African Voice. 250+ Delegates. 29 Countries. One Pan-African Marketing Voice. Get 2026 Conference Updates Share Your Experience 2025 Event H... | H22: AMC Conference 2025 Highlights – African Marketing Confederation | J22: =LEN(I22) -> 0 | K22: 2025 Event Highlights AMC Marketing Conference AMC Marketing Conference 250+ Delegates. 29 Countries. One Pan-African Voice.250+ Delegates. 29 Countries.One Pan-African Marketing Voice. Get 2026 Conference Updates Share Your Experience 2025 Event Highlights AMC Marketing Conference 400+ Delegates. 29 Countries.One Pan-African Voice. Get 2026 Conference Updates 2025 Event Highlights AMC Marketing Conference Get 2026 Conference Updates | M22: =LEN(L22) -> 0 | N22: H1: 2025 H2: Moments that Shaped the 2025 AMC Conference H2: Wednesday, 20 August H2: Opening Keynote H2: Back to Basics – Thriving in Tough Times H2: Creating Authentic Connections Through User-Generated & Short-Form Video | S22: =IF(LEN(R22)>0, _xludf.IMAGE(R22), "") | U22: =IFERROR(HYPERLINK("#Main!A"&MATCH(D21,Main!A:A,0),"Open"),HYPERLINK("#Main!A1","Open")) -> Open
A23: To Do | B23: Unassigned | C23: amc-conference-2025-amc-conference-{n} | D23: https://africanmarketingconfederation.org/amc-conference-2025/ | E23: https://africanmarketingconfederation.org/wp-admin/post.php?post=23710&action=elementor | F23: [Auto]: amc conference 2025 | G23: Thriving in Africa’s Evolving Markets: Trust, Trends & Technology AMC Conference 2025 20 – 22 August | Accra, Ghana Meet Our Speakers at the 2025 AMC Africa Conference See Speaker's Bio See Speaker's Bio See Speaker's Bio See Speaker's Bio See Speak... | H23: AMC Conference 2025 | J23: =LEN(I23) -> 0 | K23: Join Africa's top marketers at the AMC Conference 2025 n Accra, Ghana from 20-22 August - 3 days of insights, innovation, and powerful networking. | M23: =LEN(L23) -> 0 | N23: H1: AMC Conference 2025 H2: Meet Our Speakers at the 2025 AMC Africa Conference H2: Attend AMC Conference 2025 in Accra, Ghana H2: 2025 Conference Sponsors H3: AMC Conference 2025 H2: Unmatched Networking | S23: =IF(LEN(R23)>0, _xludf.IMAGE(R23), "") | U23: =IFERROR(HYPERLINK("#Main!A"&MATCH(D22,Main!A:A,0),"Open"),HYPERLINK("#Main!A1","Open")) -> Open
... A27: To Do | B27: Unassigned | C27: amc-conference-programme-hybrid-programme​-–-afri | D27: https://africanmarketingconfederation.org/amc-conference-programme/ | E27: https://africanmarketingconfederation.org/wp-admin/post.php?post=5057&action=elementor | F27: [Auto]: amc conference programme | G27: Skip to content AMC Conference 2022 HYBRID CONFERENCE PROGRAMME​ 23 - 24 March 2022 Navigating Africa’s Unique Marketing Mix Conference day 1 Conference day 2 BOOK NOW FOR THE AMC CONFERENCE 2022 BOOK NOW Conference day 1 Wednesday, 23 March 2022 08h... | H27: HYBRID PROGRAMME​ – African Marketing Confederation | J27: =LEN(I27) -> 0 | K27: AMC Conference 2022 HYBRID CONFERENCE PROGRAMME​ 23 - 24 March 2022 Navigating Africa's Unique Marketing Mix Conference day 1 Conference day 2 BOOK NOW FOR THE AMC CONFERENCE 2022 BOOK NOW Conference day 1 Wednesday, 23 March 2022 08h30 WELCOME | MC Opening Remarks 08h40 AMC STAKEHOLDER WELCOME 08h55 AFRICA MARKETING BAROMETER | Marketing Trends | M27: =LEN(L27) -> 0 | N27: H2: AMC Conference 2022 H2: HYBRID CONFERENCE PROGRAMME​ H2: BOOK NOW FOR THE AMC CONFERENCE 2022 H2: Conference day 1 H2: Conference day 2 H2: BOOK NOW FOR THE AMC CONFERENCE 2022 | S27: =IF(LEN(R27)>0, _xludf.IMAGE(R27), "") | U27: =IFERROR(HYPERLINK("#Main!A"&MATCH(D26,Main!A:A,0),"Open"),HYPERLINK("#Main!A1","Open")) -> Open
A28: To Do | B28: Unassigned | C28: amc-conference-sponsors-untitled | D28: https://africanmarketingconfederation.org/amc-conference-sponsors/ | F28: [Auto]: amc conference sponsors | H28: MISSING TITLE | J28: =LEN(I28) -> 0 | K28: MISSING DESCRIPTION | M28: =LEN(L28) -> 0 | S28: =IF(LEN(R28)>0, _xludf.IMAGE(R28), "") | U28: =IFERROR(HYPERLINK("#Main!A"&MATCH(D27,Main!A:A,0),"Open"),HYPERLINK("#Main!A1","Open")) -> Open
A29: To Do | B29: Unassigned | C29: amc-conference-thank-you-amc-conference-|-thank-y | D29: https://africanmarketingconfederation.org/amc-conference-thank-you/ | E29: https://africanmarketingconfederation.org/wp-admin/post.php?post=12477&action=elementor | F29: [Auto]: amc conference thank you | G29: Back to AMC Website Thank You! Success! Thank you for completing the enquiry form. Our team will contact you shortly! × 2nd Annual African Marketing Confederation Conference Africa's $3.4 trillion Economy: Opportunities for Marketers The African Mark... | H29: AMC Conference | Thank You – African Marketing Confederation | J29: =LEN(I29) -> 0 | K29: Back to AMC Website Thank You! Success! Thank you for completing the enquiry form. Our team will contact you shortly! × Dismiss this alert. 2nd Annual African Marketing Confederation Conference Africa's $3.4 trillion Economy: Opportunities for Marketers The African Marketing Confederation (AMC) and Uganda Marketers Society (UMS) welcome you to the 2nd Annual Conference, themed | M29: =LEN(L29) -> 0 | N29: H1: Thank You! H2: Africa's $3.4 trillion Economy: Opportunities for Marketers H3: Join us at this Conference H2: Topics that will be covered H3: Africa Free Trade Area H3: Business Intelligence | S29: =IF(LEN(R29)>0, _xludf.IMAGE(R29), "") | U29: =IFERROR(HYPERLINK("#Main!A"&MATCH(D28,Main!A:A,0),"Open"),HYPERLINK("#Main!A1","Open")) -> Open
A30: To Do | B30: Unassigned | C30: amc-forum-mombasa-amc-forum-mombasa-–-afri | D30: https://africanmarketingconfederation.org/amc-forum-mombasa/ | E30: https://africanmarketingconfederation.org/wp-admin/post.php?post=21958&action=elementor | F30: [Auto]: amc forum mombasa | G30: AMC Marketing Conference Sarova WhiteSands Beach Resort, Mombasa As a must-attend for all marketing professionals, this year’s marketing forum will address the crucial theme: Brand Resilience Amidst Economic Uncertainty In such tumultuous times acros... | H30: AMC Forum Mombasa – African Marketing Confederation | J30: =LEN(I30) -> 0 | K30: AMC Marketing Conference Sarova WhiteSands Beach Resort, Mombasa As a must-attend for all marketing professionals, this year’s marketing forum will address the crucial theme: Brand Resilience Amidst Economic Uncertainty In such tumultuous times across Africa and the rest of the world, brand resilience is both more important and challenging than ever.This year’s theme will offer | M30: =LEN(L30) -> 0 | N30: H1: AMC Marketing Conference H2: Brand Resilience Amidst Economic Uncertainty H3: Hear From Africa’s Marketing Leaders H2: Sponsors H2: Ali Hussein Kassim H3: Kenya | S30: =IF(LEN(R30)>0, _xludf.IMAGE(R30), "") | U30: =IFERROR(HYPERLINK("#Main!A"&MATCH(D29,Main!A:A,0),"Open"),HYPERLINK("#Main!A1","Open")) -> Open
A31: To Do | B31: Unassigned | C31: amc-forum-payments-amc-forum-payments-–-afr | D31: https://africanmarketingconfederation.org/amc-forum-payments/ | E31: https://africanmarketingconfederation.org/wp-admin/post.php?post=21984&action=elementor | F31: [Auto]: amc forum payments | G31: AMC Conference 2025 Thriving in Africa’s Evolving Markets: Trust, Trends & Technology No products found! PUBLICATIONS Strategic Marketing for Africa Magazine CONTACT INFORMATION info@africanmarketingconfederation.org 0 Your Cart Your cart is empty Re... | H31: AMC Forum Payments – African Marketing Confederation | J31: =LEN(I31) -> 0 | K31: AMC Conference 2025 Thriving in Africa’s Evolving Markets:Trust, Trends & Technology No products found! PUBLICATIONS Strategic Marketing for Africa Magazine CONTACT INFORMATION info@africanmarketingconfederation.org © 2021 by African Marketing Confederation | Privacy Policy | M31: =LEN(L31) -> 0 | N31: H2: AMC Conference 2025 | S31: =IF(LEN(R31)>0, _xludf.IMAGE(R31), "") | U31: =IFERROR(HYPERLINK("#Main!A"&MATCH(D30,Main!A:A,0),"Open"),HYPERLINK("#Main!A1","Open")) -> Open
A32: To Do | B32: Unassigned | C32: amc-launch-event-zambia-thank-you-2026-amc-launch-event-zambia- | D32: https://africanmarketingconfederation.org/amc-launch-event-zambia-thank-you-2026/ | E32: https://africanmarketingconfederation.org/wp-admin/post.php?post=33131&action=elementor | F32: [Auto]: amc launch event zambia thank you 2026 | G32: 2026 AMC Conference Launch Event 16 March 2026 | 10:00 CAT (GMT +2) Thank you for registering to view the live stream of the African Marketing Confederation Conference launch event. You will receive your access link as soon as the live stream becomes... | H32: AMC Launch Event Zambia Thank You 2026 – African Marketing Confederation | J32: =LEN(I32) -> 0 | K32: 2026 AMC Conference Launch Event 16 March 2026 | 10:00 CAT (GMT +2)Thank you for registering to view the live stream of the African Marketing Confederation Conference launch event.You will receive your access link as soon as the live stream becomes available. 00Days 00Hours Secure Your Place Now Kindly use the Registration ID Number sent to your | M32: =LEN(L32) -> 0 | N32: H1: 2026 AMC Conference Launch Event H2: AMC Full-Conference Package Labadi Beach Hotel H2: AMC Full-Conference Package La Palm Royal Beach Hotel H2: AMC Day Attendance Package H2: AMC Conference Only Package | S32: =IF(LEN(R32)>0, _xludf.IMAGE(R32), "") | U32: =IFERROR(HYPERLINK("#Main!A"&MATCH(D31,Main!A:A,0),"Open"),HYPERLINK("#Main!A1","Open")) -> Open
A33: To Do | B33: Unassigned | C33: amc-marketing-conference-2024-amc-forum-mombasa-–-afri | D33: https://africanmarketingconfederation.org/amc-marketing-conference-2024/ | E33: https://africanmarketingconfederation.org/wp-admin/post.php?post=21958&action=elementor | F33: [Auto]: amc marketing conference 2024 | G33: AMC Marketing Conference Sarova WhiteSands Beach Resort, Mombasa As a must-attend for all marketing professionals, this year’s marketing forum will address the crucial theme: Brand Resilience Amidst Economic Uncertainty In such tumultuous times acros... | H33: AMC Forum Mombasa – African Marketing Confederation | J33: =LEN(I33) -> 0 | K33: AMC Marketing Conference Sarova WhiteSands Beach Resort, Mombasa As a must-attend for all marketing professionals, this year’s marketing forum will address the crucial theme: Brand Resilience Amidst Economic Uncertainty In such tumultuous times across Africa and the rest of the world, brand resilience is both more important and challenging than ever.This year’s theme will offer | M33: =LEN(L33) -> 0 | N33: H1: AMC Marketing Conference H2: Brand Resilience Amidst Economic Uncertainty H3: Hear From Africa’s Marketing Leaders H2: Sponsors H2: Ali Hussein Kassim H3: Kenya | S33: =IF(LEN(R33)>0, _xludf.IMAGE(R33), "") | U33: =IFERROR(HYPERLINK("#Main!A"&MATCH(D32,Main!A:A,0),"Open"),HYPERLINK("#Main!A1","Open")) -> Open
A34: To Do | B34: Unassigned | C34: amc-marketing-conference-2024-amc-conference-{n}-ghana | D34: https://africanmarketingconfederation.org/amc-marketing-conference-2024/amc-conference-2025-ghana-sponsors/ | E34: https://africanmarketingconfederation.org/wp-admin/post.php?post=25857&action=elementor | F34: [Auto]: amc conference 2025 ghana sponsors | G34: 2025 AMC conference Thank you for your interest in sponsoring the 2025 AMC Conference. A member of our team will be in touch to discuss available opportunities and next steps. PUBLICATIONS Strategic Marketing for Africa Magazine CONTACT INFORMATION i... | H34: AMC Conference 2025 Ghana Sponsors – African Marketing Confederation | J34: =LEN(I34) -> 0 | K34: 2025 AMC conference Thank you for your interest in sponsoring the 2025 AMC Conference. A member of our team will be in touch to discuss available opportunities and next steps. PUBLICATIONS Strategic Marketing for Africa Magazine CONTACT INFORMATION info@africanmarketingconfederation.org © 2021 by African Marketing Confederation | Privacy Policy | M34: =LEN(L34) -> 0 | N34: H1: 2025 AMC conference | S34: =IF(LEN(R34)>0, _xludf.IMAGE(R34), "") | U34: =IFERROR(HYPERLINK("#Main!A"&MATCH(D33,Main!A:A,0),"Open"),HYPERLINK("#Main!A1","Open")) -> Open
A35: To Do | B35: Unassigned | C35: amc-marketing-conference-2024-amc-launch-event-{n}-–-a | D35: https://africanmarketingconfederation.org/amc-marketing-conference-2024/amc-launch-event-2025/ | E35: https://africanmarketingconfederation.org/wp-admin/post.php?post=25788&action=elementor | F35: [Auto]: amc launch event 2025 | G35: AMC Conference launch 2025 Labadi Beach Hotel or Online 15 May 2025 I 10 AM – 12 PM GMT AMC Conference launch 2025 Name (Required) First Last Email (Required) Enter Email Confirm Email Phone Number (Required) Which country are you from? (Required) A... | H35: AMC Launch Event 2025 – African Marketing Confederation | J35: =LEN(I35) -> 0 | K35: AMC Conference launch 2025 Labadi Beach Hotel or Online15 May 2025 I 10 AM – 12 PM GMT AMC Conference launch 2025 Name(Required) First Last Email(Required) Enter Email Confirm Email Phone Number(Required)Which country are you from?(Required)AfghanistanAlbaniaAlgeriaAmerican SamoaAndorraAngolaAnguillaAntarcticaAntigua and BarbudaArgentinaArmeniaArubaAustraliaAustriaAzerbaijanBahamasBahrainBangladeshBarbadosBelarusBelgiumBelizeBeninBermudaBhutanBoliviaBonaire, Sint Eustatius and SabaBosnia and HerzegovinaBotswanaBouvet IslandBrazilBritish Indian Ocean TerritoryBrunei DarussalamBulgariaBurkina FasoBurundiCabo VerdeCambodiaCameroonCanadaCayman IslandsCentral African RepublicChadChileChinaChristmas | M35: =LEN(L35) -> 0 | N35: H1: AMC Conference launch 2025 H2: AMC Conference launch 2025 | S35: =IF(LEN(R35)>0, _xludf.IMAGE(R35), "") | U35: =IFERROR(HYPERLINK("#Main!A"&MATCH(D34,Main!A:A,0),"Open"),HYPERLINK("#Main!A1","Open")) -> Open
A36: To Do | B36: Unassigned | C36: amc-marketing-conference-2024-amc-preregister-{n}-–-af | D36: https://africanmarketingconfederation.org/amc-marketing-conference-2024/amc-preregister-2025/ | E36: https://africanmarketingconfederation.org/wp-admin/post.php?post=26290&action=elementor | F36: [Auto]: amc preregister 2025 | G36: Pre-register for AMC Conference 2025 20 – 22 August | Accra, Ghana Complete the form below to be notified as soon as final registration and payment options become available. AMC Conference 2025 Name (Required) First Last Email (Required) Enter Email ... | H36: AMC Preregister 2025 – African Marketing Confederation | J36: =LEN(I36) -> 0 | K36: Pre-register for AMC Conference 2025 20 - 22 August | Accra, Ghana Complete the form below to be notified as soon as final registration and payment options become available. AMC Conference 2025 Name(Required) First Last Email(Required) Enter Email Confirm Email Phone Number(Required)Which country are you from?(Required)AfghanistanAlbaniaAlgeriaAmerican SamoaAndorraAngolaAnguillaAntarcticaAntigua and BarbudaArgentinaArmeniaArubaAustraliaAustriaAzerbaijanBahamasBahrainBangladeshBarbadosBelarusBelgiumBelizeBeninBermudaBhutanBoliviaBonaire, Sint Eustatius and SabaBosnia and | M36: =LEN(L36) -> 0 | N36: H1: Pre-register for AMC Conference 2025 H2: AMC Conference 2025 | S36: =IF(LEN(R36)>0, _xludf.IMAGE(R36), "") | U36: =IFERROR(HYPERLINK("#Main!A"&MATCH(D35,Main!A:A,0),"Open"),HYPERLINK("#Main!A1","Open")) -> Open
A37: To Do | B37: Unassigned | C37: amc-marketing-conference-2024-{n}-amc-conference-award | D37: https://africanmarketingconfederation.org/amc-marketing-conference-2024/amc-programme-2025/ | E37: https://africanmarketingconfederation.org/wp-admin/post.php?post=24882&action=elementor | F37: [Auto]: amc programme 2025 | G37: Conference Menu 2025 AMC Conference Programme Day 1 Day 2 Day 3 DOWNLOAD PROGRAMME DAY 1 DOWNLOAD PROGRAMME DAY 2 DOWNLOAD PROGRAMME DAY 3 PUBLICATIONS Strategic Marketing for Africa Magazine CONTACT INFORMATION info@africanmarketingconfederation.org... | H37: 2025 AMC Conference Awards | J37: =LEN(I37) -> 0 | K37: Celebrate excellence at the 2025 AMC Conference Awards as we honour outstanding achievements, innovation and leadership in Africa’s marketing industry. | M37: =LEN(L37) -> 0 | N37: H1: 2025 AMC Conference | S37: =IF(LEN(R37)>0, _xludf.IMAGE(R37), "") | U37: =IFERROR(HYPERLINK("#Main!A"&MATCH(D36,Main!A:A,0),"Open"),HYPERLINK("#Main!A1","Open")) -> Open
A38: To Do | B38: Unassigned | C38: amc-marketing-conference-2024-amc-speakers-presentatio | D38: https://africanmarketingconfederation.org/amc-marketing-conference-2024/amc-speakers-presentations-2024/ | E38: https://africanmarketingconfederation.org/wp-admin/post.php?post=22595&action=elementor | F38: [Auto]: amc speakers presentations 2024 | G38: AMC speakers presentations 2024 Day 1 Day 2 Day 3 PUBLICATIONS Strategic Marketing for Africa Magazine CONTACT INFORMATION info@africanmarketingconfederation.org 0 Your Cart Your cart is empty Return to Shop Continue Shopping | H38: AMC speakers presentations 2024 – African Marketing Confederation | J38: =LEN(I38) -> 0 | K38: AMC speakers presentations 2024 Day 1 https://youtu.be/daWjshF4Bdc Day 2 https://youtu.be/7Qf2P8YLD7I Day 3 PUBLICATIONS Strategic Marketing for Africa Magazine CONTACT INFORMATION info@africanmarketingconfederation.org © 2021 by African Marketing Confederation | Privacy Policy | M38: =LEN(L38) -> 0 | N38: H1: AMC speakers presentations 2024 | S38: =IF(LEN(R38)>0, _xludf.IMAGE(R38), "") | U38: =IFERROR(HYPERLINK("#Main!A"&MATCH(D37,Main!A:A,0),"Open"),HYPERLINK("#Main!A1","Open")) -> Open
A39: To Do | B39: Unassigned | C39: amc-marketing-conference-2024-awards-{n}-–-african-mar | D39: https://africanmarketingconfederation.org/amc-marketing-conference-2024/awards-2025/ | E39: https://africanmarketingconfederation.org/wp-admin/post.php?post=29496&action=elementor | F39: [Auto]: awards 2025 | G39: Conference Menu AMC Conference Awards 2025 AMC Awards 2025 Categories View detailed explanations of each award below. Click on the awards below to view detailed explanations of each criterion. Tourism & Destination Marketing Campaign of the Year Best... | H39: Awards 2025 – African Marketing Confederation | J39: =LEN(I39) -> 0 | K39: Conference Menu AMC Conference Awards 2025 AMC Awards 2025 Categories View detailed explanations of each award below.Click on the awards below to view detailed explanations of each criterion. Tourism & Destination Marketing Campaign of the Year Best Social Media Campaignof the Year Most Effective Campaignof the Year Best Use of Local Insights Best Cause-Related Campaign | M39: =LEN(L39) -> 0 | N39: H1: AMC Conference Awards 2025 H2: AMC Awards 2025 Categories H2: Tourism & Destination Marketing Campaign H2: of the Year H2: Best Social Media Campaign of the Year H2: Best Social Media Campaign | S39: =IF(LEN(R39)>0, _xludf.IMAGE(R39), "") | U39: =IFERROR(HYPERLINK("#Main!A"&MATCH(D38,Main!A:A,0),"Open"),HYPERLINK("#Main!A1","Open")) -> Open
A40: To Do | B40: Unassigned | C40: amc-marketing-conference-2024-programme-{n}-–-african- | D40: https://africanmarketingconfederation.org/amc-marketing-conference-2024/programme-2024/ | E40: https://africanmarketingconfederation.org/wp-admin/post.php?post=16104&action=elementor | F40: [Auto]: programme 2024 | G40: Programme AMC 3rd Annual Conference 2024 Join us for an unparalleled marketing experience at the upcoming conference hosted by the African Marketing Confederation (AMC) in Kenya. From August 28th to 30th, 2024, immerse yourself in insightful discussi... | H40: Programme 2024 – African Marketing Confederation | J40: =LEN(I40) -> 0 | K40: Programme AMC 3rd Annual Conference 2024 Join us for an unparalleled marketing experience at the upcoming conference hosted by the African Marketing Confederation (AMC) in Kenya. From August 28th to 30th, 2024, immerse yourself in insightful discussions, cutting-edge strategies, and industry trends that are shaping the future of marketing across the continent. Engage with top-notch | M40: =LEN(L40) -> 0 | N40: H1: Programme H2: AMC 3rd Annual Conference 2024 H2: Programme TBA H3: Tuesday | 28 August 2024 H2: Conference Day 2 H3: Wednesday | 28th August 2024 | S40: =IF(LEN(R40)>0, _xludf.IMAGE(R40), "") | U40: =IFERROR(HYPERLINK("#Main!A"&MATCH(D39,Main!A:A,0),"Open"),HYPERLINK("#Main!A1","Open")) -> Open
A41: To Do | B41: Unassigned | C41: amc-marketing-conference-2024-untitled | D41: https://africanmarketingconfederation.org/amc-marketing-conference-2024/speakers-2024/ | F41: [Auto]: speakers 2024 | H41: MISSING TITLE | J41: =LEN(I41) -> 0 | K41: MISSING DESCRIPTION | M41: =LEN(L41) -> 0 | S41: =IF(LEN(R41)>0, _xludf.IMAGE(R41), "") | U41: =IFERROR(HYPERLINK("#Main!A"&MATCH(D40,Main!A:A,0),"Open"),HYPERLINK("#Main!A1","Open")) -> Open
A42: To Do | B42: Unassigned | C42: amc-marketing-conference-2024-testimony-thank-you-page | D42: https://africanmarketingconfederation.org/amc-marketing-conference-2024/testimony-thank-you-page/ | E42: https://africanmarketingconfederation.org/wp-admin/post.php?post=23021&action=elementor | F42: [Auto]: testimony thank you page | G42: Thank you For your Feedback Thank you For the Feedback PUBLICATIONS Strategic Marketing for Africa Magazine CONTACT INFORMATION info@africanmarketingconfederation.org 0 Your Cart Your cart is empty Return to Shop Continue Shopping | H42: Testimony Thank you Page – African Marketing Confederation | J42: =LEN(I42) -> 0 | K42: Thank you For your Feedback Thank you For the Feedback PUBLICATIONS Strategic Marketing for Africa Magazine CONTACT INFORMATION info@africanmarketingconfederation.org © 2021 by African Marketing Confederation | Privacy Policy | M42: =LEN(L42) -> 0 | N42: H1: Thank you | S42: =IF(LEN(R42)>0, _xludf.IMAGE(R42), "") | U42: =IFERROR(HYPERLINK("#Main!A"&MATCH(D41,Main!A:A,0),"Open"),HYPERLINK("#Main!A1","Open")) -> Open
A43: To Do | B43: Unassigned | C43: amc-masterclass-bookings-amc-masterclass-|-bookin | D43: https://africanmarketingconfederation.org/amc-masterclass-bookings/ | E43: https://africanmarketingconfederation.org/wp-admin/post.php?post=6816&action=elementor | F43: [Auto]: amc masterclass bookings | G43: Skip to content 0 Your Cart Your cart is empty Return to Shop Continue Shopping | H43: AMC Masterclass | Bookings – African Marketing Confederation | J43: =LEN(I43) -> 0 | K43: MISSING DESCRIPTION | M43: =LEN(L43) -> 0 | S43: =IF(LEN(R43)>0, _xludf.IMAGE(R43), "") | U43: =IFERROR(HYPERLINK("#Main!A"&MATCH(D42,Main!A:A,0),"Open"),HYPERLINK("#Main!A1","Open")) -> Open
A44: To Do | B44: Unassigned | C44: amc-masterclass-thank-you-amc-masterclass-|-thank- | D44: https://africanmarketingconfederation.org/amc-masterclass-thank-you/ | E44: https://africanmarketingconfederation.org/wp-admin/post.php?post=6822&action=elementor | F44: [Auto]: amc masterclass thank you | G44: AMC VIRTUAL MASTERCLASS 31 May 2022 Thank you for your Booking We received your booking and will contact you shortly! 0 Your Cart Your cart is empty Return to Shop Continue Shopping | H44: AMC Masterclass | Thank you – African Marketing Confederation | J44: =LEN(I44) -> 0 | K44: AMC VIRTUAL MASTERCLASS 31 May 2022 Thank you for your Booking We received your booking and will contact you shortly! | M44: =LEN(L44) -> 0 | N44: H2: AMC VIRTUAL H2: Thank you for your Booking | S44: =IF(LEN(R44)>0, _xludf.IMAGE(R44), "") | U44: =IFERROR(HYPERLINK("#Main!A"&MATCH(D43,Main!A:A,0),"Open"),HYPERLINK("#Main!A1","Open")) -> Open
A45: To Do | B45: Unassigned | C45: amc-masterclass-amc-masterclass-–-africa | D45: https://africanmarketingconfederation.org/amc-masterclass/ | E45: https://africanmarketingconfederation.org/wp-admin/post.php?post=6553&action=elementor | F45: [Auto]: amc masterclass | G45: Skip to content AMC VIRTUAL MASTERCLASS 31 May 2022 Thank you for attending Building The Perfect Blueprint for Digital and Strategic Marketing Align your digital efforts with your strategic goals and develop strong online marketing capabilities to he... | H45: AMC Masterclass – African Marketing Confederation | J45: =LEN(I45) -> 0 | K45: AMC VIRTUAL MASTERCLASS 31 May 2022 Thank you for attending Building The Perfect Blueprint for Digital and Strategic Marketing Align your digital efforts with your strategic goals and develop strong online marketing capabilities to help your company stay ahead of the curve.Masterclass Outcomes: You will receive all the tools you need to overcome and avoid | M45: =LEN(L45) -> 0 | N45: H2: AMC VIRTUAL H2: Building The Perfect Blueprint for Digital and Strategic Marketing H2: Facilitator H3: Specialisms H2: AMC VIRTUAL MASTERCLASS H2: Tuesday, 31 May 2022 | S45: =IF(LEN(R45)>0, _xludf.IMAGE(R45), "") | U45: =IFERROR(HYPERLINK("#Main!A"&MATCH(D44,Main!A:A,0),"Open"),HYPERLINK("#Main!A1","Open")) -> Open
A46: To Do | B46: Unassigned | C46: amc-relaunch-programme-amc-relaunch-–-programme | D46: https://africanmarketingconfederation.org/amc-relaunch-programme/ | E46: https://africanmarketingconfederation.org/wp-admin/post.php?post=4492&action=elementor | F46: [Auto]: amc relaunch programme | G46: Skip to content amc relaunch Thank you for joining our first online gathering! WATCH RECORDINGS NOW WATCH NOW AMC RELAUNCH RECORDINGS The AMC relaunch event shared the vision and goals of the AMC, as well as hosting talks and discussions with top mar... | H46: AMC RELAUNCH – PROGRAMME – African Marketing Confederation | J46: =LEN(I46) -> 0 | K46: amc relaunch Thank you for joining our first online gathering! WATCH RECORDINGS NOW WATCH NOW AMC RELAUNCH RECORDINGS The AMC relaunch event shared the vision and goals of the AMC, as well as hosting talks and discussions with top marketing thought leaders and professionals. The African Marketing Confederation (AMC) – the ground breaking Pan-African body | M46: =LEN(L46) -> 0 | N46: H2: amc relaunch H2: Thank you for joining our first online gathering! H2: WATCH RECORDINGS NOW H2: AMC RELAUNCH RECORDINGS H2: LIGHTNING TALKS | Solidarity and Support for the African Marketing Confederation H2: Thank you for attending the 2021 AMC relaunch | S46: =IF(LEN(R46)>0, _xludf.IMAGE(R46), "") | U46: =IFERROR(HYPERLINK("#Main!A"&MATCH(D45,Main!A:A,0),"Open"),HYPERLINK("#Main!A1","Open")) -> Open
A47: To Do | B47: Unassigned | C47: amc-sign-up-now-form-2025-amc-sign-up-now-form-{n} | D47: https://africanmarketingconfederation.org/amc-sign-up-now-form-2025/ | E47: https://africanmarketingconfederation.org/wp-admin/post.php?post=23001&action=elementor | F47: [Auto]: amc sign up now form 2025 | G47: Get Ready for Ghana in 2025! Name (Required) First Last Email (Required) Enter Email Confirm Email Phone Number (Required) Which country are you from? (Required) Afghanistan Albania Algeria American Samoa Andorra Angola Anguilla Antarctica Antigua an... | H47: AMC Sign up now Form 2025 – African Marketing Confederation | J47: =LEN(I47) -> 0 | K47: Get Ready for Ghana in 2025! Name(Required) First Last Email(Required) Enter Email Confirm Email Phone Number(Required)CountryAfghanistanAlbaniaAlgeriaAmerican SamoaAndorraAngolaAnguillaAntarcticaAntigua and BarbudaArgentinaArmeniaArubaAustraliaAustriaAzerbaijanBahamasBahrainBangladeshBarbadosBelarusBelgiumBelizeBeninBermudaBhutanBoliviaBonaire, Sint Eustatius and SabaBosnia and HerzegovinaBotswanaBouvet IslandBrazilBritish Indian Ocean TerritoryBrunei DarussalamBulgariaBurkina FasoBurundiCabo VerdeCambodiaCameroonCanadaCayman IslandsCentral African RepublicChadChileChinaChristmas IslandCocos IslandsColombiaComorosCongoCongo, Democratic Republic of theCook IslandsCosta RicaCroatiaCubaCuraçaoCyprusCzechiaCôte d'IvoireDenmarkDjiboutiDominicaDominican RepublicEcuadorEgyptEl SalvadorEquatorial GuineaEritreaEstoniaEswatiniEthiopiaFalkland IslandsFaroe IslandsFijiFinlandFranceFrench GuianaFrench PolynesiaFrench Southern TerritoriesGabonGambiaGeorgiaGermanyGhanaGibraltarGreeceGreenlandGrenadaGuadeloupeGuamGuatemalaGuernseyGuineaGuinea-BissauGuyanaHaitiHeard Island and | M47: =LEN(L47) -> 0 | N47: H1: Get Ready for Ghana in 2025! H2: Sponsors | S47: =IF(LEN(R47)>0, _xludf.IMAGE(R47), "") | U47: =IFERROR(HYPERLINK("#Main!A"&MATCH(D46,Main!A:A,0),"Open"),HYPERLINK("#Main!A1","Open")) -> Open
A48: To Do | B48: Unassigned | C48: amc-sponsors-2025-sponsorship-opportunitie | D48: https://africanmarketingconfederation.org/amc-sponsors-2025/ | E48: https://africanmarketingconfederation.org/wp-admin/post.php?post=21952&action=elementor | F48: [Auto]: amc sponsors 2025 | G48: Africa’s Premier Marketing Event The 2025 African Marketing Confederation conference is poised to be the largest and most transformative gathering of marketing leaders, brand strategists, creative innovators, and key business leaders on the continent... | H48: Sponsorship Opportunities – 2025 AMC Conference | J48: =LEN(I48) -> 0 | K48: Explore sponsorship opportunities for AMC Conference 2025 and position your brand alongside Africa’s leading marketers, innovators, and industry decision-makers. | M48: =LEN(L48) -> 0 | N48: H1: Africa’s Premier Marketing Event H2: Why Sponsor the 2025 AMC Conference? H2: Amplified Brand Exposure: H2: High-Impact Networking: H2: Prime Event Access: H2: Enhanced Brand Authority: | S48: =IF(LEN(R48)>0, _xludf.IMAGE(R48), "") | U48: =IFERROR(HYPERLINK("#Main!A"&MATCH(D47,Main!A:A,0),"Open"),HYPERLINK("#Main!A1","Open")) -> Open
A49: To Do | B49: Unassigned | C49: amc-testimony-page-2024-amc-testimony-page-{n}-– | D49: https://africanmarketingconfederation.org/amc-testimony-page-2024/ | E49: https://africanmarketingconfederation.org/wp-admin/post.php?post=22679&action=elementor | F49: [Auto]: amc testimony page 2024 | G49: How was your experience at the 2024 AMC Conference? Name (Required) First Last Email (Required) Enter Email Confirm Email Phone (Required) What Is Your Phone Number's Country Code? (Required) Afghanistan Albania Algeria American Samoa Andorra Angola ... | H49: AMC Testimony page 2024 – African Marketing Confederation | J49: =LEN(I49) -> 0 | K49: How was your experience at the2024 AMC Conference? Name(Required) First Last Email(Required) Company Name How was your experience at the AMC Conference 2024? We'd love to hear about your key takeaways and memorable moments!What improvements would you recommend for the next AMC Conference to make it even more impactful? Sponsors Previous Next PUBLICATIONS Strategic Marketing | M49: =LEN(L49) -> 0 | N49: H1: How was your experience at the 2024 AMC Conference? H2: Sponsors | S49: =IF(LEN(R49)>0, _xludf.IMAGE(R49), "") | U49: =IFERROR(HYPERLINK("#Main!A"&MATCH(D48,Main!A:A,0),"Open"),HYPERLINK("#Main!A1","Open")) -> Open
A50: To Do | B50: Unassigned | C50: awards-2026-1-{n}-amc-awards-{n}-–-afr | D50: https://africanmarketingconfederation.org/awards-2026-1/ | E50: https://africanmarketingconfederation.org/wp-admin/post.php?post=32554&action=elementor | F50: [Auto]: awards 2026 1 | G50: 2026 AMC AWARDS 2026 AMC Awards Submit Your Nomination View Awards Brochure Where Africa’s Boldest Ideas Take the Stage Entries Close: 26 July Held annually at the African Marketing Confederation Conference , the AMC Awards stand as the definitive c... | H50: 2026 AMC Awards-1 – African Marketing Confederation | J50: =LEN(I50) -> 0 | K50: The African Marketing Confederation presents the 2026 AMC Awards. Submit your nominations to recognise innovative strategies, impact, and marketing results. | M50: =LEN(L50) -> 0 | N50: H1: 2026 AMC AWARDS H3: Entries Close: 26 July H2: A Global Stage for Africa’s Marketing Excellence H2: 2026 AMC Awards Categories H2: 2026 AMC Awards Categories H2: 2026 AMC Awards Categories | S50: =IF(LEN(R50)>0, _xludf.IMAGE(R50), "") | U50: =IFERROR(HYPERLINK("#Main!A"&MATCH(D49,Main!A:A,0),"Open"),HYPERLINK("#Main!A1","Open")) -> Open
A51: To Do | B51: Unassigned | C51: awards-2026-test-awards-{n}-test-–-africa | D51: https://africanmarketingconfederation.org/awards-2026-test/ | E51: https://africanmarketingconfederation.org/wp-admin/post.php?post=34552&action=elementor | F51: [Auto]: awards 2026 test | G51: Skip to content 2026 AMC AWARDS 2026 AMC Awards Submit Your Nomination View Awards Brochure Where Africa’s Boldest Ideas Take the Stage Entries Close: 26 July Held annually at the African Marketing Confederation Conference , the AMC Awards stand as t... | H51: Awards 2026 test – African Marketing Confederation | J51: =LEN(I51) -> 0 | K51: 2026 AMC AWARDS 2026AMC Awards Submit Your Nomination View Awards Brochure Where Africa’s Boldest Ideas Take the Stage https://africanmarketingconfederation.org/wp-content/uploads/2026/03/16x9-AMC-Awards-Nominations-Video-2026.mp4 Entries Close: 26 July Held annually at the African Marketing Confederation Conference, the AMC Awards stand as the definitive celebration of marketing excellence across the continent. This distinguished platform brings together Africa’s leading minds and boldest work, recognising campaigns and | M51: =LEN(L51) -> 0 | N51: H1: 2026 AMC AWARDS H3: Entries Close: 26 July H2: A Global Stage for Africa’s Marketing Excellence H2: 2026 AMC Awards Categories H2: 2026 AMC Awards Categories H2: 2026 AMC Awards Categories | S51: =IF(LEN(R51)>0, _xludf.IMAGE(R51), "") | U51: =IFERROR(HYPERLINK("#Main!A"&MATCH(D50,Main!A:A,0),"Open"),HYPERLINK("#Main!A1","Open")) -> Open
A52: To Do | B52: Unassigned | C52: awards-2026-{n}-amc-awards-–-african | D52: https://africanmarketingconfederation.org/awards-2026/ | E52: https://africanmarketingconfederation.org/wp-admin/post.php?post=34622&action=elementor | F52: [Auto]: awards 2026 | G52: Skip to content 2026 AMC AWARDS 2026 AMC Awards Submit Your Nomination View Awards Brochure Where Africa’s Boldest Ideas Take the Stage Entries Close: 26 June Held annually at the African Marketing Confederation Conference , the AMC Awards stand as ... | H52: 2026 AMC Awards – African Marketing Confederation | J52: =LEN(I52) -> 0 | K52: The African Marketing Confederation presents the 2026 AMC Awards. Submit your nominations to recognise innovative strategies, impact, and marketing results. | M52: =LEN(L52) -> 0 | N52: H1: 2026 AMC AWARDS H3: Entries Close: 26 June H2: A Global Stage for Africa’s Marketing Excellence H2: 2026 AMC Awards Categories H2: 2026 AMC Awards Categories H2: 2026 AMC Awards Categories | S52: =IF(LEN(R52)>0, _xludf.IMAGE(R52), "") | U52: =IFERROR(HYPERLINK("#Main!A"&MATCH(D51,Main!A:A,0),"Open"),HYPERLINK("#Main!A1","Open")) -> Open
A53: To Do | B53: Unassigned | C53: certified-professional-marketer-africa-certified-professional-m | D53: https://africanmarketingconfederation.org/certified-professional-marketer-africa/ | E53: https://africanmarketingconfederation.org/wp-admin/post.php?post=28742&action=elementor | F53: [Auto]: certified professional marketer africa | G53: Skip to content Certified Professional Marketer (Africa), CPM(A) The only designation of its kind on the continent - built for Africa, by Africa. Strategic Flexible Uniquely Africa Take your place among Africa’s marketing leaders with the Certified P... | H53: Certified Professional Marketer (Africa) – African Marketing Confederation | J53: =LEN(I53) -> 0 | K53: Certified Professional Marketer (Africa), CPM(A) The only designation of its kind on the continent - built for Africa, by Africa. Strategic Flexible Uniquely Africa Take your place among Africa’s marketing leaders with the Certified Professional Marketer (Africa) – CPM(A) A prestigious, Pan-African designation offered exclusively through the African Marketing Confederation (AMC).This is not just a | M53: =LEN(L53) -> 0 | N53: H2: Certified Professional Marketer (Africa), CPM(A) H2: The only designation of its kind on the continent - built for Africa, by Africa. H2: Take your place among Africa’s marketing leaders with the Certified Professional Marketer (Africa) – CPM(A) H2: Why Choose the CPM(A) H2: A Leading Marketing Programme in Africa H2: Why Choose the CPM(A) | S53: =IF(LEN(R53)>0, _xludf.IMAGE(R53), "") | U53: =IFERROR(HYPERLINK("#Main!A"&MATCH(D52,Main!A:A,0),"Open"),HYPERLINK("#Main!A1","Open")) -> Open
A54: To Do | B54: Unassigned | C54: chartered-marketer-africa-final-submission-fee-chartered-marketer-(afri | D54: https://africanmarketingconfederation.org/chartered-marketer-africa-final-submission-fee/ | E54: https://africanmarketingconfederation.org/wp-admin/post.php?post=20001&action=elementor | F54: [Auto]: chartered marketer africa final submission fee | G54: Skip to content Final Submission Fee Receive a 15% discount on your final submission fee by making payment before 31 August 2024. No products found! 0 Your Cart Your cart is empty Return to Shop Continue Shopping | H54: Chartered Marketer (Africa) Final submission fee – African Marketing Confederation | J54: =LEN(I54) -> 0 | K54: Final Submission Fee Receive a 15% discount on your final submission feeby making payment before 31 August 2024. Add to cart $2190,00 Original price was: $2190,00.$1862,00Current price is: $1862,00. Add to cart | M54: =LEN(L54) -> 0 | N54: H1: Final Submission Fee | S54: =IF(LEN(R54)>0, _xludf.IMAGE(R54), "") | U54: =IFERROR(HYPERLINK("#Main!A"&MATCH(D53,Main!A:A,0),"Open"),HYPERLINK("#Main!A1","Open")) -> Open
A55: To Do | B55: Unassigned | C55: chartered-marketer-africa-programme-fee-chartered-marketer-(afri | D55: https://africanmarketingconfederation.org/chartered-marketer-africa-programme-fee/ | E55: https://africanmarketingconfederation.org/wp-admin/post.php?post=19980&action=elementor | F55: [Auto]: chartered marketer africa programme fee | G55: Skip to content Programme Fee Receive a 15% discount on your programme fee by making payment before 31 August 2024. No products found! 0 Your Cart Your cart is empty Return to Shop Continue Shopping | H55: Chartered Marketer (Africa) Programme fee – African Marketing Confederation | J55: =LEN(I55) -> 0 | K55: Programme Fee Receive a 15% discount on your programme fee by making payment before 31 August 2024. Add to cart $810,00 Original price was: $810,00.$689,00Current price is: $689,00. Add to cart | M55: =LEN(L55) -> 0 | N55: H1: Programme Fee | S55: =IF(LEN(R55)>0, _xludf.IMAGE(R55), "") | U55: =IFERROR(HYPERLINK("#Main!A"&MATCH(D54,Main!A:A,0),"Open"),HYPERLINK("#Main!A1","Open")) -> Open
... A57: To Do | B57: Unassigned | C57: chartered-marketer-africa-the-chartered-marketer-a | D57: https://africanmarketingconfederation.org/chartered-marketer-africa/ | E57: https://africanmarketingconfederation.org/wp-admin/post.php?post=9075&action=elementor | F57: [Auto]: chartered marketer africa | G57: Skip to content The Chartered Marketer Africa Be recognised as one of Africa’s marketing titans Download Brochure Register Africa's Highest Professional Marketing Designation The CM(A) is awarded by the African Marketing Confederation (AMC) to the to... | H57: The Chartered Marketer Africa – African Marketing Confederation | J57: =LEN(I57) -> 0 | K57: Become one of Africa’s marketing titans. The Chartered Marketer Africa is awarded to the top marketing professionals on the continent. | M57: =LEN(L57) -> 0 | N57: H1: The Chartered Marketer Africa H2: Africa's Highest Professional Marketing Designation H2: Benefits of Attaining the CM(A) Designation: H2: Professionalism H2: Branding H2: Networking | S57: =IF(LEN(R57)>0, _xludf.IMAGE(R57), "") | U57: =IFERROR(HYPERLINK("#Main!A"&MATCH(D56,Main!A:A,0),"Open"),HYPERLINK("#Main!A1","Open")) -> Open
A58: To Do | B58: Unassigned | C58: checkout-cart-–-african-marketing | D58: https://africanmarketingconfederation.org/checkout/ | E58: https://africanmarketingconfederation.org/wp-admin/post.php?post=17908&action=elementor | F58: [Auto]: checkout | G58: Skip to content Your cart is currently empty. Return to shop 0 Your Cart Your cart is empty Return to Shop Continue Shopping | H58: Cart – African Marketing Confederation | J58: =LEN(I58) -> 0 | K58: Your cart is currently empty. Return to shop | M58: =LEN(L58) -> 0 | S58: =IF(LEN(R58)>0, _xludf.IMAGE(R58), "") | U58: =IFERROR(HYPERLINK("#Main!A"&MATCH(D57,Main!A:A,0),"Open"),HYPERLINK("#Main!A1","Open")) -> Open
A59: To Do | B59: Unassigned | C59: conference-faq-2025-{n}-amc-conference-–-faq | D59: https://africanmarketingconfederation.org/conference-faq-2025/ | E59: https://africanmarketingconfederation.org/wp-admin/post.php?post=24640&action=elementor | F59: [Auto]: conference faq 2025 | G59: FAQ 2025 African Marketing Confederation Conference General Information What is the African Marketing Confederation Conference? The African Marketing Confederation Conference is a premier gathering of marketing professionals, industry leaders, and in... | H59: 2025 AMC Conference – FAQs Page | J59: =LEN(I59) -> 0 | K59: Find answers to all your questions about the AMC Conference 2025 - venue, registration, speakers, agenda, sponsorship, and more information in our FAQs section. | M59: =LEN(L59) -> 0 | N59: H1: FAQ | S59: =IF(LEN(R59)>0, _xludf.IMAGE(R59), "") | U59: =IFERROR(HYPERLINK("#Main!A"&MATCH(D58,Main!A:A,0),"Open"),HYPERLINK("#Main!A1","Open")) -> Open
A60: To Do | B60: Unassigned | C60: conference-registrations-2024-conference-registrations | D60: https://africanmarketingconfederation.org/conference-registrations-2024/ | E60: https://africanmarketingconfederation.org/wp-admin/post.php?post=16472&action=elementor | F60: [Auto]: conference registrations 2024 | G60: Skip to content AMC Conference Brand Resilience Amidst Economic Uncertainty 25 - 27 September 2024 In collaboration with: View Presentations Interested in our 2024 Conference? Complete the form below to receive further information. AMC conference 20... | H60: Conference Registrations 2024 – African Marketing Confederation | J60: =LEN(I60) -> 0 | K60: realalexisbreeze selfieAMC Conference Brand Resilience Amidst Economic Uncertainty 25 - 27 September 2024 In collaboration with: View Presentations Interested in our 2024 Conference? Complete the form below to receive further information. #gform_wrapper_3[data-form-index="2"].gform-theme,[data-parent-form="3_2"]{--gf-color-primary: #204ce5;--gf-color-primary-rgb: 32, 76, 229;--gf-color-primary-contrast: #fff;--gf-color-primary-contrast-rgb: 255, 255, 255;--gf-color-primary-darker: #001AB3;--gf-color-primary-lighter: #527EFF;--gf-color-secondary: #fff;--gf-color-secondary-rgb: 255, 255, 255;--gf-color-secondary-contrast: #112337;--gf-color-secondary-contrast-rgb: 17, 35, 55;--gf-color-secondary-darker: #F5F5F5;--gf-color-secondary-lighter: #FFFFFF;--gf-color-out-ctrl-light: rgba(17, 35, 55, | M60: =LEN(L60) -> 0 | N60: H1: AMC Conference H2: Interested in our 2024 Conference? H2: AMC conference 2024 | S60: =IF(LEN(R60)>0, _xludf.IMAGE(R60), "") | U60: =IFERROR(HYPERLINK("#Main!A"&MATCH(D59,Main!A:A,0),"Open"),HYPERLINK("#Main!A1","Open")) -> Open
A61: To Do | B61: Unassigned | C61: contact-us-contact-us-–-african-mar | D61: https://africanmarketingconfederation.org/contact-us/ | E61: https://africanmarketingconfederation.org/wp-admin/post.php?post=92&action=elementor | F61: [Auto]: contact us | G61: Skip to content Enquire now Contact Us Want to know more about membership, courses, or anything else? Leave your details and we will respond promptly. Enquiries Name (Required) First Last Email (Required) Contact Number (Required) Select your Country... | H61: Contact Us – African Marketing Confederation | J61: =LEN(I61) -> 0 | K61: Contact us to know more about membership, courses, and our upcoming conference. | M61: =LEN(L61) -> 0 | N61: H1: Enquire now H2: Enquiries | S61: =IF(LEN(R61)>0, _xludf.IMAGE(R61), "") | U61: =IFERROR(HYPERLINK("#Main!A"&MATCH(D60,Main!A:A,0),"Open"),HYPERLINK("#Main!A1","Open")) -> Open
A62: To Do | B62: Unassigned | C62: download-brochure-download-brochure-–-afri | D62: https://africanmarketingconfederation.org/download-brochure/ | E62: https://africanmarketingconfederation.org/wp-admin/post.php?post=18478&action=elementor | F62: [Auto]: download brochure | G62: Skip to content Download Brochure Download Brochure Download Form Download Code of Conduct Submit relevant Documents 0 Your Cart Your cart is empty Return to Shop Continue Shopping | H62: Download Brochure – African Marketing Confederation | J62: =LEN(I62) -> 0 | K62: Download Brochure Download Brochure Download Form Download Code of Conduct Submit relevant Documents | M62: =LEN(L62) -> 0 | N62: H2: Download Brochure H2: Submit relevant Documents | S62: =IF(LEN(R62)>0, _xludf.IMAGE(R62), "") | U62: =IFERROR(HYPERLINK("#Main!A"&MATCH(D61,Main!A:A,0),"Open"),HYPERLINK("#Main!A1","Open")) -> Open
A63: To Do | B63: Unassigned | C63: download-prospectus-2024-download-prospectus-{n}- | D63: https://africanmarketingconfederation.org/download-prospectus-2024/ | E63: https://africanmarketingconfederation.org/wp-admin/post.php?post=19172&action=elementor | F63: [Auto]: download prospectus 2024 | G63: Skip to content Download Prospectus Thank you for your interest. Download Prospectus 0 Your Cart Your cart is empty Return to Shop Continue Shopping | H63: Download Prospectus 2024 – African Marketing Confederation | J63: =LEN(I63) -> 0 | K63: Download Prospectus Thank you for your interest. Download Prospectus | M63: =LEN(L63) -> 0 | N63: H2: Download Prospectus | S63: =IF(LEN(R63)>0, _xludf.IMAGE(R63), "") | U63: =IFERROR(HYPERLINK("#Main!A"&MATCH(D62,Main!A:A,0),"Open"),HYPERLINK("#Main!A1","Open")) -> Open
A64: To Do | B64: Unassigned | C64: education-education-–-african-mark | D64: https://africanmarketingconfederation.org/education/ | E64: https://africanmarketingconfederation.org/wp-admin/post.php?post=88&action=elementor | F64: [Auto]: education | G64: Skip to content short Courses For over a decade, we’ve been empowering Pan-African marketers to achieve greatness. Now, we’re taking things to the next level with our AMC Short Courses – designed by marketers for marketers. Our comprehensive courses ... | H64: Education – African Marketing Confederation | J64: =LEN(I64) -> 0 | K64: short Courses For over a decade, we've been empowering Pan-African marketers to achieve greatness. Now, we're taking things to the next level with our AMC Short Courses - designed by marketers for marketers. Our comprehensive courses cover the full scope of practical marketing and sales topics, helping you stay ahead of the curve and increase | M64: =LEN(L64) -> 0 | N64: H2: short Courses H3: The Chartered Marketer Africa H3: Enquire now H2: Enquiries | S64: =IF(LEN(R64)>0, _xludf.IMAGE(R64), "") | U64: =IFERROR(HYPERLINK("#Main!A"&MATCH(D63,Main!A:A,0),"Open"),HYPERLINK("#Main!A1","Open")) -> Open
A65: To Do | B65: Unassigned | C65: elementor-16548-thank-you-for-registerin | D65: https://africanmarketingconfederation.org/elementor-16548/ | E65: https://africanmarketingconfederation.org/wp-admin/post.php?post=16548&action=elementor | F65: [Auto]: elementor 16548 | G65: Skip to content SUBMISSION RECEIVED Thank you for submitting your information! We appreciate your interest in the 2024 AMC Conference and will keep you updated with all the details about the upcoming event . Speakers Programme Awards 0 Your Cart Your... | H65: Thank you for registering – African Marketing Confederation | J65: =LEN(I65) -> 0 | K65: SUBMISSION RECEIVED Thank you for submitting your information! We appreciate your interest in the 2024 AMC Conference and will keep you updated with all the details about the upcoming event. Speakers Programme Awards | M65: =LEN(L65) -> 0 | N65: H2: SUBMISSION RECEIVED | S65: =IF(LEN(R65)>0, _xludf.IMAGE(R65), "") | U65: =IFERROR(HYPERLINK("#Main!A"&MATCH(D64,Main!A:A,0),"Open"),HYPERLINK("#Main!A1","Open")) -> Open
A66: To Do | B66: Unassigned | C66: elementor-20341-elementor-#{n}-–-african | D66: https://africanmarketingconfederation.org/elementor-20341/ | E66: https://africanmarketingconfederation.org/wp-admin/post.php?post=20341&action=elementor | F66: [Auto]: elementor 20341 | G66: Skip to content 0 Your Cart Your cart is empty Return to Shop Continue Shopping | H66: Elementor #20341 – African Marketing Confederation | J66: =LEN(I66) -> 0 | K66: MISSING DESCRIPTION | M66: =LEN(L66) -> 0 | S66: =IF(LEN(R66)>0, _xludf.IMAGE(R66), "") | U66: =IFERROR(HYPERLINK("#Main!A"&MATCH(D65,Main!A:A,0),"Open"),HYPERLINK("#Main!A1","Open")) -> Open
A67: To Do | B67: Unassigned | C67: elementor-31820-elementor-#{n}-–-african | D67: https://africanmarketingconfederation.org/elementor-31820/ | E67: https://africanmarketingconfederation.org/wp-admin/post.php?post=31820&action=elementor | F67: [Auto]: elementor 31820 | G67: Skip to content 2026 TICON Africa Conference In partnership with the ICT Association of Zambia 23-25 September 2026 24-26 September 2026 Livingstone, Zambia Livingstone, Zambia Powering Africa’s Digital Rise Sign Up for Updates Join the TICON Africa ... | H67: Elementor #31820 – African Marketing Confederation | J67: =LEN(I67) -> 0 | K67: 2026 TICON Africa Conference In partnership with the ICT Association of Zambia 23-25 September 2026 24-26 September 2026 Livingstone, Zambia Livingstone, Zambia Powering Africa’s Digital Rise Sign Up for Updates Join the TICON Africa Conference 2026 TICON Africa Conference 2026 in Zambia The TICON Africa Conference returns in 2026 for its fourth iteration, this time | M67: =LEN(L67) -> 0 | N67: H1: TICON Africa Conference 2026 H2: 2026 TICON Africa Conference H2: 23-25 September 2026 H2: 24-26 September 2026 Livingstone, Zambia H2: Livingstone, Zambia H2: Join the | S67: =IF(LEN(R67)>0, _xludf.IMAGE(R67), "") | U67: =IFERROR(HYPERLINK("#Main!A"&MATCH(D66,Main!A:A,0),"Open"),HYPERLINK("#Main!A1","Open")) -> Open
A68: To Do | B68: Unassigned | C68: general-enquiry-form-thank-you-general-enquiry-form-–-t | D68: https://africanmarketingconfederation.org/general-enquiry-form-thank-you/ | E68: https://africanmarketingconfederation.org/wp-admin/post.php?post=5597&action=elementor | F68: [Auto]: general enquiry form thank you | G68: Skip to content Thank You! Thank you for getting in touch! We appreciate you contacting us. One of our members will be getting back to you soon. 0 Your Cart Your cart is empty Return to Shop Continue Shopping | H68: General Enquiry Form – Thank You – African Marketing Confederation | J68: =LEN(I68) -> 0 | K68: Thank You! Thank you for getting in touch! We appreciate you contacting us. One of our members will be getting back to you soon. | M68: =LEN(L68) -> 0 | N68: H3: Thank You! | S68: =IF(LEN(R68)>0, _xludf.IMAGE(R68), "") | U68: =IFERROR(HYPERLINK("#Main!A"&MATCH(D67,Main!A:A,0),"Open"),HYPERLINK("#Main!A1","Open")) -> Open
A69: To Do | B69: Unassigned | C69: launch-event-2026-amc-conference-launch-event-{n}-amc-con | D69: https://africanmarketingconfederation.org/launch-event-2026-amc-conference/ | E69: https://africanmarketingconfederation.org/wp-admin/post.php?post=33050&action=elementor | F69: [Auto]: launch event 2026 amc conference | G69: The Official Launch of the 2026 AMC Conference 10:00 CAT (GMT +2) | 16 March 2026 | Live Online from Lusaka 10:00 CAT (GMT +2) 16 March 2026 Live Online from Lusaka The livestream is available for viewing. Click on the link below to watch. Watch the ... | H69: Launch Event 2026 AMC Conference – African Marketing Confederation | J69: =LEN(I69) -> 0 | K69: The Official Launch of the 2026 AMC Conference 10:00 CAT (GMT +2) | 16 March 2026 | Live Online from Lusaka 10:00 CAT (GMT +2) 16 March 2026 Live Online from Lusaka The livestream is available for viewing. Click on the link below to watch. Watch the Launch Event Three Conferences. One United Movement. The | M69: =LEN(L69) -> 0 | N69: H1: 2026 AMC Conference H2: The Official Launch of the H2: 2026 AMC Conference H2: 10:00 CAT (GMT +2) | 16 March 2026 | Live Online from Lusaka H2: 10:00 CAT (GMT +2) 16 March 2026 Live Online from Lusaka H2: Three Conferences. | S69: =IF(LEN(R69)>0, _xludf.IMAGE(R69), "") | U69: =IFERROR(HYPERLINK("#Main!A"&MATCH(D68,Main!A:A,0),"Open"),HYPERLINK("#Main!A1","Open")) -> Open
A70: To Do | B70: Unassigned | C70: members-members-–-african-market | D70: https://africanmarketingconfederation.org/members/ | E70: https://africanmarketingconfederation.org/wp-admin/post.php?post=86&action=elementor | F70: [Auto]: members | G70: Skip to content OUR MEMBERS Marketers Association of Zimbabwe The Marketers Association of Zimbabwe was launched in 2007 with a vision to be a leading body of marketing professionals promoting professionalism of the highest standards and establishing... | H70: Members – African Marketing Confederation | J70: =LEN(I70) -> 0 | K70: OUR MEMBERS Marketers Association of Zimbabwe The Marketers Association of Zimbabwe was launched in 2007 with a vision to be a leading body of marketing professionals promoting professionalism of the highest standards and establishing channels of career development for the benefit of organisations and the economy at large. Visit Website IMM Institute, South Africa The | M70: =LEN(L70) -> 0 | N70: H1: OUR MEMBERS H2: Marketers Association of Zimbabwe H2: IMM Institute, South Africa H2: The Zambia Institute of Marketing H2: Marketing Society of Kenya H2: Chartered Institute of Marketing, Ghana | S70: =IF(LEN(R70)>0, _xludf.IMAGE(R70), "") | U70: =IFERROR(HYPERLINK("#Main!A"&MATCH(D69,Main!A:A,0),"Open"),HYPERLINK("#Main!A1","Open")) -> Open
A71: To Do | B71: Unassigned | C71: news-articles-news-articles-–-african- | D71: https://africanmarketingconfederation.org/news-articles/ | E71: https://africanmarketingconfederation.org/wp-admin/post.php?post=2196&action=elementor | F71: [Auto]: news articles | G71: European marketers gather to choose their top achievers for 2026 April 30, 2026 Marketing associations from across Europe nominated national champions, with 10 finalists competing for the Marketer of the Year title. Read More » | H71: News Articles – African Marketing Confederation | J71: =LEN(I71) -> 0 | K71: AMC Conference Featured Marketing News LATEST news Subscribe Now Free monthly marketing news, articles, events and publication release notifications. Subscribe | M71: =LEN(L71) -> 0 | N71: H1: LATEST news H3: European marketers gather to choose their top achievers for 2026 H3: Namibia bets on Walvis Bay port as increasingly viable alternative H3: ChatGPT ads in Africa: A game changer or a trust gamble? H3: Report identifies five forces influencing global purchasing decisions H3: Out now! New issue brings latest news and insights for Africa’s marketers | S71: =IF(LEN(R71)>0, _xludf.IMAGE(R71), "") | U71: =IFERROR(HYPERLINK("#Main!A"&MATCH(D70,Main!A:A,0),"Open"),HYPERLINK("#Main!A1","Open")) -> Open
A72: To Do | B72: Unassigned | C72: privacy-policy-privacy-policy-–-african | D72: https://africanmarketingconfederation.org/privacy-policy/ | E72: https://africanmarketingconfederation.org/wp-admin/post.php?post=3&action=elementor | F72: [Auto]: privacy policy | G72: Skip to content Privacy Policy Who we are The ground-breaking African Marketing Confederation (AMC) was founded in 2011 when marketing associations from four African countries met in Livingston, Zambia, to discuss the status and development of the ma... | H72: Privacy Policy – African Marketing Confederation | J72: =LEN(I72) -> 0 | K72: Privacy Policy Who we are The ground-breaking African Marketing Confederation (AMC) was founded in 2011 when marketing associations from four African countries met in Livingston, Zambia, to discuss the status and development of the marketing profession across Africa. Collaboration between the various national bodies and associations was deemed to be of the utmost importance in | M72: =LEN(L72) -> 0 | N72: H1: Privacy Policy H3: The ground-breaking African Marketing Confederation (AMC) was founded in 2011 when marketing associations from four African countries met in Livingston, Zambia, to discuss the status and development of the marketing profession across Africa. H3: When clients visit our website and request that our team send them a quote or wish to register to attend the conference, the following information will be requested may be requested from them through a contact form but is not limited to name, surname, company name, job title, how they heard about us, how many delegates will attend and if they wish to subscribe to our newsletter. H3: Articles on this site may include embedded content (e.g videos, images, articles, etc.). Embedded content from other websites behave in the exact same way as if the visitor has visited the other website. H3: This information captured from the website is collected and stored on the company CRM platform called Salesforce. Professional information may be, with the consent of Smart Procurement World, be shared with other organisations or customers for the purpose of facilitating business relationships in our customer’s best interests. H3: If you have an account on this site, or have left comments, you can request to receive an exported file of the personal data we hold about you, including any data you have provided to us. You can also request that we erase any personal data we hold about you. This does not include any data we are obliged to keep for administrative, legal, or security purposes. | S72: =IF(LEN(R72)>0, _xludf.IMAGE(R72), "") | U72: =IFERROR(HYPERLINK("#Main!A"&MATCH(D71,Main!A:A,0),"Open"),HYPERLINK("#Main!A1","Open")) -> Open
A73: To Do | B73: Unassigned | C73: publication-download-list-publication-download-lis | D73: https://africanmarketingconfederation.org/publication-download-list/ | E73: https://africanmarketingconfederation.org/wp-admin/post.php?post=9047&action=elementor | F73: [Auto]: publication download list | G73: Skip to content Download All Publications now Click on the publication edition below to download! Edition 1 | 2026 Edition 1 | 2026 Edition 4 | 2025 Edition 4 | 2025 Edition 3 | 2025 Edition 3 | 2025 Edition 2 | 2025 Edition 1 | 2025 Edition 4 | 2024... | H73: Publication Download List – African Marketing Confederation | J73: =LEN(I73) -> 0 | K73: Download All Publications now Click on the publication edition below to download! Edition 1 | 2026 Edition 1 | 2026 Edition 4 | 2025 Edition 4 | 2025 Edition 3 | 2025 Edition 3 | 2025 Edition 2 | 2025 Edition 1 | 2025 Edition 4 | 2024 Edition 3 | 2024 Edition 2 | | M73: =LEN(L73) -> 0 | N73: H3: Download All Publications now | S73: =IF(LEN(R73)>0, _xludf.IMAGE(R73), "") | U73: =IFERROR(HYPERLINK("#Main!A"&MATCH(D72,Main!A:A,0),"Open"),HYPERLINK("#Main!A1","Open")) -> Open
A74: To Do | B74: Unassigned | C74: publications-2-publications-–-african-m | D74: https://africanmarketingconfederation.org/publications-2/ | E74: https://africanmarketingconfederation.org/wp-admin/post.php?post=3686&action=elementor | F74: [Auto]: publications 2 | G74: Skip to content Strategic Marketing for Africa Explore the Latest in African Marketing Now Download Publication Glad to have contributed to one of the most competitive marketing platforms on the African continent…Please keep up the good work! Dr Taba... | H74: Publications – African Marketing Confederation | J74: =LEN(I74) -> 0 | K74: Download Strategic Marketing for Africa, the continent's premier marketing publication. Discover the latest industry insights and trends from top experts today. | M74: =LEN(L74) -> 0 | N74: H1: Strategic Marketing for Africa | S74: =IF(LEN(R74)>0, _xludf.IMAGE(R74), "") | U74: =IFERROR(HYPERLINK("#Main!A"&MATCH(D73,Main!A:A,0),"Open"),HYPERLINK("#Main!A1","Open")) -> Open
A75: To Do | B75: Unassigned | C75: speakers-2025-our-speakers-–-{n}-amc-c | D75: https://africanmarketingconfederation.org/speakers-2025/ | E75: https://africanmarketingconfederation.org/wp-admin/post.php?post=21962&action=elementor | F75: [Auto]: speakers 2025 | G75: Speakers AMC Conference 2025 Learn from Africa's Leading Marketing Minds The AMC Conference is renowned for attracting high-level marketing professionals, bold thinkers, and industry pioneers from across the continent. 2025 AMC Conference attendees c... | H75: Our Speakers – 2025 AMC Conference | J75: =LEN(I75) -> 0 | K75: Discover what to expect from the AMC Conference 2025 speaker lineup, including insightful sessions led by Africa’s brightest marketing minds and thought leaders | M75: =LEN(L75) -> 0 | N75: H1: Speakers | S75: =IF(LEN(R75)>0, _xludf.IMAGE(R75), "") | U75: =IFERROR(HYPERLINK("#Main!A"&MATCH(D74,Main!A:A,0),"Open"),HYPERLINK("#Main!A1","Open")) -> Open
A76: To Do | B76: Unassigned | C76: speakers-speakers-–-african-marke | D76: https://africanmarketingconfederation.org/speakers/ | E76: https://africanmarketingconfederation.org/wp-admin/post.php?post=3252&action=elementor | F76: [Auto]: speakers | G76: Skip to content amc relaunch JOIN OUR FIRST ONLINE GATHERING! WATCH RECORDINGS NOW WATCH NOW amc relaunch THANK YOU FOR JOINING OUR FIRST ONLINE GATHERING! WATCH RECORDINGS NOW WATCH NOW speakers Ms Harriet Khataba Thought Leader and Chief Executive ... | H76: Speakers – African Marketing Confederation | J76: =LEN(I76) -> 0 | K76: amc relaunch JOIN OUR FIRST ONLINE GATHERING! WATCH RECORDINGS NOW WATCH NOW amc relaunch THANK YOU FOR JOINING OUR FIRST ONLINE GATHERING! WATCH RECORDINGS NOW WATCH NOW speakers Ms Harriet KhatabaThought Leader and Chief Executive Officer, Her Story Matters Mr Gillian RusikeExecutive, African Marketing Confederation Mrs Helen McInteePresident, African Marketing Confederation Dr. Alistair MokoenaCountry Director, | M76: =LEN(L76) -> 0 | N76: H2: amc relaunch H2: JOIN OUR FIRST ONLINE GATHERING! H2: WATCH RECORDINGS NOW H2: WATCH RECORDINGS NOW H2: amc relaunch H2: THANK YOU FOR JOINING OUR FIRST ONLINE GATHERING! | S76: =IF(LEN(R76)>0, _xludf.IMAGE(R76), "") | U76: =IFERROR(HYPERLINK("#Main!A"&MATCH(D75,Main!A:A,0),"Open"),HYPERLINK("#Main!A1","Open")) -> Open
A77: To Do | B77: Unassigned | C77: sub-committees-sub-committees-–-african | D77: https://africanmarketingconfederation.org/sub-committees/ | E77: https://africanmarketingconfederation.org/wp-admin/post.php?post=3634&action=elementor | F77: [Auto]: sub committees | G77: Skip to content Sub Committees AMC’s Education and Membership Committee The AMC’s Education and Membership Committee is committed to assisting in the skills enhancement of marketing professionals on the continent, ensuring qualification mobility arou... | H77: Sub Committees – African Marketing Confederation | J77: =LEN(I77) -> 0 | K77: Sub Committees AMC’s Education and Membership Committee The AMC’s Education and Membership Committee is committed to assisting in the skills enhancement of marketing professionals on the continent, ensuring qualification mobility around the globe. To these ends the Committee is currently focusing on the following projects: The Chartered Marketer (Africa) programme (set to be launched early | M77: =LEN(L77) -> 0 | N77: H1: Sub Committees H2: AMC’s Education and Membership Committee H2: The AMC’s Events Committee H2: The AMC Publishing Committee H2: The AMC Research Committee | S77: =IF(LEN(R77)>0, _xludf.IMAGE(R77), "") | U77: =IFERROR(HYPERLINK("#Main!A"&MATCH(D76,Main!A:A,0),"Open"),HYPERLINK("#Main!A1","Open")) -> Open
A78: To Do | B78: Unassigned | C78: subscribe-subscribe-–-african-mark | D78: https://africanmarketingconfederation.org/subscribe/ | E78: https://africanmarketingconfederation.org/wp-admin/post.php?post=7781&action=elementor | F78: [Auto]: subscribe | G78: Skip to content Subscribe Now Subscribe Name First Last Email Select your Country Afghanistan Albania Algeria American Samoa Andorra Angola Anguilla Antarctica Antigua and Barbuda Argentina Armenia Aruba Australia Austria Azerbaijan Bahamas Bahrain B... | H78: Subscribe – African Marketing Confederation | J78: =LEN(I78) -> 0 | K78: Subscribe Now Subscribe Name First Last Email Select your CountryAfghanistanAlbaniaAlgeriaAmerican SamoaAndorraAngolaAnguillaAntarcticaAntigua and BarbudaArgentinaArmeniaArubaAustraliaAustriaAzerbaijanBahamasBahrainBangladeshBarbadosBelarusBelgiumBelizeBeninBermudaBhutanBoliviaBonaire, Sint Eustatius and SabaBosnia and HerzegovinaBotswanaBouvet IslandBrazilBritish Indian Ocean TerritoryBrunei DarussalamBulgariaBurkina FasoBurundiCabo VerdeCambodiaCameroonCanadaCayman IslandsCentral African RepublicChadChileChinaChristmas IslandCocos IslandsColombiaComorosCongoCongo, Democratic Republic of theCook IslandsCosta RicaCroatiaCubaCuraçaoCyprusCzechiaCôte d'IvoireDenmarkDjiboutiDominicaDominican RepublicEcuadorEgyptEl SalvadorEquatorial GuineaEritreaEstoniaEswatiniEthiopiaFalkland IslandsFaroe IslandsFijiFinlandFranceFrench GuianaFrench PolynesiaFrench Southern TerritoriesGabonGambiaGeorgiaGermanyGhanaGibraltarGreeceGreenlandGrenadaGuadeloupeGuamGuatemalaGuernseyGuineaGuinea-BissauGuyanaHaitiHeard Island and McDonald IslandsHoly SeeHondurasHong KongHungaryIcelandIndiaIndonesiaIranIraqIrelandIsle of ManIsraelItalyJamaicaJapanJerseyJordanKazakhstanKenyaKiribatiKorea, | M78: =LEN(L78) -> 0 | N78: H3: Subscribe Now H2: Subscribe | S78: =IF(LEN(R78)>0, _xludf.IMAGE(R78), "") | U78: =IFERROR(HYPERLINK("#Main!A"&MATCH(D77,Main!A:A,0),"Open"),HYPERLINK("#Main!A1","Open")) -> Open
A79: To Do | B79: Unassigned | C79: test-homeslider-test-homeslider-–-africa | D79: https://africanmarketingconfederation.org/test-homeslider/ | E79: https://africanmarketingconfederation.org/wp-admin/post.php?post=5490&action=elementor | F79: [Auto]: test homeslider | G79: Skip to content Conference Book Now Connecting Marketing Professionals A must read for all marketers The 2nd edition of the Strategic Marketing for Africa magazine is now available. Read Now conference Book Now Connecting Marketing Professionals A mu... | H79: Test HomeSlider – African Marketing Confederation | J79: =LEN(I79) -> 0 | K79: ConferenceBook NowConnecting Marketing Professionals A must read for all marketersThe 2nd edition of the Strategic Marketing for Africa magazine is now available. Read Now Previous Next conferenceBook NowConnecting Marketing Professionals A must read for all marketersThe 2nd edition of the Strategic Marketing for Africa magazine is now available. Read Now Previous Next | M79: =LEN(L79) -> 0 | S79: =IF(LEN(R79)>0, _xludf.IMAGE(R79), "") | U79: =IFERROR(HYPERLINK("#Main!A"&MATCH(D78,Main!A:A,0),"Open"),HYPERLINK("#Main!A1","Open")) -> Open
A80: To Do | B80: Unassigned | C80: test-payment-gate-test-payment-gate-–-afri | D80: https://africanmarketingconfederation.org/test-payment-gate/ | E80: https://africanmarketingconfederation.org/wp-admin/post.php?post=27352&action=elementor | F80: [Auto]: test payment gate | G80: Skip to content Add to cart Rated 0 out of 5 SPONSORSHIP PACKAGES AMC Day Attendance Package Full-day conference attendance All lunches & 3 dinners Accommodation & breakfasts excluded $ 550 Add to cart View Product Add to cart Rated 0 out of 5 SPONSO... | H80: Test payment gate – African Marketing Confederation | J80: =LEN(I80) -> 0 | K80: Add to cart Rated 0 out of 5 CELEBRITY ENDORSEMENTS TEST 2$ $2 Add to cart View Product Add to cart Rated 0 out of 5 Application Fee Non-refundable application fee: $150 Add to cart View Product Add to cart Rated 0 out of 5 SPONSORSHIP PACKAGES AMC Day Attendance Package Full-day conference attendance All | M80: =LEN(L80) -> 0 | N80: H2: AMC Day Attendance Package H3: $ 550 H2: AMC Conference Only Package H3: $ 330 H2: AMC Full-Conference Package La Palm Royal Beach Hotel H3: $ 1330 | S80: =IF(LEN(R80)>0, _xludf.IMAGE(R80), "") | U80: =IFERROR(HYPERLINK("#Main!A"&MATCH(D79,Main!A:A,0),"Open"),HYPERLINK("#Main!A1","Open")) -> Open
A81: To Do | B81: Unassigned | C81: thank-you-for-registering-2024-registrations-kenya-thank-you-for-registerin | D81: https://africanmarketingconfederation.org/thank-you-for-registering-2024-registrations-kenya/ | E81: https://africanmarketingconfederation.org/wp-admin/post.php?post=21591&action=elementor | F81: [Auto]: thank you for registering 2024 registrations kenya | G81: Skip to content Thank You FOr Registering Kenyan delegates, don’t miss your chance to grab discounted tickets! Buy Tickets 0 Your Cart Your cart is empty Return to Shop Continue Shopping | H81: Thank you for registering 2024 Registrations KENYA – African Marketing Confederation | J81: =LEN(I81) -> 0 | K81: Thank You FOr Registering Kenyan delegates, don’t miss your chance to grab discounted tickets! Buy Tickets | M81: =LEN(L81) -> 0 | N81: H2: Thank You FOr Registering | S81: =IF(LEN(R81)>0, _xludf.IMAGE(R81), "") | U81: =IFERROR(HYPERLINK("#Main!A"&MATCH(D80,Main!A:A,0),"Open"),HYPERLINK("#Main!A1","Open")) -> Open
A82: To Do | B82: Unassigned | C82: thank-you-for-registering-2024-registrations-thank-you-for-registerin | D82: https://africanmarketingconfederation.org/thank-you-for-registering-2024-registrations/ | E82: https://africanmarketingconfederation.org/wp-admin/post.php?post=17195&action=elementor | F82: [Auto]: thank you for registering 2024 registrations | G82: Skip to content Thank You FOr Registering Please finalise your booking by selecting one of our tailored packages and completing payment via our secure online payment gateway. View Packages Download Prospectus 0 Your Cart Your cart is empty Return to... | H82: Thank you for registering 2024 Registrations – African Marketing Confederation | J82: =LEN(I82) -> 0 | K82: Thank You FOr Registering Please finalise your booking by selecting one of our tailored packages and completing payment via our secure online payment gateway. View Packages Download Prospectus | M82: =LEN(L82) -> 0 | N82: H2: Thank You FOr Registering | S82: =IF(LEN(R82)>0, _xludf.IMAGE(R82), "") | U82: =IFERROR(HYPERLINK("#Main!A"&MATCH(D81,Main!A:A,0),"Open"),HYPERLINK("#Main!A1","Open")) -> Open
A83: To Do | B83: Unassigned | C83: thank-you-for-subscribing-thank-you-for-subscribin | D83: https://africanmarketingconfederation.org/thank-you-for-subscribing/ | E83: https://africanmarketingconfederation.org/wp-admin/post.php?post=7916&action=elementor | F83: [Auto]: thank you for subscribing | G83: Skip to content Thank You for Subscribing to the The African Marketing Confederation newsletter. The AMC newsletter will keep you up to date with the latest marketing news, articles,event and publication release notifications. Here is what you can ex... | H83: Thank You for Subscribing – African Marketing Confederation | J83: =LEN(I83) -> 0 | K83: Thank You for Subscribing to the The African Marketing Confederation newsletter. The AMC newsletter will keep you up to date with the latest marketing news, articles,event and publication release notifications. Here is what you can expect from us: Top industry articles The AMC newsletter will keep you up to date with the latest marketing news, | M83: =LEN(L83) -> 0 | N83: H2: Thank You for Subscribing H2: to the The African Marketing Confederation newsletter. H2: Top industry articles H2: Strategic Marketing for Africa H2: Events H2: Education | S83: =IF(LEN(R83)>0, _xludf.IMAGE(R83), "") | U83: =IFERROR(HYPERLINK("#Main!A"&MATCH(D82,Main!A:A,0),"Open"),HYPERLINK("#Main!A1","Open")) -> Open
A84: To Do | B84: Unassigned | C84: thank-you-for-the-nomination-2024-thank-you-for-the-nomina | D84: https://africanmarketingconfederation.org/thank-you-for-the-nomination-2024/ | E84: https://africanmarketingconfederation.org/wp-admin/post.php?post=17000&action=elementor | F84: [Auto]: thank you for the nomination 2024 | G84: Skip to content Thank You for your nomination! Speakers Programme Awards 0 Your Cart Your cart is empty Return to Shop Continue Shopping | H84: Thank you for the nomination 2024 – African Marketing Confederation | J84: =LEN(I84) -> 0 | K84: Thank You for your nomination! Speakers Programme Awards | M84: =LEN(L84) -> 0 | N84: H2: Thank You for your nomination! | S84: =IF(LEN(R84)>0, _xludf.IMAGE(R84), "") | U84: =IFERROR(HYPERLINK("#Main!A"&MATCH(D83,Main!A:A,0),"Open"),HYPERLINK("#Main!A1","Open")) -> Open
A85: To Do | B85: Unassigned | C85: thank-you-for-the-submission-2024-thank-you-for-the-submis | D85: https://africanmarketingconfederation.org/thank-you-for-the-submission-2024/ | E85: https://africanmarketingconfederation.org/wp-admin/post.php?post=17196&action=elementor | F85: [Auto]: thank you for the submission 2024 | G85: Skip to content Thank You for your Submission! Speakers Programme Awards 0 Your Cart Your cart is empty Return to Shop Continue Shopping | H85: Thank you for the Submission 2024 – African Marketing Confederation | J85: =LEN(I85) -> 0 | K85: Thank You for your Submission! Speakers Programme Awards | M85: =LEN(L85) -> 0 | N85: H2: Thank You for your Submission! | S85: =IF(LEN(R85)>0, _xludf.IMAGE(R85), "") | U85: =IFERROR(HYPERLINK("#Main!A"&MATCH(D84,Main!A:A,0),"Open"),HYPERLINK("#Main!A1","Open")) -> Open
A86: To Do | B86: Unassigned | C86: upcoming-events-upcoming-events-–-africa | D86: https://africanmarketingconfederation.org/upcoming-events/ | E86: https://africanmarketingconfederation.org/wp-admin/post.php?post=4909&action=elementor | F86: [Auto]: upcoming events | G86: Skip to content UPCOMING EVENTS upcoming events AMC Conference 2022 19- 22 October The AMC Conference is the must attend Pan African event for marketing professionals. It will focus on solutions for marketers across the continent and will provide pra... | H86: Upcoming Events – African Marketing Confederation | J86: =LEN(I86) -> 0 | K86: UPCOMING EVENTS upcoming events AMC Conference 2022 19- 22 October The AMC Conference is the must attend Pan African event for marketing professionals. It will focus on solutions for marketers across the continent and will provide practical tools for marketers to use in appealing to its diverse audience. More Info Subscribe Now Free monthly marketing | M86: =LEN(L86) -> 0 | N86: H2: UPCOMING EVENTS H2: upcoming events H3: AMC Conference 2022 H3: Subscribe Now | S86: =IF(LEN(R86)>0, _xludf.IMAGE(R86), "") | U86: =IFERROR(HYPERLINK("#Main!A"&MATCH(D85,Main!A:A,0),"Open"),HYPERLINK("#Main!A1","Open")) -> Open
A87: To Do | B87: Unassigned | C87: virtual-programme-virtual-programme-–-afri | D87: https://africanmarketingconfederation.org/virtual-programme/ | E87: https://africanmarketingconfederation.org/wp-admin/post.php?post=5290&action=elementor | F87: [Auto]: virtual programme | G87: Skip to content AMC Conference 2022 virtual conference programme 23 - 24 March 2022 Navigating Africa’s Unique Marketing Mix Conference day 1 Conference day 2 BOOK NOW FOR THE AMC CONFERENCE 2022 BOOK NOW Conference day 1 Wednesday, 23 March 2022 08h... | H87: VIRTUAL PROGRAMME – African Marketing Confederation | J87: =LEN(I87) -> 0 | K87: AMC Conference 2022 virtual conference programme 23 - 24 March 2022 Navigating Africa's Unique Marketing Mix Conference day 1 Conference day 2 BOOK NOW FOR THE AMC CONFERENCE 2022 BOOK NOW Conference day 1 Wednesday, 23 March 2022 08h30 WELCOME | MC Opening Remarks 08h40 AMC STAKEHOLDER WELCOME 08h55 AFRICA MARKETING BAROMETER | Marketing Trends | M87: =LEN(L87) -> 0 | N87: H2: AMC Conference 2022 H2: virtual conference programme H2: BOOK NOW FOR THE AMC CONFERENCE 2022 H2: Conference day 1 H2: Conference day 2 H2: BOOK NOW FOR THE AMC CONFERENCE 2022 | S87: =IF(LEN(R87)>0, _xludf.IMAGE(R87), "") | U87: =IFERROR(HYPERLINK("#Main!A"&MATCH(D86,Main!A:A,0),"Open"),HYPERLINK("#Main!A1","Open")) -> Open

Sheet FixPlan
A1: Issue Type | B1: Severity | C1: Priority Score | D1: Affected Count | E1: Affected URLs | F1: Detail Reference Tab | G1: Resolution Type | H1: URL | I1: Recommended Fix | J1: Likely Root Cause | K1: Owner | L1: Agency Owner | M1: Effort | N1: Est. Hours | O1: Est. Sprint Points | P1: Aging/Priority | Q1: Status | R1: Verified By | S1: Date Resolved | T1: Revenue Risk | U1: Action Needed | V1: Jump to Details | W1: Sprint | X1: Category | Y1: View Details | Z1: Open in Main | AA1: Hub Status (Content Hub) | AB1: BACK TO DASHBOARD
A2: Noindex Directive | B2: Critical | C2: 105 | D2: 0 | F2: Indexability | G2: Manual Content | I2: Remove unintended noindex directives on index-worthy URLs. | J2: Meta robots or X-Robots-Tag contains noindex. | K2: Dev | L2: Dev | M2: M | N2: 10 | O2: 5 | P2: Immediate (Current Sprint) | Q2: To Do | T2: High Risk | U2: Yes | V2: =HYPERLINK("#Main!A1","Open Main") -> Open Main | X2: SEO | Y2: =IFERROR(HYPERLINK("#Main!A"&MATCH(H2,Main!A:A,0),"View URL Details"),HYPERLINK("#Main!A1","View URL Details")) -> View URL Details | Z2: =IFERROR(HYPERLINK("#Main!A"&MATCH(H2,Main!A:A,0),"Open"),HYPERLINK("#Main!A1","Open")) -> Open | AA2: =IFERROR(INDEX('Content Optimization Hub'!A:A,MATCH(H2,'Content Optimization Hub'!C:C,0)),"Not in Hub") -> Not in Hub
A3: Canonical Points Elsewhere | B3: Critical | C3: 105 | D3: 0 | F3: Indexability | G3: Global Template | I3: Align canonical to preferred final URL and ensure internal links use canonical target. | J3: Canonical targets a different URL variant. | K3: Dev | L3: Dev | M3: M | N3: 10 | O3: 5 | P3: Immediate (Current Sprint) | Q3: To Do | T3: High Risk | U3: Yes | V3: =HYPERLINK("#Main!A1","Open Main") -> Open Main | X3: SEO | Y3: =IFERROR(HYPERLINK("#Main!A"&MATCH(H3,Main!A:A,0),"View URL Details"),HYPERLINK("#Main!A1","View URL Details")) -> View URL Details | Z3: =IFERROR(HYPERLINK("#Main!A"&MATCH(H3,Main!A:A,0),"Open"),HYPERLINK("#Main!A1","Open")) -> Open | AA3: =IFERROR(INDEX('Content Optimization Hub'!A:A,MATCH(H3,'Content Optimization Hub'!C:C,0)),"Not in Hub") -> Not in Hub
A4: Robots.txt Disallow Root | B4: Critical | C4: 105 | D4: 0 | F4: Technical | G4: Global Template | I4: Apply fix based on issue type and re-run audit. | J4: Template/technical implementation quality issue. | K4: Server/Host | L4: Server/Host | M4: M | N4: 10 | O4: 5 | P4: Immediate (Current Sprint) | Q4: To Do | T4: High Risk | U4: Yes | V4: =HYPERLINK("#Main!A1","Open Main") -> Open Main | X4: SEO | Y4: =IFERROR(HYPERLINK("#Main!A"&MATCH(H4,Main!A:A,0),"View URL Details"),HYPERLINK("#Main!A1","View URL Details")) -> View URL Details | Z4: =IFERROR(HYPERLINK("#Main!A"&MATCH(H4,Main!A:A,0),"Open"),HYPERLINK("#Main!A1","Open")) -> Open | AA4: =IFERROR(INDEX('Content Optimization Hub'!A:A,MATCH(H4,'Content Optimization Hub'!C:C,0)),"Not in Hub") -> Not in Hub
A5: CWV LCP Above 4.0s | B5: Critical | C5: 105 | D5: 0 | F5: Technical | G5: Global Template | I5: Apply fix based on issue type and re-run audit. | J5: Template/technical implementation quality issue. | K5: Dev | L5: Dev | M5: M | N5: 10 | O5: 5 | P5: Immediate (Current Sprint) | Q5: To Do | T5: High Risk | U5: Yes | V5: =HYPERLINK("#Main!A1","Open Main") -> Open Main | X5: SEO | Y5: =IFERROR(HYPERLINK("#Main!A"&MATCH(H5,Main!A:A,0),"View URL Details"),HYPERLINK("#Main!A1","View URL Details")) -> View URL Details | Z5: =IFERROR(HYPERLINK("#Main!A"&MATCH(H5,Main!A:A,0),"Open"),HYPERLINK("#Main!A1","Open")) -> Open | AA5: =IFERROR(INDEX('Content Optimization Hub'!A:A,MATCH(H5,'Content Optimization Hub'!C:C,0)),"Not in Hub") -> Not in Hub
A6: Broken Internal Links | B6: Critical | C6: 105 | D6: 0 | F6: Links | G6: Manual Content | I6: Update internal links to valid URLs and remove dead references. | J6: Internal links resolve to missing or error pages. | K6: Dev | L6: Dev | M6: M | N6: 10 | O6: 5 | P6: Immediate (Current Sprint) | Q6: To Do | T6: High Risk | U6: Yes | V6: =HYPERLINK("#Main!A1","Open Main") -> Open Main | X6: SEO | Y6: =IFERROR(HYPERLINK("#Main!A"&MATCH(H6,Main!A:A,0),"View URL Details"),HYPERLINK("#Main!A1","View URL Details")) -> View URL Details | Z6: =IFERROR(HYPERLINK("#Main!A"&MATCH(H6,Main!A:A,0),"Open"),HYPERLINK("#Main!A1","Open")) -> Open | AA6: =IFERROR(INDEX('Content Optimization Hub'!A:A,MATCH(H6,'Content Optimization Hub'!C:C,0)),"Not in Hub") -> Not in Hub
A7: Non-200 Status | B7: Critical | C7: 105 | D7: 2 | E7: https://africanmarketingconfederation.org/amc-conference-sponsors/ https://africanmarketingconfederation.org/amc-marketing-conference-2024/speakers-2024/ | F7: Technical | G7: Manual Content | H7: https://africanmarketingconfederation.org/amc-conference-sponsors/ | I7: Fix status code, restore page, or implement correct redirect to canonical destination. | J7: URL returns 4xx/5xx or equivalent failure. | K7: Server/Host | L7: Server/Host | M7: M | N7: 10 | O7: 5 | P7: Immediate (Current Sprint) | Q7: To Do | T7: High Risk | U7: Yes | V7: =IFERROR(HYPERLINK("#Main!A"&MATCH("https://africanmarketingconfederation.org/amc-conference-sponsors/",Main!A:A,0),"Jump to Main"),HYPERLINK("#Main!A1","Open Main")) -> Open Main | X7: SEO | Y7: =IFERROR(HYPERLINK("#Main!A"&MATCH(H7,Main!A:A,0),"View URL Details"),HYPERLINK("#Main!A1","View URL Details")) -> View URL Details | Z7: =IFERROR(HYPERLINK("#Main!A"&MATCH(H7,Main!A:A,0),"Open"),HYPERLINK("#Main!A1","Open")) -> Open | AA7: =IFERROR(INDEX('Content Optimization Hub'!A:A,MATCH(H7,'Content Optimization Hub'!C:C,0)),"Not in Hub") -> Not in Hub
A8: Missing Title | B8: Critical | C8: 105 | D8: 2 | E8: https://africanmarketingconfederation.org/amc-conference-sponsors/ https://africanmarketingconfederation.org/amc-marketing-conference-2024/speakers-2024/ | F8: Technical | G8: Manual Content | H8: https://africanmarketingconfederation.org/amc-conference-sponsors/ | I8: Add unique descriptive title on affected template/page type. | J8: Template/page missing title tag. | K8: Copy Writer | L8: Copy Writer | M8: M | N8: 10 | O8: 5 | P8: Immediate (Current Sprint) | Q8: To Do | T8: High Risk | U8: Yes | V8: =IFERROR(HYPERLINK("#Main!A"&MATCH("https://africanmarketingconfederation.org/amc-conference-sponsors/",Main!A:A,0),"Jump to Main"),HYPERLINK("#Main!A1","Open Main")) -> Open Main | X8: SEO | Y8: =IFERROR(HYPERLINK("#Main!A"&MATCH(H8,Main!A:A,0),"View URL Details"),HYPERLINK("#Main!A1","View URL Details")) -> View URL Details | Z8: =IFERROR(HYPERLINK("#Main!A"&MATCH(H8,Main!A:A,0),"Open"),HYPERLINK("#Main!A1","Open")) -> Open | AA8: =IFERROR(INDEX('Content Optimization Hub'!A:A,MATCH(H8,'Content Optimization Hub'!C:C,0)),"Not in Hub") -> Not in Hub
A9: Redirect Chains | B9: Warning | C9: 67 | D9: 0 | F9: Technical | G9: Global Template | I9: Apply fix based on issue type and re-run audit. | J9: Template/technical implementation quality issue. | K9: Dev | L9: Dev | M9: S | N9: 4 | O9: 2 | P9: Next Sprint | Q9: To Do | T9: Medium Risk | U9: Yes | V9: =HYPERLINK("#Main!A1","Open Main") -> Open Main | X9: SEO | Y9: =IFERROR(HYPERLINK("#Main!A"&MATCH(H9,Main!A:A,0),"View URL Details"),HYPERLINK("#Main!A1","View URL Details")) -> View URL Details | Z9: =IFERROR(HYPERLINK("#Main!A"&MATCH(H9,Main!A:A,0),"Open"),HYPERLINK("#Main!A1","Open")) -> Open | AA9: =IFERROR(INDEX('Content Optimization Hub'!A:A,MATCH(H9,'Content Optimization Hub'!C:C,0)),"Not in Hub") -> Not in Hub
A10: CWV LCP Needs Improvement (2.5-4.0s) | B10: Warning | C10: 67 | D10: 0 | F10: Technical | G10: Global Template | I10: Apply fix based on issue type and re-run audit. | J10: Template/technical implementation quality issue. | K10: Copy Writer | L10: Copy Writer | M10: S | N10: 4 | O10: 2 | P10: Next Sprint | Q10: To Do | T10: Medium Risk | U10: Yes | V10: =HYPERLINK("#Main!A1","Open Main") -> Open Main | X10: SEO | Y10: =IFERROR(HYPERLINK("#Main!A"&MATCH(H10,Main!A:A,0),"View URL Details"),HYPERLINK("#Main!A1","View URL Details")) -> View URL Details | Z10: =IFERROR(HYPERLINK("#Main!A"&MATCH(H10,Main!A:A,0),"Open"),HYPERLINK("#Main!A1","Open")) -> Open | AA10: =IFERROR(INDEX('Content Optimization Hub'!A:A,MATCH(H10,'Content Optimization Hub'!C:C,0)),"Not in Hub") -> Not in Hub
A11: Missing FAQ/QA Schema | B11: Warning | C11: 67 | D11: 0 | F11: AEO | G11: Global Template | I11: Add valid FAQPage or QAPage JSON-LD where appropriate and ensure on-page parity. | J11: No FAQPage/QAPage schema found for likely Q&A style content. | K11: Dev | L11: Dev | M11: S | N11: 4 | O11: 2 | P11: Next Sprint | Q11: To Do | T11: Medium Risk | U11: Yes | V11: =HYPERLINK("#Main!A1","Open Main") -> Open Main | X11: AEO | Y11: =IFERROR(HYPERLINK("#Main!A"&MATCH(H11,Main!A:A,0),"View URL Details"),HYPERLINK("#Main!A1","View URL Details")) -> View URL Details | Z11: =IFERROR(HYPERLINK("#Main!A"&MATCH(H11,Main!A:A,0),"Open"),HYPERLINK("#Main!A1","Open")) -> Open | AA11: =IFERROR(INDEX('Content Optimization Hub'!A:A,MATCH(H11,'Content Optimization Hub'!C:C,0)),"Not in Hub") -> Not in Hub
A12: Deep URL (>3 clicks) | B12: Warning | C12: 67 | D12: 0 | F12: Technical | G12: Manual Content | I12: Apply fix based on issue type and re-run audit. | J12: Template/technical implementation quality issue. | K12: Copy Writer | L12: Copy Writer | M12: S | N12: 4 | O12: 2 | P12: Next Sprint | Q12: To Do | T12: Medium Risk | U12: Yes | V12: =HYPERLINK("#Main!A1","Open Main") -> Open Main | X12: SEO | Y12: =IFERROR(HYPERLINK("#Main!A"&MATCH(H12,Main!A:A,0),"View URL Details"),HYPERLINK("#Main!A1","View URL Details")) -> View URL Details | Z12: =IFERROR(HYPERLINK("#Main!A"&MATCH(H12,Main!A:A,0),"Open"),HYPERLINK("#Main!A1","Open")) -> Open | AA12: =IFERROR(INDEX('Content Optimization Hub'!A:A,MATCH(H12,'Content Optimization Hub'!C:C,0)),"Not in Hub") -> Not in Hub
A13: Low Image Alt Coverage | B13: Warning | C13: 67 | D13: 0 | F13: Technical | G13: Manual Content | I13: Apply fix based on issue type and re-run audit. | J13: Template/technical implementation quality issue. | K13: Copy Writer | L13: Copy Writer | M13: S | N13: 4 | O13: 2 | P13: Next Sprint | Q13: To Do | T13: Medium Risk | U13: Yes | V13: =HYPERLINK("#Main!A1","Open Main") -> Open Main | X13: SEO | Y13: =IFERROR(HYPERLINK("#Main!A"&MATCH(H13,Main!A:A,0),"View URL Details"),HYPERLINK("#Main!A1","View URL Details")) -> View URL Details | Z13: =IFERROR(HYPERLINK("#Main!A"&MATCH(H13,Main!A:A,0),"Open"),HYPERLINK("#Main!A1","Open")) -> Open | AA13: =IFERROR(INDEX('Content Optimization Hub'!A:A,MATCH(H13,'Content Optimization Hub'!C:C,0)),"Not in Hub") -> Not in Hub
A14: Mixed Content | B14: Warning | C14: 67 | D14: 0 | F14: Technical | G14: Manual Content | I14: Serve all assets over HTTPS and update hardcoded URLs. | J14: HTTPS page references insecure HTTP assets. | K14: Dev | L14: Dev | M14: S | N14: 4 | O14: 2 | P14: Next Sprint | Q14: To Do | T14: Medium Risk | U14: Yes | V14: =HYPERLINK("#Main!A1","Open Main") -> Open Main | X14: SEO | Y14: =IFERROR(HYPERLINK("#Main!A"&MATCH(H14,Main!A:A,0),"View URL Details"),HYPERLINK("#Main!A1","View URL Details")) -> View URL Details | Z14: =IFERROR(HYPERLINK("#Main!A"&MATCH(H14,Main!A:A,0),"Open"),HYPERLINK("#Main!A1","Open")) -> Open | AA14: =IFERROR(INDEX('Content Optimization Hub'!A:A,MATCH(H14,'Content Optimization Hub'!C:C,0)),"Not in Hub") -> Not in Hub
A15: Canonical Missing | B15: Warning | C15: 67 | D15: 0 | F15: Indexability | G15: Global Template | I15: Apply fix based on issue type and re-run audit. | J15: Template/technical implementation quality issue. | K15: Dev | L15: Dev | M15: S | N15: 4 | O15: 2 | P15: Next Sprint | Q15: To Do | T15: Medium Risk | U15: Yes | V15: =HYPERLINK("#Main!A1","Open Main") -> Open Main | X15: SEO | Y15: =IFERROR(HYPERLINK("#Main!A"&MATCH(H15,Main!A:A,0),"View URL Details"),HYPERLINK("#Main!A1","View URL Details")) -> View URL Details | Z15: =IFERROR(HYPERLINK("#Main!A"&MATCH(H15,Main!A:A,0),"Open"),HYPERLINK("#Main!A1","Open")) -> Open | AA15: =IFERROR(INDEX('Content Optimization Hub'!A:A,MATCH(H15,'Content Optimization Hub'!C:C,0)),"Not in Hub") -> Not in Hub
A16: Hreflang Without Reciprocity | B16: Warning | C16: 67 | D16: 0 | F16: Technical | G16: Manual Content | I16: Apply fix based on issue type and re-run audit. | J16: Template/technical implementation quality issue. | K16: Copy Writer | L16: Copy Writer | M16: S | N16: 4 | O16: 2 | P16: Next Sprint | Q16: To Do | T16: Medium Risk | U16: Yes | V16: =HYPERLINK("#Main!A1","Open Main") -> Open Main | X16: SEO | Y16: =IFERROR(HYPERLINK("#Main!A"&MATCH(H16,Main!A:A,0),"View URL Details"),HYPERLINK("#Main!A1","View URL Details")) -> View URL Details | Z16: =IFERROR(HYPERLINK("#Main!A"&MATCH(H16,Main!A:A,0),"Open"),HYPERLINK("#Main!A1","Open")) -> Open | AA16: =IFERROR(INDEX('Content Optimization Hub'!A:A,MATCH(H16,'Content Optimization Hub'!C:C,0)),"Not in Hub") -> Not in Hub
A17: Multiple H1 | B17: Warning | C17: 67 | D17: 18 | E17: =HYPERLINK("#Technical!A1","SEE DETAILS IN Technical") -> SEE DETAILS IN Technical | F17: Technical | G17: Global Template | H17: https://africanmarketingconfederation.org/ | I17: Apply fix based on issue type and re-run audit. | J17: Template/technical implementation quality issue. | K17: Copy Writer | L17: Copy Writer | M17: S | N17: 4 | O17: 2 | P17: Next Sprint | Q17: To Do | T17: Medium Risk | U17: Yes | V17: =IFERROR(HYPERLINK("#Main!A"&MATCH("https://africanmarketingconfederation.org/",Main!A:A,0),"Jump to Main"),HYPERLINK("#Main!A1","Open Main")) -> Open Main | X17: SEO | Y17: =IFERROR(HYPERLINK("#Main!A"&MATCH(H17,Main!A:A,0),"View URL Details"),HYPERLINK("#Main!A1","View URL Details")) -> View URL Details | Z17: =IFERROR(HYPERLINK("#Main!A"&MATCH(H17,Main!A:A,0),"Open"),HYPERLINK("#Main!A1","Open")) -> Open | AA17: =IFERROR(INDEX('Content Optimization Hub'!A:A,MATCH(H17,'Content Optimization Hub'!C:C,0)),"Not in Hub") -> Not in Hub
A18: Missing Meta Description | B18: Warning | C18: 67 | D18: 5 | E18: https://africanmarketingconfederation.org/amc-conference-sponsors/ https://africanmarketingconfederation.org/amc-marketing-conference-2024/speakers-2024/ https://africanmarketingconfederation.org/elementor-20341/ https://africanmarketingconfederation.org/amc-conference-2023/amc-awards-book-now/ https://africanmarketingconfederation.org/amc-masterclass-bookings/ | F18: Technical | G18: Manual Content | H18: https://africanmarketingconfederation.org/amc-conference-sponsors/ | I18: Add concise unique description aligned with user intent. | J18: Meta description missing or empty. | K18: Copy Writer | L18: Copy Writer | M18: S | N18: 4 | O18: 2 | P18: Next Sprint | Q18: To Do | T18: Medium Risk | U18: Yes | V18: =IFERROR(HYPERLINK("#Main!A"&MATCH("https://africanmarketingconfederation.org/amc-conference-sponsors/",Main!A:A,0),"Jump to Main"),HYPERLINK("#Main!A1","Open Main")) -> Open Main | X18: SEO | Y18: =IFERROR(HYPERLINK("#Main!A"&MATCH(H18,Main!A:A,0),"View URL Details"),HYPERLINK("#Main!A1","View URL Details")) -> View URL Details | Z18: =IFERROR(HYPERLINK("#Main!A"&MATCH(H18,Main!A:A,0),"Open"),HYPERLINK("#Main!A1","Open")) -> Open | AA18: =IFERROR(INDEX('Content Optimization Hub'!A:A,MATCH(H18,'Content Optimization Hub'!C:C,0)),"Not in Hub") -> Not in Hub
A19: Missing H1 | B19: Warning | C19: 67 | D19: 32 | E19: =HYPERLINK("#Technical!A1","SEE DETAILS IN Technical") -> SEE DETAILS IN Technical | F19: Technical | G19: Global Template | H19: https://africanmarketingconfederation.org/publication-download-list/ | I19: Apply fix based on issue type and re-run audit. | J19: Template/technical implementation quality issue. | K19: Copy Writer | L19: Copy Writer | M19: S | N19: 4 | O19: 2 | P19: Next Sprint | Q19: To Do | T19: Medium Risk | U19: Yes | V19: =IFERROR(HYPERLINK("#Main!A"&MATCH("https://africanmarketingconfederation.org/publication-download-list/",Main!A:A,0),"Jump to Main"),HYPERLINK("#Main!A1","Open Main")) -> Open Main | X19: SEO | Y19: =IFERROR(HYPERLINK("#Main!A"&MATCH(H19,Main!A:A,0),"View URL Details"),HYPERLINK("#Main!A1","View URL Details")) -> View URL Details | Z19: =IFERROR(HYPERLINK("#Main!A"&MATCH(H19,Main!A:A,0),"Open"),HYPERLINK("#Main!A1","Open")) -> Open | AA19: =IFERROR(INDEX('Content Optimization Hub'!A:A,MATCH(H19,'Content Optimization Hub'!C:C,0)),"Not in Hub") -> Not in Hub
A20: Low AEO Readiness Score | B20: Warning | C20: 67 | D20: 85 | E20: =HYPERLINK("#AEO!A1","SEE DETAILS IN AEO") -> SEE DETAILS IN AEO | F20: AEO | G20: Global Template | H20: https://africanmarketingconfederation.org/publications-2/ | I20: Add short direct answer blocks, question-led headings, and answer-ready formatting. | J20: Page lacks concise answer-oriented signals and structured answer patterns. | K20: Copy Writer | L20: Copy Writer | M20: S | N20: 4 | O20: 2 | P20: Next Sprint | Q20: To Do | T20: Medium Risk | U20: Yes | V20: =IFERROR(HYPERLINK("#Main!A"&MATCH("https://africanmarketingconfederation.org/publications-2/",Main!A:A,0),"Jump to Main"),HYPERLINK("#Main!A1","Open Main")) -> Open Main | X20: AEO | Y20: =IFERROR(HYPERLINK("#Main!A"&MATCH(H20,Main!A:A,0),"View URL Details"),HYPERLINK("#Main!A1","View URL Details")) -> View URL Details | Z20: =IFERROR(HYPERLINK("#Main!A"&MATCH(H20,Main!A:A,0),"Open"),HYPERLINK("#Main!A1","Open")) -> Open | AA20: =IFERROR(INDEX('Content Optimization Hub'!A:A,MATCH(H20,'Content Optimization Hub'!C:C,0)),"Not in Hub") -> Not in Hub
A21: Uses URL Parameters | B21: Observation | C21: 37 | D21: 0 | F21: Technical | G21: Manual Content | I21: Apply fix based on issue type and re-run audit. | J21: Template/technical implementation quality issue. | K21: Dev | L21: Dev | M21: S | N21: 4 | O21: 2 | P21: Backlog | Q21: In Review | T21: Monitor | U21: No | V21: =HYPERLINK("#Main!A1","Open Main") -> Open Main | X21: SEO | Y21: =IFERROR(HYPERLINK("#Main!A"&MATCH(H21,Main!A:A,0),"View URL Details"),HYPERLINK("#Main!A1","View URL Details")) -> View URL Details | Z21: =IFERROR(HYPERLINK("#Main!A"&MATCH(H21,Main!A:A,0),"Open"),HYPERLINK("#Main!A1","Open")) -> Open | AA21: =IFERROR(INDEX('Content Optimization Hub'!A:A,MATCH(H21,'Content Optimization Hub'!C:C,0)),"Not in Hub") -> Not in Hub
A22: Generic Anchor Text Present | B22: Observation | C22: 37 | D22: 0 | F22: Links | G22: Manual Content | I22: Apply fix based on issue type and re-run audit. | J22: Template/technical implementation quality issue. | K22: Copy Writer | L22: Copy Writer | M22: S | N22: 4 | O22: 2 | P22: Backlog | Q22: In Review | T22: Monitor | U22: No | V22: =HYPERLINK("#Main!A1","Open Main") -> Open Main | X22: SEO | Y22: =IFERROR(HYPERLINK("#Main!A"&MATCH(H22,Main!A:A,0),"View URL Details"),HYPERLINK("#Main!A1","View URL Details")) -> View URL Details | Z22: =IFERROR(HYPERLINK("#Main!A"&MATCH(H22,Main!A:A,0),"Open"),HYPERLINK("#Main!A1","Open")) -> Open | AA22: =IFERROR(INDEX('Content Optimization Hub'!A:A,MATCH(H22,'Content Optimization Hub'!C:C,0)),"Not in Hub") -> Not in Hub
A23: INP Above 100ms | B23: Observation | C23: 37 | D23: 0 | F23: Technical | G23: Manual Content | I23: Apply fix based on issue type and re-run audit. | J23: Template/technical implementation quality issue. | K23: Copy Writer | L23: Copy Writer | M23: S | N23: 4 | O23: 2 | P23: Backlog | Q23: In Review | T23: Monitor | U23: No | V23: =HYPERLINK("#Main!A1","Open Main") -> Open Main | X23: SEO | Y23: =IFERROR(HYPERLINK("#Main!A"&MATCH(H23,Main!A:A,0),"View URL Details"),HYPERLINK("#Main!A1","View URL Details")) -> View URL Details | Z23: =IFERROR(HYPERLINK("#Main!A"&MATCH(H23,Main!A:A,0),"Open"),HYPERLINK("#Main!A1","Open")) -> Open | AA23: =IFERROR(INDEX('Content Optimization Hub'!A:A,MATCH(H23,'Content Optimization Hub'!C:C,0)),"Not in Hub") -> Not in Hub
A24: CLS Above 0.1 | B24: Observation | C24: 37 | D24: 0 | F24: Technical | G24: Manual Content | I24: Apply fix based on issue type and re-run audit. | J24: Template/technical implementation quality issue. | K24: Copy Writer | L24: Copy Writer | M24: S | N24: 4 | O24: 2 | P24: Backlog | Q24: In Review | T24: Monitor | U24: No | V24: =HYPERLINK("#Main!A1","Open Main") -> Open Main | X24: SEO | Y24: =IFERROR(HYPERLINK("#Main!A"&MATCH(H24,Main!A:A,0),"View URL Details"),HYPERLINK("#Main!A1","View URL Details")) -> View URL Details | Z24: =IFERROR(HYPERLINK("#Main!A"&MATCH(H24,Main!A:A,0),"Open"),HYPERLINK("#Main!A1","Open")) -> Open | AA24: =IFERROR(INDEX('Content Optimization Hub'!A:A,MATCH(H24,'Content Optimization Hub'!C:C,0)),"Not in Hub") -> Not in Hub
A25: llms.txt Missing | B25: Observation | C25: 37 | D25: 0 | F25: Technical | G25: Manual Content | I25: Apply fix based on issue type and re-run audit. | J25: Template/technical implementation quality issue. | K25: Copy Writer | L25: Copy Writer | M25: S | N25: 4 | O25: 2 | P25: Backlog | Q25: In Review | T25: Monitor | U25: No | V25: =HYPERLINK("#Main!A1","Open Main") -> Open Main | X25: SEO | Y25: =IFERROR(HYPERLINK("#Main!A"&MATCH(H25,Main!A:A,0),"View URL Details"),HYPERLINK("#Main!A1","View URL Details")) -> View URL Details | Z25: =IFERROR(HYPERLINK("#Main!A"&MATCH(H25,Main!A:A,0),"Open"),HYPERLINK("#Main!A1","Open")) -> Open | AA25: =IFERROR(INDEX('Content Optimization Hub'!A:A,MATCH(H25,'Content Optimization Hub'!C:C,0)),"Not in Hub") -> Not in Hub
A26: Image Filename Quality Issues | B26: Observation | C26: 37 | D26: 2 | E26: https://africanmarketingconfederation.org/amc-conference-2026/ https://africanmarketingconfederation.org/amc-conference-2025-highlights/ | F26: Technical | G26: Manual Content | H26: https://africanmarketingconfederation.org/amc-conference-2026/ | I26: Apply fix based on issue type and re-run audit. | J26: Template/technical implementation quality issue. | K26: Copy Writer | L26: Copy Writer | M26: S | N26: 4 | O26: 2 | P26: Backlog | Q26: In Review | T26: Monitor | U26: No | V26: =IFERROR(HYPERLINK("#Main!A"&MATCH("https://africanmarketingconfederation.org/amc-conference-2026/",Main!A:A,0),"Jump to Main"),HYPERLINK("#Main!A1","Open Main")) -> Open Main | X26: SEO | Y26: =IFERROR(HYPERLINK("#Main!A"&MATCH(H26,Main!A:A,0),"View URL Details"),HYPERLINK("#Main!A1","View URL Details")) -> View URL Details | Z26: =IFERROR(HYPERLINK("#Main!A"&MATCH(H26,Main!A:A,0),"Open"),HYPERLINK("#Main!A1","Open")) -> Open | AA26: =IFERROR(INDEX('Content Optimization Hub'!A:A,MATCH(H26,'Content Optimization Hub'!C:C,0)),"Not in Hub") -> Not in Hub
A27: Low Regional Authority | B27: Observation | C27: 37 | D27: 2 | E27: https://africanmarketingconfederation.org/amc-conference-sponsors/ https://africanmarketingconfederation.org/amc-marketing-conference-2024/speakers-2024/ | F27: Technical | G27: Manual Content | H27: https://africanmarketingconfederation.org/amc-conference-sponsors/ | I27: Apply fix based on issue type and re-run audit. | J27: Template/technical implementation quality issue. | K27: Copy Writer | L27: Copy Writer | M27: S | N27: 4 | O27: 2 | P27: Backlog | Q27: In Review | T27: Monitor | U27: No | V27: =IFERROR(HYPERLINK("#Main!A"&MATCH("https://africanmarketingconfederation.org/amc-conference-sponsors/",Main!A:A,0),"Jump to Main"),HYPERLINK("#Main!A1","Open Main")) -> Open Main | X27: SEO | Y27: =IFERROR(HYPERLINK("#Main!A"&MATCH(H27,Main!A:A,0),"View URL Details"),HYPERLINK("#Main!A1","View URL Details")) -> View URL Details | Z27: =IFERROR(HYPERLINK("#Main!A"&MATCH(H27,Main!A:A,0),"Open"),HYPERLINK("#Main!A1","Open")) -> Open | AA27: =IFERROR(INDEX('Content Optimization Hub'!A:A,MATCH(H27,'Content Optimization Hub'!C:C,0)),"Not in Hub") -> Not in Hub
A28: No Compression Header | B28: Observation | C28: 37 | D28: 85 | E28: =HYPERLINK("#Technical!A1","SEE DETAILS IN Technical") -> SEE DETAILS IN Technical | F28: Technical | G28: Global Template | H28: https://africanmarketingconfederation.org/publications-2/ | I28: Apply fix based on issue type and re-run audit. | J28: Template/technical implementation quality issue. | K28: Server/Host | L28: Server/Host | M28: S | N28: 4 | O28: 2 | P28: Backlog | Q28: In Review | T28: Monitor | U28: No | V28: =IFERROR(HYPERLINK("#Main!A"&MATCH("https://africanmarketingconfederation.org/publications-2/",Main!A:A,0),"Jump to Main"),HYPERLINK("#Main!A1","Open Main")) -> Open Main | X28: SEO | Y28: =IFERROR(HYPERLINK("#Main!A"&MATCH(H28,Main!A:A,0),"View URL Details"),HYPERLINK("#Main!A1","View URL Details")) -> View URL Details | Z28: =IFERROR(HYPERLINK("#Main!A"&MATCH(H28,Main!A:A,0),"Open"),HYPERLINK("#Main!A1","Open")) -> Open | AA28: =IFERROR(INDEX('Content Optimization Hub'!A:A,MATCH(H28,'Content Optimization Hub'!C:C,0)),"Not in Hub") -> Not in Hub
A29: No Cache-Control Header | B29: Observation | C29: 37 | D29: 85 | E29: =HYPERLINK("#Technical!A1","SEE DETAILS IN Technical") -> SEE DETAILS IN Technical | F29: Technical | G29: Global Template | H29: https://africanmarketingconfederation.org/publications-2/ | I29: Apply fix based on issue type and re-run audit. | J29: Template/technical implementation quality issue. | K29: Server/Host | L29: Server/Host | M29: S | N29: 4 | O29: 2 | P29: Backlog | Q29: In Review | T29: Monitor | U29: No | V29: =IFERROR(HYPERLINK("#Main!A"&MATCH("https://africanmarketingconfederation.org/publications-2/",Main!A:A,0),"Jump to Main"),HYPERLINK("#Main!A1","Open Main")) -> Open Main | X29: SEO | Y29: =IFERROR(HYPERLINK("#Main!A"&MATCH(H29,Main!A:A,0),"View URL Details"),HYPERLINK("#Main!A1","View URL Details")) -> View URL Details | Z29: =IFERROR(HYPERLINK("#Main!A"&MATCH(H29,Main!A:A,0),"Open"),HYPERLINK("#Main!A1","Open")) -> Open | AA29: =IFERROR(INDEX('Content Optimization Hub'!A:A,MATCH(H29,'Content Optimization Hub'!C:C,0)),"Not in Hub") -> Not in Hub
A30: No ETag Header | B30: Observation | C30: 37 | D30: 85 | E30: =HYPERLINK("#Technical!A1","SEE DETAILS IN Technical") -> SEE DETAILS IN Technical | F30: Technical | G30: Global Template | H30: https://africanmarketingconfederation.org/publications-2/ | I30: Apply fix based on issue type and re-run audit. | J30: Template/technical implementation quality issue. | K30: Server/Host | L30: Server/Host | M30: S | N30: 4 | O30: 2 | P30: Backlog | Q30: In Review | T30: Monitor | U30: No | V30: =IFERROR(HYPERLINK("#Main!A"&MATCH("https://africanmarketingconfederation.org/publications-2/",Main!A:A,0),"Jump to Main"),HYPERLINK("#Main!A1","Open Main")) -> Open Main | X30: SEO | Y30: =IFERROR(HYPERLINK("#Main!A"&MATCH(H30,Main!A:A,0),"View URL Details"),HYPERLINK("#Main!A1","View URL Details")) -> View URL Details | Z30: =IFERROR(HYPERLINK("#Main!A"&MATCH(H30,Main!A:A,0),"Open"),HYPERLINK("#Main!A1","Open")) -> Open | AA30: =IFERROR(INDEX('Content Optimization Hub'!A:A,MATCH(H30,'Content Optimization Hub'!C:C,0)),"Not in Hub") -> Not in Hub
A31: No Question Headings | B31: Observation | C31: 37 | D31: 85 | E31: =HYPERLINK("#AEO!A1","SEE DETAILS IN AEO") -> SEE DETAILS IN AEO | F31: AEO | G31: Global Template | H31: https://africanmarketingconfederation.org/publications-2/ | I31: Add clear question-style headings (especially H2/H3) for key intents. | J31: Headings are not phrased as user questions. | K31: Copy Writer | L31: Copy Writer | M31: S | N31: 4 | O31: 2 | P31: Backlog | Q31: In Review | T31: Monitor | U31: No | V31: =IFERROR(HYPERLINK("#Main!A"&MATCH("https://africanmarketingconfederation.org/publications-2/",Main!A:A,0),"Jump to Main"),HYPERLINK("#Main!A1","Open Main")) -> Open Main | X31: AEO | Y31: =IFERROR(HYPERLINK("#Main!A"&MATCH(H31,Main!A:A,0),"View URL Details"),HYPERLINK("#Main!A1","View URL Details")) -> View URL Details | Z31: =IFERROR(HYPERLINK("#Main!A"&MATCH(H31,Main!A:A,0),"Open"),HYPERLINK("#Main!A1","Open")) -> Open | AA31: =IFERROR(INDEX('Content Optimization Hub'!A:A,MATCH(H31,'Content Optimization Hub'!C:C,0)),"Not in Hub") -> Not in Hub
A32: No Answer-Friendly Structure | B32: Observation | C32: 37 | D32: 85 | E32: =HYPERLINK("#AEO!A1","SEE DETAILS IN AEO") -> SEE DETAILS IN AEO | F32: AEO | G32: Global Template | H32: https://africanmarketingconfederation.org/publications-2/ | I32: Introduce structured bullets, ordered steps, or tables for key answers. | J32: Page lacks lists/tables that help concise answer extraction. | K32: Copy Writer | L32: Copy Writer | M32: S | N32: 4 | O32: 2 | P32: Backlog | Q32: In Review | T32: Monitor | U32: No | V32: =IFERROR(HYPERLINK("#Main!A"&MATCH("https://africanmarketingconfederation.org/publications-2/",Main!A:A,0),"Jump to Main"),HYPERLINK("#Main!A1","Open Main")) -> Open Main | X32: AEO | Y32: =IFERROR(HYPERLINK("#Main!A"&MATCH(H32,Main!A:A,0),"View URL Details"),HYPERLINK("#Main!A1","View URL Details")) -> View URL Details | Z32: =IFERROR(HYPERLINK("#Main!A"&MATCH(H32,Main!A:A,0),"Open"),HYPERLINK("#Main!A1","Open")) -> Open | AA32: =IFERROR(INDEX('Content Optimization Hub'!A:A,MATCH(H32,'Content Optimization Hub'!C:C,0)),"Not in Hub") -> Not in Hub
A33: No 40-60 Word Answer Paragraphs | B33: Observation | C33: 37 | D33: 85 | E33: =HYPERLINK("#AEO!A1","SEE DETAILS IN AEO") -> SEE DETAILS IN AEO | F33: AEO | G33: Global Template | H33: https://africanmarketingconfederation.org/publications-2/ | I33: Add a direct 30-60 word answer summary near question headings. | J33: No concise answer-length paragraph detected. | K33: Copy Writer | L33: Copy Writer | M33: S | N33: 4 | O33: 2 | P33: Backlog | Q33: In Review | T33: Monitor | U33: No | V33: =IFERROR(HYPERLINK("#Main!A"&MATCH("https://africanmarketingconfederation.org/publications-2/",Main!A:A,0),"Jump to Main"),HYPERLINK("#Main!A1","Open Main")) -> Open Main | X33: AEO | Y33: =IFERROR(HYPERLINK("#Main!A"&MATCH(H33,Main!A:A,0),"View URL Details"),HYPERLINK("#Main!A1","View URL Details")) -> View URL Details | Z33: =IFERROR(HYPERLINK("#Main!A"&MATCH(H33,Main!A:A,0),"Open"),HYPERLINK("#Main!A1","Open")) -> Open | AA33: =IFERROR(INDEX('Content Optimization Hub'!A:A,MATCH(H33,'Content Optimization Hub'!C:C,0)),"Not in Hub") -> Not in Hub
A34: AI Crawlers Not Explicitly Allowed | B34: Observation | C34: 37 | D34: 85 | E34: =HYPERLINK("#Technical!A1","SEE DETAILS IN Technical") -> SEE DETAILS IN Technical | F34: Technical | G34: Global Template | H34: https://africanmarketingconfederation.org/publications-2/ | I34: Apply fix based on issue type and re-run audit. | J34: Template/technical implementation quality issue. | K34: Copy Writer | L34: Copy Writer | M34: S | N34: 4 | O34: 2 | P34: Backlog | Q34: In Review | T34: Monitor | U34: No | V34: =IFERROR(HYPERLINK("#Main!A"&MATCH("https://africanmarketingconfederation.org/publications-2/",Main!A:A,0),"Jump to Main"),HYPERLINK("#Main!A1","Open Main")) -> Open Main | X34: SEO | Y34: =IFERROR(HYPERLINK("#Main!A"&MATCH(H34,Main!A:A,0),"View URL Details"),HYPERLINK("#Main!A1","View URL Details")) -> View URL Details | Z34: =IFERROR(HYPERLINK("#Main!A"&MATCH(H34,Main!A:A,0),"Open"),HYPERLINK("#Main!A1","Open")) -> Open | AA34: =IFERROR(INDEX('Content Optimization Hub'!A:A,MATCH(H34,'Content Optimization Hub'!C:C,0)),"Not in Hub") -> Not in Hub
A35: Thin Content | B35: Observation | C35: 37 | D35: 44 | E35: =HYPERLINK("#Technical!A1","SEE DETAILS IN Technical") -> SEE DETAILS IN Technical | F35: Technical | G35: Global Template | H35: https://africanmarketingconfederation.org/publications-2/ | I35: Expand page with helpful, unique, intent-matching content. | J35: Insufficient body content for indexing confidence. | K35: Copy Writer | L35: Copy Writer | M35: S | N35: 4 | O35: 2 | P35: Backlog | Q35: In Review | T35: Monitor | U35: No | V35: =IFERROR(HYPERLINK("#Main!A"&MATCH("https://africanmarketingconfederation.org/publications-2/",Main!A:A,0),"Jump to Main"),HYPERLINK("#Main!A1","Open Main")) -> Open Main | X35: SEO | Y35: =IFERROR(HYPERLINK("#Main!A"&MATCH(H35,Main!A:A,0),"View URL Details"),HYPERLINK("#Main!A1","View URL Details")) -> View URL Details | Z35: =IFERROR(HYPERLINK("#Main!A"&MATCH(H35,Main!A:A,0),"Open"),HYPERLINK("#Main!A1","Open")) -> Open | AA35: =IFERROR(INDEX('Content Optimization Hub'!A:A,MATCH(H35,'Content Optimization Hub'!C:C,0)),"Not in Hub") -> Not in Hub

Sheet Main
A1: Health Icon | B1: URL | C1: Status Code | D1: Indexability | E1: Load Time (s) | F1: Title | G1: Meta Description | H1: Word Count (Body) | I1: SEO Health Score | J1: Severity Badge | K1: Title Length | L1: Meta Desc Length | M1: OG-Image | N1: Has Valid JSON-LD | O1: H1 Content | P1: H1 Length | Q1: H2 Content | R1: H2 Length | S1: H3 Content | T1: H3 Length | U1: H4 Content | V1: H4 Length | W1: H5 Content | X1: H5 Length | Y1: H6 Content | Z1: H6 Length | AA1: CWV LCP (s) | AB1: CWV INP (ms) | AC1: CWV CLS | AD1: Field vs Lab | AE1: Regional Authority Score | AF1: Technical View | AG1: BACK TO DASHBOARD
A2: FAIL 🔴 | B2: https://africanmarketingconfederation.org/amc-conference-sponsors/ | C2: 404 | D2: Indexable | E2: 4.004 | H2: 0 | I2: 6 | J2: Critical | K2: 0 | L2: 0 | N2: FALSE | P2: 0 | R2: 0 | T2: 0 | V2: 0 | X2: 0 | Z2: 0 | AD2: Lab | AE2: 0 | AF2: =IFERROR(HYPERLINK("#Technical!A"&MATCH(B2,Technical!A:A,0),"Open Technical"),HYPERLINK("#Technical!A1","Open Technical")) -> Open Technical
A3: FAIL 🔴 | B3: https://africanmarketingconfederation.org/amc-marketing-conference-2024/speakers-2024/ | C3: 404 | D3: Indexable | E3: 3.907 | H3: 0 | I3: 6 | J3: Critical | K3: 0 | L3: 0 | N3: FALSE | P3: 0 | R3: 0 | T3: 0 | V3: 0 | X3: 0 | Z3: 0 | AD3: Lab | AE3: 0 | AF3: =IFERROR(HYPERLINK("#Technical!A"&MATCH(B3,Technical!A:A,0),"Open Technical"),HYPERLINK("#Technical!A1","Open Technical")) -> Open Technical
A4: WARN 🟡 | B4: https://africanmarketingconfederation.org/ | C4: 200 | D4: Indexable | E4: 2.695 | F4: African Marketing Confederation - Uniting Marketers for Excellence | G4: The African Marketing Confederation is the ground-breaking Pan-African body driving the development of top marketing standards across Africa and beyond. | H4: 35 | I4: 56 | J4: Warning | K4: 66 | L4: 152 | N4: FALSE | P4: 0 | R4: 0 | T4: 0 | V4: 0 | X4: 0 | Z4: 0 | AD4: Lab | AE4: 100 | AF4: =IFERROR(HYPERLINK("#Technical!A"&MATCH(B4,Technical!A:A,0),"Open Technical"),HYPERLINK("#Technical!A1","Open Technical")) -> Open Technical
A5: WARN 🟡 | B5: https://africanmarketingconfederation.org/about-us/ | C5: 200 | D5: Indexable | E5: 0.052 | F5: African Marketing Confederation – The Leading Marketing Professional Body – African Marketing Confederation | G5: ABOUT The African Marketing Confederation​ The African Marketing Confederation is the ground-breaking Pan African body of marketing professionals spearheading the ongoing development of the highest possible standards of marketing across Africa. Founded in 2011, the AMC is a collaboration between the African national marketing bodies and associations to exchange expertise and information, and to promote | H5: 219 | I5: 66 | J5: Warning | K5: 107 | L5: 405 | N5: FALSE | P5: 0 | R5: 0 | T5: 0 | V5: 0 | X5: 0 | Z5: 0 | AD5: Lab | AE5: 70 | AF5: =IFERROR(HYPERLINK("#Technical!A"&MATCH(B5,Technical!A:A,0),"Open Technical"),HYPERLINK("#Technical!A1","Open Technical")) -> Open Technical
A6: WARN 🟡 | B6: https://africanmarketingconfederation.org/african-marketing-confederation-tourism-chapter/ | C6: 200 | D6: Indexable | E6: 0.121 | F6: African Marketing Confederation Tourism Chapter – African Marketing Confederation | G6: African Marketing Confederation Tourism Chapter Shaping Africa’s Tourism Narrative Through Strategic Marketing Tourism is one of Africa’s most powerful economic engines - generating jobs, stimulating investment, and fostering cultural exchange.The African Marketing Confederation is proud to launch the Tourism Chapter, a bold initiative to elevate African tourism through the lens of world-class marketing. Launched at the | H6: 339 | I6: 59 | J6: Warning | K6: 81 | L6: 423 | N6: FALSE | P6: 0 | R6: 0 | T6: 0 | V6: 0 | X6: 0 | Z6: 0 | AD6: Lab | AE6: 60 | AF6: =IFERROR(HYPERLINK("#Technical!A"&MATCH(B6,Technical!A:A,0),"Open Technical"),HYPERLINK("#Technical!A1","Open Technical")) -> Open Technical
A7: WARN 🟡 | B7: https://africanmarketingconfederation.org/amc-awards-2024/ | C7: 200 | D7: Indexable | E7: 0.051 | F7: AMC Awards 2024 – African Marketing Confederation | G7: NOMINATIONS are Open ! AMC Awards The African Marketing Confederation Awards event is held annually as part of the African Marketing Confederation Forum. This distinguished event celebrates and acknowledges outstanding marketing campaigns and the visionary individuals behind them. The awards presented honor not only the groundbreaking strategies and creative brilliance that set these campaigns apart but | H7: 1637 | I7: 59 | J7: Warning | K7: 49 | L7: 406 | N7: FALSE | P7: 0 | R7: 0 | T7: 0 | V7: 0 | X7: 0 | Z7: 0 | AD7: Lab | AE7: 100 | AF7: =IFERROR(HYPERLINK("#Technical!A"&MATCH(B7,Technical!A:A,0),"Open Technical"),HYPERLINK("#Technical!A1","Open Technical")) -> Open Technical
A8: WARN 🟡 | B8: https://africanmarketingconfederation.org/amc-conference-2022-prospectus/ | C8: 200 | D8: Indexable | E8: 0.035 | F8: AMC Conference 2022 – Prospectus – African Marketing Confederation | G8: AMC Conference 2022 23 - 24 March 2022 Navigating Africa's Unique Marketing Mix BOOK NOW Days Hours Minutes Seconds download prospectus To download the AMC 2022 Conference Prospectus please complete the form below: First Name Last Name Email Mobile Company I've read and agree to the Privacy Policy BOOK NOW FOR THE AMC CONFERENCE 2022 | H8: 100 | I8: 56 | J8: Warning | K8: 66 | L8: 335 | N8: FALSE | P8: 0 | R8: 0 | T8: 0 | V8: 0 | X8: 0 | Z8: 0 | AD8: Lab | AE8: 30 | AF8: =IFERROR(HYPERLINK("#Technical!A"&MATCH(B8,Technical!A:A,0),"Open Technical"),HYPERLINK("#Technical!A1","Open Technical")) -> Open Technical
A9: WARN 🟡 | B9: https://africanmarketingconfederation.org/amc-conference-2022-thank-you/ | C9: 200 | D9: Indexable | E9: 0.04 | F9: AMC Conference 2022 – Thank You – African Marketing Confederation | G9: AMC Conference 2022 23 - 24 March 2022 Navigating Africa's Unique Marketing Mix ENQUIRE NOW Days Hours Minutes Seconds Success! Thank you for completing the enquiry form. Our team will contact you shortly! × Dismiss alert The AMC Conference is the must attend Pan African event for marketing professionals. It will focus on solutions for | H9: 347 | I9: 59 | J9: Warning | K9: 65 | L9: 337 | N9: FALSE | P9: 0 | R9: 0 | T9: 0 | V9: 0 | X9: 0 | Z9: 0 | AD9: Lab | AE9: 100 | AF9: =IFERROR(HYPERLINK("#Technical!A"&MATCH(B9,Technical!A:A,0),"Open Technical"),HYPERLINK("#Technical!A1","Open Technical")) -> Open Technical
A10: WARN 🟡 | B10: https://africanmarketingconfederation.org/amc-conference-2022/ | C10: 200 | D10: Indexable | E10: 0.04 | F10: AMC Conference 2022 – African Marketing Confederation | G10: corinna kopf onlyfans leaks AMC Conference 2022 Thank you for attending19 - 22 October 2022 The African Marketing Confederation's Annual Conference brought together the best collection of marketing leaders from top companies, marketing bodies and associations to share tactics and best practices on how to build the next generation of marketing. Event Highlights Thank you for Attending! | H10: 32 | I10: 56 | J10: Warning | K10: 53 | L10: 387 | N10: FALSE | P10: 0 | R10: 0 | T10: 0 | V10: 0 | X10: 0 | Z10: 0 | AD10: Lab | AE10: 100 | AF10: =IFERROR(HYPERLINK("#Technical!A"&MATCH(B10,Technical!A:A,0),"Open Technical"),HYPERLINK("#Technical!A1","Open Technical")) -> Open Technical
A11: WARN 🟡 | B11: https://africanmarketingconfederation.org/amc-conference-2023/ | C11: 200 | D11: Indexable | E11: 0.053 | F11: AMC Conference 2023 – African Marketing Confederation | G11: AMC Conference 6 - 9 September 2023 Imperial Botanical Beach Hotel, Entebbe, Uganda Thank you for joining us! View Presentations 2nd Annual African Marketing Confederation Conference Africa's $3.4 trillion Economy: Opportunities for Marketers Welcome to the Recap of the 2nd Annual African Marketing Conference: Unveiling Africa's $3.4 Trillion EconomyOur conference was a remarkable exploration of | H11: 399 | I11: 69 | J11: Warning | K11: 53 | L11: 398 | N11: FALSE | P11: 0 | R11: 0 | T11: 0 | V11: 0 | X11: 0 | Z11: 0 | AD11: Lab | AE11: 80 | AF11: =IFERROR(HYPERLINK("#Technical!A"&MATCH(B11,Technical!A:A,0),"Open Technical"),HYPERLINK("#Technical!A1","Open Technical")) -> Open Technical
A12: WARN 🟡 | B12: https://africanmarketingconfederation.org/amc-conference-2023/amc-awards-book-now/ | C12: 200 | D12: Indexable | E12: 0.038 | F12: AMC Awards | Book Now – African Marketing Confederation | H12: 15 | I12: 46 | J12: Warning | K12: 55 | L12: 0 | N12: FALSE | P12: 0 | R12: 0 | T12: 0 | V12: 0 | X12: 0 | Z12: 0 | AD12: Lab | AE12: 30 | AF12: =IFERROR(HYPERLINK("#Technical!A"&MATCH(B12,Technical!A:A,0),"Open Technical"),HYPERLINK("#Technical!A1","Open Technical")) -> Open Technical
A13: WARN 🟡 | B13: https://africanmarketingconfederation.org/amc-conference-2023/amc-awards/ | C13: 200 | D13: Indexable | E13: 0.052 | F13: AMC Awards – African Marketing Confederation | G13: AMC Awards Welcome to the prestigious African Marketing Confederation Awards, a distinguished event that celebrates and acknowledges the remarkable achievements, cutting-edge innovations, and exceptional leadership demonstrated by outstanding individuals within the dynamic realm of marketing across the expansive African region.During the 2nd Annual African Marketing Confederation Conference, held from 6th to 9th September at the | H13: 310 | I13: 69 | J13: Warning | K13: 44 | L13: 432 | N13: FALSE | P13: 0 | R13: 0 | T13: 0 | V13: 0 | X13: 0 | Z13: 0 | AD13: Lab | AE13: 40 | AF13: =IFERROR(HYPERLINK("#Technical!A"&MATCH(B13,Technical!A:A,0),"Open Technical"),HYPERLINK("#Technical!A1","Open Technical")) -> Open Technical
A14: WARN 🟡 | B14: https://africanmarketingconfederation.org/amc-conference-2023/book-now-thank-you/ | C14: 200 | D14: Indexable | E14: 0.053 | F14: Book Now | Thank you – African Marketing Confederation | G14: Thank you for completing your booking! Congratulations on booking your seat to the 2023 AfricaPro Conference presenting the 2nd Annual African Marketing Confederation Conference and Inaugural Technology Information Confederation Africa Conference! You will receive your email confirmation shortly with more event information. Be sure to keep an eye on the event website for up to | H14: 81 | I14: 56 | J14: Warning | K14: 54 | L14: 379 | N14: FALSE | P14: 0 | R14: 0 | T14: 0 | V14: 0 | X14: 0 | Z14: 0 | AD14: Lab | AE14: 30 | AF14: =IFERROR(HYPERLINK("#Technical!A"&MATCH(B14,Technical!A:A,0),"Open Technical"),HYPERLINK("#Technical!A1","Open Technical")) -> Open Technical
A15: WARN 🟡 | B15: https://africanmarketingconfederation.org/amc-conference-2023/book-now/ | C15: 200 | D15: Indexable | E15: 0.057 | F15: Book Now – African Marketing Confederation | G15: Book Now Individual Booking Package Options 1: Full Conference + Accommodation 5 - 9 September 2023 890 USD 3 Day Conference Including Excursions: 5 Sept - Networking evening and light dinner 6 Sept - Official opening and barbecue dinner 7 Sept - Sunset Cruise on Lake Victoria 8 Sept - Cultural Gala dinner at Ndere | H15: 179 | I15: 66 | J15: Warning | K15: 42 | L15: 316 | N15: FALSE | P15: 0 | R15: 0 | T15: 0 | V15: 0 | X15: 0 | Z15: 0 | AD15: Lab | AE15: 30 | AF15: =IFERROR(HYPERLINK("#Technical!A"&MATCH(B15,Technical!A:A,0),"Open Technical"),HYPERLINK("#Technical!A1","Open Technical")) -> Open Technical
A16: WARN 🟡 | B16: https://africanmarketingconfederation.org/amc-conference-2023/download-prospectus/ | C16: 200 | D16: Indexable | E16: 0.048 | F16: Download Prospectus – African Marketing Confederation | G16: BOOK NOW Prospectus Download the African Marketing Confederation Prospectus Learn more about the available sponsorship and exhibitor packages and how you can be a part of this exciting event First Name Last Name Email Position Are you a member of a country member body?--Select--Yes No I would like to receive monthly updates from AMCYes No | H16: 95 | I16: 66 | J16: Warning | K16: 53 | L16: 340 | N16: FALSE | P16: 0 | R16: 0 | T16: 0 | V16: 0 | X16: 0 | Z16: 0 | AD16: Lab | AE16: 30 | AF16: =IFERROR(HYPERLINK("#Technical!A"&MATCH(B16,Technical!A:A,0),"Open Technical"),HYPERLINK("#Technical!A1","Open Technical")) -> Open Technical
A17: WARN 🟡 | B17: https://africanmarketingconfederation.org/amc-conference-2023/gallery/ | C17: 200 | D17: Indexable | E17: 0.056 | F17: Gallery – African Marketing Confederation | G17: Conference Gallery sydney sweeney met gala All Day 1 Day 2 Day 3 Night 1 Night 2 Night 3 | H17: 30 | I17: 66 | J17: Warning | K17: 41 | L17: 88 | N17: FALSE | P17: 0 | R17: 0 | T17: 0 | V17: 0 | X17: 0 | Z17: 0 | AD17: Lab | AE17: 30 | AF17: =IFERROR(HYPERLINK("#Technical!A"&MATCH(B17,Technical!A:A,0),"Open Technical"),HYPERLINK("#Technical!A1","Open Technical")) -> Open Technical
A18: WARN 🟡 | B18: https://africanmarketingconfederation.org/amc-conference-2023/partners/ | C18: 200 | D18: Indexable | E18: 0.056 | F18: Partners – African Marketing Confederation | G18: Conference Partners AMC Member Bodies | H18: 20 | I18: 66 | J18: Warning | K18: 42 | L18: 37 | N18: FALSE | P18: 0 | R18: 0 | T18: 0 | V18: 0 | X18: 0 | Z18: 0 | AD18: Lab | AE18: 30 | AF18: =IFERROR(HYPERLINK("#Technical!A"&MATCH(B18,Technical!A:A,0),"Open Technical"),HYPERLINK("#Technical!A1","Open Technical")) -> Open Technical
A19: WARN 🟡 | B19: https://africanmarketingconfederation.org/amc-conference-2023/programme/ | C19: 200 | D19: Indexable | E19: 0.053 | F19: Programme – African Marketing Confederation | G19: Programme Download Conference Presentations Are Marketers Intelligent Enough For AI - Fred Kithinzi Taking Africa to the world and bringing the world to Africa - Nondumiso Mabece| Next Media DGCEO Presentation Strategy and Technology: Expanding the Success of Pan-African Brands - Prof. Robert Ebo Hinson Winning African Markets - Simon Harvey Culture as the New | H19: 678 | I19: 69 | J19: Warning | K19: 43 | L19: 362 | N19: FALSE | P19: 0 | R19: 0 | T19: 0 | V19: 0 | X19: 0 | Z19: 0 | AD19: Lab | AE19: 90 | AF19: =IFERROR(HYPERLINK("#Technical!A"&MATCH(B19,Technical!A:A,0),"Open Technical"),HYPERLINK("#Technical!A1","Open Technical")) -> Open Technical
A20: WARN 🟡 | B20: https://africanmarketingconfederation.org/amc-conference-2023/speakers/ | C20: 200 | D20: Indexable | E20: 0.035 | F20: Speakers – African Marketing Confederation | G20: Speakers Ali Hussein Kassim Kenya CEO - AHK Corp View Bio Cathy Adengo Uganda Head of Sustainability, Stanbic Bank Uganda View Bio Doreen Asaasira Muhangazi Uganda Chief Human Resource Officer View Bio James Sutton United Kingdom Strategy and Commercial Director - CIM-UK View Bio Juliet Ziswa Zimbabwe Marketing Director - OK Zimbabwe Limited Group View | H20: 2642 | I20: 69 | J20: Warning | K20: 42 | L20: 354 | N20: FALSE | P20: 0 | R20: 0 | T20: 0 | V20: 0 | X20: 0 | Z20: 0 | AD20: Lab | AE20: 100 | AF20: =IFERROR(HYPERLINK("#Technical!A"&MATCH(B20,Technical!A:A,0),"Open Technical"),HYPERLINK("#Technical!A1","Open Technical")) -> Open Technical
A21: WARN 🟡 | B21: https://africanmarketingconfederation.org/amc-conference-2024-recap/ | C21: 200 | D21: Indexable | E21: 0.039 | F21: AMC Conference 2024 Recap – African Marketing Confederation | G21: Event Highlights AMC Marketing Conference 2024 Shaping the Future of African Marketing Get 2025 Conference Updates Share Your Experience Conference Day 1 The conference kicked off with insightful addresses, including a keynote from marketing expert Hermawan Kartajaya. Dr Philip Kotler, the Father of Modern Marketing, delivered a welcome address live from Chicago and we ended | H21: 1418 | I21: 59 | J21: Warning | K21: 59 | L21: 377 | N21: FALSE | P21: 0 | R21: 0 | T21: 0 | V21: 0 | X21: 0 | Z21: 0 | AD21: Lab | AE21: 100 | AF21: =IFERROR(HYPERLINK("#Technical!A"&MATCH(B21,Technical!A:A,0),"Open Technical"),HYPERLINK("#Technical!A1","Open Technical")) -> Open Technical
A22: WARN 🟡 | B22: https://africanmarketingconfederation.org/amc-conference-2024-sponsors-packages/ | C22: 200 | D22: Indexable | E22: 0.048 | F22: Sponsors Packages – African Marketing Confederation | G22: SPONSORSHIP PACKAGES Diamond Package Overall Anchor and Title Sponsor $50000,00 View Product Platinum Package Industry Leader Sponsor / per Professional Body Stream $20000,00 View Product Silver Package Full Day (Option to Choose Day 1, 2, or 3) Provision of Delegates Apparel in the Form of Golf Shirts and Caps (Day 2 & 3) $12000,00 View | H22: 110 | I22: 66 | J22: Warning | K22: 51 | L22: 339 | N22: FALSE | P22: 0 | R22: 0 | T22: 0 | V22: 0 | X22: 0 | Z22: 0 | AD22: Lab | AE22: 40 | AF22: =IFERROR(HYPERLINK("#Technical!A"&MATCH(B22,Technical!A:A,0),"Open Technical"),HYPERLINK("#Technical!A1","Open Technical")) -> Open Technical
A23: WARN 🟡 | B23: https://africanmarketingconfederation.org/amc-conference-2025-highlights/ | C23: 200 | D23: Indexable | E23: 0.235 | F23: AMC Conference 2025 Highlights – African Marketing Confederation | G23: 2025 Event Highlights AMC Marketing Conference AMC Marketing Conference 250+ Delegates. 29 Countries. One Pan-African Voice.250+ Delegates. 29 Countries.One Pan-African Marketing Voice. Get 2026 Conference Updates Share Your Experience 2025 Event Highlights AMC Marketing Conference 400+ Delegates. 29 Countries.One Pan-African Voice. Get 2026 Conference Updates 2025 Event Highlights AMC Marketing Conference Get 2026 Conference Updates | H23: 1853 | I23: 56 | J23: Warning | K23: 64 | L23: 437 | N23: FALSE | P23: 0 | R23: 0 | T23: 0 | V23: 0 | X23: 0 | Z23: 0 | AD23: Lab | AE23: 90 | AF23: =IFERROR(HYPERLINK("#Technical!A"&MATCH(B23,Technical!A:A,0),"Open Technical"),HYPERLINK("#Technical!A1","Open Technical")) -> Open Technical
A24: WARN 🟡 | B24: https://africanmarketingconfederation.org/amc-conference-2025/ | C24: 200 | D24: Indexable | E24: 0.04 | F24: AMC Conference 2025 | G24: Join Africa's top marketers at the AMC Conference 2025 n Accra, Ghana from 20-22 August - 3 days of insights, innovation, and powerful networking. | H24: 1161 | I24: 59 | J24: Warning | K24: 19 | L24: 146 | N24: FALSE | P24: 0 | R24: 0 | T24: 0 | V24: 0 | X24: 0 | Z24: 0 | AD24: Lab | AE24: 100 | AF24: =IFERROR(HYPERLINK("#Technical!A"&MATCH(B24,Technical!A:A,0),"Open Technical"),HYPERLINK("#Technical!A1","Open Technical")) -> Open Technical
... A41: WARN 🟡 | B41: https://africanmarketingconfederation.org/amc-marketing-conference-2024/testimony-thank-you-page/ | C41: 200 | D41: Indexable | E41: 0.04 | F41: Testimony Thank you Page – African Marketing Confederation | G41: Thank you For your Feedback Thank you For the Feedback PUBLICATIONS Strategic Marketing for Africa Magazine CONTACT INFORMATION info@africanmarketingconfederation.org © 2021 by African Marketing Confederation | Privacy Policy | H41: 31 | I41: 56 | J41: Warning | K41: 58 | L41: 225 | N41: FALSE | P41: 0 | R41: 0 | T41: 0 | V41: 0 | X41: 0 | Z41: 0 | AD41: Lab | AE41: 40 | AF41: =IFERROR(HYPERLINK("#Technical!A"&MATCH(B41,Technical!A:A,0),"Open Technical"),HYPERLINK("#Technical!A1","Open Technical")) -> Open Technical
A42: WARN 🟡 | B42: https://africanmarketingconfederation.org/amc-masterclass-bookings/ | C42: 200 | D42: Indexable | E42: 0.046 | F42: AMC Masterclass | Bookings – African Marketing Confederation | H42: 15 | I42: 46 | J42: Warning | K42: 60 | L42: 0 | N42: FALSE | P42: 0 | R42: 0 | T42: 0 | V42: 0 | X42: 0 | Z42: 0 | AD42: Lab | AE42: 30 | AF42: =IFERROR(HYPERLINK("#Technical!A"&MATCH(B42,Technical!A:A,0),"Open Technical"),HYPERLINK("#Technical!A1","Open Technical")) -> Open Technical
A43: WARN 🟡 | B43: https://africanmarketingconfederation.org/amc-masterclass-thank-you/ | C43: 200 | D43: Indexable | E43: 0.031 | F43: AMC Masterclass | Thank you – African Marketing Confederation | G43: AMC VIRTUAL MASTERCLASS 31 May 2022 Thank you for your Booking We received your booking and will contact you shortly! | H43: 32 | I43: 56 | J43: Warning | K43: 61 | L43: 117 | N43: FALSE | P43: 0 | R43: 0 | T43: 0 | V43: 0 | X43: 0 | Z43: 0 | AD43: Lab | AE43: 30 | AF43: =IFERROR(HYPERLINK("#Technical!A"&MATCH(B43,Technical!A:A,0),"Open Technical"),HYPERLINK("#Technical!A1","Open Technical")) -> Open Technical
A44: WARN 🟡 | B44: https://africanmarketingconfederation.org/amc-masterclass/ | C44: 200 | D44: Indexable | E44: 0.035 | F44: AMC Masterclass – African Marketing Confederation | G44: AMC VIRTUAL MASTERCLASS 31 May 2022 Thank you for attending Building The Perfect Blueprint for Digital and Strategic Marketing Align your digital efforts with your strategic goals and develop strong online marketing capabilities to help your company stay ahead of the curve.Masterclass Outcomes: You will receive all the tools you need to overcome and avoid | H44: 214 | I44: 56 | J44: Warning | K44: 49 | L44: 357 | N44: FALSE | P44: 0 | R44: 0 | T44: 0 | V44: 0 | X44: 0 | Z44: 0 | AD44: Lab | AE44: 30 | AF44: =IFERROR(HYPERLINK("#Technical!A"&MATCH(B44,Technical!A:A,0),"Open Technical"),HYPERLINK("#Technical!A1","Open Technical")) -> Open Technical
A45: WARN 🟡 | B45: https://africanmarketingconfederation.org/amc-relaunch-programme/ | C45: 200 | D45: Indexable | E45: 0.037 | F45: AMC RELAUNCH – PROGRAMME – African Marketing Confederation | G45: amc relaunch Thank you for joining our first online gathering! WATCH RECORDINGS NOW WATCH NOW AMC RELAUNCH RECORDINGS The AMC relaunch event shared the vision and goals of the AMC, as well as hosting talks and discussions with top marketing thought leaders and professionals. The African Marketing Confederation (AMC) – the ground breaking Pan-African body | H45: 452 | I45: 59 | J45: Warning | K45: 58 | L45: 356 | N45: FALSE | P45: 0 | R45: 0 | T45: 0 | V45: 0 | X45: 0 | Z45: 0 | AD45: Lab | AE45: 70 | AF45: =IFERROR(HYPERLINK("#Technical!A"&MATCH(B45,Technical!A:A,0),"Open Technical"),HYPERLINK("#Technical!A1","Open Technical")) -> Open Technical
A46: WARN 🟡 | B46: https://africanmarketingconfederation.org/amc-sign-up-now-form-2025/ | C46: 200 | D46: Indexable | E46: 0.045 | F46: AMC Sign up now Form 2025 – African Marketing Confederation | G46: Get Ready for Ghana in 2025! Name(Required) First Last Email(Required) Enter Email Confirm Email Phone Number(Required)CountryAfghanistanAlbaniaAlgeriaAmerican SamoaAndorraAngolaAnguillaAntarcticaAntigua and BarbudaArgentinaArmeniaArubaAustraliaAustriaAzerbaijanBahamasBahrainBangladeshBarbadosBelarusBelgiumBelizeBeninBermudaBhutanBoliviaBonaire, Sint Eustatius and SabaBosnia and HerzegovinaBotswanaBouvet IslandBrazilBritish Indian Ocean TerritoryBrunei DarussalamBulgariaBurkina FasoBurundiCabo VerdeCambodiaCameroonCanadaCayman IslandsCentral African RepublicChadChileChinaChristmas IslandCocos IslandsColombiaComorosCongoCongo, Democratic Republic of theCook IslandsCosta RicaCroatiaCubaCuraçaoCyprusCzechiaCôte d'IvoireDenmarkDjiboutiDominicaDominican RepublicEcuadorEgyptEl SalvadorEquatorial GuineaEritreaEstoniaEswatiniEthiopiaFalkland IslandsFaroe IslandsFijiFinlandFranceFrench GuianaFrench PolynesiaFrench Southern TerritoriesGabonGambiaGeorgiaGermanyGhanaGibraltarGreeceGreenlandGrenadaGuadeloupeGuamGuatemalaGuernseyGuineaGuinea-BissauGuyanaHaitiHeard Island and | H46: 573 | I46: 69 | J46: Warning | K46: 59 | L46: 1077 | N46: FALSE | P46: 0 | R46: 0 | T46: 0 | V46: 0 | X46: 0 | Z46: 0 | AD46: Lab | AE46: 100 | AF46: =IFERROR(HYPERLINK("#Technical!A"&MATCH(B46,Technical!A:A,0),"Open Technical"),HYPERLINK("#Technical!A1","Open Technical")) -> Open Technical
A47: WARN 🟡 | B47: https://africanmarketingconfederation.org/amc-sponsors-2025/ | C47: 200 | D47: Indexable | E47: 0.047 | F47: Sponsorship Opportunities – 2025 AMC Conference | G47: Explore sponsorship opportunities for AMC Conference 2025 and position your brand alongside Africa’s leading marketers, innovators, and industry decision-makers. | H47: 1132 | I47: 69 | J47: Warning | K47: 47 | L47: 161 | N47: FALSE | P47: 0 | R47: 0 | T47: 0 | V47: 0 | X47: 0 | Z47: 0 | AD47: Lab | AE47: 100 | AF47: =IFERROR(HYPERLINK("#Technical!A"&MATCH(B47,Technical!A:A,0),"Open Technical"),HYPERLINK("#Technical!A1","Open Technical")) -> Open Technical
A48: WARN 🟡 | B48: https://africanmarketingconfederation.org/amc-testimony-page-2024/ | C48: 200 | D48: Indexable | E48: 0.037 | F48: AMC Testimony page 2024 – African Marketing Confederation | G48: How was your experience at the2024 AMC Conference? Name(Required) First Last Email(Required) Company Name How was your experience at the AMC Conference 2024? We'd love to hear about your key takeaways and memorable moments!What improvements would you recommend for the next AMC Conference to make it even more impactful? Sponsors Previous Next PUBLICATIONS Strategic Marketing | H48: 587 | I48: 69 | J48: Warning | K48: 57 | L48: 376 | N48: FALSE | P48: 0 | R48: 0 | T48: 0 | V48: 0 | X48: 0 | Z48: 0 | AD48: Lab | AE48: 100 | AF48: =IFERROR(HYPERLINK("#Technical!A"&MATCH(B48,Technical!A:A,0),"Open Technical"),HYPERLINK("#Technical!A1","Open Technical")) -> Open Technical
A49: WARN 🟡 | B49: https://africanmarketingconfederation.org/awards-2026-1/ | C49: 200 | D49: Indexable | E49: 0.051 | F49: 2026 AMC Awards-1 – African Marketing Confederation | G49: The African Marketing Confederation presents the 2026 AMC Awards. Submit your nominations to recognise innovative strategies, impact, and marketing results. | H49: 1053 | I49: 59 | J49: Warning | K49: 51 | L49: 156 | N49: FALSE | P49: 0 | R49: 0 | T49: 0 | V49: 0 | X49: 0 | Z49: 0 | AD49: Lab | AE49: 100 | AF49: =IFERROR(HYPERLINK("#Technical!A"&MATCH(B49,Technical!A:A,0),"Open Technical"),HYPERLINK("#Technical!A1","Open Technical")) -> Open Technical
A50: WARN 🟡 | B50: https://africanmarketingconfederation.org/awards-2026-test/ | C50: 200 | D50: Indexable | E50: 0.038 | F50: Awards 2026 test – African Marketing Confederation | G50: 2026 AMC AWARDS 2026AMC Awards Submit Your Nomination View Awards Brochure Where Africa’s Boldest Ideas Take the Stage https://africanmarketingconfederation.org/wp-content/uploads/2026/03/16x9-AMC-Awards-Nominations-Video-2026.mp4 Entries Close: 26 July Held annually at the African Marketing Confederation Conference, the AMC Awards stand as the definitive celebration of marketing excellence across the continent. This distinguished platform brings together Africa’s leading minds and boldest work, recognising campaigns and | H50: 1061 | I50: 59 | J50: Warning | K50: 50 | L50: 526 | N50: FALSE | P50: 0 | R50: 0 | T50: 0 | V50: 0 | X50: 0 | Z50: 0 | AD50: Lab | AE50: 100 | AF50: =IFERROR(HYPERLINK("#Technical!A"&MATCH(B50,Technical!A:A,0),"Open Technical"),HYPERLINK("#Technical!A1","Open Technical")) -> Open Technical
A51: WARN 🟡 | B51: https://africanmarketingconfederation.org/awards-2026/ | C51: 200 | D51: Indexable | E51: 0.055 | F51: 2026 AMC Awards – African Marketing Confederation | G51: The African Marketing Confederation presents the 2026 AMC Awards. Submit your nominations to recognise innovative strategies, impact, and marketing results. | H51: 1052 | I51: 59 | J51: Warning | K51: 49 | L51: 156 | N51: FALSE | P51: 0 | R51: 0 | T51: 0 | V51: 0 | X51: 0 | Z51: 0 | AD51: Lab | AE51: 100 | AF51: =IFERROR(HYPERLINK("#Technical!A"&MATCH(B51,Technical!A:A,0),"Open Technical"),HYPERLINK("#Technical!A1","Open Technical")) -> Open Technical
A52: WARN 🟡 | B52: https://africanmarketingconfederation.org/certified-professional-marketer-africa/ | C52: 200 | D52: Indexable | E52: 0.057 | F52: Certified Professional Marketer (Africa) – African Marketing Confederation | G52: Certified Professional Marketer (Africa), CPM(A) The only designation of its kind on the continent - built for Africa, by Africa. Strategic Flexible Uniquely Africa Take your place among Africa’s marketing leaders with the Certified Professional Marketer (Africa) – CPM(A) A prestigious, Pan-African designation offered exclusively through the African Marketing Confederation (AMC).This is not just a | H52: 885 | I52: 59 | J52: Warning | K52: 74 | L52: 400 | N52: FALSE | P52: 0 | R52: 0 | T52: 0 | V52: 0 | X52: 0 | Z52: 0 | AD52: Lab | AE52: 100 | AF52: =IFERROR(HYPERLINK("#Technical!A"&MATCH(B52,Technical!A:A,0),"Open Technical"),HYPERLINK("#Technical!A1","Open Technical")) -> Open Technical
A53: WARN 🟡 | B53: https://africanmarketingconfederation.org/chartered-marketer-africa-final-submission-fee/ | C53: 200 | D53: Indexable | E53: 0.046 | F53: Chartered Marketer (Africa) Final submission fee – African Marketing Confederation | G53: Final Submission Fee Receive a 15% discount on your final submission feeby making payment before 31 August 2024. Add to cart $2190,00 Original price was: $2190,00.$1862,00Current price is: $1862,00. Add to cart | H53: 37 | I53: 66 | J53: Warning | K53: 82 | L53: 210 | N53: FALSE | P53: 0 | R53: 0 | T53: 0 | V53: 0 | X53: 0 | Z53: 0 | AD53: Lab | AE53: 30 | AF53: =IFERROR(HYPERLINK("#Technical!A"&MATCH(B53,Technical!A:A,0),"Open Technical"),HYPERLINK("#Technical!A1","Open Technical")) -> Open Technical
A54: WARN 🟡 | B54: https://africanmarketingconfederation.org/chartered-marketer-africa-programme-fee/ | C54: 200 | D54: Indexable | E54: 0.059 | F54: Chartered Marketer (Africa) Programme fee – African Marketing Confederation | G54: Programme Fee Receive a 15% discount on your programme fee by making payment before 31 August 2024. Add to cart $810,00 Original price was: $810,00.$689,00Current price is: $689,00. Add to cart | H54: 35 | I54: 66 | J54: Warning | K54: 75 | L54: 193 | N54: FALSE | P54: 0 | R54: 0 | T54: 0 | V54: 0 | X54: 0 | Z54: 0 | AD54: Lab | AE54: 30 | AF54: =IFERROR(HYPERLINK("#Technical!A"&MATCH(B54,Technical!A:A,0),"Open Technical"),HYPERLINK("#Technical!A1","Open Technical")) -> Open Technical
... A64: WARN 🟡 | B64: https://africanmarketingconfederation.org/elementor-16548/ | C64: 200 | D64: Indexable | E64: 0.037 | F64: Thank you for registering – African Marketing Confederation | G64: SUBMISSION RECEIVED Thank you for submitting your information! We appreciate your interest in the 2024 AMC Conference and will keep you updated with all the details about the upcoming event. Speakers Programme Awards | H64: 49 | I64: 56 | J64: Warning | K64: 59 | L64: 216 | N64: FALSE | P64: 0 | R64: 0 | T64: 0 | V64: 0 | X64: 0 | Z64: 0 | AD64: Lab | AE64: 30 | AF64: =IFERROR(HYPERLINK("#Technical!A"&MATCH(B64,Technical!A:A,0),"Open Technical"),HYPERLINK("#Technical!A1","Open Technical")) -> Open Technical
A65: WARN 🟡 | B65: https://africanmarketingconfederation.org/elementor-20341/ | C65: 200 | D65: Indexable | E65: 0.036 | F65: Elementor #20341 – African Marketing Confederation | H65: 15 | I65: 46 | J65: Warning | K65: 50 | L65: 0 | N65: FALSE | P65: 0 | R65: 0 | T65: 0 | V65: 0 | X65: 0 | Z65: 0 | AD65: Lab | AE65: 30 | AF65: =IFERROR(HYPERLINK("#Technical!A"&MATCH(B65,Technical!A:A,0),"Open Technical"),HYPERLINK("#Technical!A1","Open Technical")) -> Open Technical
A66: WARN 🟡 | B66: https://africanmarketingconfederation.org/elementor-31820/ | C66: 200 | D66: Indexable | E66: 0.042 | F66: Elementor #31820 – African Marketing Confederation | G66: 2026 TICON Africa Conference In partnership with the ICT Association of Zambia 23-25 September 2026 24-26 September 2026 Livingstone, Zambia Livingstone, Zambia Powering Africa’s Digital Rise Sign Up for Updates Join the TICON Africa Conference 2026 TICON Africa Conference 2026 in Zambia The TICON Africa Conference returns in 2026 for its fourth iteration, this time | H66: 957 | I66: 69 | J66: Warning | K66: 50 | L66: 368 | N66: FALSE | P66: 0 | R66: 0 | T66: 0 | V66: 0 | X66: 0 | Z66: 0 | AD66: Lab | AE66: 100 | AF66: =IFERROR(HYPERLINK("#Technical!A"&MATCH(B66,Technical!A:A,0),"Open Technical"),HYPERLINK("#Technical!A1","Open Technical")) -> Open Technical
A67: WARN 🟡 | B67: https://africanmarketingconfederation.org/general-enquiry-form-thank-you/ | C67: 200 | D67: Indexable | E67: 0.068 | F67: General Enquiry Form – Thank You – African Marketing Confederation | G67: Thank You! Thank you for getting in touch! We appreciate you contacting us. One of our members will be getting back to you soon. | H67: 39 | I67: 56 | J67: Warning | K67: 66 | L67: 128 | N67: FALSE | P67: 0 | R67: 0 | T67: 0 | V67: 0 | X67: 0 | Z67: 0 | AD67: Lab | AE67: 30 | AF67: =IFERROR(HYPERLINK("#Technical!A"&MATCH(B67,Technical!A:A,0),"Open Technical"),HYPERLINK("#Technical!A1","Open Technical")) -> Open Technical
A68: WARN 🟡 | B68: https://africanmarketingconfederation.org/launch-event-2026-amc-conference/ | C68: 200 | D68: Indexable | E68: 0.081 | F68: Launch Event 2026 AMC Conference – African Marketing Confederation | G68: The Official Launch of the 2026 AMC Conference 10:00 CAT (GMT +2) | 16 March 2026 | Live Online from Lusaka 10:00 CAT (GMT +2) 16 March 2026 Live Online from Lusaka The livestream is available for viewing. Click on the link below to watch. Watch the Launch Event Three Conferences. One United Movement. The | H68: 164 | I68: 66 | J68: Warning | K68: 66 | L68: 306 | N68: FALSE | P68: 0 | R68: 0 | T68: 0 | V68: 0 | X68: 0 | Z68: 0 | AD68: Lab | AE68: 30 | AF68: =IFERROR(HYPERLINK("#Technical!A"&MATCH(B68,Technical!A:A,0),"Open Technical"),HYPERLINK("#Technical!A1","Open Technical")) -> Open Technical
A69: WARN 🟡 | B69: https://africanmarketingconfederation.org/members/ | C69: 200 | D69: Indexable | E69: 0.035 | F69: Members – African Marketing Confederation | G69: OUR MEMBERS Marketers Association of Zimbabwe The Marketers Association of Zimbabwe was launched in 2007 with a vision to be a leading body of marketing professionals promoting professionalism of the highest standards and establishing channels of career development for the benefit of organisations and the economy at large. Visit Website IMM Institute, South Africa The | H69: 1707 | I69: 69 | J69: Warning | K69: 41 | L69: 370 | N69: FALSE | P69: 0 | R69: 0 | T69: 0 | V69: 0 | X69: 0 | Z69: 0 | AD69: Lab | AE69: 100 | AF69: =IFERROR(HYPERLINK("#Technical!A"&MATCH(B69,Technical!A:A,0),"Open Technical"),HYPERLINK("#Technical!A1","Open Technical")) -> Open Technical
A70: WARN 🟡 | B70: https://africanmarketingconfederation.org/news-articles/ | C70: 200 | D70: Indexable | E70: 0.062 | F70: News Articles – African Marketing Confederation | G70: AMC Conference Featured Marketing News LATEST news Subscribe Now Free monthly marketing news, articles, events and publication release notifications. Subscribe | H70: 35 | I70: 66 | J70: Warning | K70: 47 | L70: 159 | N70: FALSE | P70: 0 | R70: 0 | T70: 0 | V70: 0 | X70: 0 | Z70: 0 | AD70: Lab | AE70: 100 | AF70: =IFERROR(HYPERLINK("#Technical!A"&MATCH(B70,Technical!A:A,0),"Open Technical"),HYPERLINK("#Technical!A1","Open Technical")) -> Open Technical
A71: WARN 🟡 | B71: https://africanmarketingconfederation.org/privacy-policy/ | C71: 200 | D71: Indexable | E71: 0.044 | F71: Privacy Policy – African Marketing Confederation | G71: Privacy Policy Who we are The ground-breaking African Marketing Confederation (AMC) was founded in 2011 when marketing associations from four African countries met in Livingston, Zambia, to discuss the status and development of the marketing profession across Africa. Collaboration between the various national bodies and associations was deemed to be of the utmost importance in | H71: 611 | I71: 59 | J71: Warning | K71: 48 | L71: 379 | N71: FALSE | P71: 0 | R71: 0 | T71: 0 | V71: 0 | X71: 0 | Z71: 0 | AD71: Lab | AE71: 60 | AF71: =IFERROR(HYPERLINK("#Technical!A"&MATCH(B71,Technical!A:A,0),"Open Technical"),HYPERLINK("#Technical!A1","Open Technical")) -> Open Technical
A72: WARN 🟡 | B72: https://africanmarketingconfederation.org/publication-download-list/ | C72: 200 | D72: Indexable | E72: 0.073 | F72: Publication Download List – African Marketing Confederation | G72: Download All Publications now Click on the publication edition below to download! Edition 1 | 2026 Edition 1 | 2026 Edition 4 | 2025 Edition 4 | 2025 Edition 3 | 2025 Edition 3 | 2025 Edition 2 | 2025 Edition 1 | 2025 Edition 4 | 2024 Edition 3 | 2024 Edition 2 | | H72: 115 | I72: 56 | J72: Warning | K72: 59 | L72: 263 | N72: FALSE | P72: 0 | R72: 0 | T72: 0 | V72: 0 | X72: 0 | Z72: 0 | AD72: Lab | AE72: 30 | AF72: =IFERROR(HYPERLINK("#Technical!A"&MATCH(B72,Technical!A:A,0),"Open Technical"),HYPERLINK("#Technical!A1","Open Technical")) -> Open Technical
A73: WARN 🟡 | B73: https://africanmarketingconfederation.org/publications-2/ | C73: 200 | D73: Indexable | E73: 0.132 | F73: Publications – African Marketing Confederation | G73: Download Strategic Marketing for Africa, the continent's premier marketing publication. Discover the latest industry insights and trends from top experts today. | H73: 97 | I73: 66 | J73: Warning | K73: 46 | L73: 160 | N73: FALSE | P73: 0 | R73: 0 | T73: 0 | V73: 0 | X73: 0 | Z73: 0 | AD73: Lab | AE73: 50 | AF73: =IFERROR(HYPERLINK("#Technical!A"&MATCH(B73,Technical!A:A,0),"Open Technical"),HYPERLINK("#Technical!A1","Open Technical")) -> Open Technical
A74: WARN 🟡 | B74: https://africanmarketingconfederation.org/speakers-2025/ | C74: 200 | D74: Indexable | E74: 0.052 | F74: Our Speakers – 2025 AMC Conference | G74: Discover what to expect from the AMC Conference 2025 speaker lineup, including insightful sessions led by Africa’s brightest marketing minds and thought leaders | H74: 3138 | I74: 59 | J74: Warning | K74: 34 | L74: 160 | N74: FALSE | P74: 0 | R74: 0 | T74: 0 | V74: 0 | X74: 0 | Z74: 0 | AD74: Lab | AE74: 100 | AF74: =IFERROR(HYPERLINK("#Technical!A"&MATCH(B74,Technical!A:A,0),"Open Technical"),HYPERLINK("#Technical!A1","Open Technical")) -> Open Technical
A75: WARN 🟡 | B75: https://africanmarketingconfederation.org/speakers/ | C75: 200 | D75: Indexable | E75: 0.162 | F75: Speakers – African Marketing Confederation | G75: amc relaunch JOIN OUR FIRST ONLINE GATHERING! WATCH RECORDINGS NOW WATCH NOW amc relaunch THANK YOU FOR JOINING OUR FIRST ONLINE GATHERING! WATCH RECORDINGS NOW WATCH NOW speakers Ms Harriet KhatabaThought Leader and Chief Executive Officer, Her Story Matters Mr Gillian RusikeExecutive, African Marketing Confederation Mrs Helen McInteePresident, African Marketing Confederation Dr. Alistair MokoenaCountry Director, | H75: 175 | I75: 56 | J75: Warning | K75: 42 | L75: 417 | N75: FALSE | P75: 0 | R75: 0 | T75: 0 | V75: 0 | X75: 0 | Z75: 0 | AD75: Lab | AE75: 40 | AF75: =IFERROR(HYPERLINK("#Technical!A"&MATCH(B75,Technical!A:A,0),"Open Technical"),HYPERLINK("#Technical!A1","Open Technical")) -> Open Technical
A76: WARN 🟡 | B76: https://africanmarketingconfederation.org/sub-committees/ | C76: 200 | D76: Indexable | E76: 0.082 | F76: Sub Committees – African Marketing Confederation | G76: Sub Committees AMC’s Education and Membership Committee The AMC’s Education and Membership Committee is committed to assisting in the skills enhancement of marketing professionals on the continent, ensuring qualification mobility around the globe. To these ends the Committee is currently focusing on the following projects: The Chartered Marketer (Africa) programme (set to be launched early | H76: 412 | I76: 69 | J76: Warning | K76: 48 | L76: 392 | N76: FALSE | P76: 0 | R76: 0 | T76: 0 | V76: 0 | X76: 0 | Z76: 0 | AD76: Lab | AE76: 30 | AF76: =IFERROR(HYPERLINK("#Technical!A"&MATCH(B76,Technical!A:A,0),"Open Technical"),HYPERLINK("#Technical!A1","Open Technical")) -> Open Technical
A77: WARN 🟡 | B77: https://africanmarketingconfederation.org/subscribe/ | C77: 200 | D77: Indexable | E77: 0.04 | F77: Subscribe – African Marketing Confederation | G77: Subscribe Now Subscribe Name First Last Email Select your CountryAfghanistanAlbaniaAlgeriaAmerican SamoaAndorraAngolaAnguillaAntarcticaAntigua and BarbudaArgentinaArmeniaArubaAustraliaAustriaAzerbaijanBahamasBahrainBangladeshBarbadosBelarusBelgiumBelizeBeninBermudaBhutanBoliviaBonaire, Sint Eustatius and SabaBosnia and HerzegovinaBotswanaBouvet IslandBrazilBritish Indian Ocean TerritoryBrunei DarussalamBulgariaBurkina FasoBurundiCabo VerdeCambodiaCameroonCanadaCayman IslandsCentral African RepublicChadChileChinaChristmas IslandCocos IslandsColombiaComorosCongoCongo, Democratic Republic of theCook IslandsCosta RicaCroatiaCubaCuraçaoCyprusCzechiaCôte d'IvoireDenmarkDjiboutiDominicaDominican RepublicEcuadorEgyptEl SalvadorEquatorial GuineaEritreaEstoniaEswatiniEthiopiaFalkland IslandsFaroe IslandsFijiFinlandFranceFrench GuianaFrench PolynesiaFrench Southern TerritoriesGabonGambiaGeorgiaGermanyGhanaGibraltarGreeceGreenlandGrenadaGuadeloupeGuamGuatemalaGuernseyGuineaGuinea-BissauGuyanaHaitiHeard Island and McDonald IslandsHoly SeeHondurasHong KongHungaryIcelandIndiaIndonesiaIranIraqIrelandIsle of ManIsraelItalyJamaicaJapanJerseyJordanKazakhstanKenyaKiribatiKorea, | H77: 438 | I77: 59 | J77: Warning | K77: 43 | L77: 1176 | N77: FALSE | P77: 0 | R77: 0 | T77: 0 | V77: 0 | X77: 0 | Z77: 0 | AD77: Lab | AE77: 100 | AF77: =IFERROR(HYPERLINK("#Technical!A"&MATCH(B77,Technical!A:A,0),"Open Technical"),HYPERLINK("#Technical!A1","Open Technical")) -> Open Technical
... A86: WARN 🟡 | B86: https://africanmarketingconfederation.org/virtual-programme/ | C86: 200 | D86: Indexable | E86: 0.044 | F86: VIRTUAL PROGRAMME – African Marketing Confederation | G86: AMC Conference 2022 virtual conference programme 23 - 24 March 2022 Navigating Africa's Unique Marketing Mix Conference day 1 Conference day 2 BOOK NOW FOR THE AMC CONFERENCE 2022 BOOK NOW Conference day 1 Wednesday, 23 March 2022 08h30 WELCOME | MC Opening Remarks 08h40 AMC STAKEHOLDER WELCOME 08h55 AFRICA MARKETING BAROMETER | Marketing Trends | H86: 1725 | I86: 59 | J86: Warning | K86: 51 | L86: 347 | N86: FALSE | P86: 0 | R86: 0 | T86: 0 | V86: 0 | X86: 0 | Z86: 0 | AD86: Lab | AE86: 30 | AF86: =IFERROR(HYPERLINK("#Technical!A"&MATCH(B86,Technical!A:A,0),"Open Technical"),HYPERLINK("#Technical!A1","Open Technical")) -> Open Technical

Sheet Technical
A1: URL | B1: Status Code | C1: Status Class | D1: SEO Health Score | E1: Severity Badge | F1: Action Needed | G1: Indexability Reason | H1: TTFB (ms) | I1: Total Request Time (ms) | J1: Final URL | K1: Canonical URL | L1: Canonical Type | M1: Owner | N1: Status | O1: Sprint | P1: Health Icon | Q1: Protocol | R1: Redirect Chain Length | S1: Redirect Target | T1: Redirect Hops | U1: HTTP->HTTPS Redirect | V1: Content-Type | W1: HTTP Version | X1: HTML Size (KB) | Y1: Compression Enabled | Z1: Cache-Control | AA1: ETag | AB1: X-Robots-Tag | AC1: Meta Robots Raw | AD1: Canonical Matches Final URL | AE1: Canonical Absolute URL | AF1: Canonical in Sitemap Match | AG1: Hreflang Present | AH1: Hreflang Count | AI1: Hreflang Self Reference | AJ1: Hreflang Reciprocal Check | AK1: Hreflang Canonical Consistency | AL1: x-default Present | AM1: Pagination rel=next | AN1: Pagination rel=prev | AO1: Last-Modified | AP1: Published Date | AQ1: Modified Date | AR1: Last Updated | AS1: Change Frequency | AT1: Priority | AU1: AI Crawlers Allowed (GPTBot/ClaudeBot/PerplexityBot) | AV1: llms.txt Present | AW1: CWV LCP (s) | AX1: CWV INP (ms) | AY1: CWV CLS | AZ1: CWV Data Source | BA1: Field vs Lab | BB1: Regional Authority Score | BC1: Regional Entity Hits | BD1: Answer Block Detected (First 60 Words) | BE1: AEO Extractability Score | BF1: Critical Issues Count | BG1: Warning Issues Count | BH1: Observation Issues Count | BI1: Inlinks Bucket | BJ1: Important But Underlinked | BK1: SERP Title Truncation Risk | BL1: SERP Meta Truncation Risk | BM1: SERP Title Pixel Approx | BN1: SERP Meta Pixel Approx | BO1: Cannibalization Hint | BP1: Stable Issue IDs | BQ1: URL Depth | BR1: Param URL Flag | BS1: Open in Main | BT1: BACK TO DASHBOARD
A2: https://africanmarketingconfederation.org/amc-conference-sponsors/ | B2: 404 | C2: 4xx | D2: 6 | E2: Critical | F2: Yes | G2: HTTP 404 | H2: 4003.69 | J2: https://africanmarketingconfederation.org/amc-forum-sponsors/ | M2: Server/Host | N2: Open | P2: FAIL 🔴 | Q2: https | R2: 1 | U2: FALSE | V2: text/html; charset=UTF-8 | W2: HTTP/1.1 | Y2: FALSE | AG2: FALSE | AH2: 0 | AI2: FALSE | AL2: FALSE | AM2: FALSE | AN2: FALSE | AR2: 2024-09-18T12:27:33+00:00 | AS2: weekly | AT2: 0.7 | AU2: FALSE | AV2: TRUE | AZ2: Lab | BA2: Lab | BB2: 0 | BC2: 0 | BD2: FALSE | BE2: Low | BF2: 2 | BG2: 2 | BH2: 8 | BI2: 0 | BJ2: TRUE | BK2: FALSE | BL2: FALSE | BM2: 0 | BN2: 0 | BP2: https://africanmarketingconfederation.org/amc-conference-sponsors/::non-200_status | https://africanmarketingconfederation.org/amc-conference-sponsors/::missing_title | https://africanmarketingconfederation.org/amc-conference-sponsors/::missing_meta_description | https://africanmarketingconfederation.org/amc-conference-sponsors/::low_aeo_readiness_score | https://africanmarketingconfederation.org/amc-conference-sponsors/::no_compression_header | https://africanmarketingconfederation.org/amc-conference-sponsors/::no_cache-control_header | https://africanmarketingconfederation.org/amc-conference-sponsors/::no_etag_header | https://africanmarketingconfederation.org/amc-conference-sponsors/::no_question_headings | https://africanmarketingconfederation.org/amc-conference-sponsors/::no_answer-friendly_structure | https://africanmarketingconfederation.org/amc-conference-sponsors/::no_40-60_word_answer_paragraphs | https://africanmarketingconfederation.org/amc-conference-sponsors/::low_regional_authority | https://africanmarketingconfederation.org/amc-conference-sponsors/::ai_crawlers_not_explicitly_allowed | BQ2: 1 | BR2: FALSE | BS2: =IFERROR(HYPERLINK("#Main!A"&MATCH(A2,Main!A:A,0),"Open"),HYPERLINK("#Main!A1","Open")) -> Open
A3: https://africanmarketingconfederation.org/amc-marketing-conference-2024/speakers-2024/ | B3: 404 | C3: 4xx | D3: 6 | E3: Critical | F3: Yes | G3: HTTP 404 | H3: 3907.51 | J3: https://africanmarketingconfederation.org/amc-forum-speakers/ | M3: Server/Host | N3: Open | P3: FAIL 🔴 | Q3: https | R3: 1 | U3: FALSE | V3: text/html; charset=UTF-8 | W3: HTTP/1.1 | Y3: FALSE | AG3: FALSE | AH3: 0 | AI3: FALSE | AL3: FALSE | AM3: FALSE | AN3: FALSE | AR3: 2024-09-18T12:11:23+00:00 | AS3: weekly | AT3: 0.7 | AU3: FALSE | AV3: TRUE | AZ3: Lab | BA3: Lab | BB3: 0 | BC3: 0 | BD3: FALSE | BE3: Low | BF3: 2 | BG3: 2 | BH3: 8 | BI3: 0 | BJ3: TRUE | BK3: FALSE | BL3: FALSE | BM3: 0 | BN3: 0 | BP3: https://africanmarketingconfederation.org/amc-marketing-conference-2024/speakers-2024/::non-200_status | https://africanmarketingconfederation.org/amc-marketing-conference-2024/speakers-2024/::missing_title | https://africanmarketingconfederation.org/amc-marketing-conference-2024/speakers-2024/::missing_meta_description | https://africanmarketingconfederation.org/amc-marketing-conference-2024/speakers-2024/::low_aeo_readiness_score | https://africanmarketingconfederation.org/amc-marketing-conference-2024/speakers-2024/::no_compression_header | https://africanmarketingconfederation.org/amc-marketing-conference-2024/speakers-2024/::no_cache-control_header | https://africanmarketingconfederation.org/amc-marketing-conference-2024/speakers-2024/::no_etag_header | https://africanmarketingconfederation.org/amc-marketing-conference-2024/speakers-2024/::no_question_headings | https://africanmarketingconfederation.org/amc-marketing-conference-2024/speakers-2024/::no_answer-friendly_structure | https://africanmarketingconfederation.org/amc-marketing-conference-2024/speakers-2024/::no_40-60_word_answer_paragraphs | https://africanmarketingconfederation.org/amc-marketing-conference-2024/speakers-2024/::low_regional_authority | https://africanmarketingconfederation.org/amc-marketing-conference-2024/speakers-2024/::ai_crawlers_not_explicitly_allowed | BQ3: 2 | BR3: FALSE | BS3: =IFERROR(HYPERLINK("#Main!A"&MATCH(A3,Main!A:A,0),"Open"),HYPERLINK("#Main!A1","Open")) -> Open
A4: https://africanmarketingconfederation.org/ | B4: 200 | C4: 2xx | D4: 56 | E4: Warning | F4: Yes | G4: Indexable | H4: 511.76 | I4: 753.62 | J4: https://africanmarketingconfederation.org/ | M4: Copy Writer | N4: Open | P4: WARN 🟡 | Q4: https | R4: 0 | U4: FALSE | V4: text/html; charset=UTF-8 | W4: HTTP/1.1 | X4: 530.36 | Y4: FALSE | AG4: FALSE | AH4: 0 | AI4: FALSE | AL4: FALSE | AM4: FALSE | AN4: FALSE | AR4: 2026-04-29T08:23:06+00:00 | AS4: always | AT4: 1 | AU4: FALSE | AV4: TRUE | AZ4: Lab | BA4: Lab | BB4: 100 | BC4: 16 | BD4: FALSE | BE4: Medium | BF4: 0 | BG4: 2 | BH4: 8 | BI4: 0 | BJ4: TRUE | BK4: FALSE | BL4: FALSE | BM4: 475 | BN4: 942 | BP4: https://africanmarketingconfederation.org/::multiple_h1 | https://africanmarketingconfederation.org/::low_aeo_readiness_score | https://africanmarketingconfederation.org/::no_compression_header | https://africanmarketingconfederation.org/::no_cache-control_header | https://africanmarketingconfederation.org/::no_etag_header | https://africanmarketingconfederation.org/::thin_content | https://africanmarketingconfederation.org/::no_question_headings | https://africanmarketingconfederation.org/::no_answer-friendly_structure | https://africanmarketingconfederation.org/::no_40-60_word_answer_paragraphs | https://africanmarketingconfederation.org/::ai_crawlers_not_explicitly_allowed | BQ4: 0 | BR4: FALSE | BS4: =IFERROR(HYPERLINK("#Main!A"&MATCH(A4,Main!A:A,0),"Open"),HYPERLINK("#Main!A1","Open")) -> Open
A5: https://africanmarketingconfederation.org/about-us/ | B5: 200 | C5: 2xx | D5: 66 | E5: Warning | F5: Yes | G5: Indexable | H5: 51.68 | I5: 64.32 | J5: https://africanmarketingconfederation.org/about-us/ | M5: Copy Writer | N5: Open | P5: WARN 🟡 | Q5: https | R5: 0 | U5: FALSE | V5: text/html; charset=UTF-8 | W5: HTTP/1.1 | X5: 306.73 | Y5: FALSE | AG5: FALSE | AH5: 0 | AI5: FALSE | AL5: FALSE | AM5: FALSE | AN5: FALSE | AR5: 2026-04-17T08:53:24+00:00 | AS5: weekly | AT5: 0.7 | AU5: FALSE | AV5: TRUE | AZ5: Lab | BA5: Lab | BB5: 70 | BC5: 5 | BD5: FALSE | BE5: Medium | BF5: 0 | BG5: 1 | BH5: 8 | BI5: 0 | BJ5: TRUE | BK5: FALSE | BL5: FALSE | BM5: 770 | BN5: 2511 | BP5: https://africanmarketingconfederation.org/about-us/::low_aeo_readiness_score | https://africanmarketingconfederation.org/about-us/::no_compression_header | https://africanmarketingconfederation.org/about-us/::no_cache-control_header | https://africanmarketingconfederation.org/about-us/::no_etag_header | https://africanmarketingconfederation.org/about-us/::thin_content | https://africanmarketingconfederation.org/about-us/::no_question_headings | https://africanmarketingconfederation.org/about-us/::no_answer-friendly_structure | https://africanmarketingconfederation.org/about-us/::no_40-60_word_answer_paragraphs | https://africanmarketingconfederation.org/about-us/::ai_crawlers_not_explicitly_allowed | BQ5: 1 | BR5: FALSE | BS5: =IFERROR(HYPERLINK("#Main!A"&MATCH(A5,Main!A:A,0),"Open"),HYPERLINK("#Main!A1","Open")) -> Open
A6: https://africanmarketingconfederation.org/african-marketing-confederation-tourism-chapter/ | B6: 200 | C6: 2xx | D6: 59 | E6: Warning | F6: Yes | G6: Indexable | H6: 120.78 | I6: 132.78 | J6: https://africanmarketingconfederation.org/african-marketing-confederation-tourism-chapter/ | M6: Copy Writer | N6: Open | P6: WARN 🟡 | Q6: https | R6: 0 | U6: FALSE | V6: text/html; charset=UTF-8 | W6: HTTP/1.1 | X6: 318.06 | Y6: FALSE | AG6: FALSE | AH6: 0 | AI6: FALSE | AL6: FALSE | AM6: FALSE | AN6: FALSE | AR6: 2026-04-17T08:55:48+00:00 | AS6: weekly | AT6: 0.7 | AU6: FALSE | AV6: TRUE | AZ6: Lab | BA6: Lab | BB6: 60 | BC6: 4 | BD6: FALSE | BE6: Medium | BF6: 0 | BG6: 2 | BH6: 7 | BI6: 0 | BJ6: TRUE | BK6: FALSE | BL6: FALSE | BM6: 583 | BN6: 2622 | BP6: https://africanmarketingconfederation.org/african-marketing-confederation-tourism-chapter/::multiple_h1 | https://africanmarketingconfederation.org/african-marketing-confederation-tourism-chapter/::low_aeo_readiness_score | https://africanmarketingconfederation.org/african-marketing-confederation-tourism-chapter/::no_compression_header | https://africanmarketingconfederation.org/african-marketing-confederation-tourism-chapter/::no_cache-control_header | https://africanmarketingconfederation.org/african-marketing-confederation-tourism-chapter/::no_etag_header | https://africanmarketingconfederation.org/african-marketing-confederation-tourism-chapter/::no_question_headings | https://africanmarketingconfederation.org/african-marketing-confederation-tourism-chapter/::no_answer-friendly_structure | https://africanmarketingconfederation.org/african-marketing-confederation-tourism-chapter/::no_40-60_word_answer_paragraphs | https://africanmarketingconfederation.org/african-marketing-confederation-tourism-chapter/::ai_crawlers_not_explicitly_allowed | BQ6: 1 | BR6: FALSE | BS6: =IFERROR(HYPERLINK("#Main!A"&MATCH(A6,Main!A:A,0),"Open"),HYPERLINK("#Main!A1","Open")) -> Open
A7: https://africanmarketingconfederation.org/amc-awards-2024/ | B7: 200 | C7: 2xx | D7: 59 | E7: Warning | F7: Yes | G7: Indexable | H7: 50.59 | I7: 115.56 | J7: https://africanmarketingconfederation.org/amc-awards-2024/ | M7: Copy Writer | N7: Open | P7: WARN 🟡 | Q7: https | R7: 0 | U7: FALSE | V7: text/html; charset=UTF-8 | W7: HTTP/1.1 | X7: 481.16 | Y7: FALSE | AG7: FALSE | AH7: 0 | AI7: FALSE | AL7: FALSE | AM7: FALSE | AN7: FALSE | AR7: 2025-04-24T13:54:46+00:00 | AS7: weekly | AT7: 0.7 | AU7: FALSE | AV7: TRUE | AZ7: Lab | BA7: Lab | BB7: 100 | BC7: 16 | BD7: TRUE | BE7: Medium | BF7: 0 | BG7: 2 | BH7: 7 | BI7: 0 | BJ7: TRUE | BK7: FALSE | BL7: FALSE | BM7: 352 | BN7: 2517 | BP7: https://africanmarketingconfederation.org/amc-awards-2024/::multiple_h1 | https://africanmarketingconfederation.org/amc-awards-2024/::low_aeo_readiness_score | https://africanmarketingconfederation.org/amc-awards-2024/::no_compression_header | https://africanmarketingconfederation.org/amc-awards-2024/::no_cache-control_header | https://africanmarketingconfederation.org/amc-awards-2024/::no_etag_header | https://africanmarketingconfederation.org/amc-awards-2024/::no_question_headings | https://africanmarketingconfederation.org/amc-awards-2024/::no_answer-friendly_structure | https://africanmarketingconfederation.org/amc-awards-2024/::no_40-60_word_answer_paragraphs | https://africanmarketingconfederation.org/amc-awards-2024/::ai_crawlers_not_explicitly_allowed | BQ7: 1 | BR7: FALSE | BS7: =IFERROR(HYPERLINK("#Main!A"&MATCH(A7,Main!A:A,0),"Open"),HYPERLINK("#Main!A1","Open")) -> Open
A8: https://africanmarketingconfederation.org/amc-conference-2022-prospectus/ | B8: 200 | C8: 2xx | D8: 56 | E8: Warning | F8: Yes | G8: Indexable | H8: 34.66 | I8: 46.66 | J8: https://africanmarketingconfederation.org/amc-conference-2022-prospectus/ | M8: Copy Writer | N8: Open | P8: WARN 🟡 | Q8: https | R8: 0 | U8: FALSE | V8: text/html; charset=UTF-8 | W8: HTTP/1.1 | X8: 264.53 | Y8: FALSE | AG8: FALSE | AH8: 0 | AI8: FALSE | AL8: FALSE | AM8: FALSE | AN8: FALSE | AR8: 2025-07-14T07:22:03+00:00 | AS8: weekly | AT8: 0.7 | AU8: FALSE | AV8: TRUE | AZ8: Lab | BA8: Lab | BB8: 30 | BC8: 3 | BD8: FALSE | BE8: Medium | BF8: 0 | BG8: 2 | BH8: 8 | BI8: 0 | BJ8: TRUE | BK8: FALSE | BL8: FALSE | BM8: 475 | BN8: 2077 | BP8: https://africanmarketingconfederation.org/amc-conference-2022-prospectus/::missing_h1 | https://africanmarketingconfederation.org/amc-conference-2022-prospectus/::low_aeo_readiness_score | https://africanmarketingconfederation.org/amc-conference-2022-prospectus/::no_compression_header | https://africanmarketingconfederation.org/amc-conference-2022-prospectus/::no_cache-control_header | https://africanmarketingconfederation.org/amc-conference-2022-prospectus/::no_etag_header | https://africanmarketingconfederation.org/amc-conference-2022-prospectus/::thin_content | https://africanmarketingconfederation.org/amc-conference-2022-prospectus/::no_question_headings | https://africanmarketingconfederation.org/amc-conference-2022-prospectus/::no_answer-friendly_structure | https://africanmarketingconfederation.org/amc-conference-2022-prospectus/::no_40-60_word_answer_paragraphs | https://africanmarketingconfederation.org/amc-conference-2022-prospectus/::ai_crawlers_not_explicitly_allowed | BQ8: 1 | BR8: FALSE | BS8: =IFERROR(HYPERLINK("#Main!A"&MATCH(A8,Main!A:A,0),"Open"),HYPERLINK("#Main!A1","Open")) -> Open
A9: https://africanmarketingconfederation.org/amc-conference-2022-thank-you/ | B9: 200 | C9: 2xx | D9: 59 | E9: Warning | F9: Yes | G9: Indexable | H9: 40.13 | I9: 55.8 | J9: https://africanmarketingconfederation.org/amc-conference-2022-thank-you/ | M9: Copy Writer | N9: Open | P9: WARN 🟡 | Q9: https | R9: 0 | U9: FALSE | V9: text/html; charset=UTF-8 | W9: HTTP/1.1 | X9: 329.21 | Y9: FALSE | AG9: FALSE | AH9: 0 | AI9: FALSE | AL9: FALSE | AM9: FALSE | AN9: FALSE | AR9: 2021-11-26T08:41:00+00:00 | AS9: weekly | AT9: 0.7 | AU9: FALSE | AV9: TRUE | AZ9: Lab | BA9: Lab | BB9: 100 | BC9: 8 | BD9: FALSE | BE9: Medium | BF9: 0 | BG9: 2 | BH9: 7 | BI9: 0 | BJ9: TRUE | BK9: FALSE | BL9: FALSE | BM9: 468 | BN9: 2089 | BP9: https://africanmarketingconfederation.org/amc-conference-2022-thank-you/::missing_h1 | https://africanmarketingconfederation.org/amc-conference-2022-thank-you/::low_aeo_readiness_score | https://africanmarketingconfederation.org/amc-conference-2022-thank-you/::no_compression_header | https://africanmarketingconfederation.org/amc-conference-2022-thank-you/::no_cache-control_header | https://africanmarketingconfederation.org/amc-conference-2022-thank-you/::no_etag_header | https://africanmarketingconfederation.org/amc-conference-2022-thank-you/::no_question_headings | https://africanmarketingconfederation.org/amc-conference-2022-thank-you/::no_answer-friendly_structure | https://africanmarketingconfederation.org/amc-conference-2022-thank-you/::no_40-60_word_answer_paragraphs | https://africanmarketingconfederation.org/amc-conference-2022-thank-you/::ai_crawlers_not_explicitly_allowed | BQ9: 1 | BR9: FALSE | BS9: =IFERROR(HYPERLINK("#Main!A"&MATCH(A9,Main!A:A,0),"Open"),HYPERLINK("#Main!A1","Open")) -> Open
A10: https://africanmarketingconfederation.org/amc-conference-2022/ | B10: 200 | C10: 2xx | D10: 56 | E10: Warning | F10: Yes | G10: Indexable | H10: 40 | I10: 52 | J10: https://africanmarketingconfederation.org/amc-conference-2022/ | M10: Copy Writer | N10: Open | P10: WARN 🟡 | Q10: https | R10: 0 | U10: FALSE | V10: text/html; charset=UTF-8 | W10: HTTP/1.1 | X10: 324.66 | Y10: FALSE | AG10: FALSE | AH10: 0 | AI10: FALSE | AL10: FALSE | AM10: FALSE | AN10: FALSE | AR10: 2026-01-21T00:07:32+00:00 | AS10: weekly | AT10: 0.7 | AU10: FALSE | AV10: TRUE | AZ10: Lab | BA10: Lab | BB10: 100 | BC10: 9 | BD10: FALSE | BE10: Medium | BF10: 0 | BG10: 2 | BH10: 8 | BI10: 0 | BJ10: TRUE | BK10: FALSE | BL10: FALSE | BM10: 381 | BN10: 2399 | BP10: https://africanmarketingconfederation.org/amc-conference-2022/::missing_h1 | https://africanmarketingconfederation.org/amc-conference-2022/::low_aeo_readiness_score | https://africanmarketingconfederation.org/amc-conference-2022/::no_compression_header | https://africanmarketingconfederation.org/amc-conference-2022/::no_cache-control_header | https://africanmarketingconfederation.org/amc-conference-2022/::no_etag_header | https://africanmarketingconfederation.org/amc-conference-2022/::thin_content | https://africanmarketingconfederation.org/amc-conference-2022/::no_question_headings | https://africanmarketingconfederation.org/amc-conference-2022/::no_answer-friendly_structure | https://africanmarketingconfederation.org/amc-conference-2022/::no_40-60_word_answer_paragraphs | https://africanmarketingconfederation.org/amc-conference-2022/::ai_crawlers_not_explicitly_allowed | BQ10: 1 | BR10: FALSE | BS10: =IFERROR(HYPERLINK("#Main!A"&MATCH(A10,Main!A:A,0),"Open"),HYPERLINK("#Main!A1","Open")) -> Open
A11: https://africanmarketingconfederation.org/amc-conference-2023/ | B11: 200 | C11: 2xx | D11: 69 | E11: Warning | F11: Yes | G11: Indexable | H11: 53.43 | I11: 74.47 | J11: https://africanmarketingconfederation.org/amc-conference-2023/ | M11: Copy Writer | N11: Open | P11: WARN 🟡 | Q11: https | R11: 0 | U11: FALSE | V11: text/html; charset=UTF-8 | W11: HTTP/1.1 | X11: 360.09 | Y11: FALSE | AG11: FALSE | AH11: 0 | AI11: FALSE | AL11: FALSE | AM11: FALSE | AN11: FALSE | AR11: 2025-03-03T07:59:34+00:00 | AS11: weekly | AT11: 0.7 | AU11: FALSE | AV11: TRUE | AZ11: Lab | BA11: Lab | BB11: 80 | BC11: 6 | BD11: FALSE | BE11: Medium | BF11: 0 | BG11: 1 | BH11: 7 | BI11: 0 | BJ11: TRUE | BK11: FALSE | BL11: FALSE | BM11: 381 | BN11: 2467 | BP11: https://africanmarketingconfederation.org/amc-conference-2023/::low_aeo_readiness_score | https://africanmarketingconfederation.org/amc-conference-2023/::no_compression_header | https://africanmarketingconfederation.org/amc-conference-2023/::no_cache-control_header | https://africanmarketingconfederation.org/amc-conference-2023/::no_etag_header | https://africanmarketingconfederation.org/amc-conference-2023/::no_question_headings | https://africanmarketingconfederation.org/amc-conference-2023/::no_answer-friendly_structure | https://africanmarketingconfederation.org/amc-conference-2023/::no_40-60_word_answer_paragraphs | https://africanmarketingconfederation.org/amc-conference-2023/::ai_crawlers_not_explicitly_allowed | BQ11: 1 | BR11: FALSE | BS11: =IFERROR(HYPERLINK("#Main!A"&MATCH(A11,Main!A:A,0),"Open"),HYPERLINK("#Main!A1","Open")) -> Open
