Workbook

Sheet Table of Contents
A1: Table of Contents
A2: Section | B2: Open | C2: Description
A3: =HYPERLINK("#'Dashboard'!A1","Dashboard") -> Dashboard | B3: =HYPERLINK("#'Dashboard'!A1","Open") -> Open | C3: Executive overview of site-wide SEO performance and critical alerts.
A4: =HYPERLINK("#'Content Optimisation Hub'!A1","Content Optimisation Hub") -> Content Optimisation Hub | B4: =HYPERLINK("#'Content Optimisation Hub'!A1","Open") -> Open | C4: Diagnostic command center: live title, meta, and H1–H6 health plus on-page score.
A5: =HYPERLINK("#'FixPlan'!A1","FixPlan") -> FixPlan | B5: =HYPERLINK("#'FixPlan'!A1","Open") -> Open | C5: Prioritized list of technical and content fixes with estimated effort.
A6: =HYPERLINK("#'Main'!A1","Main") -> Main | B6: =HYPERLINK("#'Main'!A1","Open") -> Open | C6: Primary URL inventory with titles, meta descriptions, and crawl signals.
A7: =HYPERLINK("#'Priority URLs'!A1","Priority URLs") -> Priority URLs | B7: =HYPERLINK("#'Priority URLs'!A1","Open") -> Open | C7: High-value pages requiring immediate attention based on business risk.
A8: =HYPERLINK("#'AIOSEO'!A1","AIOSEO") -> AIOSEO | B8: =HYPERLINK("#'AIOSEO'!A1","Open") -> Open | C8: Plugin-aligned recommendations and edit links for AIOSEO users.
A9: =HYPERLINK("#'SitemapQA'!A1","SitemapQA") -> SitemapQA | B9: =HYPERLINK("#'SitemapQA'!A1","Open") -> Open | C9: Sitemap coverage, URL membership checks, and sitemap metadata QA.
A10: =HYPERLINK("#'ResolvedIssues'!A1","ResolvedIssues") -> ResolvedIssues | B10: =HYPERLINK("#'ResolvedIssues'!A1","Open") -> Open | C10: Issues marked resolved when compared to the previous export.
A11: =HYPERLINK("#'DeltaFromPreviousRun'!A1","DeltaFromPreviousRun") -> DeltaFromPreviousRun | B11: =HYPERLINK("#'DeltaFromPreviousRun'!A1","Open") -> Open | C11: New, fixed, and persistent issues compared to a prior audit workbook.
A12: =HYPERLINK("#'RunMetadata'!A1","RunMetadata") -> RunMetadata | B12: =HYPERLINK("#'RunMetadata'!A1","Open") -> Open | C12: Run configuration, timestamps, and environment notes.
A13: =HYPERLINK("#'Issue Register'!A1","Issue Register") -> Issue Register | B13: =HYPERLINK("#'Issue Register'!A1","Open") -> Open | C13: Diagnostic metrics for Issue Register.
A14: =HYPERLINK("#'Technical Diagnostics'!A1","Technical Diagnostics") -> Technical Diagnostics | B14: =HYPERLINK("#'Technical Diagnostics'!A1","Open") -> Open | C14: Diagnostic metrics for Technical Diagnostics.
A15: =HYPERLINK("#'Content & AI Readiness'!A1","Content & AI Readiness") -> Content & AI Readiness | B15: =HYPERLINK("#'Content & AI Readiness'!A1","Open") -> Open | C15: Diagnostic metrics for Content & AI Readiness.
A16: =HYPERLINK("#'Link Intelligence'!A1","Link Intelligence") -> Link Intelligence | B16: =HYPERLINK("#'Link Intelligence'!A1","Open") -> Open | C16: Diagnostic metrics for Link Intelligence.
A17: =HYPERLINK("#'Template & Duplication Risks'!A1","Template & Duplication Risks") -> Template & Duplication Risks | B17: =HYPERLINK("#'Template & Duplication Risks'!A1","Open") -> Open | C17: Diagnostic metrics for Template & Duplication Risks.
A18: =HYPERLINK("#'Playbook'!A1","Playbook") -> Playbook | B18: =HYPERLINK("#'Playbook'!A1","Open") -> Open | C18: Diagnostic metrics for Playbook.

Sheet Dashboard
A1: Executive SEO & AEO Performance Report
A2: Executive SEO & AEO Dashboard
A4: EXECUTIVE METRICS | B4: Value | D4: Status | E4: Count | G4: Traditional SEO vs. 2026 AEO Readiness | I4: BUSINESS IMPACT SUMMARY | M4: PRIORITY SNAPSHOT | N4: Value
A5: =HYPERLINK("#'Main'!A1","Total URLs") -> Total URLs | B5: 10 | D5: 200 OK | E5: 0 | G5: Dimension | H5: Score | I5: 0 URLs returned error responses (0 4xx / 0 5xx). Critical issue volume is 0 URLs and warning volume is 0. Primary blocker: No ETag Header affecting 10 URLs. | M5: Primary blocking issue | N5: No ETag Header
A6: =HYPERLINK("#'Technical Diagnostics'!A1","Overall Health Score") -> Overall Health Score | B6: =IFERROR(AVERAGE('Technical Diagnostics'!$E:$E)/100,0) -> 0.62 | D6: 3xx Redirects | E6: 0 | G6: Traditional SEO | H6: 0 | M6: Top Issue Affected URLs | N6: 10
A7: =HYPERLINK("#'Technical Diagnostics'!A1","SEO Pass Rate %") -> SEO Pass Rate % | B7: =IFERROR(COUNTIFS('Technical Diagnostics'!$F:$F,"Pass")/(COUNTA('Technical Diagnostics'!$A:$A)-1),0) -> 0 | D7: 4xx Errors | E7: 0 | G7: 2026 AEO Readiness | H7: 0 | M7: 4xx/5xx URLs | N7: 0
A8: =HYPERLINK("#'Technical Diagnostics'!A1","Pass URLs") -> Pass URLs | B8: =COUNTIFS('Technical Diagnostics'!$F:$F,"Pass") -> 0 | D8: 5xx Errors | E8: 0 | M8: Avg TTFB (ms) | N8: 0
A9: =HYPERLINK("#'Priority URLs'!A1","Critical URLs") -> Critical URLs | B9: =COUNTIFS('Technical Diagnostics'!$D:$D,"Critical") -> 0 | D9: Other | E9: 0 | G9: Strategic Narrative
A10: =HYPERLINK("#'Technical Diagnostics'!A1","Warning URLs") -> Warning URLs | B10: =COUNTIFS('Technical Diagnostics'!$D:$D,"Warning")+COUNTIFS('Technical Diagnostics'!$D:$D,"Needs Work") -> 10 | G10: SEO and AEO signals are moving together; continue balancing crawl health with answer-first content.
A11: =HYPERLINK("#'Technical Diagnostics'!A1","Error Rate % (4xx/5xx)") -> Error Rate % (4xx/5xx) | B11: =IFERROR((COUNTIFS('Technical Diagnostics'!$C:$C,">=400",'Technical Diagnostics'!$C:$C,"<500")+COUNTIFS('Technical Diagnostics'!$C:$C,">=500",'Technical Diagnostics'!$C:$C,"<600"))/COUNTIFS('Technical Diagnostics'!$C:$C,">0"),0) -> 0
A12: =HYPERLINK("#'Technical Diagnostics'!A1","Crawl Success Rate % (2xx)") -> Crawl Success Rate % (2xx) | B12: =IFERROR(COUNTIFS('Technical Diagnostics'!$C:$C,">=200",'Technical Diagnostics'!$C:$C,"<300")/COUNTIFS('Technical Diagnostics'!$C:$C,">0"),0) -> 1 | D12: Severity | E12: Count | I12: Quick Navigation | J12: Open
A13: =HYPERLINK("#'Technical Diagnostics'!A1","Critical URL Rate %") -> Critical URL Rate % | B13: =IFERROR(B9/(COUNTA('Technical Diagnostics'!$A:$A)-1),0) -> 0 | D13: Critical | E13: 7 | I13: Fix Plan | J13: =HYPERLINK("#FixPlan!A1","Open") -> Open
A14: =HYPERLINK("#'Technical Diagnostics'!A1","Warning URL Rate %") -> Warning URL Rate % | B14: =IFERROR(B10/(COUNTA('Technical Diagnostics'!$A:$A)-1),0) -> 1 | D14: Warning | E14: 12 | G14: TOP ISSUES TO FIX FIRST | H14: Affected URLs | I14: Main URL Data | J14: =HYPERLINK("#Main!A1","Open") -> Open
A15: Projected Health Score % (if all To Do done) | B15: =MIN(1,B6+(1-B6)*IFERROR(COUNTIFS('Issue Register'!$J:$J,"Open")/(COUNTA('Technical Diagnostics'!$A:$A)-1),0)*0.9) -> 1 | D15: Medium | E15: 0 | G15: =HYPERLINK("#FixPlan!A8","Low AEO Readiness Score") -> Low AEO Readiness Score | H15: 10 | I15: Technical Diagnostics | J15: =HYPERLINK("#'Technical Diagnostics'!A1","Open") -> Open
A16: Projected Pass Rate % (if all To Do done) | B16: =MIN(1,B7+(1-B7)*IFERROR(COUNTIFS('Issue Register'!$J:$J,"Open")/(COUNTA('Technical Diagnostics'!$A:$A)-1),0)*0.85) -> 1 | D16: Low | E16: 15 | G16: =HYPERLINK("#FixPlan!A7","Low Image Alt Coverage") -> Low Image Alt Coverage | H16: 10 | I16: Indexability | J16: =HYPERLINK("#'Technical Diagnostics'!A1","Open") -> Open
A17: =HYPERLINK("#'Content Optimisation Hub'!A1","Content Hub Readiness (%)") -> Content Hub Readiness (%) | B17: =IFERROR(COUNTIF('Content Optimisation Hub'!C:C,"Complete")/(COUNTA('Content Optimisation Hub'!F:F)-1),0) -> 0 | G17: =HYPERLINK("#FixPlan!A6","AI Crawlers Not Explicitly Allowed") -> AI Crawlers Not Explicitly Allowed | H17: 10 | I17: AEO Opportunities | J17: =HYPERLINK("#'Content & AI Readiness'!A1","Open") -> Open
A18: =HYPERLINK("#'Content & AI Readiness'!A1","URLs with Schema") -> URLs with Schema | B18: =COUNTIFS('Content & AI Readiness'!$K:$K,">0") -> 0 | G18: =HYPERLINK("#FixPlan!A5","No 40-60 Word Answer Paragraphs") -> No 40-60 Word Answer Paragraphs | H18: 10 | I18: AIOSEO Action Queue | J18: =HYPERLINK("#AIOSEO!A1","Open") -> Open
A19: =HYPERLINK("#'Link Intelligence'!A1","Broken Internal Links") -> Broken Internal Links | B19: =SUMIFS('Link Intelligence'!$H:$H,'Link Intelligence'!$B:$B,"Summary") -> 0 | G19: =HYPERLINK("#FixPlan!A4","No Answer-Friendly Structure") -> No Answer-Friendly Structure | H19: 10
G22: OWNER ISSUE SUMMARY
G23: Owner | H23: Issue Rows | I23: Affected URLs | J23: Critical | K23: Warning
G24: =HYPERLINK("#'FixPlan'!A1","Copy Writer") -> Copy Writer | H24: 20 | I24: 74 | J24: 1 | K24: 8
G25: =HYPERLINK("#'FixPlan'!A1","Server/Host") -> Server/Host | H25: 5 | I25: 10 | J25: 2 | K25: 0
G26: =HYPERLINK("#'FixPlan'!A1","Dev") -> Dev | H26: 9 | I26: 0 | J26: 4 | K26: 4

Sheet FixPlan
A1: Issue Type | B1: Severity | C1: Priority Score | D1: Affected Count | E1: Affected URLs | F1: Detail Reference Tab | G1: Resolution Type | H1: URL | I1: Recommended Fix | J1: Likely Root Cause | K1: Owner | L1: Agency Owner | M1: Effort | N1: Est. Hours | O1: Est. Sprint Points | P1: Aging/Priority | Q1: Status | R1: Verified By | S1: Date Resolved | T1: Revenue Risk | U1: Action Needed | V1: Jump to Details | W1: Sprint | X1: Category | Y1: Open in Main | Z1: Hub Status (Content Hub) | AA1: BACK TO DASHBOARD
A2: Non-200 Status | B2: Critical | C2: 105 | D2: 0 | F2: Technical Diagnostics | G2: Manual Content | I2: Fix status code, restore page, or implement correct redirect to canonical destination. | J2: URL returns 4xx/5xx or equivalent failure. | K2: Server/Host | L2: Server/Host | M2: M | N2: 10 | O2: 5 | P2: Immediate (Current Sprint) | Q2: To Do | T2: High Risk | U2: Yes | V2: Open in Main Tab | X2: SEO | Y2: =IFERROR(HYPERLINK("#'Main'!B"&MATCH(TRIM(H2),Main!B:B,0),"Open"),HYPERLINK("#'Main'!B1","Open")) -> Open | Z2: =IFERROR(INDEX('Content Optimisation Hub'!C:C,MATCH(H2,'Content Optimisation Hub'!F:F,0)),"Not in Hub") -> Not in Hub
A3: Missing Title | B3: Critical | C3: 105 | D3: 0 | F3: Technical Diagnostics | G3: Manual Content | I3: Add unique descriptive title on affected template/page type. | J3: Template/page missing title tag. | K3: Copy Writer | L3: Copy Writer | M3: M | N3: 10 | O3: 5 | P3: Immediate (Current Sprint) | Q3: To Do | T3: High Risk | U3: Yes | V3: Open in Main Tab | X3: SEO | Y3: =IFERROR(HYPERLINK("#'Main'!B"&MATCH(TRIM(H3),Main!B:B,0),"Open"),HYPERLINK("#'Main'!B1","Open")) -> Open | Z3: =IFERROR(INDEX('Content Optimisation Hub'!C:C,MATCH(H3,'Content Optimisation Hub'!F:F,0)),"Not in Hub") -> Not in Hub
A4: Noindex Directive | B4: Critical | C4: 105 | D4: 0 | F4: Technical Diagnostics | G4: Manual Content | I4: Remove unintended noindex directives on index-worthy URLs. | J4: Meta robots or X-Robots-Tag contains noindex. | K4: Dev | L4: Dev | M4: M | N4: 10 | O4: 5 | P4: Immediate (Current Sprint) | Q4: To Do | T4: High Risk | U4: Yes | V4: Open in Main Tab | X4: SEO | Y4: =IFERROR(HYPERLINK("#'Main'!B"&MATCH(TRIM(H4),Main!B:B,0),"Open"),HYPERLINK("#'Main'!B1","Open")) -> Open | Z4: =IFERROR(INDEX('Content Optimisation Hub'!C:C,MATCH(H4,'Content Optimisation Hub'!F:F,0)),"Not in Hub") -> Not in Hub
A5: Canonical Points Elsewhere | B5: Critical | C5: 105 | D5: 0 | F5: Technical Diagnostics | G5: Global Template | I5: Align canonical to preferred final URL and ensure internal links use canonical target. | J5: Canonical targets a different URL variant. | K5: Dev | L5: Dev | M5: M | N5: 10 | O5: 5 | P5: Immediate (Current Sprint) | Q5: To Do | T5: High Risk | U5: Yes | V5: Open in Main Tab | X5: SEO | Y5: =IFERROR(HYPERLINK("#'Main'!B"&MATCH(TRIM(H5),Main!B:B,0),"Open"),HYPERLINK("#'Main'!B1","Open")) -> Open | Z5: =IFERROR(INDEX('Content Optimisation Hub'!C:C,MATCH(H5,'Content Optimisation Hub'!F:F,0)),"Not in Hub") -> Not in Hub
A6: Robots.txt Disallow Root | B6: Critical | C6: 105 | D6: 0 | F6: Technical Diagnostics | G6: Global Template | I6: Apply fix based on issue type and re-run audit. | J6: Template/technical implementation quality issue. | K6: Server/Host | L6: Server/Host | M6: M | N6: 10 | O6: 5 | P6: Immediate (Current Sprint) | Q6: To Do | T6: High Risk | U6: Yes | V6: Open in Main Tab | X6: SEO | Y6: =IFERROR(HYPERLINK("#'Main'!B"&MATCH(TRIM(H6),Main!B:B,0),"Open"),HYPERLINK("#'Main'!B1","Open")) -> Open | Z6: =IFERROR(INDEX('Content Optimisation Hub'!C:C,MATCH(H6,'Content Optimisation Hub'!F:F,0)),"Not in Hub") -> Not in Hub
A7: CWV LCP Above 4.0s | B7: Critical | C7: 105 | D7: 0 | F7: Technical Diagnostics | G7: Global Template | I7: Apply fix based on issue type and re-run audit. | J7: Template/technical implementation quality issue. | K7: Dev | L7: Dev | M7: M | N7: 10 | O7: 5 | P7: Immediate (Current Sprint) | Q7: To Do | T7: High Risk | U7: Yes | V7: Open in Main Tab | X7: SEO | Y7: =IFERROR(HYPERLINK("#'Main'!B"&MATCH(TRIM(H7),Main!B:B,0),"Open"),HYPERLINK("#'Main'!B1","Open")) -> Open | Z7: =IFERROR(INDEX('Content Optimisation Hub'!C:C,MATCH(H7,'Content Optimisation Hub'!F:F,0)),"Not in Hub") -> Not in Hub
A8: Broken Internal Links | B8: Critical | C8: 105 | D8: 0 | F8: Link Intelligence | G8: Manual Content | I8: Update internal links to valid URLs and remove dead references. | J8: Internal links resolve to missing or error pages. | K8: Dev | L8: Dev | M8: M | N8: 10 | O8: 5 | P8: Immediate (Current Sprint) | Q8: To Do | T8: High Risk | U8: Yes | V8: Open in Main Tab | X8: SEO | Y8: =IFERROR(HYPERLINK("#'Main'!B"&MATCH(TRIM(H8),Main!B:B,0),"Open"),HYPERLINK("#'Main'!B1","Open")) -> Open | Z8: =IFERROR(INDEX('Content Optimisation Hub'!C:C,MATCH(H8,'Content Optimisation Hub'!F:F,0)),"Not in Hub") -> Not in Hub
A9: Redirect Chains | B9: Warning | C9: 67 | D9: 0 | F9: Technical Diagnostics | G9: Global Template | I9: Apply fix based on issue type and re-run audit. | J9: Template/technical implementation quality issue. | K9: Dev | L9: Dev | M9: S | N9: 4 | O9: 2 | P9: Next Sprint | Q9: To Do | T9: Medium Risk | U9: Yes | V9: Open in Main Tab | X9: SEO | Y9: =IFERROR(HYPERLINK("#'Main'!B"&MATCH(TRIM(H9),Main!B:B,0),"Open"),HYPERLINK("#'Main'!B1","Open")) -> Open | Z9: =IFERROR(INDEX('Content Optimisation Hub'!C:C,MATCH(H9,'Content Optimisation Hub'!F:F,0)),"Not in Hub") -> Not in Hub
A10: CWV LCP Needs Improvement (2.5-4.0s) | B10: Warning | C10: 67 | D10: 0 | F10: Technical Diagnostics | G10: Global Template | I10: Apply fix based on issue type and re-run audit. | J10: Template/technical implementation quality issue. | K10: Copy Writer | L10: Copy Writer | M10: S | N10: 4 | O10: 2 | P10: Next Sprint | Q10: To Do | T10: Medium Risk | U10: Yes | V10: Open in Main Tab | X10: SEO | Y10: =IFERROR(HYPERLINK("#'Main'!B"&MATCH(TRIM(H10),Main!B:B,0),"Open"),HYPERLINK("#'Main'!B1","Open")) -> Open | Z10: =IFERROR(INDEX('Content Optimisation Hub'!C:C,MATCH(H10,'Content Optimisation Hub'!F:F,0)),"Not in Hub") -> Not in Hub
A11: Missing FAQ/QA Schema | B11: Warning | C11: 67 | D11: 0 | F11: Content & AI Readiness | G11: Global Template | I11: Add valid FAQPage or QAPage JSON-LD where appropriate and ensure on-page parity. | J11: No FAQPage/QAPage schema found for likely Q&A style content. | K11: Dev | L11: Dev | M11: S | N11: 4 | O11: 2 | P11: Next Sprint | Q11: To Do | T11: Medium Risk | U11: Yes | V11: Open in Main Tab | X11: AEO | Y11: =IFERROR(HYPERLINK("#'Main'!B"&MATCH(TRIM(H11),Main!B:B,0),"Open"),HYPERLINK("#'Main'!B1","Open")) -> Open | Z11: =IFERROR(INDEX('Content Optimisation Hub'!C:C,MATCH(H11,'Content Optimisation Hub'!F:F,0)),"Not in Hub") -> Not in Hub
A12: Deep URL (>3 clicks) | B12: Warning | C12: 67 | D12: 0 | F12: Technical Diagnostics | G12: Manual Content | I12: Apply fix based on issue type and re-run audit. | J12: Template/technical implementation quality issue. | K12: Copy Writer | L12: Copy Writer | M12: S | N12: 4 | O12: 2 | P12: Next Sprint | Q12: To Do | T12: Medium Risk | U12: Yes | V12: Open in Main Tab | X12: SEO | Y12: =IFERROR(HYPERLINK("#'Main'!B"&MATCH(TRIM(H12),Main!B:B,0),"Open"),HYPERLINK("#'Main'!B1","Open")) -> Open | Z12: =IFERROR(INDEX('Content Optimisation Hub'!C:C,MATCH(H12,'Content Optimisation Hub'!F:F,0)),"Not in Hub") -> Not in Hub
A13: Mixed Content | B13: Warning | C13: 67 | D13: 0 | F13: Technical Diagnostics | G13: Manual Content | I13: Serve all assets over HTTPS and update hardcoded URLs. | J13: HTTPS page references insecure HTTP assets. | K13: Dev | L13: Dev | M13: S | N13: 4 | O13: 2 | P13: Next Sprint | Q13: To Do | T13: Medium Risk | U13: Yes | V13: Open in Main Tab | X13: SEO | Y13: =IFERROR(HYPERLINK("#'Main'!B"&MATCH(TRIM(H13),Main!B:B,0),"Open"),HYPERLINK("#'Main'!B1","Open")) -> Open | Z13: =IFERROR(INDEX('Content Optimisation Hub'!C:C,MATCH(H13,'Content Optimisation Hub'!F:F,0)),"Not in Hub") -> Not in Hub
... A15: Hreflang Without Reciprocity | B15: Warning | C15: 67 | D15: 0 | F15: Technical Diagnostics | G15: Manual Content | I15: Apply fix based on issue type and re-run audit. | J15: Template/technical implementation quality issue. | K15: Copy Writer | L15: Copy Writer | M15: S | N15: 4 | O15: 2 | P15: Next Sprint | Q15: To Do | T15: Medium Risk | U15: Yes | V15: Open in Main Tab | X15: SEO | Y15: =IFERROR(HYPERLINK("#'Main'!B"&MATCH(TRIM(H15),Main!B:B,0),"Open"),HYPERLINK("#'Main'!B1","Open")) -> Open | Z15: =IFERROR(INDEX('Content Optimisation Hub'!C:C,MATCH(H15,'Content Optimisation Hub'!F:F,0)),"Not in Hub") -> Not in Hub
A16: Low Image Alt Coverage | B16: Warning | C16: 67 | D16: 10 | E16: https://africanmarketingconfederation.org/amc-awards-2024 https://africanmarketingconfederation.org/african-marketing-confederation-tourism-chapter https://africanmarketingconfederation.org/ https://africanmarketingconfederation.org/about-us https://africanmarketingconfederation.org/amc-conference-2022-prospectus https://africanmarketingconfederation.org/amc-conference-2022-thank-you https://africanmarketingconfederation.org/amc-conference-2022 https://africanmarketingconfederation.org/amc-conference-2023 https://africanmarketingconfederation.org/amc-conference-2023/amc-awards-book-now https://africanmarketingconfederation.org/amc-conference-2023/amc-awards | F16: Technical Diagnostics | G16: Manual Content | H16: https://africanmarketingconfederation.org/amc-awards-2024 | I16: Apply fix based on issue type and re-run audit. | J16: Template/technical implementation quality issue. | K16: Copy Writer | L16: Copy Writer | M16: S | N16: 4 | O16: 2 | P16: Next Sprint | Q16: To Do | T16: Medium Risk | U16: Yes | V16: Open in Main Tab | X16: SEO | Y16: =IFERROR(HYPERLINK("#'Main'!B"&MATCH(TRIM(H16),Main!B:B,0),"Open"),HYPERLINK("#'Main'!B1","Open")) -> Open | Z16: =IFERROR(INDEX('Content Optimisation Hub'!C:C,MATCH(H16,'Content Optimisation Hub'!F:F,0)),"Not in Hub") -> Not in Hub
A17: Low AEO Readiness Score | B17: Warning | C17: 67 | D17: 10 | E17: https://africanmarketingconfederation.org/amc-awards-2024 https://africanmarketingconfederation.org/african-marketing-confederation-tourism-chapter https://africanmarketingconfederation.org/ https://africanmarketingconfederation.org/about-us https://africanmarketingconfederation.org/amc-conference-2022-prospectus https://africanmarketingconfederation.org/amc-conference-2022-thank-you https://africanmarketingconfederation.org/amc-conference-2022 https://africanmarketingconfederation.org/amc-conference-2023 https://africanmarketingconfederation.org/amc-conference-2023/amc-awards-book-now https://africanmarketingconfederation.org/amc-conference-2023/amc-awards | F17: Content & AI Readiness | G17: Manual Content | H17: https://africanmarketingconfederation.org/amc-awards-2024 | I17: Add short direct answer blocks, question-led headings, and answer-ready formatting. | J17: Page lacks concise answer-oriented signals and structured answer patterns. | K17: Copy Writer | L17: Copy Writer | M17: S | N17: 4 | O17: 2 | P17: Next Sprint | Q17: To Do | T17: Medium Risk | U17: Yes | V17: Open in Main Tab | X17: AEO | Y17: =IFERROR(HYPERLINK("#'Main'!B"&MATCH(TRIM(H17),Main!B:B,0),"Open"),HYPERLINK("#'Main'!B1","Open")) -> Open | Z17: =IFERROR(INDEX('Content Optimisation Hub'!C:C,MATCH(H17,'Content Optimisation Hub'!F:F,0)),"Not in Hub") -> Not in Hub
A18: Multiple H1 | B18: Warning | C18: 67 | D18: 3 | E18: https://africanmarketingconfederation.org/amc-awards-2024 https://africanmarketingconfederation.org/african-marketing-confederation-tourism-chapter https://africanmarketingconfederation.org/ | F18: Technical Diagnostics | G18: Manual Content | H18: https://africanmarketingconfederation.org/amc-awards-2024 | I18: Apply fix based on issue type and re-run audit. | J18: Template/technical implementation quality issue. | K18: Copy Writer | L18: Copy Writer | M18: S | N18: 4 | O18: 2 | P18: Next Sprint | Q18: To Do | T18: Medium Risk | U18: Yes | V18: Open in Main Tab | X18: SEO | Y18: =IFERROR(HYPERLINK("#'Main'!B"&MATCH(TRIM(H18),Main!B:B,0),"Open"),HYPERLINK("#'Main'!B1","Open")) -> Open | Z18: =IFERROR(INDEX('Content Optimisation Hub'!C:C,MATCH(H18,'Content Optimisation Hub'!F:F,0)),"Not in Hub") -> Not in Hub
A19: Missing H1 | B19: Warning | C19: 67 | D19: 4 | E19: https://africanmarketingconfederation.org/amc-conference-2022-prospectus https://africanmarketingconfederation.org/amc-conference-2022-thank-you https://africanmarketingconfederation.org/amc-conference-2022 https://africanmarketingconfederation.org/amc-conference-2023/amc-awards-book-now | F19: Technical Diagnostics | G19: Manual Content | H19: https://africanmarketingconfederation.org/amc-conference-2022-prospectus | I19: Apply fix based on issue type and re-run audit. | J19: Template/technical implementation quality issue. | K19: Copy Writer | L19: Copy Writer | M19: S | N19: 4 | O19: 2 | P19: Next Sprint | Q19: To Do | T19: Medium Risk | U19: Yes | V19: Open in Main Tab | X19: SEO | Y19: =IFERROR(HYPERLINK("#'Main'!B"&MATCH(TRIM(H19),Main!B:B,0),"Open"),HYPERLINK("#'Main'!B1","Open")) -> Open | Z19: =IFERROR(INDEX('Content Optimisation Hub'!C:C,MATCH(H19,'Content Optimisation Hub'!F:F,0)),"Not in Hub") -> Not in Hub
A20: Missing Meta Description | B20: Warning | C20: 67 | D20: 1 | E20: https://africanmarketingconfederation.org/amc-conference-2023/amc-awards-book-now | F20: Technical Diagnostics | G20: Manual Content | H20: https://africanmarketingconfederation.org/amc-conference-2023/amc-awards-book-now | I20: Add concise unique description aligned with user intent. | J20: Meta description missing or empty. | K20: Copy Writer | L20: Copy Writer | M20: S | N20: 4 | O20: 2 | P20: Next Sprint | Q20: To Do | T20: Medium Risk | U20: Yes | V20: Open in Main Tab | X20: SEO | Y20: =IFERROR(HYPERLINK("#'Main'!B"&MATCH(TRIM(H20),Main!B:B,0),"Open"),HYPERLINK("#'Main'!B1","Open")) -> Open | Z20: =IFERROR(INDEX('Content Optimisation Hub'!C:C,MATCH(H20,'Content Optimisation Hub'!F:F,0)),"Not in Hub") -> Not in Hub
A21: Uses URL Parameters | B21: Observation | C21: 37 | D21: 0 | F21: Technical Diagnostics | G21: Manual Content | I21: Apply fix based on issue type and re-run audit. | J21: Template/technical implementation quality issue. | K21: Dev | L21: Dev | M21: S | N21: 4 | O21: 2 | P21: Backlog | Q21: In Review | T21: Monitor | U21: No | V21: Open in Main Tab | X21: SEO | Y21: =IFERROR(HYPERLINK("#'Main'!B"&MATCH(TRIM(H21),Main!B:B,0),"Open"),HYPERLINK("#'Main'!B1","Open")) -> Open | Z21: =IFERROR(INDEX('Content Optimisation Hub'!C:C,MATCH(H21,'Content Optimisation Hub'!F:F,0)),"Not in Hub") -> Not in Hub
A22: Image Filename Quality Issues | B22: Observation | C22: 37 | D22: 0 | F22: Technical Diagnostics | G22: Manual Content | I22: Apply fix based on issue type and re-run audit. | J22: Template/technical implementation quality issue. | K22: Copy Writer | L22: Copy Writer | M22: S | N22: 4 | O22: 2 | P22: Backlog | Q22: In Review | T22: Monitor | U22: No | V22: Open in Main Tab | X22: SEO | Y22: =IFERROR(HYPERLINK("#'Main'!B"&MATCH(TRIM(H22),Main!B:B,0),"Open"),HYPERLINK("#'Main'!B1","Open")) -> Open | Z22: =IFERROR(INDEX('Content Optimisation Hub'!C:C,MATCH(H22,'Content Optimisation Hub'!F:F,0)),"Not in Hub") -> Not in Hub
A23: No Compression Header | B23: Observation | C23: 37 | D23: 0 | F23: Technical Diagnostics | G23: Global Template | I23: Apply fix based on issue type and re-run audit. | J23: Template/technical implementation quality issue. | K23: Server/Host | L23: Server/Host | M23: S | N23: 4 | O23: 2 | P23: Backlog | Q23: In Review | T23: Monitor | U23: No | V23: Open in Main Tab | X23: SEO | Y23: =IFERROR(HYPERLINK("#'Main'!B"&MATCH(TRIM(H23),Main!B:B,0),"Open"),HYPERLINK("#'Main'!B1","Open")) -> Open | Z23: =IFERROR(INDEX('Content Optimisation Hub'!C:C,MATCH(H23,'Content Optimisation Hub'!F:F,0)),"Not in Hub") -> Not in Hub
A24: No Cache-Control Header | B24: Observation | C24: 37 | D24: 0 | F24: Technical Diagnostics | G24: Global Template | I24: Apply fix based on issue type and re-run audit. | J24: Template/technical implementation quality issue. | K24: Server/Host | L24: Server/Host | M24: S | N24: 4 | O24: 2 | P24: Backlog | Q24: In Review | T24: Monitor | U24: No | V24: Open in Main Tab | X24: SEO | Y24: =IFERROR(HYPERLINK("#'Main'!B"&MATCH(TRIM(H24),Main!B:B,0),"Open"),HYPERLINK("#'Main'!B1","Open")) -> Open | Z24: =IFERROR(INDEX('Content Optimisation Hub'!C:C,MATCH(H24,'Content Optimisation Hub'!F:F,0)),"Not in Hub") -> Not in Hub
A25: INP Above 100ms | B25: Observation | C25: 37 | D25: 0 | F25: Technical Diagnostics | G25: Manual Content | I25: Apply fix based on issue type and re-run audit. | J25: Template/technical implementation quality issue. | K25: Copy Writer | L25: Copy Writer | M25: S | N25: 4 | O25: 2 | P25: Backlog | Q25: In Review | T25: Monitor | U25: No | V25: Open in Main Tab | X25: SEO | Y25: =IFERROR(HYPERLINK("#'Main'!B"&MATCH(TRIM(H25),Main!B:B,0),"Open"),HYPERLINK("#'Main'!B1","Open")) -> Open | Z25: =IFERROR(INDEX('Content Optimisation Hub'!C:C,MATCH(H25,'Content Optimisation Hub'!F:F,0)),"Not in Hub") -> Not in Hub
A26: CLS Above 0.1 | B26: Observation | C26: 37 | D26: 0 | F26: Technical Diagnostics | G26: Manual Content | I26: Apply fix based on issue type and re-run audit. | J26: Template/technical implementation quality issue. | K26: Copy Writer | L26: Copy Writer | M26: S | N26: 4 | O26: 2 | P26: Backlog | Q26: In Review | T26: Monitor | U26: No | V26: Open in Main Tab | X26: SEO | Y26: =IFERROR(HYPERLINK("#'Main'!B"&MATCH(TRIM(H26),Main!B:B,0),"Open"),HYPERLINK("#'Main'!B1","Open")) -> Open | Z26: =IFERROR(INDEX('Content Optimisation Hub'!C:C,MATCH(H26,'Content Optimisation Hub'!F:F,0)),"Not in Hub") -> Not in Hub
A27: Low Regional Authority | B27: Observation | C27: 37 | D27: 0 | F27: Technical Diagnostics | G27: Manual Content | I27: Apply fix based on issue type and re-run audit. | J27: Template/technical implementation quality issue. | K27: Copy Writer | L27: Copy Writer | M27: S | N27: 4 | O27: 2 | P27: Backlog | Q27: In Review | T27: Monitor | U27: No | V27: Open in Main Tab | X27: SEO | Y27: =IFERROR(HYPERLINK("#'Main'!B"&MATCH(TRIM(H27),Main!B:B,0),"Open"),HYPERLINK("#'Main'!B1","Open")) -> Open | Z27: =IFERROR(INDEX('Content Optimisation Hub'!C:C,MATCH(H27,'Content Optimisation Hub'!F:F,0)),"Not in Hub") -> Not in Hub
A28: llms.txt Missing | B28: Observation | C28: 37 | D28: 0 | F28: Technical Diagnostics | G28: Manual Content | I28: Apply fix based on issue type and re-run audit. | J28: Template/technical implementation quality issue. | K28: Copy Writer | L28: Copy Writer | M28: S | N28: 4 | O28: 2 | P28: Backlog | Q28: In Review | T28: Monitor | U28: No | V28: Open in Main Tab | X28: SEO | Y28: =IFERROR(HYPERLINK("#'Main'!B"&MATCH(TRIM(H28),Main!B:B,0),"Open"),HYPERLINK("#'Main'!B1","Open")) -> Open | Z28: =IFERROR(INDEX('Content Optimisation Hub'!C:C,MATCH(H28,'Content Optimisation Hub'!F:F,0)),"Not in Hub") -> Not in Hub
A29: Thin Content | B29: Observation | C29: 37 | D29: 5 | E29: https://africanmarketingconfederation.org/ https://africanmarketingconfederation.org/about-us https://africanmarketingconfederation.org/amc-conference-2022-prospectus https://africanmarketingconfederation.org/amc-conference-2022 https://africanmarketingconfederation.org/amc-conference-2023/amc-awards-book-now | F29: Technical Diagnostics | G29: Manual Content | H29: https://africanmarketingconfederation.org/ | I29: Expand page with helpful, unique, intent-matching content. | J29: Insufficient body content for indexing confidence. | K29: Copy Writer | L29: Copy Writer | M29: S | N29: 4 | O29: 2 | P29: Backlog | Q29: In Review | T29: Monitor | U29: No | V29: Open in Main Tab | X29: SEO | Y29: =IFERROR(HYPERLINK("#'Main'!B"&MATCH(TRIM(H29),Main!B:B,0),"Open"),HYPERLINK("#'Main'!B1","Open")) -> Open | Z29: =IFERROR(INDEX('Content Optimisation Hub'!C:C,MATCH(H29,'Content Optimisation Hub'!F:F,0)),"Not in Hub") -> Not in Hub
A30: Generic Anchor Text Present | B30: Observation | C30: 37 | D30: 1 | E30: https://africanmarketingconfederation.org/ | F30: Link Intelligence | G30: Manual Content | H30: https://africanmarketingconfederation.org/ | I30: Apply fix based on issue type and re-run audit. | J30: Template/technical implementation quality issue. | K30: Copy Writer | L30: Copy Writer | M30: S | N30: 4 | O30: 2 | P30: Backlog | Q30: In Review | T30: Monitor | U30: No | V30: Open in Main Tab | X30: SEO | Y30: =IFERROR(HYPERLINK("#'Main'!B"&MATCH(TRIM(H30),Main!B:B,0),"Open"),HYPERLINK("#'Main'!B1","Open")) -> Open | Z30: =IFERROR(INDEX('Content Optimisation Hub'!C:C,MATCH(H30,'Content Optimisation Hub'!F:F,0)),"Not in Hub") -> Not in Hub
A31: No ETag Header | B31: Observation | C31: 37 | D31: 10 | E31: https://africanmarketingconfederation.org/amc-awards-2024 https://africanmarketingconfederation.org/african-marketing-confederation-tourism-chapter https://africanmarketingconfederation.org/ https://africanmarketingconfederation.org/about-us https://africanmarketingconfederation.org/amc-conference-2022-prospectus https://africanmarketingconfederation.org/amc-conference-2022-thank-you https://africanmarketingconfederation.org/amc-conference-2022 https://africanmarketingconfederation.org/amc-conference-2023 https://africanmarketingconfederation.org/amc-conference-2023/amc-awards-book-now https://africanmarketingconfederation.org/amc-conference-2023/amc-awards | F31: Technical Diagnostics | G31: Global Template | H31: https://africanmarketingconfederation.org/amc-awards-2024 | I31: Apply fix based on issue type and re-run audit. | J31: Template/technical implementation quality issue. | K31: Server/Host | L31: Server/Host | M31: S | N31: 4 | O31: 2 | P31: Backlog | Q31: In Review | T31: Monitor | U31: No | V31: Open in Main Tab | X31: SEO | Y31: =IFERROR(HYPERLINK("#'Main'!B"&MATCH(TRIM(H31),Main!B:B,0),"Open"),HYPERLINK("#'Main'!B1","Open")) -> Open | Z31: =IFERROR(INDEX('Content Optimisation Hub'!C:C,MATCH(H31,'Content Optimisation Hub'!F:F,0)),"Not in Hub") -> Not in Hub
A32: No Question Headings | B32: Observation | C32: 37 | D32: 10 | E32: https://africanmarketingconfederation.org/amc-awards-2024 https://africanmarketingconfederation.org/african-marketing-confederation-tourism-chapter https://africanmarketingconfederation.org/ https://africanmarketingconfederation.org/about-us https://africanmarketingconfederation.org/amc-conference-2022-prospectus https://africanmarketingconfederation.org/amc-conference-2022-thank-you https://africanmarketingconfederation.org/amc-conference-2022 https://africanmarketingconfederation.org/amc-conference-2023 https://africanmarketingconfederation.org/amc-conference-2023/amc-awards-book-now https://africanmarketingconfederation.org/amc-conference-2023/amc-awards | F32: Content & AI Readiness | G32: Manual Content | H32: https://africanmarketingconfederation.org/amc-awards-2024 | I32: Add clear question-style headings (especially H2/H3) for key intents. | J32: Headings are not phrased as user questions. | K32: Copy Writer | L32: Copy Writer | M32: S | N32: 4 | O32: 2 | P32: Backlog | Q32: In Review | T32: Monitor | U32: No | V32: Open in Main Tab | X32: AEO | Y32: =IFERROR(HYPERLINK("#'Main'!B"&MATCH(TRIM(H32),Main!B:B,0),"Open"),HYPERLINK("#'Main'!B1","Open")) -> Open | Z32: =IFERROR(INDEX('Content Optimisation Hub'!C:C,MATCH(H32,'Content Optimisation Hub'!F:F,0)),"Not in Hub") -> Not in Hub
A33: No Answer-Friendly Structure | B33: Observation | C33: 37 | D33: 10 | E33: https://africanmarketingconfederation.org/amc-awards-2024 https://africanmarketingconfederation.org/african-marketing-confederation-tourism-chapter https://africanmarketingconfederation.org/ https://africanmarketingconfederation.org/about-us https://africanmarketingconfederation.org/amc-conference-2022-prospectus https://africanmarketingconfederation.org/amc-conference-2022-thank-you https://africanmarketingconfederation.org/amc-conference-2022 https://africanmarketingconfederation.org/amc-conference-2023 https://africanmarketingconfederation.org/amc-conference-2023/amc-awards-book-now https://africanmarketingconfederation.org/amc-conference-2023/amc-awards | F33: Content & AI Readiness | G33: Manual Content | H33: https://africanmarketingconfederation.org/amc-awards-2024 | I33: Introduce structured bullets, ordered steps, or tables for key answers. | J33: Page lacks lists/tables that help concise answer extraction. | K33: Copy Writer | L33: Copy Writer | M33: S | N33: 4 | O33: 2 | P33: Backlog | Q33: In Review | T33: Monitor | U33: No | V33: Open in Main Tab | X33: AEO | Y33: =IFERROR(HYPERLINK("#'Main'!B"&MATCH(TRIM(H33),Main!B:B,0),"Open"),HYPERLINK("#'Main'!B1","Open")) -> Open | Z33: =IFERROR(INDEX('Content Optimisation Hub'!C:C,MATCH(H33,'Content Optimisation Hub'!F:F,0)),"Not in Hub") -> Not in Hub
A34: No 40-60 Word Answer Paragraphs | B34: Observation | C34: 37 | D34: 10 | E34: https://africanmarketingconfederation.org/amc-awards-2024 https://africanmarketingconfederation.org/african-marketing-confederation-tourism-chapter https://africanmarketingconfederation.org/ https://africanmarketingconfederation.org/about-us https://africanmarketingconfederation.org/amc-conference-2022-prospectus https://africanmarketingconfederation.org/amc-conference-2022-thank-you https://africanmarketingconfederation.org/amc-conference-2022 https://africanmarketingconfederation.org/amc-conference-2023 https://africanmarketingconfederation.org/amc-conference-2023/amc-awards-book-now https://africanmarketingconfederation.org/amc-conference-2023/amc-awards | F34: Content & AI Readiness | G34: Manual Content | H34: https://africanmarketingconfederation.org/amc-awards-2024 | I34: Add a direct 30-60 word answer summary near question headings. | J34: No concise answer-length paragraph detected. | K34: Copy Writer | L34: Copy Writer | M34: S | N34: 4 | O34: 2 | P34: Backlog | Q34: In Review | T34: Monitor | U34: No | V34: Open in Main Tab | X34: AEO | Y34: =IFERROR(HYPERLINK("#'Main'!B"&MATCH(TRIM(H34),Main!B:B,0),"Open"),HYPERLINK("#'Main'!B1","Open")) -> Open | Z34: =IFERROR(INDEX('Content Optimisation Hub'!C:C,MATCH(H34,'Content Optimisation Hub'!F:F,0)),"Not in Hub") -> Not in Hub
A35: AI Crawlers Not Explicitly Allowed | B35: Observation | C35: 37 | D35: 10 | E35: https://africanmarketingconfederation.org/amc-awards-2024 https://africanmarketingconfederation.org/african-marketing-confederation-tourism-chapter https://africanmarketingconfederation.org/ https://africanmarketingconfederation.org/about-us https://africanmarketingconfederation.org/amc-conference-2022-prospectus https://africanmarketingconfederation.org/amc-conference-2022-thank-you https://africanmarketingconfederation.org/amc-conference-2022 https://africanmarketingconfederation.org/amc-conference-2023 https://africanmarketingconfederation.org/amc-conference-2023/amc-awards-book-now https://africanmarketingconfederation.org/amc-conference-2023/amc-awards | F35: Technical Diagnostics | G35: Manual Content | H35: https://africanmarketingconfederation.org/amc-awards-2024 | I35: Apply fix based on issue type and re-run audit. | J35: Template/technical implementation quality issue. | K35: Copy Writer | L35: Copy Writer | M35: S | N35: 4 | O35: 2 | P35: Backlog | Q35: In Review | T35: Monitor | U35: No | V35: Open in Main Tab | X35: SEO | Y35: =IFERROR(HYPERLINK("#'Main'!B"&MATCH(TRIM(H35),Main!B:B,0),"Open"),HYPERLINK("#'Main'!B1","Open")) -> Open | Z35: =IFERROR(INDEX('Content Optimisation Hub'!C:C,MATCH(H35,'Content Optimisation Hub'!F:F,0)),"Not in Hub") -> Not in Hub

Sheet Priority URLs
A1: URL | B1: Business Risk Score | C1: Severity Badge | D1: SEO Health Score | E1: GSC Impressions | F1: GSC CTR | G1: Revenue Intent | H1: Critical Issues Count | I1: Warning Issues Count | J1: Action Needed | K1: Why Prioritized | L1: Owner | M1: Status | N1: Sprint | O1: Indexability Reason | P1: Broken Internal Links Count | Q1: Canonical Type | R1: Open in Main | S1: Open in Technical | T1: BACK TO DASHBOARD
A2: https://africanmarketingconfederation.org/amc-conference-2023/amc-awards-book-now | B2: 90 | C2: Warning | D2: 50 | E2: 0 | F2: 0 | G2: Standard | H2: 0 | I2: 4 | J2: Yes | K2: Monitor | L2: Copy Writer | M2: Open | O2: Indexable | Q2: self | R2: =IFERROR(HYPERLINK("#'Main'!B"&MATCH(TRIM(A2),Main!B:B,0),"Open"),HYPERLINK("#'Main'!B1","Open")) -> Open | S2: =IFERROR(HYPERLINK("#'Technical Diagnostics'!A"&MATCH(A2,'Technical Diagnostics'!A:A,0),"Open"),HYPERLINK("#'Technical Diagnostics'!A1","Open")) -> Open
A3: https://africanmarketingconfederation.org/amc-awards-2024 | B3: 70 | C3: Warning | D3: 60 | E3: 0 | F3: 0 | G3: Standard | H3: 0 | I3: 3 | J3: Yes | K3: Monitor | L3: Copy Writer | M3: Open | O3: Indexable | Q3: self | R3: =IFERROR(HYPERLINK("#'Main'!B"&MATCH(TRIM(A3),Main!B:B,0),"Open"),HYPERLINK("#'Main'!B1","Open")) -> Open | S3: =IFERROR(HYPERLINK("#'Technical Diagnostics'!A"&MATCH(A3,'Technical Diagnostics'!A:A,0),"Open"),HYPERLINK("#'Technical Diagnostics'!A1","Open")) -> Open
A4: https://africanmarketingconfederation.org/african-marketing-confederation-tourism-chapter | B4: 70 | C4: Warning | D4: 60 | E4: 0 | F4: 0 | G4: Standard | H4: 0 | I4: 3 | J4: Yes | K4: Monitor | L4: Copy Writer | M4: Open | O4: Indexable | Q4: self | R4: =IFERROR(HYPERLINK("#'Main'!B"&MATCH(TRIM(A4),Main!B:B,0),"Open"),HYPERLINK("#'Main'!B1","Open")) -> Open | S4: =IFERROR(HYPERLINK("#'Technical Diagnostics'!A"&MATCH(A4,'Technical Diagnostics'!A:A,0),"Open"),HYPERLINK("#'Technical Diagnostics'!A1","Open")) -> Open
A5: https://africanmarketingconfederation.org/ | B5: 70 | C5: Warning | D5: 60 | E5: 0 | F5: 0 | G5: Standard | H5: 0 | I5: 3 | J5: Yes | K5: Monitor | L5: Copy Writer | M5: Open | O5: Indexable | Q5: self | R5: =IFERROR(HYPERLINK("#'Main'!B"&MATCH(TRIM(A5),Main!B:B,0),"Open"),HYPERLINK("#'Main'!B1","Open")) -> Open | S5: =IFERROR(HYPERLINK("#'Technical Diagnostics'!A"&MATCH(A5,'Technical Diagnostics'!A:A,0),"Open"),HYPERLINK("#'Technical Diagnostics'!A1","Open")) -> Open
A6: https://africanmarketingconfederation.org/amc-conference-2022-prospectus | B6: 70 | C6: Warning | D6: 60 | E6: 0 | F6: 0 | G6: Standard | H6: 0 | I6: 3 | J6: Yes | K6: Monitor | L6: Copy Writer | M6: Open | O6: Indexable | Q6: self | R6: =IFERROR(HYPERLINK("#'Main'!B"&MATCH(TRIM(A6),Main!B:B,0),"Open"),HYPERLINK("#'Main'!B1","Open")) -> Open | S6: =IFERROR(HYPERLINK("#'Technical Diagnostics'!A"&MATCH(A6,'Technical Diagnostics'!A:A,0),"Open"),HYPERLINK("#'Technical Diagnostics'!A1","Open")) -> Open
A7: https://africanmarketingconfederation.org/amc-conference-2022-thank-you | B7: 70 | C7: Warning | D7: 60 | E7: 0 | F7: 0 | G7: Standard | H7: 0 | I7: 3 | J7: Yes | K7: Monitor | L7: Copy Writer | M7: Open | O7: Indexable | Q7: self | R7: =IFERROR(HYPERLINK("#'Main'!B"&MATCH(TRIM(A7),Main!B:B,0),"Open"),HYPERLINK("#'Main'!B1","Open")) -> Open | S7: =IFERROR(HYPERLINK("#'Technical Diagnostics'!A"&MATCH(A7,'Technical Diagnostics'!A:A,0),"Open"),HYPERLINK("#'Technical Diagnostics'!A1","Open")) -> Open
A8: https://africanmarketingconfederation.org/amc-conference-2022 | B8: 70 | C8: Warning | D8: 60 | E8: 0 | F8: 0 | G8: Standard | H8: 0 | I8: 3 | J8: Yes | K8: Monitor | L8: Copy Writer | M8: Open | O8: Indexable | Q8: self | R8: =IFERROR(HYPERLINK("#'Main'!B"&MATCH(TRIM(A8),Main!B:B,0),"Open"),HYPERLINK("#'Main'!B1","Open")) -> Open | S8: =IFERROR(HYPERLINK("#'Technical Diagnostics'!A"&MATCH(A8,'Technical Diagnostics'!A:A,0),"Open"),HYPERLINK("#'Technical Diagnostics'!A1","Open")) -> Open
A9: https://africanmarketingconfederation.org/about-us | B9: 50 | C9: Warning | D9: 70 | E9: 0 | F9: 0 | G9: Standard | H9: 0 | I9: 2 | J9: Yes | K9: Monitor | L9: Copy Writer | M9: Open | O9: Indexable | Q9: self | R9: =IFERROR(HYPERLINK("#'Main'!B"&MATCH(TRIM(A9),Main!B:B,0),"Open"),HYPERLINK("#'Main'!B1","Open")) -> Open | S9: =IFERROR(HYPERLINK("#'Technical Diagnostics'!A"&MATCH(A9,'Technical Diagnostics'!A:A,0),"Open"),HYPERLINK("#'Technical Diagnostics'!A1","Open")) -> Open
A10: https://africanmarketingconfederation.org/amc-conference-2023 | B10: 50 | C10: Warning | D10: 70 | E10: 0 | F10: 0 | G10: Standard | H10: 0 | I10: 2 | J10: Yes | K10: Monitor | L10: Copy Writer | M10: Open | O10: Indexable | Q10: self | R10: =IFERROR(HYPERLINK("#'Main'!B"&MATCH(TRIM(A10),Main!B:B,0),"Open"),HYPERLINK("#'Main'!B1","Open")) -> Open | S10: =IFERROR(HYPERLINK("#'Technical Diagnostics'!A"&MATCH(A10,'Technical Diagnostics'!A:A,0),"Open"),HYPERLINK("#'Technical Diagnostics'!A1","Open")) -> Open
A11: https://africanmarketingconfederation.org/amc-conference-2023/amc-awards | B11: 50 | C11: Warning | D11: 70 | E11: 0 | F11: 0 | G11: Standard | H11: 0 | I11: 2 | J11: Yes | K11: Monitor | L11: Copy Writer | M11: Open | O11: Indexable | Q11: self | R11: =IFERROR(HYPERLINK("#'Main'!B"&MATCH(TRIM(A11),Main!B:B,0),"Open"),HYPERLINK("#'Main'!B1","Open")) -> Open | S11: =IFERROR(HYPERLINK("#'Technical Diagnostics'!A"&MATCH(A11,'Technical Diagnostics'!A:A,0),"Open"),HYPERLINK("#'Technical Diagnostics'!A1","Open")) -> Open

Sheet Content Optimisation Hub
A1: CONTENT HUB (DIAGNOSTIC): Edit Title, Meta, and H1–H6 in-place; health columns and On-Page score update live. | Use Elementor link for CMS edits. | Set Status to Completed when done. | NOTE: If images show '#BLOCKED!', enable external content in Excel security. | AD1: BACK TO DASHBOARD
A2: Action Required | B2: On-Page Optimization Score | C2: SEO Score | D2: Technical Health | E2: Copy Score | F2: Status | G2: Assigned Owner | H2: URL | I2: URL Slug Normalization | J2: Proposed URL Slug | K2: Current Title | L2: Title Health | M2: Current Meta Desc | N2: Meta Health | O2: H1 | P2: H1 Health | Q2: H2 | R2: H2 Health | S2: H3 | T2: H3 Health | U2: H4 | V2: H4 Health | W2: H5 | X2: H5 Health | Y2: H6 | Z2: H6 Health | AA2: Elementor Builder Link | AB2: Current OG-Image URL | AC2: OG Image Preview | AD2: Open in Main
A3: =IF(B3>=85,"Complete","Needs Copy") -> Needs Copy | B3: =MIN(100,ROUND(0.3*(IF(L3="",0,IF(LEFT(L3,7)="MISSING",0,IF(ISNUMBER(SEARCH("OK",L3)),100,IF(ISNUMBER(SEARCH("SHORT",L3)),65,IF(ISNUMBER(SEARCH("LONG",L3)),50,70))))))+0.25*(IF(N3="",0,IF(LEFT(N3,7)="MISSING",0,IF(ISNUMBER(SEARCH("OK",N3)),100,IF(ISNUMBER(SEARCH("SHORT",N3)),65,IF(ISNUMBER(SEARCH("LONG",N3)),50,70))))))+0.2*(IF(P3="",0,IF(LEFT(P3,2)="OK",100,0)))+0.08*(IF(R3="",0,IF(LEFT(R3,2)="OK",100,0)))+0.06*(IF(T3="",0,IF(LEFT(T3,2)="OK",100,0)))+0.05*(IF(V3="",0,IF(LEFT(V3,2)="OK",100,0)))+0.03*(IF(X3="",0,IF(LEFT(X3,2)="OK",100,0)))+0.03*(IF(Z3="",0,IF(LEFT(Z3,2)="OK",100,0))),0)) -> 68 | C3: 64.52 | D3: 60 | E3: 78.08 | F3: To Do | G3: Copy Writer | H3: =HYPERLINK("https://africanmarketingconfederation.org/","https://africanmarketingconfederation.org/") -> https://africanmarketingconfederation.org/ | I3: =HYPERLINK("https://africanmarketingconfederation.org/","https://africanmarketingconfederation.org/") -> https://africanmarketingconfederation.org/ | K3: African Marketing Confederation - Uniting Marketers for Excellence | L3: =IF(K3="","MISSING",IF(AND(LEN(K3)>=50,LEN(K3)<=60),"OK 50-60 chars",IF(LEN(K3)<50,"SHORT: "&LEN(K3),"LONG: "&LEN(K3)))) -> LONG: 66 | M3: The African Marketing Confederation is the ground-breaking Pan-African body driving the development of top marketing standards across Africa and beyond. | N3: =IF(M3="","MISSING",IF(AND(LEN(M3)>=120,LEN(M3)<=160),"OK 120-160 chars",IF(LEN(M3)<120,"SHORT: "&LEN(M3),"LONG: "&LEN(M3)))) -> OK 120-160 chars | O3: ABOUT The African Marketing Confederation | P3: =IF(OR(ISBLANK(O3),ISNUMBER(SEARCH("|",O3))),"FIX: MULTIPLE/MISSING","OK") -> OK | Q3: The 2026 AMC Conference | Meets the Mighty Victoria Falls | 23-25 September | Livingstone, Zambia | Certified Professional Marketer (Africa) - CPM(A) | The designation where global marketing standards meet African realities | R3: =IF(ISBLANK(Q3),"MISSING","OK") -> OK | T3: =IF(ISBLANK(S3),"MISSING","OK") -> MISSING | V3: =IF(ISBLANK(U3),"MISSING","OK") -> MISSING | X3: =IF(ISBLANK(W3),"MISSING","OK") -> MISSING | Z3: =IF(ISBLANK(Y3),"MISSING","OK") -> MISSING | AA3: =HYPERLINK("https://africanmarketingconfederation.org/wp-admin/post.php?post=8&action=elementor","Open in Elementor") -> Open in Elementor | AB3: =HYPERLINK("https://africanmarketingconfederation.org/wp-content/uploads/2026/03/og-image.png","View Image") -> View Image | AC3: =IF(LEN("https://africanmarketingconfederation.org/wp-content/uploads/2026/03/og-image.png")>0, _xlfn.IMAGE("https://africanmarketingconfederation.org/wp-content/uploads/2026/03/og-image.png"), "") -> #VALUE! | AD3: =IFERROR(HYPERLINK("#'Main'!B"&MATCH(TRIM(H3),Main!B:B,0),"Open in Main"),IFERROR(HYPERLINK("#'Technical Diagnostics'!A"&MATCH(TRIM(H3),'Technical Diagnostics'!A:A,0),"Open in Technical"),"Not Found")) -> Open in Main
A4: =IF(B4>=85,"Complete","Needs Copy") -> Needs Copy | B4: =MIN(100,ROUND(0.3*(IF(L4="",0,IF(LEFT(L4,7)="MISSING",0,IF(ISNUMBER(SEARCH("OK",L4)),100,IF(ISNUMBER(SEARCH("SHORT",L4)),65,IF(ISNUMBER(SEARCH("LONG",L4)),50,70))))))+0.25*(IF(N4="",0,IF(LEFT(N4,7)="MISSING",0,IF(ISNUMBER(SEARCH("OK",N4)),100,IF(ISNUMBER(SEARCH("SHORT",N4)),65,IF(ISNUMBER(SEARCH("LONG",N4)),50,70))))))+0.2*(IF(P4="",0,IF(LEFT(P4,2)="OK",100,0)))+0.08*(IF(R4="",0,IF(LEFT(R4,2)="OK",100,0)))+0.06*(IF(T4="",0,IF(LEFT(T4,2)="OK",100,0)))+0.05*(IF(V4="",0,IF(LEFT(V4,2)="OK",100,0)))+0.03*(IF(X4="",0,IF(LEFT(X4,2)="OK",100,0)))+0.03*(IF(Z4="",0,IF(LEFT(Z4,2)="OK",100,0))),0)) -> 62 | C4: 76.15 | D4: 70 | E4: 94.58 | F4: To Do | G4: Copy Writer | H4: =HYPERLINK("https://africanmarketingconfederation.org/about-us","https://africanmarketingconfederation.org/about-us") -> https://africanmarketingconfederation.org/about-us | I4: =HYPERLINK("https://africanmarketingconfederation.org/about-us","About Us") -> About Us | J4: about-us | K4: African Marketing Confederation – The Leading Marketing Professional Body – African Marketing Confederation | L4: =IF(K4="","MISSING",IF(AND(LEN(K4)>=50,LEN(K4)<=60),"OK 50-60 chars",IF(LEN(K4)<50,"SHORT: "&LEN(K4),"LONG: "&LEN(K4)))) -> LONG: 107 | M4: ABOUT The African Marketing Confederation​ The African Marketing Confederation is the ground-breaking Pan African body of marketing professionals spearheading the ongoing development of the highest possible standards of marketing across Africa. Founded in 2011, the AMC is a collaboration between the African national marketing bodies and associations to exchange expertise and information, and to promote | N4: =IF(M4="","MISSING",IF(AND(LEN(M4)>=120,LEN(M4)<=160),"OK 120-160 chars",IF(LEN(M4)<120,"SHORT: "&LEN(M4),"LONG: "&LEN(M4)))) -> LONG: 405 | O4: ABOUT The African Marketing Confederation​ | P4: =IF(OR(ISBLANK(O4),ISNUMBER(SEARCH("|",O4))),"FIX: MULTIPLE/MISSING","OK") -> OK | Q4: Helen McIntee | President and Co-founder | David Balikuddembe | Secretary General | R4: =IF(ISBLANK(Q4),"MISSING","OK") -> OK | S4: African Marketing Confederation ​ PRESIDENT’S COUNCIL | T4: =IF(ISBLANK(S4),"MISSING","OK") -> OK | V4: =IF(ISBLANK(U4),"MISSING","OK") -> MISSING | X4: =IF(ISBLANK(W4),"MISSING","OK") -> MISSING | Z4: =IF(ISBLANK(Y4),"MISSING","OK") -> MISSING | AA4: =HYPERLINK("https://africanmarketingconfederation.org/wp-admin/post.php?post=84&action=elementor","Open in Elementor") -> Open in Elementor | AB4: =HYPERLINK("https://africanmarketingconfederation.org/wp-content/uploads/2026/03/og-image.png","View Image") -> View Image | AC4: =IF(LEN("https://africanmarketingconfederation.org/wp-content/uploads/2026/03/og-image.png")>0, _xlfn.IMAGE("https://africanmarketingconfederation.org/wp-content/uploads/2026/03/og-image.png"), "") -> #VALUE! | AD4: =IFERROR(HYPERLINK("#'Main'!B"&MATCH(TRIM(H4),Main!B:B,0),"Open in Main"),IFERROR(HYPERLINK("#'Technical Diagnostics'!A"&MATCH(TRIM(H4),'Technical Diagnostics'!A:A,0),"Open in Technical"),"Not Found")) -> Open in Main
A5: =IF(B5>=85,"Complete","Needs Copy") -> Needs Copy | B5: =MIN(100,ROUND(0.3*(IF(L5="",0,IF(LEFT(L5,7)="MISSING",0,IF(ISNUMBER(SEARCH("OK",L5)),100,IF(ISNUMBER(SEARCH("SHORT",L5)),65,IF(ISNUMBER(SEARCH("LONG",L5)),50,70))))))+0.25*(IF(N5="",0,IF(LEFT(N5,7)="MISSING",0,IF(ISNUMBER(SEARCH("OK",N5)),100,IF(ISNUMBER(SEARCH("SHORT",N5)),65,IF(ISNUMBER(SEARCH("LONG",N5)),50,70))))))+0.2*(IF(P5="",0,IF(LEFT(P5,2)="OK",100,0)))+0.08*(IF(R5="",0,IF(LEFT(R5,2)="OK",100,0)))+0.06*(IF(T5="",0,IF(LEFT(T5,2)="OK",100,0)))+0.05*(IF(V5="",0,IF(LEFT(V5,2)="OK",100,0)))+0.03*(IF(X5="",0,IF(LEFT(X5,2)="OK",100,0)))+0.03*(IF(Z5="",0,IF(LEFT(Z5,2)="OK",100,0))),0)) -> 62 | C5: 70 | D5: 60 | E5: 100 | F5: To Do | G5: Copy Writer | H5: =HYPERLINK("https://africanmarketingconfederation.org/african-marketing-confederation-tourism-chapter","https://africanmarketingconfederation.org/african-marketing-confederation-tourism-chapter") -> https://africanmarketingconfederation.org/african-marketing-confederation-tourism-chapter | I5: =HYPERLINK("https://africanmarketingconfederation.org/african-marketing-confederation-tourism-chapter","African Marketing Confederation Tourism Chapter") -> African Marketing Confederation Tourism Chapter | J5: african-marketing-confederation-tourism-chapter | K5: African Marketing Confederation Tourism Chapter – African Marketing Confederation | L5: =IF(K5="","MISSING",IF(AND(LEN(K5)>=50,LEN(K5)<=60),"OK 50-60 chars",IF(LEN(K5)<50,"SHORT: "&LEN(K5),"LONG: "&LEN(K5)))) -> LONG: 81 | M5: African Marketing Confederation Tourism Chapter Shaping Africa’s Tourism Narrative Through Strategic Marketing Tourism is one of Africa’s most powerful economic engines - generating jobs, stimulating investment, and fostering cultural exchange.The African Marketing Confederation is proud to launch the Tourism Chapter, a bold initiative to elevate African tourism through the lens of world-class marketing. Launched at the | N5: =IF(M5="","MISSING",IF(AND(LEN(M5)>=120,LEN(M5)<=160),"OK 120-160 chars",IF(LEN(M5)<120,"SHORT: "&LEN(M5),"LONG: "&LEN(M5)))) -> LONG: 423 | O5: African Marketing Confederation Tourism Chapter | P5: =IF(OR(ISBLANK(O5),ISNUMBER(SEARCH("|",O5))),"FIX: MULTIPLE/MISSING","OK") -> OK | Q5: Charting the Course: Purpose, Mission & Vision for Africa’s Tourism Future | Our Goals and Objectives: | R5: =IF(ISBLANK(Q5),"MISSING","OK") -> OK | S5: Shaping Africa’s Tourism Narrative Through Strategic Marketing | T5: =IF(ISBLANK(S5),"MISSING","OK") -> OK | V5: =IF(ISBLANK(U5),"MISSING","OK") -> MISSING | X5: =IF(ISBLANK(W5),"MISSING","OK") -> MISSING | Z5: =IF(ISBLANK(Y5),"MISSING","OK") -> MISSING | AA5: =HYPERLINK("https://africanmarketingconfederation.org/wp-admin/post.php?post=28165&action=elementor","Open in Elementor") -> Open in Elementor | AB5: =HYPERLINK("https://africanmarketingconfederation.org/wp-content/uploads/2026/03/og-image.png","View Image") -> View Image | AC5: =IF(LEN("https://africanmarketingconfederation.org/wp-content/uploads/2026/03/og-image.png")>0, _xlfn.IMAGE("https://africanmarketingconfederation.org/wp-content/uploads/2026/03/og-image.png"), "") -> #VALUE! | AD5: =IFERROR(HYPERLINK("#'Main'!B"&MATCH(TRIM(H5),Main!B:B,0),"Open in Main"),IFERROR(HYPERLINK("#'Technical Diagnostics'!A"&MATCH(TRIM(H5),'Technical Diagnostics'!A:A,0),"Open in Technical"),"Not Found")) -> Open in Main
A6: =IF(B6>=85,"Complete","Needs Copy") -> Needs Copy | B6: =MIN(100,ROUND(0.3*(IF(L6="",0,IF(LEFT(L6,7)="MISSING",0,IF(ISNUMBER(SEARCH("OK",L6)),100,IF(ISNUMBER(SEARCH("SHORT",L6)),65,IF(ISNUMBER(SEARCH("LONG",L6)),50,70))))))+0.25*(IF(N6="",0,IF(LEFT(N6,7)="MISSING",0,IF(ISNUMBER(SEARCH("OK",N6)),100,IF(ISNUMBER(SEARCH("SHORT",N6)),65,IF(ISNUMBER(SEARCH("LONG",N6)),50,70))))))+0.2*(IF(P6="",0,IF(LEFT(P6,2)="OK",100,0)))+0.08*(IF(R6="",0,IF(LEFT(R6,2)="OK",100,0)))+0.06*(IF(T6="",0,IF(LEFT(T6,2)="OK",100,0)))+0.05*(IF(V6="",0,IF(LEFT(V6,2)="OK",100,0)))+0.03*(IF(X6="",0,IF(LEFT(X6,2)="OK",100,0)))+0.03*(IF(Z6="",0,IF(LEFT(Z6,2)="OK",100,0))),0)) -> 60 | C6: 70 | D6: 60 | E6: 100 | F6: To Do | G6: Copy Writer | H6: =HYPERLINK("https://africanmarketingconfederation.org/amc-awards-2024","https://africanmarketingconfederation.org/amc-awards-2024") -> https://africanmarketingconfederation.org/amc-awards-2024 | I6: =HYPERLINK("https://africanmarketingconfederation.org/amc-awards-2024","Amc Awards 2024") -> Amc Awards 2024 | J6: amc-awards-2024 | K6: AMC Awards 2024 – African Marketing Confederation | L6: =IF(K6="","MISSING",IF(AND(LEN(K6)>=50,LEN(K6)<=60),"OK 50-60 chars",IF(LEN(K6)<50,"SHORT: "&LEN(K6),"LONG: "&LEN(K6)))) -> SHORT: 49 | M6: NOMINATIONS are Open ! AMC Awards The African Marketing Confederation Awards event is held annually as part of the African Marketing Confederation Forum. This distinguished event celebrates and acknowledges outstanding marketing campaigns and the visionary individuals behind them. The awards presented honor not only the groundbreaking strategies and creative brilliance that set these campaigns apart but | N6: =IF(M6="","MISSING",IF(AND(LEN(M6)>=120,LEN(M6)<=160),"OK 120-160 chars",IF(LEN(M6)<120,"SHORT: "&LEN(M6),"LONG: "&LEN(M6)))) -> LONG: 406 | O6: NOMINATIONS are Open ! | P6: =IF(OR(ISBLANK(O6),ISNUMBER(SEARCH("|",O6))),"FIX: MULTIPLE/MISSING","OK") -> OK | Q6: Awards Categories | Tourism & Destination Marketing Campaign | of the Year | Best Social Media Campaign | R6: =IF(ISBLANK(Q6),"MISSING","OK") -> OK | T6: =IF(ISBLANK(S6),"MISSING","OK") -> MISSING | V6: =IF(ISBLANK(U6),"MISSING","OK") -> MISSING | X6: =IF(ISBLANK(W6),"MISSING","OK") -> MISSING | Z6: =IF(ISBLANK(Y6),"MISSING","OK") -> MISSING | AA6: =HYPERLINK("https://africanmarketingconfederation.org/wp-admin/post.php?post=16125&action=elementor","Open in Elementor") -> Open in Elementor | AB6: =HYPERLINK("https://africanmarketingconfederation.org/wp-content/uploads/2021/08/amc_faw.png","View Image") -> View Image | AC6: =IF(LEN("https://africanmarketingconfederation.org/wp-content/uploads/2021/08/amc_faw.png")>0, _xlfn.IMAGE("https://africanmarketingconfederation.org/wp-content/uploads/2021/08/amc_faw.png"), "") -> #VALUE! | AD6: =IFERROR(HYPERLINK("#'Main'!B"&MATCH(TRIM(H6),Main!B:B,0),"Open in Main"),IFERROR(HYPERLINK("#'Technical Diagnostics'!A"&MATCH(TRIM(H6),'Technical Diagnostics'!A:A,0),"Open in Technical"),"Not Found")) -> Open in Main
A7: =IF(B7>=85,"Complete","Needs Copy") -> Needs Copy | B7: =MIN(100,ROUND(0.3*(IF(L7="",0,IF(LEFT(L7,7)="MISSING",0,IF(ISNUMBER(SEARCH("OK",L7)),100,IF(ISNUMBER(SEARCH("SHORT",L7)),65,IF(ISNUMBER(SEARCH("LONG",L7)),50,70))))))+0.25*(IF(N7="",0,IF(LEFT(N7,7)="MISSING",0,IF(ISNUMBER(SEARCH("OK",N7)),100,IF(ISNUMBER(SEARCH("SHORT",N7)),65,IF(ISNUMBER(SEARCH("LONG",N7)),50,70))))))+0.2*(IF(P7="",0,IF(LEFT(P7,2)="OK",100,0)))+0.08*(IF(R7="",0,IF(LEFT(R7,2)="OK",100,0)))+0.06*(IF(T7="",0,IF(LEFT(T7,2)="OK",100,0)))+0.05*(IF(V7="",0,IF(LEFT(V7,2)="OK",100,0)))+0.03*(IF(X7="",0,IF(LEFT(X7,2)="OK",100,0)))+0.03*(IF(Z7="",0,IF(LEFT(Z7,2)="OK",100,0))),0)) -> 57 | C7: 56.92 | D7: 60 | E7: 47.67 | F7: To Do | G7: Copy Writer | H7: =HYPERLINK("https://africanmarketingconfederation.org/amc-conference-2022","https://africanmarketingconfederation.org/amc-conference-2022") -> https://africanmarketingconfederation.org/amc-conference-2022 | I7: =HYPERLINK("https://africanmarketingconfederation.org/amc-conference-2022","Amc Conference 2022") -> Amc Conference 2022 | J7: amc-conference-2022 | K7: AMC Conference 2022 – African Marketing Confederation | L7: =IF(K7="","MISSING",IF(AND(LEN(K7)>=50,LEN(K7)<=60),"OK 50-60 chars",IF(LEN(K7)<50,"SHORT: "&LEN(K7),"LONG: "&LEN(K7)))) -> OK 50-60 chars | M7: corinna kopf onlyfans leaks AMC Conference 2022 Thank you for attending19 - 22 October 2022 The African Marketing Confederation's Annual Conference brought together the best collection of marketing leaders from top companies, marketing bodies and associations to share tactics and best practices on how to build the next generation of marketing. Event Highlights Thank you for Attending! | N7: =IF(M7="","MISSING",IF(AND(LEN(M7)>=120,LEN(M7)<=160),"OK 120-160 chars",IF(LEN(M7)<120,"SHORT: "&LEN(M7),"LONG: "&LEN(M7)))) -> LONG: 387 | P7: =IF(OR(ISBLANK(O7),ISNUMBER(SEARCH("|",O7))),"FIX: MULTIPLE/MISSING","OK") -> FIX: MULTIPLE/MISSING | Q7: AMC Conference 2022 | Event Highlights | R7: =IF(ISBLANK(Q7),"MISSING","OK") -> OK | S7: AMC officially welcomes new member associations into the fold | Marketers are placing the ads where consumers don’t want to see them | Time for Africa to control its own narrative and image, delegates told | Excitement as Ghana announced as host of 2025 AMC marketing conference | T7: =IF(ISBLANK(S7),"MISSING","OK") -> OK | V7: =IF(ISBLANK(U7),"MISSING","OK") -> MISSING | X7: =IF(ISBLANK(W7),"MISSING","OK") -> MISSING | Z7: =IF(ISBLANK(Y7),"MISSING","OK") -> MISSING | AA7: =HYPERLINK("https://africanmarketingconfederation.org/wp-admin/post.php?post=4494&action=elementor","Open in Elementor") -> Open in Elementor | AB7: =HYPERLINK("https://africanmarketingconfederation.org/wp-content/uploads/2026/03/og-image.png","View Image") -> View Image | AC7: =IF(LEN("https://africanmarketingconfederation.org/wp-content/uploads/2026/03/og-image.png")>0, _xlfn.IMAGE("https://africanmarketingconfederation.org/wp-content/uploads/2026/03/og-image.png"), "") -> #VALUE! | AD7: =IFERROR(HYPERLINK("#'Main'!B"&MATCH(TRIM(H7),Main!B:B,0),"Open in Main"),IFERROR(HYPERLINK("#'Technical Diagnostics'!A"&MATCH(TRIM(H7),'Technical Diagnostics'!A:A,0),"Open in Technical"),"Not Found")) -> Open in Main
A8: =IF(B8>=85,"Complete","Needs Copy") -> Needs Copy | B8: =MIN(100,ROUND(0.3*(IF(L8="",0,IF(LEFT(L8,7)="MISSING",0,IF(ISNUMBER(SEARCH("OK",L8)),100,IF(ISNUMBER(SEARCH("SHORT",L8)),65,IF(ISNUMBER(SEARCH("LONG",L8)),50,70))))))+0.25*(IF(N8="",0,IF(LEFT(N8,7)="MISSING",0,IF(ISNUMBER(SEARCH("OK",N8)),100,IF(ISNUMBER(SEARCH("SHORT",N8)),65,IF(ISNUMBER(SEARCH("LONG",N8)),50,70))))))+0.2*(IF(P8="",0,IF(LEFT(P8,2)="OK",100,0)))+0.08*(IF(R8="",0,IF(LEFT(R8,2)="OK",100,0)))+0.06*(IF(T8="",0,IF(LEFT(T8,2)="OK",100,0)))+0.05*(IF(V8="",0,IF(LEFT(V8,2)="OK",100,0)))+0.03*(IF(X8="",0,IF(LEFT(X8,2)="OK",100,0)))+0.03*(IF(Z8="",0,IF(LEFT(Z8,2)="OK",100,0))),0)) -> 36 | C8: 58.75 | D8: 60 | E8: 55 | F8: To Do | G8: Copy Writer | H8: =HYPERLINK("https://africanmarketingconfederation.org/amc-conference-2022-prospectus","https://africanmarketingconfederation.org/amc-conference-2022-prospectus") -> https://africanmarketingconfederation.org/amc-conference-2022-prospectus | I8: =HYPERLINK("https://africanmarketingconfederation.org/amc-conference-2022-prospectus","Amc Conference 2022 Prospectus") -> Amc Conference 2022 Prospectus | J8: amc-conference-2022-prospectus | K8: AMC Conference 2022 – Prospectus – African Marketing Confederation | L8: =IF(K8="","MISSING",IF(AND(LEN(K8)>=50,LEN(K8)<=60),"OK 50-60 chars",IF(LEN(K8)<50,"SHORT: "&LEN(K8),"LONG: "&LEN(K8)))) -> LONG: 66 | M8: AMC Conference 2022 23 - 24 March 2022 Navigating Africa's Unique Marketing Mix BOOK NOW Days Hours Minutes Seconds download prospectus To download the AMC 2022 Conference Prospectus please complete the form below: First Name Last Name Email Mobile Company I've read and agree to the Privacy Policy BOOK NOW FOR THE AMC CONFERENCE 2022 | N8: =IF(M8="","MISSING",IF(AND(LEN(M8)>=120,LEN(M8)<=160),"OK 120-160 chars",IF(LEN(M8)<120,"SHORT: "&LEN(M8),"LONG: "&LEN(M8)))) -> LONG: 335 | P8: =IF(OR(ISBLANK(O8),ISNUMBER(SEARCH("|",O8))),"FIX: MULTIPLE/MISSING","OK") -> FIX: MULTIPLE/MISSING | Q8: AMC Conference 2022 | download prospectus | BOOK NOW FOR THE AMC CONFERENCE 2022 | R8: =IF(ISBLANK(Q8),"MISSING","OK") -> OK | T8: =IF(ISBLANK(S8),"MISSING","OK") -> MISSING | V8: =IF(ISBLANK(U8),"MISSING","OK") -> MISSING | X8: =IF(ISBLANK(W8),"MISSING","OK") -> MISSING | Z8: =IF(ISBLANK(Y8),"MISSING","OK") -> MISSING | AA8: =HYPERLINK("https://africanmarketingconfederation.org/wp-admin/post.php?post=5619&action=elementor","Open in Elementor") -> Open in Elementor | AB8: =HYPERLINK("https://africanmarketingconfederation.org/wp-content/uploads/2026/03/og-image.png","View Image") -> View Image | AC8: =IF(LEN("https://africanmarketingconfederation.org/wp-content/uploads/2026/03/og-image.png")>0, _xlfn.IMAGE("https://africanmarketingconfederation.org/wp-content/uploads/2026/03/og-image.png"), "") -> #VALUE! | AD8: =IFERROR(HYPERLINK("#'Main'!B"&MATCH(TRIM(H8),Main!B:B,0),"Open in Main"),IFERROR(HYPERLINK("#'Technical Diagnostics'!A"&MATCH(TRIM(H8),'Technical Diagnostics'!A:A,0),"Open in Technical"),"Not Found")) -> Open in Main
A9: =IF(B9>=85,"Complete","Needs Copy") -> Needs Copy | B9: =MIN(100,ROUND(0.3*(IF(L9="",0,IF(LEFT(L9,7)="MISSING",0,IF(ISNUMBER(SEARCH("OK",L9)),100,IF(ISNUMBER(SEARCH("SHORT",L9)),65,IF(ISNUMBER(SEARCH("LONG",L9)),50,70))))))+0.25*(IF(N9="",0,IF(LEFT(N9,7)="MISSING",0,IF(ISNUMBER(SEARCH("OK",N9)),100,IF(ISNUMBER(SEARCH("SHORT",N9)),65,IF(ISNUMBER(SEARCH("LONG",N9)),50,70))))))+0.2*(IF(P9="",0,IF(LEFT(P9,2)="OK",100,0)))+0.08*(IF(R9="",0,IF(LEFT(R9,2)="OK",100,0)))+0.06*(IF(T9="",0,IF(LEFT(T9,2)="OK",100,0)))+0.05*(IF(V9="",0,IF(LEFT(V9,2)="OK",100,0)))+0.03*(IF(X9="",0,IF(LEFT(X9,2)="OK",100,0)))+0.03*(IF(Z9="",0,IF(LEFT(Z9,2)="OK",100,0))),0)) -> 42 | C9: 62.5 | D9: 60 | E9: 70 | F9: To Do | G9: Copy Writer | H9: =HYPERLINK("https://africanmarketingconfederation.org/amc-conference-2022-thank-you","https://africanmarketingconfederation.org/amc-conference-2022-thank-you") -> https://africanmarketingconfederation.org/amc-conference-2022-thank-you | I9: =HYPERLINK("https://africanmarketingconfederation.org/amc-conference-2022-thank-you","Amc Conference 2022 Thank You") -> Amc Conference 2022 Thank You | J9: amc-conference-2022-thank-you | K9: AMC Conference 2022 – Thank You – African Marketing Confederation | L9: =IF(K9="","MISSING",IF(AND(LEN(K9)>=50,LEN(K9)<=60),"OK 50-60 chars",IF(LEN(K9)<50,"SHORT: "&LEN(K9),"LONG: "&LEN(K9)))) -> LONG: 65 | M9: AMC Conference 2022 23 - 24 March 2022 Navigating Africa's Unique Marketing Mix ENQUIRE NOW Days Hours Minutes Seconds Success! Thank you for completing the enquiry form. Our team will contact you shortly! × Dismiss alert The AMC Conference is the must attend Pan African event for marketing professionals. It will focus on solutions for | N9: =IF(M9="","MISSING",IF(AND(LEN(M9)>=120,LEN(M9)<=160),"OK 120-160 chars",IF(LEN(M9)<120,"SHORT: "&LEN(M9),"LONG: "&LEN(M9)))) -> LONG: 337 | P9: =IF(OR(ISBLANK(O9),ISNUMBER(SEARCH("|",O9))),"FIX: MULTIPLE/MISSING","OK") -> FIX: MULTIPLE/MISSING | Q9: AMC Conference 2022 | WHO SHOULD ATTEND | Countries Participating | R9: =IF(ISBLANK(Q9),"MISSING","OK") -> OK | S9: South Africa | Nigeria | Morocco | T9: =IF(ISBLANK(S9),"MISSING","OK") -> OK | V9: =IF(ISBLANK(U9),"MISSING","OK") -> MISSING | X9: =IF(ISBLANK(W9),"MISSING","OK") -> MISSING | Z9: =IF(ISBLANK(Y9),"MISSING","OK") -> MISSING | AA9: =HYPERLINK("https://africanmarketingconfederation.org/wp-admin/post.php?post=4941&action=elementor","Open in Elementor") -> Open in Elementor | AB9: =HYPERLINK("https://africanmarketingconfederation.org/wp-content/uploads/2026/03/og-image.png","View Image") -> View Image | AC9: =IF(LEN("https://africanmarketingconfederation.org/wp-content/uploads/2026/03/og-image.png")>0, _xlfn.IMAGE("https://africanmarketingconfederation.org/wp-content/uploads/2026/03/og-image.png"), "") -> #VALUE! | AD9: =IFERROR(HYPERLINK("#'Main'!B"&MATCH(TRIM(H9),Main!B:B,0),"Open in Main"),IFERROR(HYPERLINK("#'Technical Diagnostics'!A"&MATCH(TRIM(H9),'Technical Diagnostics'!A:A,0),"Open in Technical"),"Not Found")) -> Open in Main
A10: =IF(B10>=85,"Complete","Needs Copy") -> Needs Copy | B10: =MIN(100,ROUND(0.3*(IF(L10="",0,IF(LEFT(L10,7)="MISSING",0,IF(ISNUMBER(SEARCH("OK",L10)),100,IF(ISNUMBER(SEARCH("SHORT",L10)),65,IF(ISNUMBER(SEARCH("LONG",L10)),50,70))))))+0.25*(IF(N10="",0,IF(LEFT(N10,7)="MISSING",0,IF(ISNUMBER(SEARCH("OK",N10)),100,IF(ISNUMBER(SEARCH("SHORT",N10)),65,IF(ISNUMBER(SEARCH("LONG",N10)),50,70))))))+0.2*(IF(P10="",0,IF(LEFT(P10,2)="OK",100,0)))+0.08*(IF(R10="",0,IF(LEFT(R10,2)="OK",100,0)))+0.06*(IF(T10="",0,IF(LEFT(T10,2)="OK",100,0)))+0.05*(IF(V10="",0,IF(LEFT(V10,2)="OK",100,0)))+0.03*(IF(X10="",0,IF(LEFT(X10,2)="OK",100,0)))+0.03*(IF(Z10="",0,IF(LEFT(Z10,2)="OK",100,0))),0)) -> 77 | C10: 77.5 | D10: 70 | E10: 100 | F10: To Do | G10: Copy Writer | H10: =HYPERLINK("https://africanmarketingconfederation.org/amc-conference-2023","https://africanmarketingconfederation.org/amc-conference-2023") -> https://africanmarketingconfederation.org/amc-conference-2023 | I10: =HYPERLINK("https://africanmarketingconfederation.org/amc-conference-2023","Amc Conference 2023") -> Amc Conference 2023 | J10: amc-conference-2023 | K10: AMC Conference 2023 – African Marketing Confederation | L10: =IF(K10="","MISSING",IF(AND(LEN(K10)>=50,LEN(K10)<=60),"OK 50-60 chars",IF(LEN(K10)<50,"SHORT: "&LEN(K10),"LONG: "&LEN(K10)))) -> OK 50-60 chars | M10: AMC Conference 6 - 9 September 2023 Imperial Botanical Beach Hotel, Entebbe, Uganda Thank you for joining us! View Presentations 2nd Annual African Marketing Confederation Conference Africa's $3.4 trillion Economy: Opportunities for Marketers Welcome to the Recap of the 2nd Annual African Marketing Conference: Unveiling Africa's $3.4 Trillion EconomyOur conference was a remarkable exploration of | N10: =IF(M10="","MISSING",IF(AND(LEN(M10)>=120,LEN(M10)<=160),"OK 120-160 chars",IF(LEN(M10)<120,"SHORT: "&LEN(M10),"LONG: "&LEN(M10)))) -> LONG: 398 | O10: AMC Conference | P10: =IF(OR(ISBLANK(O10),ISNUMBER(SEARCH("|",O10))),"FIX: MULTIPLE/MISSING","OK") -> OK | Q10: Africa's $3.4 trillion Economy: Opportunities for Marketers | Thank you for joining us! | Topics covered | R10: =IF(ISBLANK(Q10),"MISSING","OK") -> OK | S10: Africa Free Trade Area | Business Intelligence | T10: =IF(ISBLANK(S10),"MISSING","OK") -> OK | V10: =IF(ISBLANK(U10),"MISSING","OK") -> MISSING | X10: =IF(ISBLANK(W10),"MISSING","OK") -> MISSING | Z10: =IF(ISBLANK(Y10),"MISSING","OK") -> MISSING | AA10: =HYPERLINK("https://africanmarketingconfederation.org/wp-admin/post.php?post=12371&action=elementor","Open in Elementor") -> Open in Elementor | AB10: =HYPERLINK("https://africanmarketingconfederation.org/wp-content/uploads/2021/08/amc_faw.png","View Image") -> View Image | AC10: =IF(LEN("https://africanmarketingconfederation.org/wp-content/uploads/2021/08/amc_faw.png")>0, _xlfn.IMAGE("https://africanmarketingconfederation.org/wp-content/uploads/2021/08/amc_faw.png"), "") -> #VALUE! | AD10: =IFERROR(HYPERLINK("#'Main'!B"&MATCH(TRIM(H10),Main!B:B,0),"Open in Main"),IFERROR(HYPERLINK("#'Technical Diagnostics'!A"&MATCH(TRIM(H10),'Technical Diagnostics'!A:A,0),"Open in Technical"),"Not Found")) -> Open in Main
A11: =IF(B11>=85,"Complete","Needs Copy") -> Needs Copy | B11: =MIN(100,ROUND(0.3*(IF(L11="",0,IF(LEFT(L11,7)="MISSING",0,IF(ISNUMBER(SEARCH("OK",L11)),100,IF(ISNUMBER(SEARCH("SHORT",L11)),65,IF(ISNUMBER(SEARCH("LONG",L11)),50,70))))))+0.25*(IF(N11="",0,IF(LEFT(N11,7)="MISSING",0,IF(ISNUMBER(SEARCH("OK",N11)),100,IF(ISNUMBER(SEARCH("SHORT",N11)),65,IF(ISNUMBER(SEARCH("LONG",N11)),50,70))))))+0.2*(IF(P11="",0,IF(LEFT(P11,2)="OK",100,0)))+0.08*(IF(R11="",0,IF(LEFT(R11,2)="OK",100,0)))+0.06*(IF(T11="",0,IF(LEFT(T11,2)="OK",100,0)))+0.05*(IF(V11="",0,IF(LEFT(V11,2)="OK",100,0)))+0.03*(IF(X11="",0,IF(LEFT(X11,2)="OK",100,0)))+0.03*(IF(Z11="",0,IF(LEFT(Z11,2)="OK",100,0))),0)) -> 60 | C11: 77.5 | D11: 70 | E11: 100 | F11: To Do | G11: Copy Writer | H11: =HYPERLINK("https://africanmarketingconfederation.org/amc-conference-2023/amc-awards","https://africanmarketingconfederation.org/amc-conference-2023/amc-awards") -> https://africanmarketingconfederation.org/amc-conference-2023/amc-awards | I11: =HYPERLINK("https://africanmarketingconfederation.org/amc-conference-2023/amc-awards","Amc Awards") -> Amc Awards | J11: amc-awards | K11: AMC Awards – African Marketing Confederation | L11: =IF(K11="","MISSING",IF(AND(LEN(K11)>=50,LEN(K11)<=60),"OK 50-60 chars",IF(LEN(K11)<50,"SHORT: "&LEN(K11),"LONG: "&LEN(K11)))) -> SHORT: 44 | M11: AMC Awards Welcome to the prestigious African Marketing Confederation Awards, a distinguished event that celebrates and acknowledges the remarkable achievements, cutting-edge innovations, and exceptional leadership demonstrated by outstanding individuals within the dynamic realm of marketing across the expansive African region.During the 2nd Annual African Marketing Confederation Conference, held from 6th to 9th September at the | N11: =IF(M11="","MISSING",IF(AND(LEN(M11)>=120,LEN(M11)<=160),"OK 120-160 chars",IF(LEN(M11)<120,"SHORT: "&LEN(M11),"LONG: "&LEN(M11)))) -> LONG: 432 | O11: AMC Awards | P11: =IF(OR(ISBLANK(O11),ISNUMBER(SEARCH("|",O11))),"FIX: MULTIPLE/MISSING","OK") -> OK | Q11: AMC AWARD Winners | R11: =IF(ISBLANK(Q11),"MISSING","OK") -> OK | T11: =IF(ISBLANK(S11),"MISSING","OK") -> MISSING | V11: =IF(ISBLANK(U11),"MISSING","OK") -> MISSING | X11: =IF(ISBLANK(W11),"MISSING","OK") -> MISSING | Z11: =IF(ISBLANK(Y11),"MISSING","OK") -> MISSING | AA11: =HYPERLINK("https://africanmarketingconfederation.org/wp-admin/post.php?post=12954&action=elementor","Open in Elementor") -> Open in Elementor | AB11: =HYPERLINK("https://africanmarketingconfederation.org/wp-content/uploads/2021/08/amc_faw.png","View Image") -> View Image | AC11: =IF(LEN("https://africanmarketingconfederation.org/wp-content/uploads/2021/08/amc_faw.png")>0, _xlfn.IMAGE("https://africanmarketingconfederation.org/wp-content/uploads/2021/08/amc_faw.png"), "") -> #VALUE! | AD11: =IFERROR(HYPERLINK("#'Main'!B"&MATCH(TRIM(H11),Main!B:B,0),"Open in Main"),IFERROR(HYPERLINK("#'Technical Diagnostics'!A"&MATCH(TRIM(H11),'Technical Diagnostics'!A:A,0),"Open in Technical"),"Not Found")) -> Open in Main
A12: =IF(B12>=85,"Complete","Needs Copy") -> Needs Copy | B12: =MIN(100,ROUND(0.3*(IF(L12="",0,IF(LEFT(L12,7)="MISSING",0,IF(ISNUMBER(SEARCH("OK",L12)),100,IF(ISNUMBER(SEARCH("SHORT",L12)),65,IF(ISNUMBER(SEARCH("LONG",L12)),50,70))))))+0.25*(IF(N12="",0,IF(LEFT(N12,7)="MISSING",0,IF(ISNUMBER(SEARCH("OK",N12)),100,IF(ISNUMBER(SEARCH("SHORT",N12)),65,IF(ISNUMBER(SEARCH("LONG",N12)),50,70))))))+0.2*(IF(P12="",0,IF(LEFT(P12,2)="OK",100,0)))+0.08*(IF(R12="",0,IF(LEFT(R12,2)="OK",100,0)))+0.06*(IF(T12="",0,IF(LEFT(T12,2)="OK",100,0)))+0.05*(IF(V12="",0,IF(LEFT(V12,2)="OK",100,0)))+0.03*(IF(X12="",0,IF(LEFT(X12,2)="OK",100,0)))+0.03*(IF(Z12="",0,IF(LEFT(Z12,2)="OK",100,0))),0)) -> 46 | C12: 44.4 | D12: 50 | E12: 27.58 | F12: To Do | G12: Copy Writer | H12: =HYPERLINK("https://africanmarketingconfederation.org/amc-conference-2023/amc-awards-book-now","https://africanmarketingconfederation.org/amc-conference-2023/amc-awards-book-now") -> https://africanmarketingconfederation.org/amc-conference-2023/amc-awards-book-now | I12: =HYPERLINK("https://africanmarketingconfederation.org/amc-conference-2023/amc-awards-book-now","Amc Awards Book Now") -> Amc Awards Book Now | J12: amc-awards-book-now | K12: AMC Awards | Book Now – African Marketing Confederation | L12: =IF(K12="","MISSING",IF(AND(LEN(K12)>=50,LEN(K12)<=60),"OK 50-60 chars",IF(LEN(K12)<50,"SHORT: "&LEN(K12),"LONG: "&LEN(K12)))) -> OK 50-60 chars | M12: MISSING DESCRIPTION | N12: =IF(M12="","MISSING",IF(AND(LEN(M12)>=120,LEN(M12)<=160),"OK 120-160 chars",IF(LEN(M12)<120,"SHORT: "&LEN(M12),"LONG: "&LEN(M12)))) -> SHORT: 19 | P12: =IF(OR(ISBLANK(O12),ISNUMBER(SEARCH("|",O12))),"FIX: MULTIPLE/MISSING","OK") -> FIX: MULTIPLE/MISSING | R12: =IF(ISBLANK(Q12),"MISSING","OK") -> MISSING | T12: =IF(ISBLANK(S12),"MISSING","OK") -> MISSING | V12: =IF(ISBLANK(U12),"MISSING","OK") -> MISSING | X12: =IF(ISBLANK(W12),"MISSING","OK") -> MISSING | Z12: =IF(ISBLANK(Y12),"MISSING","OK") -> MISSING | AA12: =HYPERLINK("https://africanmarketingconfederation.org/wp-admin/post.php?post=13164&action=elementor","Open in Elementor") -> Open in Elementor | AB12: =HYPERLINK("https://africanmarketingconfederation.org/wp-content/uploads/2021/08/amc_faw.png","View Image") -> View Image | AC12: =IF(LEN("https://africanmarketingconfederation.org/wp-content/uploads/2021/08/amc_faw.png")>0, _xlfn.IMAGE("https://africanmarketingconfederation.org/wp-content/uploads/2021/08/amc_faw.png"), "") -> #VALUE! | AD12: =IFERROR(HYPERLINK("#'Main'!B"&MATCH(TRIM(H12),Main!B:B,0),"Open in Main"),IFERROR(HYPERLINK("#'Technical Diagnostics'!A"&MATCH(TRIM(H12),'Technical Diagnostics'!A:A,0),"Open in Technical"),"Not Found")) -> Open in Main

Sheet Issue Register
A1: URL | B1: Section | C1: Issue | D1: Severity | E1: Affected URL Count | F1: Reference Area | G1: Stable Issue ID | H1: Owner | I1: Sprint | J1: Status | K1: Affected URLs Sample | L1: Source Legacy Tab | M1: Source Row ID | N1: Open in Main | O1: Open in Reference | P1: BACK TO DASHBOARD
B2: AEO Opportunities | C2: Low AEO Readiness Score | D2: Warning | E2: 10 | F2: Content & AI Readiness | J2: Open | K2: https://africanmarketingconfederation.org/amc-awards-2024 | https://africanmarketingconfederation.org/african-marketing-confederation-tourism-chapter | https://africanmarketingconfederation.org/ | https://africanmarketingconfederation.org/about-us | https://africanmarketingconfederation.org/amc-conference-2022-prospectus | https://africanmarketingconfederation.org/amc-conference-2022-thank-you | https://africanmarketingconfederation.org/amc-conference-2022 | https://africanmarketingconfederation.org/amc-conference-2023 | https://africanmarketingconfederation.org/amc-conference-2023/amc-awards-book-now | https://africanmarketingconfederation.org/amc-conference-2023/amc-awards || Full list: see Content & AI Readiness tab | L2: Summary | M2: 2 | N2: =IFERROR(HYPERLINK("#'Main'!B"&MATCH(TRIM(A2),Main!B:B,0),"Open"),HYPERLINK("#'Main'!B1","Open")) -> Open | O2: =IFERROR(HYPERLINK("#"&F2&"!A"&MATCH(A2,INDIRECT("'"&F2&"'!A:A"),0),"Open"),HYPERLINK("#"&F2&"!A1","Open")) -> Open
B3: AEO Opportunities | C3: Missing FAQ/QA Schema | D3: Warning | E3: 0 | F3: Content & AI Readiness | J3: Open | K3: || Full list: see Content & AI Readiness tab | L3: Summary | M3: 3 | N3: =IFERROR(HYPERLINK("#'Main'!B"&MATCH(TRIM(A3),Main!B:B,0),"Open"),HYPERLINK("#'Main'!B1","Open")) -> Open | O3: =IFERROR(HYPERLINK("#"&F3&"!A"&MATCH(A3,INDIRECT("'"&F3&"'!A:A"),0),"Open"),HYPERLINK("#"&F3&"!A1","Open")) -> Open
B4: AEO Opportunities | C4: No 40-60 Word Answer Paragraphs | D4: Observation | E4: 10 | F4: Content & AI Readiness | J4: Open | K4: https://africanmarketingconfederation.org/amc-awards-2024 | https://africanmarketingconfederation.org/african-marketing-confederation-tourism-chapter | https://africanmarketingconfederation.org/ | https://africanmarketingconfederation.org/about-us | https://africanmarketingconfederation.org/amc-conference-2022-prospectus | https://africanmarketingconfederation.org/amc-conference-2022-thank-you | https://africanmarketingconfederation.org/amc-conference-2022 | https://africanmarketingconfederation.org/amc-conference-2023 | https://africanmarketingconfederation.org/amc-conference-2023/amc-awards-book-now | https://africanmarketingconfederation.org/amc-conference-2023/amc-awards || Full list: see Content & AI Readiness tab | L4: Summary | M4: 4 | N4: =IFERROR(HYPERLINK("#'Main'!B"&MATCH(TRIM(A4),Main!B:B,0),"Open"),HYPERLINK("#'Main'!B1","Open")) -> Open | O4: =IFERROR(HYPERLINK("#"&F4&"!A"&MATCH(A4,INDIRECT("'"&F4&"'!A:A"),0),"Open"),HYPERLINK("#"&F4&"!A1","Open")) -> Open
B5: AEO Opportunities | C5: No Answer-Friendly Structure | D5: Observation | E5: 10 | F5: Content & AI Readiness | J5: Open | K5: https://africanmarketingconfederation.org/amc-awards-2024 | https://africanmarketingconfederation.org/african-marketing-confederation-tourism-chapter | https://africanmarketingconfederation.org/ | https://africanmarketingconfederation.org/about-us | https://africanmarketingconfederation.org/amc-conference-2022-prospectus | https://africanmarketingconfederation.org/amc-conference-2022-thank-you | https://africanmarketingconfederation.org/amc-conference-2022 | https://africanmarketingconfederation.org/amc-conference-2023 | https://africanmarketingconfederation.org/amc-conference-2023/amc-awards-book-now | https://africanmarketingconfederation.org/amc-conference-2023/amc-awards || Full list: see Content & AI Readiness tab | L5: Summary | M5: 5 | N5: =IFERROR(HYPERLINK("#'Main'!B"&MATCH(TRIM(A5),Main!B:B,0),"Open"),HYPERLINK("#'Main'!B1","Open")) -> Open | O5: =IFERROR(HYPERLINK("#"&F5&"!A"&MATCH(A5,INDIRECT("'"&F5&"'!A:A"),0),"Open"),HYPERLINK("#"&F5&"!A1","Open")) -> Open
B6: AEO Opportunities | C6: No Question Headings | D6: Observation | E6: 10 | F6: Content & AI Readiness | J6: Open | K6: https://africanmarketingconfederation.org/amc-awards-2024 | https://africanmarketingconfederation.org/african-marketing-confederation-tourism-chapter | https://africanmarketingconfederation.org/ | https://africanmarketingconfederation.org/about-us | https://africanmarketingconfederation.org/amc-conference-2022-prospectus | https://africanmarketingconfederation.org/amc-conference-2022-thank-you | https://africanmarketingconfederation.org/amc-conference-2022 | https://africanmarketingconfederation.org/amc-conference-2023 | https://africanmarketingconfederation.org/amc-conference-2023/amc-awards-book-now | https://africanmarketingconfederation.org/amc-conference-2023/amc-awards || Full list: see Content & AI Readiness tab | L6: Summary | M6: 6 | N6: =IFERROR(HYPERLINK("#'Main'!B"&MATCH(TRIM(A6),Main!B:B,0),"Open"),HYPERLINK("#'Main'!B1","Open")) -> Open | O6: =IFERROR(HYPERLINK("#"&F6&"!A"&MATCH(A6,INDIRECT("'"&F6&"'!A:A"),0),"Open"),HYPERLINK("#"&F6&"!A1","Open")) -> Open
B7: AEO Opportunities | E7: 0 | J7: Open | K7: Detailed rows: see Content & AI Readiness tab | L7: Summary | M7: 7 | N7: =IFERROR(HYPERLINK("#'Main'!B"&MATCH(TRIM(A7),Main!B:B,0),"Open"),HYPERLINK("#'Main'!B1","Open")) -> Open | O7: =IFERROR(HYPERLINK("#"&F7&"!A"&MATCH(A7,INDIRECT("'"&F7&"'!A:A"),0),"Open"),HYPERLINK("#"&F7&"!A1","Open")) -> Open
B8: Issue Counts | C8: Broken Internal Links | D8: Critical | E8: 0 | F8: Link Intelligence | J8: Open | K8: || Full list: see Technical Diagnostics / Link Intelligence tabs | L8: Summary | M8: 8 | N8: =IFERROR(HYPERLINK("#'Main'!B"&MATCH(TRIM(A8),Main!B:B,0),"Open"),HYPERLINK("#'Main'!B1","Open")) -> Open | O8: =IFERROR(HYPERLINK("#"&F8&"!A"&MATCH(A8,INDIRECT("'"&F8&"'!A:A"),0),"Open"),HYPERLINK("#"&F8&"!A1","Open")) -> Open
B9: Issue Counts | C9: CWV LCP Above 4.0s | D9: Critical | E9: 0 | F9: Technical Diagnostics | J9: Open | K9: || Full list: see Technical Diagnostics / Link Intelligence tabs | L9: Summary | M9: 9 | N9: =IFERROR(HYPERLINK("#'Main'!B"&MATCH(TRIM(A9),Main!B:B,0),"Open"),HYPERLINK("#'Main'!B1","Open")) -> Open | O9: =IFERROR(HYPERLINK("#"&F9&"!A"&MATCH(A9,INDIRECT("'"&F9&"'!A:A"),0),"Open"),HYPERLINK("#"&F9&"!A1","Open")) -> Open
B10: Issue Counts | C10: Canonical Points Elsewhere | D10: Critical | E10: 0 | F10: Technical Diagnostics | J10: Open | K10: || Full list: see Technical Diagnostics / Link Intelligence tabs | L10: Summary | M10: 10 | N10: =IFERROR(HYPERLINK("#'Main'!B"&MATCH(TRIM(A10),Main!B:B,0),"Open"),HYPERLINK("#'Main'!B1","Open")) -> Open | O10: =IFERROR(HYPERLINK("#"&F10&"!A"&MATCH(A10,INDIRECT("'"&F10&"'!A:A"),0),"Open"),HYPERLINK("#"&F10&"!A1","Open")) -> Open
B11: Issue Counts | C11: Missing Title | D11: Critical | E11: 0 | F11: Technical Diagnostics | J11: Open | K11: || Full list: see Technical Diagnostics / Link Intelligence tabs | L11: Summary | M11: 11 | N11: =IFERROR(HYPERLINK("#'Main'!B"&MATCH(TRIM(A11),Main!B:B,0),"Open"),HYPERLINK("#'Main'!B1","Open")) -> Open | O11: =IFERROR(HYPERLINK("#"&F11&"!A"&MATCH(A11,INDIRECT("'"&F11&"'!A:A"),0),"Open"),HYPERLINK("#"&F11&"!A1","Open")) -> Open
B12: Issue Counts | C12: Noindex Directive | D12: Critical | E12: 0 | F12: Technical Diagnostics | J12: Open | K12: || Full list: see Technical Diagnostics / Link Intelligence tabs | L12: Summary | M12: 12 | N12: =IFERROR(HYPERLINK("#'Main'!B"&MATCH(TRIM(A12),Main!B:B,0),"Open"),HYPERLINK("#'Main'!B1","Open")) -> Open | O12: =IFERROR(HYPERLINK("#"&F12&"!A"&MATCH(A12,INDIRECT("'"&F12&"'!A:A"),0),"Open"),HYPERLINK("#"&F12&"!A1","Open")) -> Open
B13: Issue Counts | C13: Non-200 Status | D13: Critical | E13: 0 | F13: Technical Diagnostics | J13: Open | K13: || Full list: see Technical Diagnostics / Link Intelligence tabs | L13: Summary | M13: 13 | N13: =IFERROR(HYPERLINK("#'Main'!B"&MATCH(TRIM(A13),Main!B:B,0),"Open"),HYPERLINK("#'Main'!B1","Open")) -> Open | O13: =IFERROR(HYPERLINK("#"&F13&"!A"&MATCH(A13,INDIRECT("'"&F13&"'!A:A"),0),"Open"),HYPERLINK("#"&F13&"!A1","Open")) -> Open
B14: Issue Counts | C14: Robots.txt Disallow Root | D14: Critical | E14: 0 | F14: Technical Diagnostics | J14: Open | K14: || Full list: see Technical Diagnostics / Link Intelligence tabs | L14: Summary | M14: 14 | N14: =IFERROR(HYPERLINK("#'Main'!B"&MATCH(TRIM(A14),Main!B:B,0),"Open"),HYPERLINK("#'Main'!B1","Open")) -> Open | O14: =IFERROR(HYPERLINK("#"&F14&"!A"&MATCH(A14,INDIRECT("'"&F14&"'!A:A"),0),"Open"),HYPERLINK("#"&F14&"!A1","Open")) -> Open
B15: Issue Counts | C15: Low AEO Readiness Score | D15: Warning | E15: 10 | F15: Content & AI Readiness | J15: Open | K15: https://africanmarketingconfederation.org/amc-awards-2024 | https://africanmarketingconfederation.org/african-marketing-confederation-tourism-chapter | https://africanmarketingconfederation.org/ | https://africanmarketingconfederation.org/about-us | https://africanmarketingconfederation.org/amc-conference-2022-prospectus | https://africanmarketingconfederation.org/amc-conference-2022-thank-you | https://africanmarketingconfederation.org/amc-conference-2022 | https://africanmarketingconfederation.org/amc-conference-2023 | https://africanmarketingconfederation.org/amc-conference-2023/amc-awards-book-now | https://africanmarketingconfederation.org/amc-conference-2023/amc-awards || Full list: see Technical Diagnostics / Link Intelligence tabs | L15: Summary | M15: 15 | N15: =IFERROR(HYPERLINK("#'Main'!B"&MATCH(TRIM(A15),Main!B:B,0),"Open"),HYPERLINK("#'Main'!B1","Open")) -> Open | O15: =IFERROR(HYPERLINK("#"&F15&"!A"&MATCH(A15,INDIRECT("'"&F15&"'!A:A"),0),"Open"),HYPERLINK("#"&F15&"!A1","Open")) -> Open
B16: Issue Counts | C16: Low Image Alt Coverage | D16: Warning | E16: 10 | F16: Technical Diagnostics | J16: Open | K16: https://africanmarketingconfederation.org/amc-awards-2024 | https://africanmarketingconfederation.org/african-marketing-confederation-tourism-chapter | https://africanmarketingconfederation.org/ | https://africanmarketingconfederation.org/about-us | https://africanmarketingconfederation.org/amc-conference-2022-prospectus | https://africanmarketingconfederation.org/amc-conference-2022-thank-you | https://africanmarketingconfederation.org/amc-conference-2022 | https://africanmarketingconfederation.org/amc-conference-2023 | https://africanmarketingconfederation.org/amc-conference-2023/amc-awards-book-now | https://africanmarketingconfederation.org/amc-conference-2023/amc-awards || Full list: see Technical Diagnostics / Link Intelligence tabs | L16: Summary | M16: 16 | N16: =IFERROR(HYPERLINK("#'Main'!B"&MATCH(TRIM(A16),Main!B:B,0),"Open"),HYPERLINK("#'Main'!B1","Open")) -> Open | O16: =IFERROR(HYPERLINK("#"&F16&"!A"&MATCH(A16,INDIRECT("'"&F16&"'!A:A"),0),"Open"),HYPERLINK("#"&F16&"!A1","Open")) -> Open
B17: Issue Counts | C17: Missing H1 | D17: Warning | E17: 4 | F17: Technical Diagnostics | J17: Open | K17: https://africanmarketingconfederation.org/amc-conference-2022-prospectus | https://africanmarketingconfederation.org/amc-conference-2022-thank-you | https://africanmarketingconfederation.org/amc-conference-2022 | https://africanmarketingconfederation.org/amc-conference-2023/amc-awards-book-now || Full list: see Technical Diagnostics / Link Intelligence tabs | L17: Summary | M17: 17 | N17: =IFERROR(HYPERLINK("#'Main'!B"&MATCH(TRIM(A17),Main!B:B,0),"Open"),HYPERLINK("#'Main'!B1","Open")) -> Open | O17: =IFERROR(HYPERLINK("#"&F17&"!A"&MATCH(A17,INDIRECT("'"&F17&"'!A:A"),0),"Open"),HYPERLINK("#"&F17&"!A1","Open")) -> Open
B18: Issue Counts | C18: Multiple H1 | D18: Warning | E18: 3 | F18: Technical Diagnostics | J18: Open | K18: https://africanmarketingconfederation.org/amc-awards-2024 | https://africanmarketingconfederation.org/african-marketing-confederation-tourism-chapter | https://africanmarketingconfederation.org/ || Full list: see Technical Diagnostics / Link Intelligence tabs | L18: Summary | M18: 18 | N18: =IFERROR(HYPERLINK("#'Main'!B"&MATCH(TRIM(A18),Main!B:B,0),"Open"),HYPERLINK("#'Main'!B1","Open")) -> Open | O18: =IFERROR(HYPERLINK("#"&F18&"!A"&MATCH(A18,INDIRECT("'"&F18&"'!A:A"),0),"Open"),HYPERLINK("#"&F18&"!A1","Open")) -> Open
B19: Issue Counts | C19: Missing Meta Description | D19: Warning | E19: 1 | F19: Technical Diagnostics | J19: Open | K19: https://africanmarketingconfederation.org/amc-conference-2023/amc-awards-book-now || Full list: see Technical Diagnostics / Link Intelligence tabs | L19: Summary | M19: 19 | N19: =IFERROR(HYPERLINK("#'Main'!B"&MATCH(TRIM(A19),Main!B:B,0),"Open"),HYPERLINK("#'Main'!B1","Open")) -> Open | O19: =IFERROR(HYPERLINK("#"&F19&"!A"&MATCH(A19,INDIRECT("'"&F19&"'!A:A"),0),"Open"),HYPERLINK("#"&F19&"!A1","Open")) -> Open
... B41: Issue Counts | C41: llms.txt Missing | D41: Observation | E41: 0 | F41: Technical Diagnostics | J41: Open | K41: || Full list: see Technical Diagnostics / Link Intelligence tabs | L41: Summary | M41: 41 | N41: =IFERROR(HYPERLINK("#'Main'!B"&MATCH(TRIM(A41),Main!B:B,0),"Open"),HYPERLINK("#'Main'!B1","Open")) -> Open | O41: =IFERROR(HYPERLINK("#"&F41&"!A"&MATCH(A41,INDIRECT("'"&F41&"'!A:A"),0),"Open"),HYPERLINK("#"&F41&"!A1","Open")) -> Open
B42: Issue Counts | E42: 0 | J42: Open | L42: Summary | M42: 42 | N42: =IFERROR(HYPERLINK("#'Main'!B"&MATCH(TRIM(A42),Main!B:B,0),"Open"),HYPERLINK("#'Main'!B1","Open")) -> Open | O42: =IFERROR(HYPERLINK("#"&F42&"!A"&MATCH(A42,INDIRECT("'"&F42&"'!A:A"),0),"Open"),HYPERLINK("#"&F42&"!A1","Open")) -> Open
B43: Top 10 Critical URLs | E43: 0 | J43: Open | L43: Summary | M43: 43 | N43: =IFERROR(HYPERLINK("#'Main'!B"&MATCH(TRIM(A43),Main!B:B,0),"Open"),HYPERLINK("#'Main'!B1","Open")) -> Open | O43: =IFERROR(HYPERLINK("#"&F43&"!A"&MATCH(A43,INDIRECT("'"&F43&"'!A:A"),0),"Open"),HYPERLINK("#"&F43&"!A1","Open")) -> Open
B44: Top Issues by Template | E44: 0 | J44: Open | L44: Summary | M44: 44 | N44: =IFERROR(HYPERLINK("#'Main'!B"&MATCH(TRIM(A44),Main!B:B,0),"Open"),HYPERLINK("#'Main'!B1","Open")) -> Open | O44: =IFERROR(HYPERLINK("#"&F44&"!A"&MATCH(A44,INDIRECT("'"&F44&"'!A:A"),0),"Open"),HYPERLINK("#"&F44&"!A1","Open")) -> Open
B45: Top Issues by Template | C45: /amc-conference-2023/ -> Low Image Alt Coverage | D45: Observation | E45: 3 | F45: Template & Duplication Risks | J45: Open | L45: Summary | M45: 45 | N45: =IFERROR(HYPERLINK("#'Main'!B"&MATCH(TRIM(A45),Main!B:B,0),"Open"),HYPERLINK("#'Main'!B1","Open")) -> Open | O45: =IFERROR(HYPERLINK("#"&F45&"!A"&MATCH(A45,INDIRECT("'"&F45&"'!A:A"),0),"Open"),HYPERLINK("#"&F45&"!A1","Open")) -> Open
B46: Top Issues by Template | C46: /amc-conference-2023/ -> Low AEO Readiness Score | D46: Observation | E46: 3 | F46: Template & Duplication Risks | J46: Open | L46: Summary | M46: 46 | N46: =IFERROR(HYPERLINK("#'Main'!B"&MATCH(TRIM(A46),Main!B:B,0),"Open"),HYPERLINK("#'Main'!B1","Open")) -> Open | O46: =IFERROR(HYPERLINK("#"&F46&"!A"&MATCH(A46,INDIRECT("'"&F46&"'!A:A"),0),"Open"),HYPERLINK("#"&F46&"!A1","Open")) -> Open
B47: Top Issues by Template | C47: /amc-conference-2023/ -> No ETag Header | D47: Observation | E47: 3 | F47: Template & Duplication Risks | J47: Open | L47: Summary | M47: 47 | N47: =IFERROR(HYPERLINK("#'Main'!B"&MATCH(TRIM(A47),Main!B:B,0),"Open"),HYPERLINK("#'Main'!B1","Open")) -> Open | O47: =IFERROR(HYPERLINK("#"&F47&"!A"&MATCH(A47,INDIRECT("'"&F47&"'!A:A"),0),"Open"),HYPERLINK("#"&F47&"!A1","Open")) -> Open
B48: Top Issues by Template | C48: /amc-conference-2023/ -> No Question Headings | D48: Observation | E48: 3 | F48: Template & Duplication Risks | J48: Open | L48: Summary | M48: 48 | N48: =IFERROR(HYPERLINK("#'Main'!B"&MATCH(TRIM(A48),Main!B:B,0),"Open"),HYPERLINK("#'Main'!B1","Open")) -> Open | O48: =IFERROR(HYPERLINK("#"&F48&"!A"&MATCH(A48,INDIRECT("'"&F48&"'!A:A"),0),"Open"),HYPERLINK("#"&F48&"!A1","Open")) -> Open
B49: Top Issues by Template | C49: /amc-conference-2023/ -> No Answer-Friendly Structure | D49: Observation | E49: 3 | F49: Template & Duplication Risks | J49: Open | L49: Summary | M49: 49 | N49: =IFERROR(HYPERLINK("#'Main'!B"&MATCH(TRIM(A49),Main!B:B,0),"Open"),HYPERLINK("#'Main'!B1","Open")) -> Open | O49: =IFERROR(HYPERLINK("#"&F49&"!A"&MATCH(A49,INDIRECT("'"&F49&"'!A:A"),0),"Open"),HYPERLINK("#"&F49&"!A1","Open")) -> Open
B50: Top Issues by Template | C50: /amc-conference-2023/ -> No 40-60 Word Answer Paragraphs | D50: Observation | E50: 3 | F50: Template & Duplication Risks | J50: Open | L50: Summary | M50: 50 | N50: =IFERROR(HYPERLINK("#'Main'!B"&MATCH(TRIM(A50),Main!B:B,0),"Open"),HYPERLINK("#'Main'!B1","Open")) -> Open | O50: =IFERROR(HYPERLINK("#"&F50&"!A"&MATCH(A50,INDIRECT("'"&F50&"'!A:A"),0),"Open"),HYPERLINK("#"&F50&"!A1","Open")) -> Open
B51: Top Issues by Template | C51: /amc-conference-2023/ -> AI Crawlers Not Explicitly Allowed | D51: Observation | E51: 3 | F51: Template & Duplication Risks | J51: Open | L51: Summary | M51: 51 | N51: =IFERROR(HYPERLINK("#'Main'!B"&MATCH(TRIM(A51),Main!B:B,0),"Open"),HYPERLINK("#'Main'!B1","Open")) -> Open | O51: =IFERROR(HYPERLINK("#"&F51&"!A"&MATCH(A51,INDIRECT("'"&F51&"'!A:A"),0),"Open"),HYPERLINK("#"&F51&"!A1","Open")) -> Open
B52: Top Issues by Template | C52: /amc-conference-2023/ -> Missing Meta Description | D52: Observation | E52: 1 | F52: Template & Duplication Risks | J52: Open | L52: Summary | M52: 52 | N52: =IFERROR(HYPERLINK("#'Main'!B"&MATCH(TRIM(A52),Main!B:B,0),"Open"),HYPERLINK("#'Main'!B1","Open")) -> Open | O52: =IFERROR(HYPERLINK("#"&F52&"!A"&MATCH(A52,INDIRECT("'"&F52&"'!A:A"),0),"Open"),HYPERLINK("#"&F52&"!A1","Open")) -> Open
B53: Top Issues by Template | C53: /amc-conference-2023/ -> Missing H1 | D53: Observation | E53: 1 | F53: Template & Duplication Risks | J53: Open | L53: Summary | M53: 53 | N53: =IFERROR(HYPERLINK("#'Main'!B"&MATCH(TRIM(A53),Main!B:B,0),"Open"),HYPERLINK("#'Main'!B1","Open")) -> Open | O53: =IFERROR(HYPERLINK("#"&F53&"!A"&MATCH(A53,INDIRECT("'"&F53&"'!A:A"),0),"Open"),HYPERLINK("#"&F53&"!A1","Open")) -> Open
B54: Top Issues by Template | C54: /amc-conference-2023/ -> Thin Content | D54: Observation | E54: 1 | F54: Template & Duplication Risks | J54: Open | L54: Summary | M54: 54 | N54: =IFERROR(HYPERLINK("#'Main'!B"&MATCH(TRIM(A54),Main!B:B,0),"Open"),HYPERLINK("#'Main'!B1","Open")) -> Open | O54: =IFERROR(HYPERLINK("#"&F54&"!A"&MATCH(A54,INDIRECT("'"&F54&"'!A:A"),0),"Open"),HYPERLINK("#"&F54&"!A1","Open")) -> Open
B55: Top Issues by Template | C55: /amc-awards-2024/ -> Multiple H1 | D55: Observation | E55: 1 | F55: Template & Duplication Risks | J55: Open | L55: Summary | M55: 55 | N55: =IFERROR(HYPERLINK("#'Main'!B"&MATCH(TRIM(A55),Main!B:B,0),"Open"),HYPERLINK("#'Main'!B1","Open")) -> Open | O55: =IFERROR(HYPERLINK("#"&F55&"!A"&MATCH(A55,INDIRECT("'"&F55&"'!A:A"),0),"Open"),HYPERLINK("#"&F55&"!A1","Open")) -> Open
B56: Top Issues by Template | C56: /amc-awards-2024/ -> Low Image Alt Coverage | D56: Observation | E56: 1 | F56: Template & Duplication Risks | J56: Open | L56: Summary | M56: 56 | N56: =IFERROR(HYPERLINK("#'Main'!B"&MATCH(TRIM(A56),Main!B:B,0),"Open"),HYPERLINK("#'Main'!B1","Open")) -> Open | O56: =IFERROR(HYPERLINK("#"&F56&"!A"&MATCH(A56,INDIRECT("'"&F56&"'!A:A"),0),"Open"),HYPERLINK("#"&F56&"!A1","Open")) -> Open
... B64: Top Issues by Template | C64: /african-marketing-confederation-tourism-chapter/ -> Low Image Alt Coverage | D64: Observation | E64: 1 | F64: Template & Duplication Risks | J64: Open | L64: Summary | M64: 64 | N64: =IFERROR(HYPERLINK("#'Main'!B"&MATCH(TRIM(A64),Main!B:B,0),"Open"),HYPERLINK("#'Main'!B1","Open")) -> Open | O64: =IFERROR(HYPERLINK("#"&F64&"!A"&MATCH(A64,INDIRECT("'"&F64&"'!A:A"),0),"Open"),HYPERLINK("#"&F64&"!A1","Open")) -> Open
A65: https://africanmarketingconfederation.org/amc-awards-2024 | B65: Issue Inventory | C65: Multiple H1 | D65: Warning | E65: 1 | F65: Technical Diagnostics | G65: https://africanmarketingconfederation.org/amc-awards-2024::multiple_h1 | H65: Copy Writer | J65: Open | K65: https://africanmarketingconfederation.org/amc-awards-2024 | L65: IssueInventory | M65: 2 | N65: =IFERROR(HYPERLINK("#'Main'!B"&MATCH(TRIM(A65),Main!B:B,0),"Open"),HYPERLINK("#'Main'!B1","Open")) -> Open | O65: =IFERROR(HYPERLINK("#"&F65&"!A"&MATCH(A65,INDIRECT("'"&F65&"'!A:A"),0),"Open"),HYPERLINK("#"&F65&"!A1","Open")) -> Open
A66: https://africanmarketingconfederation.org/amc-awards-2024 | B66: Issue Inventory | C66: Low Image Alt Coverage | D66: Warning | E66: 1 | F66: Technical Diagnostics | G66: https://africanmarketingconfederation.org/amc-awards-2024::low_image_alt_coverage | H66: Copy Writer | J66: Open | K66: https://africanmarketingconfederation.org/amc-awards-2024 | L66: IssueInventory | M66: 3 | N66: =IFERROR(HYPERLINK("#'Main'!B"&MATCH(TRIM(A66),Main!B:B,0),"Open"),HYPERLINK("#'Main'!B1","Open")) -> Open | O66: =IFERROR(HYPERLINK("#"&F66&"!A"&MATCH(A66,INDIRECT("'"&F66&"'!A:A"),0),"Open"),HYPERLINK("#"&F66&"!A1","Open")) -> Open
A67: https://africanmarketingconfederation.org/amc-awards-2024 | B67: Issue Inventory | C67: Low AEO Readiness Score | D67: Warning | E67: 1 | F67: Content & AI Readiness | G67: https://africanmarketingconfederation.org/amc-awards-2024::low_aeo_readiness_score | H67: Copy Writer | J67: Open | K67: https://africanmarketingconfederation.org/amc-awards-2024 | L67: IssueInventory | M67: 4 | N67: =IFERROR(HYPERLINK("#'Main'!B"&MATCH(TRIM(A67),Main!B:B,0),"Open"),HYPERLINK("#'Main'!B1","Open")) -> Open | O67: =IFERROR(HYPERLINK("#"&F67&"!A"&MATCH(A67,INDIRECT("'"&F67&"'!A:A"),0),"Open"),HYPERLINK("#"&F67&"!A1","Open")) -> Open
A68: https://africanmarketingconfederation.org/amc-awards-2024 | B68: Issue Inventory | C68: No ETag Header | D68: Observation | E68: 1 | F68: Technical Diagnostics | G68: https://africanmarketingconfederation.org/amc-awards-2024::no_etag_header | H68: Server/Host | J68: Open | K68: https://africanmarketingconfederation.org/amc-awards-2024 | L68: IssueInventory | M68: 5 | N68: =IFERROR(HYPERLINK("#'Main'!B"&MATCH(TRIM(A68),Main!B:B,0),"Open"),HYPERLINK("#'Main'!B1","Open")) -> Open | O68: =IFERROR(HYPERLINK("#"&F68&"!A"&MATCH(A68,INDIRECT("'"&F68&"'!A:A"),0),"Open"),HYPERLINK("#"&F68&"!A1","Open")) -> Open
A69: https://africanmarketingconfederation.org/amc-awards-2024 | B69: Issue Inventory | C69: No Question Headings | D69: Observation | E69: 1 | F69: Content & AI Readiness | G69: https://africanmarketingconfederation.org/amc-awards-2024::no_question_headings | H69: Copy Writer | J69: Open | K69: https://africanmarketingconfederation.org/amc-awards-2024 | L69: IssueInventory | M69: 6 | N69: =IFERROR(HYPERLINK("#'Main'!B"&MATCH(TRIM(A69),Main!B:B,0),"Open"),HYPERLINK("#'Main'!B1","Open")) -> Open | O69: =IFERROR(HYPERLINK("#"&F69&"!A"&MATCH(A69,INDIRECT("'"&F69&"'!A:A"),0),"Open"),HYPERLINK("#"&F69&"!A1","Open")) -> Open
A70: https://africanmarketingconfederation.org/amc-awards-2024 | B70: Issue Inventory | C70: No Answer-Friendly Structure | D70: Observation | E70: 1 | F70: Technical Diagnostics | G70: https://africanmarketingconfederation.org/amc-awards-2024::no_answer-friendly_structure | H70: Copy Writer | J70: Open | K70: https://africanmarketingconfederation.org/amc-awards-2024 | L70: IssueInventory | M70: 7 | N70: =IFERROR(HYPERLINK("#'Main'!B"&MATCH(TRIM(A70),Main!B:B,0),"Open"),HYPERLINK("#'Main'!B1","Open")) -> Open | O70: =IFERROR(HYPERLINK("#"&F70&"!A"&MATCH(A70,INDIRECT("'"&F70&"'!A:A"),0),"Open"),HYPERLINK("#"&F70&"!A1","Open")) -> Open
A71: https://africanmarketingconfederation.org/amc-awards-2024 | B71: Issue Inventory | C71: No 40-60 Word Answer Paragraphs | D71: Observation | E71: 1 | F71: Technical Diagnostics | G71: https://africanmarketingconfederation.org/amc-awards-2024::no_40-60_word_answer_paragraphs | H71: Copy Writer | J71: Open | K71: https://africanmarketingconfederation.org/amc-awards-2024 | L71: IssueInventory | M71: 8 | N71: =IFERROR(HYPERLINK("#'Main'!B"&MATCH(TRIM(A71),Main!B:B,0),"Open"),HYPERLINK("#'Main'!B1","Open")) -> Open | O71: =IFERROR(HYPERLINK("#"&F71&"!A"&MATCH(A71,INDIRECT("'"&F71&"'!A:A"),0),"Open"),HYPERLINK("#"&F71&"!A1","Open")) -> Open
A72: https://africanmarketingconfederation.org/amc-awards-2024 | B72: Issue Inventory | C72: AI Crawlers Not Explicitly Allowed | D72: Observation | E72: 1 | F72: Technical Diagnostics | G72: https://africanmarketingconfederation.org/amc-awards-2024::ai_crawlers_not_explicitly_allowed | H72: Copy Writer | J72: Open | K72: https://africanmarketingconfederation.org/amc-awards-2024 | L72: IssueInventory | M72: 9 | N72: =IFERROR(HYPERLINK("#'Main'!B"&MATCH(TRIM(A72),Main!B:B,0),"Open"),HYPERLINK("#'Main'!B1","Open")) -> Open | O72: =IFERROR(HYPERLINK("#"&F72&"!A"&MATCH(A72,INDIRECT("'"&F72&"'!A:A"),0),"Open"),HYPERLINK("#"&F72&"!A1","Open")) -> Open
A73: https://africanmarketingconfederation.org/african-marketing-confederation-tourism-chapter | B73: Issue Inventory | C73: Multiple H1 | D73: Warning | E73: 1 | F73: Technical Diagnostics | G73: https://africanmarketingconfederation.org/african-marketing-confederation-tourism-chapter::multiple_h1 | H73: Copy Writer | J73: Open | K73: https://africanmarketingconfederation.org/african-marketing-confederation-tourism-chapter | L73: IssueInventory | M73: 10 | N73: =IFERROR(HYPERLINK("#'Main'!B"&MATCH(TRIM(A73),Main!B:B,0),"Open"),HYPERLINK("#'Main'!B1","Open")) -> Open | O73: =IFERROR(HYPERLINK("#"&F73&"!A"&MATCH(A73,INDIRECT("'"&F73&"'!A:A"),0),"Open"),HYPERLINK("#"&F73&"!A1","Open")) -> Open
A74: https://africanmarketingconfederation.org/african-marketing-confederation-tourism-chapter | B74: Issue Inventory | C74: Low Image Alt Coverage | D74: Warning | E74: 1 | F74: Technical Diagnostics | G74: https://africanmarketingconfederation.org/african-marketing-confederation-tourism-chapter::low_image_alt_coverage | H74: Copy Writer | J74: Open | K74: https://africanmarketingconfederation.org/african-marketing-confederation-tourism-chapter | L74: IssueInventory | M74: 11 | N74: =IFERROR(HYPERLINK("#'Main'!B"&MATCH(TRIM(A74),Main!B:B,0),"Open"),HYPERLINK("#'Main'!B1","Open")) -> Open | O74: =IFERROR(HYPERLINK("#"&F74&"!A"&MATCH(A74,INDIRECT("'"&F74&"'!A:A"),0),"Open"),HYPERLINK("#"&F74&"!A1","Open")) -> Open
A75: https://africanmarketingconfederation.org/african-marketing-confederation-tourism-chapter | B75: Issue Inventory | C75: Low AEO Readiness Score | D75: Warning | E75: 1 | F75: Content & AI Readiness | G75: https://africanmarketingconfederation.org/african-marketing-confederation-tourism-chapter::low_aeo_readiness_score | H75: Copy Writer | J75: Open | K75: https://africanmarketingconfederation.org/african-marketing-confederation-tourism-chapter | L75: IssueInventory | M75: 12 | N75: =IFERROR(HYPERLINK("#'Main'!B"&MATCH(TRIM(A75),Main!B:B,0),"Open"),HYPERLINK("#'Main'!B1","Open")) -> Open | O75: =IFERROR(HYPERLINK("#"&F75&"!A"&MATCH(A75,INDIRECT("'"&F75&"'!A:A"),0),"Open"),HYPERLINK("#"&F75&"!A1","Open")) -> Open
A76: https://africanmarketingconfederation.org/african-marketing-confederation-tourism-chapter | B76: Issue Inventory | C76: No ETag Header | D76: Observation | E76: 1 | F76: Technical Diagnostics | G76: https://africanmarketingconfederation.org/african-marketing-confederation-tourism-chapter::no_etag_header | H76: Server/Host | J76: Open | K76: https://africanmarketingconfederation.org/african-marketing-confederation-tourism-chapter | L76: IssueInventory | M76: 13 | N76: =IFERROR(HYPERLINK("#'Main'!B"&MATCH(TRIM(A76),Main!B:B,0),"Open"),HYPERLINK("#'Main'!B1","Open")) -> Open | O76: =IFERROR(HYPERLINK("#"&F76&"!A"&MATCH(A76,INDIRECT("'"&F76&"'!A:A"),0),"Open"),HYPERLINK("#"&F76&"!A1","Open")) -> Open
... A148: https://africanmarketingconfederation.org/amc-conference-2023/amc-awards | B148: Issue Inventory | C148: AI Crawlers Not Explicitly Allowed | D148: Observation | E148: 1 | F148: Technical Diagnostics | G148: https://africanmarketingconfederation.org/amc-conference-2023/amc-awards::ai_crawlers_not_explicitly_allowed | H148: Copy Writer | J148: Open | K148: https://africanmarketingconfederation.org/amc-conference-2023/amc-awards | L148: IssueInventory | M148: 85 | N148: =IFERROR(HYPERLINK("#'Main'!B"&MATCH(TRIM(A148),Main!B:B,0),"Open"),HYPERLINK("#'Main'!B1","Open")) -> Open | O148: =IFERROR(HYPERLINK("#"&F148&"!A"&MATCH(A148,INDIRECT("'"&F148&"'!A:A"),0),"Open"),HYPERLINK("#"&F148&"!A1","Open")) -> Open

Sheet Technical Diagnostics
A1: URL | B1: Diagnostic Category | C1: Status Code | D1: Severity Badge | E1: SEO Health Score | F1: Pass Flag | G1: Critical Issues Count | H1: Warning Issues Count | I1: Extraction State | J1: Extraction Source | K1: Indexability Reason | L1: Canonical Type | M1: Redirect Chain Length | N1: Redirect Loop Flag | O1: Strict-Transport-Security | P1: Content-Security-Policy | Q1: X-Content-Type-Options | R1: Desktop PSI Score | S1: Mobile PSI Score | T1: Mobile LCP (s) | U1: Mobile CLS | V1: Mobile TTFB (s) | W1: Final URL | X1: Canonical URL | Y1: Meta Robots Raw | Z1: X-Robots-Tag | AA1: Source Legacy Tab | AB1: Open in Main | AC1: BACK TO DASHBOARD
A2: https://africanmarketingconfederation.org/amc-awards-2024 | B2: Technical | Indexability | C2: 200 | D2: Warning | E2: 60 | F2: Non-Pass | G2: 0 | H2: 3 | I2: partial | J2: rendered_browser | K2: Indexable | L2: self | M2: 0 | N2: FALSE | R2: 0 | S2: 0 | T2: 0 | U2: 0 | V2: 0 | W2: https://africanmarketingconfederation.org/amc-awards-2024 | X2: https://africanmarketingconfederation.org/amc-awards-2024 | Y2: max-image-preview:large | AA2: Technical | Indexability | AB2: =IFERROR(HYPERLINK("#'Main'!B"&MATCH(TRIM(A2),Main!B:B,0),"Open"),HYPERLINK("#'Main'!B1","Open")) -> Open
A3: https://africanmarketingconfederation.org/african-marketing-confederation-tourism-chapter | B3: Technical | Indexability | C3: 200 | D3: Warning | E3: 60 | F3: Non-Pass | G3: 0 | H3: 3 | I3: partial | J3: rendered_browser | K3: Indexable | L3: self | M3: 0 | N3: FALSE | R3: 0 | S3: 0 | T3: 0 | U3: 0 | V3: 0 | W3: https://africanmarketingconfederation.org/african-marketing-confederation-tourism-chapter | X3: https://africanmarketingconfederation.org/african-marketing-confederation-tourism-chapter | Y3: max-image-preview:large | AA3: Technical | Indexability | AB3: =IFERROR(HYPERLINK("#'Main'!B"&MATCH(TRIM(A3),Main!B:B,0),"Open"),HYPERLINK("#'Main'!B1","Open")) -> Open
A4: https://africanmarketingconfederation.org/ | B4: Technical | Indexability | C4: 200 | D4: Warning | E4: 60 | F4: Non-Pass | G4: 0 | H4: 3 | I4: partial | J4: rendered_browser | K4: Indexable | L4: self | M4: 0 | N4: FALSE | R4: 0 | S4: 0 | T4: 0 | U4: 0 | V4: 0 | W4: https://africanmarketingconfederation.org/ | X4: https://africanmarketingconfederation.org/ | Y4: max-image-preview:large | AA4: Technical | Indexability | AB4: =IFERROR(HYPERLINK("#'Main'!B"&MATCH(TRIM(A4),Main!B:B,0),"Open"),HYPERLINK("#'Main'!B1","Open")) -> Open
A5: https://africanmarketingconfederation.org/about-us | B5: Technical | Indexability | C5: 200 | D5: Warning | E5: 70 | F5: Non-Pass | G5: 0 | H5: 2 | I5: partial | J5: rendered_browser | K5: Indexable | L5: self | M5: 0 | N5: FALSE | R5: 0 | S5: 0 | T5: 0 | U5: 0 | V5: 0 | W5: https://africanmarketingconfederation.org/about-us | X5: https://africanmarketingconfederation.org/about-us | Y5: max-image-preview:large | AA5: Technical | Indexability | AB5: =IFERROR(HYPERLINK("#'Main'!B"&MATCH(TRIM(A5),Main!B:B,0),"Open"),HYPERLINK("#'Main'!B1","Open")) -> Open
A6: https://africanmarketingconfederation.org/amc-conference-2022-prospectus | B6: Technical | Indexability | C6: 200 | D6: Warning | E6: 60 | F6: Non-Pass | G6: 0 | H6: 3 | I6: partial | J6: rendered_browser | K6: Indexable | L6: self | M6: 0 | N6: FALSE | R6: 0 | S6: 0 | T6: 0 | U6: 0 | V6: 0 | W6: https://africanmarketingconfederation.org/amc-conference-2022-prospectus | X6: https://africanmarketingconfederation.org/amc-conference-2022-prospectus | Y6: max-image-preview:large | AA6: Technical | Indexability | AB6: =IFERROR(HYPERLINK("#'Main'!B"&MATCH(TRIM(A6),Main!B:B,0),"Open"),HYPERLINK("#'Main'!B1","Open")) -> Open
A7: https://africanmarketingconfederation.org/amc-conference-2022-thank-you | B7: Technical | Indexability | C7: 200 | D7: Warning | E7: 60 | F7: Non-Pass | G7: 0 | H7: 3 | I7: partial | J7: rendered_browser | K7: Indexable | L7: self | M7: 0 | N7: FALSE | R7: 0 | S7: 0 | T7: 0 | U7: 0 | V7: 0 | W7: https://africanmarketingconfederation.org/amc-conference-2022-thank-you | X7: https://africanmarketingconfederation.org/amc-conference-2022-thank-you | Y7: max-image-preview:large | AA7: Technical | Indexability | AB7: =IFERROR(HYPERLINK("#'Main'!B"&MATCH(TRIM(A7),Main!B:B,0),"Open"),HYPERLINK("#'Main'!B1","Open")) -> Open
A8: https://africanmarketingconfederation.org/amc-conference-2022 | B8: Technical | Indexability | C8: 200 | D8: Warning | E8: 60 | F8: Non-Pass | G8: 0 | H8: 3 | I8: partial | J8: rendered_browser | K8: Indexable | L8: self | M8: 0 | N8: FALSE | R8: 0 | S8: 0 | T8: 0 | U8: 0 | V8: 0 | W8: https://africanmarketingconfederation.org/amc-conference-2022 | X8: https://africanmarketingconfederation.org/amc-conference-2022 | Y8: max-image-preview:large | AA8: Technical | Indexability | AB8: =IFERROR(HYPERLINK("#'Main'!B"&MATCH(TRIM(A8),Main!B:B,0),"Open"),HYPERLINK("#'Main'!B1","Open")) -> Open
A9: https://africanmarketingconfederation.org/amc-conference-2023 | B9: Technical | Indexability | C9: 200 | D9: Warning | E9: 70 | F9: Non-Pass | G9: 0 | H9: 2 | I9: partial | J9: rendered_browser | K9: Indexable | L9: self | M9: 0 | N9: FALSE | R9: 0 | S9: 0 | T9: 0 | U9: 0 | V9: 0 | W9: https://africanmarketingconfederation.org/amc-conference-2023 | X9: https://africanmarketingconfederation.org/amc-conference-2023 | Y9: max-image-preview:large | AA9: Technical | Indexability | AB9: =IFERROR(HYPERLINK("#'Main'!B"&MATCH(TRIM(A9),Main!B:B,0),"Open"),HYPERLINK("#'Main'!B1","Open")) -> Open
A10: https://africanmarketingconfederation.org/amc-conference-2023/amc-awards-book-now | B10: Technical | Indexability | C10: 200 | D10: Warning | E10: 50 | F10: Non-Pass | G10: 0 | H10: 4 | I10: partial | J10: rendered_browser | K10: Indexable | L10: self | M10: 0 | N10: FALSE | R10: 0 | S10: 0 | T10: 0 | U10: 0 | V10: 0 | W10: https://africanmarketingconfederation.org/amc-conference-2023/amc-awards-book-now | X10: https://africanmarketingconfederation.org/amc-conference-2023/amc-awards-book-now | Y10: max-image-preview:large | AA10: Technical | Indexability | AB10: =IFERROR(HYPERLINK("#'Main'!B"&MATCH(TRIM(A10),Main!B:B,0),"Open"),HYPERLINK("#'Main'!B1","Open")) -> Open
A11: https://africanmarketingconfederation.org/amc-conference-2023/amc-awards | B11: Technical | Indexability | C11: 200 | D11: Warning | E11: 70 | F11: Non-Pass | G11: 0 | H11: 2 | I11: partial | J11: rendered_browser | K11: Indexable | L11: self | M11: 0 | N11: FALSE | R11: 0 | S11: 0 | T11: 0 | U11: 0 | V11: 0 | W11: https://africanmarketingconfederation.org/amc-conference-2023/amc-awards | X11: https://africanmarketingconfederation.org/amc-conference-2023/amc-awards | Y11: max-image-preview:large | AA11: Technical | Indexability | AB11: =IFERROR(HYPERLINK("#'Main'!B"&MATCH(TRIM(A11),Main!B:B,0),"Open"),HYPERLINK("#'Main'!B1","Open")) -> Open

Sheet Content & AI Readiness
A1: URL | B1: Content Category | C1: Word Count | D1: Readability (Rough Flesch) | E1: Thin Content Flag | F1: H1 Count | G1: Missing H1 Flag | H1: Meta Description Missing | I1: AEO Readiness Score | J1: AEO Badge | K1: Schema Types Count | L1: Schema Types Found | M1: Schema Parse Errors | N1: Question Heading Count | O1: FAQ Section Count | P1: Image Count | Q1: Images Missing Alt | R1: Image Alt Coverage (%) | S1: AEO Extractability Score | T1: Title Missing | U1: Media Mixed Content Detected | V1: Source Legacy Tab | W1: Open in Main | X1: BACK TO DASHBOARD
A2: https://africanmarketingconfederation.org/amc-awards-2024 | B2: Content | AEO | Media | C2: 1637 | D2: 179.14 | E2: FALSE | F2: 2 | G2: FALSE | H2: FALSE | I2: 30 | J2: Needs Work | K2: 0 | M2: 0 | N2: 0 | O2: 0 | P2: 47 | Q2: 25 | R2: 46.81 | S2: 0 | T2: FALSE | U2: FALSE | V2: Content | AEO | Media | W2: =IFERROR(HYPERLINK("#'Main'!B"&MATCH(TRIM(A2),Main!B:B,0),"Open"),HYPERLINK("#'Main'!B1","Open")) -> Open
A3: https://africanmarketingconfederation.org/african-marketing-confederation-tourism-chapter | B3: Content | AEO | Media | C3: 339 | D3: 180.37 | E3: FALSE | F3: 2 | G3: FALSE | H3: FALSE | I3: 30 | J3: Needs Work | K3: 0 | M3: 0 | N3: 0 | O3: 0 | P3: 25 | Q3: 9 | R3: 64 | S3: 0 | T3: FALSE | U3: FALSE | V3: Content | AEO | Media | W3: =IFERROR(HYPERLINK("#'Main'!B"&MATCH(TRIM(A3),Main!B:B,0),"Open"),HYPERLINK("#'Main'!B1","Open")) -> Open
A4: https://africanmarketingconfederation.org/ | B4: Content | AEO | Media | C4: 37 | D4: 188.06 | E4: TRUE | F4: 5 | G4: FALSE | H4: FALSE | I4: 30 | J4: Needs Work | K4: 0 | M4: 0 | N4: 0 | O4: 0 | P4: 55 | Q4: 13 | R4: 76.36 | S4: 0 | T4: FALSE | U4: FALSE | V4: Content | AEO | Media | W4: =IFERROR(HYPERLINK("#'Main'!B"&MATCH(TRIM(A4),Main!B:B,0),"Open"),HYPERLINK("#'Main'!B1","Open")) -> Open
A5: https://africanmarketingconfederation.org/about-us | B5: Content | AEO | Media | C5: 235 | D5: 172.76 | E5: TRUE | F5: 1 | G5: FALSE | H5: FALSE | I5: 30 | J5: Needs Work | K5: 0 | M5: 0 | N5: 0 | O5: 0 | P5: 44 | Q5: 12 | R5: 72.73 | S5: 0 | T5: FALSE | U5: FALSE | V5: Content | AEO | Media | W5: =IFERROR(HYPERLINK("#'Main'!B"&MATCH(TRIM(A5),Main!B:B,0),"Open"),HYPERLINK("#'Main'!B1","Open")) -> Open
A6: https://africanmarketingconfederation.org/amc-conference-2022-prospectus | B6: Content | AEO | Media | C6: 120 | D6: 145.94 | E6: TRUE | F6: 0 | G6: TRUE | H6: FALSE | I6: 30 | J6: Needs Work | K6: 0 | M6: 0 | N6: 0 | O6: 0 | P6: 23 | Q6: 8 | R6: 65.22 | S6: 0 | T6: FALSE | U6: FALSE | V6: Content | AEO | Media | W6: =IFERROR(HYPERLINK("#'Main'!B"&MATCH(TRIM(A6),Main!B:B,0),"Open"),HYPERLINK("#'Main'!B1","Open")) -> Open
A7: https://africanmarketingconfederation.org/amc-conference-2022-thank-you | B7: Content | AEO | Media | C7: 367 | D7: 178.18 | E7: FALSE | F7: 0 | G7: TRUE | H7: FALSE | I7: 30 | J7: Needs Work | K7: 0 | M7: 0 | N7: 0 | O7: 0 | P7: 30 | Q7: 15 | R7: 50 | S7: 0 | T7: FALSE | U7: FALSE | V7: Content | AEO | Media | W7: =IFERROR(HYPERLINK("#'Main'!B"&MATCH(TRIM(A7),Main!B:B,0),"Open"),HYPERLINK("#'Main'!B1","Open")) -> Open
A8: https://africanmarketingconfederation.org/amc-conference-2022 | B8: Content | AEO | Media | C8: 32 | D8: 196.01 | E8: TRUE | F8: 0 | G8: TRUE | H8: FALSE | I8: 30 | J8: Needs Work | K8: 0 | M8: 0 | N8: 0 | O8: 0 | P8: 28 | Q8: 13 | R8: 53.57 | S8: 0 | T8: FALSE | U8: FALSE | V8: Content | AEO | Media | W8: =IFERROR(HYPERLINK("#'Main'!B"&MATCH(TRIM(A8),Main!B:B,0),"Open"),HYPERLINK("#'Main'!B1","Open")) -> Open
A9: https://africanmarketingconfederation.org/amc-conference-2023 | B9: Content | AEO | Media | C9: 415 | D9: 168.54 | E9: FALSE | F9: 1 | G9: FALSE | H9: FALSE | I9: 30 | J9: Needs Work | K9: 0 | M9: 0 | N9: 0 | O9: 0 | P9: 56 | Q9: 37 | R9: 33.93 | S9: 0 | T9: FALSE | U9: FALSE | V9: Content | AEO | Media | W9: =IFERROR(HYPERLINK("#'Main'!B"&MATCH(TRIM(A9),Main!B:B,0),"Open"),HYPERLINK("#'Main'!B1","Open")) -> Open
A10: https://africanmarketingconfederation.org/amc-conference-2023/amc-awards-book-now | B10: Content | AEO | Media | C10: 31 | D10: 175.37 | E10: TRUE | F10: 0 | G10: TRUE | H10: TRUE | I10: 30 | J10: Needs Work | K10: 0 | M10: 0 | N10: 0 | O10: 0 | P10: 20 | Q10: 5 | R10: 75 | S10: 0 | T10: FALSE | U10: FALSE | V10: Content | AEO | Media | W10: =IFERROR(HYPERLINK("#'Main'!B"&MATCH(TRIM(A10),Main!B:B,0),"Open"),HYPERLINK("#'Main'!B1","Open")) -> Open
A11: https://africanmarketingconfederation.org/amc-conference-2023/amc-awards | B11: Content | AEO | Media | C11: 326 | D11: 176.75 | E11: FALSE | F11: 1 | G11: FALSE | H11: FALSE | I11: 30 | J11: Needs Work | K11: 0 | M11: 0 | N11: 0 | O11: 0 | P11: 25 | Q11: 7 | R11: 72 | S11: 0 | T11: FALSE | U11: FALSE | V11: Content | AEO | Media | W11: =IFERROR(HYPERLINK("#'Main'!B"&MATCH(TRIM(A11),Main!B:B,0),"Open"),HYPERLINK("#'Main'!B1","Open")) -> Open

Sheet Link Intelligence
A1: URL | B1: Record Type | C1: Target URL | D1: Anchor Text | E1: Target Status (if crawled) | F1: Crawlable | G1: Internal Links Count | H1: Broken Internal Links Count | I1: Unresolved Internal Links Count | J1: External Links Count | K1: Inlinks Count | L1: Orphan Candidate | M1: Click Depth | N1: Internal PageRank | O1: Generic Anchor Text Count | P1: Nofollow Internal Links Count | Q1: Nofollow External Links Count | R1: Internal Link Statuses | S1: Source Legacy Tab | T1: Open in Main | U1: BACK TO DASHBOARD
A2: https://africanmarketingconfederation.org/amc-awards-2024 | B2: Summary | G2: 16 | H2: 0 | I2: 0 | J2: 4 | K2: 0 | L2: TRUE | M2: 0 | N2: 0.019665 | O2: 0 | P2: 0 | Q2: 0 | R2: https://africanmarketingconfederation.org/amc-conference-2025 => 200 | https://africanmarketingconfederation.org/amc-conference-2025-delegate-packages => 404 | https://africanmarketingconfederation.org/amc-marketing-conference-2024/amc-programme-2025 => 200 | https://africanmarketingconfederation.org/amc-marketing-conference-2024/awards-2025 => 200 | https://africanmarketingconfederation.org/amc-sponsors-2025 => 200 | https://africanmarketingconfederation.org/conference-faq-2025 => 200 | https://africanmarketingconfederation.org/privacy-policy => 200 | https://africanmarketingconfederation.org/publications-2 => 200 | https://africanmarketingconfederation.org/speakers-2025 => 200 | S2: Links | T2: =IFERROR(HYPERLINK("#'Main'!B"&MATCH(TRIM(A2),Main!B:B,0),"Open"),HYPERLINK("#'Main'!B1","Open")) -> Open
A3: https://africanmarketingconfederation.org/african-marketing-confederation-tourism-chapter | B3: Summary | G3: 58 | H3: 0 | I3: 0 | J3: 3 | K3: 6 | L3: FALSE | M3: 1 | N3: 0.271899 | O3: 0 | P3: 0 | Q3: 0 | R3: https://africanmarketingconfederation.org/ => 200 | https://africanmarketingconfederation.org/about-us => 200 | https://africanmarketingconfederation.org/african-marketing-confederation-tourism-chapter => 200 | https://africanmarketingconfederation.org/amc-conference-2025-delegate-packages => 404 | https://africanmarketingconfederation.org/amc-conference-2025-highlights => 200 | https://africanmarketingconfederation.org/amc-conference-2026 => 200 | https://africanmarketingconfederation.org/certified-professional-marketer-africa => 200 | https://africanmarketingconfederation.org/chartered-marketer-africa => 200 | https://africanmarketingconfederation.org/contact-us => 200 | https://africanmarketingconfederation.org/education => 200 | https://africanmarketingconfederation.org/members => 200 | https://africanmarketingconfederation.org/news-articles => 200 | https://africanmarketingconfederation.org/privacy-policy => 200 | https://africanmarketingconfederation.org/publications-2 => 200 | https://africanmarketingconfederation.org/sub-committees => 200 | S3: Links | T3: =IFERROR(HYPERLINK("#'Main'!B"&MATCH(TRIM(A3),Main!B:B,0),"Open"),HYPERLINK("#'Main'!B1","Open")) -> Open
A4: https://africanmarketingconfederation.org/ | B4: Summary | G4: 62 | H4: 0 | I4: 0 | J4: 2 | K4: 8 | L4: FALSE | M4: 0 | N4: 0.287449 | O4: 3 | P4: 0 | Q4: 0 | R4: https://africanmarketingconfederation.org/ => 200 | https://africanmarketingconfederation.org/about-us => 200 | https://africanmarketingconfederation.org/african-marketing-confederation-tourism-chapter => 200 | https://africanmarketingconfederation.org/amc-conference-2025 => 200 | https://africanmarketingconfederation.org/amc-conference-2025-delegate-packages => 404 | https://africanmarketingconfederation.org/amc-conference-2026 => 200 | https://africanmarketingconfederation.org/certified-professional-marketer-africa => 200 | https://africanmarketingconfederation.org/chartered-marketer-africa => 200 | https://africanmarketingconfederation.org/contact-us => 200 | https://africanmarketingconfederation.org/cost-of-groceries-the-primary-worry-for-almost-half-of-sa-consumers => 200 | https://africanmarketingconfederation.org/cracking-the-africa-code-the-functional-path-to-market-leadership => 200 | https://africanmarketingconfederation.org/education => 200 | https://africanmarketingconfederation.org/lays-world-cup-marketing-strategy-focuses-on-fan-fun-and-togetherness => 200 | https://africanmarketingconfederation.org/members => 200 | https://africanmarketingconfederation.org/national-foods-holdings-expands-food-processing-capacity-in-zimbabwe => 200 | https://africanmarketingconfederation.org/news-articles => 200 | https://africanmarketingconfederation.org/privacy-policy => 200 | https://africanmarketingconfederation.org/publications-2 => 200 | https://africanmarketingconfederation.org/social-media-overtakes-television-as-main-source-of-news-for-kenyans => 200 | https://africanmarketingconfederation.org/sub-committees => 200 | https://africanmarketingconfederation.org/subscribe => 200 | https://africanmarketingconfederation.org/traceability-giving-africa-a-marketing-edge-the-world-can-audit => 200 | S4: Links | T4: =IFERROR(HYPERLINK("#'Main'!B"&MATCH(TRIM(A4),Main!B:B,0),"Open"),HYPERLINK("#'Main'!B1","Open")) -> Open
A5: https://africanmarketingconfederation.org/about-us | B5: Summary | G5: 32 | H5: 0 | I5: 0 | J5: 7 | K5: 6 | L5: FALSE | M5: 1 | N5: 0.271899 | O5: 0 | P5: 0 | Q5: 0 | R5: https://africanmarketingconfederation.org/ => 200 | https://africanmarketingconfederation.org/about-us => 200 | https://africanmarketingconfederation.org/african-marketing-confederation-tourism-chapter => 200 | https://africanmarketingconfederation.org/amc-conference-2025-delegate-packages => 404 | https://africanmarketingconfederation.org/amc-conference-2026 => 200 | https://africanmarketingconfederation.org/certified-professional-marketer-africa => 200 | https://africanmarketingconfederation.org/chartered-marketer-africa => 200 | https://africanmarketingconfederation.org/contact-us => 200 | https://africanmarketingconfederation.org/education => 200 | https://africanmarketingconfederation.org/members => 200 | https://africanmarketingconfederation.org/news-articles => 200 | https://africanmarketingconfederation.org/privacy-policy => 200 | https://africanmarketingconfederation.org/publications-2 => 200 | https://africanmarketingconfederation.org/sub-committees => 200 | S5: Links | T5: =IFERROR(HYPERLINK("#'Main'!B"&MATCH(TRIM(A5),Main!B:B,0),"Open"),HYPERLINK("#'Main'!B1","Open")) -> Open
A6: https://africanmarketingconfederation.org/amc-conference-2022-prospectus | B6: Summary | G6: 32 | H6: 0 | I6: 0 | J6: 4 | K6: 0 | L6: TRUE | M6: 0 | N6: 0.019665 | O6: 0 | P6: 0 | Q6: 0 | R6: https://africanmarketingconfederation.org/ => 200 | https://africanmarketingconfederation.org/about-us => 200 | https://africanmarketingconfederation.org/african-marketing-confederation-tourism-chapter => 200 | https://africanmarketingconfederation.org/amc-conference-2025-delegate-packages => 404 | https://africanmarketingconfederation.org/amc-conference-2026 => 200 | https://africanmarketingconfederation.org/certified-professional-marketer-africa => 200 | https://africanmarketingconfederation.org/chartered-marketer-africa => 200 | https://africanmarketingconfederation.org/contact-us => 200 | https://africanmarketingconfederation.org/education => 200 | https://africanmarketingconfederation.org/members => 200 | https://africanmarketingconfederation.org/news-articles => 200 | https://africanmarketingconfederation.org/privacy-policy => 200 | https://africanmarketingconfederation.org/publications-2 => 200 | https://africanmarketingconfederation.org/sub-committees => 200 | S6: Links | T6: =IFERROR(HYPERLINK("#'Main'!B"&MATCH(TRIM(A6),Main!B:B,0),"Open"),HYPERLINK("#'Main'!B1","Open")) -> Open
A7: https://africanmarketingconfederation.org/amc-conference-2022-thank-you | B7: Summary | G7: 32 | H7: 0 | I7: 0 | J7: 2 | K7: 0 | L7: TRUE | M7: 0 | N7: 0.019665 | O7: 0 | P7: 0 | Q7: 0 | R7: https://africanmarketingconfederation.org/ => 200 | https://africanmarketingconfederation.org/about-us => 200 | https://africanmarketingconfederation.org/african-marketing-confederation-tourism-chapter => 200 | https://africanmarketingconfederation.org/amc-conference-2025-delegate-packages => 404 | https://africanmarketingconfederation.org/amc-conference-2026 => 200 | https://africanmarketingconfederation.org/certified-professional-marketer-africa => 200 | https://africanmarketingconfederation.org/chartered-marketer-africa => 200 | https://africanmarketingconfederation.org/contact-us => 200 | https://africanmarketingconfederation.org/education => 200 | https://africanmarketingconfederation.org/members => 200 | https://africanmarketingconfederation.org/news-articles => 200 | https://africanmarketingconfederation.org/privacy-policy => 200 | https://africanmarketingconfederation.org/publications-2 => 200 | https://africanmarketingconfederation.org/sub-committees => 200 | https://africanmarketingconfederation.org/wp-content/uploads/2021/11/AMC-2022_Prospectus-low-res.pdf => 404 | S7: Links | T7: =IFERROR(HYPERLINK("#'Main'!B"&MATCH(TRIM(A7),Main!B:B,0),"Open"),HYPERLINK("#'Main'!B1","Open")) -> Open
A8: https://africanmarketingconfederation.org/amc-conference-2022 | B8: Summary | G8: 99 | H8: 0 | I8: 0 | J8: 3 | K8: 0 | L8: TRUE | M8: 0 | N8: 0.019665 | O8: 0 | P8: 0 | Q8: 0 | R8: https://africanmarketingconfederation.org/ => 200 | https://africanmarketingconfederation.org/2024-amc-awards-recognise-marketing-excellence-from-the-continent => 200 | https://africanmarketingconfederation.org/about-us => 200 | https://africanmarketingconfederation.org/african-marketing-confederation-tourism-chapter => 200 | https://africanmarketingconfederation.org/amc-conference-2025 => 200 | https://africanmarketingconfederation.org/amc-conference-2025-delegate-packages => 404 | https://africanmarketingconfederation.org/amc-conference-2026 => 200 | https://africanmarketingconfederation.org/amc-marketing-conference-2024/amc-programme-2025 => 200 | https://africanmarketingconfederation.org/amc-marketing-conference-2024/awards-2025 => 200 | https://africanmarketingconfederation.org/amc-officially-welcomes-new-member-associations-into-the-fold => 200 | https://africanmarketingconfederation.org/amc-sponsors-2025 => 200 | https://africanmarketingconfederation.org/certified-professional-marketer-africa => 200 | https://africanmarketingconfederation.org/chartered-marketer-africa => 200 | https://africanmarketingconfederation.org/conference-faq-2025 => 200 | https://africanmarketingconfederation.org/contact-us => 200 | https://africanmarketingconfederation.org/education => 200 | https://africanmarketingconfederation.org/excitement-as-ghana-announced-as-host-of-2025-amc-marketing-conference => 200 | https://africanmarketingconfederation.org/how-a-bold-strategy-saved-kiwi-marketing-association-from-extinction => 200 | https://africanmarketingconfederation.org/marketers-are-placing-the-ads-where-consumers-dont-want-to-see-them => 200 | https://africanmarketingconfederation.org/members => 200 | https://africanmarketingconfederation.org/news-articles => 200 | https://africanmarketingconfederation.org/privacy-policy => 200 | https://africanmarketingconfederation.org/publications-2 => 200 | https://africanmarketingconfederation.org/speakers-2025 => 200 | https://africanmarketingconfederation.org/sub-committees => 200 | https://africanmarketingconfederation.org/time-for-africa-to-control-its-own-narrative-and-image-delegates-told => 200 | https://africanmarketingconfederation.org/wp-content/uploads/2022/10/EA2A2394-scaled.jpg => 200 | https://africanmarketingconfederation.org/wp-content/uploads/2022/10/EA2A2427-scaled.jpg => 200 | https://africanmarketingconfederation.org/wp-content/uploads/2022/10/EA2A2487-scaled.jpg => 200 | https://africanmarketingconfederation.org/wp-content/uploads/2022/10/EA2A2512-scaled.jpg => 200 | https://africanmarketingconfederation.org/wp-content/uploads/2022/10/EA2A2525-scaled.jpg => 200 | https://africanmarketingconfederation.org/wp-content/uploads/2022/10/EA2A2527-scaled.jpg => 200 | https://africanmarketingconfederation.org/wp-content/uploads/2022/10/EA2A2536-scaled.jpg => 200 | https://africanmarketingconfederation.org/wp-content/uploads/2022/10/EA2A2999-scaled.jpg => 200 | https://africanmarketingconfederation.org/wp-content/uploads/2022/10/EA2A3057-scaled.jpg => 200 | https://africanmarketingconfederation.org/wp-content/uploads/2022/10/EA2A3111-scaled.jpg => 200 | https://africanmarketingconfederation.org/wp-content/uploads/2022/10/EA2A3195-scaled.jpg => 200 | https://africanmarketingconfederation.org/wp-content/uploads/2022/10/EA2A3198-scaled.jpg => 200 | https://africanmarketingconfederation.org/wp-content/uploads/2022/10/EA2A3217-scaled.jpg => 200 | https://africanmarketingconfederation.org/wp-content/uploads/2022/10/EA2A3254-scaled.jpg => 200 | https://africanmarketingconfederation.org/wp-content/uploads/2022/10/EA2A3268-scaled.jpg => 200 | https://africanmarketingconfederation.org/wp-content/uploads/2022/10/EA2A3293-scaled.jpg => 200 | https://africanmarketingconfederation.org/wp-content/uploads/2022/10/EA2A3369-scaled.jpg => 200 | https://africanmarketingconfederation.org/wp-content/uploads/2022/10/EA2A3396-scaled.jpg => 200 | https://africanmarketingconfederation.org/wp-content/uploads/2022/10/EA2A3485-scaled.jpg => 200 | https://africanmarketingconfederation.org/wp-content/uploads/2022/10/EA2A3505-scaled.jpg => 200 | https://africanmarketingconfederation.org/wp-content/uploads/2022/10/EA2A3816-scaled.jpg => 200 | https://africanmarketingconfederation.org/wp-content/uploads/2022/10/EA2A3869-scaled.jpg => 200 | https://africanmarketingconfederation.org/wp-content/uploads/2022/10/EA2A3879-scaled.jpg => 200 | https://africanmarketingconfederation.org/wp-content/uploads/2022/10/EA2A3892-scaled.jpg => 200 | https://africanmarketingconfederation.org/wp-content/uploads/2022/10/EA2A3922-scaled.jpg => 200 | https://africanmarketingconfederation.org/wp-content/uploads/2022/10/EA2A3930-scaled.jpg => 200 | https://africanmarketingconfederation.org/wp-content/uploads/2022/10/EA2A3936-scaled.jpg => 200 | https://africanmarketingconfederation.org/wp-content/uploads/2022/10/EA2A4027-scaled.jpg => 200 | https://africanmarketingconfederation.org/wp-content/uploads/2022/10/EA2A4067-scaled.jpg => 200 | https://africanmarketingconfederation.org/wp-content/uploads/2022/10/EA2A4121-scaled.jpg => 200 | https://africanmarketingconfederation.org/wp-content/uploads/2022/10/EA2A4137-scaled.jpg => 200 | https://africanmarketingconfederation.org/wp-content/uploads/2022/10/IMG_0031-scaled.jpg => 200 | https://africanmarketingconfederation.org/wp-content/uploads/2022/10/IMG_9698-scaled.jpg => 200 | https://africanmarketingconfederation.org/wp-content/uploads/2022/10/IMG_9719-scaled.jpg => 200 | https://africanmarketingconfederation.org/wp-content/uploads/2022/10/IMG_9758-scaled.jpg => 200 | https://africanmarketingconfederation.org/wp-content/uploads/2022/10/IMG_9953-scaled.jpg => 200 | https://africanmarketingconfederation.org/wp-content/uploads/2022/10/IMG_9964-scaled.jpg => 200 | https://africanmarketingconfederation.org/wp-content/uploads/2022/10/IMG_9985-scaled.jpg => 200 | S8: Links | T8: =IFERROR(HYPERLINK("#'Main'!B"&MATCH(TRIM(A8),Main!B:B,0),"Open"),HYPERLINK("#'Main'!B1","Open")) -> Open
A9: https://africanmarketingconfederation.org/amc-conference-2023 | B9: Summary | G9: 41 | H9: 0 | I9: 0 | J9: 13 | K9: 2 | L9: FALSE | M9: 0 | N9: 0.035214 | O9: 0 | P9: 0 | Q9: 0 | R9: https://africanmarketingconfederation.org/amc-conference-2023/gallery => 200 | https://africanmarketingconfederation.org/amc-conference-2023/programme => 200 | https://africanmarketingconfederation.org/amc-conference-2023/speakers => 200 | https://africanmarketingconfederation.org/amc-conference-2025 => 200 | https://africanmarketingconfederation.org/amc-conference-2025-delegate-packages => 404 | https://africanmarketingconfederation.org/amc-marketing-conference-2024/amc-programme-2025 => 200 | https://africanmarketingconfederation.org/amc-marketing-conference-2024/awards-2025 => 200 | https://africanmarketingconfederation.org/amc-sponsors-2025 => 200 | https://africanmarketingconfederation.org/calendar_events => 404 | https://africanmarketingconfederation.org/conference-faq-2025 => 200 | https://africanmarketingconfederation.org/privacy-policy => 200 | https://africanmarketingconfederation.org/publications-2 => 200 | https://africanmarketingconfederation.org/speakers-2025 => 200 | https://africanmarketingconfederation.org/wp-content/uploads/2023/09/AMC-TICON-0164.jpg => 200 | https://africanmarketingconfederation.org/wp-content/uploads/2023/09/AMC-TICON-1113.jpg => 200 | https://africanmarketingconfederation.org/wp-content/uploads/2023/09/AMC-TICON-1127.jpg => 200 | https://africanmarketingconfederation.org/wp-content/uploads/2023/09/AMC-Ticon-00246.jpg => 200 | https://africanmarketingconfederation.org/wp-content/uploads/2023/09/AMC-Ticon-00449.jpg => 200 | https://africanmarketingconfederation.org/wp-content/uploads/2023/09/AMC-Ticon-00481.jpg => 200 | https://africanmarketingconfederation.org/wp-content/uploads/2023/09/AMC-Ticon-00638.jpg => 200 | https://africanmarketingconfederation.org/wp-content/uploads/2023/09/AMC-Ticon-00682.jpg => 200 | https://africanmarketingconfederation.org/wp-content/uploads/2023/09/AMC-Ticon-00742.jpg => 200 | https://africanmarketingconfederation.org/wp-content/uploads/2023/09/AMC-Ticon-01128.jpg => 200 | https://africanmarketingconfederation.org/wp-content/uploads/2023/09/AMC-Ticon-01363.jpg => 200 | https://africanmarketingconfederation.org/wp-content/uploads/2023/09/AMC-Ticon-01409.jpg => 200 | https://africanmarketingconfederation.org/wp-content/uploads/2023/09/AMC-Ticon-01476.jpg => 200 | https://africanmarketingconfederation.org/wp-content/uploads/2023/09/AMC-Ticon-01530.jpg => 200 | https://africanmarketingconfederation.org/wp-content/uploads/2023/09/AMC-Ticon-01616.jpg => 200 | https://africanmarketingconfederation.org/wp-content/uploads/2023/09/AMC-Ticon-02950-1.jpg => 200 | https://africanmarketingconfederation.org/wp-content/uploads/2023/09/AMC-Ticon-03063.jpg => 200 | https://africanmarketingconfederation.org/wp-content/uploads/2023/09/AMC-Ticon-09823.jpg => 200 | https://africanmarketingconfederation.org/wp-content/uploads/2023/09/AMC-Ticon-09825.jpg => 200 | https://africanmarketingconfederation.org/wp-content/uploads/2023/09/AMC-Ticon-09953.jpg => 200 | S9: Links | T9: =IFERROR(HYPERLINK("#'Main'!B"&MATCH(TRIM(A9),Main!B:B,0),"Open"),HYPERLINK("#'Main'!B1","Open")) -> Open
A10: https://africanmarketingconfederation.org/amc-conference-2023/amc-awards-book-now | B10: Summary | G10: 19 | H10: 0 | I10: 0 | J10: 2 | K10: 0 | L10: TRUE | M10: 0 | N10: 0.019665 | O10: 0 | P10: 0 | Q10: 0 | R10: https://africanmarketingconfederation.org/ => 200 | https://africanmarketingconfederation.org/amc-conference-2023 => 200 | https://africanmarketingconfederation.org/amc-conference-2023/amc-awards => 200 | https://africanmarketingconfederation.org/amc-conference-2023/gallery => 200 | https://africanmarketingconfederation.org/amc-conference-2023/partners => 200 | https://africanmarketingconfederation.org/amc-conference-2023/programme => 200 | https://africanmarketingconfederation.org/amc-conference-2023/speakers => 200 | https://africanmarketingconfederation.org/amc-conference-2025-delegate-packages => 404 | https://africanmarketingconfederation.org/privacy-policy => 200 | https://africanmarketingconfederation.org/publications-2 => 200 | S10: Links | T10: =IFERROR(HYPERLINK("#'Main'!B"&MATCH(TRIM(A10),Main!B:B,0),"Open"),HYPERLINK("#'Main'!B1","Open")) -> Open
A11: https://africanmarketingconfederation.org/amc-conference-2023/amc-awards | B11: Summary | G11: 19 | H11: 0 | I11: 0 | J11: 2 | K11: 2 | L11: FALSE | M11: 0 | N11: 0.035214 | O11: 0 | P11: 0 | Q11: 0 | R11: https://africanmarketingconfederation.org/ => 200 | https://africanmarketingconfederation.org/amc-conference-2023 => 200 | https://africanmarketingconfederation.org/amc-conference-2023/amc-awards => 200 | https://africanmarketingconfederation.org/amc-conference-2023/gallery => 200 | https://africanmarketingconfederation.org/amc-conference-2023/partners => 200 | https://africanmarketingconfederation.org/amc-conference-2023/programme => 200 | https://africanmarketingconfederation.org/amc-conference-2023/speakers => 200 | https://africanmarketingconfederation.org/amc-conference-2025-delegate-packages => 404 | https://africanmarketingconfederation.org/privacy-policy => 200 | https://africanmarketingconfederation.org/publications-2 => 200 | S11: Links | T11: =IFERROR(HYPERLINK("#'Main'!B"&MATCH(TRIM(A11),Main!B:B,0),"Open"),HYPERLINK("#'Main'!B1","Open")) -> Open
A12: https://africanmarketingconfederation.org/amc-awards-2024 | B12: Detail | C12: http://www.africanmarketingconfederation.org/ | E12: 0 | F12: TRUE | G12: 0 | H12: 0 | I12: 0 | J12: 0 | K12: 0 | L12: FALSE | M12: 0 | N12: 0 | O12: 0 | P12: 0 | Q12: 0 | S12: LinksDetail | T12: =IFERROR(HYPERLINK("#'Main'!B"&MATCH(TRIM(A12),Main!B:B,0),"Open"),HYPERLINK("#'Main'!B1","Open")) -> Open
A13: https://africanmarketingconfederation.org/amc-awards-2024 | B13: Detail | C13: https://africanmarketingconfederation.org/amc-conference-2025 | D13: GHANA 2025 | E13: 200 | F13: TRUE | G13: 0 | H13: 0 | I13: 0 | J13: 0 | K13: 0 | L13: FALSE | M13: 0 | N13: 0 | O13: 0 | P13: 0 | Q13: 0 | S13: LinksDetail | T13: =IFERROR(HYPERLINK("#'Main'!B"&MATCH(TRIM(A13),Main!B:B,0),"Open"),HYPERLINK("#'Main'!B1","Open")) -> Open
A14: https://africanmarketingconfederation.org/amc-awards-2024 | B14: Detail | C14: https://africanmarketingconfederation.org/speakers-2025 | D14: SPEAKERS 2025 | E14: 200 | F14: TRUE | G14: 0 | H14: 0 | I14: 0 | J14: 0 | K14: 0 | L14: FALSE | M14: 0 | N14: 0 | O14: 0 | P14: 0 | Q14: 0 | S14: LinksDetail | T14: =IFERROR(HYPERLINK("#'Main'!B"&MATCH(TRIM(A14),Main!B:B,0),"Open"),HYPERLINK("#'Main'!B1","Open")) -> Open
A15: https://africanmarketingconfederation.org/amc-awards-2024 | B15: Detail | C15: https://africanmarketingconfederation.org/amc-marketing-conference-2024/amc-programme-2025 | D15: AMC PROGRAMME 2025 | E15: 200 | F15: TRUE | G15: 0 | H15: 0 | I15: 0 | J15: 0 | K15: 0 | L15: FALSE | M15: 0 | N15: 0 | O15: 0 | P15: 0 | Q15: 0 | S15: LinksDetail | T15: =IFERROR(HYPERLINK("#'Main'!B"&MATCH(TRIM(A15),Main!B:B,0),"Open"),HYPERLINK("#'Main'!B1","Open")) -> Open
A16: https://africanmarketingconfederation.org/amc-awards-2024 | B16: Detail | C16: https://africanmarketingconfederation.org/amc-marketing-conference-2024/awards-2025 | D16: AWARDS 2025 | E16: 200 | F16: TRUE | G16: 0 | H16: 0 | I16: 0 | J16: 0 | K16: 0 | L16: FALSE | M16: 0 | N16: 0 | O16: 0 | P16: 0 | Q16: 0 | S16: LinksDetail | T16: =IFERROR(HYPERLINK("#'Main'!B"&MATCH(TRIM(A16),Main!B:B,0),"Open"),HYPERLINK("#'Main'!B1","Open")) -> Open
A17: https://africanmarketingconfederation.org/amc-awards-2024 | B17: Detail | C17: https://africanmarketingconfederation.org/amc-sponsors-2025 | D17: SPONSORS 2025 | E17: 200 | F17: TRUE | G17: 0 | H17: 0 | I17: 0 | J17: 0 | K17: 0 | L17: FALSE | M17: 0 | N17: 0 | O17: 0 | P17: 0 | Q17: 0 | S17: LinksDetail | T17: =IFERROR(HYPERLINK("#'Main'!B"&MATCH(TRIM(A17),Main!B:B,0),"Open"),HYPERLINK("#'Main'!B1","Open")) -> Open
A18: https://africanmarketingconfederation.org/amc-awards-2024 | B18: Detail | C18: https://africanmarketingconfederation.org/conference-faq-2025 | D18: FAQ 2025 | E18: 200 | F18: TRUE | G18: 0 | H18: 0 | I18: 0 | J18: 0 | K18: 0 | L18: FALSE | M18: 0 | N18: 0 | O18: 0 | P18: 0 | Q18: 0 | S18: LinksDetail | T18: =IFERROR(HYPERLINK("#'Main'!B"&MATCH(TRIM(A18),Main!B:B,0),"Open"),HYPERLINK("#'Main'!B1","Open")) -> Open
A19: https://africanmarketingconfederation.org/amc-awards-2024 | B19: Detail | C19: https://africanmarketingconfederation.org/amc-conference-2025 | D19: GHANA 2025 | E19: 200 | F19: TRUE | G19: 0 | H19: 0 | I19: 0 | J19: 0 | K19: 0 | L19: FALSE | M19: 0 | N19: 0 | O19: 0 | P19: 0 | Q19: 0 | S19: LinksDetail | T19: =IFERROR(HYPERLINK("#'Main'!B"&MATCH(TRIM(A19),Main!B:B,0),"Open"),HYPERLINK("#'Main'!B1","Open")) -> Open
A20: https://africanmarketingconfederation.org/amc-awards-2024 | B20: Detail | C20: https://africanmarketingconfederation.org/speakers-2025 | D20: SPEAKERS 2025 | E20: 200 | F20: TRUE | G20: 0 | H20: 0 | I20: 0 | J20: 0 | K20: 0 | L20: FALSE | M20: 0 | N20: 0 | O20: 0 | P20: 0 | Q20: 0 | S20: LinksDetail | T20: =IFERROR(HYPERLINK("#'Main'!B"&MATCH(TRIM(A20),Main!B:B,0),"Open"),HYPERLINK("#'Main'!B1","Open")) -> Open
A21: https://africanmarketingconfederation.org/amc-awards-2024 | B21: Detail | C21: https://africanmarketingconfederation.org/amc-marketing-conference-2024/amc-programme-2025 | D21: AMC PROGRAMME 2025 | E21: 200 | F21: TRUE | G21: 0 | H21: 0 | I21: 0 | J21: 0 | K21: 0 | L21: FALSE | M21: 0 | N21: 0 | O21: 0 | P21: 0 | Q21: 0 | S21: LinksDetail | T21: =IFERROR(HYPERLINK("#'Main'!B"&MATCH(TRIM(A21),Main!B:B,0),"Open"),HYPERLINK("#'Main'!B1","Open")) -> Open
A22: https://africanmarketingconfederation.org/amc-awards-2024 | B22: Detail | C22: https://africanmarketingconfederation.org/amc-marketing-conference-2024/awards-2025 | D22: AWARDS 2025 | E22: 200 | F22: TRUE | G22: 0 | H22: 0 | I22: 0 | J22: 0 | K22: 0 | L22: FALSE | M22: 0 | N22: 0 | O22: 0 | P22: 0 | Q22: 0 | S22: LinksDetail | T22: =IFERROR(HYPERLINK("#'Main'!B"&MATCH(TRIM(A22),Main!B:B,0),"Open"),HYPERLINK("#'Main'!B1","Open")) -> Open
A23: https://africanmarketingconfederation.org/amc-awards-2024 | B23: Detail | C23: https://africanmarketingconfederation.org/amc-sponsors-2025 | D23: SPONSORS 2025 | E23: 200 | F23: TRUE | G23: 0 | H23: 0 | I23: 0 | J23: 0 | K23: 0 | L23: FALSE | M23: 0 | N23: 0 | O23: 0 | P23: 0 | Q23: 0 | S23: LinksDetail | T23: =IFERROR(HYPERLINK("#'Main'!B"&MATCH(TRIM(A23),Main!B:B,0),"Open"),HYPERLINK("#'Main'!B1","Open")) -> Open
A24: https://africanmarketingconfederation.org/amc-awards-2024 | B24: Detail | C24: https://africanmarketingconfederation.org/conference-faq-2025 | D24: FAQ 2025 | E24: 200 | F24: TRUE | G24: 0 | H24: 0 | I24: 0 | J24: 0 | K24: 0 | L24: FALSE | M24: 0 | N24: 0 | O24: 0 | P24: 0 | Q24: 0 | S24: LinksDetail | T24: =IFERROR(HYPERLINK("#'Main'!B"&MATCH(TRIM(A24),Main!B:B,0),"Open"),HYPERLINK("#'Main'!B1","Open")) -> Open
A25: https://africanmarketingconfederation.org/amc-awards-2024 | B25: Detail | C25: https://africanmarketingconfederation.org/publications-2 | D25: Strategic Marketing for Africa Magazine | E25: 200 | F25: TRUE | G25: 0 | H25: 0 | I25: 0 | J25: 0 | K25: 0 | L25: FALSE | M25: 0 | N25: 0 | O25: 0 | P25: 0 | Q25: 0 | S25: LinksDetail | T25: =IFERROR(HYPERLINK("#'Main'!B"&MATCH(TRIM(A25),Main!B:B,0),"Open"),HYPERLINK("#'Main'!B1","Open")) -> Open
A26: https://africanmarketingconfederation.org/amc-awards-2024 | B26: Detail | C26: https://www.facebook.com/The-African-Marketing-Confederation-108980418182403 | E26: 0 | F26: TRUE | G26: 0 | H26: 0 | I26: 0 | J26: 0 | K26: 0 | L26: FALSE | M26: 0 | N26: 0 | O26: 0 | P26: 0 | Q26: 0 | S26: LinksDetail | T26: =IFERROR(HYPERLINK("#'Main'!B"&MATCH(TRIM(A26),Main!B:B,0),"Open"),HYPERLINK("#'Main'!B1","Open")) -> Open
A27: https://africanmarketingconfederation.org/amc-awards-2024 | B27: Detail | C27: https://www.linkedin.com/company/african-marketing-confederation | E27: 0 | F27: TRUE | G27: 0 | H27: 0 | I27: 0 | J27: 0 | K27: 0 | L27: FALSE | M27: 0 | N27: 0 | O27: 0 | P27: 0 | Q27: 0 | S27: LinksDetail | T27: =IFERROR(HYPERLINK("#'Main'!B"&MATCH(TRIM(A27),Main!B:B,0),"Open"),HYPERLINK("#'Main'!B1","Open")) -> Open
A28: https://africanmarketingconfederation.org/amc-awards-2024 | B28: Detail | C28: https://twitter.com/connect_amc | E28: 0 | F28: TRUE | G28: 0 | H28: 0 | I28: 0 | J28: 0 | K28: 0 | L28: FALSE | M28: 0 | N28: 0 | O28: 0 | P28: 0 | Q28: 0 | S28: LinksDetail | T28: =IFERROR(HYPERLINK("#'Main'!B"&MATCH(TRIM(A28),Main!B:B,0),"Open"),HYPERLINK("#'Main'!B1","Open")) -> Open
A29: https://africanmarketingconfederation.org/amc-awards-2024 | B29: Detail | C29: https://africanmarketingconfederation.org/privacy-policy | D29: © 2021 by African Marketing Confederation | Privacy Policy | E29: 200 | F29: TRUE | G29: 0 | H29: 0 | I29: 0 | J29: 0 | K29: 0 | L29: FALSE | M29: 0 | N29: 0 | O29: 0 | P29: 0 | Q29: 0 | S29: LinksDetail | T29: =IFERROR(HYPERLINK("#'Main'!B"&MATCH(TRIM(A29),Main!B:B,0),"Open"),HYPERLINK("#'Main'!B1","Open")) -> Open
A30: https://africanmarketingconfederation.org/amc-awards-2024 | B30: Detail | C30: https://africanmarketingconfederation.org/amc-conference-2025-delegate-packages | D30: Return to Shop | E30: 404 | F30: FALSE | G30: 0 | H30: 0 | I30: 0 | J30: 0 | K30: 0 | L30: FALSE | M30: 0 | N30: 0 | O30: 0 | P30: 0 | Q30: 0 | S30: LinksDetail | T30: =IFERROR(HYPERLINK("#'Main'!B"&MATCH(TRIM(A30),Main!B:B,0),"Open"),HYPERLINK("#'Main'!B1","Open")) -> Open
A31: https://africanmarketingconfederation.org/amc-awards-2024 | B31: Detail | C31: https://africanmarketingconfederation.org/amc-conference-2025-delegate-packages | D31: Continue Shopping | E31: 404 | F31: FALSE | G31: 0 | H31: 0 | I31: 0 | J31: 0 | K31: 0 | L31: FALSE | M31: 0 | N31: 0 | O31: 0 | P31: 0 | Q31: 0 | S31: LinksDetail | T31: =IFERROR(HYPERLINK("#'Main'!B"&MATCH(TRIM(A31),Main!B:B,0),"Open"),HYPERLINK("#'Main'!B1","Open")) -> Open
A32: https://africanmarketingconfederation.org/african-marketing-confederation-tourism-chapter | B32: Detail | C32: https://africanmarketingconfederation.org/ | E32: 200 | F32: TRUE | G32: 0 | H32: 0 | I32: 0 | J32: 0 | K32: 0 | L32: FALSE | M32: 0 | N32: 0 | O32: 0 | P32: 0 | Q32: 0 | S32: LinksDetail | T32: =IFERROR(HYPERLINK("#'Main'!B"&MATCH(TRIM(A32),Main!B:B,0),"Open"),HYPERLINK("#'Main'!B1","Open")) -> Open
A33: https://africanmarketingconfederation.org/african-marketing-confederation-tourism-chapter | B33: Detail | C33: https://africanmarketingconfederation.org/ | D33: HOME | E33: 200 | F33: TRUE | G33: 0 | H33: 0 | I33: 0 | J33: 0 | K33: 0 | L33: FALSE | M33: 0 | N33: 0 | O33: 0 | P33: 0 | Q33: 0 | S33: LinksDetail | T33: =IFERROR(HYPERLINK("#'Main'!B"&MATCH(TRIM(A33),Main!B:B,0),"Open"),HYPERLINK("#'Main'!B1","Open")) -> Open
A34: https://africanmarketingconfederation.org/african-marketing-confederation-tourism-chapter | B34: Detail | C34: https://africanmarketingconfederation.org/about-us | D34: ABOUT US | E34: 200 | F34: TRUE | G34: 0 | H34: 0 | I34: 0 | J34: 0 | K34: 0 | L34: FALSE | M34: 0 | N34: 0 | O34: 0 | P34: 0 | Q34: 0 | S34: LinksDetail | T34: =IFERROR(HYPERLINK("#'Main'!B"&MATCH(TRIM(A34),Main!B:B,0),"Open"),HYPERLINK("#'Main'!B1","Open")) -> Open
A35: https://africanmarketingconfederation.org/african-marketing-confederation-tourism-chapter | B35: Detail | C35: https://africanmarketingconfederation.org/sub-committees | D35: AMC COMMITTEES | E35: 200 | F35: TRUE | G35: 0 | H35: 0 | I35: 0 | J35: 0 | K35: 0 | L35: FALSE | M35: 0 | N35: 0 | O35: 0 | P35: 0 | Q35: 0 | S35: LinksDetail | T35: =IFERROR(HYPERLINK("#'Main'!B"&MATCH(TRIM(A35),Main!B:B,0),"Open"),HYPERLINK("#'Main'!B1","Open")) -> Open
A36: https://africanmarketingconfederation.org/african-marketing-confederation-tourism-chapter | B36: Detail | C36: https://africanmarketingconfederation.org/members | D36: MEMBERS | E36: 200 | F36: TRUE | G36: 0 | H36: 0 | I36: 0 | J36: 0 | K36: 0 | L36: FALSE | M36: 0 | N36: 0 | O36: 0 | P36: 0 | Q36: 0 | S36: LinksDetail | T36: =IFERROR(HYPERLINK("#'Main'!B"&MATCH(TRIM(A36),Main!B:B,0),"Open"),HYPERLINK("#'Main'!B1","Open")) -> Open
A37: https://africanmarketingconfederation.org/african-marketing-confederation-tourism-chapter | B37: Detail | C37: https://africanmarketingconfederation.org/african-marketing-confederation-tourism-chapter | D37: TOURISM CHAPTER | E37: 200 | F37: TRUE | G37: 0 | H37: 0 | I37: 0 | J37: 0 | K37: 0 | L37: FALSE | M37: 0 | N37: 0 | O37: 0 | P37: 0 | Q37: 0 | S37: LinksDetail | T37: =IFERROR(HYPERLINK("#'Main'!B"&MATCH(TRIM(A37),Main!B:B,0),"Open"),HYPERLINK("#'Main'!B1","Open")) -> Open
A38: https://africanmarketingconfederation.org/african-marketing-confederation-tourism-chapter | B38: Detail | C38: https://africanmarketingconfederation.org/education | D38: EDUCATION | E38: 200 | F38: TRUE | G38: 0 | H38: 0 | I38: 0 | J38: 0 | K38: 0 | L38: FALSE | M38: 0 | N38: 0 | O38: 0 | P38: 0 | Q38: 0 | S38: LinksDetail | T38: =IFERROR(HYPERLINK("#'Main'!B"&MATCH(TRIM(A38),Main!B:B,0),"Open"),HYPERLINK("#'Main'!B1","Open")) -> Open
A39: https://africanmarketingconfederation.org/african-marketing-confederation-tourism-chapter | B39: Detail | C39: https://africanmarketingconfederation.org/chartered-marketer-africa | D39: CHARTERED MARKETER (AFRICA) | E39: 200 | F39: TRUE | G39: 0 | H39: 0 | I39: 0 | J39: 0 | K39: 0 | L39: FALSE | M39: 0 | N39: 0 | O39: 0 | P39: 0 | Q39: 0 | S39: LinksDetail | T39: =IFERROR(HYPERLINK("#'Main'!B"&MATCH(TRIM(A39),Main!B:B,0),"Open"),HYPERLINK("#'Main'!B1","Open")) -> Open
A40: https://africanmarketingconfederation.org/african-marketing-confederation-tourism-chapter | B40: Detail | C40: https://africanmarketingconfederation.org/certified-professional-marketer-africa | D40: CPM(A) | E40: 200 | F40: TRUE | G40: 0 | H40: 0 | I40: 0 | J40: 0 | K40: 0 | L40: FALSE | M40: 0 | N40: 0 | O40: 0 | P40: 0 | Q40: 0 | S40: LinksDetail | T40: =IFERROR(HYPERLINK("#'Main'!B"&MATCH(TRIM(A40),Main!B:B,0),"Open"),HYPERLINK("#'Main'!B1","Open")) -> Open
A41: https://africanmarketingconfederation.org/african-marketing-confederation-tourism-chapter | B41: Detail | C41: https://africanmarketingconfederation.org/news-articles | D41: NEWS & PUBLICATIONS | E41: 200 | F41: TRUE | G41: 0 | H41: 0 | I41: 0 | J41: 0 | K41: 0 | L41: FALSE | M41: 0 | N41: 0 | O41: 0 | P41: 0 | Q41: 0 | S41: LinksDetail | T41: =IFERROR(HYPERLINK("#'Main'!B"&MATCH(TRIM(A41),Main!B:B,0),"Open"),HYPERLINK("#'Main'!B1","Open")) -> Open
A42: https://africanmarketingconfederation.org/african-marketing-confederation-tourism-chapter | B42: Detail | C42: https://africanmarketingconfederation.org/news-articles | D42: NEWS ARTICLES | E42: 200 | F42: TRUE | G42: 0 | H42: 0 | I42: 0 | J42: 0 | K42: 0 | L42: FALSE | M42: 0 | N42: 0 | O42: 0 | P42: 0 | Q42: 0 | S42: LinksDetail | T42: =IFERROR(HYPERLINK("#'Main'!B"&MATCH(TRIM(A42),Main!B:B,0),"Open"),HYPERLINK("#'Main'!B1","Open")) -> Open
A43: https://africanmarketingconfederation.org/african-marketing-confederation-tourism-chapter | B43: Detail | C43: https://africanmarketingconfederation.org/publications-2 | D43: PUBLICATIONS | E43: 200 | F43: TRUE | G43: 0 | H43: 0 | I43: 0 | J43: 0 | K43: 0 | L43: FALSE | M43: 0 | N43: 0 | O43: 0 | P43: 0 | Q43: 0 | S43: LinksDetail | T43: =IFERROR(HYPERLINK("#'Main'!B"&MATCH(TRIM(A43),Main!B:B,0),"Open"),HYPERLINK("#'Main'!B1","Open")) -> Open
A44: https://africanmarketingconfederation.org/african-marketing-confederation-tourism-chapter | B44: Detail | C44: https://africanmarketingconfederation.org/amc-conference-2026 | D44: AMC Conference | E44: 200 | F44: TRUE | G44: 0 | H44: 0 | I44: 0 | J44: 0 | K44: 0 | L44: FALSE | M44: 0 | N44: 0 | O44: 0 | P44: 0 | Q44: 0 | S44: LinksDetail | T44: =IFERROR(HYPERLINK("#'Main'!B"&MATCH(TRIM(A44),Main!B:B,0),"Open"),HYPERLINK("#'Main'!B1","Open")) -> Open
... A58: https://africanmarketingconfederation.org/african-marketing-confederation-tourism-chapter | B58: Detail | C58: https://africanmarketingconfederation.org/contact-us | D58: CONTACT US | E58: 200 | F58: TRUE | G58: 0 | H58: 0 | I58: 0 | J58: 0 | K58: 0 | L58: FALSE | M58: 0 | N58: 0 | O58: 0 | P58: 0 | Q58: 0 | S58: LinksDetail | T58: =IFERROR(HYPERLINK("#'Main'!B"&MATCH(TRIM(A58),Main!B:B,0),"Open"),HYPERLINK("#'Main'!B1","Open")) -> Open
A59: https://africanmarketingconfederation.org/african-marketing-confederation-tourism-chapter | B59: Detail | C59: http://www.africanmarketingconfederation.org/ | E59: 0 | F59: TRUE | G59: 0 | H59: 0 | I59: 0 | J59: 0 | K59: 0 | L59: FALSE | M59: 0 | N59: 0 | O59: 0 | P59: 0 | Q59: 0 | S59: LinksDetail | T59: =IFERROR(HYPERLINK("#'Main'!B"&MATCH(TRIM(A59),Main!B:B,0),"Open"),HYPERLINK("#'Main'!B1","Open")) -> Open
A60: https://africanmarketingconfederation.org/african-marketing-confederation-tourism-chapter | B60: Detail | C60: https://africanmarketingconfederation.org/ | D60: HOME | E60: 200 | F60: TRUE | G60: 0 | H60: 0 | I60: 0 | J60: 0 | K60: 0 | L60: FALSE | M60: 0 | N60: 0 | O60: 0 | P60: 0 | Q60: 0 | S60: LinksDetail | T60: =IFERROR(HYPERLINK("#'Main'!B"&MATCH(TRIM(A60),Main!B:B,0),"Open"),HYPERLINK("#'Main'!B1","Open")) -> Open
A61: https://africanmarketingconfederation.org/african-marketing-confederation-tourism-chapter | B61: Detail | C61: https://africanmarketingconfederation.org/about-us | D61: ABOUT US | E61: 200 | F61: TRUE | G61: 0 | H61: 0 | I61: 0 | J61: 0 | K61: 0 | L61: FALSE | M61: 0 | N61: 0 | O61: 0 | P61: 0 | Q61: 0 | S61: LinksDetail | T61: =IFERROR(HYPERLINK("#'Main'!B"&MATCH(TRIM(A61),Main!B:B,0),"Open"),HYPERLINK("#'Main'!B1","Open")) -> Open
A62: https://africanmarketingconfederation.org/african-marketing-confederation-tourism-chapter | B62: Detail | C62: https://africanmarketingconfederation.org/sub-committees | D62: AMC COMMITTEES | E62: 200 | F62: TRUE | G62: 0 | H62: 0 | I62: 0 | J62: 0 | K62: 0 | L62: FALSE | M62: 0 | N62: 0 | O62: 0 | P62: 0 | Q62: 0 | S62: LinksDetail | T62: =IFERROR(HYPERLINK("#'Main'!B"&MATCH(TRIM(A62),Main!B:B,0),"Open"),HYPERLINK("#'Main'!B1","Open")) -> Open
A63: https://africanmarketingconfederation.org/african-marketing-confederation-tourism-chapter | B63: Detail | C63: https://africanmarketingconfederation.org/members | D63: MEMBERS | E63: 200 | F63: TRUE | G63: 0 | H63: 0 | I63: 0 | J63: 0 | K63: 0 | L63: FALSE | M63: 0 | N63: 0 | O63: 0 | P63: 0 | Q63: 0 | S63: LinksDetail | T63: =IFERROR(HYPERLINK("#'Main'!B"&MATCH(TRIM(A63),Main!B:B,0),"Open"),HYPERLINK("#'Main'!B1","Open")) -> Open
A64: https://africanmarketingconfederation.org/african-marketing-confederation-tourism-chapter | B64: Detail | C64: https://africanmarketingconfederation.org/african-marketing-confederation-tourism-chapter | D64: TOURISM CHAPTER | E64: 200 | F64: TRUE | G64: 0 | H64: 0 | I64: 0 | J64: 0 | K64: 0 | L64: FALSE | M64: 0 | N64: 0 | O64: 0 | P64: 0 | Q64: 0 | S64: LinksDetail | T64: =IFERROR(HYPERLINK("#'Main'!B"&MATCH(TRIM(A64),Main!B:B,0),"Open"),HYPERLINK("#'Main'!B1","Open")) -> Open
A65: https://africanmarketingconfederation.org/african-marketing-confederation-tourism-chapter | B65: Detail | C65: https://africanmarketingconfederation.org/education | D65: EDUCATION | E65: 200 | F65: TRUE | G65: 0 | H65: 0 | I65: 0 | J65: 0 | K65: 0 | L65: FALSE | M65: 0 | N65: 0 | O65: 0 | P65: 0 | Q65: 0 | S65: LinksDetail | T65: =IFERROR(HYPERLINK("#'Main'!B"&MATCH(TRIM(A65),Main!B:B,0),"Open"),HYPERLINK("#'Main'!B1","Open")) -> Open
A66: https://africanmarketingconfederation.org/african-marketing-confederation-tourism-chapter | B66: Detail | C66: https://africanmarketingconfederation.org/chartered-marketer-africa | D66: CHARTERED MARKETER (AFRICA) | E66: 200 | F66: TRUE | G66: 0 | H66: 0 | I66: 0 | J66: 0 | K66: 0 | L66: FALSE | M66: 0 | N66: 0 | O66: 0 | P66: 0 | Q66: 0 | S66: LinksDetail | T66: =IFERROR(HYPERLINK("#'Main'!B"&MATCH(TRIM(A66),Main!B:B,0),"Open"),HYPERLINK("#'Main'!B1","Open")) -> Open
A67: https://africanmarketingconfederation.org/african-marketing-confederation-tourism-chapter | B67: Detail | C67: https://africanmarketingconfederation.org/certified-professional-marketer-africa | D67: CPM(A) | E67: 200 | F67: TRUE | G67: 0 | H67: 0 | I67: 0 | J67: 0 | K67: 0 | L67: FALSE | M67: 0 | N67: 0 | O67: 0 | P67: 0 | Q67: 0 | S67: LinksDetail | T67: =IFERROR(HYPERLINK("#'Main'!B"&MATCH(TRIM(A67),Main!B:B,0),"Open"),HYPERLINK("#'Main'!B1","Open")) -> Open
A68: https://africanmarketingconfederation.org/african-marketing-confederation-tourism-chapter | B68: Detail | C68: https://africanmarketingconfederation.org/news-articles | D68: NEWS & PUBLICATIONS | E68: 200 | F68: TRUE | G68: 0 | H68: 0 | I68: 0 | J68: 0 | K68: 0 | L68: FALSE | M68: 0 | N68: 0 | O68: 0 | P68: 0 | Q68: 0 | S68: LinksDetail | T68: =IFERROR(HYPERLINK("#'Main'!B"&MATCH(TRIM(A68),Main!B:B,0),"Open"),HYPERLINK("#'Main'!B1","Open")) -> Open
A69: https://africanmarketingconfederation.org/african-marketing-confederation-tourism-chapter | B69: Detail | C69: https://africanmarketingconfederation.org/news-articles | D69: NEWS ARTICLES | E69: 200 | F69: TRUE | G69: 0 | H69: 0 | I69: 0 | J69: 0 | K69: 0 | L69: FALSE | M69: 0 | N69: 0 | O69: 0 | P69: 0 | Q69: 0 | S69: LinksDetail | T69: =IFERROR(HYPERLINK("#'Main'!B"&MATCH(TRIM(A69),Main!B:B,0),"Open"),HYPERLINK("#'Main'!B1","Open")) -> Open
A70: https://africanmarketingconfederation.org/african-marketing-confederation-tourism-chapter | B70: Detail | C70: https://africanmarketingconfederation.org/publications-2 | D70: PUBLICATIONS | E70: 200 | F70: TRUE | G70: 0 | H70: 0 | I70: 0 | J70: 0 | K70: 0 | L70: FALSE | M70: 0 | N70: 0 | O70: 0 | P70: 0 | Q70: 0 | S70: LinksDetail | T70: =IFERROR(HYPERLINK("#'Main'!B"&MATCH(TRIM(A70),Main!B:B,0),"Open"),HYPERLINK("#'Main'!B1","Open")) -> Open
A71: https://africanmarketingconfederation.org/african-marketing-confederation-tourism-chapter | B71: Detail | C71: https://africanmarketingconfederation.org/amc-conference-2026 | D71: AMC Conference | E71: 200 | F71: TRUE | G71: 0 | H71: 0 | I71: 0 | J71: 0 | K71: 0 | L71: FALSE | M71: 0 | N71: 0 | O71: 0 | P71: 0 | Q71: 0 | S71: LinksDetail | T71: =IFERROR(HYPERLINK("#'Main'!B"&MATCH(TRIM(A71),Main!B:B,0),"Open"),HYPERLINK("#'Main'!B1","Open")) -> Open
... A87: https://africanmarketingconfederation.org/african-marketing-confederation-tourism-chapter | B87: Detail | C87: https://africanmarketingconfederation.org/publications-2 | D87: Strategic Marketing for Africa Magazine | E87: 200 | F87: TRUE | G87: 0 | H87: 0 | I87: 0 | J87: 0 | K87: 0 | L87: FALSE | M87: 0 | N87: 0 | O87: 0 | P87: 0 | Q87: 0 | S87: LinksDetail | T87: =IFERROR(HYPERLINK("#'Main'!B"&MATCH(TRIM(A87),Main!B:B,0),"Open"),HYPERLINK("#'Main'!B1","Open")) -> Open
A88: https://africanmarketingconfederation.org/african-marketing-confederation-tourism-chapter | B88: Detail | C88: https://www.facebook.com/The-African-Marketing-Confederation-108980418182403 | E88: 0 | F88: TRUE | G88: 0 | H88: 0 | I88: 0 | J88: 0 | K88: 0 | L88: FALSE | M88: 0 | N88: 0 | O88: 0 | P88: 0 | Q88: 0 | S88: LinksDetail | T88: =IFERROR(HYPERLINK("#'Main'!B"&MATCH(TRIM(A88),Main!B:B,0),"Open"),HYPERLINK("#'Main'!B1","Open")) -> Open
A89: https://africanmarketingconfederation.org/african-marketing-confederation-tourism-chapter | B89: Detail | C89: https://www.linkedin.com/company/african-marketing-confederation | E89: 0 | F89: TRUE | G89: 0 | H89: 0 | I89: 0 | J89: 0 | K89: 0 | L89: FALSE | M89: 0 | N89: 0 | O89: 0 | P89: 0 | Q89: 0 | S89: LinksDetail | T89: =IFERROR(HYPERLINK("#'Main'!B"&MATCH(TRIM(A89),Main!B:B,0),"Open"),HYPERLINK("#'Main'!B1","Open")) -> Open
A90: https://africanmarketingconfederation.org/african-marketing-confederation-tourism-chapter | B90: Detail | C90: https://africanmarketingconfederation.org/privacy-policy | D90: © 2026 by African Marketing Confederation | Privacy Policy | E90: 200 | F90: TRUE | G90: 0 | H90: 0 | I90: 0 | J90: 0 | K90: 0 | L90: FALSE | M90: 0 | N90: 0 | O90: 0 | P90: 0 | Q90: 0 | S90: LinksDetail | T90: =IFERROR(HYPERLINK("#'Main'!B"&MATCH(TRIM(A90),Main!B:B,0),"Open"),HYPERLINK("#'Main'!B1","Open")) -> Open
A91: https://africanmarketingconfederation.org/african-marketing-confederation-tourism-chapter | B91: Detail | C91: https://africanmarketingconfederation.org/amc-conference-2025-delegate-packages | D91: Return to Shop | E91: 404 | F91: FALSE | G91: 0 | H91: 0 | I91: 0 | J91: 0 | K91: 0 | L91: FALSE | M91: 0 | N91: 0 | O91: 0 | P91: 0 | Q91: 0 | S91: LinksDetail | T91: =IFERROR(HYPERLINK("#'Main'!B"&MATCH(TRIM(A91),Main!B:B,0),"Open"),HYPERLINK("#'Main'!B1","Open")) -> Open
A92: https://africanmarketingconfederation.org/african-marketing-confederation-tourism-chapter | B92: Detail | C92: https://africanmarketingconfederation.org/amc-conference-2025-delegate-packages | D92: Continue Shopping | E92: 404 | F92: FALSE | G92: 0 | H92: 0 | I92: 0 | J92: 0 | K92: 0 | L92: FALSE | M92: 0 | N92: 0 | O92: 0 | P92: 0 | Q92: 0 | S92: LinksDetail | T92: =IFERROR(HYPERLINK("#'Main'!B"&MATCH(TRIM(A92),Main!B:B,0),"Open"),HYPERLINK("#'Main'!B1","Open")) -> Open
A93: https://africanmarketingconfederation.org/ | B93: Detail | C93: https://africanmarketingconfederation.org/ | E93: 200 | F93: TRUE | G93: 0 | H93: 0 | I93: 0 | J93: 0 | K93: 0 | L93: FALSE | M93: 0 | N93: 0 | O93: 0 | P93: 0 | Q93: 0 | S93: LinksDetail | T93: =IFERROR(HYPERLINK("#'Main'!B"&MATCH(TRIM(A93),Main!B:B,0),"Open"),HYPERLINK("#'Main'!B1","Open")) -> Open
A94: https://africanmarketingconfederation.org/ | B94: Detail | C94: https://africanmarketingconfederation.org/ | D94: HOME | E94: 200 | F94: TRUE | G94: 0 | H94: 0 | I94: 0 | J94: 0 | K94: 0 | L94: FALSE | M94: 0 | N94: 0 | O94: 0 | P94: 0 | Q94: 0 | S94: LinksDetail | T94: =IFERROR(HYPERLINK("#'Main'!B"&MATCH(TRIM(A94),Main!B:B,0),"Open"),HYPERLINK("#'Main'!B1","Open")) -> Open
A95: https://africanmarketingconfederation.org/ | B95: Detail | C95: https://africanmarketingconfederation.org/about-us | D95: ABOUT US | E95: 200 | F95: TRUE | G95: 0 | H95: 0 | I95: 0 | J95: 0 | K95: 0 | L95: FALSE | M95: 0 | N95: 0 | O95: 0 | P95: 0 | Q95: 0 | S95: LinksDetail | T95: =IFERROR(HYPERLINK("#'Main'!B"&MATCH(TRIM(A95),Main!B:B,0),"Open"),HYPERLINK("#'Main'!B1","Open")) -> Open
A96: https://africanmarketingconfederation.org/ | B96: Detail | C96: https://africanmarketingconfederation.org/sub-committees | D96: AMC COMMITTEES | E96: 200 | F96: TRUE | G96: 0 | H96: 0 | I96: 0 | J96: 0 | K96: 0 | L96: FALSE | M96: 0 | N96: 0 | O96: 0 | P96: 0 | Q96: 0 | S96: LinksDetail | T96: =IFERROR(HYPERLINK("#'Main'!B"&MATCH(TRIM(A96),Main!B:B,0),"Open"),HYPERLINK("#'Main'!B1","Open")) -> Open
A97: https://africanmarketingconfederation.org/ | B97: Detail | C97: https://africanmarketingconfederation.org/members | D97: MEMBERS | E97: 200 | F97: TRUE | G97: 0 | H97: 0 | I97: 0 | J97: 0 | K97: 0 | L97: FALSE | M97: 0 | N97: 0 | O97: 0 | P97: 0 | Q97: 0 | S97: LinksDetail | T97: =IFERROR(HYPERLINK("#'Main'!B"&MATCH(TRIM(A97),Main!B:B,0),"Open"),HYPERLINK("#'Main'!B1","Open")) -> Open
A98: https://africanmarketingconfederation.org/ | B98: Detail | C98: https://africanmarketingconfederation.org/african-marketing-confederation-tourism-chapter | D98: TOURISM CHAPTER | E98: 200 | F98: TRUE | G98: 0 | H98: 0 | I98: 0 | J98: 0 | K98: 0 | L98: FALSE | M98: 0 | N98: 0 | O98: 0 | P98: 0 | Q98: 0 | S98: LinksDetail | T98: =IFERROR(HYPERLINK("#'Main'!B"&MATCH(TRIM(A98),Main!B:B,0),"Open"),HYPERLINK("#'Main'!B1","Open")) -> Open
A99: https://africanmarketingconfederation.org/ | B99: Detail | C99: https://africanmarketingconfederation.org/education | D99: EDUCATION | E99: 200 | F99: TRUE | G99: 0 | H99: 0 | I99: 0 | J99: 0 | K99: 0 | L99: FALSE | M99: 0 | N99: 0 | O99: 0 | P99: 0 | Q99: 0 | S99: LinksDetail | T99: =IFERROR(HYPERLINK("#'Main'!B"&MATCH(TRIM(A99),Main!B:B,0),"Open"),HYPERLINK("#'Main'!B1","Open")) -> Open
A100: https://africanmarketingconfederation.org/ | B100: Detail | C100: https://africanmarketingconfederation.org/chartered-marketer-africa | D100: CHARTERED MARKETER (AFRICA) | E100: 200 | F100: TRUE | G100: 0 | H100: 0 | I100: 0 | J100: 0 | K100: 0 | L100: FALSE | M100: 0 | N100: 0 | O100: 0 | P100: 0 | Q100: 0 | S100: LinksDetail | T100: =IFERROR(HYPERLINK("#'Main'!B"&MATCH(TRIM(A100),Main!B:B,0),"Open"),HYPERLINK("#'Main'!B1","Open")) -> Open
A101: https://africanmarketingconfederation.org/ | B101: Detail | C101: https://africanmarketingconfederation.org/certified-professional-marketer-africa | D101: CPM(A) | E101: 200 | F101: TRUE | G101: 0 | H101: 0 | I101: 0 | J101: 0 | K101: 0 | L101: FALSE | M101: 0 | N101: 0 | O101: 0 | P101: 0 | Q101: 0 | S101: LinksDetail | T101: =IFERROR(HYPERLINK("#'Main'!B"&MATCH(TRIM(A101),Main!B:B,0),"Open"),HYPERLINK("#'Main'!B1","Open")) -> Open
A102: https://africanmarketingconfederation.org/ | B102: Detail | C102: https://africanmarketingconfederation.org/news-articles | D102: NEWS & PUBLICATIONS | E102: 200 | F102: TRUE | G102: 0 | H102: 0 | I102: 0 | J102: 0 | K102: 0 | L102: FALSE | M102: 0 | N102: 0 | O102: 0 | P102: 0 | Q102: 0 | S102: LinksDetail | T102: =IFERROR(HYPERLINK("#'Main'!B"&MATCH(TRIM(A102),Main!B:B,0),"Open"),HYPERLINK("#'Main'!B1","Open")) -> Open
A103: https://africanmarketingconfederation.org/ | B103: Detail | C103: https://africanmarketingconfederation.org/news-articles | D103: NEWS ARTICLES | E103: 200 | F103: TRUE | G103: 0 | H103: 0 | I103: 0 | J103: 0 | K103: 0 | L103: FALSE | M103: 0 | N103: 0 | O103: 0 | P103: 0 | Q103: 0 | S103: LinksDetail | T103: =IFERROR(HYPERLINK("#'Main'!B"&MATCH(TRIM(A103),Main!B:B,0),"Open"),HYPERLINK("#'Main'!B1","Open")) -> Open
A104: https://africanmarketingconfederation.org/ | B104: Detail | C104: https://africanmarketingconfederation.org/publications-2 | D104: PUBLICATIONS | E104: 200 | F104: TRUE | G104: 0 | H104: 0 | I104: 0 | J104: 0 | K104: 0 | L104: FALSE | M104: 0 | N104: 0 | O104: 0 | P104: 0 | Q104: 0 | S104: LinksDetail | T104: =IFERROR(HYPERLINK("#'Main'!B"&MATCH(TRIM(A104),Main!B:B,0),"Open"),HYPERLINK("#'Main'!B1","Open")) -> Open
A105: https://africanmarketingconfederation.org/ | B105: Detail | C105: https://africanmarketingconfederation.org/amc-conference-2026 | D105: AMC Conference | E105: 200 | F105: TRUE | G105: 0 | H105: 0 | I105: 0 | J105: 0 | K105: 0 | L105: FALSE | M105: 0 | N105: 0 | O105: 0 | P105: 0 | Q105: 0 | S105: LinksDetail | T105: =IFERROR(HYPERLINK("#'Main'!B"&MATCH(TRIM(A105),Main!B:B,0),"Open"),HYPERLINK("#'Main'!B1","Open")) -> Open
... A131: https://africanmarketingconfederation.org/ | B131: Detail | C131: https://africanmarketingconfederation.org/subscribe | D131: Subscribe | E131: 200 | F131: TRUE | G131: 0 | H131: 0 | I131: 0 | J131: 0 | K131: 0 | L131: FALSE | M131: 0 | N131: 0 | O131: 0 | P131: 0 | Q131: 0 | S131: LinksDetail | T131: =IFERROR(HYPERLINK("#'Main'!B"&MATCH(TRIM(A131),Main!B:B,0),"Open"),HYPERLINK("#'Main'!B1","Open")) -> Open
A132: https://africanmarketingconfederation.org/ | B132: Detail | C132: https://africanmarketingconfederation.org/lays-world-cup-marketing-strategy-focuses-on-fan-fun-and-togetherness | E132: 200 | F132: TRUE | G132: 0 | H132: 0 | I132: 0 | J132: 0 | K132: 0 | L132: FALSE | M132: 0 | N132: 0 | O132: 0 | P132: 0 | Q132: 0 | S132: LinksDetail | T132: =IFERROR(HYPERLINK("#'Main'!B"&MATCH(TRIM(A132),Main!B:B,0),"Open"),HYPERLINK("#'Main'!B1","Open")) -> Open
A133: https://africanmarketingconfederation.org/ | B133: Detail | C133: https://africanmarketingconfederation.org/lays-world-cup-marketing-strategy-focuses-on-fan-fun-and-togetherness | D133: Lay’s World Cup marketing strategy focuses on fan fun and togetherness | E133: 200 | F133: TRUE | G133: 0 | H133: 0 | I133: 0 | J133: 0 | K133: 0 | L133: FALSE | M133: 0 | N133: 0 | O133: 0 | P133: 0 | Q133: 0 | S133: LinksDetail | T133: =IFERROR(HYPERLINK("#'Main'!B"&MATCH(TRIM(A133),Main!B:B,0),"Open"),HYPERLINK("#'Main'!B1","Open")) -> Open
A134: https://africanmarketingconfederation.org/ | B134: Detail | C134: https://africanmarketingconfederation.org/lays-world-cup-marketing-strategy-focuses-on-fan-fun-and-togetherness | D134: Read More » | E134: 200 | F134: TRUE | G134: 0 | H134: 0 | I134: 0 | J134: 0 | K134: 0 | L134: FALSE | M134: 0 | N134: 0 | O134: 0 | P134: 0 | Q134: 0 | S134: LinksDetail | T134: =IFERROR(HYPERLINK("#'Main'!B"&MATCH(TRIM(A134),Main!B:B,0),"Open"),HYPERLINK("#'Main'!B1","Open")) -> Open
A135: https://africanmarketingconfederation.org/ | B135: Detail | C135: https://africanmarketingconfederation.org/cost-of-groceries-the-primary-worry-for-almost-half-of-sa-consumers | E135: 200 | F135: TRUE | G135: 0 | H135: 0 | I135: 0 | J135: 0 | K135: 0 | L135: FALSE | M135: 0 | N135: 0 | O135: 0 | P135: 0 | Q135: 0 | S135: LinksDetail | T135: =IFERROR(HYPERLINK("#'Main'!B"&MATCH(TRIM(A135),Main!B:B,0),"Open"),HYPERLINK("#'Main'!B1","Open")) -> Open
A136: https://africanmarketingconfederation.org/ | B136: Detail | C136: https://africanmarketingconfederation.org/cost-of-groceries-the-primary-worry-for-almost-half-of-sa-consumers | D136: Cost of groceries the primary worry for almost half of SA consumers | E136: 200 | F136: TRUE | G136: 0 | H136: 0 | I136: 0 | J136: 0 | K136: 0 | L136: FALSE | M136: 0 | N136: 0 | O136: 0 | P136: 0 | Q136: 0 | S136: LinksDetail | T136: =IFERROR(HYPERLINK("#'Main'!B"&MATCH(TRIM(A136),Main!B:B,0),"Open"),HYPERLINK("#'Main'!B1","Open")) -> Open
A137: https://africanmarketingconfederation.org/ | B137: Detail | C137: https://africanmarketingconfederation.org/cost-of-groceries-the-primary-worry-for-almost-half-of-sa-consumers | D137: Read More » | E137: 200 | F137: TRUE | G137: 0 | H137: 0 | I137: 0 | J137: 0 | K137: 0 | L137: FALSE | M137: 0 | N137: 0 | O137: 0 | P137: 0 | Q137: 0 | S137: LinksDetail | T137: =IFERROR(HYPERLINK("#'Main'!B"&MATCH(TRIM(A137),Main!B:B,0),"Open"),HYPERLINK("#'Main'!B1","Open")) -> Open
A138: https://africanmarketingconfederation.org/ | B138: Detail | C138: https://africanmarketingconfederation.org/social-media-overtakes-television-as-main-source-of-news-for-kenyans | E138: 200 | F138: TRUE | G138: 0 | H138: 0 | I138: 0 | J138: 0 | K138: 0 | L138: FALSE | M138: 0 | N138: 0 | O138: 0 | P138: 0 | Q138: 0 | S138: LinksDetail | T138: =IFERROR(HYPERLINK("#'Main'!B"&MATCH(TRIM(A138),Main!B:B,0),"Open"),HYPERLINK("#'Main'!B1","Open")) -> Open
A139: https://africanmarketingconfederation.org/ | B139: Detail | C139: https://africanmarketingconfederation.org/social-media-overtakes-television-as-main-source-of-news-for-kenyans | D139: Social media overtakes television as main source of news for Kenyans | E139: 200 | F139: TRUE | G139: 0 | H139: 0 | I139: 0 | J139: 0 | K139: 0 | L139: FALSE | M139: 0 | N139: 0 | O139: 0 | P139: 0 | Q139: 0 | S139: LinksDetail | T139: =IFERROR(HYPERLINK("#'Main'!B"&MATCH(TRIM(A139),Main!B:B,0),"Open"),HYPERLINK("#'Main'!B1","Open")) -> Open
A140: https://africanmarketingconfederation.org/ | B140: Detail | C140: https://africanmarketingconfederation.org/social-media-overtakes-television-as-main-source-of-news-for-kenyans | D140: Read More » | E140: 200 | F140: TRUE | G140: 0 | H140: 0 | I140: 0 | J140: 0 | K140: 0 | L140: FALSE | M140: 0 | N140: 0 | O140: 0 | P140: 0 | Q140: 0 | S140: LinksDetail | T140: =IFERROR(HYPERLINK("#'Main'!B"&MATCH(TRIM(A140),Main!B:B,0),"Open"),HYPERLINK("#'Main'!B1","Open")) -> Open
A141: https://africanmarketingconfederation.org/ | B141: Detail | C141: https://africanmarketingconfederation.org/national-foods-holdings-expands-food-processing-capacity-in-zimbabwe | E141: 200 | F141: TRUE | G141: 0 | H141: 0 | I141: 0 | J141: 0 | K141: 0 | L141: FALSE | M141: 0 | N141: 0 | O141: 0 | P141: 0 | Q141: 0 | S141: LinksDetail | T141: =IFERROR(HYPERLINK("#'Main'!B"&MATCH(TRIM(A141),Main!B:B,0),"Open"),HYPERLINK("#'Main'!B1","Open")) -> Open
A142: https://africanmarketingconfederation.org/ | B142: Detail | C142: https://africanmarketingconfederation.org/national-foods-holdings-expands-food-processing-capacity-in-zimbabwe | D142: National Foods Holdings expands food-processing capacity in Zimbabwe | E142: 200 | F142: TRUE | G142: 0 | H142: 0 | I142: 0 | J142: 0 | K142: 0 | L142: FALSE | M142: 0 | N142: 0 | O142: 0 | P142: 0 | Q142: 0 | S142: LinksDetail | T142: =IFERROR(HYPERLINK("#'Main'!B"&MATCH(TRIM(A142),Main!B:B,0),"Open"),HYPERLINK("#'Main'!B1","Open")) -> Open
A143: https://africanmarketingconfederation.org/ | B143: Detail | C143: https://africanmarketingconfederation.org/national-foods-holdings-expands-food-processing-capacity-in-zimbabwe | D143: Read More » | E143: 200 | F143: TRUE | G143: 0 | H143: 0 | I143: 0 | J143: 0 | K143: 0 | L143: FALSE | M143: 0 | N143: 0 | O143: 0 | P143: 0 | Q143: 0 | S143: LinksDetail | T143: =IFERROR(HYPERLINK("#'Main'!B"&MATCH(TRIM(A143),Main!B:B,0),"Open"),HYPERLINK("#'Main'!B1","Open")) -> Open
A144: https://africanmarketingconfederation.org/ | B144: Detail | C144: https://africanmarketingconfederation.org/cracking-the-africa-code-the-functional-path-to-market-leadership | E144: 200 | F144: TRUE | G144: 0 | H144: 0 | I144: 0 | J144: 0 | K144: 0 | L144: FALSE | M144: 0 | N144: 0 | O144: 0 | P144: 0 | Q144: 0 | S144: LinksDetail | T144: =IFERROR(HYPERLINK("#'Main'!B"&MATCH(TRIM(A144),Main!B:B,0),"Open"),HYPERLINK("#'Main'!B1","Open")) -> Open
A145: https://africanmarketingconfederation.org/ | B145: Detail | C145: https://africanmarketingconfederation.org/cracking-the-africa-code-the-functional-path-to-market-leadership | D145: Cracking the Africa Code: The functional path to market leadership | E145: 200 | F145: TRUE | G145: 0 | H145: 0 | I145: 0 | J145: 0 | K145: 0 | L145: FALSE | M145: 0 | N145: 0 | O145: 0 | P145: 0 | Q145: 0 | S145: LinksDetail | T145: =IFERROR(HYPERLINK("#'Main'!B"&MATCH(TRIM(A145),Main!B:B,0),"Open"),HYPERLINK("#'Main'!B1","Open")) -> Open
A146: https://africanmarketingconfederation.org/ | B146: Detail | C146: https://africanmarketingconfederation.org/cracking-the-africa-code-the-functional-path-to-market-leadership | D146: Read More » | E146: 200 | F146: TRUE | G146: 0 | H146: 0 | I146: 0 | J146: 0 | K146: 0 | L146: FALSE | M146: 0 | N146: 0 | O146: 0 | P146: 0 | Q146: 0 | S146: LinksDetail | T146: =IFERROR(HYPERLINK("#'Main'!B"&MATCH(TRIM(A146),Main!B:B,0),"Open"),HYPERLINK("#'Main'!B1","Open")) -> Open
A147: https://africanmarketingconfederation.org/ | B147: Detail | C147: https://africanmarketingconfederation.org/traceability-giving-africa-a-marketing-edge-the-world-can-audit | E147: 200 | F147: TRUE | G147: 0 | H147: 0 | I147: 0 | J147: 0 | K147: 0 | L147: FALSE | M147: 0 | N147: 0 | O147: 0 | P147: 0 | Q147: 0 | S147: LinksDetail | T147: =IFERROR(HYPERLINK("#'Main'!B"&MATCH(TRIM(A147),Main!B:B,0),"Open"),HYPERLINK("#'Main'!B1","Open")) -> Open
A148: https://africanmarketingconfederation.org/ | B148: Detail | C148: https://africanmarketingconfederation.org/traceability-giving-africa-a-marketing-edge-the-world-can-audit | D148: Traceability: Giving Africa a marketing edge the world can audit | E148: 200 | F148: TRUE | G148: 0 | H148: 0 | I148: 0 | J148: 0 | K148: 0 | L148: FALSE | M148: 0 | N148: 0 | O148: 0 | P148: 0 | Q148: 0 | S148: LinksDetail | T148: =IFERROR(HYPERLINK("#'Main'!B"&MATCH(TRIM(A148),Main!B:B,0),"Open"),HYPERLINK("#'Main'!B1","Open")) -> Open
A149: https://africanmarketingconfederation.org/ | B149: Detail | C149: https://africanmarketingconfederation.org/traceability-giving-africa-a-marketing-edge-the-world-can-audit | D149: Read More » | E149: 200 | F149: TRUE | G149: 0 | H149: 0 | I149: 0 | J149: 0 | K149: 0 | L149: FALSE | M149: 0 | N149: 0 | O149: 0 | P149: 0 | Q149: 0 | S149: LinksDetail | T149: =IFERROR(HYPERLINK("#'Main'!B"&MATCH(TRIM(A149),Main!B:B,0),"Open"),HYPERLINK("#'Main'!B1","Open")) -> Open
A150: https://africanmarketingconfederation.org/ | B150: Detail | C150: https://africanmarketingconfederation.org/news-articles | D150: View all articles » | E150: 200 | F150: TRUE | G150: 0 | H150: 0 | I150: 0 | J150: 0 | K150: 0 | L150: FALSE | M150: 0 | N150: 0 | O150: 0 | P150: 0 | Q150: 0 | S150: LinksDetail | T150: =IFERROR(HYPERLINK("#'Main'!B"&MATCH(TRIM(A150),Main!B:B,0),"Open"),HYPERLINK("#'Main'!B1","Open")) -> Open
A151: https://africanmarketingconfederation.org/ | B151: Detail | C151: https://africanmarketingconfederation.org/publications-2 | D151: Strategic Marketing for Africa Magazine | E151: 200 | F151: TRUE | G151: 0 | H151: 0 | I151: 0 | J151: 0 | K151: 0 | L151: FALSE | M151: 0 | N151: 0 | O151: 0 | P151: 0 | Q151: 0 | S151: LinksDetail | T151: =IFERROR(HYPERLINK("#'Main'!B"&MATCH(TRIM(A151),Main!B:B,0),"Open"),HYPERLINK("#'Main'!B1","Open")) -> Open
A152: https://africanmarketingconfederation.org/ | B152: Detail | C152: https://www.facebook.com/The-African-Marketing-Confederation-108980418182403 | E152: 0 | F152: TRUE | G152: 0 | H152: 0 | I152: 0 | J152: 0 | K152: 0 | L152: FALSE | M152: 0 | N152: 0 | O152: 0 | P152: 0 | Q152: 0 | S152: LinksDetail | T152: =IFERROR(HYPERLINK("#'Main'!B"&MATCH(TRIM(A152),Main!B:B,0),"Open"),HYPERLINK("#'Main'!B1","Open")) -> Open
A153: https://africanmarketingconfederation.org/ | B153: Detail | C153: https://www.linkedin.com/company/african-marketing-confederation | E153: 0 | F153: TRUE | G153: 0 | H153: 0 | I153: 0 | J153: 0 | K153: 0 | L153: FALSE | M153: 0 | N153: 0 | O153: 0 | P153: 0 | Q153: 0 | S153: LinksDetail | T153: =IFERROR(HYPERLINK("#'Main'!B"&MATCH(TRIM(A153),Main!B:B,0),"Open"),HYPERLINK("#'Main'!B1","Open")) -> Open
...

Sheet Template & Duplication Risks
A1: URL | B1: Risk Category | C1: Subfolder / Template Group | D1: Issue | E1: Affected Ratio | F1: Affected URL Count | G1: Example URLs | H1: Exact Action | I1: Severity | J1: Source Legacy Tab | K1: Open in Main | L1: BACK TO DASHBOARD
B2: Template Pattern | C2: /amc-conference-2022-prospectus/ | D2: Missing H1 is template-wide | E2: 100 | F2: 1 | H2: Update template to render exactly one descriptive H1 for each page based on page-specific title data. | I2: Warning | J2: Pattern and Template Issues | K2: =IFERROR(HYPERLINK("#'Main'!B"&MATCH(TRIM(A2),Main!B:B,0),"Open"),HYPERLINK("#'Main'!B1","Open")) -> Open
B3: Template Pattern | C3: /amc-conference-2022-thank-you/ | D3: Missing H1 is template-wide | E3: 100 | F3: 1 | H3: Update template to render exactly one descriptive H1 for each page based on page-specific title data. | I3: Warning | J3: Pattern and Template Issues | K3: =IFERROR(HYPERLINK("#'Main'!B"&MATCH(TRIM(A3),Main!B:B,0),"Open"),HYPERLINK("#'Main'!B1","Open")) -> Open
B4: Template Pattern | C4: /amc-conference-2022/ | D4: Missing H1 is template-wide | E4: 100 | F4: 1 | H4: Update template to render exactly one descriptive H1 for each page based on page-specific title data. | I4: Warning | J4: Pattern and Template Issues | K4: =IFERROR(HYPERLINK("#'Main'!B"&MATCH(TRIM(A4),Main!B:B,0),"Open"),HYPERLINK("#'Main'!B1","Open")) -> Open

Sheet Playbook
A1: Section | B1: Item | C1: Guideline | D1: Why It Matters | E1: BACK TO DASHBOARD
A2: [Meta Data Standards]
B3: Meta Title | C3: 50-60 characters. Place primary keyword at the front. Avoid brand repetition unless there is space. | D3: Improves clarity and reduces SERP truncation risk.
B4: Meta Description | C4: 120-160 characters. Must contain a clear Call-To-Action (CTA) and active verbs. | D4: Supports stronger click-through and intent alignment.
B5: Target Keywords | C5: 1 Primary, 2 Secondary per page. Do not keyword stuff; focus on user intent. | D5: Keeps copy focused on topical relevance over keyword density.
A7: [On-Page Structure (H-Tags)]
B8: H1 Tag | C8: Exactly ONE per page. Must contain the primary topic/keyword. Think of it as the 'Book Title'. | D8: Provides the clearest top-level topical signal.
B9: H2 Tags | C9: Main sections. Use question formats (Who, What, How) to trigger Answer Engine extraction. | D9: Improves structured scannability for users and LLMs.
B10: H3 Tags | C10: Sub-sections under H2s. Use for lists, steps, or detailed breakdowns. | D10: Strengthens hierarchy and supports extraction-ready formatting.
B11: H4-H6 Tags | C11: Use sparingly. Only for granular formatting within complex H3 topics. | D11: Avoids over-nesting while preserving semantic structure.
A13: [AEO (Answer Engine Optimisation) & Content]
B14: AEO Answer Blocks | C14: 40-60 words. Placed directly beneath an H2 question. Must be factual, objective, and devoid of marketing fluff. | D14: Optimises direct extraction for answer engines and voice search.
B15: FAQ Schema | C15: Minimum 2-3 questions per informational page. Answers must be direct and stand alone without needing the rest of the page for context. | D15: Improves machine readability and rich-answer eligibility.
B16: Content Readability | C16: Keep sentences under 20 words. Use bullet points for any list of 3 or more items. | D16: Increases comprehension and snippet usability.
A18: [Visual & Social Branding]
B19: OG Image | C19: 1200 x 630 pixels. Keep text centered (safe zone) so it isn't cropped by mobile devices on LinkedIn/X. | D19: Ensures consistent social card presentation.
B20: Social Share Note | C20: Customize the message for the platform. LinkedIn = Professional insight. X (Twitter) = Quick hook. Facebook = Conversational. | D20: Improves engagement by matching platform context.
A22: [Glossary & Legend]
A23: How To Use | B23: Step 1: Start on Dashboard | C23: 5-minute executive scan | D23: Review pass rate, critical URL count, and Immediate Actions to understand overall risk first.
A24: How To Use | B24: Step 2: Prioritize and Assign | C24: Work top-down by Business Risk Score | D24: Use Priority URLs and FixPlan to pick highest-impact items, assign owner, and set status/sprint.
A25: How To Use | B25: Step 3: Execute and Validate | C25: Close loop every sprint | D25: Implement fixes, then verify by checking Technical/Indexability/AEO tabs and rerunning the audit.
A26: Orientation | B26: Where to Start | C26: Critical > Warning > Observation | D26: If you're short on time, work only Critical and Warning issues first, then return to Observation items.
A27: Color Key | B27: Green | C27: Good | D27: Pass / aligned with best practice or completed workflow item.
A28: Color Key | B28: Orange | C28: Medium risk | D28: Warning / in progress / medium-priority attention needed.
A29: Color Key | B29: Red | C29: High risk | D29: Failure / high-priority issue or to-do critical task.

Sheet AIOSEO
A1: URL | B1: WordPress Post ID | C1: Direct Edit Link | D1: AIOSEO Panel | E1: Severity | F1: Issue | G1: Priority Score | H1: Current Value | I1: Recommended Target | J1: How to Fix in AIOSEO | K1: Reference Tab | L1: Reference Field | M1: Action Needed | N1: Owner | O1: Status | P1: Est. Hours | Q1: Stable Issue ID | R1: Why It Matters | S1: Open in Main | T1: Open in Technical | U1: BACK TO DASHBOARD
A2: https://africanmarketingconfederation.org/amc-conference-2023/amc-awards-book-now | B2: 13164 | C2: https://africanmarketingconfederation.org/wp-admin/post.php?post=13164&action=edit | D2: Basic SEO | E2: Warning | F2: Missing meta description | G2: 67 | H2: Missing | I2: 120-160 characters | J2: In AIOSEO snippet settings, add a concise, unique meta description aligned to page intent. | K2: Main | L2: Meta Description | M2: Yes | N2: Copy Writer | O2: Open | P2: 4 | Q2: https://africanmarketingconfederation.org/amc-conference-2023/amc-awards-book-now::aioseo_missing_meta_description | R2: Missing descriptions reduce control over search snippet messaging. | S2: =IFERROR(HYPERLINK("#'Main'!B"&MATCH(TRIM(A2),Main!B:B,0),"Open"),HYPERLINK("#'Main'!B1","Open")) -> Open | T2: =IFERROR(HYPERLINK("#'Technical Diagnostics'!A"&MATCH(A2,'Technical Diagnostics'!A:A,0),"Open"),HYPERLINK("#'Technical Diagnostics'!A1","Open")) -> Open
A3: https://africanmarketingconfederation.org/ | B3: 8 | C3: https://africanmarketingconfederation.org/wp-admin/post.php?post=8&action=edit | D3: Content | E3: Warning | F3: Low AEO readiness score | G3: 67 | H3: 30 | I3: >=60 | J3: Add concise answer blocks, question-led subheadings, and clear structured sections. | K3: AEO | L3: AEO Readiness Score | M3: Yes | N3: Copy Writer | O3: Open | P3: 4 | Q3: https://africanmarketingconfederation.org/::aioseo_low_aeo_readiness_score | R3: Weak answer-style structure lowers AI/answer-engine retrieval potential. | S3: =IFERROR(HYPERLINK("#'Main'!B"&MATCH(TRIM(A3),Main!B:B,0),"Open"),HYPERLINK("#'Main'!B1","Open")) -> Open | T3: =IFERROR(HYPERLINK("#'Technical Diagnostics'!A"&MATCH(A3,'Technical Diagnostics'!A:A,0),"Open"),HYPERLINK("#'Technical Diagnostics'!A1","Open")) -> Open
A4: https://africanmarketingconfederation.org/about-us | B4: 84 | C4: https://africanmarketingconfederation.org/wp-admin/post.php?post=84&action=edit | D4: Content | E4: Warning | F4: Low AEO readiness score | G4: 67 | H4: 30 | I4: >=60 | J4: Add concise answer blocks, question-led subheadings, and clear structured sections. | K4: AEO | L4: AEO Readiness Score | M4: Yes | N4: Copy Writer | O4: Open | P4: 4 | Q4: https://africanmarketingconfederation.org/about-us::aioseo_low_aeo_readiness_score | R4: Weak answer-style structure lowers AI/answer-engine retrieval potential. | S4: =IFERROR(HYPERLINK("#'Main'!B"&MATCH(TRIM(A4),Main!B:B,0),"Open"),HYPERLINK("#'Main'!B1","Open")) -> Open | T4: =IFERROR(HYPERLINK("#'Technical Diagnostics'!A"&MATCH(A4,'Technical Diagnostics'!A:A,0),"Open"),HYPERLINK("#'Technical Diagnostics'!A1","Open")) -> Open
A5: https://africanmarketingconfederation.org/african-marketing-confederation-tourism-chapter | B5: 28165 | C5: https://africanmarketingconfederation.org/wp-admin/post.php?post=28165&action=edit | D5: Content | E5: Warning | F5: Low AEO readiness score | G5: 67 | H5: 30 | I5: >=60 | J5: Add concise answer blocks, question-led subheadings, and clear structured sections. | K5: AEO | L5: AEO Readiness Score | M5: Yes | N5: Copy Writer | O5: Open | P5: 4 | Q5: https://africanmarketingconfederation.org/african-marketing-confederation-tourism-chapter::aioseo_low_aeo_readiness_score | R5: Weak answer-style structure lowers AI/answer-engine retrieval potential. | S5: =IFERROR(HYPERLINK("#'Main'!B"&MATCH(TRIM(A5),Main!B:B,0),"Open"),HYPERLINK("#'Main'!B1","Open")) -> Open | T5: =IFERROR(HYPERLINK("#'Technical Diagnostics'!A"&MATCH(A5,'Technical Diagnostics'!A:A,0),"Open"),HYPERLINK("#'Technical Diagnostics'!A1","Open")) -> Open
A6: https://africanmarketingconfederation.org/amc-awards-2024 | B6: 16125 | C6: https://africanmarketingconfederation.org/wp-admin/post.php?post=16125&action=edit | D6: Content | E6: Warning | F6: Low AEO readiness score | G6: 67 | H6: 30 | I6: >=60 | J6: Add concise answer blocks, question-led subheadings, and clear structured sections. | K6: AEO | L6: AEO Readiness Score | M6: Yes | N6: Copy Writer | O6: Open | P6: 4 | Q6: https://africanmarketingconfederation.org/amc-awards-2024::aioseo_low_aeo_readiness_score | R6: Weak answer-style structure lowers AI/answer-engine retrieval potential. | S6: =IFERROR(HYPERLINK("#'Main'!B"&MATCH(TRIM(A6),Main!B:B,0),"Open"),HYPERLINK("#'Main'!B1","Open")) -> Open | T6: =IFERROR(HYPERLINK("#'Technical Diagnostics'!A"&MATCH(A6,'Technical Diagnostics'!A:A,0),"Open"),HYPERLINK("#'Technical Diagnostics'!A1","Open")) -> Open
A7: https://africanmarketingconfederation.org/amc-conference-2022 | B7: 4494 | C7: https://africanmarketingconfederation.org/wp-admin/post.php?post=4494&action=edit | D7: Content | E7: Warning | F7: Low AEO readiness score | G7: 67 | H7: 30 | I7: >=60 | J7: Add concise answer blocks, question-led subheadings, and clear structured sections. | K7: AEO | L7: AEO Readiness Score | M7: Yes | N7: Copy Writer | O7: Open | P7: 4 | Q7: https://africanmarketingconfederation.org/amc-conference-2022::aioseo_low_aeo_readiness_score | R7: Weak answer-style structure lowers AI/answer-engine retrieval potential. | S7: =IFERROR(HYPERLINK("#'Main'!B"&MATCH(TRIM(A7),Main!B:B,0),"Open"),HYPERLINK("#'Main'!B1","Open")) -> Open | T7: =IFERROR(HYPERLINK("#'Technical Diagnostics'!A"&MATCH(A7,'Technical Diagnostics'!A:A,0),"Open"),HYPERLINK("#'Technical Diagnostics'!A1","Open")) -> Open
A8: https://africanmarketingconfederation.org/amc-conference-2022-prospectus | B8: 5619 | C8: https://africanmarketingconfederation.org/wp-admin/post.php?post=5619&action=edit | D8: Content | E8: Warning | F8: Low AEO readiness score | G8: 67 | H8: 30 | I8: >=60 | J8: Add concise answer blocks, question-led subheadings, and clear structured sections. | K8: AEO | L8: AEO Readiness Score | M8: Yes | N8: Copy Writer | O8: Open | P8: 4 | Q8: https://africanmarketingconfederation.org/amc-conference-2022-prospectus::aioseo_low_aeo_readiness_score | R8: Weak answer-style structure lowers AI/answer-engine retrieval potential. | S8: =IFERROR(HYPERLINK("#'Main'!B"&MATCH(TRIM(A8),Main!B:B,0),"Open"),HYPERLINK("#'Main'!B1","Open")) -> Open | T8: =IFERROR(HYPERLINK("#'Technical Diagnostics'!A"&MATCH(A8,'Technical Diagnostics'!A:A,0),"Open"),HYPERLINK("#'Technical Diagnostics'!A1","Open")) -> Open
A9: https://africanmarketingconfederation.org/amc-conference-2022-thank-you | B9: 4941 | C9: https://africanmarketingconfederation.org/wp-admin/post.php?post=4941&action=edit | D9: Content | E9: Warning | F9: Low AEO readiness score | G9: 67 | H9: 30 | I9: >=60 | J9: Add concise answer blocks, question-led subheadings, and clear structured sections. | K9: AEO | L9: AEO Readiness Score | M9: Yes | N9: Copy Writer | O9: Open | P9: 4 | Q9: https://africanmarketingconfederation.org/amc-conference-2022-thank-you::aioseo_low_aeo_readiness_score | R9: Weak answer-style structure lowers AI/answer-engine retrieval potential. | S9: =IFERROR(HYPERLINK("#'Main'!B"&MATCH(TRIM(A9),Main!B:B,0),"Open"),HYPERLINK("#'Main'!B1","Open")) -> Open | T9: =IFERROR(HYPERLINK("#'Technical Diagnostics'!A"&MATCH(A9,'Technical Diagnostics'!A:A,0),"Open"),HYPERLINK("#'Technical Diagnostics'!A1","Open")) -> Open
A10: https://africanmarketingconfederation.org/amc-conference-2023 | B10: 12371 | C10: https://africanmarketingconfederation.org/wp-admin/post.php?post=12371&action=edit | D10: Content | E10: Warning | F10: Low AEO readiness score | G10: 67 | H10: 30 | I10: >=60 | J10: Add concise answer blocks, question-led subheadings, and clear structured sections. | K10: AEO | L10: AEO Readiness Score | M10: Yes | N10: Copy Writer | O10: Open | P10: 4 | Q10: https://africanmarketingconfederation.org/amc-conference-2023::aioseo_low_aeo_readiness_score | R10: Weak answer-style structure lowers AI/answer-engine retrieval potential. | S10: =IFERROR(HYPERLINK("#'Main'!B"&MATCH(TRIM(A10),Main!B:B,0),"Open"),HYPERLINK("#'Main'!B1","Open")) -> Open | T10: =IFERROR(HYPERLINK("#'Technical Diagnostics'!A"&MATCH(A10,'Technical Diagnostics'!A:A,0),"Open"),HYPERLINK("#'Technical Diagnostics'!A1","Open")) -> Open
A11: https://africanmarketingconfederation.org/amc-conference-2023/amc-awards | B11: 12954 | C11: https://africanmarketingconfederation.org/wp-admin/post.php?post=12954&action=edit | D11: Content | E11: Warning | F11: Low AEO readiness score | G11: 67 | H11: 30 | I11: >=60 | J11: Add concise answer blocks, question-led subheadings, and clear structured sections. | K11: AEO | L11: AEO Readiness Score | M11: Yes | N11: Copy Writer | O11: Open | P11: 4 | Q11: https://africanmarketingconfederation.org/amc-conference-2023/amc-awards::aioseo_low_aeo_readiness_score | R11: Weak answer-style structure lowers AI/answer-engine retrieval potential. | S11: =IFERROR(HYPERLINK("#'Main'!B"&MATCH(TRIM(A11),Main!B:B,0),"Open"),HYPERLINK("#'Main'!B1","Open")) -> Open | T11: =IFERROR(HYPERLINK("#'Technical Diagnostics'!A"&MATCH(A11,'Technical Diagnostics'!A:A,0),"Open"),HYPERLINK("#'Technical Diagnostics'!A1","Open")) -> Open
A12: https://africanmarketingconfederation.org/amc-conference-2023/amc-awards-book-now | B12: 13164 | C12: https://africanmarketingconfederation.org/wp-admin/post.php?post=13164&action=edit | D12: Content | E12: Warning | F12: Low AEO readiness score | G12: 67 | H12: 30 | I12: >=60 | J12: Add concise answer blocks, question-led subheadings, and clear structured sections. | K12: AEO | L12: AEO Readiness Score | M12: Yes | N12: Copy Writer | O12: Open | P12: 4 | Q12: https://africanmarketingconfederation.org/amc-conference-2023/amc-awards-book-now::aioseo_low_aeo_readiness_score | R12: Weak answer-style structure lowers AI/answer-engine retrieval potential. | S12: =IFERROR(HYPERLINK("#'Main'!B"&MATCH(TRIM(A12),Main!B:B,0),"Open"),HYPERLINK("#'Main'!B1","Open")) -> Open | T12: =IFERROR(HYPERLINK("#'Technical Diagnostics'!A"&MATCH(A12,'Technical Diagnostics'!A:A,0),"Open"),HYPERLINK("#'Technical Diagnostics'!A1","Open")) -> Open
A13: https://africanmarketingconfederation.org/ | B13: 8 | C13: https://africanmarketingconfederation.org/wp-admin/post.php?post=8&action=edit | D13: Readability | E13: Warning | F13: Low image alt coverage | G13: 67 | H13: 76.36 | I13: >=80% | J13: Add descriptive alt text to meaningful images in the page editor/media fields. | K13: Media | L13: Image Alt Coverage (%) | M13: Yes | N13: Copy Writer | O13: Open | P13: 4 | Q13: https://africanmarketingconfederation.org/::aioseo_low_image_alt_coverage | R13: Missing alt text reduces accessibility and weakens image context signals. | S13: =IFERROR(HYPERLINK("#'Main'!B"&MATCH(TRIM(A13),Main!B:B,0),"Open"),HYPERLINK("#'Main'!B1","Open")) -> Open | T13: =IFERROR(HYPERLINK("#'Technical Diagnostics'!A"&MATCH(A13,'Technical Diagnostics'!A:A,0),"Open"),HYPERLINK("#'Technical Diagnostics'!A1","Open")) -> Open
A14: https://africanmarketingconfederation.org/ | B14: 8 | C14: https://africanmarketingconfederation.org/wp-admin/post.php?post=8&action=edit | D14: Readability | E14: Warning | F14: Thin content | G14: 67 | H14: 37 | I14: >=300 words (quality first) | J14: Expand page copy with useful, unique sections that answer key user questions. | K14: Content | L14: Word Count | M14: Yes | N14: Copy Writer | O14: Open | P14: 4 | Q14: https://africanmarketingconfederation.org/::aioseo_thin_content | R14: Low-content pages can struggle to satisfy intent and rank competitively. | S14: =IFERROR(HYPERLINK("#'Main'!B"&MATCH(TRIM(A14),Main!B:B,0),"Open"),HYPERLINK("#'Main'!B1","Open")) -> Open | T14: =IFERROR(HYPERLINK("#'Technical Diagnostics'!A"&MATCH(A14,'Technical Diagnostics'!A:A,0),"Open"),HYPERLINK("#'Technical Diagnostics'!A1","Open")) -> Open
... A72: https://africanmarketingconfederation.org/amc-conference-2023/amc-awards-book-now | B72: 13164 | C72: https://africanmarketingconfederation.org/wp-admin/post.php?post=13164&action=edit | D72: Readability | E72: Observation | F72: No question-style headings | G72: 37 | H72: 0 | I72: >=1 where intent is informational | J72: Add at least one natural question heading (H2/H3) matching user intent. | K72: AEO | L72: Question Heading Count | M72: No | N72: Copy Writer | O72: Open | P72: 4 | Q72: https://africanmarketingconfederation.org/amc-conference-2023/amc-awards-book-now::aioseo_no_question-style_headings | R72: Question headings better align with query phrasing and snippet extraction. | S72: =IFERROR(HYPERLINK("#'Main'!B"&MATCH(TRIM(A72),Main!B:B,0),"Open"),HYPERLINK("#'Main'!B1","Open")) -> Open | T72: =IFERROR(HYPERLINK("#'Technical Diagnostics'!A"&MATCH(A72,'Technical Diagnostics'!A:A,0),"Open"),HYPERLINK("#'Technical Diagnostics'!A1","Open")) -> Open
A73: https://africanmarketingconfederation.org/ | B73: 8 | C73: https://africanmarketingconfederation.org/wp-admin/post.php?post=8&action=edit | D73: Schema | E73: Observation | F73: No FAQ/QA schema | G73: 37 | H73: FALSE | I73: True when page has Q&A intent | J73: If content is Q&A style, add FAQPage/QAPage schema in AIOSEO and keep markup aligned with on-page content. | K73: AEO | L73: QAPage/FAQ Schema Present | M73: No | N73: Copy Writer | O73: Open | P73: 4 | Q73: https://africanmarketingconfederation.org/::aioseo_no_faq_qa_schema | R73: Q&A schema can improve eligibility for answer-rich results. | S73: =IFERROR(HYPERLINK("#'Main'!B"&MATCH(TRIM(A73),Main!B:B,0),"Open"),HYPERLINK("#'Main'!B1","Open")) -> Open | T73: =IFERROR(HYPERLINK("#'Technical Diagnostics'!A"&MATCH(A73,'Technical Diagnostics'!A:A,0),"Open"),HYPERLINK("#'Technical Diagnostics'!A1","Open")) -> Open
A74: https://africanmarketingconfederation.org/about-us | B74: 84 | C74: https://africanmarketingconfederation.org/wp-admin/post.php?post=84&action=edit | D74: Schema | E74: Observation | F74: No FAQ/QA schema | G74: 37 | H74: FALSE | I74: True when page has Q&A intent | J74: If content is Q&A style, add FAQPage/QAPage schema in AIOSEO and keep markup aligned with on-page content. | K74: AEO | L74: QAPage/FAQ Schema Present | M74: No | N74: Copy Writer | O74: Open | P74: 4 | Q74: https://africanmarketingconfederation.org/about-us::aioseo_no_faq_qa_schema | R74: Q&A schema can improve eligibility for answer-rich results. | S74: =IFERROR(HYPERLINK("#'Main'!B"&MATCH(TRIM(A74),Main!B:B,0),"Open"),HYPERLINK("#'Main'!B1","Open")) -> Open | T74: =IFERROR(HYPERLINK("#'Technical Diagnostics'!A"&MATCH(A74,'Technical Diagnostics'!A:A,0),"Open"),HYPERLINK("#'Technical Diagnostics'!A1","Open")) -> Open
A75: https://africanmarketingconfederation.org/african-marketing-confederation-tourism-chapter | B75: 28165 | C75: https://africanmarketingconfederation.org/wp-admin/post.php?post=28165&action=edit | D75: Schema | E75: Observation | F75: No FAQ/QA schema | G75: 37 | H75: FALSE | I75: True when page has Q&A intent | J75: If content is Q&A style, add FAQPage/QAPage schema in AIOSEO and keep markup aligned with on-page content. | K75: AEO | L75: QAPage/FAQ Schema Present | M75: No | N75: Copy Writer | O75: Open | P75: 4 | Q75: https://africanmarketingconfederation.org/african-marketing-confederation-tourism-chapter::aioseo_no_faq_qa_schema | R75: Q&A schema can improve eligibility for answer-rich results. | S75: =IFERROR(HYPERLINK("#'Main'!B"&MATCH(TRIM(A75),Main!B:B,0),"Open"),HYPERLINK("#'Main'!B1","Open")) -> Open | T75: =IFERROR(HYPERLINK("#'Technical Diagnostics'!A"&MATCH(A75,'Technical Diagnostics'!A:A,0),"Open"),HYPERLINK("#'Technical Diagnostics'!A1","Open")) -> Open
A76: https://africanmarketingconfederation.org/amc-awards-2024 | B76: 16125 | C76: https://africanmarketingconfederation.org/wp-admin/post.php?post=16125&action=edit | D76: Schema | E76: Observation | F76: No FAQ/QA schema | G76: 37 | H76: FALSE | I76: True when page has Q&A intent | J76: If content is Q&A style, add FAQPage/QAPage schema in AIOSEO and keep markup aligned with on-page content. | K76: AEO | L76: QAPage/FAQ Schema Present | M76: No | N76: Copy Writer | O76: Open | P76: 4 | Q76: https://africanmarketingconfederation.org/amc-awards-2024::aioseo_no_faq_qa_schema | R76: Q&A schema can improve eligibility for answer-rich results. | S76: =IFERROR(HYPERLINK("#'Main'!B"&MATCH(TRIM(A76),Main!B:B,0),"Open"),HYPERLINK("#'Main'!B1","Open")) -> Open | T76: =IFERROR(HYPERLINK("#'Technical Diagnostics'!A"&MATCH(A76,'Technical Diagnostics'!A:A,0),"Open"),HYPERLINK("#'Technical Diagnostics'!A1","Open")) -> Open
A77: https://africanmarketingconfederation.org/amc-conference-2022 | B77: 4494 | C77: https://africanmarketingconfederation.org/wp-admin/post.php?post=4494&action=edit | D77: Schema | E77: Observation | F77: No FAQ/QA schema | G77: 37 | H77: FALSE | I77: True when page has Q&A intent | J77: If content is Q&A style, add FAQPage/QAPage schema in AIOSEO and keep markup aligned with on-page content. | K77: AEO | L77: QAPage/FAQ Schema Present | M77: No | N77: Copy Writer | O77: Open | P77: 4 | Q77: https://africanmarketingconfederation.org/amc-conference-2022::aioseo_no_faq_qa_schema | R77: Q&A schema can improve eligibility for answer-rich results. | S77: =IFERROR(HYPERLINK("#'Main'!B"&MATCH(TRIM(A77),Main!B:B,0),"Open"),HYPERLINK("#'Main'!B1","Open")) -> Open | T77: =IFERROR(HYPERLINK("#'Technical Diagnostics'!A"&MATCH(A77,'Technical Diagnostics'!A:A,0),"Open"),HYPERLINK("#'Technical Diagnostics'!A1","Open")) -> Open
A78: https://africanmarketingconfederation.org/amc-conference-2022-prospectus | B78: 5619 | C78: https://africanmarketingconfederation.org/wp-admin/post.php?post=5619&action=edit | D78: Schema | E78: Observation | F78: No FAQ/QA schema | G78: 37 | H78: FALSE | I78: True when page has Q&A intent | J78: If content is Q&A style, add FAQPage/QAPage schema in AIOSEO and keep markup aligned with on-page content. | K78: AEO | L78: QAPage/FAQ Schema Present | M78: No | N78: Copy Writer | O78: Open | P78: 4 | Q78: https://africanmarketingconfederation.org/amc-conference-2022-prospectus::aioseo_no_faq_qa_schema | R78: Q&A schema can improve eligibility for answer-rich results. | S78: =IFERROR(HYPERLINK("#'Main'!B"&MATCH(TRIM(A78),Main!B:B,0),"Open"),HYPERLINK("#'Main'!B1","Open")) -> Open | T78: =IFERROR(HYPERLINK("#'Technical Diagnostics'!A"&MATCH(A78,'Technical Diagnostics'!A:A,0),"Open"),HYPERLINK("#'Technical Diagnostics'!A1","Open")) -> Open
A79: https://africanmarketingconfederation.org/amc-conference-2022-thank-you | B79: 4941 | C79: https://africanmarketingconfederation.org/wp-admin/post.php?post=4941&action=edit | D79: Schema | E79: Observation | F79: No FAQ/QA schema | G79: 37 | H79: FALSE | I79: True when page has Q&A intent | J79: If content is Q&A style, add FAQPage/QAPage schema in AIOSEO and keep markup aligned with on-page content. | K79: AEO | L79: QAPage/FAQ Schema Present | M79: No | N79: Copy Writer | O79: Open | P79: 4 | Q79: https://africanmarketingconfederation.org/amc-conference-2022-thank-you::aioseo_no_faq_qa_schema | R79: Q&A schema can improve eligibility for answer-rich results. | S79: =IFERROR(HYPERLINK("#'Main'!B"&MATCH(TRIM(A79),Main!B:B,0),"Open"),HYPERLINK("#'Main'!B1","Open")) -> Open | T79: =IFERROR(HYPERLINK("#'Technical Diagnostics'!A"&MATCH(A79,'Technical Diagnostics'!A:A,0),"Open"),HYPERLINK("#'Technical Diagnostics'!A1","Open")) -> Open
A80: https://africanmarketingconfederation.org/amc-conference-2023 | B80: 12371 | C80: https://africanmarketingconfederation.org/wp-admin/post.php?post=12371&action=edit | D80: Schema | E80: Observation | F80: No FAQ/QA schema | G80: 37 | H80: FALSE | I80: True when page has Q&A intent | J80: If content is Q&A style, add FAQPage/QAPage schema in AIOSEO and keep markup aligned with on-page content. | K80: AEO | L80: QAPage/FAQ Schema Present | M80: No | N80: Copy Writer | O80: Open | P80: 4 | Q80: https://africanmarketingconfederation.org/amc-conference-2023::aioseo_no_faq_qa_schema | R80: Q&A schema can improve eligibility for answer-rich results. | S80: =IFERROR(HYPERLINK("#'Main'!B"&MATCH(TRIM(A80),Main!B:B,0),"Open"),HYPERLINK("#'Main'!B1","Open")) -> Open | T80: =IFERROR(HYPERLINK("#'Technical Diagnostics'!A"&MATCH(A80,'Technical Diagnostics'!A:A,0),"Open"),HYPERLINK("#'Technical Diagnostics'!A1","Open")) -> Open
A81: https://africanmarketingconfederation.org/amc-conference-2023/amc-awards | B81: 12954 | C81: https://africanmarketingconfederation.org/wp-admin/post.php?post=12954&action=edit | D81: Schema | E81: Observation | F81: No FAQ/QA schema | G81: 37 | H81: FALSE | I81: True when page has Q&A intent | J81: If content is Q&A style, add FAQPage/QAPage schema in AIOSEO and keep markup aligned with on-page content. | K81: AEO | L81: QAPage/FAQ Schema Present | M81: No | N81: Copy Writer | O81: Open | P81: 4 | Q81: https://africanmarketingconfederation.org/amc-conference-2023/amc-awards::aioseo_no_faq_qa_schema | R81: Q&A schema can improve eligibility for answer-rich results. | S81: =IFERROR(HYPERLINK("#'Main'!B"&MATCH(TRIM(A81),Main!B:B,0),"Open"),HYPERLINK("#'Main'!B1","Open")) -> Open | T81: =IFERROR(HYPERLINK("#'Technical Diagnostics'!A"&MATCH(A81,'Technical Diagnostics'!A:A,0),"Open"),HYPERLINK("#'Technical Diagnostics'!A1","Open")) -> Open
