Workbook

Sheet Table of Contents
A1: Table of Contents
A2: Section | B2: Open | C2: Description
A3: Dashboard | B3: =HYPERLINK("#'Dashboard'!A1","Open") -> Open | C3: Executive overview of site-wide SEO performance and critical alerts.
A4: Content Optimization Hub | B4: =HYPERLINK("#'Content Optimization Hub'!A1","Open") -> Open | C4: Interactive workspace for drafting SEO titles, descriptions, and AEO content.
A5: Quick Reference Guide | B5: =HYPERLINK("#'Quick Reference Guide'!A1","Open") -> Open | C5: In-workbook SEO and AEO copy standards and guardrails.
A6: FixPlan | B6: =HYPERLINK("#'FixPlan'!A1","Open") -> Open | C6: Prioritized list of technical and content fixes with estimated effort.
A7: Main | B7: =HYPERLINK("#'Main'!A1","Open") -> Open | C7: Primary URL inventory with titles, meta descriptions, and crawl signals.
A8: Technical | B8: =HYPERLINK("#'Technical'!A1","Open") -> Open | C8: Deep-dive diagnostic data for every crawled URL (Status, Load Time, etc.).
A9: PSI Performance | B9: =HYPERLINK("#'PSI Performance'!A1","Open") -> Open | C9: Lab PageSpeed scores and mobile CWV-related proxies.
A10: Content | B10: =HYPERLINK("#'Content'!A1","Open") -> Open | C10: Content depth, readability, headings, and thin-content flags per URL.
A11: AEO | B11: =HYPERLINK("#'AEO'!A1","Open") -> Open | C11: Answer Engine Optimization readiness scores and answer-block candidates.
A12: Schema & Metadata | B12: =HYPERLINK("#'Schema & Metadata'!A1","Open") -> Open | C12: JSON-LD, microdata, Open Graph, and Twitter card signals.
A13: Links | B13: =HYPERLINK("#'Links'!A1","Open") -> Open | C13: Internal and external link counts and anchor-text quality per URL.
A14: Indexability | B14: =HYPERLINK("#'Indexability'!A1","Open") -> Open | C14: Robots directives, canonicals, and indexability classification.
A15: Redirects | B15: =HYPERLINK("#'Redirects'!A1","Open") -> Open | C15: Redirect chains, hop lists, HTTPS upgrades, and loop detection.
A16: Priority URLs | B16: =HYPERLINK("#'Priority URLs'!A1","Open") -> Open | C16: High-value pages requiring immediate attention based on business risk.
A17: AIOSEO | B17: =HYPERLINK("#'AIOSEO'!A1","Open") -> Open | C17: Plugin-aligned recommendations and edit links for AIOSEO users.
A18: Security | B18: =HYPERLINK("#'Security'!A1","Open") -> Open | C18: Transport and hardening headers (HSTS, CSP, XFO, referrer policy, etc.).
A19: Summary | B19: =HYPERLINK("#'Summary'!A1","Open") -> Open | C19: Aggregated issue counts, AEO opportunities, and top critical URLs from the run.
A20: LinksDetail | B20: =HYPERLINK("#'LinksDetail'!A1","Open") -> Open | C20: Row-level outbound internal links with crawl resolution status.
A21: Media | B21: =HYPERLINK("#'Media'!A1","Open") -> Open | C21: Image inventory, alt coverage, filename quality, and mixed content flags.
A22: Pattern and Template Issues | B22: =HYPERLINK("#'Pattern and Template Issues'!A1","Open") -> Open | C22: Folder-level clusters and template-wide systemic issue patterns.
A23: Duplicates | B23: =HYPERLINK("#'Duplicates'!A1","Open") -> Open | C23: Near-duplicate titles and meta descriptions across the crawl set.
A24: IssueInventory | B24: =HYPERLINK("#'IssueInventory'!A1","Open") -> Open | C24: Flattened issue log with severity, owner seed, and stable IDs.
A25: RunMetadata | B25: =HYPERLINK("#'RunMetadata'!A1","Open") -> Open | C25: Run configuration, timestamps, and environment notes.
A26: DeltaFromPreviousRun | B26: =HYPERLINK("#'DeltaFromPreviousRun'!A1","Open") -> Open | C26: New, fixed, and persistent issues compared to a prior audit workbook.
A27: ResolvedIssues | B27: =HYPERLINK("#'ResolvedIssues'!A1","Open") -> Open | C27: Issues marked resolved when compared to the previous export.
A28: Glossary & Legend | B28: =HYPERLINK("#'Glossary & Legend'!A1","Open") -> Open | C28: Definitions for metrics, badges, and workbook conventions.
A29: CrawlGraph | B29: =HYPERLINK("#'CrawlGraph'!A1","Open") -> Open | C29: Derived link graph metrics (click depth, inlinks, PageRank proxy).
A30: SitemapQA | B30: =HYPERLINK("#'SitemapQA'!A1","Open") -> Open | C30: Sitemap coverage, URL membership checks, and sitemap metadata QA.

Sheet Dashboard
A1: Executive SEO & AEO Performance Report
A2: Executive SEO & AEO Dashboard
A4: EXECUTIVE METRICS | B4: Value | D4: Status | E4: Count | G4: OWNER ISSUE SUMMARY
A5: =HYPERLINK("#'Main'!A1","Total URLs") -> Total URLs | B5: 10 | D5: 200 OK | E5: 10 | G5: Owner | H5: Issue Rows | I5: Affected URLs | J5: Critical | K5: Warning
A6: =HYPERLINK("#'Summary'!A1","Overall Health Score") -> Overall Health Score | B6: =IFERROR(30.2/100,0) -> 0.302 | D6: 3xx Redirects | E6: 0 | G6: =HYPERLINK("#'FixPlan'!A1","Copy Writer") -> Copy Writer | H6: 20 | I6: 74 | J6: 1 | K6: 8
A7: =HYPERLINK("#'Summary'!A1","SEO Pass Rate %") -> SEO Pass Rate % | B7: 0 | D7: 4xx Errors | E7: 0 | G7: =HYPERLINK("#'FixPlan'!A1","Dev") -> Dev | H7: 9 | I7: 10 | J7: 4 | K7: 4
A8: =HYPERLINK("#'Technical'!A1","Pass URLs") -> Pass URLs | B8: 0 | D8: 5xx Errors | E8: 0 | G8: =HYPERLINK("#'FixPlan'!A1","Server/Host") -> Server/Host | H8: 5 | I8: 10 | J8: 2 | K8: 0
A9: =HYPERLINK("#'FixPlan'!A1","Critical URLs") -> Critical URLs | B9: 10 | D9: Other | E9: 0
A10: =HYPERLINK("#'Technical'!A1","Warning URLs") -> Warning URLs | B10: 0
A11: =HYPERLINK("#'Technical'!A1","Error Rate % (4xx/5xx)") -> Error Rate % (4xx/5xx) | B11: =IFERROR(0/10,0) -> 0
A12: =HYPERLINK("#'Technical'!A1","Crawl Success Rate % (2xx)") -> Crawl Success Rate % (2xx) | B12: =IFERROR(10/10,0) -> 1 | D12: Severity | E12: Count | J12: Quick Navigation | K12: Open
A13: =HYPERLINK("#'Technical'!A1","Critical URL Rate %") -> Critical URL Rate % | B13: =IFERROR(10/10,0) -> 1 | D13: Critical | E13: 7 | J13: Fix Plan | K13: =HYPERLINK("#FixPlan!A1","Open") -> Open
A14: =HYPERLINK("#'Technical'!A1","Warning URL Rate %") -> Warning URL Rate % | B14: =IFERROR(0/10,0) -> 0 | D14: Warning | E14: 12 | J14: Main URL Data | K14: =HYPERLINK("#Main!A1","Open") -> Open
A15: Projected Health Score % (if all To Do done) | B15: 0.9302 | D15: Medium | E15: 0 | J15: Technical Diagnostics | K15: =HYPERLINK("#Technical!A1","Open") -> Open
A16: Projected Pass Rate % (if all To Do done) | B16: 0.85 | D16: Low | E16: 15 | J16: Indexability | K16: =HYPERLINK("#Indexability!A1","Open") -> Open
A17: =HYPERLINK("#'Content Optimization Hub'!A1","Content Hub Readiness (%)") -> Content Hub Readiness (%) | B17: =IFERROR(COUNTIF('Content Optimization Hub'!A:A,"Complete")/COUNTA('Content Optimization Hub'!E:E),0) -> 0.18181818 | J17: AEO Opportunities | K17: =HYPERLINK("#AEO!A1","Open") -> Open
A18: =HYPERLINK("#'Schema & Metadata'!A1","URLs with Schema") -> URLs with Schema | B18: 0 | J18: AIOSEO Action Queue | K18: =HYPERLINK("#AIOSEO!A1","Open") -> Open
A19: =HYPERLINK("#'Links'!A1","Broken Internal Links") -> Broken Internal Links | B19: 0
E20: Traditional SEO vs. 2026 AEO Readiness | J20: BUSINESS IMPACT SUMMARY
E21: Dimension | F21: Score | J21: 0 error URLs detected (0 4xx / 0 5xx). Critical issue volume is 10 URLs and warning volume is 0. Top blocker: Broken Internal Links affecting 10 URLs.
E22: Traditional SEO | F22: 0.5812
E23: 2026 AEO Readiness | F23: 0
E24: Strategic Narrative
E25: SEO and AEO signals are moving together; continue balancing crawl health with answer-first content.
B44: TOP ISSUES TO FIX FIRST | C44: Affected URLs
B45: =HYPERLINK("#FixPlan!A2","Broken Internal Links") -> Broken Internal Links | C45: 10
B46: =HYPERLINK("#FixPlan!A9","Low AEO Readiness Score") -> Low AEO Readiness Score | C46: 10
B47: =HYPERLINK("#FixPlan!A8","Low Image Alt Coverage") -> Low Image Alt Coverage | C47: 10
B48: =HYPERLINK("#FixPlan!A7","AI Crawlers Not Explicitly Allowed") -> AI Crawlers Not Explicitly Allowed | C48: 10
B49: =HYPERLINK("#FixPlan!A6","No 40-60 Word Answer Paragraphs") -> No 40-60 Word Answer Paragraphs | C49: 10

Sheet Content Optimization Hub
A1: CONTENT HUB INSTRUCTIONS: 1. Draft in 'Proposed' columns. | 2. Watch 'Count' for Green. | 3. Click 'Elementor' link. | 4. Mark 'Status' as 'Completed'. | NOTE: If images show '#BLOCKED!', click the 'Security Warning' bar at the top of Excel and select 'Enable Content'.
A2: Action Required | B2: Status | C2: Assigned Owner | D2: Content Cluster ID | E2: URL | F2: Elementor Builder Link | G2: Target Keywords | H2: Current Page Copy Snippet | I2: Current Title | J2: Proposed Title (50-60 Chars) | K2: Title Count | L2: Current Meta Desc | M2: Proposed Meta Desc (120-160 Chars) | N2: Desc Count | O2: Current H-Tag Structure | P2: Proposed H-Tag Fixes | Q2: AEO Answer Block Draft | R2: FAQ/QA Draft | S2: Current OG-Image URL | T2: OG Image Preview | U2: Social Share Note | V2: SEO Score | W2: Technical Health | X2: Copy Score | Y2: Open in Main
A3: Needs Copy | B3: To Do | C3: Unassigned | D3: home-african-marketing-confed | E3: https://africanmarketingconfederation.org/ | F3: https://africanmarketingconfederation.org/wp-admin/post.php?post=8&action=elementor | H3: European marketers gather to choose their top achievers for 2026 Marketing associations from across Europe nominated national champions, with 10 finalists competing for the Marketer of the Year title. Read More » April 30, 2026 | I3: African Marketing Confederation - Uniting Marketers for Excellence | L3: The African Marketing Confederation is the ground-breaking Pan-African body driving the development of top marketing standards across Africa and beyond. | O3: H1: ABOUT The African Marketing Confederation H2: The 2026 AMC Conference H2: Meets the Mighty Victoria Falls H2: 23-25 September | Livingstone, Zambia H2: The 2026 AMC Conference H2: Meets the Mighty Victoria Falls | S3: https://africanmarketingconfederation.org/wp-content/uploads/2026/03/og-image.png | T3: =IF(LEN(S3)>0, _xlfn.IMAGE(S3), "") -> #VALUE! | V3: 36.75 | W3: 24 | X3: 75 | Y3: =IFERROR(HYPERLINK("#Main!A"&MATCH(E2,Main!A:A,0),"Open"),HYPERLINK("#Main!A1","Open")) -> Open
A4: Needs Copy | B4: To Do | C4: Unassigned | D4: about-us-african-marketing-confed | E4: https://africanmarketingconfederation.org/about-us | F4: https://africanmarketingconfederation.org/wp-admin/post.php?post=84&action=elementor | G4: About Us | H4: Skip to content ABOUT The African Marketing Confederation The African Marketing Confederation is the ground-breaking Pan African body of marketing professionals spearheading the ongoing development of the highest possible standards of marketing acro... | I4: African Marketing Confederation – The Leading Marketing Professional Body – African Marketing Confederation | L4: ABOUT The African Marketing Confederation The African Marketing Confederation is the ground-breaking Pan African body of marketing professionals spearheading the ongoing development of the highest possible standards of marketing across Africa. Founded in 2011, the AMC is a collaboration between the African national marketing bodies and associations to exchange expertise and information, and to promote | O4: H1: ABOUT The African Marketing Confederation H3: African Marketing Confederation PRESIDENT’S COUNCIL H2: Helen McIntee H2: President and Co-founder H2: David Balikuddembe H2: Secretary General | S4: https://africanmarketingconfederation.org/wp-content/uploads/2026/03/og-image.png | T4: =IF(LEN(S4)>0, _xlfn.IMAGE(S4), "") -> #VALUE! | V4: 46.5 | W4: 37 | X4: 75 | Y4: =IFERROR(HYPERLINK("#Main!A"&MATCH(E3,Main!A:A,0),"Open"),HYPERLINK("#Main!A1","Open")) -> Open
A5: Needs Optimization | B5: To Do | C5: Unassigned | D5: african-marketing-confederation-tourism-chapter-african-marketing-confed | E5: https://africanmarketingconfederation.org/african-marketing-confederation-tourism-chapter | F5: https://africanmarketingconfederation.org/wp-admin/post.php?post=28165&action=elementor | G5: African Marketing Confederation Tourism Chapter | H5: Skip to content African Marketing Confederation Tourism Chapter Shaping Africa’s Tourism Narrative Through Strategic Marketing Tourism is one of Africa’s most powerful economic engines – generating jobs, stimulating investment, and fostering cultural... | I5: African Marketing Confederation Tourism Chapter – African Marketing Confederation | L5: African Marketing Confederation Tourism Chapter Shaping Africa’s Tourism Narrative Through Strategic Marketing Tourism is one of Africa’s most powerful economic engines - generating jobs, stimulating investment, and fostering cultural exchange.The African Marketing Confederation is proud to launch the Tourism Chapter, a bold initiative to elevate African tourism through the lens of world-class marketing. Launched at the | O5: H1: African Marketing Confederation Tourism Chapter H3: Shaping Africa’s Tourism Narrative Through Strategic Marketing H2: Charting the Course: Purpose, Mission & Vision for Africa’s Tourism Future H2: Our Goals and Objectives: | S5: https://africanmarketingconfederation.org/wp-content/uploads/2026/03/og-image.png | T5: =IF(LEN(S5)>0, _xlfn.IMAGE(S5), "") -> #VALUE! | V5: 47.5 | W5: 30 | X5: 100 | Y5: =IFERROR(HYPERLINK("#Main!A"&MATCH(E4,Main!A:A,0),"Open"),HYPERLINK("#Main!A1","Open")) -> Open
A6: Needs Optimization | B6: To Do | C6: Unassigned | D6: amc-awards-2024-amc-awards-{n}-–-african | E6: https://africanmarketingconfederation.org/amc-awards-2024 | F6: https://africanmarketingconfederation.org/wp-admin/post.php?post=16125&action=elementor | G6: Amc Awards 2024 | H6: English Français Português Español Igbo Deutsch Kiswahili ພາສາລາວ العربية Afsoomaali Sesotho 简体中文 Русский Zulu en NOMINATIONS are Open ! AMC Awards The African Marketing Confederation Awards event is held annually as part of the African Marketing Con... | I6: AMC Awards 2024 – African Marketing Confederation | L6: NOMINATIONS are Open ! AMC Awards The African Marketing Confederation Awards event is held annually as part of the African Marketing Confederation Forum. This distinguished event celebrates and acknowledges outstanding marketing campaigns and the visionary individuals behind them. The awards presented honor not only the groundbreaking strategies and creative brilliance that set these campaigns apart but | O6: H1: NOMINATIONS are Open ! H2: Awards Categories H2: Tourism & Destination Marketing Campaign H2: of the Year H2: Best Social Media Campaign of the Year H2: Best Social Media Campaign | S6: https://africanmarketingconfederation.org/wp-content/uploads/2021/08/amc_faw.png | T6: =IF(LEN(S6)>0, _xlfn.IMAGE(S6), "") -> #VALUE! | V6: 47.5 | W6: 30 | X6: 100 | Y6: =IFERROR(HYPERLINK("#Main!A"&MATCH(E5,Main!A:A,0),"Open"),HYPERLINK("#Main!A1","Open")) -> Open
A7: Needs Copy | B7: To Do | C7: Unassigned | D7: amc-conference-2022-amc-conference-{n}-–-afr | E7: https://africanmarketingconfederation.org/amc-conference-2022 | F7: https://africanmarketingconfederation.org/wp-admin/post.php?post=4494&action=elementor | G7: Amc Conference 2022 | H7: AMC officially welcomes new member associations into the fold October 8, 2024 No Comments Angola, Botswana, Ethiopia, Mozambique and Tanzania receive their membership certificates. AMC now has 16 members. Read More » | I7: AMC Conference 2022 – African Marketing Confederation | L7: corinna kopf onlyfans leaks AMC Conference 2022 Thank you for attending19 - 22 October 2022 The African Marketing Confederation's Annual Conference brought together the best collection of marketing leaders from top companies, marketing bodies and associations to share tactics and best practices on how to build the next generation of marketing. Event Highlights Thank you for Attending! | O7: H2: AMC Conference 2022 H2: Event Highlights H3: AMC officially welcomes new member associations into the fold H3: Marketers are placing the ads where consumers don’t want to see them H3: Time for Africa to control its own narrative and image, delegates told H3: Excitement as Ghana announced as host of 2025 AMC marketing conference | S7: https://africanmarketingconfederation.org/wp-content/uploads/2026/03/og-image.png | T7: =IF(LEN(S7)>0, _xlfn.IMAGE(S7), "") -> #VALUE! | V7: 31.5 | W7: 27 | X7: 45 | Y7: =IFERROR(HYPERLINK("#Main!A"&MATCH(E6,Main!A:A,0),"Open"),HYPERLINK("#Main!A1","Open")) -> Open
A8: Needs Copy | B8: To Do | C8: Unassigned | D8: amc-conference-2022-prospectus-amc-conference-{n}-–-pro | E8: https://africanmarketingconfederation.org/amc-conference-2022-prospectus | F8: https://africanmarketingconfederation.org/wp-admin/post.php?post=5619&action=elementor | G8: Amc Conference 2022 Prospectus | H8: Skip to content AMC Conference 2022 23 - 24 March 2022 Navigating Africa’s Unique Marketing Mix BOOK NOW 00 Days 00 Hours 00 Minutes 00 Seconds download prospectus To download the AMC 2022 Conference Prospectus please complete the form below: First ... | I8: AMC Conference 2022 – Prospectus – African Marketing Confederation | L8: AMC Conference 2022 23 - 24 March 2022 Navigating Africa's Unique Marketing Mix BOOK NOW Days Hours Minutes Seconds download prospectus To download the AMC 2022 Conference Prospectus please complete the form below: First Name Last Name Email Mobile Company I've read and agree to the Privacy Policy BOOK NOW FOR THE AMC CONFERENCE 2022 | O8: H2: AMC Conference 2022 H2: download prospectus H2: BOOK NOW FOR THE AMC CONFERENCE 2022 | S8: https://africanmarketingconfederation.org/wp-content/uploads/2026/03/og-image.png | T8: =IF(LEN(S8)>0, _xlfn.IMAGE(S8), "") -> #VALUE! | V8: 31.5 | W8: 27 | X8: 45 | Y8: =IFERROR(HYPERLINK("#Main!A"&MATCH(E7,Main!A:A,0),"Open"),HYPERLINK("#Main!A1","Open")) -> Open
A9: Needs Copy | B9: To Do | C9: Unassigned | D9: amc-conference-2022-thank-you-amc-conference-{n}-–-tha | E9: https://africanmarketingconfederation.org/amc-conference-2022-thank-you | F9: https://africanmarketingconfederation.org/wp-admin/post.php?post=4941&action=elementor | G9: Amc Conference 2022 Thank You | H9: Skip to content AMC Conference 2022 23 - 24 March 2022 Navigating Africa’s Unique Marketing Mix ENQUIRE NOW 00 Days 00 Hours 00 Minutes 00 Seconds Success! Thank you for completing the enquiry form. Our team will contact you shortly! × The AMC Confer... | I9: AMC Conference 2022 – Thank You – African Marketing Confederation | L9: AMC Conference 2022 23 - 24 March 2022 Navigating Africa's Unique Marketing Mix ENQUIRE NOW Days Hours Minutes Seconds Success! Thank you for completing the enquiry form. Our team will contact you shortly! × Dismiss alert The AMC Conference is the must attend Pan African event for marketing professionals. It will focus on solutions for | O9: H2: AMC Conference 2022 H2: WHO SHOULD ATTEND H2: Countries Participating H3: South Africa H3: Nigeria H3: Morocco | S9: https://africanmarketingconfederation.org/wp-content/uploads/2026/03/og-image.png | T9: =IF(LEN(S9)>0, _xlfn.IMAGE(S9), "") -> #VALUE! | V9: 40 | W9: 30 | X9: 70 | Y9: =IFERROR(HYPERLINK("#Main!A"&MATCH(E8,Main!A:A,0),"Open"),HYPERLINK("#Main!A1","Open")) -> Open
A10: Complete | B10: To Do | C10: Unassigned | D10: amc-conference-2023-amc-conference-{n}-–-afr | E10: https://africanmarketingconfederation.org/amc-conference-2023 | F10: https://africanmarketingconfederation.org/wp-admin/post.php?post=12371&action=elementor | G10: Amc Conference 2023 | H10: AMC Conference 6 - 9 September 2023 Imperial Botanical Beach Hotel, Entebbe, Uganda Thank you for joining us! View Presentations 2nd Annual African Marketing Confederation Conference Africa's $3.4 trillion Economy: Opportunities for Marketers Welcome... | I10: AMC Conference 2023 – African Marketing Confederation | L10: AMC Conference 6 - 9 September 2023 Imperial Botanical Beach Hotel, Entebbe, Uganda Thank you for joining us! View Presentations 2nd Annual African Marketing Confederation Conference Africa's $3.4 trillion Economy: Opportunities for Marketers Welcome to the Recap of the 2nd Annual African Marketing Conference: Unveiling Africa's $3.4 Trillion EconomyOur conference was a remarkable exploration of | O10: H1: AMC Conference H2: Africa's $3.4 trillion Economy: Opportunities for Marketers H2: Thank you for joining us! H2: Topics covered H3: Africa Free Trade Area H3: Business Intelligence | S10: https://africanmarketingconfederation.org/wp-content/uploads/2021/08/amc_faw.png | T10: =IF(LEN(S10)>0, _xlfn.IMAGE(S10), "") -> #VALUE! | V10: 55 | W10: 40 | X10: 100 | Y10: =IFERROR(HYPERLINK("#Main!A"&MATCH(E9,Main!A:A,0),"Open"),HYPERLINK("#Main!A1","Open")) -> Open
A11: Complete | B11: To Do | C11: Unassigned | D11: amc-conference-2023-amc-awards-–-african-mar | E11: https://africanmarketingconfederation.org/amc-conference-2023/amc-awards | F11: https://africanmarketingconfederation.org/wp-admin/post.php?post=12954&action=elementor | G11: Amc Awards | H11: Skip to content AMC Awards Welcome to the prestigious African Marketing Confederation Awards, a distinguished event that celebrates and acknowledges the remarkable achievements, cutting-edge innovations, and exceptional leadership demonstrated by out... | I11: AMC Awards – African Marketing Confederation | L11: AMC Awards Welcome to the prestigious African Marketing Confederation Awards, a distinguished event that celebrates and acknowledges the remarkable achievements, cutting-edge innovations, and exceptional leadership demonstrated by outstanding individuals within the dynamic realm of marketing across the expansive African region.During the 2nd Annual African Marketing Confederation Conference, held from 6th to 9th September at the | O11: H1: AMC Awards H2: AMC AWARD Winners | S11: https://africanmarketingconfederation.org/wp-content/uploads/2021/08/amc_faw.png | T11: =IF(LEN(S11)>0, _xlfn.IMAGE(S11), "") -> #VALUE! | V11: 55 | W11: 40 | X11: 100 | Y11: =IFERROR(HYPERLINK("#Main!A"&MATCH(E10,Main!A:A,0),"Open"),HYPERLINK("#Main!A1","Open")) -> Open
A12: Needs Copy | B12: To Do | C12: Unassigned | D12: amc-conference-2023-amc-awards-|-book-now-–- | E12: https://africanmarketingconfederation.org/amc-conference-2023/amc-awards-book-now | F12: https://africanmarketingconfederation.org/wp-admin/post.php?post=13164&action=elementor | G12: Amc Awards Book Now | H12: Skip to content English Français Português Español Igbo Deutsch Kiswahili ພາສາລາວ العربية Afsoomaali Sesotho 简体中文 Русский Zulu en 0 Your Cart Your cart is empty Return to Shop Continue Shopping Notifications | I12: AMC Awards | Book Now – African Marketing Confederation | L12: MISSING DESCRIPTION | S12: https://africanmarketingconfederation.org/wp-content/uploads/2021/08/amc_faw.png | T12: =IF(LEN(S12)>0, _xlfn.IMAGE(S12), "") -> #VALUE! | V12: 19 | W12: 17 | X12: 25 | Y12: =IFERROR(HYPERLINK("#Main!A"&MATCH(E11,Main!A:A,0),"Open"),HYPERLINK("#Main!A1","Open")) -> Open

Sheet Quick Reference Guide
A1: Section | B1: Item | C1: Guideline | D1: Why It Matters | E1: BACK TO DASHBOARD
A2: [Meta Data Standards]
B3: Meta Title | C3: 50-60 characters. Place primary keyword at the front. Avoid brand repetition unless there is space. | D3: Improves clarity and reduces SERP truncation risk.
B4: Meta Description | C4: 120-160 characters. Must contain a clear Call-To-Action (CTA) and active verbs. | D4: Supports stronger click-through and intent alignment.
B5: Target Keywords | C5: 1 Primary, 2 Secondary per page. Do not keyword stuff; focus on user intent. | D5: Keeps copy focused on topical relevance over keyword density.
A7: [On-Page Structure (H-Tags)]
B8: H1 Tag | C8: Exactly ONE per page. Must contain the primary topic/keyword. Think of it as the 'Book Title'. | D8: Provides the clearest top-level topical signal.
B9: H2 Tags | C9: Main sections. Use question formats (Who, What, How) to trigger Answer Engine extraction. | D9: Improves structured scannability for users and LLMs.
B10: H3 Tags | C10: Sub-sections under H2s. Use for lists, steps, or detailed breakdowns. | D10: Strengthens hierarchy and supports extraction-ready formatting.
B11: H4-H6 Tags | C11: Use sparingly. Only for granular formatting within complex H3 topics. | D11: Avoids over-nesting while preserving semantic structure.
A13: [AEO (Answer Engine Optimization) & Content]
B14: AEO Answer Blocks | C14: 40-60 words. Placed directly beneath an H2 question. Must be factual, objective, and devoid of marketing fluff (e.g., 'The best way to...'). | D14: Optimizes direct extraction for answer engines and voice search.
B15: FAQ Schema | C15: Minimum 2-3 questions per informational page. Answers must be direct and stand alone without needing the rest of the page for context. | D15: Improves machine readability and rich-answer eligibility.
B16: Content Readability | C16: Keep sentences under 20 words. Use bullet points for any list of 3 or more items. | D16: Increases comprehension and snippet usability.
A18: [Visual & Social Branding]
B19: OG Image | C19: 1200 x 630 pixels. Keep text centered (safe zone) so it isn't cropped by mobile devices on LinkedIn/X. | D19: Ensures consistent social card presentation.
B20: Social Share Note | C20: Customize the message for the platform. LinkedIn = Professional insight. X (Twitter) = Quick hook. Facebook = Conversational. | D20: Improves engagement by matching platform context.

Sheet FixPlan
A1: Issue Type | B1: Severity | C1: Priority Score | D1: Affected Count | E1: Affected URLs | F1: Detail Reference Tab | G1: Resolution Type | H1: URL | I1: Recommended Fix | J1: Likely Root Cause | K1: Owner | L1: Agency Owner | M1: Effort | N1: Est. Hours | O1: Est. Sprint Points | P1: Aging/Priority | Q1: Status | R1: Verified By | S1: Date Resolved | T1: Revenue Risk | U1: Action Needed | V1: Jump to Details | W1: Sprint | X1: Category | Y1: Fix Type | Z1: Estimated Traffic Impact | AA1: Fix Effort | AB1: ROI Score | AC1: Exact Action | AD1: Open in Main | AE1: Hub Status (Content Hub) | AF1: BACK TO DASHBOARD
A2: Non-200 Status | B2: Critical | C2: 105 | D2: 0 | F2: Technical | G2: Manual Content | I2: Fix status code, restore page, or implement correct redirect to canonical destination. | J2: URL returns 4xx/5xx or equivalent failure. | K2: Server/Host | L2: Server/Host | M2: M | N2: 10 | O2: 5 | P2: Immediate (Current Sprint) | Q2: To Do | T2: High Risk | U2: Yes | V2: Open in Main Tab | X2: SEO | Y2: Technical | Z2: Low | AA2: 10 | AB2: 0 | AC2: Resolve 'Non-200 Status' using technical best practices and validate in the related detail tab. | AD2: =IFERROR(HYPERLINK("#Main!A"&MATCH(H2,Main!A:A,0),"Open"),HYPERLINK("#Main!A1","Open")) -> Open | AE2: =IFERROR(INDEX('Content Optimization Hub'!A:A,MATCH(H2,'Content Optimization Hub'!C:C,0)),"Not in Hub") -> Not in Hub
A3: Missing Title | B3: Critical | C3: 105 | D3: 0 | F3: Technical | G3: Manual Content | I3: Add unique descriptive title on affected template/page type. | J3: Template/page missing title tag. | K3: Copy Writer | L3: Copy Writer | M3: M | N3: 10 | O3: 5 | P3: Immediate (Current Sprint) | Q3: To Do | T3: High Risk | U3: Yes | V3: Open in Main Tab | X3: SEO | Y3: Content | Z3: Low | AA3: 10 | AB3: 0 | AC3: Resolve 'Missing Title' using content best practices and validate in the related detail tab. | AD3: =IFERROR(HYPERLINK("#Main!A"&MATCH(H3,Main!A:A,0),"Open"),HYPERLINK("#Main!A1","Open")) -> Open | AE3: =IFERROR(INDEX('Content Optimization Hub'!A:A,MATCH(H3,'Content Optimization Hub'!C:C,0)),"Not in Hub") -> Not in Hub
A4: Noindex Directive | B4: Critical | C4: 105 | D4: 0 | F4: Indexability | G4: Manual Content | I4: Remove unintended noindex directives on index-worthy URLs. | J4: Meta robots or X-Robots-Tag contains noindex. | K4: Dev | L4: Dev | M4: M | N4: 10 | O4: 5 | P4: Immediate (Current Sprint) | Q4: To Do | T4: High Risk | U4: Yes | V4: Open in Main Tab | X4: SEO | Y4: Technical | Z4: Low | AA4: 10 | AB4: 0 | AC4: Resolve 'Noindex Directive' using technical best practices and validate in the related detail tab. | AD4: =IFERROR(HYPERLINK("#Main!A"&MATCH(H4,Main!A:A,0),"Open"),HYPERLINK("#Main!A1","Open")) -> Open | AE4: =IFERROR(INDEX('Content Optimization Hub'!A:A,MATCH(H4,'Content Optimization Hub'!C:C,0)),"Not in Hub") -> Not in Hub
A5: Canonical Points Elsewhere | B5: Critical | C5: 105 | D5: 0 | F5: Indexability | G5: Global Template | I5: Align canonical to preferred final URL and ensure internal links use canonical target. | J5: Canonical targets a different URL variant. | K5: Dev | L5: Dev | M5: M | N5: 10 | O5: 5 | P5: Immediate (Current Sprint) | Q5: To Do | T5: High Risk | U5: Yes | V5: Open in Main Tab | X5: SEO | Y5: Technical | Z5: Low | AA5: 10 | AB5: 0 | AC5: Resolve 'Canonical Points Elsewhere' using technical best practices and validate in the related detail tab. | AD5: =IFERROR(HYPERLINK("#Main!A"&MATCH(H5,Main!A:A,0),"Open"),HYPERLINK("#Main!A1","Open")) -> Open | AE5: =IFERROR(INDEX('Content Optimization Hub'!A:A,MATCH(H5,'Content Optimization Hub'!C:C,0)),"Not in Hub") -> Not in Hub
A6: Robots.txt Disallow Root | B6: Critical | C6: 105 | D6: 0 | F6: Technical | G6: Global Template | I6: Apply fix based on issue type and re-run audit. | J6: Template/technical implementation quality issue. | K6: Server/Host | L6: Server/Host | M6: M | N6: 10 | O6: 5 | P6: Immediate (Current Sprint) | Q6: To Do | T6: High Risk | U6: Yes | V6: Open in Main Tab | X6: SEO | Y6: Content | Z6: Low | AA6: 10 | AB6: 0 | AC6: Resolve 'Robots.txt Disallow Root' using content best practices and validate in the related detail tab. | AD6: =IFERROR(HYPERLINK("#Main!A"&MATCH(H6,Main!A:A,0),"Open"),HYPERLINK("#Main!A1","Open")) -> Open | AE6: =IFERROR(INDEX('Content Optimization Hub'!A:A,MATCH(H6,'Content Optimization Hub'!C:C,0)),"Not in Hub") -> Not in Hub
A7: CWV LCP Above 4.0s | B7: Critical | C7: 105 | D7: 0 | F7: Technical | G7: Global Template | I7: Apply fix based on issue type and re-run audit. | J7: Template/technical implementation quality issue. | K7: Dev | L7: Dev | M7: M | N7: 10 | O7: 5 | P7: Immediate (Current Sprint) | Q7: To Do | T7: High Risk | U7: Yes | V7: Open in Main Tab | X7: SEO | Y7: Content | Z7: Low | AA7: 10 | AB7: 0 | AC7: Resolve 'CWV LCP Above 4.0s' using content best practices and validate in the related detail tab. | AD7: =IFERROR(HYPERLINK("#Main!A"&MATCH(H7,Main!A:A,0),"Open"),HYPERLINK("#Main!A1","Open")) -> Open | AE7: =IFERROR(INDEX('Content Optimization Hub'!A:A,MATCH(H7,'Content Optimization Hub'!C:C,0)),"Not in Hub") -> Not in Hub
A8: Broken Internal Links | B8: Critical | C8: 105 | D8: 10 | E8: https://africanmarketingconfederation.org/african-marketing-confederation-tourism-chapter https://africanmarketingconfederation.org/ https://africanmarketingconfederation.org/about-us https://africanmarketingconfederation.org/amc-awards-2024 https://africanmarketingconfederation.org/amc-conference-2022-prospectus https://africanmarketingconfederation.org/amc-conference-2022 https://africanmarketingconfederation.org/amc-conference-2022-thank-you https://africanmarketingconfederation.org/amc-conference-2023 https://africanmarketingconfederation.org/amc-conference-2023/amc-awards https://africanmarketingconfederation.org/amc-conference-2023/amc-awards-book-now | F8: Links | G8: Manual Content | H8: https://africanmarketingconfederation.org/african-marketing-confederation-tourism-chapter | I8: Update internal links to valid URLs and remove dead references. | J8: Internal links resolve to missing or error pages. | K8: Dev | L8: Dev | M8: M | N8: 10 | O8: 5 | P8: Immediate (Current Sprint) | Q8: To Do | T8: High Risk | U8: Yes | V8: Open in Main Tab | X8: SEO | Y8: Content | Z8: Low | AA8: 10 | AB8: 0 | AC8: Resolve 'Broken Internal Links' using content best practices and validate in the related detail tab. | AD8: =IFERROR(HYPERLINK("#Main!A"&MATCH(H8,Main!A:A,0),"Open"),HYPERLINK("#Main!A1","Open")) -> Open | AE8: =IFERROR(INDEX('Content Optimization Hub'!A:A,MATCH(H8,'Content Optimization Hub'!C:C,0)),"Not in Hub") -> Not in Hub
A9: Redirect Chains | B9: Warning | C9: 67 | D9: 0 | F9: Technical | G9: Global Template | I9: Apply fix based on issue type and re-run audit. | J9: Template/technical implementation quality issue. | K9: Dev | L9: Dev | M9: S | N9: 4 | O9: 2 | P9: Next Sprint | Q9: To Do | T9: Medium Risk | U9: Yes | V9: Open in Main Tab | X9: SEO | Y9: Technical | Z9: Low | AA9: 4 | AB9: 0 | AC9: Resolve 'Redirect Chains' using technical best practices and validate in the related detail tab. | AD9: =IFERROR(HYPERLINK("#Main!A"&MATCH(H9,Main!A:A,0),"Open"),HYPERLINK("#Main!A1","Open")) -> Open | AE9: =IFERROR(INDEX('Content Optimization Hub'!A:A,MATCH(H9,'Content Optimization Hub'!C:C,0)),"Not in Hub") -> Not in Hub
A10: CWV LCP Needs Improvement (2.5-4.0s) | B10: Warning | C10: 67 | D10: 0 | F10: Technical | G10: Global Template | I10: Apply fix based on issue type and re-run audit. | J10: Template/technical implementation quality issue. | K10: Copy Writer | L10: Copy Writer | M10: S | N10: 4 | O10: 2 | P10: Next Sprint | Q10: To Do | T10: Medium Risk | U10: Yes | V10: Open in Main Tab | X10: SEO | Y10: Content | Z10: Low | AA10: 4 | AB10: 0 | AC10: Resolve 'CWV LCP Needs Improvement (2.5-4.0s)' using content best practices and validate in the related detail tab. | AD10: =IFERROR(HYPERLINK("#Main!A"&MATCH(H10,Main!A:A,0),"Open"),HYPERLINK("#Main!A1","Open")) -> Open | AE10: =IFERROR(INDEX('Content Optimization Hub'!A:A,MATCH(H10,'Content Optimization Hub'!C:C,0)),"Not in Hub") -> Not in Hub
A11: Missing FAQ/QA Schema | B11: Warning | C11: 67 | D11: 0 | F11: AEO | G11: Global Template | I11: Add valid FAQPage or QAPage JSON-LD where appropriate and ensure on-page parity. | J11: No FAQPage/QAPage schema found for likely Q&A style content. | K11: Dev | L11: Dev | M11: S | N11: 4 | O11: 2 | P11: Next Sprint | Q11: To Do | T11: Medium Risk | U11: Yes | V11: Open in Main Tab | X11: AEO | Y11: Content | Z11: Low | AA11: 4 | AB11: 0 | AC11: Resolve 'Missing FAQ/QA Schema' using content best practices and validate in the related detail tab. | AD11: =IFERROR(HYPERLINK("#Main!A"&MATCH(H11,Main!A:A,0),"Open"),HYPERLINK("#Main!A1","Open")) -> Open | AE11: =IFERROR(INDEX('Content Optimization Hub'!A:A,MATCH(H11,'Content Optimization Hub'!C:C,0)),"Not in Hub") -> Not in Hub
A12: Deep URL (>3 clicks) | B12: Warning | C12: 67 | D12: 0 | F12: Technical | G12: Manual Content | I12: Apply fix based on issue type and re-run audit. | J12: Template/technical implementation quality issue. | K12: Copy Writer | L12: Copy Writer | M12: S | N12: 4 | O12: 2 | P12: Next Sprint | Q12: To Do | T12: Medium Risk | U12: Yes | V12: Open in Main Tab | X12: SEO | Y12: Content | Z12: Low | AA12: 4 | AB12: 0 | AC12: Resolve 'Deep URL (>3 clicks)' using content best practices and validate in the related detail tab. | AD12: =IFERROR(HYPERLINK("#Main!A"&MATCH(H12,Main!A:A,0),"Open"),HYPERLINK("#Main!A1","Open")) -> Open | AE12: =IFERROR(INDEX('Content Optimization Hub'!A:A,MATCH(H12,'Content Optimization Hub'!C:C,0)),"Not in Hub") -> Not in Hub
A13: Mixed Content | B13: Warning | C13: 67 | D13: 0 | F13: Technical | G13: Manual Content | I13: Serve all assets over HTTPS and update hardcoded URLs. | J13: HTTPS page references insecure HTTP assets. | K13: Dev | L13: Dev | M13: S | N13: 4 | O13: 2 | P13: Next Sprint | Q13: To Do | T13: Medium Risk | U13: Yes | V13: Open in Main Tab | X13: SEO | Y13: Content | Z13: Low | AA13: 4 | AB13: 0 | AC13: Resolve 'Mixed Content' using content best practices and validate in the related detail tab. | AD13: =IFERROR(HYPERLINK("#Main!A"&MATCH(H13,Main!A:A,0),"Open"),HYPERLINK("#Main!A1","Open")) -> Open | AE13: =IFERROR(INDEX('Content Optimization Hub'!A:A,MATCH(H13,'Content Optimization Hub'!C:C,0)),"Not in Hub") -> Not in Hub
A14: Canonical Missing | B14: Warning | C14: 67 | D14: 0 | F14: Indexability | G14: Global Template | I14: Apply fix based on issue type and re-run audit. | J14: Template/technical implementation quality issue. | K14: Dev | L14: Dev | M14: S | N14: 4 | O14: 2 | P14: Next Sprint | Q14: To Do | T14: Medium Risk | U14: Yes | V14: Open in Main Tab | X14: SEO | Y14: Technical | Z14: Low | AA14: 4 | AB14: 0 | AC14: Resolve 'Canonical Missing' using technical best practices and validate in the related detail tab. | AD14: =IFERROR(HYPERLINK("#Main!A"&MATCH(H14,Main!A:A,0),"Open"),HYPERLINK("#Main!A1","Open")) -> Open | AE14: =IFERROR(INDEX('Content Optimization Hub'!A:A,MATCH(H14,'Content Optimization Hub'!C:C,0)),"Not in Hub") -> Not in Hub
A15: Hreflang Without Reciprocity | B15: Warning | C15: 67 | D15: 0 | F15: Technical | G15: Manual Content | I15: Apply fix based on issue type and re-run audit. | J15: Template/technical implementation quality issue. | K15: Copy Writer | L15: Copy Writer | M15: S | N15: 4 | O15: 2 | P15: Next Sprint | Q15: To Do | T15: Medium Risk | U15: Yes | V15: Open in Main Tab | X15: SEO | Y15: Content | Z15: Low | AA15: 4 | AB15: 0 | AC15: Resolve 'Hreflang Without Reciprocity' using content best practices and validate in the related detail tab. | AD15: =IFERROR(HYPERLINK("#Main!A"&MATCH(H15,Main!A:A,0),"Open"),HYPERLINK("#Main!A1","Open")) -> Open | AE15: =IFERROR(INDEX('Content Optimization Hub'!A:A,MATCH(H15,'Content Optimization Hub'!C:C,0)),"Not in Hub") -> Not in Hub
A16: Low Image Alt Coverage | B16: Warning | C16: 67 | D16: 10 | E16: https://africanmarketingconfederation.org/african-marketing-confederation-tourism-chapter https://africanmarketingconfederation.org/ https://africanmarketingconfederation.org/about-us https://africanmarketingconfederation.org/amc-awards-2024 https://africanmarketingconfederation.org/amc-conference-2022-prospectus https://africanmarketingconfederation.org/amc-conference-2022 https://africanmarketingconfederation.org/amc-conference-2022-thank-you https://africanmarketingconfederation.org/amc-conference-2023 https://africanmarketingconfederation.org/amc-conference-2023/amc-awards https://africanmarketingconfederation.org/amc-conference-2023/amc-awards-book-now | F16: Technical | G16: Manual Content | H16: https://africanmarketingconfederation.org/african-marketing-confederation-tourism-chapter | I16: Apply fix based on issue type and re-run audit. | J16: Template/technical implementation quality issue. | K16: Copy Writer | L16: Copy Writer | M16: S | N16: 4 | O16: 2 | P16: Next Sprint | Q16: To Do | T16: Medium Risk | U16: Yes | V16: Open in Main Tab | X16: SEO | Y16: Content | Z16: Low | AA16: 4 | AB16: 0 | AC16: Resolve 'Low Image Alt Coverage' using content best practices and validate in the related detail tab. | AD16: =IFERROR(HYPERLINK("#Main!A"&MATCH(H16,Main!A:A,0),"Open"),HYPERLINK("#Main!A1","Open")) -> Open | AE16: =IFERROR(INDEX('Content Optimization Hub'!A:A,MATCH(H16,'Content Optimization Hub'!C:C,0)),"Not in Hub") -> Not in Hub
A17: Low AEO Readiness Score | B17: Warning | C17: 67 | D17: 10 | E17: https://africanmarketingconfederation.org/african-marketing-confederation-tourism-chapter https://africanmarketingconfederation.org/ https://africanmarketingconfederation.org/about-us https://africanmarketingconfederation.org/amc-awards-2024 https://africanmarketingconfederation.org/amc-conference-2022-prospectus https://africanmarketingconfederation.org/amc-conference-2022 https://africanmarketingconfederation.org/amc-conference-2022-thank-you https://africanmarketingconfederation.org/amc-conference-2023 https://africanmarketingconfederation.org/amc-conference-2023/amc-awards https://africanmarketingconfederation.org/amc-conference-2023/amc-awards-book-now | F17: AEO | G17: Manual Content | H17: https://africanmarketingconfederation.org/african-marketing-confederation-tourism-chapter | I17: Add short direct answer blocks, question-led headings, and answer-ready formatting. | J17: Page lacks concise answer-oriented signals and structured answer patterns. | K17: Copy Writer | L17: Copy Writer | M17: S | N17: 4 | O17: 2 | P17: Next Sprint | Q17: To Do | T17: Medium Risk | U17: Yes | V17: Open in Main Tab | X17: AEO | Y17: Content | Z17: Low | AA17: 4 | AB17: 0 | AC17: Resolve 'Low AEO Readiness Score' using content best practices and validate in the related detail tab. | AD17: =IFERROR(HYPERLINK("#Main!A"&MATCH(H17,Main!A:A,0),"Open"),HYPERLINK("#Main!A1","Open")) -> Open | AE17: =IFERROR(INDEX('Content Optimization Hub'!A:A,MATCH(H17,'Content Optimization Hub'!C:C,0)),"Not in Hub") -> Not in Hub
A18: Multiple H1 | B18: Warning | C18: 67 | D18: 3 | E18: https://africanmarketingconfederation.org/african-marketing-confederation-tourism-chapter https://africanmarketingconfederation.org/ https://africanmarketingconfederation.org/amc-awards-2024 | F18: Technical | G18: Manual Content | H18: https://africanmarketingconfederation.org/african-marketing-confederation-tourism-chapter | I18: Apply fix based on issue type and re-run audit. | J18: Template/technical implementation quality issue. | K18: Copy Writer | L18: Copy Writer | M18: S | N18: 4 | O18: 2 | P18: Next Sprint | Q18: To Do | T18: Medium Risk | U18: Yes | V18: Open in Main Tab | X18: SEO | Y18: Content | Z18: Low | AA18: 4 | AB18: 0 | AC18: Resolve 'Multiple H1' using content best practices and validate in the related detail tab. | AD18: =IFERROR(HYPERLINK("#Main!A"&MATCH(H18,Main!A:A,0),"Open"),HYPERLINK("#Main!A1","Open")) -> Open | AE18: =IFERROR(INDEX('Content Optimization Hub'!A:A,MATCH(H18,'Content Optimization Hub'!C:C,0)),"Not in Hub") -> Not in Hub
A19: Missing H1 | B19: Warning | C19: 67 | D19: 4 | E19: https://africanmarketingconfederation.org/amc-conference-2022-prospectus https://africanmarketingconfederation.org/amc-conference-2022 https://africanmarketingconfederation.org/amc-conference-2022-thank-you https://africanmarketingconfederation.org/amc-conference-2023/amc-awards-book-now | F19: Technical | G19: Manual Content | H19: https://africanmarketingconfederation.org/amc-conference-2022-prospectus | I19: Apply fix based on issue type and re-run audit. | J19: Template/technical implementation quality issue. | K19: Copy Writer | L19: Copy Writer | M19: S | N19: 4 | O19: 2 | P19: Next Sprint | Q19: To Do | T19: Medium Risk | U19: Yes | V19: Open in Main Tab | X19: SEO | Y19: Content | Z19: Low | AA19: 4 | AB19: 0 | AC19: Resolve 'Missing H1' using content best practices and validate in the related detail tab. | AD19: =IFERROR(HYPERLINK("#Main!A"&MATCH(H19,Main!A:A,0),"Open"),HYPERLINK("#Main!A1","Open")) -> Open | AE19: =IFERROR(INDEX('Content Optimization Hub'!A:A,MATCH(H19,'Content Optimization Hub'!C:C,0)),"Not in Hub") -> Not in Hub
A20: Missing Meta Description | B20: Warning | C20: 67 | D20: 1 | E20: https://africanmarketingconfederation.org/amc-conference-2023/amc-awards-book-now | F20: Technical | G20: Manual Content | H20: https://africanmarketingconfederation.org/amc-conference-2023/amc-awards-book-now | I20: Add concise unique description aligned with user intent. | J20: Meta description missing or empty. | K20: Copy Writer | L20: Copy Writer | M20: S | N20: 4 | O20: 2 | P20: Next Sprint | Q20: To Do | T20: Medium Risk | U20: Yes | V20: Open in Main Tab | X20: SEO | Y20: Content | Z20: Low | AA20: 4 | AB20: 0 | AC20: Resolve 'Missing Meta Description' using content best practices and validate in the related detail tab. | AD20: =IFERROR(HYPERLINK("#Main!A"&MATCH(H20,Main!A:A,0),"Open"),HYPERLINK("#Main!A1","Open")) -> Open | AE20: =IFERROR(INDEX('Content Optimization Hub'!A:A,MATCH(H20,'Content Optimization Hub'!C:C,0)),"Not in Hub") -> Not in Hub
A21: Uses URL Parameters | B21: Observation | C21: 37 | D21: 0 | F21: Technical | G21: Manual Content | I21: Apply fix based on issue type and re-run audit. | J21: Template/technical implementation quality issue. | K21: Dev | L21: Dev | M21: S | N21: 4 | O21: 2 | P21: Backlog | Q21: In Review | T21: Monitor | U21: No | V21: Open in Main Tab | X21: SEO | Y21: Content | Z21: Low | AA21: 4 | AB21: 0 | AC21: Resolve 'Uses URL Parameters' using content best practices and validate in the related detail tab. | AD21: =IFERROR(HYPERLINK("#Main!A"&MATCH(H21,Main!A:A,0),"Open"),HYPERLINK("#Main!A1","Open")) -> Open | AE21: =IFERROR(INDEX('Content Optimization Hub'!A:A,MATCH(H21,'Content Optimization Hub'!C:C,0)),"Not in Hub") -> Not in Hub
A22: Image Filename Quality Issues | B22: Observation | C22: 37 | D22: 0 | F22: Technical | G22: Manual Content | I22: Apply fix based on issue type and re-run audit. | J22: Template/technical implementation quality issue. | K22: Copy Writer | L22: Copy Writer | M22: S | N22: 4 | O22: 2 | P22: Backlog | Q22: In Review | T22: Monitor | U22: No | V22: Open in Main Tab | X22: SEO | Y22: Content | Z22: Low | AA22: 4 | AB22: 0 | AC22: Resolve 'Image Filename Quality Issues' using content best practices and validate in the related detail tab. | AD22: =IFERROR(HYPERLINK("#Main!A"&MATCH(H22,Main!A:A,0),"Open"),HYPERLINK("#Main!A1","Open")) -> Open | AE22: =IFERROR(INDEX('Content Optimization Hub'!A:A,MATCH(H22,'Content Optimization Hub'!C:C,0)),"Not in Hub") -> Not in Hub
A23: No Compression Header | B23: Observation | C23: 37 | D23: 0 | F23: Technical | G23: Global Template | I23: Apply fix based on issue type and re-run audit. | J23: Template/technical implementation quality issue. | K23: Server/Host | L23: Server/Host | M23: S | N23: 4 | O23: 2 | P23: Backlog | Q23: In Review | T23: Monitor | U23: No | V23: Open in Main Tab | X23: SEO | Y23: Content | Z23: Low | AA23: 4 | AB23: 0 | AC23: Resolve 'No Compression Header' using content best practices and validate in the related detail tab. | AD23: =IFERROR(HYPERLINK("#Main!A"&MATCH(H23,Main!A:A,0),"Open"),HYPERLINK("#Main!A1","Open")) -> Open | AE23: =IFERROR(INDEX('Content Optimization Hub'!A:A,MATCH(H23,'Content Optimization Hub'!C:C,0)),"Not in Hub") -> Not in Hub
A24: No Cache-Control Header | B24: Observation | C24: 37 | D24: 0 | F24: Technical | G24: Global Template | I24: Apply fix based on issue type and re-run audit. | J24: Template/technical implementation quality issue. | K24: Server/Host | L24: Server/Host | M24: S | N24: 4 | O24: 2 | P24: Backlog | Q24: In Review | T24: Monitor | U24: No | V24: Open in Main Tab | X24: SEO | Y24: Content | Z24: Low | AA24: 4 | AB24: 0 | AC24: Resolve 'No Cache-Control Header' using content best practices and validate in the related detail tab. | AD24: =IFERROR(HYPERLINK("#Main!A"&MATCH(H24,Main!A:A,0),"Open"),HYPERLINK("#Main!A1","Open")) -> Open | AE24: =IFERROR(INDEX('Content Optimization Hub'!A:A,MATCH(H24,'Content Optimization Hub'!C:C,0)),"Not in Hub") -> Not in Hub
A25: INP Above 100ms | B25: Observation | C25: 37 | D25: 0 | F25: Technical | G25: Manual Content | I25: Apply fix based on issue type and re-run audit. | J25: Template/technical implementation quality issue. | K25: Copy Writer | L25: Copy Writer | M25: S | N25: 4 | O25: 2 | P25: Backlog | Q25: In Review | T25: Monitor | U25: No | V25: Open in Main Tab | X25: SEO | Y25: Content | Z25: Low | AA25: 4 | AB25: 0 | AC25: Resolve 'INP Above 100ms' using content best practices and validate in the related detail tab. | AD25: =IFERROR(HYPERLINK("#Main!A"&MATCH(H25,Main!A:A,0),"Open"),HYPERLINK("#Main!A1","Open")) -> Open | AE25: =IFERROR(INDEX('Content Optimization Hub'!A:A,MATCH(H25,'Content Optimization Hub'!C:C,0)),"Not in Hub") -> Not in Hub
A26: CLS Above 0.1 | B26: Observation | C26: 37 | D26: 0 | F26: Technical | G26: Manual Content | I26: Apply fix based on issue type and re-run audit. | J26: Template/technical implementation quality issue. | K26: Copy Writer | L26: Copy Writer | M26: S | N26: 4 | O26: 2 | P26: Backlog | Q26: In Review | T26: Monitor | U26: No | V26: Open in Main Tab | X26: SEO | Y26: Content | Z26: Low | AA26: 4 | AB26: 0 | AC26: Resolve 'CLS Above 0.1' using content best practices and validate in the related detail tab. | AD26: =IFERROR(HYPERLINK("#Main!A"&MATCH(H26,Main!A:A,0),"Open"),HYPERLINK("#Main!A1","Open")) -> Open | AE26: =IFERROR(INDEX('Content Optimization Hub'!A:A,MATCH(H26,'Content Optimization Hub'!C:C,0)),"Not in Hub") -> Not in Hub
A27: Low Regional Authority | B27: Observation | C27: 37 | D27: 0 | F27: Technical | G27: Manual Content | I27: Apply fix based on issue type and re-run audit. | J27: Template/technical implementation quality issue. | K27: Copy Writer | L27: Copy Writer | M27: S | N27: 4 | O27: 2 | P27: Backlog | Q27: In Review | T27: Monitor | U27: No | V27: Open in Main Tab | X27: SEO | Y27: Content | Z27: Low | AA27: 4 | AB27: 0 | AC27: Resolve 'Low Regional Authority' using content best practices and validate in the related detail tab. | AD27: =IFERROR(HYPERLINK("#Main!A"&MATCH(H27,Main!A:A,0),"Open"),HYPERLINK("#Main!A1","Open")) -> Open | AE27: =IFERROR(INDEX('Content Optimization Hub'!A:A,MATCH(H27,'Content Optimization Hub'!C:C,0)),"Not in Hub") -> Not in Hub
A28: llms.txt Missing | B28: Observation | C28: 37 | D28: 0 | F28: Technical | G28: Manual Content | I28: Apply fix based on issue type and re-run audit. | J28: Template/technical implementation quality issue. | K28: Copy Writer | L28: Copy Writer | M28: S | N28: 4 | O28: 2 | P28: Backlog | Q28: In Review | T28: Monitor | U28: No | V28: Open in Main Tab | X28: SEO | Y28: Content | Z28: Low | AA28: 4 | AB28: 0 | AC28: Resolve 'llms.txt Missing' using content best practices and validate in the related detail tab. | AD28: =IFERROR(HYPERLINK("#Main!A"&MATCH(H28,Main!A:A,0),"Open"),HYPERLINK("#Main!A1","Open")) -> Open | AE28: =IFERROR(INDEX('Content Optimization Hub'!A:A,MATCH(H28,'Content Optimization Hub'!C:C,0)),"Not in Hub") -> Not in Hub
A29: Thin Content | B29: Observation | C29: 37 | D29: 5 | E29: https://africanmarketingconfederation.org/ https://africanmarketingconfederation.org/about-us https://africanmarketingconfederation.org/amc-conference-2022-prospectus https://africanmarketingconfederation.org/amc-conference-2022 https://africanmarketingconfederation.org/amc-conference-2023/amc-awards-book-now | F29: Technical | G29: Manual Content | H29: https://africanmarketingconfederation.org/ | I29: Expand page with helpful, unique, intent-matching content. | J29: Insufficient body content for indexing confidence. | K29: Copy Writer | L29: Copy Writer | M29: S | N29: 4 | O29: 2 | P29: Backlog | Q29: In Review | T29: Monitor | U29: No | V29: Open in Main Tab | X29: SEO | Y29: Content | Z29: Low | AA29: 4 | AB29: 0 | AC29: Resolve 'Thin Content' using content best practices and validate in the related detail tab. | AD29: =IFERROR(HYPERLINK("#Main!A"&MATCH(H29,Main!A:A,0),"Open"),HYPERLINK("#Main!A1","Open")) -> Open | AE29: =IFERROR(INDEX('Content Optimization Hub'!A:A,MATCH(H29,'Content Optimization Hub'!C:C,0)),"Not in Hub") -> Not in Hub
A30: Generic Anchor Text Present | B30: Observation | C30: 37 | D30: 1 | E30: https://africanmarketingconfederation.org/ | F30: Links | G30: Manual Content | H30: https://africanmarketingconfederation.org/ | I30: Apply fix based on issue type and re-run audit. | J30: Template/technical implementation quality issue. | K30: Copy Writer | L30: Copy Writer | M30: S | N30: 4 | O30: 2 | P30: Backlog | Q30: In Review | T30: Monitor | U30: No | V30: Open in Main Tab | X30: SEO | Y30: Content | Z30: Low | AA30: 4 | AB30: 0 | AC30: Resolve 'Generic Anchor Text Present' using content best practices and validate in the related detail tab. | AD30: =IFERROR(HYPERLINK("#Main!A"&MATCH(H30,Main!A:A,0),"Open"),HYPERLINK("#Main!A1","Open")) -> Open | AE30: =IFERROR(INDEX('Content Optimization Hub'!A:A,MATCH(H30,'Content Optimization Hub'!C:C,0)),"Not in Hub") -> Not in Hub
A31: No ETag Header | B31: Observation | C31: 37 | D31: 10 | E31: https://africanmarketingconfederation.org/african-marketing-confederation-tourism-chapter https://africanmarketingconfederation.org/ https://africanmarketingconfederation.org/about-us https://africanmarketingconfederation.org/amc-awards-2024 https://africanmarketingconfederation.org/amc-conference-2022-prospectus https://africanmarketingconfederation.org/amc-conference-2022 https://africanmarketingconfederation.org/amc-conference-2022-thank-you https://africanmarketingconfederation.org/amc-conference-2023 https://africanmarketingconfederation.org/amc-conference-2023/amc-awards https://africanmarketingconfederation.org/amc-conference-2023/amc-awards-book-now | F31: Technical | G31: Global Template | H31: https://africanmarketingconfederation.org/african-marketing-confederation-tourism-chapter | I31: Apply fix based on issue type and re-run audit. | J31: Template/technical implementation quality issue. | K31: Server/Host | L31: Server/Host | M31: S | N31: 4 | O31: 2 | P31: Backlog | Q31: In Review | T31: Monitor | U31: No | V31: Open in Main Tab | X31: SEO | Y31: Content | Z31: Low | AA31: 4 | AB31: 0 | AC31: Resolve 'No ETag Header' using content best practices and validate in the related detail tab. | AD31: =IFERROR(HYPERLINK("#Main!A"&MATCH(H31,Main!A:A,0),"Open"),HYPERLINK("#Main!A1","Open")) -> Open | AE31: =IFERROR(INDEX('Content Optimization Hub'!A:A,MATCH(H31,'Content Optimization Hub'!C:C,0)),"Not in Hub") -> Not in Hub
A32: No Question Headings | B32: Observation | C32: 37 | D32: 10 | E32: https://africanmarketingconfederation.org/african-marketing-confederation-tourism-chapter https://africanmarketingconfederation.org/ https://africanmarketingconfederation.org/about-us https://africanmarketingconfederation.org/amc-awards-2024 https://africanmarketingconfederation.org/amc-conference-2022-prospectus https://africanmarketingconfederation.org/amc-conference-2022 https://africanmarketingconfederation.org/amc-conference-2022-thank-you https://africanmarketingconfederation.org/amc-conference-2023 https://africanmarketingconfederation.org/amc-conference-2023/amc-awards https://africanmarketingconfederation.org/amc-conference-2023/amc-awards-book-now | F32: AEO | G32: Manual Content | H32: https://africanmarketingconfederation.org/african-marketing-confederation-tourism-chapter | I32: Add clear question-style headings (especially H2/H3) for key intents. | J32: Headings are not phrased as user questions. | K32: Copy Writer | L32: Copy Writer | M32: S | N32: 4 | O32: 2 | P32: Backlog | Q32: In Review | T32: Monitor | U32: No | V32: Open in Main Tab | X32: AEO | Y32: Content | Z32: Low | AA32: 4 | AB32: 0 | AC32: Resolve 'No Question Headings' using content best practices and validate in the related detail tab. | AD32: =IFERROR(HYPERLINK("#Main!A"&MATCH(H32,Main!A:A,0),"Open"),HYPERLINK("#Main!A1","Open")) -> Open | AE32: =IFERROR(INDEX('Content Optimization Hub'!A:A,MATCH(H32,'Content Optimization Hub'!C:C,0)),"Not in Hub") -> Not in Hub
A33: No Answer-Friendly Structure | B33: Observation | C33: 37 | D33: 10 | E33: https://africanmarketingconfederation.org/african-marketing-confederation-tourism-chapter https://africanmarketingconfederation.org/ https://africanmarketingconfederation.org/about-us https://africanmarketingconfederation.org/amc-awards-2024 https://africanmarketingconfederation.org/amc-conference-2022-prospectus https://africanmarketingconfederation.org/amc-conference-2022 https://africanmarketingconfederation.org/amc-conference-2022-thank-you https://africanmarketingconfederation.org/amc-conference-2023 https://africanmarketingconfederation.org/amc-conference-2023/amc-awards https://africanmarketingconfederation.org/amc-conference-2023/amc-awards-book-now | F33: AEO | G33: Manual Content | H33: https://africanmarketingconfederation.org/african-marketing-confederation-tourism-chapter | I33: Introduce structured bullets, ordered steps, or tables for key answers. | J33: Page lacks lists/tables that help concise answer extraction. | K33: Copy Writer | L33: Copy Writer | M33: S | N33: 4 | O33: 2 | P33: Backlog | Q33: In Review | T33: Monitor | U33: No | V33: Open in Main Tab | X33: AEO | Y33: Content | Z33: Low | AA33: 4 | AB33: 0 | AC33: Resolve 'No Answer-Friendly Structure' using content best practices and validate in the related detail tab. | AD33: =IFERROR(HYPERLINK("#Main!A"&MATCH(H33,Main!A:A,0),"Open"),HYPERLINK("#Main!A1","Open")) -> Open | AE33: =IFERROR(INDEX('Content Optimization Hub'!A:A,MATCH(H33,'Content Optimization Hub'!C:C,0)),"Not in Hub") -> Not in Hub
A34: No 40-60 Word Answer Paragraphs | B34: Observation | C34: 37 | D34: 10 | E34: https://africanmarketingconfederation.org/african-marketing-confederation-tourism-chapter https://africanmarketingconfederation.org/ https://africanmarketingconfederation.org/about-us https://africanmarketingconfederation.org/amc-awards-2024 https://africanmarketingconfederation.org/amc-conference-2022-prospectus https://africanmarketingconfederation.org/amc-conference-2022 https://africanmarketingconfederation.org/amc-conference-2022-thank-you https://africanmarketingconfederation.org/amc-conference-2023 https://africanmarketingconfederation.org/amc-conference-2023/amc-awards https://africanmarketingconfederation.org/amc-conference-2023/amc-awards-book-now | F34: AEO | G34: Manual Content | H34: https://africanmarketingconfederation.org/african-marketing-confederation-tourism-chapter | I34: Add a direct 30-60 word answer summary near question headings. | J34: No concise answer-length paragraph detected. | K34: Copy Writer | L34: Copy Writer | M34: S | N34: 4 | O34: 2 | P34: Backlog | Q34: In Review | T34: Monitor | U34: No | V34: Open in Main Tab | X34: AEO | Y34: Content | Z34: Low | AA34: 4 | AB34: 0 | AC34: Resolve 'No 40-60 Word Answer Paragraphs' using content best practices and validate in the related detail tab. | AD34: =IFERROR(HYPERLINK("#Main!A"&MATCH(H34,Main!A:A,0),"Open"),HYPERLINK("#Main!A1","Open")) -> Open | AE34: =IFERROR(INDEX('Content Optimization Hub'!A:A,MATCH(H34,'Content Optimization Hub'!C:C,0)),"Not in Hub") -> Not in Hub
A35: AI Crawlers Not Explicitly Allowed | B35: Observation | C35: 37 | D35: 10 | E35: https://africanmarketingconfederation.org/african-marketing-confederation-tourism-chapter https://africanmarketingconfederation.org/ https://africanmarketingconfederation.org/about-us https://africanmarketingconfederation.org/amc-awards-2024 https://africanmarketingconfederation.org/amc-conference-2022-prospectus https://africanmarketingconfederation.org/amc-conference-2022 https://africanmarketingconfederation.org/amc-conference-2022-thank-you https://africanmarketingconfederation.org/amc-conference-2023 https://africanmarketingconfederation.org/amc-conference-2023/amc-awards https://africanmarketingconfederation.org/amc-conference-2023/amc-awards-book-now | F35: Technical | G35: Manual Content | H35: https://africanmarketingconfederation.org/african-marketing-confederation-tourism-chapter | I35: Apply fix based on issue type and re-run audit. | J35: Template/technical implementation quality issue. | K35: Copy Writer | L35: Copy Writer | M35: S | N35: 4 | O35: 2 | P35: Backlog | Q35: In Review | T35: Monitor | U35: No | V35: Open in Main Tab | X35: SEO | Y35: Content | Z35: Low | AA35: 4 | AB35: 0 | AC35: Resolve 'AI Crawlers Not Explicitly Allowed' using content best practices and validate in the related detail tab. | AD35: =IFERROR(HYPERLINK("#Main!A"&MATCH(H35,Main!A:A,0),"Open"),HYPERLINK("#Main!A1","Open")) -> Open | AE35: =IFERROR(INDEX('Content Optimization Hub'!A:A,MATCH(H35,'Content Optimization Hub'!C:C,0)),"Not in Hub") -> Not in Hub

Sheet Main
A1: Health Icon | B1: URL | C1: Status Code | D1: Indexability | E1: Load Time (s) | F1: Title | G1: Meta Description | H1: Word Count (Body) | I1: SEO Health Score | J1: Severity Badge | K1: Action Needed | L1: Extraction State | M1: Extraction Source | N1: Title Length | O1: Meta Desc Length | P1: OG-Image | Q1: Has Valid JSON-LD | R1: H1 Content | S1: H1 Length | T1: H2 Content | U1: H2 Length | V1: H3 Content | W1: H3 Length | X1: H4 Content | Y1: H4 Length | Z1: H5 Content | AA1: H5 Length | AB1: H6 Content | AC1: H6 Length | AD1: CWV LCP (s) | AE1: CWV CLS | AF1: Field vs Lab | AG1: Regional Authority Score | AH1: Desktop PSI Score | AI1: Mobile PSI Score | AJ1: Mobile LCP (s) | AK1: Mobile CLS | AL1: Mobile TTFB (s) | AM1: GSC Clicks | AN1: GSC Impressions | AO1: GSC CTR | AP1: GSC Avg Position | AQ1: Click Depth | AR1: Orphan Pages | AS1: Internal PageRank | AT1: Found via Sitemap | AU1: Found via Crawl | AV1: Discovery Source | AW1: Technical Health | AX1: Copy Score | AY1: SEO Score | AZ1: Technical View | BA1: BACK TO DASHBOARD
A2: FAIL 🔴 | B2: https://africanmarketingconfederation.org/ | C2: 200 | D2: Indexable | E2: 0.053 | F2: African Marketing Confederation - Uniting Marketers for Excellence | G2: The African Marketing Confederation is the ground-breaking Pan-African body driving the development of top marketing standards across Africa and beyond. | H2: 35 | I2: 24 | J2: Critical | K2: Yes | L2: partial | M2: rendered_browser | N2: 66 | O2: 152 | P2: https://africanmarketingconfederation.org/wp-content/uploads/2026/03/og-image.png | Q2: FALSE | S2: 0 | U2: 0 | W2: 0 | Y2: 0 | AA2: 0 | AC2: 0 | AD2: 0 | AF2: Lab | AG2: 100 | AH2: 0 | AI2: 0 | AJ2: 0 | AK2: 0 | AL2: 0 | AM2: 0 | AN2: 0 | AO2: 0 | AP2: 0 | AQ2: 0 | AR2: FALSE | AS2: 0.287449 | AT2: TRUE | AU2: TRUE | AV2: Both | AW2: 24 | AX2: 75 | AY2: 36.75 | AZ2: =IFERROR(HYPERLINK("#Technical!A"&MATCH(B2,Technical!A:A,0),"Open Technical"),HYPERLINK("#Technical!A1","Open Technical")) -> Open Technical
A3: FAIL 🔴 | B3: https://africanmarketingconfederation.org/about-us | C3: 200 | D3: Indexable | E3: 0.073 | F3: African Marketing Confederation – The Leading Marketing Professional Body – African Marketing Confederation | G3: ABOUT The African Marketing Confederation The African Marketing Confederation is the ground-breaking Pan African body of marketing professionals spearheading the ongoing development of the highest possible standards of marketing across Africa. Founded in 2011, the AMC is a collaboration between the African national marketing bodies and associations to exchange expertise and information, and to promote | H3: 235 | I3: 37 | J3: Critical | K3: Yes | L3: partial | M3: rendered_browser | N3: 107 | O3: 405 | P3: https://africanmarketingconfederation.org/wp-content/uploads/2026/03/og-image.png | Q3: FALSE | S3: 0 | U3: 0 | W3: 0 | Y3: 0 | AA3: 0 | AC3: 0 | AD3: 0 | AF3: Lab | AG3: 70 | AH3: 0 | AI3: 0 | AJ3: 0 | AK3: 0 | AL3: 0 | AM3: 0 | AN3: 0 | AO3: 0 | AP3: 0 | AQ3: 1 | AR3: FALSE | AS3: 0.271899 | AT3: TRUE | AU3: TRUE | AV3: Both | AW3: 37 | AX3: 75 | AY3: 46.5 | AZ3: =IFERROR(HYPERLINK("#Technical!A"&MATCH(B3,Technical!A:A,0),"Open Technical"),HYPERLINK("#Technical!A1","Open Technical")) -> Open Technical
A4: FAIL 🔴 | B4: https://africanmarketingconfederation.org/african-marketing-confederation-tourism-chapter | C4: 200 | D4: Indexable | E4: 0.086 | F4: African Marketing Confederation Tourism Chapter – African Marketing Confederation | G4: African Marketing Confederation Tourism Chapter Shaping Africa’s Tourism Narrative Through Strategic Marketing Tourism is one of Africa’s most powerful economic engines - generating jobs, stimulating investment, and fostering cultural exchange.The African Marketing Confederation is proud to launch the Tourism Chapter, a bold initiative to elevate African tourism through the lens of world-class marketing. Launched at the | H4: 354 | I4: 30 | J4: Critical | K4: Yes | L4: partial | M4: rendered_browser | N4: 81 | O4: 423 | P4: https://africanmarketingconfederation.org/wp-content/uploads/2026/03/og-image.png | Q4: FALSE | S4: 0 | U4: 0 | W4: 0 | Y4: 0 | AA4: 0 | AC4: 0 | AD4: 0 | AF4: Lab | AG4: 60 | AH4: 0 | AI4: 0 | AJ4: 0 | AK4: 0 | AL4: 0 | AM4: 0 | AN4: 0 | AO4: 0 | AP4: 0 | AQ4: 1 | AR4: FALSE | AS4: 0.271899 | AT4: TRUE | AU4: TRUE | AV4: Both | AW4: 30 | AX4: 100 | AY4: 47.5 | AZ4: =IFERROR(HYPERLINK("#Technical!A"&MATCH(B4,Technical!A:A,0),"Open Technical"),HYPERLINK("#Technical!A1","Open Technical")) -> Open Technical
A5: FAIL 🔴 | B5: https://africanmarketingconfederation.org/amc-awards-2024 | C5: 200 | D5: Indexable | E5: 2.983 | F5: AMC Awards 2024 – African Marketing Confederation | G5: NOMINATIONS are Open ! AMC Awards The African Marketing Confederation Awards event is held annually as part of the African Marketing Confederation Forum. This distinguished event celebrates and acknowledges outstanding marketing campaigns and the visionary individuals behind them. The awards presented honor not only the groundbreaking strategies and creative brilliance that set these campaigns apart but | H5: 1668 | I5: 30 | J5: Critical | K5: Yes | L5: partial | M5: rendered_browser | N5: 49 | O5: 406 | P5: https://africanmarketingconfederation.org/wp-content/uploads/2021/08/amc_faw.png | Q5: FALSE | S5: 0 | U5: 0 | W5: 0 | Y5: 0 | AA5: 0 | AC5: 0 | AD5: 0 | AF5: Lab | AG5: 100 | AH5: 0 | AI5: 0 | AJ5: 0 | AK5: 0 | AL5: 0 | AM5: 0 | AN5: 0 | AO5: 0 | AP5: 0 | AR5: TRUE | AS5: 0.019665 | AT5: TRUE | AU5: TRUE | AV5: Both | AW5: 30 | AX5: 100 | AY5: 47.5 | AZ5: =IFERROR(HYPERLINK("#Technical!A"&MATCH(B5,Technical!A:A,0),"Open Technical"),HYPERLINK("#Technical!A1","Open Technical")) -> Open Technical
A6: FAIL 🔴 | B6: https://africanmarketingconfederation.org/amc-conference-2022 | C6: 200 | D6: Indexable | E6: 0.073 | F6: AMC Conference 2022 – African Marketing Confederation | G6: corinna kopf onlyfans leaks AMC Conference 2022 Thank you for attending19 - 22 October 2022 The African Marketing Confederation's Annual Conference brought together the best collection of marketing leaders from top companies, marketing bodies and associations to share tactics and best practices on how to build the next generation of marketing. Event Highlights Thank you for Attending! | H6: 32 | I6: 27 | J6: Critical | K6: Yes | L6: partial | M6: rendered_browser | N6: 53 | O6: 387 | P6: https://africanmarketingconfederation.org/wp-content/uploads/2026/03/og-image.png | Q6: FALSE | S6: 0 | U6: 0 | W6: 0 | Y6: 0 | AA6: 0 | AC6: 0 | AD6: 0 | AF6: Lab | AG6: 100 | AH6: 0 | AI6: 0 | AJ6: 0 | AK6: 0 | AL6: 0 | AM6: 0 | AN6: 0 | AO6: 0 | AP6: 0 | AR6: TRUE | AS6: 0.019665 | AT6: TRUE | AU6: TRUE | AV6: Both | AW6: 27 | AX6: 45 | AY6: 31.5 | AZ6: =IFERROR(HYPERLINK("#Technical!A"&MATCH(B6,Technical!A:A,0),"Open Technical"),HYPERLINK("#Technical!A1","Open Technical")) -> Open Technical
A7: FAIL 🔴 | B7: https://africanmarketingconfederation.org/amc-conference-2022-prospectus | C7: 200 | D7: Indexable | E7: 4.143 | F7: AMC Conference 2022 – Prospectus – African Marketing Confederation | G7: AMC Conference 2022 23 - 24 March 2022 Navigating Africa's Unique Marketing Mix BOOK NOW Days Hours Minutes Seconds download prospectus To download the AMC 2022 Conference Prospectus please complete the form below: First Name Last Name Email Mobile Company I've read and agree to the Privacy Policy BOOK NOW FOR THE AMC CONFERENCE 2022 | H7: 120 | I7: 27 | J7: Critical | K7: Yes | L7: partial | M7: rendered_browser | N7: 66 | O7: 335 | P7: https://africanmarketingconfederation.org/wp-content/uploads/2026/03/og-image.png | Q7: FALSE | S7: 0 | U7: 0 | W7: 0 | Y7: 0 | AA7: 0 | AC7: 0 | AD7: 0 | AF7: Lab | AG7: 30 | AH7: 0 | AI7: 0 | AJ7: 0 | AK7: 0 | AL7: 0 | AM7: 0 | AN7: 0 | AO7: 0 | AP7: 0 | AR7: TRUE | AS7: 0.019665 | AT7: TRUE | AU7: TRUE | AV7: Both | AW7: 27 | AX7: 45 | AY7: 31.5 | AZ7: =IFERROR(HYPERLINK("#Technical!A"&MATCH(B7,Technical!A:A,0),"Open Technical"),HYPERLINK("#Technical!A1","Open Technical")) -> Open Technical
A8: FAIL 🔴 | B8: https://africanmarketingconfederation.org/amc-conference-2022-thank-you | C8: 200 | D8: Indexable | E8: 3.351 | F8: AMC Conference 2022 – Thank You – African Marketing Confederation | G8: AMC Conference 2022 23 - 24 March 2022 Navigating Africa's Unique Marketing Mix ENQUIRE NOW Days Hours Minutes Seconds Success! Thank you for completing the enquiry form. Our team will contact you shortly! × Dismiss alert The AMC Conference is the must attend Pan African event for marketing professionals. It will focus on solutions for | H8: 367 | I8: 30 | J8: Critical | K8: Yes | L8: partial | M8: rendered_browser | N8: 65 | O8: 337 | P8: https://africanmarketingconfederation.org/wp-content/uploads/2026/03/og-image.png | Q8: FALSE | S8: 0 | U8: 0 | W8: 0 | Y8: 0 | AA8: 0 | AC8: 0 | AD8: 0 | AF8: Lab | AG8: 100 | AH8: 0 | AI8: 0 | AJ8: 0 | AK8: 0 | AL8: 0 | AM8: 0 | AN8: 0 | AO8: 0 | AP8: 0 | AR8: TRUE | AS8: 0.019665 | AT8: TRUE | AU8: TRUE | AV8: Both | AW8: 30 | AX8: 70 | AY8: 40 | AZ8: =IFERROR(HYPERLINK("#Technical!A"&MATCH(B8,Technical!A:A,0),"Open Technical"),HYPERLINK("#Technical!A1","Open Technical")) -> Open Technical
A9: FAIL 🔴 | B9: https://africanmarketingconfederation.org/amc-conference-2023 | C9: 200 | D9: Indexable | E9: 0.082 | F9: AMC Conference 2023 – African Marketing Confederation | G9: AMC Conference 6 - 9 September 2023 Imperial Botanical Beach Hotel, Entebbe, Uganda Thank you for joining us! View Presentations 2nd Annual African Marketing Confederation Conference Africa's $3.4 trillion Economy: Opportunities for Marketers Welcome to the Recap of the 2nd Annual African Marketing Conference: Unveiling Africa's $3.4 Trillion EconomyOur conference was a remarkable exploration of | H9: 415 | I9: 40 | J9: Critical | K9: Yes | L9: partial | M9: rendered_browser | N9: 53 | O9: 398 | P9: https://africanmarketingconfederation.org/wp-content/uploads/2021/08/amc_faw.png | Q9: FALSE | S9: 0 | U9: 0 | W9: 0 | Y9: 0 | AA9: 0 | AC9: 0 | AD9: 0 | AF9: Lab | AG9: 80 | AH9: 0 | AI9: 0 | AJ9: 0 | AK9: 0 | AL9: 0 | AM9: 0 | AN9: 0 | AO9: 0 | AP9: 0 | AR9: FALSE | AS9: 0.035214 | AT9: TRUE | AU9: TRUE | AV9: Both | AW9: 40 | AX9: 100 | AY9: 55 | AZ9: =IFERROR(HYPERLINK("#Technical!A"&MATCH(B9,Technical!A:A,0),"Open Technical"),HYPERLINK("#Technical!A1","Open Technical")) -> Open Technical
A10: FAIL 🔴 | B10: https://africanmarketingconfederation.org/amc-conference-2023/amc-awards | C10: 200 | D10: Indexable | E10: 0.055 | F10: AMC Awards – African Marketing Confederation | G10: AMC Awards Welcome to the prestigious African Marketing Confederation Awards, a distinguished event that celebrates and acknowledges the remarkable achievements, cutting-edge innovations, and exceptional leadership demonstrated by outstanding individuals within the dynamic realm of marketing across the expansive African region.During the 2nd Annual African Marketing Confederation Conference, held from 6th to 9th September at the | H10: 326 | I10: 40 | J10: Critical | K10: Yes | L10: partial | M10: rendered_browser | N10: 44 | O10: 432 | P10: https://africanmarketingconfederation.org/wp-content/uploads/2021/08/amc_faw.png | Q10: FALSE | S10: 0 | U10: 0 | W10: 0 | Y10: 0 | AA10: 0 | AC10: 0 | AD10: 0 | AF10: Lab | AG10: 40 | AH10: 0 | AI10: 0 | AJ10: 0 | AK10: 0 | AL10: 0 | AM10: 0 | AN10: 0 | AO10: 0 | AP10: 0 | AR10: FALSE | AS10: 0.035214 | AT10: TRUE | AU10: TRUE | AV10: Both | AW10: 40 | AX10: 100 | AY10: 55 | AZ10: =IFERROR(HYPERLINK("#Technical!A"&MATCH(B10,Technical!A:A,0),"Open Technical"),HYPERLINK("#Technical!A1","Open Technical")) -> Open Technical
A11: FAIL 🔴 | B11: https://africanmarketingconfederation.org/amc-conference-2023/amc-awards-book-now | C11: 200 | D11: Indexable | E11: 2.697 | F11: AMC Awards | Book Now – African Marketing Confederation | H11: 31 | I11: 17 | J11: Critical | K11: Yes | L11: partial | M11: rendered_browser | N11: 55 | O11: 0 | P11: https://africanmarketingconfederation.org/wp-content/uploads/2021/08/amc_faw.png | Q11: FALSE | S11: 0 | U11: 0 | W11: 0 | Y11: 0 | AA11: 0 | AC11: 0 | AD11: 0 | AF11: Lab | AG11: 30 | AH11: 0 | AI11: 0 | AJ11: 0 | AK11: 0 | AL11: 0 | AM11: 0 | AN11: 0 | AO11: 0 | AP11: 0 | AR11: TRUE | AS11: 0.019665 | AT11: TRUE | AU11: TRUE | AV11: Both | AW11: 17 | AX11: 25 | AY11: 19 | AZ11: =IFERROR(HYPERLINK("#Technical!A"&MATCH(B11,Technical!A:A,0),"Open Technical"),HYPERLINK("#Technical!A1","Open Technical")) -> Open Technical

Sheet Technical
A1: URL | B1: Status Code | C1: Status Class | D1: SEO Health Score | E1: Severity Badge | F1: Action Needed | G1: Indexability Reason | H1: TTFB (ms) | I1: Total Request Time (ms) | J1: Final URL | K1: Canonical URL | L1: Canonical Type | M1: Owner | N1: Status | O1: Sprint | P1: Extraction State | Q1: Extraction Source | R1: Health Icon | S1: SEO Score | T1: Technical Health | U1: Copy Score | V1: Protocol | W1: Redirect Chain Length | X1: Redirect Target | Y1: Redirect Hops | Z1: HTTP->HTTPS Redirect | AA1: Content-Type | AB1: HTTP Version | AC1: HTML Size (KB) | AD1: Compression Enabled | AE1: Cache-Control | AF1: ETag | AG1: X-Robots-Tag | AH1: Meta Robots Raw | AI1: Canonical Matches Final URL | AJ1: Canonical Absolute URL | AK1: Canonical in Sitemap Match | AL1: Hreflang Present | AM1: Hreflang Count | AN1: Hreflang Self Reference | AO1: Hreflang Reciprocal Check | AP1: Hreflang Canonical Consistency | AQ1: x-default Present | AR1: Pagination rel=next | AS1: Pagination rel=prev | AT1: Last-Modified | AU1: Published Date | AV1: Modified Date | AW1: Last Updated | AX1: Change Frequency | AY1: Priority | AZ1: Schema Types Count | BA1: Schema Types Found | BB1: Internal Links Count | BC1: Unique Internal Links Count | BD1: External Links Count | BE1: AI Crawlers Allowed (GPTBot/ClaudeBot/PerplexityBot) | BF1: llms.txt Present | BG1: Desktop PSI Score | BH1: Mobile PSI Score | BI1: Mobile LCP (s) | BJ1: Mobile CLS | BK1: Mobile TTFB (s) | BL1: CWV LCP (s) | BM1: CWV CLS | BN1: CWV Data Source | BO1: Field vs Lab | BP1: GSC Clicks | BQ1: GSC Impressions | BR1: GSC CTR | BS1: GSC Avg Position | BT1: Click Depth | BU1: Internal Inlinks | BV1: Orphan Pages | BW1: Internal PageRank | BX1: Regional Authority Score | BY1: Regional Entity Hits | BZ1: Answer Block Detected (First 60 Words) | CA1: AEO Extractability Score | CB1: Critical Issues Count | CC1: Warning Issues Count | CD1: Observation Issues Count | CE1: Inlinks Bucket | CF1: Important But Underlinked | CG1: SERP Title Truncation Risk | CH1: SERP Meta Truncation Risk | CI1: SERP Title Pixel Approx | CJ1: SERP Meta Pixel Approx | CK1: Cannibalization Hint | CL1: Stable Issue IDs | CM1: URL Depth | CN1: Param URL Flag | CO1: Open in Main | CP1: BACK TO DASHBOARD
A2: https://africanmarketingconfederation.org/ | B2: 200 | C2: 2xx | D2: 24 | E2: Critical | F2: Yes | G2: Indexable | H2: 53.13 | I2: 31360.04 | J2: https://africanmarketingconfederation.org/ | K2: https://africanmarketingconfederation.org/ | L2: self | M2: Dev | N2: Open | P2: partial | Q2: rendered_browser | R2: FAIL 🔴 | S2: 36.75 | T2: 24 | U2: 75 | V2: https | W2: 0 | Z2: FALSE | AA2: text/html; charset=UTF-8 | AB2: HTTP/1.1 | AC2: 558.26 | AD2: TRUE | AE2: max-age=0 | AH2: max-image-preview:large | AI2: TRUE | AJ2: https://africanmarketingconfederation.org/ | AK2: TRUE | AL2: FALSE | AM2: 0 | AN2: FALSE | AQ2: FALSE | AR2: FALSE | AS2: FALSE | AW2: 2026-04-29T08:23:06+00:00 | AX2: always | AY2: 1 | AZ2: 0 | BB2: 63 | BC2: 22 | BD2: 2 | BE2: FALSE | BF2: TRUE | BG2: 0 | BH2: 0 | BI2: 0 | BJ2: 0 | BK2: 0 | BL2: 0 | BN2: Lab | BO2: Lab | BP2: 0 | BQ2: 0 | BR2: 0 | BS2: 0 | BT2: 0 | BU2: 8 | BV2: FALSE | BW2: 0.287449 | BX2: 100 | BY2: 16 | BZ2: FALSE | CA2: Medium | CB2: 1 | CC2: 3 | CD2: 7 | CE2: 3-10 | CF2: FALSE | CG2: FALSE | CH2: FALSE | CI2: 475 | CJ2: 942 | CL2: https://africanmarketingconfederation.org/::broken_internal_links | https://africanmarketingconfederation.org/::multiple_h1 | https://africanmarketingconfederation.org/::low_image_alt_coverage | https://africanmarketingconfederation.org/::low_aeo_readiness_score | https://africanmarketingconfederation.org/::generic_anchor_text_present | https://africanmarketingconfederation.org/::no_etag_header | https://africanmarketingconfederation.org/::thin_content | https://africanmarketingconfederation.org/::no_question_headings | https://africanmarketingconfederation.org/::no_answer-friendly_structure | https://africanmarketingconfederation.org/::no_40-60_word_answer_paragraphs | https://africanmarketingconfederation.org/::ai_crawlers_not_explicitly_allowed | CM2: 0 | CN2: FALSE | CO2: =IFERROR(HYPERLINK("#Main!A"&MATCH(A2,Main!A:A,0),"Open"),HYPERLINK("#Main!A1","Open")) -> Open
A3: https://africanmarketingconfederation.org/about-us | B3: 200 | C3: 2xx | D3: 37 | E3: Critical | F3: Yes | G3: Indexable | H3: 72.91 | I3: 31594.1 | J3: https://africanmarketingconfederation.org/about-us | K3: https://africanmarketingconfederation.org/about-us | L3: self | M3: Dev | N3: Open | P3: partial | Q3: rendered_browser | R3: FAIL 🔴 | S3: 46.5 | T3: 37 | U3: 75 | V3: https | W3: 0 | Z3: FALSE | AA3: text/html; charset=UTF-8 | AB3: HTTP/1.1 | AC3: 321.88 | AD3: TRUE | AE3: max-age=0 | AH3: max-image-preview:large | AI3: TRUE | AJ3: https://africanmarketingconfederation.org/about-us | AK3: TRUE | AL3: FALSE | AM3: 0 | AN3: FALSE | AQ3: FALSE | AR3: FALSE | AS3: FALSE | AW3: 2026-04-17T08:53:24+00:00 | AX3: weekly | AY3: 0.7 | AZ3: 0 | BB3: 32 | BC3: 14 | BD3: 7 | BE3: FALSE | BF3: TRUE | BG3: 0 | BH3: 0 | BI3: 0 | BJ3: 0 | BK3: 0 | BL3: 0 | BN3: Lab | BO3: Lab | BP3: 0 | BQ3: 0 | BR3: 0 | BS3: 0 | BT3: 1 | BU3: 6 | BV3: FALSE | BW3: 0.271899 | BX3: 70 | BY3: 5 | BZ3: FALSE | CA3: Medium | CB3: 1 | CC3: 2 | CD3: 6 | CE3: 3-10 | CF3: FALSE | CG3: FALSE | CH3: FALSE | CI3: 770 | CJ3: 2511 | CL3: https://africanmarketingconfederation.org/about-us::broken_internal_links | https://africanmarketingconfederation.org/about-us::low_image_alt_coverage | https://africanmarketingconfederation.org/about-us::low_aeo_readiness_score | https://africanmarketingconfederation.org/about-us::no_etag_header | https://africanmarketingconfederation.org/about-us::thin_content | https://africanmarketingconfederation.org/about-us::no_question_headings | https://africanmarketingconfederation.org/about-us::no_answer-friendly_structure | https://africanmarketingconfederation.org/about-us::no_40-60_word_answer_paragraphs | https://africanmarketingconfederation.org/about-us::ai_crawlers_not_explicitly_allowed | CM3: 1 | CN3: FALSE | CO3: =IFERROR(HYPERLINK("#Main!A"&MATCH(A3,Main!A:A,0),"Open"),HYPERLINK("#Main!A1","Open")) -> Open
A4: https://africanmarketingconfederation.org/african-marketing-confederation-tourism-chapter | B4: 200 | C4: 2xx | D4: 30 | E4: Critical | F4: Yes | G4: Indexable | H4: 86.43 | I4: 16330.88 | J4: https://africanmarketingconfederation.org/african-marketing-confederation-tourism-chapter | K4: https://africanmarketingconfederation.org/african-marketing-confederation-tourism-chapter | L4: self | M4: Dev | N4: Open | P4: partial | Q4: rendered_browser | R4: FAIL 🔴 | S4: 47.5 | T4: 30 | U4: 100 | V4: https | W4: 0 | Z4: FALSE | AA4: text/html; charset=UTF-8 | AB4: HTTP/1.1 | AC4: 324.39 | AD4: TRUE | AE4: max-age=0 | AH4: max-image-preview:large | AI4: TRUE | AJ4: https://africanmarketingconfederation.org/african-marketing-confederation-tourism-chapter | AK4: TRUE | AL4: FALSE | AM4: 0 | AN4: FALSE | AQ4: FALSE | AR4: FALSE | AS4: FALSE | AW4: 2026-04-17T08:55:48+00:00 | AX4: weekly | AY4: 0.7 | AZ4: 0 | BB4: 58 | BC4: 15 | BD4: 3 | BE4: FALSE | BF4: TRUE | BG4: 0 | BH4: 0 | BI4: 0 | BJ4: 0 | BK4: 0 | BL4: 0 | BN4: Lab | BO4: Lab | BP4: 0 | BQ4: 0 | BR4: 0 | BS4: 0 | BT4: 1 | BU4: 6 | BV4: FALSE | BW4: 0.271899 | BX4: 60 | BY4: 4 | BZ4: FALSE | CA4: Medium | CB4: 1 | CC4: 3 | CD4: 5 | CE4: 3-10 | CF4: FALSE | CG4: FALSE | CH4: FALSE | CI4: 583 | CJ4: 2622 | CL4: https://africanmarketingconfederation.org/african-marketing-confederation-tourism-chapter::broken_internal_links | https://africanmarketingconfederation.org/african-marketing-confederation-tourism-chapter::multiple_h1 | https://africanmarketingconfederation.org/african-marketing-confederation-tourism-chapter::low_image_alt_coverage | https://africanmarketingconfederation.org/african-marketing-confederation-tourism-chapter::low_aeo_readiness_score | https://africanmarketingconfederation.org/african-marketing-confederation-tourism-chapter::no_etag_header | https://africanmarketingconfederation.org/african-marketing-confederation-tourism-chapter::no_question_headings | https://africanmarketingconfederation.org/african-marketing-confederation-tourism-chapter::no_answer-friendly_structure | https://africanmarketingconfederation.org/african-marketing-confederation-tourism-chapter::no_40-60_word_answer_paragraphs | https://africanmarketingconfederation.org/african-marketing-confederation-tourism-chapter::ai_crawlers_not_explicitly_allowed | CM4: 1 | CN4: FALSE | CO4: =IFERROR(HYPERLINK("#Main!A"&MATCH(A4,Main!A:A,0),"Open"),HYPERLINK("#Main!A1","Open")) -> Open
A5: https://africanmarketingconfederation.org/amc-awards-2024 | B5: 200 | C5: 2xx | D5: 30 | E5: Critical | F5: Yes | G5: Indexable | H5: 2983.38 | I5: 36223.58 | J5: https://africanmarketingconfederation.org/amc-awards-2024 | K5: https://africanmarketingconfederation.org/amc-awards-2024 | L5: self | M5: Dev | N5: Open | P5: partial | Q5: rendered_browser | R5: FAIL 🔴 | S5: 47.5 | T5: 30 | U5: 100 | V5: https | W5: 0 | Z5: FALSE | AA5: text/html; charset=UTF-8 | AB5: HTTP/1.1 | AC5: 513.32 | AD5: TRUE | AE5: max-age=0 | AH5: max-image-preview:large | AI5: TRUE | AJ5: https://africanmarketingconfederation.org/amc-awards-2024 | AK5: TRUE | AL5: FALSE | AM5: 0 | AN5: FALSE | AQ5: FALSE | AR5: FALSE | AS5: FALSE | AW5: 2025-04-24T13:54:46+00:00 | AX5: weekly | AY5: 0.7 | AZ5: 0 | BB5: 16 | BC5: 9 | BD5: 4 | BE5: FALSE | BF5: TRUE | BG5: 0 | BH5: 0 | BI5: 0 | BJ5: 0 | BK5: 0 | BL5: 0 | BN5: Lab | BO5: Lab | BP5: 0 | BQ5: 0 | BR5: 0 | BS5: 0 | BU5: 0 | BV5: TRUE | BW5: 0.019665 | BX5: 100 | BY5: 16 | BZ5: TRUE | CA5: Medium | CB5: 1 | CC5: 3 | CD5: 5 | CE5: 0 | CF5: TRUE | CG5: FALSE | CH5: FALSE | CI5: 352 | CJ5: 2517 | CL5: https://africanmarketingconfederation.org/amc-awards-2024::broken_internal_links | https://africanmarketingconfederation.org/amc-awards-2024::multiple_h1 | https://africanmarketingconfederation.org/amc-awards-2024::low_image_alt_coverage | https://africanmarketingconfederation.org/amc-awards-2024::low_aeo_readiness_score | https://africanmarketingconfederation.org/amc-awards-2024::no_etag_header | https://africanmarketingconfederation.org/amc-awards-2024::no_question_headings | https://africanmarketingconfederation.org/amc-awards-2024::no_answer-friendly_structure | https://africanmarketingconfederation.org/amc-awards-2024::no_40-60_word_answer_paragraphs | https://africanmarketingconfederation.org/amc-awards-2024::ai_crawlers_not_explicitly_allowed | CM5: 1 | CN5: FALSE | CO5: =IFERROR(HYPERLINK("#Main!A"&MATCH(A5,Main!A:A,0),"Open"),HYPERLINK("#Main!A1","Open")) -> Open
A6: https://africanmarketingconfederation.org/amc-conference-2022 | B6: 200 | C6: 2xx | D6: 27 | E6: Critical | F6: Yes | G6: Indexable | H6: 74.09 | I6: 18216.87 | J6: https://africanmarketingconfederation.org/amc-conference-2022 | K6: https://africanmarketingconfederation.org/amc-conference-2022 | L6: self | M6: Dev | N6: Open | P6: partial | Q6: rendered_browser | R6: FAIL 🔴 | S6: 31.5 | T6: 27 | U6: 45 | V6: https | W6: 0 | Z6: FALSE | AA6: text/html; charset=UTF-8 | AB6: HTTP/1.1 | AC6: 342.1 | AD6: TRUE | AE6: max-age=0 | AH6: max-image-preview:large | AI6: TRUE | AJ6: https://africanmarketingconfederation.org/amc-conference-2022 | AK6: TRUE | AL6: FALSE | AM6: 0 | AN6: FALSE | AQ6: FALSE | AR6: FALSE | AS6: FALSE | AW6: 2026-01-21T00:07:32+00:00 | AX6: weekly | AY6: 0.7 | AZ6: 0 | BB6: 99 | BC6: 64 | BD6: 3 | BE6: FALSE | BF6: TRUE | BG6: 0 | BH6: 0 | BI6: 0 | BJ6: 0 | BK6: 0 | BL6: 0 | BN6: Lab | BO6: Lab | BP6: 0 | BQ6: 0 | BR6: 0 | BS6: 0 | BU6: 0 | BV6: TRUE | BW6: 0.019665 | BX6: 100 | BY6: 9 | BZ6: FALSE | CA6: Medium | CB6: 1 | CC6: 3 | CD6: 6 | CE6: 0 | CF6: TRUE | CG6: FALSE | CH6: FALSE | CI6: 381 | CJ6: 2399 | CL6: https://africanmarketingconfederation.org/amc-conference-2022::broken_internal_links | https://africanmarketingconfederation.org/amc-conference-2022::missing_h1 | https://africanmarketingconfederation.org/amc-conference-2022::low_image_alt_coverage | https://africanmarketingconfederation.org/amc-conference-2022::low_aeo_readiness_score | https://africanmarketingconfederation.org/amc-conference-2022::no_etag_header | https://africanmarketingconfederation.org/amc-conference-2022::thin_content | https://africanmarketingconfederation.org/amc-conference-2022::no_question_headings | https://africanmarketingconfederation.org/amc-conference-2022::no_answer-friendly_structure | https://africanmarketingconfederation.org/amc-conference-2022::no_40-60_word_answer_paragraphs | https://africanmarketingconfederation.org/amc-conference-2022::ai_crawlers_not_explicitly_allowed | CM6: 1 | CN6: FALSE | CO6: =IFERROR(HYPERLINK("#Main!A"&MATCH(A6,Main!A:A,0),"Open"),HYPERLINK("#Main!A1","Open")) -> Open
A7: https://africanmarketingconfederation.org/amc-conference-2022-prospectus | B7: 200 | C7: 2xx | D7: 27 | E7: Critical | F7: Yes | G7: Indexable | H7: 4142.54 | I7: 31174.77 | J7: https://africanmarketingconfederation.org/amc-conference-2022-prospectus | K7: https://africanmarketingconfederation.org/amc-conference-2022-prospectus | L7: self | M7: Dev | N7: Open | P7: partial | Q7: rendered_browser | R7: FAIL 🔴 | S7: 31.5 | T7: 27 | U7: 45 | V7: https | W7: 0 | Z7: FALSE | AA7: text/html; charset=UTF-8 | AB7: HTTP/1.1 | AC7: 279.86 | AD7: TRUE | AE7: max-age=0 | AH7: max-image-preview:large | AI7: TRUE | AJ7: https://africanmarketingconfederation.org/amc-conference-2022-prospectus | AK7: TRUE | AL7: FALSE | AM7: 0 | AN7: FALSE | AQ7: FALSE | AR7: FALSE | AS7: FALSE | AW7: 2025-07-14T07:22:03+00:00 | AX7: weekly | AY7: 0.7 | AZ7: 0 | BB7: 32 | BC7: 14 | BD7: 4 | BE7: FALSE | BF7: TRUE | BG7: 0 | BH7: 0 | BI7: 0 | BJ7: 0 | BK7: 0 | BL7: 0 | BN7: Lab | BO7: Lab | BP7: 0 | BQ7: 0 | BR7: 0 | BS7: 0 | BU7: 0 | BV7: TRUE | BW7: 0.019665 | BX7: 30 | BY7: 3 | BZ7: FALSE | CA7: Medium | CB7: 1 | CC7: 3 | CD7: 6 | CE7: 0 | CF7: TRUE | CG7: FALSE | CH7: FALSE | CI7: 475 | CJ7: 2077 | CL7: https://africanmarketingconfederation.org/amc-conference-2022-prospectus::broken_internal_links | https://africanmarketingconfederation.org/amc-conference-2022-prospectus::missing_h1 | https://africanmarketingconfederation.org/amc-conference-2022-prospectus::low_image_alt_coverage | https://africanmarketingconfederation.org/amc-conference-2022-prospectus::low_aeo_readiness_score | https://africanmarketingconfederation.org/amc-conference-2022-prospectus::no_etag_header | https://africanmarketingconfederation.org/amc-conference-2022-prospectus::thin_content | https://africanmarketingconfederation.org/amc-conference-2022-prospectus::no_question_headings | https://africanmarketingconfederation.org/amc-conference-2022-prospectus::no_answer-friendly_structure | https://africanmarketingconfederation.org/amc-conference-2022-prospectus::no_40-60_word_answer_paragraphs | https://africanmarketingconfederation.org/amc-conference-2022-prospectus::ai_crawlers_not_explicitly_allowed | CM7: 1 | CN7: FALSE | CO7: =IFERROR(HYPERLINK("#Main!A"&MATCH(A7,Main!A:A,0),"Open"),HYPERLINK("#Main!A1","Open")) -> Open
A8: https://africanmarketingconfederation.org/amc-conference-2022-thank-you | B8: 200 | C8: 2xx | D8: 30 | E8: Critical | F8: Yes | G8: Indexable | H8: 3350.89 | I8: 21531.29 | J8: https://africanmarketingconfederation.org/amc-conference-2022-thank-you | K8: https://africanmarketingconfederation.org/amc-conference-2022-thank-you | L8: self | M8: Dev | N8: Open | P8: partial | Q8: rendered_browser | R8: FAIL 🔴 | S8: 40 | T8: 30 | U8: 70 | V8: https | W8: 0 | Z8: FALSE | AA8: text/html; charset=UTF-8 | AB8: HTTP/1.1 | AC8: 341.57 | AD8: TRUE | AE8: max-age=0 | AH8: max-image-preview:large | AI8: TRUE | AJ8: https://africanmarketingconfederation.org/amc-conference-2022-thank-you | AK8: TRUE | AL8: FALSE | AM8: 0 | AN8: FALSE | AQ8: FALSE | AR8: FALSE | AS8: FALSE | AW8: 2021-11-26T08:41:00+00:00 | AX8: weekly | AY8: 0.7 | AZ8: 0 | BB8: 32 | BC8: 15 | BD8: 2 | BE8: FALSE | BF8: TRUE | BG8: 0 | BH8: 0 | BI8: 0 | BJ8: 0 | BK8: 0 | BL8: 0 | BN8: Lab | BO8: Lab | BP8: 0 | BQ8: 0 | BR8: 0 | BS8: 0 | BU8: 0 | BV8: TRUE | BW8: 0.019665 | BX8: 100 | BY8: 8 | BZ8: FALSE | CA8: Medium | CB8: 1 | CC8: 3 | CD8: 5 | CE8: 0 | CF8: TRUE | CG8: FALSE | CH8: FALSE | CI8: 468 | CJ8: 2089 | CL8: https://africanmarketingconfederation.org/amc-conference-2022-thank-you::broken_internal_links | https://africanmarketingconfederation.org/amc-conference-2022-thank-you::missing_h1 | https://africanmarketingconfederation.org/amc-conference-2022-thank-you::low_image_alt_coverage | https://africanmarketingconfederation.org/amc-conference-2022-thank-you::low_aeo_readiness_score | https://africanmarketingconfederation.org/amc-conference-2022-thank-you::no_etag_header | https://africanmarketingconfederation.org/amc-conference-2022-thank-you::no_question_headings | https://africanmarketingconfederation.org/amc-conference-2022-thank-you::no_answer-friendly_structure | https://africanmarketingconfederation.org/amc-conference-2022-thank-you::no_40-60_word_answer_paragraphs | https://africanmarketingconfederation.org/amc-conference-2022-thank-you::ai_crawlers_not_explicitly_allowed | CM8: 1 | CN8: FALSE | CO8: =IFERROR(HYPERLINK("#Main!A"&MATCH(A8,Main!A:A,0),"Open"),HYPERLINK("#Main!A1","Open")) -> Open
A9: https://africanmarketingconfederation.org/amc-conference-2023 | B9: 200 | C9: 2xx | D9: 40 | E9: Critical | F9: Yes | G9: Indexable | H9: 81.59 | I9: 29324.73 | J9: https://africanmarketingconfederation.org/amc-conference-2023 | K9: https://africanmarketingconfederation.org/amc-conference-2023 | L9: self | M9: Dev | N9: Open | P9: partial | Q9: rendered_browser | R9: FAIL 🔴 | S9: 55 | T9: 40 | U9: 100 | V9: https | W9: 0 | Z9: FALSE | AA9: text/html; charset=UTF-8 | AB9: HTTP/1.1 | AC9: 371.04 | AD9: TRUE | AE9: max-age=0 | AH9: max-image-preview:large | AI9: TRUE | AJ9: https://africanmarketingconfederation.org/amc-conference-2023 | AK9: TRUE | AL9: FALSE | AM9: 0 | AN9: FALSE | AQ9: FALSE | AR9: FALSE | AS9: FALSE | AW9: 2025-03-03T07:59:34+00:00 | AX9: weekly | AY9: 0.7 | AZ9: 0 | BB9: 41 | BC9: 33 | BD9: 13 | BE9: FALSE | BF9: TRUE | BG9: 0 | BH9: 0 | BI9: 0 | BJ9: 0 | BK9: 0 | BL9: 0 | BN9: Lab | BO9: Lab | BP9: 0 | BQ9: 0 | BR9: 0 | BS9: 0 | BU9: 2 | BV9: FALSE | BW9: 0.035214 | BX9: 80 | BY9: 6 | BZ9: FALSE | CA9: Medium | CB9: 1 | CC9: 2 | CD9: 5 | CE9: 1-2 | CF9: TRUE | CG9: FALSE | CH9: FALSE | CI9: 381 | CJ9: 2467 | CL9: https://africanmarketingconfederation.org/amc-conference-2023::broken_internal_links | https://africanmarketingconfederation.org/amc-conference-2023::low_image_alt_coverage | https://africanmarketingconfederation.org/amc-conference-2023::low_aeo_readiness_score | https://africanmarketingconfederation.org/amc-conference-2023::no_etag_header | https://africanmarketingconfederation.org/amc-conference-2023::no_question_headings | https://africanmarketingconfederation.org/amc-conference-2023::no_answer-friendly_structure | https://africanmarketingconfederation.org/amc-conference-2023::no_40-60_word_answer_paragraphs | https://africanmarketingconfederation.org/amc-conference-2023::ai_crawlers_not_explicitly_allowed | CM9: 1 | CN9: FALSE | CO9: =IFERROR(HYPERLINK("#Main!A"&MATCH(A9,Main!A:A,0),"Open"),HYPERLINK("#Main!A1","Open")) -> Open
A10: https://africanmarketingconfederation.org/amc-conference-2023/amc-awards | B10: 200 | C10: 2xx | D10: 40 | E10: Critical | F10: Yes | G10: Indexable | H10: 55.23 | I10: 18121.64 | J10: https://africanmarketingconfederation.org/amc-conference-2023/amc-awards | K10: https://africanmarketingconfederation.org/amc-conference-2023/amc-awards | L10: self | M10: Dev | N10: Open | P10: partial | Q10: rendered_browser | R10: FAIL 🔴 | S10: 55 | T10: 40 | U10: 100 | V10: https | W10: 0 | Z10: FALSE | AA10: text/html; charset=UTF-8 | AB10: HTTP/1.1 | AC10: 272.64 | AD10: TRUE | AE10: max-age=0 | AH10: max-image-preview:large | AI10: TRUE | AJ10: https://africanmarketingconfederation.org/amc-conference-2023/amc-awards | AK10: TRUE | AL10: FALSE | AM10: 0 | AN10: FALSE | AQ10: FALSE | AR10: FALSE | AS10: FALSE | AW10: 2023-11-23T11:51:22+00:00 | AX10: weekly | AY10: 0.7 | AZ10: 0 | BB10: 19 | BC10: 10 | BD10: 2 | BE10: FALSE | BF10: TRUE | BG10: 0 | BH10: 0 | BI10: 0 | BJ10: 0 | BK10: 0 | BL10: 0 | BN10: Lab | BO10: Lab | BP10: 0 | BQ10: 0 | BR10: 0 | BS10: 0 | BU10: 2 | BV10: FALSE | BW10: 0.035214 | BX10: 40 | BY10: 4 | BZ10: FALSE | CA10: Medium | CB10: 1 | CC10: 2 | CD10: 5 | CE10: 1-2 | CF10: TRUE | CG10: FALSE | CH10: FALSE | CI10: 316 | CJ10: 2678 | CL10: https://africanmarketingconfederation.org/amc-conference-2023/amc-awards::broken_internal_links | https://africanmarketingconfederation.org/amc-conference-2023/amc-awards::low_image_alt_coverage | https://africanmarketingconfederation.org/amc-conference-2023/amc-awards::low_aeo_readiness_score | https://africanmarketingconfederation.org/amc-conference-2023/amc-awards::no_etag_header | https://africanmarketingconfederation.org/amc-conference-2023/amc-awards::no_question_headings | https://africanmarketingconfederation.org/amc-conference-2023/amc-awards::no_answer-friendly_structure | https://africanmarketingconfederation.org/amc-conference-2023/amc-awards::no_40-60_word_answer_paragraphs | https://africanmarketingconfederation.org/amc-conference-2023/amc-awards::ai_crawlers_not_explicitly_allowed | CM10: 2 | CN10: FALSE | CO10: =IFERROR(HYPERLINK("#Main!A"&MATCH(A10,Main!A:A,0),"Open"),HYPERLINK("#Main!A1","Open")) -> Open
A11: https://africanmarketingconfederation.org/amc-conference-2023/amc-awards-book-now | B11: 200 | C11: 2xx | D11: 17 | E11: Critical | F11: Yes | G11: Indexable | H11: 2696.86 | I11: 21720.75 | J11: https://africanmarketingconfederation.org/amc-conference-2023/amc-awards-book-now | K11: https://africanmarketingconfederation.org/amc-conference-2023/amc-awards-book-now | L11: self | M11: Dev | N11: Open | P11: partial | Q11: rendered_browser | R11: FAIL 🔴 | S11: 19 | T11: 17 | U11: 25 | V11: https | W11: 0 | Z11: FALSE | AA11: text/html; charset=UTF-8 | AB11: HTTP/1.1 | AC11: 239.75 | AD11: TRUE | AE11: max-age=0 | AH11: max-image-preview:large | AI11: TRUE | AJ11: https://africanmarketingconfederation.org/amc-conference-2023/amc-awards-book-now | AK11: TRUE | AL11: FALSE | AM11: 0 | AN11: FALSE | AQ11: FALSE | AR11: FALSE | AS11: FALSE | AW11: 2023-08-22T14:14:41+00:00 | AX11: weekly | AY11: 0.7 | AZ11: 0 | BB11: 19 | BC11: 10 | BD11: 2 | BE11: FALSE | BF11: TRUE | BG11: 0 | BH11: 0 | BI11: 0 | BJ11: 0 | BK11: 0 | BL11: 0 | BN11: Lab | BO11: Lab | BP11: 0 | BQ11: 0 | BR11: 0 | BS11: 0 | BU11: 0 | BV11: TRUE | BW11: 0.019665 | BX11: 30 | BY11: 3 | BZ11: FALSE | CA11: Medium | CB11: 1 | CC11: 4 | CD11: 6 | CE11: 0 | CF11: TRUE | CG11: FALSE | CH11: FALSE | CI11: 396 | CJ11: 0 | CL11: https://africanmarketingconfederation.org/amc-conference-2023/amc-awards-book-now::broken_internal_links | https://africanmarketingconfederation.org/amc-conference-2023/amc-awards-book-now::missing_meta_description | https://africanmarketingconfederation.org/amc-conference-2023/amc-awards-book-now::missing_h1 | https://africanmarketingconfederation.org/amc-conference-2023/amc-awards-book-now::low_image_alt_coverage | https://africanmarketingconfederation.org/amc-conference-2023/amc-awards-book-now::low_aeo_readiness_score | https://africanmarketingconfederation.org/amc-conference-2023/amc-awards-book-now::no_etag_header | https://africanmarketingconfederation.org/amc-conference-2023/amc-awards-book-now::thin_content | https://africanmarketingconfederation.org/amc-conference-2023/amc-awards-book-now::no_question_headings | https://africanmarketingconfederation.org/amc-conference-2023/amc-awards-book-now::no_answer-friendly_structure | https://africanmarketingconfederation.org/amc-conference-2023/amc-awards-book-now::no_40-60_word_answer_paragraphs | https://africanmarketingconfederation.org/amc-conference-2023/amc-awards-book-now::ai_crawlers_not_explicitly_allowed | CM11: 2 | CN11: FALSE | CO11: =IFERROR(HYPERLINK("#Main!A"&MATCH(A11,Main!A:A,0),"Open"),HYPERLINK("#Main!A1","Open")) -> Open

Sheet Content
A1: URL | B1: Word Count | C1: Word Count Band | D1: Readability (Rough Flesch) | E1: H1 Count | F1: Missing H1 Flag | G1: Multiple H1 Flag | H1: Title Missing | I1: Meta Description Missing | J1: Thin Content Flag | K1: Sentence Count | L1: Body Text-to-HTML Ratio | M1: Open in Main | N1: BACK TO DASHBOARD
A2: https://africanmarketingconfederation.org/african-marketing-confederation-tourism-chapter | B2: 354 | C2: OK | D2: 179.2 | E2: 2 | F2: FALSE | G2: TRUE | H2: FALSE | I2: FALSE | J2: FALSE | K2: 13 | M2: =IFERROR(HYPERLINK("#Main!A"&MATCH(A2,Main!A:A,0),"Open"),HYPERLINK("#Main!A1","Open")) -> Open
A3: https://africanmarketingconfederation.org/ | B3: 35 | C3: Thin | D3: 189.07 | E3: 5 | F3: FALSE | G3: TRUE | H3: FALSE | I3: FALSE | J3: TRUE | K3: 2 | M3: =IFERROR(HYPERLINK("#Main!A"&MATCH(A3,Main!A:A,0),"Open"),HYPERLINK("#Main!A1","Open")) -> Open
A4: https://africanmarketingconfederation.org/about-us | B4: 235 | C4: Thin | D4: 172.76 | E4: 1 | F4: FALSE | G4: FALSE | H4: FALSE | I4: FALSE | J4: TRUE | K4: 7 | M4: =IFERROR(HYPERLINK("#Main!A"&MATCH(A4,Main!A:A,0),"Open"),HYPERLINK("#Main!A1","Open")) -> Open
A5: https://africanmarketingconfederation.org/amc-awards-2024 | B5: 1668 | C5: Strong | D5: 178.62 | E5: 2 | F5: FALSE | G5: TRUE | H5: FALSE | I5: FALSE | J5: FALSE | K5: 60 | M5: =IFERROR(HYPERLINK("#Main!A"&MATCH(A5,Main!A:A,0),"Open"),HYPERLINK("#Main!A1","Open")) -> Open
A6: https://africanmarketingconfederation.org/amc-conference-2022-prospectus | B6: 120 | C6: Thin | D6: 145.94 | E6: 0 | F6: TRUE | G6: FALSE | H6: FALSE | I6: FALSE | J6: TRUE | K6: 2 | M6: =IFERROR(HYPERLINK("#Main!A"&MATCH(A6,Main!A:A,0),"Open"),HYPERLINK("#Main!A1","Open")) -> Open
A7: https://africanmarketingconfederation.org/amc-conference-2022 | B7: 32 | C7: Thin | D7: 196.01 | E7: 0 | F7: TRUE | G7: FALSE | H7: FALSE | I7: FALSE | J7: TRUE | K7: 3 | M7: =IFERROR(HYPERLINK("#Main!A"&MATCH(A7,Main!A:A,0),"Open"),HYPERLINK("#Main!A1","Open")) -> Open
A8: https://africanmarketingconfederation.org/amc-conference-2022-thank-you | B8: 367 | C8: OK | D8: 178.18 | E8: 0 | F8: TRUE | G8: FALSE | H8: FALSE | I8: FALSE | J8: FALSE | K8: 13 | M8: =IFERROR(HYPERLINK("#Main!A"&MATCH(A8,Main!A:A,0),"Open"),HYPERLINK("#Main!A1","Open")) -> Open
A9: https://africanmarketingconfederation.org/amc-conference-2023 | B9: 415 | C9: OK | D9: 168.54 | E9: 1 | F9: FALSE | G9: FALSE | H9: FALSE | I9: FALSE | J9: FALSE | K9: 11 | M9: =IFERROR(HYPERLINK("#Main!A"&MATCH(A9,Main!A:A,0),"Open"),HYPERLINK("#Main!A1","Open")) -> Open
A10: https://africanmarketingconfederation.org/amc-conference-2023/amc-awards | B10: 326 | C10: OK | D10: 176.75 | E10: 1 | F10: FALSE | G10: FALSE | H10: FALSE | I10: FALSE | J10: FALSE | K10: 11 | M10: =IFERROR(HYPERLINK("#Main!A"&MATCH(A10,Main!A:A,0),"Open"),HYPERLINK("#Main!A1","Open")) -> Open
A11: https://africanmarketingconfederation.org/amc-conference-2023/amc-awards-book-now | B11: 31 | C11: Thin | D11: 175.37 | E11: 0 | F11: TRUE | G11: FALSE | H11: FALSE | I11: TRUE | J11: TRUE | K11: 1 | M11: =IFERROR(HYPERLINK("#Main!A"&MATCH(A11,Main!A:A,0),"Open"),HYPERLINK("#Main!A1","Open")) -> Open

Sheet AEO
A1: URL | B1: AEO Readiness Score | C1: AEO Badge | D1: Why It Matters | E1: FAQ Section Count | F1: Question Heading Count | G1: Paragraphs 40-60 Words Count | H1: QAPage/FAQ Schema Present | I1: Speakable Schema Present | J1: HowTo Signal | K1: Definition Signal | L1: List/Table Answer Signal | M1: Answer Block Detected (First 60 Words) | N1: AEO Extractability Score | O1: Snippet Preview Mockup | P1: Title Missing | Q1: Meta Description Missing | R1: Open in Main | S1: BACK TO DASHBOARD
A2: https://africanmarketingconfederation.org/african-marketing-confederation-tourism-chapter | B2: 0 | C2: Needs Work | D2: Missing 30-60 word answer blocks reduces eligibility for featured snippets. Question-style headings help match conversational search and answer intent. FAQ/QA schema improves machine understanding for rich answer surfaces. Speakable markup can improve voice assistant readability of key answers. Answer-friendly structure (how-to, definitions, lists/tables) helps extraction by answer engines. | E2: 0 | F2: 0 | G2: 0 | H2: FALSE | I2: FALSE | J2: FALSE | K2: FALSE | L2: FALSE | M2: FALSE | N2: Medium | P2: FALSE | Q2: FALSE | R2: =IFERROR(HYPERLINK("#Main!A"&MATCH(A2,Main!A:A,0),"Open"),HYPERLINK("#Main!A1","Open")) -> Open
A3: https://africanmarketingconfederation.org/ | B3: 0 | C3: Needs Work | D3: Missing 30-60 word answer blocks reduces eligibility for featured snippets. Question-style headings help match conversational search and answer intent. FAQ/QA schema improves machine understanding for rich answer surfaces. Speakable markup can improve voice assistant readability of key answers. Answer-friendly structure (how-to, definitions, lists/tables) helps extraction by answer engines. | E3: 0 | F3: 0 | G3: 0 | H3: FALSE | I3: FALSE | J3: FALSE | K3: FALSE | L3: FALSE | M3: FALSE | N3: Medium | P3: FALSE | Q3: FALSE | R3: =IFERROR(HYPERLINK("#Main!A"&MATCH(A3,Main!A:A,0),"Open"),HYPERLINK("#Main!A1","Open")) -> Open
A4: https://africanmarketingconfederation.org/about-us | B4: 0 | C4: Needs Work | D4: Missing 30-60 word answer blocks reduces eligibility for featured snippets. Question-style headings help match conversational search and answer intent. FAQ/QA schema improves machine understanding for rich answer surfaces. Speakable markup can improve voice assistant readability of key answers. Answer-friendly structure (how-to, definitions, lists/tables) helps extraction by answer engines. | E4: 0 | F4: 0 | G4: 0 | H4: FALSE | I4: FALSE | J4: FALSE | K4: FALSE | L4: FALSE | M4: FALSE | N4: Medium | P4: FALSE | Q4: FALSE | R4: =IFERROR(HYPERLINK("#Main!A"&MATCH(A4,Main!A:A,0),"Open"),HYPERLINK("#Main!A1","Open")) -> Open
A5: https://africanmarketingconfederation.org/amc-awards-2024 | B5: 0 | C5: Needs Work | D5: Missing 30-60 word answer blocks reduces eligibility for featured snippets. Question-style headings help match conversational search and answer intent. FAQ/QA schema improves machine understanding for rich answer surfaces. Speakable markup can improve voice assistant readability of key answers. Answer-friendly structure (how-to, definitions, lists/tables) helps extraction by answer engines. | E5: 0 | F5: 0 | G5: 0 | H5: FALSE | I5: FALSE | J5: FALSE | K5: FALSE | L5: FALSE | M5: TRUE | N5: Medium | P5: FALSE | Q5: FALSE | R5: =IFERROR(HYPERLINK("#Main!A"&MATCH(A5,Main!A:A,0),"Open"),HYPERLINK("#Main!A1","Open")) -> Open
A6: https://africanmarketingconfederation.org/amc-conference-2022-prospectus | B6: 0 | C6: Needs Work | D6: Missing 30-60 word answer blocks reduces eligibility for featured snippets. Question-style headings help match conversational search and answer intent. FAQ/QA schema improves machine understanding for rich answer surfaces. Speakable markup can improve voice assistant readability of key answers. Answer-friendly structure (how-to, definitions, lists/tables) helps extraction by answer engines. | E6: 0 | F6: 0 | G6: 0 | H6: FALSE | I6: FALSE | J6: FALSE | K6: FALSE | L6: FALSE | M6: FALSE | N6: Medium | P6: FALSE | Q6: FALSE | R6: =IFERROR(HYPERLINK("#Main!A"&MATCH(A6,Main!A:A,0),"Open"),HYPERLINK("#Main!A1","Open")) -> Open
A7: https://africanmarketingconfederation.org/amc-conference-2022 | B7: 0 | C7: Needs Work | D7: Missing 30-60 word answer blocks reduces eligibility for featured snippets. Question-style headings help match conversational search and answer intent. FAQ/QA schema improves machine understanding for rich answer surfaces. Speakable markup can improve voice assistant readability of key answers. Answer-friendly structure (how-to, definitions, lists/tables) helps extraction by answer engines. | E7: 0 | F7: 0 | G7: 0 | H7: FALSE | I7: FALSE | J7: FALSE | K7: FALSE | L7: FALSE | M7: FALSE | N7: Medium | P7: FALSE | Q7: FALSE | R7: =IFERROR(HYPERLINK("#Main!A"&MATCH(A7,Main!A:A,0),"Open"),HYPERLINK("#Main!A1","Open")) -> Open
A8: https://africanmarketingconfederation.org/amc-conference-2022-thank-you | B8: 0 | C8: Needs Work | D8: Missing 30-60 word answer blocks reduces eligibility for featured snippets. Question-style headings help match conversational search and answer intent. FAQ/QA schema improves machine understanding for rich answer surfaces. Speakable markup can improve voice assistant readability of key answers. Answer-friendly structure (how-to, definitions, lists/tables) helps extraction by answer engines. | E8: 0 | F8: 0 | G8: 0 | H8: FALSE | I8: FALSE | J8: FALSE | K8: FALSE | L8: FALSE | M8: FALSE | N8: Medium | P8: FALSE | Q8: FALSE | R8: =IFERROR(HYPERLINK("#Main!A"&MATCH(A8,Main!A:A,0),"Open"),HYPERLINK("#Main!A1","Open")) -> Open
A9: https://africanmarketingconfederation.org/amc-conference-2023 | B9: 0 | C9: Needs Work | D9: Missing 30-60 word answer blocks reduces eligibility for featured snippets. Question-style headings help match conversational search and answer intent. FAQ/QA schema improves machine understanding for rich answer surfaces. Speakable markup can improve voice assistant readability of key answers. Answer-friendly structure (how-to, definitions, lists/tables) helps extraction by answer engines. | E9: 0 | F9: 0 | G9: 0 | H9: FALSE | I9: FALSE | J9: FALSE | K9: FALSE | L9: FALSE | M9: FALSE | N9: Medium | P9: FALSE | Q9: FALSE | R9: =IFERROR(HYPERLINK("#Main!A"&MATCH(A9,Main!A:A,0),"Open"),HYPERLINK("#Main!A1","Open")) -> Open
A10: https://africanmarketingconfederation.org/amc-conference-2023/amc-awards | B10: 0 | C10: Needs Work | D10: Missing 30-60 word answer blocks reduces eligibility for featured snippets. Question-style headings help match conversational search and answer intent. FAQ/QA schema improves machine understanding for rich answer surfaces. Speakable markup can improve voice assistant readability of key answers. Answer-friendly structure (how-to, definitions, lists/tables) helps extraction by answer engines. | E10: 0 | F10: 0 | G10: 0 | H10: FALSE | I10: FALSE | J10: FALSE | K10: FALSE | L10: FALSE | M10: FALSE | N10: Medium | P10: FALSE | Q10: FALSE | R10: =IFERROR(HYPERLINK("#Main!A"&MATCH(A10,Main!A:A,0),"Open"),HYPERLINK("#Main!A1","Open")) -> Open
A11: https://africanmarketingconfederation.org/amc-conference-2023/amc-awards-book-now | B11: 0 | C11: Needs Work | D11: Missing 30-60 word answer blocks reduces eligibility for featured snippets. Question-style headings help match conversational search and answer intent. FAQ/QA schema improves machine understanding for rich answer surfaces. Speakable markup can improve voice assistant readability of key answers. Answer-friendly structure (how-to, definitions, lists/tables) helps extraction by answer engines. Missing title/meta weakens topical context and lowers snippet confidence. | E11: 0 | F11: 0 | G11: 0 | H11: FALSE | I11: FALSE | J11: FALSE | K11: FALSE | L11: FALSE | M11: FALSE | N11: Medium | P11: FALSE | Q11: TRUE | R11: =IFERROR(HYPERLINK("#Main!A"&MATCH(A11,Main!A:A,0),"Open"),HYPERLINK("#Main!A1","Open")) -> Open

Sheet Schema & Metadata
A1: URL | B1: Schema Types Found | C1: Schema Types Count | D1: Schema Parse Errors | E1: OG Title | F1: OG Description | G1: OG Image | H1: Open Graph Complete | I1: Twitter Card Type | J1: Open in Main | K1: BACK TO DASHBOARD
A2: https://africanmarketingconfederation.org/african-marketing-confederation-tourism-chapter | C2: 0 | D2: 0 | E2: African Marketing Confederation Tourism Chapter – African Marketing Confederation | F2: African Marketing Confederation Tourism Chapter Shaping Africa’s Tourism Narrative Through Strategic Marketing Tourism is one of Africa’s most powerful economic engines - generating jobs, stimulating investment, and fostering cultural exchange.The African Marketing Confederation is proud to launch the Tourism Chapter, a bold initiative to elevate African tourism through the lens of world-class marketing. Launched at the | G2: https://africanmarketingconfederation.org/wp-content/uploads/2026/03/og-image.png | H2: TRUE | I2: summary_large_image | J2: =IFERROR(HYPERLINK("#Main!A"&MATCH(A2,Main!A:A,0),"Open"),HYPERLINK("#Main!A1","Open")) -> Open
A3: https://africanmarketingconfederation.org/ | C3: 0 | D3: 0 | E3: Home page of the african marketing confederation | F3: The 2026 AMC Conference Meets the Mighty Victoria Falls 23-25 September | Livingstone, Zambia Sign Up for Updates The 2026 AMC Conference Meets the Mighty Victoria Falls 23-25 September | Livingstone, Zambia Sign Up for Updates Certified Professional Marketer (Africa) - CPM(A) The designation where global marketing standards meet African realities Learn More ABOUT The | G3: https://africanmarketingconfederation.org/wp-content/uploads/2026/03/og-image.png | H3: TRUE | I3: summary_large_image | J3: =IFERROR(HYPERLINK("#Main!A"&MATCH(A3,Main!A:A,0),"Open"),HYPERLINK("#Main!A1","Open")) -> Open
A4: https://africanmarketingconfederation.org/about-us | C4: 0 | D4: 0 | E4: African Marketing Confederation – The Leading Marketing Professional Body – African Marketing Confederation | F4: ABOUT The African Marketing Confederation The African Marketing Confederation is the ground-breaking Pan African body of marketing professionals spearheading the ongoing development of the highest possible standards of marketing across Africa. Founded in 2011, the AMC is a collaboration between the African national marketing bodies and associations to exchange expertise and information, and to promote | G4: https://africanmarketingconfederation.org/wp-content/uploads/2026/03/og-image.png | H4: TRUE | I4: summary_large_image | J4: =IFERROR(HYPERLINK("#Main!A"&MATCH(A4,Main!A:A,0),"Open"),HYPERLINK("#Main!A1","Open")) -> Open
A5: https://africanmarketingconfederation.org/amc-awards-2024 | C5: 0 | D5: 0 | E5: AMC Awards 2024 – African Marketing Confederation | F5: NOMINATIONS are Open ! AMC Awards The African Marketing Confederation Awards event is held annually as part of the African Marketing Confederation Forum. This distinguished event celebrates and acknowledges outstanding marketing campaigns and the visionary individuals behind them. The awards presented honor not only the groundbreaking strategies and creative brilliance that set these campaigns apart but | G5: https://africanmarketingconfederation.org/wp-content/uploads/2021/08/amc_faw.png | H5: TRUE | I5: summary_large_image | J5: =IFERROR(HYPERLINK("#Main!A"&MATCH(A5,Main!A:A,0),"Open"),HYPERLINK("#Main!A1","Open")) -> Open
A6: https://africanmarketingconfederation.org/amc-conference-2022-prospectus | C6: 0 | D6: 0 | E6: AMC Conference 2022 – Prospectus – African Marketing Confederation | F6: AMC Conference 2022 23 - 24 March 2022 Navigating Africa's Unique Marketing Mix BOOK NOW Days Hours Minutes Seconds download prospectus To download the AMC 2022 Conference Prospectus please complete the form below: First Name Last Name Email Mobile Company I've read and agree to the Privacy Policy BOOK NOW FOR THE AMC CONFERENCE 2022 | G6: https://africanmarketingconfederation.org/wp-content/uploads/2026/03/og-image.png | H6: TRUE | I6: summary_large_image | J6: =IFERROR(HYPERLINK("#Main!A"&MATCH(A6,Main!A:A,0),"Open"),HYPERLINK("#Main!A1","Open")) -> Open
A7: https://africanmarketingconfederation.org/amc-conference-2022 | C7: 0 | D7: 0 | E7: AMC Conference 2022 – African Marketing Confederation | F7: corinna kopf onlyfans leaks AMC Conference 2022 Thank you for attending19 - 22 October 2022 The African Marketing Confederation's Annual Conference brought together the best collection of marketing leaders from top companies, marketing bodies and associations to share tactics and best practices on how to build the next generation of marketing. Event Highlights Thank you for Attending! | G7: https://africanmarketingconfederation.org/wp-content/uploads/2026/03/og-image.png | H7: TRUE | I7: summary_large_image | J7: =IFERROR(HYPERLINK("#Main!A"&MATCH(A7,Main!A:A,0),"Open"),HYPERLINK("#Main!A1","Open")) -> Open
A8: https://africanmarketingconfederation.org/amc-conference-2022-thank-you | C8: 0 | D8: 0 | E8: AMC Conference 2022 – Thank You – African Marketing Confederation | F8: AMC Conference 2022 23 - 24 March 2022 Navigating Africa's Unique Marketing Mix ENQUIRE NOW Days Hours Minutes Seconds Success! Thank you for completing the enquiry form. Our team will contact you shortly! × Dismiss alert The AMC Conference is the must attend Pan African event for marketing professionals. It will focus on solutions for | G8: https://africanmarketingconfederation.org/wp-content/uploads/2026/03/og-image.png | H8: TRUE | I8: summary_large_image | J8: =IFERROR(HYPERLINK("#Main!A"&MATCH(A8,Main!A:A,0),"Open"),HYPERLINK("#Main!A1","Open")) -> Open
A9: https://africanmarketingconfederation.org/amc-conference-2023 | C9: 0 | D9: 0 | E9: AMC Conference 2023 – African Marketing Confederation | F9: AMC Conference 6 - 9 September 2023 Imperial Botanical Beach Hotel, Entebbe, Uganda Thank you for joining us! View Presentations 2nd Annual African Marketing Confederation Conference Africa's $3.4 trillion Economy: Opportunities for Marketers Welcome to the Recap of the 2nd Annual African Marketing Conference: Unveiling Africa's $3.4 Trillion EconomyOur conference was a remarkable exploration of | G9: https://africanmarketingconfederation.org/wp-content/uploads/2021/08/amc_faw.png | H9: TRUE | I9: summary_large_image | J9: =IFERROR(HYPERLINK("#Main!A"&MATCH(A9,Main!A:A,0),"Open"),HYPERLINK("#Main!A1","Open")) -> Open
A10: https://africanmarketingconfederation.org/amc-conference-2023/amc-awards | C10: 0 | D10: 0 | E10: AMC Awards – African Marketing Confederation | F10: AMC Awards Welcome to the prestigious African Marketing Confederation Awards, a distinguished event that celebrates and acknowledges the remarkable achievements, cutting-edge innovations, and exceptional leadership demonstrated by outstanding individuals within the dynamic realm of marketing across the expansive African region.During the 2nd Annual African Marketing Confederation Conference, held from 6th to 9th September at the | G10: https://africanmarketingconfederation.org/wp-content/uploads/2021/08/amc_faw.png | H10: TRUE | I10: summary_large_image | J10: =IFERROR(HYPERLINK("#Main!A"&MATCH(A10,Main!A:A,0),"Open"),HYPERLINK("#Main!A1","Open")) -> Open
A11: https://africanmarketingconfederation.org/amc-conference-2023/amc-awards-book-now | C11: 0 | D11: 0 | E11: AMC Awards | Book Now – African Marketing Confederation | G11: https://africanmarketingconfederation.org/wp-content/uploads/2021/08/amc_faw.png | H11: FALSE | I11: summary_large_image | J11: =IFERROR(HYPERLINK("#Main!A"&MATCH(A11,Main!A:A,0),"Open"),HYPERLINK("#Main!A1","Open")) -> Open

Sheet Links
A1: URL | B1: Internal Links Count | C1: Unique Internal Links Count | D1: Broken Internal Links Count | E1: Unresolved Internal Links Count | F1: Generic Anchor Text Count | G1: External Links Count | H1: Nofollow Internal Links Count | I1: Nofollow External Links Count | J1: Internal Link Statuses | K1: Open in Main | L1: BACK TO DASHBOARD
A2: https://africanmarketingconfederation.org/african-marketing-confederation-tourism-chapter | B2: 58 | C2: 15 | D2: 1 | E2: 0 | F2: 0 | G2: 3 | H2: 0 | I2: 0 | J2: https://africanmarketingconfederation.org/ => 200 | https://africanmarketingconfederation.org/about-us => 200 | https://africanmarketingconfederation.org/african-marketing-confederation-tourism-chapter => 200 | https://africanmarketingconfederation.org/amc-conference-2025-delegate-packages => 404 | https://africanmarketingconfederation.org/amc-conference-2025-highlights => 200 | https://africanmarketingconfederation.org/amc-conference-2026 => 200 | https://africanmarketingconfederation.org/certified-professional-marketer-africa => 200 | https://africanmarketingconfederation.org/chartered-marketer-africa => 200 | https://africanmarketingconfederation.org/contact-us => 200 | https://africanmarketingconfederation.org/education => 200 | https://africanmarketingconfederation.org/members => 200 | https://africanmarketingconfederation.org/news-articles => 200 | https://africanmarketingconfederation.org/privacy-policy => 200 | https://africanmarketingconfederation.org/publications-2 => 200 | https://africanmarketingconfederation.org/sub-committees => 200 | K2: =IFERROR(HYPERLINK("#Main!A"&MATCH(A2,Main!A:A,0),"Open"),HYPERLINK("#Main!A1","Open")) -> Open
A3: https://africanmarketingconfederation.org/ | B3: 63 | C3: 22 | D3: 1 | E3: 0 | F3: 3 | G3: 2 | H3: 0 | I3: 0 | J3: https://africanmarketingconfederation.org/ => 200 | https://africanmarketingconfederation.org/about-us => 200 | https://africanmarketingconfederation.org/african-marketing-confederation-tourism-chapter => 200 | https://africanmarketingconfederation.org/amc-conference-2025 => 200 | https://africanmarketingconfederation.org/amc-conference-2025-delegate-packages => 404 | https://africanmarketingconfederation.org/amc-conference-2026 => 200 | https://africanmarketingconfederation.org/certified-professional-marketer-africa => 200 | https://africanmarketingconfederation.org/chartered-marketer-africa => 200 | https://africanmarketingconfederation.org/chatgpt-ads-in-africa-a-game-changer-or-a-trust-gamble => 200 | https://africanmarketingconfederation.org/contact-us => 200 | https://africanmarketingconfederation.org/education => 200 | https://africanmarketingconfederation.org/european-marketers-gather-to-choose-their-top-achievers-for-2026 => 200 | https://africanmarketingconfederation.org/members => 200 | https://africanmarketingconfederation.org/namibia-bets-on-walvis-bay-port-as-increasingly-viable-alternative => 200 | https://africanmarketingconfederation.org/news-articles => 200 | https://africanmarketingconfederation.org/omnicom-media-study-warns-negative-reach-can-undermine-ad-campaigns => 200 | https://africanmarketingconfederation.org/out-now-new-issue-brings-latest-news-and-insights-for-africas-marketers => 200 | https://africanmarketingconfederation.org/privacy-policy => 200 | https://africanmarketingconfederation.org/publications-2 => 200 | https://africanmarketingconfederation.org/report-identifies-five-forces-influencing-global-purchasing-decisions => 200 | https://africanmarketingconfederation.org/sub-committees => 200 | https://africanmarketingconfederation.org/subscribe => 200 | K3: =IFERROR(HYPERLINK("#Main!A"&MATCH(A3,Main!A:A,0),"Open"),HYPERLINK("#Main!A1","Open")) -> Open
A4: https://africanmarketingconfederation.org/about-us | B4: 32 | C4: 14 | D4: 1 | E4: 0 | F4: 0 | G4: 7 | H4: 0 | I4: 0 | J4: https://africanmarketingconfederation.org/ => 200 | https://africanmarketingconfederation.org/about-us => 200 | https://africanmarketingconfederation.org/african-marketing-confederation-tourism-chapter => 200 | https://africanmarketingconfederation.org/amc-conference-2025-delegate-packages => 404 | https://africanmarketingconfederation.org/amc-conference-2026 => 200 | https://africanmarketingconfederation.org/certified-professional-marketer-africa => 200 | https://africanmarketingconfederation.org/chartered-marketer-africa => 200 | https://africanmarketingconfederation.org/contact-us => 200 | https://africanmarketingconfederation.org/education => 200 | https://africanmarketingconfederation.org/members => 200 | https://africanmarketingconfederation.org/news-articles => 200 | https://africanmarketingconfederation.org/privacy-policy => 200 | https://africanmarketingconfederation.org/publications-2 => 200 | https://africanmarketingconfederation.org/sub-committees => 200 | K4: =IFERROR(HYPERLINK("#Main!A"&MATCH(A4,Main!A:A,0),"Open"),HYPERLINK("#Main!A1","Open")) -> Open
A5: https://africanmarketingconfederation.org/amc-awards-2024 | B5: 16 | C5: 9 | D5: 1 | E5: 0 | F5: 0 | G5: 4 | H5: 0 | I5: 0 | J5: https://africanmarketingconfederation.org/amc-conference-2025 => 200 | https://africanmarketingconfederation.org/amc-conference-2025-delegate-packages => 404 | https://africanmarketingconfederation.org/amc-marketing-conference-2024/amc-programme-2025 => 200 | https://africanmarketingconfederation.org/amc-marketing-conference-2024/awards-2025 => 200 | https://africanmarketingconfederation.org/amc-sponsors-2025 => 200 | https://africanmarketingconfederation.org/conference-faq-2025 => 200 | https://africanmarketingconfederation.org/privacy-policy => 200 | https://africanmarketingconfederation.org/publications-2 => 200 | https://africanmarketingconfederation.org/speakers-2025 => 200 | K5: =IFERROR(HYPERLINK("#Main!A"&MATCH(A5,Main!A:A,0),"Open"),HYPERLINK("#Main!A1","Open")) -> Open
A6: https://africanmarketingconfederation.org/amc-conference-2022-prospectus | B6: 32 | C6: 14 | D6: 1 | E6: 0 | F6: 0 | G6: 4 | H6: 0 | I6: 0 | J6: https://africanmarketingconfederation.org/ => 200 | https://africanmarketingconfederation.org/about-us => 200 | https://africanmarketingconfederation.org/african-marketing-confederation-tourism-chapter => 200 | https://africanmarketingconfederation.org/amc-conference-2025-delegate-packages => 404 | https://africanmarketingconfederation.org/amc-conference-2026 => 200 | https://africanmarketingconfederation.org/certified-professional-marketer-africa => 200 | https://africanmarketingconfederation.org/chartered-marketer-africa => 200 | https://africanmarketingconfederation.org/contact-us => 200 | https://africanmarketingconfederation.org/education => 200 | https://africanmarketingconfederation.org/members => 200 | https://africanmarketingconfederation.org/news-articles => 200 | https://africanmarketingconfederation.org/privacy-policy => 200 | https://africanmarketingconfederation.org/publications-2 => 200 | https://africanmarketingconfederation.org/sub-committees => 200 | K6: =IFERROR(HYPERLINK("#Main!A"&MATCH(A6,Main!A:A,0),"Open"),HYPERLINK("#Main!A1","Open")) -> Open
A7: https://africanmarketingconfederation.org/amc-conference-2022 | B7: 99 | C7: 64 | D7: 1 | E7: 0 | F7: 0 | G7: 3 | H7: 0 | I7: 0 | J7: https://africanmarketingconfederation.org/ => 200 | https://africanmarketingconfederation.org/2024-amc-awards-recognise-marketing-excellence-from-the-continent => 200 | https://africanmarketingconfederation.org/about-us => 200 | https://africanmarketingconfederation.org/african-marketing-confederation-tourism-chapter => 200 | https://africanmarketingconfederation.org/amc-conference-2025 => 200 | https://africanmarketingconfederation.org/amc-conference-2025-delegate-packages => 404 | https://africanmarketingconfederation.org/amc-conference-2026 => 200 | https://africanmarketingconfederation.org/amc-marketing-conference-2024/amc-programme-2025 => 200 | https://africanmarketingconfederation.org/amc-marketing-conference-2024/awards-2025 => 200 | https://africanmarketingconfederation.org/amc-officially-welcomes-new-member-associations-into-the-fold => 200 | https://africanmarketingconfederation.org/amc-sponsors-2025 => 200 | https://africanmarketingconfederation.org/certified-professional-marketer-africa => 200 | https://africanmarketingconfederation.org/chartered-marketer-africa => 200 | https://africanmarketingconfederation.org/conference-faq-2025 => 200 | https://africanmarketingconfederation.org/contact-us => 200 | https://africanmarketingconfederation.org/education => 200 | https://africanmarketingconfederation.org/excitement-as-ghana-announced-as-host-of-2025-amc-marketing-conference => 200 | https://africanmarketingconfederation.org/how-a-bold-strategy-saved-kiwi-marketing-association-from-extinction => 200 | https://africanmarketingconfederation.org/marketers-are-placing-the-ads-where-consumers-dont-want-to-see-them => 200 | https://africanmarketingconfederation.org/members => 200 | https://africanmarketingconfederation.org/news-articles => 200 | https://africanmarketingconfederation.org/privacy-policy => 200 | https://africanmarketingconfederation.org/publications-2 => 200 | https://africanmarketingconfederation.org/speakers-2025 => 200 | https://africanmarketingconfederation.org/sub-committees => 200 | https://africanmarketingconfederation.org/time-for-africa-to-control-its-own-narrative-and-image-delegates-told => 200 | https://africanmarketingconfederation.org/wp-content/uploads/2022/10/EA2A2394-scaled.jpg => 200 | https://africanmarketingconfederation.org/wp-content/uploads/2022/10/EA2A2427-scaled.jpg => 200 | https://africanmarketingconfederation.org/wp-content/uploads/2022/10/EA2A2487-scaled.jpg => 200 | https://africanmarketingconfederation.org/wp-content/uploads/2022/10/EA2A2512-scaled.jpg => 200 | https://africanmarketingconfederation.org/wp-content/uploads/2022/10/EA2A2525-scaled.jpg => 200 | https://africanmarketingconfederation.org/wp-content/uploads/2022/10/EA2A2527-scaled.jpg => 200 | https://africanmarketingconfederation.org/wp-content/uploads/2022/10/EA2A2536-scaled.jpg => 200 | https://africanmarketingconfederation.org/wp-content/uploads/2022/10/EA2A2999-scaled.jpg => 200 | https://africanmarketingconfederation.org/wp-content/uploads/2022/10/EA2A3057-scaled.jpg => 200 | https://africanmarketingconfederation.org/wp-content/uploads/2022/10/EA2A3111-scaled.jpg => 200 | https://africanmarketingconfederation.org/wp-content/uploads/2022/10/EA2A3195-scaled.jpg => 200 | https://africanmarketingconfederation.org/wp-content/uploads/2022/10/EA2A3198-scaled.jpg => 200 | https://africanmarketingconfederation.org/wp-content/uploads/2022/10/EA2A3217-scaled.jpg => 200 | https://africanmarketingconfederation.org/wp-content/uploads/2022/10/EA2A3254-scaled.jpg => 200 | https://africanmarketingconfederation.org/wp-content/uploads/2022/10/EA2A3268-scaled.jpg => 200 | https://africanmarketingconfederation.org/wp-content/uploads/2022/10/EA2A3293-scaled.jpg => 200 | https://africanmarketingconfederation.org/wp-content/uploads/2022/10/EA2A3369-scaled.jpg => 200 | https://africanmarketingconfederation.org/wp-content/uploads/2022/10/EA2A3396-scaled.jpg => 200 | https://africanmarketingconfederation.org/wp-content/uploads/2022/10/EA2A3485-scaled.jpg => 200 | https://africanmarketingconfederation.org/wp-content/uploads/2022/10/EA2A3505-scaled.jpg => 200 | https://africanmarketingconfederation.org/wp-content/uploads/2022/10/EA2A3816-scaled.jpg => 200 | https://africanmarketingconfederation.org/wp-content/uploads/2022/10/EA2A3869-scaled.jpg => 200 | https://africanmarketingconfederation.org/wp-content/uploads/2022/10/EA2A3879-scaled.jpg => 200 | https://africanmarketingconfederation.org/wp-content/uploads/2022/10/EA2A3892-scaled.jpg => 200 | https://africanmarketingconfederation.org/wp-content/uploads/2022/10/EA2A3922-scaled.jpg => 200 | https://africanmarketingconfederation.org/wp-content/uploads/2022/10/EA2A3930-scaled.jpg => 200 | https://africanmarketingconfederation.org/wp-content/uploads/2022/10/EA2A3936-scaled.jpg => 200 | https://africanmarketingconfederation.org/wp-content/uploads/2022/10/EA2A4027-scaled.jpg => 200 | https://africanmarketingconfederation.org/wp-content/uploads/2022/10/EA2A4067-scaled.jpg => 200 | https://africanmarketingconfederation.org/wp-content/uploads/2022/10/EA2A4121-scaled.jpg => 200 | https://africanmarketingconfederation.org/wp-content/uploads/2022/10/EA2A4137-scaled.jpg => 200 | https://africanmarketingconfederation.org/wp-content/uploads/2022/10/IMG_0031-scaled.jpg => 200 | https://africanmarketingconfederation.org/wp-content/uploads/2022/10/IMG_9698-scaled.jpg => 200 | https://africanmarketingconfederation.org/wp-content/uploads/2022/10/IMG_9719-scaled.jpg => 200 | https://africanmarketingconfederation.org/wp-content/uploads/2022/10/IMG_9758-scaled.jpg => 200 | https://africanmarketingconfederation.org/wp-content/uploads/2022/10/IMG_9953-scaled.jpg => 200 | https://africanmarketingconfederation.org/wp-content/uploads/2022/10/IMG_9964-scaled.jpg => 200 | https://africanmarketingconfederation.org/wp-content/uploads/2022/10/IMG_9985-scaled.jpg => 200 | K7: =IFERROR(HYPERLINK("#Main!A"&MATCH(A7,Main!A:A,0),"Open"),HYPERLINK("#Main!A1","Open")) -> Open
A8: https://africanmarketingconfederation.org/amc-conference-2022-thank-you | B8: 32 | C8: 15 | D8: 2 | E8: 0 | F8: 0 | G8: 2 | H8: 0 | I8: 0 | J8: https://africanmarketingconfederation.org/ => 200 | https://africanmarketingconfederation.org/about-us => 200 | https://africanmarketingconfederation.org/african-marketing-confederation-tourism-chapter => 200 | https://africanmarketingconfederation.org/amc-conference-2025-delegate-packages => 404 | https://africanmarketingconfederation.org/amc-conference-2026 => 200 | https://africanmarketingconfederation.org/certified-professional-marketer-africa => 200 | https://africanmarketingconfederation.org/chartered-marketer-africa => 200 | https://africanmarketingconfederation.org/contact-us => 200 | https://africanmarketingconfederation.org/education => 200 | https://africanmarketingconfederation.org/members => 200 | https://africanmarketingconfederation.org/news-articles => 200 | https://africanmarketingconfederation.org/privacy-policy => 200 | https://africanmarketingconfederation.org/publications-2 => 200 | https://africanmarketingconfederation.org/sub-committees => 200 | https://africanmarketingconfederation.org/wp-content/uploads/2021/11/AMC-2022_Prospectus-low-res.pdf => 404 | K8: =IFERROR(HYPERLINK("#Main!A"&MATCH(A8,Main!A:A,0),"Open"),HYPERLINK("#Main!A1","Open")) -> Open
A9: https://africanmarketingconfederation.org/amc-conference-2023 | B9: 41 | C9: 33 | D9: 2 | E9: 0 | F9: 0 | G9: 13 | H9: 0 | I9: 0 | J9: https://africanmarketingconfederation.org/amc-conference-2023/gallery => 200 | https://africanmarketingconfederation.org/amc-conference-2023/programme => 200 | https://africanmarketingconfederation.org/amc-conference-2023/speakers => 200 | https://africanmarketingconfederation.org/amc-conference-2025 => 200 | https://africanmarketingconfederation.org/amc-conference-2025-delegate-packages => 404 | https://africanmarketingconfederation.org/amc-marketing-conference-2024/amc-programme-2025 => 200 | https://africanmarketingconfederation.org/amc-marketing-conference-2024/awards-2025 => 200 | https://africanmarketingconfederation.org/amc-sponsors-2025 => 200 | https://africanmarketingconfederation.org/calendar_events => 404 | https://africanmarketingconfederation.org/conference-faq-2025 => 200 | https://africanmarketingconfederation.org/privacy-policy => 200 | https://africanmarketingconfederation.org/publications-2 => 200 | https://africanmarketingconfederation.org/speakers-2025 => 200 | https://africanmarketingconfederation.org/wp-content/uploads/2023/09/AMC-TICON-0164.jpg => 200 | https://africanmarketingconfederation.org/wp-content/uploads/2023/09/AMC-TICON-1113.jpg => 200 | https://africanmarketingconfederation.org/wp-content/uploads/2023/09/AMC-TICON-1127.jpg => 200 | https://africanmarketingconfederation.org/wp-content/uploads/2023/09/AMC-Ticon-00246.jpg => 200 | https://africanmarketingconfederation.org/wp-content/uploads/2023/09/AMC-Ticon-00449.jpg => 200 | https://africanmarketingconfederation.org/wp-content/uploads/2023/09/AMC-Ticon-00481.jpg => 200 | https://africanmarketingconfederation.org/wp-content/uploads/2023/09/AMC-Ticon-00638.jpg => 200 | https://africanmarketingconfederation.org/wp-content/uploads/2023/09/AMC-Ticon-00682.jpg => 200 | https://africanmarketingconfederation.org/wp-content/uploads/2023/09/AMC-Ticon-00742.jpg => 200 | https://africanmarketingconfederation.org/wp-content/uploads/2023/09/AMC-Ticon-01128.jpg => 200 | https://africanmarketingconfederation.org/wp-content/uploads/2023/09/AMC-Ticon-01363.jpg => 200 | https://africanmarketingconfederation.org/wp-content/uploads/2023/09/AMC-Ticon-01409.jpg => 200 | https://africanmarketingconfederation.org/wp-content/uploads/2023/09/AMC-Ticon-01476.jpg => 200 | https://africanmarketingconfederation.org/wp-content/uploads/2023/09/AMC-Ticon-01530.jpg => 200 | https://africanmarketingconfederation.org/wp-content/uploads/2023/09/AMC-Ticon-01616.jpg => 200 | https://africanmarketingconfederation.org/wp-content/uploads/2023/09/AMC-Ticon-02950-1.jpg => 200 | https://africanmarketingconfederation.org/wp-content/uploads/2023/09/AMC-Ticon-03063.jpg => 200 | https://africanmarketingconfederation.org/wp-content/uploads/2023/09/AMC-Ticon-09823.jpg => 200 | https://africanmarketingconfederation.org/wp-content/uploads/2023/09/AMC-Ticon-09825.jpg => 200 | https://africanmarketingconfederation.org/wp-content/uploads/2023/09/AMC-Ticon-09953.jpg => 200 | K9: =IFERROR(HYPERLINK("#Main!A"&MATCH(A9,Main!A:A,0),"Open"),HYPERLINK("#Main!A1","Open")) -> Open
A10: https://africanmarketingconfederation.org/amc-conference-2023/amc-awards | B10: 19 | C10: 10 | D10: 1 | E10: 0 | F10: 0 | G10: 2 | H10: 0 | I10: 0 | J10: https://africanmarketingconfederation.org/ => 200 | https://africanmarketingconfederation.org/amc-conference-2023 => 200 | https://africanmarketingconfederation.org/amc-conference-2023/amc-awards => 200 | https://africanmarketingconfederation.org/amc-conference-2023/gallery => 200 | https://africanmarketingconfederation.org/amc-conference-2023/partners => 200 | https://africanmarketingconfederation.org/amc-conference-2023/programme => 200 | https://africanmarketingconfederation.org/amc-conference-2023/speakers => 200 | https://africanmarketingconfederation.org/amc-conference-2025-delegate-packages => 404 | https://africanmarketingconfederation.org/privacy-policy => 200 | https://africanmarketingconfederation.org/publications-2 => 200 | K10: =IFERROR(HYPERLINK("#Main!A"&MATCH(A10,Main!A:A,0),"Open"),HYPERLINK("#Main!A1","Open")) -> Open
A11: https://africanmarketingconfederation.org/amc-conference-2023/amc-awards-book-now | B11: 19 | C11: 10 | D11: 1 | E11: 0 | F11: 0 | G11: 2 | H11: 0 | I11: 0 | J11: https://africanmarketingconfederation.org/ => 200 | https://africanmarketingconfederation.org/amc-conference-2023 => 200 | https://africanmarketingconfederation.org/amc-conference-2023/amc-awards => 200 | https://africanmarketingconfederation.org/amc-conference-2023/gallery => 200 | https://africanmarketingconfederation.org/amc-conference-2023/partners => 200 | https://africanmarketingconfederation.org/amc-conference-2023/programme => 200 | https://africanmarketingconfederation.org/amc-conference-2023/speakers => 200 | https://africanmarketingconfederation.org/amc-conference-2025-delegate-packages => 404 | https://africanmarketingconfederation.org/privacy-policy => 200 | https://africanmarketingconfederation.org/publications-2 => 200 | K11: =IFERROR(HYPERLINK("#Main!A"&MATCH(A11,Main!A:A,0),"Open"),HYPERLINK("#Main!A1","Open")) -> Open

Sheet Indexability
A1: URL | B1: Status Code | C1: Status Class | D1: Indexability Reason | E1: Canonical URL | F1: Canonical Type | G1: Canonical Matches Final URL | H1: Canonical in Sitemap Match | I1: Meta Robots Raw | J1: X-Robots-Tag | K1: Final URL | L1: Open in Main | M1: BACK TO DASHBOARD
A2: https://africanmarketingconfederation.org/african-marketing-confederation-tourism-chapter | B2: 200 | C2: 2xx | D2: Indexable | E2: https://africanmarketingconfederation.org/african-marketing-confederation-tourism-chapter | F2: self | G2: TRUE | H2: TRUE | I2: max-image-preview:large | K2: https://africanmarketingconfederation.org/african-marketing-confederation-tourism-chapter | L2: =IFERROR(HYPERLINK("#Main!A"&MATCH(A2,Main!A:A,0),"Open"),HYPERLINK("#Main!A1","Open")) -> Open
A3: https://africanmarketingconfederation.org/ | B3: 200 | C3: 2xx | D3: Indexable | E3: https://africanmarketingconfederation.org/ | F3: self | G3: TRUE | H3: TRUE | I3: max-image-preview:large | K3: https://africanmarketingconfederation.org/ | L3: =IFERROR(HYPERLINK("#Main!A"&MATCH(A3,Main!A:A,0),"Open"),HYPERLINK("#Main!A1","Open")) -> Open
A4: https://africanmarketingconfederation.org/about-us | B4: 200 | C4: 2xx | D4: Indexable | E4: https://africanmarketingconfederation.org/about-us | F4: self | G4: TRUE | H4: TRUE | I4: max-image-preview:large | K4: https://africanmarketingconfederation.org/about-us | L4: =IFERROR(HYPERLINK("#Main!A"&MATCH(A4,Main!A:A,0),"Open"),HYPERLINK("#Main!A1","Open")) -> Open
A5: https://africanmarketingconfederation.org/amc-awards-2024 | B5: 200 | C5: 2xx | D5: Indexable | E5: https://africanmarketingconfederation.org/amc-awards-2024 | F5: self | G5: TRUE | H5: TRUE | I5: max-image-preview:large | K5: https://africanmarketingconfederation.org/amc-awards-2024 | L5: =IFERROR(HYPERLINK("#Main!A"&MATCH(A5,Main!A:A,0),"Open"),HYPERLINK("#Main!A1","Open")) -> Open
A6: https://africanmarketingconfederation.org/amc-conference-2022-prospectus | B6: 200 | C6: 2xx | D6: Indexable | E6: https://africanmarketingconfederation.org/amc-conference-2022-prospectus | F6: self | G6: TRUE | H6: TRUE | I6: max-image-preview:large | K6: https://africanmarketingconfederation.org/amc-conference-2022-prospectus | L6: =IFERROR(HYPERLINK("#Main!A"&MATCH(A6,Main!A:A,0),"Open"),HYPERLINK("#Main!A1","Open")) -> Open
A7: https://africanmarketingconfederation.org/amc-conference-2022 | B7: 200 | C7: 2xx | D7: Indexable | E7: https://africanmarketingconfederation.org/amc-conference-2022 | F7: self | G7: TRUE | H7: TRUE | I7: max-image-preview:large | K7: https://africanmarketingconfederation.org/amc-conference-2022 | L7: =IFERROR(HYPERLINK("#Main!A"&MATCH(A7,Main!A:A,0),"Open"),HYPERLINK("#Main!A1","Open")) -> Open
A8: https://africanmarketingconfederation.org/amc-conference-2022-thank-you | B8: 200 | C8: 2xx | D8: Indexable | E8: https://africanmarketingconfederation.org/amc-conference-2022-thank-you | F8: self | G8: TRUE | H8: TRUE | I8: max-image-preview:large | K8: https://africanmarketingconfederation.org/amc-conference-2022-thank-you | L8: =IFERROR(HYPERLINK("#Main!A"&MATCH(A8,Main!A:A,0),"Open"),HYPERLINK("#Main!A1","Open")) -> Open
A9: https://africanmarketingconfederation.org/amc-conference-2023 | B9: 200 | C9: 2xx | D9: Indexable | E9: https://africanmarketingconfederation.org/amc-conference-2023 | F9: self | G9: TRUE | H9: TRUE | I9: max-image-preview:large | K9: https://africanmarketingconfederation.org/amc-conference-2023 | L9: =IFERROR(HYPERLINK("#Main!A"&MATCH(A9,Main!A:A,0),"Open"),HYPERLINK("#Main!A1","Open")) -> Open
A10: https://africanmarketingconfederation.org/amc-conference-2023/amc-awards | B10: 200 | C10: 2xx | D10: Indexable | E10: https://africanmarketingconfederation.org/amc-conference-2023/amc-awards | F10: self | G10: TRUE | H10: TRUE | I10: max-image-preview:large | K10: https://africanmarketingconfederation.org/amc-conference-2023/amc-awards | L10: =IFERROR(HYPERLINK("#Main!A"&MATCH(A10,Main!A:A,0),"Open"),HYPERLINK("#Main!A1","Open")) -> Open
A11: https://africanmarketingconfederation.org/amc-conference-2023/amc-awards-book-now | B11: 200 | C11: 2xx | D11: Indexable | E11: https://africanmarketingconfederation.org/amc-conference-2023/amc-awards-book-now | F11: self | G11: TRUE | H11: TRUE | I11: max-image-preview:large | K11: https://africanmarketingconfederation.org/amc-conference-2023/amc-awards-book-now | L11: =IFERROR(HYPERLINK("#Main!A"&MATCH(A11,Main!A:A,0),"Open"),HYPERLINK("#Main!A1","Open")) -> Open

Sheet Redirects
A1: URL | B1: Status Code | C1: Final URL | D1: Redirect Chain Length | E1: Redirect Target | F1: Redirect Hops | G1: HTTP->HTTPS Redirect | H1: Redirect Loop Flag | I1: Open in Main | J1: BACK TO DASHBOARD
A2: https://africanmarketingconfederation.org/african-marketing-confederation-tourism-chapter | B2: 200 | C2: https://africanmarketingconfederation.org/african-marketing-confederation-tourism-chapter | D2: 0 | G2: FALSE | H2: FALSE | I2: =IFERROR(HYPERLINK("#Main!A"&MATCH(A2,Main!A:A,0),"Open"),HYPERLINK("#Main!A1","Open")) -> Open
A3: https://africanmarketingconfederation.org/ | B3: 200 | C3: https://africanmarketingconfederation.org/ | D3: 0 | G3: FALSE | H3: FALSE | I3: =IFERROR(HYPERLINK("#Main!A"&MATCH(A3,Main!A:A,0),"Open"),HYPERLINK("#Main!A1","Open")) -> Open
A4: https://africanmarketingconfederation.org/about-us | B4: 200 | C4: https://africanmarketingconfederation.org/about-us | D4: 0 | G4: FALSE | H4: FALSE | I4: =IFERROR(HYPERLINK("#Main!A"&MATCH(A4,Main!A:A,0),"Open"),HYPERLINK("#Main!A1","Open")) -> Open
A5: https://africanmarketingconfederation.org/amc-awards-2024 | B5: 200 | C5: https://africanmarketingconfederation.org/amc-awards-2024 | D5: 0 | G5: FALSE | H5: FALSE | I5: =IFERROR(HYPERLINK("#Main!A"&MATCH(A5,Main!A:A,0),"Open"),HYPERLINK("#Main!A1","Open")) -> Open
A6: https://africanmarketingconfederation.org/amc-conference-2022-prospectus | B6: 200 | C6: https://africanmarketingconfederation.org/amc-conference-2022-prospectus | D6: 0 | G6: FALSE | H6: FALSE | I6: =IFERROR(HYPERLINK("#Main!A"&MATCH(A6,Main!A:A,0),"Open"),HYPERLINK("#Main!A1","Open")) -> Open
A7: https://africanmarketingconfederation.org/amc-conference-2022 | B7: 200 | C7: https://africanmarketingconfederation.org/amc-conference-2022 | D7: 0 | G7: FALSE | H7: FALSE | I7: =IFERROR(HYPERLINK("#Main!A"&MATCH(A7,Main!A:A,0),"Open"),HYPERLINK("#Main!A1","Open")) -> Open
A8: https://africanmarketingconfederation.org/amc-conference-2022-thank-you | B8: 200 | C8: https://africanmarketingconfederation.org/amc-conference-2022-thank-you | D8: 0 | G8: FALSE | H8: FALSE | I8: =IFERROR(HYPERLINK("#Main!A"&MATCH(A8,Main!A:A,0),"Open"),HYPERLINK("#Main!A1","Open")) -> Open
A9: https://africanmarketingconfederation.org/amc-conference-2023 | B9: 200 | C9: https://africanmarketingconfederation.org/amc-conference-2023 | D9: 0 | G9: FALSE | H9: FALSE | I9: =IFERROR(HYPERLINK("#Main!A"&MATCH(A9,Main!A:A,0),"Open"),HYPERLINK("#Main!A1","Open")) -> Open
A10: https://africanmarketingconfederation.org/amc-conference-2023/amc-awards | B10: 200 | C10: https://africanmarketingconfederation.org/amc-conference-2023/amc-awards | D10: 0 | G10: FALSE | H10: FALSE | I10: =IFERROR(HYPERLINK("#Main!A"&MATCH(A10,Main!A:A,0),"Open"),HYPERLINK("#Main!A1","Open")) -> Open
A11: https://africanmarketingconfederation.org/amc-conference-2023/amc-awards-book-now | B11: 200 | C11: https://africanmarketingconfederation.org/amc-conference-2023/amc-awards-book-now | D11: 0 | G11: FALSE | H11: FALSE | I11: =IFERROR(HYPERLINK("#Main!A"&MATCH(A11,Main!A:A,0),"Open"),HYPERLINK("#Main!A1","Open")) -> Open

Sheet Priority URLs
A1: URL | B1: Business Risk Score | C1: Severity Badge | D1: SEO Health Score | E1: GSC Impressions | F1: GSC CTR | G1: Revenue Intent | H1: Critical Issues Count | I1: Warning Issues Count | J1: Action Needed | K1: Why Prioritized | L1: Owner | M1: Status | N1: Sprint | O1: Indexability Reason | P1: Broken Internal Links Count | Q1: Canonical Type | R1: Open in Main | S1: Open in Technical | T1: BACK TO DASHBOARD
A2: https://africanmarketingconfederation.org/amc-conference-2023/amc-awards-book-now | B2: 153 | C2: Critical | D2: 17 | E2: 0 | F2: 0 | G2: Standard | H2: 1 | I2: 4 | J2: Yes | K2: Has critical issues | Broken internal links | L2: Dev | M2: Open | O2: Indexable | P2: 1 | Q2: self | R2: =IFERROR(HYPERLINK("#Main!A"&MATCH(A2,Main!A:A,0),"Open"),HYPERLINK("#Main!A1","Open")) -> Open | S2: =IFERROR(HYPERLINK("#Technical!A"&MATCH(A2,Technical!A:A,0),"Open"),HYPERLINK("#Technical!A1","Open")) -> Open
A3: https://africanmarketingconfederation.org/ | B3: 136 | C3: Critical | D3: 24 | E3: 0 | F3: 0 | G3: Standard | H3: 1 | I3: 3 | J3: Yes | K3: Has critical issues | Broken internal links | L3: Dev | M3: Open | O3: Indexable | P3: 1 | Q3: self | R3: =IFERROR(HYPERLINK("#Main!A"&MATCH(A3,Main!A:A,0),"Open"),HYPERLINK("#Main!A1","Open")) -> Open | S3: =IFERROR(HYPERLINK("#Technical!A"&MATCH(A3,Technical!A:A,0),"Open"),HYPERLINK("#Technical!A1","Open")) -> Open
A4: https://africanmarketingconfederation.org/amc-conference-2022-prospectus | B4: 133 | C4: Critical | D4: 27 | E4: 0 | F4: 0 | G4: Standard | H4: 1 | I4: 3 | J4: Yes | K4: Has critical issues | Broken internal links | L4: Dev | M4: Open | O4: Indexable | P4: 1 | Q4: self | R4: =IFERROR(HYPERLINK("#Main!A"&MATCH(A4,Main!A:A,0),"Open"),HYPERLINK("#Main!A1","Open")) -> Open | S4: =IFERROR(HYPERLINK("#Technical!A"&MATCH(A4,Technical!A:A,0),"Open"),HYPERLINK("#Technical!A1","Open")) -> Open
A5: https://africanmarketingconfederation.org/amc-conference-2022 | B5: 133 | C5: Critical | D5: 27 | E5: 0 | F5: 0 | G5: Standard | H5: 1 | I5: 3 | J5: Yes | K5: Has critical issues | Broken internal links | L5: Dev | M5: Open | O5: Indexable | P5: 1 | Q5: self | R5: =IFERROR(HYPERLINK("#Main!A"&MATCH(A5,Main!A:A,0),"Open"),HYPERLINK("#Main!A1","Open")) -> Open | S5: =IFERROR(HYPERLINK("#Technical!A"&MATCH(A5,Technical!A:A,0),"Open"),HYPERLINK("#Technical!A1","Open")) -> Open
A6: https://africanmarketingconfederation.org/african-marketing-confederation-tourism-chapter | B6: 130 | C6: Critical | D6: 30 | E6: 0 | F6: 0 | G6: Standard | H6: 1 | I6: 3 | J6: Yes | K6: Has critical issues | Broken internal links | L6: Dev | M6: Open | O6: Indexable | P6: 1 | Q6: self | R6: =IFERROR(HYPERLINK("#Main!A"&MATCH(A6,Main!A:A,0),"Open"),HYPERLINK("#Main!A1","Open")) -> Open | S6: =IFERROR(HYPERLINK("#Technical!A"&MATCH(A6,Technical!A:A,0),"Open"),HYPERLINK("#Technical!A1","Open")) -> Open
A7: https://africanmarketingconfederation.org/amc-awards-2024 | B7: 130 | C7: Critical | D7: 30 | E7: 0 | F7: 0 | G7: Standard | H7: 1 | I7: 3 | J7: Yes | K7: Has critical issues | Broken internal links | L7: Dev | M7: Open | O7: Indexable | P7: 1 | Q7: self | R7: =IFERROR(HYPERLINK("#Main!A"&MATCH(A7,Main!A:A,0),"Open"),HYPERLINK("#Main!A1","Open")) -> Open | S7: =IFERROR(HYPERLINK("#Technical!A"&MATCH(A7,Technical!A:A,0),"Open"),HYPERLINK("#Technical!A1","Open")) -> Open
A8: https://africanmarketingconfederation.org/amc-conference-2022-thank-you | B8: 130 | C8: Critical | D8: 30 | E8: 0 | F8: 0 | G8: Standard | H8: 1 | I8: 3 | J8: Yes | K8: Has critical issues | Broken internal links | L8: Dev | M8: Open | O8: Indexable | P8: 2 | Q8: self | R8: =IFERROR(HYPERLINK("#Main!A"&MATCH(A8,Main!A:A,0),"Open"),HYPERLINK("#Main!A1","Open")) -> Open | S8: =IFERROR(HYPERLINK("#Technical!A"&MATCH(A8,Technical!A:A,0),"Open"),HYPERLINK("#Technical!A1","Open")) -> Open
A9: https://africanmarketingconfederation.org/about-us | B9: 113 | C9: Critical | D9: 37 | E9: 0 | F9: 0 | G9: Standard | H9: 1 | I9: 2 | J9: Yes | K9: Has critical issues | Broken internal links | L9: Dev | M9: Open | O9: Indexable | P9: 1 | Q9: self | R9: =IFERROR(HYPERLINK("#Main!A"&MATCH(A9,Main!A:A,0),"Open"),HYPERLINK("#Main!A1","Open")) -> Open | S9: =IFERROR(HYPERLINK("#Technical!A"&MATCH(A9,Technical!A:A,0),"Open"),HYPERLINK("#Technical!A1","Open")) -> Open
A10: https://africanmarketingconfederation.org/amc-conference-2023 | B10: 110 | C10: Critical | D10: 40 | E10: 0 | F10: 0 | G10: Standard | H10: 1 | I10: 2 | J10: Yes | K10: Has critical issues | Broken internal links | L10: Dev | M10: Open | O10: Indexable | P10: 2 | Q10: self | R10: =IFERROR(HYPERLINK("#Main!A"&MATCH(A10,Main!A:A,0),"Open"),HYPERLINK("#Main!A1","Open")) -> Open | S10: =IFERROR(HYPERLINK("#Technical!A"&MATCH(A10,Technical!A:A,0),"Open"),HYPERLINK("#Technical!A1","Open")) -> Open
A11: https://africanmarketingconfederation.org/amc-conference-2023/amc-awards | B11: 110 | C11: Critical | D11: 40 | E11: 0 | F11: 0 | G11: Standard | H11: 1 | I11: 2 | J11: Yes | K11: Has critical issues | Broken internal links | L11: Dev | M11: Open | O11: Indexable | P11: 1 | Q11: self | R11: =IFERROR(HYPERLINK("#Main!A"&MATCH(A11,Main!A:A,0),"Open"),HYPERLINK("#Main!A1","Open")) -> Open | S11: =IFERROR(HYPERLINK("#Technical!A"&MATCH(A11,Technical!A:A,0),"Open"),HYPERLINK("#Technical!A1","Open")) -> Open

Sheet AIOSEO
A1: URL | B1: WordPress Post ID | C1: Direct Edit Link | D1: AIOSEO Panel | E1: Severity | F1: Issue | G1: Priority Score | H1: Current Value | I1: Recommended Target | J1: How to Fix in AIOSEO | K1: Reference Tab | L1: Reference Field | M1: Action Needed | N1: Owner | O1: Status | P1: Est. Hours | Q1: Stable Issue ID | R1: Why It Matters | S1: Open in Main | T1: Open in Technical | U1: BACK TO DASHBOARD
A2: https://africanmarketingconfederation.org/ | B2: 8 | C2: https://africanmarketingconfederation.org/wp-admin/post.php?post=8&action=edit | D2: Links | E2: Critical | F2: Broken internal links | G2: 105 | H2: 1 | I2: 0 | J2: Replace dead links with live targets, or remove them in the page editor. | K2: Links | L2: Broken Internal Links Count | M2: Yes | N2: Dev | O2: Open | P2: 10 | Q2: https://africanmarketingconfederation.org/::aioseo_broken_internal_links | R2: Broken links waste crawl budget and degrade user experience. | S2: =IFERROR(HYPERLINK("#Main!A"&MATCH(A2,Main!A:A,0),"Open"),HYPERLINK("#Main!A1","Open")) -> Open | T2: =IFERROR(HYPERLINK("#Technical!A"&MATCH(A2,Technical!A:A,0),"Open"),HYPERLINK("#Technical!A1","Open")) -> Open
A3: https://africanmarketingconfederation.org/about-us | B3: 84 | C3: https://africanmarketingconfederation.org/wp-admin/post.php?post=84&action=edit | D3: Links | E3: Critical | F3: Broken internal links | G3: 105 | H3: 1 | I3: 0 | J3: Replace dead links with live targets, or remove them in the page editor. | K3: Links | L3: Broken Internal Links Count | M3: Yes | N3: Dev | O3: Open | P3: 10 | Q3: https://africanmarketingconfederation.org/about-us::aioseo_broken_internal_links | R3: Broken links waste crawl budget and degrade user experience. | S3: =IFERROR(HYPERLINK("#Main!A"&MATCH(A3,Main!A:A,0),"Open"),HYPERLINK("#Main!A1","Open")) -> Open | T3: =IFERROR(HYPERLINK("#Technical!A"&MATCH(A3,Technical!A:A,0),"Open"),HYPERLINK("#Technical!A1","Open")) -> Open
A4: https://africanmarketingconfederation.org/african-marketing-confederation-tourism-chapter | B4: 28165 | C4: https://africanmarketingconfederation.org/wp-admin/post.php?post=28165&action=edit | D4: Links | E4: Critical | F4: Broken internal links | G4: 105 | H4: 1 | I4: 0 | J4: Replace dead links with live targets, or remove them in the page editor. | K4: Links | L4: Broken Internal Links Count | M4: Yes | N4: Dev | O4: Open | P4: 10 | Q4: https://africanmarketingconfederation.org/african-marketing-confederation-tourism-chapter::aioseo_broken_internal_links | R4: Broken links waste crawl budget and degrade user experience. | S4: =IFERROR(HYPERLINK("#Main!A"&MATCH(A4,Main!A:A,0),"Open"),HYPERLINK("#Main!A1","Open")) -> Open | T4: =IFERROR(HYPERLINK("#Technical!A"&MATCH(A4,Technical!A:A,0),"Open"),HYPERLINK("#Technical!A1","Open")) -> Open
A5: https://africanmarketingconfederation.org/amc-awards-2024 | B5: 16125 | C5: https://africanmarketingconfederation.org/wp-admin/post.php?post=16125&action=edit | D5: Links | E5: Critical | F5: Broken internal links | G5: 105 | H5: 1 | I5: 0 | J5: Replace dead links with live targets, or remove them in the page editor. | K5: Links | L5: Broken Internal Links Count | M5: Yes | N5: Dev | O5: Open | P5: 10 | Q5: https://africanmarketingconfederation.org/amc-awards-2024::aioseo_broken_internal_links | R5: Broken links waste crawl budget and degrade user experience. | S5: =IFERROR(HYPERLINK("#Main!A"&MATCH(A5,Main!A:A,0),"Open"),HYPERLINK("#Main!A1","Open")) -> Open | T5: =IFERROR(HYPERLINK("#Technical!A"&MATCH(A5,Technical!A:A,0),"Open"),HYPERLINK("#Technical!A1","Open")) -> Open
A6: https://africanmarketingconfederation.org/amc-conference-2022 | B6: 4494 | C6: https://africanmarketingconfederation.org/wp-admin/post.php?post=4494&action=edit | D6: Links | E6: Critical | F6: Broken internal links | G6: 105 | H6: 1 | I6: 0 | J6: Replace dead links with live targets, or remove them in the page editor. | K6: Links | L6: Broken Internal Links Count | M6: Yes | N6: Dev | O6: Open | P6: 10 | Q6: https://africanmarketingconfederation.org/amc-conference-2022::aioseo_broken_internal_links | R6: Broken links waste crawl budget and degrade user experience. | S6: =IFERROR(HYPERLINK("#Main!A"&MATCH(A6,Main!A:A,0),"Open"),HYPERLINK("#Main!A1","Open")) -> Open | T6: =IFERROR(HYPERLINK("#Technical!A"&MATCH(A6,Technical!A:A,0),"Open"),HYPERLINK("#Technical!A1","Open")) -> Open
A7: https://africanmarketingconfederation.org/amc-conference-2022-prospectus | B7: 5619 | C7: https://africanmarketingconfederation.org/wp-admin/post.php?post=5619&action=edit | D7: Links | E7: Critical | F7: Broken internal links | G7: 105 | H7: 1 | I7: 0 | J7: Replace dead links with live targets, or remove them in the page editor. | K7: Links | L7: Broken Internal Links Count | M7: Yes | N7: Dev | O7: Open | P7: 10 | Q7: https://africanmarketingconfederation.org/amc-conference-2022-prospectus::aioseo_broken_internal_links | R7: Broken links waste crawl budget and degrade user experience. | S7: =IFERROR(HYPERLINK("#Main!A"&MATCH(A7,Main!A:A,0),"Open"),HYPERLINK("#Main!A1","Open")) -> Open | T7: =IFERROR(HYPERLINK("#Technical!A"&MATCH(A7,Technical!A:A,0),"Open"),HYPERLINK("#Technical!A1","Open")) -> Open
A8: https://africanmarketingconfederation.org/amc-conference-2022-thank-you | B8: 4941 | C8: https://africanmarketingconfederation.org/wp-admin/post.php?post=4941&action=edit | D8: Links | E8: Critical | F8: Broken internal links | G8: 105 | H8: 2 | I8: 0 | J8: Replace dead links with live targets, or remove them in the page editor. | K8: Links | L8: Broken Internal Links Count | M8: Yes | N8: Dev | O8: Open | P8: 10 | Q8: https://africanmarketingconfederation.org/amc-conference-2022-thank-you::aioseo_broken_internal_links | R8: Broken links waste crawl budget and degrade user experience. | S8: =IFERROR(HYPERLINK("#Main!A"&MATCH(A8,Main!A:A,0),"Open"),HYPERLINK("#Main!A1","Open")) -> Open | T8: =IFERROR(HYPERLINK("#Technical!A"&MATCH(A8,Technical!A:A,0),"Open"),HYPERLINK("#Technical!A1","Open")) -> Open
A9: https://africanmarketingconfederation.org/amc-conference-2023 | B9: 12371 | C9: https://africanmarketingconfederation.org/wp-admin/post.php?post=12371&action=edit | D9: Links | E9: Critical | F9: Broken internal links | G9: 105 | H9: 2 | I9: 0 | J9: Replace dead links with live targets, or remove them in the page editor. | K9: Links | L9: Broken Internal Links Count | M9: Yes | N9: Dev | O9: Open | P9: 10 | Q9: https://africanmarketingconfederation.org/amc-conference-2023::aioseo_broken_internal_links | R9: Broken links waste crawl budget and degrade user experience. | S9: =IFERROR(HYPERLINK("#Main!A"&MATCH(A9,Main!A:A,0),"Open"),HYPERLINK("#Main!A1","Open")) -> Open | T9: =IFERROR(HYPERLINK("#Technical!A"&MATCH(A9,Technical!A:A,0),"Open"),HYPERLINK("#Technical!A1","Open")) -> Open
A10: https://africanmarketingconfederation.org/amc-conference-2023/amc-awards | B10: 12954 | C10: https://africanmarketingconfederation.org/wp-admin/post.php?post=12954&action=edit | D10: Links | E10: Critical | F10: Broken internal links | G10: 105 | H10: 1 | I10: 0 | J10: Replace dead links with live targets, or remove them in the page editor. | K10: Links | L10: Broken Internal Links Count | M10: Yes | N10: Dev | O10: Open | P10: 10 | Q10: https://africanmarketingconfederation.org/amc-conference-2023/amc-awards::aioseo_broken_internal_links | R10: Broken links waste crawl budget and degrade user experience. | S10: =IFERROR(HYPERLINK("#Main!A"&MATCH(A10,Main!A:A,0),"Open"),HYPERLINK("#Main!A1","Open")) -> Open | T10: =IFERROR(HYPERLINK("#Technical!A"&MATCH(A10,Technical!A:A,0),"Open"),HYPERLINK("#Technical!A1","Open")) -> Open
A11: https://africanmarketingconfederation.org/amc-conference-2023/amc-awards-book-now | B11: 13164 | C11: https://africanmarketingconfederation.org/wp-admin/post.php?post=13164&action=edit | D11: Links | E11: Critical | F11: Broken internal links | G11: 105 | H11: 1 | I11: 0 | J11: Replace dead links with live targets, or remove them in the page editor. | K11: Links | L11: Broken Internal Links Count | M11: Yes | N11: Dev | O11: Open | P11: 10 | Q11: https://africanmarketingconfederation.org/amc-conference-2023/amc-awards-book-now::aioseo_broken_internal_links | R11: Broken links waste crawl budget and degrade user experience. | S11: =IFERROR(HYPERLINK("#Main!A"&MATCH(A11,Main!A:A,0),"Open"),HYPERLINK("#Main!A1","Open")) -> Open | T11: =IFERROR(HYPERLINK("#Technical!A"&MATCH(A11,Technical!A:A,0),"Open"),HYPERLINK("#Technical!A1","Open")) -> Open
A12: https://africanmarketingconfederation.org/amc-conference-2023/amc-awards-book-now | B12: 13164 | C12: https://africanmarketingconfederation.org/wp-admin/post.php?post=13164&action=edit | D12: Basic SEO | E12: Warning | F12: Missing meta description | G12: 67 | H12: Missing | I12: 120-160 characters | J12: In AIOSEO snippet settings, add a concise, unique meta description aligned to page intent. | K12: Main | L12: Meta Description | M12: Yes | N12: Copy Writer | O12: Open | P12: 4 | Q12: https://africanmarketingconfederation.org/amc-conference-2023/amc-awards-book-now::aioseo_missing_meta_description | R12: Missing descriptions reduce control over search snippet messaging. | S12: =IFERROR(HYPERLINK("#Main!A"&MATCH(A12,Main!A:A,0),"Open"),HYPERLINK("#Main!A1","Open")) -> Open | T12: =IFERROR(HYPERLINK("#Technical!A"&MATCH(A12,Technical!A:A,0),"Open"),HYPERLINK("#Technical!A1","Open")) -> Open
A13: https://africanmarketingconfederation.org/ | B13: 8 | C13: https://africanmarketingconfederation.org/wp-admin/post.php?post=8&action=edit | D13: Content | E13: Warning | F13: Low AEO readiness score | G13: 67 | H13: 0 | I13: >=60 | J13: Add concise answer blocks, question-led subheadings, and clear structured sections. | K13: AEO | L13: AEO Readiness Score | M13: Yes | N13: Copy Writer | O13: Open | P13: 4 | Q13: https://africanmarketingconfederation.org/::aioseo_low_aeo_readiness_score | R13: Weak answer-style structure lowers AI/answer-engine retrieval potential. | S13: =IFERROR(HYPERLINK("#Main!A"&MATCH(A13,Main!A:A,0),"Open"),HYPERLINK("#Main!A1","Open")) -> Open | T13: =IFERROR(HYPERLINK("#Technical!A"&MATCH(A13,Technical!A:A,0),"Open"),HYPERLINK("#Technical!A1","Open")) -> Open
A14: https://africanmarketingconfederation.org/about-us | B14: 84 | C14: https://africanmarketingconfederation.org/wp-admin/post.php?post=84&action=edit | D14: Content | E14: Warning | F14: Low AEO readiness score | G14: 67 | H14: 0 | I14: >=60 | J14: Add concise answer blocks, question-led subheadings, and clear structured sections. | K14: AEO | L14: AEO Readiness Score | M14: Yes | N14: Copy Writer | O14: Open | P14: 4 | Q14: https://africanmarketingconfederation.org/about-us::aioseo_low_aeo_readiness_score | R14: Weak answer-style structure lowers AI/answer-engine retrieval potential. | S14: =IFERROR(HYPERLINK("#Main!A"&MATCH(A14,Main!A:A,0),"Open"),HYPERLINK("#Main!A1","Open")) -> Open | T14: =IFERROR(HYPERLINK("#Technical!A"&MATCH(A14,Technical!A:A,0),"Open"),HYPERLINK("#Technical!A1","Open")) -> Open
A15: https://africanmarketingconfederation.org/african-marketing-confederation-tourism-chapter | B15: 28165 | C15: https://africanmarketingconfederation.org/wp-admin/post.php?post=28165&action=edit | D15: Content | E15: Warning | F15: Low AEO readiness score | G15: 67 | H15: 0 | I15: >=60 | J15: Add concise answer blocks, question-led subheadings, and clear structured sections. | K15: AEO | L15: AEO Readiness Score | M15: Yes | N15: Copy Writer | O15: Open | P15: 4 | Q15: https://africanmarketingconfederation.org/african-marketing-confederation-tourism-chapter::aioseo_low_aeo_readiness_score | R15: Weak answer-style structure lowers AI/answer-engine retrieval potential. | S15: =IFERROR(HYPERLINK("#Main!A"&MATCH(A15,Main!A:A,0),"Open"),HYPERLINK("#Main!A1","Open")) -> Open | T15: =IFERROR(HYPERLINK("#Technical!A"&MATCH(A15,Technical!A:A,0),"Open"),HYPERLINK("#Technical!A1","Open")) -> Open
A16: https://africanmarketingconfederation.org/amc-awards-2024 | B16: 16125 | C16: https://africanmarketingconfederation.org/wp-admin/post.php?post=16125&action=edit | D16: Content | E16: Warning | F16: Low AEO readiness score | G16: 67 | H16: 0 | I16: >=60 | J16: Add concise answer blocks, question-led subheadings, and clear structured sections. | K16: AEO | L16: AEO Readiness Score | M16: Yes | N16: Copy Writer | O16: Open | P16: 4 | Q16: https://africanmarketingconfederation.org/amc-awards-2024::aioseo_low_aeo_readiness_score | R16: Weak answer-style structure lowers AI/answer-engine retrieval potential. | S16: =IFERROR(HYPERLINK("#Main!A"&MATCH(A16,Main!A:A,0),"Open"),HYPERLINK("#Main!A1","Open")) -> Open | T16: =IFERROR(HYPERLINK("#Technical!A"&MATCH(A16,Technical!A:A,0),"Open"),HYPERLINK("#Technical!A1","Open")) -> Open
A17: https://africanmarketingconfederation.org/amc-conference-2022 | B17: 4494 | C17: https://africanmarketingconfederation.org/wp-admin/post.php?post=4494&action=edit | D17: Content | E17: Warning | F17: Low AEO readiness score | G17: 67 | H17: 0 | I17: >=60 | J17: Add concise answer blocks, question-led subheadings, and clear structured sections. | K17: AEO | L17: AEO Readiness Score | M17: Yes | N17: Copy Writer | O17: Open | P17: 4 | Q17: https://africanmarketingconfederation.org/amc-conference-2022::aioseo_low_aeo_readiness_score | R17: Weak answer-style structure lowers AI/answer-engine retrieval potential. | S17: =IFERROR(HYPERLINK("#Main!A"&MATCH(A17,Main!A:A,0),"Open"),HYPERLINK("#Main!A1","Open")) -> Open | T17: =IFERROR(HYPERLINK("#Technical!A"&MATCH(A17,Technical!A:A,0),"Open"),HYPERLINK("#Technical!A1","Open")) -> Open
A18: https://africanmarketingconfederation.org/amc-conference-2022-prospectus | B18: 5619 | C18: https://africanmarketingconfederation.org/wp-admin/post.php?post=5619&action=edit | D18: Content | E18: Warning | F18: Low AEO readiness score | G18: 67 | H18: 0 | I18: >=60 | J18: Add concise answer blocks, question-led subheadings, and clear structured sections. | K18: AEO | L18: AEO Readiness Score | M18: Yes | N18: Copy Writer | O18: Open | P18: 4 | Q18: https://africanmarketingconfederation.org/amc-conference-2022-prospectus::aioseo_low_aeo_readiness_score | R18: Weak answer-style structure lowers AI/answer-engine retrieval potential. | S18: =IFERROR(HYPERLINK("#Main!A"&MATCH(A18,Main!A:A,0),"Open"),HYPERLINK("#Main!A1","Open")) -> Open | T18: =IFERROR(HYPERLINK("#Technical!A"&MATCH(A18,Technical!A:A,0),"Open"),HYPERLINK("#Technical!A1","Open")) -> Open
A19: https://africanmarketingconfederation.org/amc-conference-2022-thank-you | B19: 4941 | C19: https://africanmarketingconfederation.org/wp-admin/post.php?post=4941&action=edit | D19: Content | E19: Warning | F19: Low AEO readiness score | G19: 67 | H19: 0 | I19: >=60 | J19: Add concise answer blocks, question-led subheadings, and clear structured sections. | K19: AEO | L19: AEO Readiness Score | M19: Yes | N19: Copy Writer | O19: Open | P19: 4 | Q19: https://africanmarketingconfederation.org/amc-conference-2022-thank-you::aioseo_low_aeo_readiness_score | R19: Weak answer-style structure lowers AI/answer-engine retrieval potential. | S19: =IFERROR(HYPERLINK("#Main!A"&MATCH(A19,Main!A:A,0),"Open"),HYPERLINK("#Main!A1","Open")) -> Open | T19: =IFERROR(HYPERLINK("#Technical!A"&MATCH(A19,Technical!A:A,0),"Open"),HYPERLINK("#Technical!A1","Open")) -> Open
A20: https://africanmarketingconfederation.org/amc-conference-2023 | B20: 12371 | C20: https://africanmarketingconfederation.org/wp-admin/post.php?post=12371&action=edit | D20: Content | E20: Warning | F20: Low AEO readiness score | G20: 67 | H20: 0 | I20: >=60 | J20: Add concise answer blocks, question-led subheadings, and clear structured sections. | K20: AEO | L20: AEO Readiness Score | M20: Yes | N20: Copy Writer | O20: Open | P20: 4 | Q20: https://africanmarketingconfederation.org/amc-conference-2023::aioseo_low_aeo_readiness_score | R20: Weak answer-style structure lowers AI/answer-engine retrieval potential. | S20: =IFERROR(HYPERLINK("#Main!A"&MATCH(A20,Main!A:A,0),"Open"),HYPERLINK("#Main!A1","Open")) -> Open | T20: =IFERROR(HYPERLINK("#Technical!A"&MATCH(A20,Technical!A:A,0),"Open"),HYPERLINK("#Technical!A1","Open")) -> Open
A21: https://africanmarketingconfederation.org/amc-conference-2023/amc-awards | B21: 12954 | C21: https://africanmarketingconfederation.org/wp-admin/post.php?post=12954&action=edit | D21: Content | E21: Warning | F21: Low AEO readiness score | G21: 67 | H21: 0 | I21: >=60 | J21: Add concise answer blocks, question-led subheadings, and clear structured sections. | K21: AEO | L21: AEO Readiness Score | M21: Yes | N21: Copy Writer | O21: Open | P21: 4 | Q21: https://africanmarketingconfederation.org/amc-conference-2023/amc-awards::aioseo_low_aeo_readiness_score | R21: Weak answer-style structure lowers AI/answer-engine retrieval potential. | S21: =IFERROR(HYPERLINK("#Main!A"&MATCH(A21,Main!A:A,0),"Open"),HYPERLINK("#Main!A1","Open")) -> Open | T21: =IFERROR(HYPERLINK("#Technical!A"&MATCH(A21,Technical!A:A,0),"Open"),HYPERLINK("#Technical!A1","Open")) -> Open
A22: https://africanmarketingconfederation.org/amc-conference-2023/amc-awards-book-now | B22: 13164 | C22: https://africanmarketingconfederation.org/wp-admin/post.php?post=13164&action=edit | D22: Content | E22: Warning | F22: Low AEO readiness score | G22: 67 | H22: 0 | I22: >=60 | J22: Add concise answer blocks, question-led subheadings, and clear structured sections. | K22: AEO | L22: AEO Readiness Score | M22: Yes | N22: Copy Writer | O22: Open | P22: 4 | Q22: https://africanmarketingconfederation.org/amc-conference-2023/amc-awards-book-now::aioseo_low_aeo_readiness_score | R22: Weak answer-style structure lowers AI/answer-engine retrieval potential. | S22: =IFERROR(HYPERLINK("#Main!A"&MATCH(A22,Main!A:A,0),"Open"),HYPERLINK("#Main!A1","Open")) -> Open | T22: =IFERROR(HYPERLINK("#Technical!A"&MATCH(A22,Technical!A:A,0),"Open"),HYPERLINK("#Technical!A1","Open")) -> Open
A23: https://africanmarketingconfederation.org/ | B23: 8 | C23: https://africanmarketingconfederation.org/wp-admin/post.php?post=8&action=edit | D23: Readability | E23: Warning | F23: Low image alt coverage | G23: 67 | H23: 79.03 | I23: >=80% | J23: Add descriptive alt text to meaningful images in the page editor/media fields. | K23: Media | L23: Image Alt Coverage (%) | M23: Yes | N23: Copy Writer | O23: Open | P23: 4 | Q23: https://africanmarketingconfederation.org/::aioseo_low_image_alt_coverage | R23: Missing alt text reduces accessibility and weakens image context signals. | S23: =IFERROR(HYPERLINK("#Main!A"&MATCH(A23,Main!A:A,0),"Open"),HYPERLINK("#Main!A1","Open")) -> Open | T23: =IFERROR(HYPERLINK("#Technical!A"&MATCH(A23,Technical!A:A,0),"Open"),HYPERLINK("#Technical!A1","Open")) -> Open
A24: https://africanmarketingconfederation.org/ | B24: 8 | C24: https://africanmarketingconfederation.org/wp-admin/post.php?post=8&action=edit | D24: Readability | E24: Warning | F24: Thin content | G24: 67 | H24: 35 | I24: >=300 words (quality first) | J24: Expand page copy with useful, unique sections that answer key user questions. | K24: Content | L24: Word Count | M24: Yes | N24: Copy Writer | O24: Open | P24: 4 | Q24: https://africanmarketingconfederation.org/::aioseo_thin_content | R24: Low-content pages can struggle to satisfy intent and rank competitively. | S24: =IFERROR(HYPERLINK("#Main!A"&MATCH(A24,Main!A:A,0),"Open"),HYPERLINK("#Main!A1","Open")) -> Open | T24: =IFERROR(HYPERLINK("#Technical!A"&MATCH(A24,Technical!A:A,0),"Open"),HYPERLINK("#Technical!A1","Open")) -> Open
... A82: https://africanmarketingconfederation.org/amc-conference-2023/amc-awards-book-now | B82: 13164 | C82: https://africanmarketingconfederation.org/wp-admin/post.php?post=13164&action=edit | D82: Readability | E82: Observation | F82: No question-style headings | G82: 37 | H82: 0 | I82: >=1 where intent is informational | J82: Add at least one natural question heading (H2/H3) matching user intent. | K82: AEO | L82: Question Heading Count | M82: No | N82: Copy Writer | O82: Open | P82: 4 | Q82: https://africanmarketingconfederation.org/amc-conference-2023/amc-awards-book-now::aioseo_no_question-style_headings | R82: Question headings better align with query phrasing and snippet extraction. | S82: =IFERROR(HYPERLINK("#Main!A"&MATCH(A82,Main!A:A,0),"Open"),HYPERLINK("#Main!A1","Open")) -> Open | T82: =IFERROR(HYPERLINK("#Technical!A"&MATCH(A82,Technical!A:A,0),"Open"),HYPERLINK("#Technical!A1","Open")) -> Open
A83: https://africanmarketingconfederation.org/ | B83: 8 | C83: https://africanmarketingconfederation.org/wp-admin/post.php?post=8&action=edit | D83: Schema | E83: Observation | F83: No FAQ/QA schema | G83: 37 | H83: FALSE | I83: True when page has Q&A intent | J83: If content is Q&A style, add FAQPage/QAPage schema in AIOSEO and keep markup aligned with on-page content. | K83: AEO | L83: QAPage/FAQ Schema Present | M83: No | N83: Copy Writer | O83: Open | P83: 4 | Q83: https://africanmarketingconfederation.org/::aioseo_no_faq_qa_schema | R83: Q&A schema can improve eligibility for answer-rich results. | S83: =IFERROR(HYPERLINK("#Main!A"&MATCH(A83,Main!A:A,0),"Open"),HYPERLINK("#Main!A1","Open")) -> Open | T83: =IFERROR(HYPERLINK("#Technical!A"&MATCH(A83,Technical!A:A,0),"Open"),HYPERLINK("#Technical!A1","Open")) -> Open
A84: https://africanmarketingconfederation.org/about-us | B84: 84 | C84: https://africanmarketingconfederation.org/wp-admin/post.php?post=84&action=edit | D84: Schema | E84: Observation | F84: No FAQ/QA schema | G84: 37 | H84: FALSE | I84: True when page has Q&A intent | J84: If content is Q&A style, add FAQPage/QAPage schema in AIOSEO and keep markup aligned with on-page content. | K84: AEO | L84: QAPage/FAQ Schema Present | M84: No | N84: Copy Writer | O84: Open | P84: 4 | Q84: https://africanmarketingconfederation.org/about-us::aioseo_no_faq_qa_schema | R84: Q&A schema can improve eligibility for answer-rich results. | S84: =IFERROR(HYPERLINK("#Main!A"&MATCH(A84,Main!A:A,0),"Open"),HYPERLINK("#Main!A1","Open")) -> Open | T84: =IFERROR(HYPERLINK("#Technical!A"&MATCH(A84,Technical!A:A,0),"Open"),HYPERLINK("#Technical!A1","Open")) -> Open
A85: https://africanmarketingconfederation.org/african-marketing-confederation-tourism-chapter | B85: 28165 | C85: https://africanmarketingconfederation.org/wp-admin/post.php?post=28165&action=edit | D85: Schema | E85: Observation | F85: No FAQ/QA schema | G85: 37 | H85: FALSE | I85: True when page has Q&A intent | J85: If content is Q&A style, add FAQPage/QAPage schema in AIOSEO and keep markup aligned with on-page content. | K85: AEO | L85: QAPage/FAQ Schema Present | M85: No | N85: Copy Writer | O85: Open | P85: 4 | Q85: https://africanmarketingconfederation.org/african-marketing-confederation-tourism-chapter::aioseo_no_faq_qa_schema | R85: Q&A schema can improve eligibility for answer-rich results. | S85: =IFERROR(HYPERLINK("#Main!A"&MATCH(A85,Main!A:A,0),"Open"),HYPERLINK("#Main!A1","Open")) -> Open | T85: =IFERROR(HYPERLINK("#Technical!A"&MATCH(A85,Technical!A:A,0),"Open"),HYPERLINK("#Technical!A1","Open")) -> Open
A86: https://africanmarketingconfederation.org/amc-awards-2024 | B86: 16125 | C86: https://africanmarketingconfederation.org/wp-admin/post.php?post=16125&action=edit | D86: Schema | E86: Observation | F86: No FAQ/QA schema | G86: 37 | H86: FALSE | I86: True when page has Q&A intent | J86: If content is Q&A style, add FAQPage/QAPage schema in AIOSEO and keep markup aligned with on-page content. | K86: AEO | L86: QAPage/FAQ Schema Present | M86: No | N86: Copy Writer | O86: Open | P86: 4 | Q86: https://africanmarketingconfederation.org/amc-awards-2024::aioseo_no_faq_qa_schema | R86: Q&A schema can improve eligibility for answer-rich results. | S86: =IFERROR(HYPERLINK("#Main!A"&MATCH(A86,Main!A:A,0),"Open"),HYPERLINK("#Main!A1","Open")) -> Open | T86: =IFERROR(HYPERLINK("#Technical!A"&MATCH(A86,Technical!A:A,0),"Open"),HYPERLINK("#Technical!A1","Open")) -> Open
A87: https://africanmarketingconfederation.org/amc-conference-2022 | B87: 4494 | C87: https://africanmarketingconfederation.org/wp-admin/post.php?post=4494&action=edit | D87: Schema | E87: Observation | F87: No FAQ/QA schema | G87: 37 | H87: FALSE | I87: True when page has Q&A intent | J87: If content is Q&A style, add FAQPage/QAPage schema in AIOSEO and keep markup aligned with on-page content. | K87: AEO | L87: QAPage/FAQ Schema Present | M87: No | N87: Copy Writer | O87: Open | P87: 4 | Q87: https://africanmarketingconfederation.org/amc-conference-2022::aioseo_no_faq_qa_schema | R87: Q&A schema can improve eligibility for answer-rich results. | S87: =IFERROR(HYPERLINK("#Main!A"&MATCH(A87,Main!A:A,0),"Open"),HYPERLINK("#Main!A1","Open")) -> Open | T87: =IFERROR(HYPERLINK("#Technical!A"&MATCH(A87,Technical!A:A,0),"Open"),HYPERLINK("#Technical!A1","Open")) -> Open
A88: https://africanmarketingconfederation.org/amc-conference-2022-prospectus | B88: 5619 | C88: https://africanmarketingconfederation.org/wp-admin/post.php?post=5619&action=edit | D88: Schema | E88: Observation | F88: No FAQ/QA schema | G88: 37 | H88: FALSE | I88: True when page has Q&A intent | J88: If content is Q&A style, add FAQPage/QAPage schema in AIOSEO and keep markup aligned with on-page content. | K88: AEO | L88: QAPage/FAQ Schema Present | M88: No | N88: Copy Writer | O88: Open | P88: 4 | Q88: https://africanmarketingconfederation.org/amc-conference-2022-prospectus::aioseo_no_faq_qa_schema | R88: Q&A schema can improve eligibility for answer-rich results. | S88: =IFERROR(HYPERLINK("#Main!A"&MATCH(A88,Main!A:A,0),"Open"),HYPERLINK("#Main!A1","Open")) -> Open | T88: =IFERROR(HYPERLINK("#Technical!A"&MATCH(A88,Technical!A:A,0),"Open"),HYPERLINK("#Technical!A1","Open")) -> Open
A89: https://africanmarketingconfederation.org/amc-conference-2022-thank-you | B89: 4941 | C89: https://africanmarketingconfederation.org/wp-admin/post.php?post=4941&action=edit | D89: Schema | E89: Observation | F89: No FAQ/QA schema | G89: 37 | H89: FALSE | I89: True when page has Q&A intent | J89: If content is Q&A style, add FAQPage/QAPage schema in AIOSEO and keep markup aligned with on-page content. | K89: AEO | L89: QAPage/FAQ Schema Present | M89: No | N89: Copy Writer | O89: Open | P89: 4 | Q89: https://africanmarketingconfederation.org/amc-conference-2022-thank-you::aioseo_no_faq_qa_schema | R89: Q&A schema can improve eligibility for answer-rich results. | S89: =IFERROR(HYPERLINK("#Main!A"&MATCH(A89,Main!A:A,0),"Open"),HYPERLINK("#Main!A1","Open")) -> Open | T89: =IFERROR(HYPERLINK("#Technical!A"&MATCH(A89,Technical!A:A,0),"Open"),HYPERLINK("#Technical!A1","Open")) -> Open
A90: https://africanmarketingconfederation.org/amc-conference-2023 | B90: 12371 | C90: https://africanmarketingconfederation.org/wp-admin/post.php?post=12371&action=edit | D90: Schema | E90: Observation | F90: No FAQ/QA schema | G90: 37 | H90: FALSE | I90: True when page has Q&A intent | J90: If content is Q&A style, add FAQPage/QAPage schema in AIOSEO and keep markup aligned with on-page content. | K90: AEO | L90: QAPage/FAQ Schema Present | M90: No | N90: Copy Writer | O90: Open | P90: 4 | Q90: https://africanmarketingconfederation.org/amc-conference-2023::aioseo_no_faq_qa_schema | R90: Q&A schema can improve eligibility for answer-rich results. | S90: =IFERROR(HYPERLINK("#Main!A"&MATCH(A90,Main!A:A,0),"Open"),HYPERLINK("#Main!A1","Open")) -> Open | T90: =IFERROR(HYPERLINK("#Technical!A"&MATCH(A90,Technical!A:A,0),"Open"),HYPERLINK("#Technical!A1","Open")) -> Open
A91: https://africanmarketingconfederation.org/amc-conference-2023/amc-awards | B91: 12954 | C91: https://africanmarketingconfederation.org/wp-admin/post.php?post=12954&action=edit | D91: Schema | E91: Observation | F91: No FAQ/QA schema | G91: 37 | H91: FALSE | I91: True when page has Q&A intent | J91: If content is Q&A style, add FAQPage/QAPage schema in AIOSEO and keep markup aligned with on-page content. | K91: AEO | L91: QAPage/FAQ Schema Present | M91: No | N91: Copy Writer | O91: Open | P91: 4 | Q91: https://africanmarketingconfederation.org/amc-conference-2023/amc-awards::aioseo_no_faq_qa_schema | R91: Q&A schema can improve eligibility for answer-rich results. | S91: =IFERROR(HYPERLINK("#Main!A"&MATCH(A91,Main!A:A,0),"Open"),HYPERLINK("#Main!A1","Open")) -> Open | T91: =IFERROR(HYPERLINK("#Technical!A"&MATCH(A91,Technical!A:A,0),"Open"),HYPERLINK("#Technical!A1","Open")) -> Open
A92: https://africanmarketingconfederation.org/amc-conference-2023/amc-awards-book-now | B92: 13164 | C92: https://africanmarketingconfederation.org/wp-admin/post.php?post=13164&action=edit | D92: Schema | E92: Observation | F92: No FAQ/QA schema | G92: 37 | H92: FALSE | I92: True when page has Q&A intent | J92: If content is Q&A style, add FAQPage/QAPage schema in AIOSEO and keep markup aligned with on-page content. | K92: AEO | L92: QAPage/FAQ Schema Present | M92: No | N92: Copy Writer | O92: Open | P92: 4 | Q92: https://africanmarketingconfederation.org/amc-conference-2023/amc-awards-book-now::aioseo_no_faq_qa_schema | R92: Q&A schema can improve eligibility for answer-rich results. | S92: =IFERROR(HYPERLINK("#Main!A"&MATCH(A92,Main!A:A,0),"Open"),HYPERLINK("#Main!A1","Open")) -> Open | T92: =IFERROR(HYPERLINK("#Technical!A"&MATCH(A92,Technical!A:A,0),"Open"),HYPERLINK("#Technical!A1","Open")) -> Open
A93: https://africanmarketingconfederation.org/ | B93: 8 | C93: https://africanmarketingconfederation.org/wp-admin/post.php?post=8&action=edit | D93: Title | E93: Observation | F93: SEO title too long | G93: 37 | H93: 66 | I93: 40-60 characters | J93: Shorten title in AIOSEO snippet editor and keep key terms in the first 55-60 characters. | K93: Main | L93: Title | M93: No | N93: Copy Writer | O93: Open | P93: 4 | Q93: https://africanmarketingconfederation.org/::aioseo_seo_title_too_long | R93: Long titles are more likely to truncate in SERPs. | S93: =IFERROR(HYPERLINK("#Main!A"&MATCH(A93,Main!A:A,0),"Open"),HYPERLINK("#Main!A1","Open")) -> Open | T93: =IFERROR(HYPERLINK("#Technical!A"&MATCH(A93,Technical!A:A,0),"Open"),HYPERLINK("#Technical!A1","Open")) -> Open
A94: https://africanmarketingconfederation.org/about-us | B94: 84 | C94: https://africanmarketingconfederation.org/wp-admin/post.php?post=84&action=edit | D94: Title | E94: Observation | F94: SEO title too long | G94: 37 | H94: 107 | I94: 40-60 characters | J94: Shorten title in AIOSEO snippet editor and keep key terms in the first 55-60 characters. | K94: Main | L94: Title | M94: No | N94: Copy Writer | O94: Open | P94: 4 | Q94: https://africanmarketingconfederation.org/about-us::aioseo_seo_title_too_long | R94: Long titles are more likely to truncate in SERPs. | S94: =IFERROR(HYPERLINK("#Main!A"&MATCH(A94,Main!A:A,0),"Open"),HYPERLINK("#Main!A1","Open")) -> Open | T94: =IFERROR(HYPERLINK("#Technical!A"&MATCH(A94,Technical!A:A,0),"Open"),HYPERLINK("#Technical!A1","Open")) -> Open
A95: https://africanmarketingconfederation.org/african-marketing-confederation-tourism-chapter | B95: 28165 | C95: https://africanmarketingconfederation.org/wp-admin/post.php?post=28165&action=edit | D95: Title | E95: Observation | F95: SEO title too long | G95: 37 | H95: 81 | I95: 40-60 characters | J95: Shorten title in AIOSEO snippet editor and keep key terms in the first 55-60 characters. | K95: Main | L95: Title | M95: No | N95: Copy Writer | O95: Open | P95: 4 | Q95: https://africanmarketingconfederation.org/african-marketing-confederation-tourism-chapter::aioseo_seo_title_too_long | R95: Long titles are more likely to truncate in SERPs. | S95: =IFERROR(HYPERLINK("#Main!A"&MATCH(A95,Main!A:A,0),"Open"),HYPERLINK("#Main!A1","Open")) -> Open | T95: =IFERROR(HYPERLINK("#Technical!A"&MATCH(A95,Technical!A:A,0),"Open"),HYPERLINK("#Technical!A1","Open")) -> Open
A96: https://africanmarketingconfederation.org/amc-conference-2022-prospectus | B96: 5619 | C96: https://africanmarketingconfederation.org/wp-admin/post.php?post=5619&action=edit | D96: Title | E96: Observation | F96: SEO title too long | G96: 37 | H96: 66 | I96: 40-60 characters | J96: Shorten title in AIOSEO snippet editor and keep key terms in the first 55-60 characters. | K96: Main | L96: Title | M96: No | N96: Copy Writer | O96: Open | P96: 4 | Q96: https://africanmarketingconfederation.org/amc-conference-2022-prospectus::aioseo_seo_title_too_long | R96: Long titles are more likely to truncate in SERPs. | S96: =IFERROR(HYPERLINK("#Main!A"&MATCH(A96,Main!A:A,0),"Open"),HYPERLINK("#Main!A1","Open")) -> Open | T96: =IFERROR(HYPERLINK("#Technical!A"&MATCH(A96,Technical!A:A,0),"Open"),HYPERLINK("#Technical!A1","Open")) -> Open
A97: https://africanmarketingconfederation.org/amc-conference-2022-thank-you | B97: 4941 | C97: https://africanmarketingconfederation.org/wp-admin/post.php?post=4941&action=edit | D97: Title | E97: Observation | F97: SEO title too long | G97: 37 | H97: 65 | I97: 40-60 characters | J97: Shorten title in AIOSEO snippet editor and keep key terms in the first 55-60 characters. | K97: Main | L97: Title | M97: No | N97: Copy Writer | O97: Open | P97: 4 | Q97: https://africanmarketingconfederation.org/amc-conference-2022-thank-you::aioseo_seo_title_too_long | R97: Long titles are more likely to truncate in SERPs. | S97: =IFERROR(HYPERLINK("#Main!A"&MATCH(A97,Main!A:A,0),"Open"),HYPERLINK("#Main!A1","Open")) -> Open | T97: =IFERROR(HYPERLINK("#Technical!A"&MATCH(A97,Technical!A:A,0),"Open"),HYPERLINK("#Technical!A1","Open")) -> Open

Sheet Security
A1: URL | B1: Strict-Transport-Security | C1: Content-Security-Policy | D1: X-Content-Type-Options | E1: X-Frame-Options | F1: Referrer-Policy | G1: Permissions-Policy | H1: Robots.txt Accessible | I1: Sitemap in Robots.txt | J1: Robots.txt Crawl-Delay | K1: Robots.txt Disallow / | L1: Open in Main | M1: BACK TO DASHBOARD
A2: https://africanmarketingconfederation.org/african-marketing-confederation-tourism-chapter | L2: =IFERROR(HYPERLINK("#Main!A"&MATCH(A2,Main!A:A,0),"Open"),HYPERLINK("#Main!A1","Open")) -> Open
A3: https://africanmarketingconfederation.org/ | L3: =IFERROR(HYPERLINK("#Main!A"&MATCH(A3,Main!A:A,0),"Open"),HYPERLINK("#Main!A1","Open")) -> Open
A4: https://africanmarketingconfederation.org/about-us | L4: =IFERROR(HYPERLINK("#Main!A"&MATCH(A4,Main!A:A,0),"Open"),HYPERLINK("#Main!A1","Open")) -> Open
A5: https://africanmarketingconfederation.org/amc-awards-2024 | L5: =IFERROR(HYPERLINK("#Main!A"&MATCH(A5,Main!A:A,0),"Open"),HYPERLINK("#Main!A1","Open")) -> Open
A6: https://africanmarketingconfederation.org/amc-conference-2022-prospectus | L6: =IFERROR(HYPERLINK("#Main!A"&MATCH(A6,Main!A:A,0),"Open"),HYPERLINK("#Main!A1","Open")) -> Open
A7: https://africanmarketingconfederation.org/amc-conference-2022 | L7: =IFERROR(HYPERLINK("#Main!A"&MATCH(A7,Main!A:A,0),"Open"),HYPERLINK("#Main!A1","Open")) -> Open
A8: https://africanmarketingconfederation.org/amc-conference-2022-thank-you | L8: =IFERROR(HYPERLINK("#Main!A"&MATCH(A8,Main!A:A,0),"Open"),HYPERLINK("#Main!A1","Open")) -> Open
A9: https://africanmarketingconfederation.org/amc-conference-2023 | L9: =IFERROR(HYPERLINK("#Main!A"&MATCH(A9,Main!A:A,0),"Open"),HYPERLINK("#Main!A1","Open")) -> Open
A10: https://africanmarketingconfederation.org/amc-conference-2023/amc-awards | L10: =IFERROR(HYPERLINK("#Main!A"&MATCH(A10,Main!A:A,0),"Open"),HYPERLINK("#Main!A1","Open")) -> Open
A11: https://africanmarketingconfederation.org/amc-conference-2023/amc-awards-book-now | L11: =IFERROR(HYPERLINK("#Main!A"&MATCH(A11,Main!A:A,0),"Open"),HYPERLINK("#Main!A1","Open")) -> Open

Sheet Summary
A1: Section | B1: Severity | C1: Issue | D1: Affected URL Count | E1: Reference Tab | F1: Affected URLs (sample) | G1: BACK TO DASHBOARD
A2: AEO Opportunities | B2: Warning | C2: Low AEO Readiness Score | D2: 10 | E2: AEO | F2: https://africanmarketingconfederation.org/african-marketing-confederation-tourism-chapter | https://africanmarketingconfederation.org/ | https://africanmarketingconfederation.org/about-us | https://africanmarketingconfederation.org/amc-awards-2024 | https://africanmarketingconfederation.org/amc-conference-2022-prospectus | https://africanmarketingconfederation.org/amc-conference-2022 | https://africanmarketingconfederation.org/amc-conference-2022-thank-you | https://africanmarketingconfederation.org/amc-conference-2023 | https://africanmarketingconfederation.org/amc-conference-2023/amc-awards | https://africanmarketingconfederation.org/amc-conference-2023/amc-awards-book-now || Full list: see AEO tab
A3: AEO Opportunities | B3: Warning | C3: Missing FAQ/QA Schema | D3: 0 | E3: AEO | F3: || Full list: see AEO tab
A4: AEO Opportunities | B4: Observation | C4: No 40-60 Word Answer Paragraphs | D4: 10 | E4: AEO | F4: https://africanmarketingconfederation.org/african-marketing-confederation-tourism-chapter | https://africanmarketingconfederation.org/ | https://africanmarketingconfederation.org/about-us | https://africanmarketingconfederation.org/amc-awards-2024 | https://africanmarketingconfederation.org/amc-conference-2022-prospectus | https://africanmarketingconfederation.org/amc-conference-2022 | https://africanmarketingconfederation.org/amc-conference-2022-thank-you | https://africanmarketingconfederation.org/amc-conference-2023 | https://africanmarketingconfederation.org/amc-conference-2023/amc-awards | https://africanmarketingconfederation.org/amc-conference-2023/amc-awards-book-now || Full list: see AEO tab
A5: AEO Opportunities | B5: Observation | C5: No Answer-Friendly Structure | D5: 10 | E5: AEO | F5: https://africanmarketingconfederation.org/african-marketing-confederation-tourism-chapter | https://africanmarketingconfederation.org/ | https://africanmarketingconfederation.org/about-us | https://africanmarketingconfederation.org/amc-awards-2024 | https://africanmarketingconfederation.org/amc-conference-2022-prospectus | https://africanmarketingconfederation.org/amc-conference-2022 | https://africanmarketingconfederation.org/amc-conference-2022-thank-you | https://africanmarketingconfederation.org/amc-conference-2023 | https://africanmarketingconfederation.org/amc-conference-2023/amc-awards | https://africanmarketingconfederation.org/amc-conference-2023/amc-awards-book-now || Full list: see AEO tab
A6: AEO Opportunities | B6: Observation | C6: No Question Headings | D6: 10 | E6: AEO | F6: https://africanmarketingconfederation.org/african-marketing-confederation-tourism-chapter | https://africanmarketingconfederation.org/ | https://africanmarketingconfederation.org/about-us | https://africanmarketingconfederation.org/amc-awards-2024 | https://africanmarketingconfederation.org/amc-conference-2022-prospectus | https://africanmarketingconfederation.org/amc-conference-2022 | https://africanmarketingconfederation.org/amc-conference-2022-thank-you | https://africanmarketingconfederation.org/amc-conference-2023 | https://africanmarketingconfederation.org/amc-conference-2023/amc-awards | https://africanmarketingconfederation.org/amc-conference-2023/amc-awards-book-now || Full list: see AEO tab
A7: AEO Opportunities | F7: Detailed rows: see AEO tab
A8: Issue Counts | B8: Critical | C8: Broken Internal Links | D8: 10 | E8: Links | F8: https://africanmarketingconfederation.org/african-marketing-confederation-tourism-chapter | https://africanmarketingconfederation.org/ | https://africanmarketingconfederation.org/about-us | https://africanmarketingconfederation.org/amc-awards-2024 | https://africanmarketingconfederation.org/amc-conference-2022-prospectus | https://africanmarketingconfederation.org/amc-conference-2022 | https://africanmarketingconfederation.org/amc-conference-2022-thank-you | https://africanmarketingconfederation.org/amc-conference-2023 | https://africanmarketingconfederation.org/amc-conference-2023/amc-awards | https://africanmarketingconfederation.org/amc-conference-2023/amc-awards-book-now || Full list: see Technical/Links/Indexability tabs
A9: Issue Counts | B9: Critical | C9: CWV LCP Above 4.0s | D9: 0 | E9: Technical | F9: || Full list: see Technical/Links/Indexability tabs
A10: Issue Counts | B10: Critical | C10: Canonical Points Elsewhere | D10: 0 | E10: Indexability | F10: || Full list: see Technical/Links/Indexability tabs
A11: Issue Counts | B11: Critical | C11: Missing Title | D11: 0 | E11: Technical | F11: || Full list: see Technical/Links/Indexability tabs
A12: Issue Counts | B12: Critical | C12: Noindex Directive | D12: 0 | E12: Indexability | F12: || Full list: see Technical/Links/Indexability tabs
A13: Issue Counts | B13: Critical | C13: Non-200 Status | D13: 0 | E13: Technical | F13: || Full list: see Technical/Links/Indexability tabs
A14: Issue Counts | B14: Critical | C14: Robots.txt Disallow Root | D14: 0 | E14: Technical | F14: || Full list: see Technical/Links/Indexability tabs
A15: Issue Counts | B15: Warning | C15: Low AEO Readiness Score | D15: 10 | E15: AEO | F15: https://africanmarketingconfederation.org/african-marketing-confederation-tourism-chapter | https://africanmarketingconfederation.org/ | https://africanmarketingconfederation.org/about-us | https://africanmarketingconfederation.org/amc-awards-2024 | https://africanmarketingconfederation.org/amc-conference-2022-prospectus | https://africanmarketingconfederation.org/amc-conference-2022 | https://africanmarketingconfederation.org/amc-conference-2022-thank-you | https://africanmarketingconfederation.org/amc-conference-2023 | https://africanmarketingconfederation.org/amc-conference-2023/amc-awards | https://africanmarketingconfederation.org/amc-conference-2023/amc-awards-book-now || Full list: see Technical/Links/Indexability tabs
A16: Issue Counts | B16: Warning | C16: Low Image Alt Coverage | D16: 10 | E16: Technical | F16: https://africanmarketingconfederation.org/african-marketing-confederation-tourism-chapter | https://africanmarketingconfederation.org/ | https://africanmarketingconfederation.org/about-us | https://africanmarketingconfederation.org/amc-awards-2024 | https://africanmarketingconfederation.org/amc-conference-2022-prospectus | https://africanmarketingconfederation.org/amc-conference-2022 | https://africanmarketingconfederation.org/amc-conference-2022-thank-you | https://africanmarketingconfederation.org/amc-conference-2023 | https://africanmarketingconfederation.org/amc-conference-2023/amc-awards | https://africanmarketingconfederation.org/amc-conference-2023/amc-awards-book-now || Full list: see Technical/Links/Indexability tabs
A17: Issue Counts | B17: Warning | C17: Missing H1 | D17: 4 | E17: Technical | F17: https://africanmarketingconfederation.org/amc-conference-2022-prospectus | https://africanmarketingconfederation.org/amc-conference-2022 | https://africanmarketingconfederation.org/amc-conference-2022-thank-you | https://africanmarketingconfederation.org/amc-conference-2023/amc-awards-book-now || Full list: see Technical/Links/Indexability tabs
A18: Issue Counts | B18: Warning | C18: Multiple H1 | D18: 3 | E18: Technical | F18: https://africanmarketingconfederation.org/african-marketing-confederation-tourism-chapter | https://africanmarketingconfederation.org/ | https://africanmarketingconfederation.org/amc-awards-2024 || Full list: see Technical/Links/Indexability tabs
A19: Issue Counts | B19: Warning | C19: Missing Meta Description | D19: 1 | E19: Technical | F19: https://africanmarketingconfederation.org/amc-conference-2023/amc-awards-book-now || Full list: see Technical/Links/Indexability tabs
... A41: Issue Counts | B41: Observation | C41: llms.txt Missing | D41: 0 | E41: Technical | F41: || Full list: see Technical/Links/Indexability tabs
A42: Issue Counts
A43: Top 10 Critical URLs
A44: Top 10 Critical URLs | B44: Critical | C44: #1 https://africanmarketingconfederation.org/amc-conference-2023/amc-awards-book-now | D44: 1 | E44: Priority URLs | F44: Broken Internal Links | Missing Meta Description | Missing H1 | Low Image Alt Coverage | Low AEO Readiness Score | No ETag Header | Thin Content | No Question Headings | No Answer-Friendly Structure | No 40-60 Word Answer Paragraphs | AI Crawlers Not Explicitly Allowed
A45: Top 10 Critical URLs | B45: Critical | C45: #2 https://africanmarketingconfederation.org/ | D45: 1 | E45: Priority URLs | F45: Broken Internal Links | Multiple H1 | Low Image Alt Coverage | Low AEO Readiness Score | Generic Anchor Text Present | No ETag Header | Thin Content | No Question Headings | No Answer-Friendly Structure | No 40-60 Word Answer Paragraphs | AI Crawlers Not Explicitly Allowed
A46: Top 10 Critical URLs | B46: Critical | C46: #3 https://africanmarketingconfederation.org/amc-conference-2022-prospectus | D46: 1 | E46: Priority URLs | F46: Broken Internal Links | Missing H1 | Low Image Alt Coverage | Low AEO Readiness Score | No ETag Header | Thin Content | No Question Headings | No Answer-Friendly Structure | No 40-60 Word Answer Paragraphs | AI Crawlers Not Explicitly Allowed
A47: Top 10 Critical URLs | B47: Critical | C47: #4 https://africanmarketingconfederation.org/amc-conference-2022 | D47: 1 | E47: Priority URLs | F47: Broken Internal Links | Missing H1 | Low Image Alt Coverage | Low AEO Readiness Score | No ETag Header | Thin Content | No Question Headings | No Answer-Friendly Structure | No 40-60 Word Answer Paragraphs | AI Crawlers Not Explicitly Allowed
A48: Top 10 Critical URLs | B48: Critical | C48: #5 https://africanmarketingconfederation.org/african-marketing-confederation-tourism-chapter | D48: 1 | E48: Priority URLs | F48: Broken Internal Links | Multiple H1 | Low Image Alt Coverage | Low AEO Readiness Score | No ETag Header | No Question Headings | No Answer-Friendly Structure | No 40-60 Word Answer Paragraphs | AI Crawlers Not Explicitly Allowed
A49: Top 10 Critical URLs | B49: Critical | C49: #6 https://africanmarketingconfederation.org/amc-awards-2024 | D49: 1 | E49: Priority URLs | F49: Broken Internal Links | Multiple H1 | Low Image Alt Coverage | Low AEO Readiness Score | No ETag Header | No Question Headings | No Answer-Friendly Structure | No 40-60 Word Answer Paragraphs | AI Crawlers Not Explicitly Allowed
A50: Top 10 Critical URLs | B50: Critical | C50: #7 https://africanmarketingconfederation.org/amc-conference-2022-thank-you | D50: 1 | E50: Priority URLs | F50: Broken Internal Links | Missing H1 | Low Image Alt Coverage | Low AEO Readiness Score | No ETag Header | No Question Headings | No Answer-Friendly Structure | No 40-60 Word Answer Paragraphs | AI Crawlers Not Explicitly Allowed
A51: Top 10 Critical URLs | B51: Critical | C51: #8 https://africanmarketingconfederation.org/about-us | D51: 1 | E51: Priority URLs | F51: Broken Internal Links | Low Image Alt Coverage | Low AEO Readiness Score | No ETag Header | Thin Content | No Question Headings | No Answer-Friendly Structure | No 40-60 Word Answer Paragraphs | AI Crawlers Not Explicitly Allowed
A52: Top 10 Critical URLs | B52: Critical | C52: #9 https://africanmarketingconfederation.org/amc-conference-2023 | D52: 1 | E52: Priority URLs | F52: Broken Internal Links | Low Image Alt Coverage | Low AEO Readiness Score | No ETag Header | No Question Headings | No Answer-Friendly Structure | No 40-60 Word Answer Paragraphs | AI Crawlers Not Explicitly Allowed
A53: Top 10 Critical URLs | B53: Critical | C53: #10 https://africanmarketingconfederation.org/amc-conference-2023/amc-awards | D53: 1 | E53: Priority URLs | F53: Broken Internal Links | Low Image Alt Coverage | Low AEO Readiness Score | No ETag Header | No Question Headings | No Answer-Friendly Structure | No 40-60 Word Answer Paragraphs | AI Crawlers Not Explicitly Allowed
A54: Top Issues by Template
A55: Top Issues by Template | B55: Observation | C55: /amc-conference-2023/ -> Broken Internal Links | D55: 3 | E55: Pattern and Template Issues
A56: Top Issues by Template | B56: Observation | C56: /amc-conference-2023/ -> Low Image Alt Coverage | D56: 3 | E56: Pattern and Template Issues
A57: Top Issues by Template | B57: Observation | C57: /amc-conference-2023/ -> Low AEO Readiness Score | D57: 3 | E57: Pattern and Template Issues
A58: Top Issues by Template | B58: Observation | C58: /amc-conference-2023/ -> No ETag Header | D58: 3 | E58: Pattern and Template Issues
A59: Top Issues by Template | B59: Observation | C59: /amc-conference-2023/ -> No Question Headings | D59: 3 | E59: Pattern and Template Issues
A60: Top Issues by Template | B60: Observation | C60: /amc-conference-2023/ -> No Answer-Friendly Structure | D60: 3 | E60: Pattern and Template Issues
A61: Top Issues by Template | B61: Observation | C61: /amc-conference-2023/ -> No 40-60 Word Answer Paragraphs | D61: 3 | E61: Pattern and Template Issues
A62: Top Issues by Template | B62: Observation | C62: /amc-conference-2023/ -> AI Crawlers Not Explicitly Allowed | D62: 3 | E62: Pattern and Template Issues
A63: Top Issues by Template | B63: Observation | C63: /amc-conference-2023/ -> Missing Meta Description | D63: 1 | E63: Pattern and Template Issues
A64: Top Issues by Template | B64: Observation | C64: /amc-conference-2023/ -> Missing H1 | D64: 1 | E64: Pattern and Template Issues
A65: Top Issues by Template | B65: Observation | C65: /amc-conference-2023/ -> Thin Content | D65: 1 | E65: Pattern and Template Issues
A66: Top Issues by Template | B66: Observation | C66: /african-marketing-confederation-tourism-chapter/ -> Broken Internal Links | D66: 1 | E66: Pattern and Template Issues
... A74: Top Issues by Template | B74: Observation | C74: /african-marketing-confederation-tourism-chapter/ -> AI Crawlers Not Explicitly Allowed | D74: 1 | E74: Pattern and Template Issues

Sheet LinksDetail
A1: Source URL | B1: Target URL | C1: Anchor Text | D1: Rel | E1: Link Type | F1: Nofollow | G1: Target Status (if crawled) | H1: Crawlable | I1: BACK TO DASHBOARD
A2: https://africanmarketingconfederation.org/african-marketing-confederation-tourism-chapter | B2: https://africanmarketingconfederation.org/ | E2: Internal | F2: FALSE | G2: 200 | H2: TRUE
A3: https://africanmarketingconfederation.org/african-marketing-confederation-tourism-chapter | B3: https://africanmarketingconfederation.org/ | C3: HOME | E3: Internal | F3: FALSE | G3: 200 | H3: TRUE
A4: https://africanmarketingconfederation.org/african-marketing-confederation-tourism-chapter | B4: https://africanmarketingconfederation.org/about-us | C4: ABOUT US | E4: Internal | F4: FALSE | G4: 200 | H4: TRUE
A5: https://africanmarketingconfederation.org/african-marketing-confederation-tourism-chapter | B5: https://africanmarketingconfederation.org/sub-committees | C5: AMC COMMITTEES | E5: Internal | F5: FALSE | G5: 200 | H5: TRUE
A6: https://africanmarketingconfederation.org/african-marketing-confederation-tourism-chapter | B6: https://africanmarketingconfederation.org/members | C6: MEMBERS | E6: Internal | F6: FALSE | G6: 200 | H6: TRUE
A7: https://africanmarketingconfederation.org/african-marketing-confederation-tourism-chapter | B7: https://africanmarketingconfederation.org/african-marketing-confederation-tourism-chapter | C7: TOURISM CHAPTER | E7: Internal | F7: FALSE | G7: 200 | H7: TRUE
A8: https://africanmarketingconfederation.org/african-marketing-confederation-tourism-chapter | B8: https://africanmarketingconfederation.org/education | C8: EDUCATION | E8: Internal | F8: FALSE | G8: 200 | H8: TRUE
A9: https://africanmarketingconfederation.org/african-marketing-confederation-tourism-chapter | B9: https://africanmarketingconfederation.org/chartered-marketer-africa | C9: CHARTERED MARKETER (AFRICA) | E9: Internal | F9: FALSE | G9: 200 | H9: TRUE
A10: https://africanmarketingconfederation.org/african-marketing-confederation-tourism-chapter | B10: https://africanmarketingconfederation.org/certified-professional-marketer-africa | C10: CPM(A) | E10: Internal | F10: FALSE | G10: 200 | H10: TRUE
A11: https://africanmarketingconfederation.org/african-marketing-confederation-tourism-chapter | B11: https://africanmarketingconfederation.org/news-articles | C11: NEWS & PUBLICATIONS | E11: Internal | F11: FALSE | G11: 200 | H11: TRUE
A12: https://africanmarketingconfederation.org/african-marketing-confederation-tourism-chapter | B12: https://africanmarketingconfederation.org/news-articles | C12: NEWS ARTICLES | E12: Internal | F12: FALSE | G12: 200 | H12: TRUE
A13: https://africanmarketingconfederation.org/african-marketing-confederation-tourism-chapter | B13: https://africanmarketingconfederation.org/publications-2 | C13: PUBLICATIONS | E13: Internal | F13: FALSE | G13: 200 | H13: TRUE
A14: https://africanmarketingconfederation.org/african-marketing-confederation-tourism-chapter | B14: https://africanmarketingconfederation.org/amc-conference-2026 | C14: AMC Conference | E14: Internal | F14: FALSE | G14: 200 | H14: TRUE
... A28: https://africanmarketingconfederation.org/african-marketing-confederation-tourism-chapter | B28: https://africanmarketingconfederation.org/contact-us | C28: CONTACT US | E28: Internal | F28: FALSE | G28: 200 | H28: TRUE
