Workbook

Sheet Table of Contents
A1: Table of Contents
A2: Section | B2: Open | C2: Description
A3: =HYPERLINK("#'Dashboard'!A1","Dashboard") -> Dashboard | B3: =HYPERLINK("#'Dashboard'!A1","Open") -> Open | C3: Executive overview of site-wide SEO performance and critical alerts.
A4: =HYPERLINK("#'Content Optimisation Hub'!A1","Content Optimisation Hub") -> Content Optimisation Hub | B4: =HYPERLINK("#'Content Optimisation Hub'!A1","Open") -> Open | C4: Diagnostic command center: live title, meta, and H1–H6 health plus on-page score.
A5: =HYPERLINK("#'FixPlan'!A1","FixPlan") -> FixPlan | B5: =HYPERLINK("#'FixPlan'!A1","Open") -> Open | C5: Prioritized list of technical and content fixes with estimated effort.
A6: =HYPERLINK("#'Main'!A1","Main") -> Main | B6: =HYPERLINK("#'Main'!A1","Open") -> Open | C6: Primary URL inventory with titles, meta descriptions, and crawl signals.
A7: =HYPERLINK("#'Priority URLs'!A1","Priority URLs") -> Priority URLs | B7: =HYPERLINK("#'Priority URLs'!A1","Open") -> Open | C7: High-value pages requiring immediate attention based on business risk.
A8: =HYPERLINK("#'AIOSEO'!A1","AIOSEO") -> AIOSEO | B8: =HYPERLINK("#'AIOSEO'!A1","Open") -> Open | C8: Plugin-aligned recommendations and edit links for AIOSEO users.
A9: =HYPERLINK("#'Link Inventory'!A1","Link Inventory") -> Link Inventory | B9: =HYPERLINK("#'Link Inventory'!A1","Open") -> Open | C9: Every anchor-level outbound link with type, rel attributes, status codes, and generic-anchor flags.
A10: =HYPERLINK("#'SitemapQA'!A1","SitemapQA") -> SitemapQA | B10: =HYPERLINK("#'SitemapQA'!A1","Open") -> Open | C10: Sitemap coverage, URL membership checks, and sitemap metadata QA.
A11: =HYPERLINK("#'ResolvedIssues'!A1","ResolvedIssues") -> ResolvedIssues | B11: =HYPERLINK("#'ResolvedIssues'!A1","Open") -> Open | C11: Issues marked resolved when compared to the previous export.
A12: =HYPERLINK("#'DeltaFromPreviousRun'!A1","DeltaFromPreviousRun") -> DeltaFromPreviousRun | B12: =HYPERLINK("#'DeltaFromPreviousRun'!A1","Open") -> Open | C12: New, fixed, and persistent issues compared to a prior audit workbook.
A13: =HYPERLINK("#'RunMetadata'!A1","RunMetadata") -> RunMetadata | B13: =HYPERLINK("#'RunMetadata'!A1","Open") -> Open | C13: Run configuration, timestamps, and environment notes.
A14: =HYPERLINK("#'Issue Register'!A1","Issue Register") -> Issue Register | B14: =HYPERLINK("#'Issue Register'!A1","Open") -> Open | C14: Diagnostic metrics for Issue Register.
A15: =HYPERLINK("#'Technical Diagnostics'!A1","Technical Diagnostics") -> Technical Diagnostics | B15: =HYPERLINK("#'Technical Diagnostics'!A1","Open") -> Open | C15: Diagnostic metrics for Technical Diagnostics.
A16: =HYPERLINK("#'Content & AI Readiness'!A1","Content & AI Readiness") -> Content & AI Readiness | B16: =HYPERLINK("#'Content & AI Readiness'!A1","Open") -> Open | C16: Diagnostic metrics for Content & AI Readiness.
A17: =HYPERLINK("#'Link Intelligence'!A1","Link Intelligence") -> Link Intelligence | B17: =HYPERLINK("#'Link Intelligence'!A1","Open") -> Open | C17: Diagnostic metrics for Link Intelligence.
A18: =HYPERLINK("#'Template & Duplication Risks'!A1","Template & Duplication Risks") -> Template & Duplication Risks | B18: =HYPERLINK("#'Template & Duplication Risks'!A1","Open") -> Open | C18: Diagnostic metrics for Template & Duplication Risks.
A19: =HYPERLINK("#'Playbook'!A1","Playbook") -> Playbook | B19: =HYPERLINK("#'Playbook'!A1","Open") -> Open | C19: Diagnostic metrics for Playbook.

Sheet Dashboard
A1: Executive SEO & AEO Performance Report
A2: Executive SEO & AEO Dashboard
A4: EXECUTIVE METRICS | B4: Value | D4: Status | E4: Count | G4: Traditional SEO vs. 2026 AEO Readiness | I4: BUSINESS IMPACT SUMMARY | M4: PRIORITY SNAPSHOT | N4: Value
A5: =HYPERLINK("#'Main'!A1","Average SEO Score") -> Average SEO Score | B5: =IFERROR(AVERAGE(INDEX(Main!$1:$1048576,0,MATCH("SEO Score",Main!$1:$1,0))),IFERROR(AVERAGE(INDEX(Main!$1:$1048576,0,MATCH("SEO Health Score",Main!$1:$1,0))),0))/100 -> 0.70312 | D5: 200 OK | E5: 0 | G5: Dimension | H5: Score | I5: ⚠️ Link Integrity Risk: 47 broken links found. The most impacted destination is https://africanmarketingconfederation.org/amc-confer ence-2025-delegate-packages. ⚡ Performance Audit: PSI data was not collected in this run. A full Performance Pass is recommended to identify mobile load-time bottlenecks. 🤖 AEO Opportunity: Your content is currently 55% optimized for AI-Search, leaving a 45% opportunity for improvement. | M5: Primary blocking issue | N5: No ETag Header
A6: =HYPERLINK("#'Technical Diagnostics'!A1","Technical Health") -> Technical Health | B6: =AVERAGE('Technical Diagnostics'!E:E)/100 -> 0.665 | D6: 3xx Redirects | E6: 0 | G6: Traditional SEO | H6: 0 | M6: Top Issue Affected URLs | N6: 20
A7: =HYPERLINK("#'Technical Diagnostics'!A1","Performance (PSI)") -> Performance (PSI) | B7: =IFERROR((IFERROR(AVERAGE(INDEX('Technical Diagnostics'!$1:$1048576,0,MATCH("Mobile PSI Score",'Technical Diagnostics'!$1:$1,0))),0)+IFERROR(AVERAGE(INDEX('Technical Diagnostics'!$1:$1048576,0,MATCH("Desktop PSI Score",'Technical Diagnostics'!$1:$1,0))),0))/2,0)/100 -> 0 | D7: 4xx Errors | E7: 0 | G7: 2026 AEO Readiness | H7: 0 | M7: 4xx/5xx URLs | N7: 0
A8: =HYPERLINK("#'Technical Diagnostics'!A1","Mobile vs. Desktop Variance") -> Mobile vs. Desktop Variance | B8: =IFERROR(AVERAGE('Technical Diagnostics'!S:S)-AVERAGE('Technical Diagnostics'!R:R),0) -> 0 | D8: 5xx Errors | E8: 0 | M8: Avg TTFB (ms) | N8: 0
A9: =HYPERLINK("#'Priority URLs'!A1","Critical URLs") -> Critical URLs | B9: =COUNTIFS('Technical Diagnostics'!$D:$D,"Critical") -> 0 | D9: Other | E9: 0 | G9: Strategic Narrative
A10: =HYPERLINK("#'Technical Diagnostics'!A1","Warning URLs") -> Warning URLs | B10: =COUNTIFS('Technical Diagnostics'!$D:$D,"Warning")+COUNTIFS('Technical Diagnostics'!$D:$D,"Needs Work") -> 20 | G10: Critical technical debt is currently the primary barrier to growth.
A11: =HYPERLINK("#'Technical Diagnostics'!A1","Error Rate % (4xx/5xx)") -> Error Rate % (4xx/5xx) | B11: =IFERROR((COUNTIFS('Technical Diagnostics'!$C:$C,">=400",'Technical Diagnostics'!$C:$C,"<500")+COUNTIFS('Technical Diagnostics'!$C:$C,">=500",'Technical Diagnostics'!$C:$C,"<600"))/COUNTIFS('Technical Diagnostics'!$C:$C,">0"),0) -> 0
A12: =HYPERLINK("#'Technical Diagnostics'!A1","Crawl Success Rate % (2xx)") -> Crawl Success Rate % (2xx) | B12: =IFERROR(COUNTIFS('Technical Diagnostics'!$C:$C,">=200",'Technical Diagnostics'!$C:$C,"<300")/COUNTIFS('Technical Diagnostics'!$C:$C,">0"),0) -> 1 | D12: Severity | E12: Count | I12: Quick Navigation | J12: Open
A13: =HYPERLINK("#'Technical Diagnostics'!A1","Critical URL Rate %") -> Critical URL Rate % | B13: =IFERROR(B9/(COUNTA('Technical Diagnostics'!$A:$A)-1),0) -> 0 | D13: Critical | E13: 7 | I13: Fix Plan | J13: =HYPERLINK("#FixPlan!A1","Open") -> Open
A14: =HYPERLINK("#'Technical Diagnostics'!A1","Warning URL Rate %") -> Warning URL Rate % | B14: =IFERROR(B10/(COUNTA('Technical Diagnostics'!$A:$A)-1),0) -> 1 | D14: Warning | E14: 12 | G14: TOP ISSUES TO FIX FIRST | H14: Affected URLs | I14: Main URL Data | J14: =HYPERLINK("#Main!A1","Open") -> Open
A15: Projected Health Score % (if all To Do done) | B15: =MIN(1,B5+(B9*0.01)) -> 0.70312 | D15: Medium | E15: 0 | G15: =HYPERLINK("#FixPlan!A6","Low AEO Readiness Score") -> Low AEO Readiness Score | H15: 20 | I15: Technical Diagnostics | J15: =HYPERLINK("#'Technical Diagnostics'!A1","Open") -> Open
A16: Projected Pass Rate % (if all To Do done) | B16: =MIN(1,B7+(B9*0.01)) -> 0 | D16: Low | E16: 15 | G16: =HYPERLINK("#FixPlan!A5","AI Crawlers Not Explicitly Allowed") -> AI Crawlers Not Explicitly Allowed | H16: 20 | I16: Indexability | J16: =HYPERLINK("#'Technical Diagnostics'!A1","Open") -> Open
A17: =HYPERLINK("#'Content Optimisation Hub'!A1","Content Hub Readiness (%)") -> Content Hub Readiness (%) | B17: =IF(COUNTA('Content Optimisation Hub'!F3:F10000)=0,0,COUNTIF('Content Optimisation Hub'!F3:F10000,"Completed")/COUNTA('Content Optimisation Hub'!F3:F10000)) -> 0 | G17: =HYPERLINK("#FixPlan!A4","No 40-60 Word Answer Paragraphs") -> No 40-60 Word Answer Paragraphs | H17: 20 | I17: AEO Opportunities | J17: =HYPERLINK("#'Content & AI Readiness'!A1","Open") -> Open
A18: =HYPERLINK("#'Main'!A1","URLs with Schema") -> URLs with Schema | B18: =COUNTIF(Main!Q2:Q10000,TRUE) -> 0 | G18: =HYPERLINK("#FixPlan!A3","No Question Headings") -> No Question Headings | H18: 20 | I18: AIOSEO Action Queue | J18: =HYPERLINK("#AIOSEO!A1","Open") -> Open
A19: =HYPERLINK("#'Content & AI Readiness'!A1","AEO Opportunity Gap") -> AEO Opportunity Gap | B19: =MAX(0, IF(IFERROR(AVERAGE(INDEX('Content & AI Readiness'!$1:$1048576,0,MATCH("AEO Extractability Score",'Content & AI Readiness'!$1:$1,0))),0)>0, 100-IFERROR(AVERAGE(INDEX('Content & AI Readiness'!$1:$1048576,0,MATCH("AEO Extractability Score",'Content & AI Readiness'!$1:$1,0))),0), (1-IFERROR(B5,0))*100)) -> 45 | G19: =HYPERLINK("#FixPlan!A2","No ETag Header") -> No ETag Header | H19: 20 | I19: Content Hub | J19: =HYPERLINK("#'Content Optimisation Hub'!A1","Open") -> Open
A20: =HYPERLINK("#'Link Inventory'!A1","Broken Internal Links") -> Broken Internal Links | B20: =SUM(COUNTIFS('Link Inventory'!$E:$E,"Internal",'Link Inventory'!$F:$F,404),COUNTIFS('Link Inventory'!$E:$E,"Internal",'Link Inventory'!$F:$F,"404")) -> 94 | I20: Tech Diagnostics | J20: =HYPERLINK("#'Technical Diagnostics'!A1","Open") -> Open
A21: =HYPERLINK("#'Link Intelligence'!A1","Generic Anchor Links (Total)") -> Generic Anchor Links (Total) | B21: =SUMIFS('Link Intelligence'!$O:$O,'Link Intelligence'!$B:$B,"Summary") -> 2 | I21: Issue Register | J21: =HYPERLINK("#'Issue Register'!A1","Open") -> Open
A22: =HYPERLINK("#'Link Inventory'!A1","External Link Health %") -> External Link Health % | B22: =IF(IFERROR(INDEX(RunMetadata!$B:$B,MATCH("External Sniff Performed",RunMetadata!$A:$A,0)),0)=0,"",IF(IFERROR(INDEX(RunMetadata!$B:$B,MATCH("External Link Unique Denominator",RunMetadata!$A:$A,0)),0)=0,"",IFERROR(IFERROR(INDEX(RunMetadata!$B:$B,MATCH("External Link Unique 200 OK",RunMetadata!$A:$A,0)),0)/IFERROR(INDEX(RunMetadata!$B:$B,MATCH("External Link Unique Denominator",RunMetadata!$A:$A,0)),1),0))) -> 0.89552239 | G22: OWNER ISSUE SUMMARY
G23: Owner | H23: Issue Rows | I23: Affected URLs | J23: Critical | K23: Warning
G24: =HYPERLINK("#'FixPlan'!A1","Copy Writer") -> Copy Writer | H24: 20 | I24: 121 | J24: 1 | K24: 8
A25: CRAWL METADATA | B25: Value | G25: =HYPERLINK("#'FixPlan'!A1","Server/Host") -> Server/Host | H25: 5 | I25: 20 | J25: 2 | K25: 0
A26: Run Date | B26: =IFERROR(INDEX(RunMetadata!$B:$B,MATCH("Run Timestamp",RunMetadata!$A:$A,0)),"") -> 2026-05-09 14:58:03 | G26: =HYPERLINK("#'FixPlan'!A1","Dev") -> Dev | H26: 9 | I26: 0 | J26: 4 | K26: 4
A27: URL Count | B27: =IFERROR(INDEX(RunMetadata!$B:$B,MATCH("Total URLs",RunMetadata!$A:$A,0)),B5) -> 20
A28: Duration | B28: =IFERROR(INDEX(RunMetadata!$B:$B,MATCH("Duration (s)",RunMetadata!$A:$A,0)),"")

Sheet FixPlan
A1: Issue Type | B1: Severity | C1: Priority Score | D1: Affected Count | E1: Affected URLs | F1: Detail Reference Tab | G1: Resolution Type | H1: URL | I1: Recommended Fix | J1: Likely Root Cause | K1: Owner | L1: Agency Owner | M1: Effort | N1: Est. Hours | O1: Est. Sprint Points | P1: Aging/Priority | Q1: Status | R1: Verified By | S1: Date Resolved | T1: Revenue Risk | U1: Action Needed | V1: Jump to Details | W1: Sprint | X1: Category | Y1: Open in Main | Z1: Hub Status (Content Hub) | AA1: BACK TO DASHBOARD
A2: Non-200 Status | B2: Critical | C2: 105 | D2: 0 | F2: Technical Diagnostics | G2: Manual Content | I2: Fix status code, restore page, or implement correct redirect to canonical destination. | J2: URL returns 4xx/5xx or equivalent failure. | K2: Server/Host | L2: Server/Host | M2: M | N2: 10 | O2: 5 | P2: Immediate (Current Sprint) | Q2: To Do | T2: High Risk | U2: Yes | V2: Open in Main Tab | X2: SEO | Y2: =IFERROR(HYPERLINK("#'Main'!B"&MATCH(TRIM(H2),Main!B:B,0),"Open"),HYPERLINK("#'Main'!B1","Open")) -> Open | Z2: =IFERROR(INDEX('Content Optimisation Hub'!C:C,MATCH(H2,'Content Optimisation Hub'!F:F,0)),"Not in Hub") -> Not in Hub
A3: Missing Title | B3: Critical | C3: 105 | D3: 0 | F3: Technical Diagnostics | G3: Manual Content | I3: Add unique descriptive title on affected template/page type. | J3: Template/page missing title tag. | K3: Copy Writer | L3: Copy Writer | M3: M | N3: 10 | O3: 5 | P3: Immediate (Current Sprint) | Q3: To Do | T3: High Risk | U3: Yes | V3: Open in Main Tab | X3: SEO | Y3: =IFERROR(HYPERLINK("#'Main'!B"&MATCH(TRIM(H3),Main!B:B,0),"Open"),HYPERLINK("#'Main'!B1","Open")) -> Open | Z3: =IFERROR(INDEX('Content Optimisation Hub'!C:C,MATCH(H3,'Content Optimisation Hub'!F:F,0)),"Not in Hub") -> Not in Hub
A4: Noindex Directive | B4: Critical | C4: 105 | D4: 0 | F4: Technical Diagnostics | G4: Manual Content | I4: Remove unintended noindex directives on index-worthy URLs. | J4: Meta robots or X-Robots-Tag contains noindex. | K4: Dev | L4: Dev | M4: M | N4: 10 | O4: 5 | P4: Immediate (Current Sprint) | Q4: To Do | T4: High Risk | U4: Yes | V4: Open in Main Tab | X4: SEO | Y4: =IFERROR(HYPERLINK("#'Main'!B"&MATCH(TRIM(H4),Main!B:B,0),"Open"),HYPERLINK("#'Main'!B1","Open")) -> Open | Z4: =IFERROR(INDEX('Content Optimisation Hub'!C:C,MATCH(H4,'Content Optimisation Hub'!F:F,0)),"Not in Hub") -> Not in Hub
A5: Canonical Points Elsewhere | B5: Critical | C5: 105 | D5: 0 | F5: Technical Diagnostics | G5: Global Template | I5: Align canonical to preferred final URL and ensure internal links use canonical target. | J5: Canonical targets a different URL variant. | K5: Dev | L5: Dev | M5: M | N5: 10 | O5: 5 | P5: Immediate (Current Sprint) | Q5: To Do | T5: High Risk | U5: Yes | V5: Open in Main Tab | X5: SEO | Y5: =IFERROR(HYPERLINK("#'Main'!B"&MATCH(TRIM(H5),Main!B:B,0),"Open"),HYPERLINK("#'Main'!B1","Open")) -> Open | Z5: =IFERROR(INDEX('Content Optimisation Hub'!C:C,MATCH(H5,'Content Optimisation Hub'!F:F,0)),"Not in Hub") -> Not in Hub
A6: Robots.txt Disallow Root | B6: Critical | C6: 105 | D6: 0 | F6: Technical Diagnostics | G6: Global Template | I6: Apply fix based on issue type and re-run audit. | J6: Template/technical implementation quality issue. | K6: Server/Host | L6: Server/Host | M6: M | N6: 10 | O6: 5 | P6: Immediate (Current Sprint) | Q6: To Do | T6: High Risk | U6: Yes | V6: Open in Main Tab | X6: SEO | Y6: =IFERROR(HYPERLINK("#'Main'!B"&MATCH(TRIM(H6),Main!B:B,0),"Open"),HYPERLINK("#'Main'!B1","Open")) -> Open | Z6: =IFERROR(INDEX('Content Optimisation Hub'!C:C,MATCH(H6,'Content Optimisation Hub'!F:F,0)),"Not in Hub") -> Not in Hub
A7: CWV LCP Above 4.0s | B7: Critical | C7: 105 | D7: 0 | F7: Technical Diagnostics | G7: Global Template | I7: Apply fix based on issue type and re-run audit. | J7: Template/technical implementation quality issue. | K7: Dev | L7: Dev | M7: M | N7: 10 | O7: 5 | P7: Immediate (Current Sprint) | Q7: To Do | T7: High Risk | U7: Yes | V7: Open in Main Tab | X7: SEO | Y7: =IFERROR(HYPERLINK("#'Main'!B"&MATCH(TRIM(H7),Main!B:B,0),"Open"),HYPERLINK("#'Main'!B1","Open")) -> Open | Z7: =IFERROR(INDEX('Content Optimisation Hub'!C:C,MATCH(H7,'Content Optimisation Hub'!F:F,0)),"Not in Hub") -> Not in Hub
A8: Broken Internal Links | B8: Critical | C8: 105 | D8: 0 | F8: Link Intelligence | G8: Manual Content | I8: Update internal links to valid URLs and remove dead references. | J8: Internal links resolve to missing or error pages. | K8: Dev | L8: Dev | M8: M | N8: 10 | O8: 5 | P8: Immediate (Current Sprint) | Q8: To Do | T8: High Risk | U8: Yes | V8: Open in Main Tab | X8: SEO | Y8: =IFERROR(HYPERLINK("#'Main'!B"&MATCH(TRIM(H8),Main!B:B,0),"Open"),HYPERLINK("#'Main'!B1","Open")) -> Open | Z8: =IFERROR(INDEX('Content Optimisation Hub'!C:C,MATCH(H8,'Content Optimisation Hub'!F:F,0)),"Not in Hub") -> Not in Hub
A9: Redirect Chains | B9: Warning | C9: 67 | D9: 0 | F9: Technical Diagnostics | G9: Global Template | I9: Apply fix based on issue type and re-run audit. | J9: Template/technical implementation quality issue. | K9: Dev | L9: Dev | M9: S | N9: 4 | O9: 2 | P9: Next Sprint | Q9: To Do | T9: Medium Risk | U9: Yes | V9: Open in Main Tab | X9: SEO | Y9: =IFERROR(HYPERLINK("#'Main'!B"&MATCH(TRIM(H9),Main!B:B,0),"Open"),HYPERLINK("#'Main'!B1","Open")) -> Open | Z9: =IFERROR(INDEX('Content Optimisation Hub'!C:C,MATCH(H9,'Content Optimisation Hub'!F:F,0)),"Not in Hub") -> Not in Hub
A10: CWV LCP Needs Improvement (2.5-4.0s) | B10: Warning | C10: 67 | D10: 0 | F10: Technical Diagnostics | G10: Global Template | I10: Apply fix based on issue type and re-run audit. | J10: Template/technical implementation quality issue. | K10: Copy Writer | L10: Copy Writer | M10: S | N10: 4 | O10: 2 | P10: Next Sprint | Q10: To Do | T10: Medium Risk | U10: Yes | V10: Open in Main Tab | X10: SEO | Y10: =IFERROR(HYPERLINK("#'Main'!B"&MATCH(TRIM(H10),Main!B:B,0),"Open"),HYPERLINK("#'Main'!B1","Open")) -> Open | Z10: =IFERROR(INDEX('Content Optimisation Hub'!C:C,MATCH(H10,'Content Optimisation Hub'!F:F,0)),"Not in Hub") -> Not in Hub
A11: Missing FAQ/QA Schema | B11: Warning | C11: 67 | D11: 0 | F11: Content & AI Readiness | G11: Global Template | I11: Publish machine-readable FAQPage or QAPage JSON-LD that mirrors visible Q&A text so answer engines can treat schema as a stable API surface. | J11: Question-style content without matching FAQPage/QAPage JSON-LD. | K11: Dev | L11: Dev | M11: S | N11: 4 | O11: 2 | P11: Next Sprint | Q11: To Do | T11: Medium Risk | U11: Yes | V11: Open in Main Tab | X11: AEO | Y11: =IFERROR(HYPERLINK("#'Main'!B"&MATCH(TRIM(H11),Main!B:B,0),"Open"),HYPERLINK("#'Main'!B1","Open")) -> Open | Z11: =IFERROR(INDEX('Content Optimisation Hub'!C:C,MATCH(H11,'Content Optimisation Hub'!F:F,0)),"Not in Hub") -> Not in Hub
A12: Deep URL (>3 clicks) | B12: Warning | C12: 67 | D12: 0 | F12: Technical Diagnostics | G12: Manual Content | I12: Apply fix based on issue type and re-run audit. | J12: Template/technical implementation quality issue. | K12: Copy Writer | L12: Copy Writer | M12: S | N12: 4 | O12: 2 | P12: Next Sprint | Q12: To Do | T12: Medium Risk | U12: Yes | V12: Open in Main Tab | X12: SEO | Y12: =IFERROR(HYPERLINK("#'Main'!B"&MATCH(TRIM(H12),Main!B:B,0),"Open"),HYPERLINK("#'Main'!B1","Open")) -> Open | Z12: =IFERROR(INDEX('Content Optimisation Hub'!C:C,MATCH(H12,'Content Optimisation Hub'!F:F,0)),"Not in Hub") -> Not in Hub
A13: Mixed Content | B13: Warning | C13: 67 | D13: 0 | F13: Technical Diagnostics | G13: Manual Content | I13: Serve all assets over HTTPS and update hardcoded URLs. | J13: HTTPS page references insecure HTTP assets. | K13: Dev | L13: Dev | M13: S | N13: 4 | O13: 2 | P13: Next Sprint | Q13: To Do | T13: Medium Risk | U13: Yes | V13: Open in Main Tab | X13: SEO | Y13: =IFERROR(HYPERLINK("#'Main'!B"&MATCH(TRIM(H13),Main!B:B,0),"Open"),HYPERLINK("#'Main'!B1","Open")) -> Open | Z13: =IFERROR(INDEX('Content Optimisation Hub'!C:C,MATCH(H13,'Content Optimisation Hub'!F:F,0)),"Not in Hub") -> Not in Hub
... A15: Hreflang Without Reciprocity | B15: Warning | C15: 67 | D15: 0 | F15: Technical Diagnostics | G15: Manual Content | I15: Apply fix based on issue type and re-run audit. | J15: Template/technical implementation quality issue. | K15: Copy Writer | L15: Copy Writer | M15: S | N15: 4 | O15: 2 | P15: Next Sprint | Q15: To Do | T15: Medium Risk | U15: Yes | V15: Open in Main Tab | X15: SEO | Y15: =IFERROR(HYPERLINK("#'Main'!B"&MATCH(TRIM(H15),Main!B:B,0),"Open"),HYPERLINK("#'Main'!B1","Open")) -> Open | Z15: =IFERROR(INDEX('Content Optimisation Hub'!C:C,MATCH(H15,'Content Optimisation Hub'!F:F,0)),"Not in Hub") -> Not in Hub
A16: Low AEO Readiness Score | B16: Warning | C16: 67 | D16: 20 | E16: SEE DETAILS IN Content & AI Readiness | F16: Content & AI Readiness | G16: Global Template | H16: https://africanmarketingconfederation.org/amc-awards-2024 | I16: Raise the weighted mix: add a 40–60 word factual paragraph under each question H2/H3, add FAQPage/HowTo/Speakable JSON-LD, tune copy to FK grade 7–10, add ul/ol/table for key facts, and ensure robots.txt explicitly allows GPTBot, PerplexityBot, and CCBot. | J16: Weighted AEO score is below the 70-point extraction-confidence band. | K16: Copy Writer | L16: Copy Writer | M16: S | N16: 4 | O16: 2 | P16: Next Sprint | Q16: To Do | T16: Medium Risk | U16: Yes | V16: Open in Main Tab | X16: AEO | Y16: =IFERROR(HYPERLINK("#'Main'!B"&MATCH(TRIM(H16),Main!B:B,0),"Open"),HYPERLINK("#'Main'!B1","Open")) -> Open | Z16: =IFERROR(INDEX('Content Optimisation Hub'!C:C,MATCH(H16,'Content Optimisation Hub'!F:F,0)),"Not in Hub") -> Not in Hub
A17: Low Image Alt Coverage | B17: Warning | C17: 67 | D17: 16 | E17: SEE DETAILS IN Technical Diagnostics | F17: Technical Diagnostics | G17: Global Template | H17: https://africanmarketingconfederation.org/amc-awards-2024 | I17: Apply fix based on issue type and re-run audit. | J17: Template/technical implementation quality issue. | K17: Copy Writer | L17: Copy Writer | M17: S | N17: 4 | O17: 2 | P17: Next Sprint | Q17: To Do | T17: Medium Risk | U17: Yes | V17: Open in Main Tab | X17: SEO | Y17: =IFERROR(HYPERLINK("#'Main'!B"&MATCH(TRIM(H17),Main!B:B,0),"Open"),HYPERLINK("#'Main'!B1","Open")) -> Open | Z17: =IFERROR(INDEX('Content Optimisation Hub'!C:C,MATCH(H17,'Content Optimisation Hub'!F:F,0)),"Not in Hub") -> Not in Hub
A18: Multiple H1 | B18: Warning | C18: 67 | D18: 5 | E18: https://africanmarketingconfederation.org/amc-awards-2024 https://africanmarketingconfederation.org/ https://africanmarketingconfederation.org/african-marketing-confederation-tourism-chapter https://africanmarketingconfederation.org/amc-conference-2024-recap https://africanmarketingconfederation.org/amc-conference-2025-highlights | F18: Technical Diagnostics | G18: Manual Content | H18: https://africanmarketingconfederation.org/amc-awards-2024 | I18: Apply fix based on issue type and re-run audit. | J18: Template/technical implementation quality issue. | K18: Copy Writer | L18: Copy Writer | M18: S | N18: 4 | O18: 2 | P18: Next Sprint | Q18: To Do | T18: Medium Risk | U18: Yes | V18: Open in Main Tab | X18: SEO | Y18: =IFERROR(HYPERLINK("#'Main'!B"&MATCH(TRIM(H18),Main!B:B,0),"Open"),HYPERLINK("#'Main'!B1","Open")) -> Open | Z18: =IFERROR(INDEX('Content Optimisation Hub'!C:C,MATCH(H18,'Content Optimisation Hub'!F:F,0)),"Not in Hub") -> Not in Hub
A19: Missing H1 | B19: Warning | C19: 67 | D19: 5 | E19: https://africanmarketingconfederation.org/amc-conference-2022-prospectus https://africanmarketingconfederation.org/amc-conference-2022-thank-you https://africanmarketingconfederation.org/amc-conference-2022 https://africanmarketingconfederation.org/amc-conference-2023/amc-awards-book-now https://africanmarketingconfederation.org/amc-conference-2023/book-now-thank-you | F19: Technical Diagnostics | G19: Manual Content | H19: https://africanmarketingconfederation.org/amc-conference-2022-prospectus | I19: Apply fix based on issue type and re-run audit. | J19: Template/technical implementation quality issue. | K19: Copy Writer | L19: Copy Writer | M19: S | N19: 4 | O19: 2 | P19: Next Sprint | Q19: To Do | T19: Medium Risk | U19: Yes | V19: Open in Main Tab | X19: SEO | Y19: =IFERROR(HYPERLINK("#'Main'!B"&MATCH(TRIM(H19),Main!B:B,0),"Open"),HYPERLINK("#'Main'!B1","Open")) -> Open | Z19: =IFERROR(INDEX('Content Optimisation Hub'!C:C,MATCH(H19,'Content Optimisation Hub'!F:F,0)),"Not in Hub") -> Not in Hub
A20: Missing Meta Description | B20: Warning | C20: 67 | D20: 1 | E20: https://africanmarketingconfederation.org/amc-conference-2023/amc-awards-book-now | F20: Technical Diagnostics | G20: Manual Content | H20: https://africanmarketingconfederation.org/amc-conference-2023/amc-awards-book-now | I20: Add concise unique description aligned with user intent. | J20: Meta description missing or empty. | K20: Copy Writer | L20: Copy Writer | M20: S | N20: 4 | O20: 2 | P20: Next Sprint | Q20: To Do | T20: Medium Risk | U20: Yes | V20: Open in Main Tab | X20: SEO | Y20: =IFERROR(HYPERLINK("#'Main'!B"&MATCH(TRIM(H20),Main!B:B,0),"Open"),HYPERLINK("#'Main'!B1","Open")) -> Open | Z20: =IFERROR(INDEX('Content Optimisation Hub'!C:C,MATCH(H20,'Content Optimisation Hub'!F:F,0)),"Not in Hub") -> Not in Hub
A21: Uses URL Parameters | B21: Observation | C21: 37 | D21: 0 | F21: Technical Diagnostics | G21: Manual Content | I21: Apply fix based on issue type and re-run audit. | J21: Template/technical implementation quality issue. | K21: Dev | L21: Dev | M21: S | N21: 4 | O21: 2 | P21: Backlog | Q21: In Review | T21: Monitor | U21: No | V21: Open in Main Tab | X21: SEO | Y21: =IFERROR(HYPERLINK("#'Main'!B"&MATCH(TRIM(H21),Main!B:B,0),"Open"),HYPERLINK("#'Main'!B1","Open")) -> Open | Z21: =IFERROR(INDEX('Content Optimisation Hub'!C:C,MATCH(H21,'Content Optimisation Hub'!F:F,0)),"Not in Hub") -> Not in Hub
A22: No Compression Header | B22: Observation | C22: 37 | D22: 0 | F22: Technical Diagnostics | G22: Global Template | I22: Apply fix based on issue type and re-run audit. | J22: Template/technical implementation quality issue. | K22: Server/Host | L22: Server/Host | M22: S | N22: 4 | O22: 2 | P22: Backlog | Q22: In Review | T22: Monitor | U22: No | V22: Open in Main Tab | X22: SEO | Y22: =IFERROR(HYPERLINK("#'Main'!B"&MATCH(TRIM(H22),Main!B:B,0),"Open"),HYPERLINK("#'Main'!B1","Open")) -> Open | Z22: =IFERROR(INDEX('Content Optimisation Hub'!C:C,MATCH(H22,'Content Optimisation Hub'!F:F,0)),"Not in Hub") -> Not in Hub
A23: No Cache-Control Header | B23: Observation | C23: 37 | D23: 0 | F23: Technical Diagnostics | G23: Global Template | I23: Apply fix based on issue type and re-run audit. | J23: Template/technical implementation quality issue. | K23: Server/Host | L23: Server/Host | M23: S | N23: 4 | O23: 2 | P23: Backlog | Q23: In Review | T23: Monitor | U23: No | V23: Open in Main Tab | X23: SEO | Y23: =IFERROR(HYPERLINK("#'Main'!B"&MATCH(TRIM(H23),Main!B:B,0),"Open"),HYPERLINK("#'Main'!B1","Open")) -> Open | Z23: =IFERROR(INDEX('Content Optimisation Hub'!C:C,MATCH(H23,'Content Optimisation Hub'!F:F,0)),"Not in Hub") -> Not in Hub
A24: No Answer-Friendly Structure | B24: Observation | C24: 37 | D24: 0 | F24: Content & AI Readiness | G24: Manual Content | I24: Break data-heavy explanations into ul/ol steps or a comparison table so LLMs can cite discrete facts without re-parsing long paragraphs. | J24: Dense prose without lists or tables where facts could be chunked. | K24: Copy Writer | L24: Copy Writer | M24: S | N24: 4 | O24: 2 | P24: Backlog | Q24: In Review | T24: Monitor | U24: No | V24: Open in Main Tab | X24: AEO | Y24: =IFERROR(HYPERLINK("#'Main'!B"&MATCH(TRIM(H24),Main!B:B,0),"Open"),HYPERLINK("#'Main'!B1","Open")) -> Open | Z24: =IFERROR(INDEX('Content Optimisation Hub'!C:C,MATCH(H24,'Content Optimisation Hub'!F:F,0)),"Not in Hub") -> Not in Hub
A25: INP Above 100ms | B25: Observation | C25: 37 | D25: 0 | F25: Technical Diagnostics | G25: Manual Content | I25: Apply fix based on issue type and re-run audit. | J25: Template/technical implementation quality issue. | K25: Copy Writer | L25: Copy Writer | M25: S | N25: 4 | O25: 2 | P25: Backlog | Q25: In Review | T25: Monitor | U25: No | V25: Open in Main Tab | X25: SEO | Y25: =IFERROR(HYPERLINK("#'Main'!B"&MATCH(TRIM(H25),Main!B:B,0),"Open"),HYPERLINK("#'Main'!B1","Open")) -> Open | Z25: =IFERROR(INDEX('Content Optimisation Hub'!C:C,MATCH(H25,'Content Optimisation Hub'!F:F,0)),"Not in Hub") -> Not in Hub
A26: CLS Above 0.1 | B26: Observation | C26: 37 | D26: 0 | F26: Technical Diagnostics | G26: Manual Content | I26: Apply fix based on issue type and re-run audit. | J26: Template/technical implementation quality issue. | K26: Copy Writer | L26: Copy Writer | M26: S | N26: 4 | O26: 2 | P26: Backlog | Q26: In Review | T26: Monitor | U26: No | V26: Open in Main Tab | X26: SEO | Y26: =IFERROR(HYPERLINK("#'Main'!B"&MATCH(TRIM(H26),Main!B:B,0),"Open"),HYPERLINK("#'Main'!B1","Open")) -> Open | Z26: =IFERROR(INDEX('Content Optimisation Hub'!C:C,MATCH(H26,'Content Optimisation Hub'!F:F,0)),"Not in Hub") -> Not in Hub
A27: Low Regional Authority | B27: Observation | C27: 37 | D27: 0 | F27: Technical Diagnostics | G27: Manual Content | I27: Apply fix based on issue type and re-run audit. | J27: Template/technical implementation quality issue. | K27: Copy Writer | L27: Copy Writer | M27: S | N27: 4 | O27: 2 | P27: Backlog | Q27: In Review | T27: Monitor | U27: No | V27: Open in Main Tab | X27: SEO | Y27: =IFERROR(HYPERLINK("#'Main'!B"&MATCH(TRIM(H27),Main!B:B,0),"Open"),HYPERLINK("#'Main'!B1","Open")) -> Open | Z27: =IFERROR(INDEX('Content Optimisation Hub'!C:C,MATCH(H27,'Content Optimisation Hub'!F:F,0)),"Not in Hub") -> Not in Hub
A28: llms.txt Missing | B28: Observation | C28: 37 | D28: 0 | F28: Technical Diagnostics | G28: Manual Content | I28: Apply fix based on issue type and re-run audit. | J28: Template/technical implementation quality issue. | K28: Copy Writer | L28: Copy Writer | M28: S | N28: 4 | O28: 2 | P28: Backlog | Q28: In Review | T28: Monitor | U28: No | V28: Open in Main Tab | X28: SEO | Y28: =IFERROR(HYPERLINK("#'Main'!B"&MATCH(TRIM(H28),Main!B:B,0),"Open"),HYPERLINK("#'Main'!B1","Open")) -> Open | Z28: =IFERROR(INDEX('Content Optimisation Hub'!C:C,MATCH(H28,'Content Optimisation Hub'!F:F,0)),"Not in Hub") -> Not in Hub
A29: Generic Anchor Text Present | B29: Observation | C29: 37 | D29: 1 | E29: https://africanmarketingconfederation.org/ | F29: Link Intelligence | G29: Manual Content | H29: https://africanmarketingconfederation.org/ | I29: Apply fix based on issue type and re-run audit. | J29: Template/technical implementation quality issue. | K29: Copy Writer | L29: Copy Writer | M29: S | N29: 4 | O29: 2 | P29: Backlog | Q29: In Review | T29: Monitor | U29: No | V29: Open in Main Tab | X29: SEO | Y29: =IFERROR(HYPERLINK("#'Main'!B"&MATCH(TRIM(H29),Main!B:B,0),"Open"),HYPERLINK("#'Main'!B1","Open")) -> Open | Z29: =IFERROR(INDEX('Content Optimisation Hub'!C:C,MATCH(H29,'Content Optimisation Hub'!F:F,0)),"Not in Hub") -> Not in Hub
A30: Thin Content | B30: Observation | C30: 37 | D30: 12 | E30: SEE DETAILS IN Technical Diagnostics | F30: Technical Diagnostics | G30: Global Template | H30: https://africanmarketingconfederation.org/about-us | I30: Expand page with helpful, unique, intent-matching content. | J30: Insufficient body content for indexing confidence. | K30: Copy Writer | L30: Copy Writer | M30: S | N30: 4 | O30: 2 | P30: Backlog | Q30: In Review | T30: Monitor | U30: No | V30: Open in Main Tab | X30: SEO | Y30: =IFERROR(HYPERLINK("#'Main'!B"&MATCH(TRIM(H30),Main!B:B,0),"Open"),HYPERLINK("#'Main'!B1","Open")) -> Open | Z30: =IFERROR(INDEX('Content Optimisation Hub'!C:C,MATCH(H30,'Content Optimisation Hub'!F:F,0)),"Not in Hub") -> Not in Hub
A31: No ETag Header | B31: Observation | C31: 37 | D31: 20 | E31: SEE DETAILS IN Technical Diagnostics | F31: Technical Diagnostics | G31: Global Template | H31: https://africanmarketingconfederation.org/amc-awards-2024 | I31: Apply fix based on issue type and re-run audit. | J31: Template/technical implementation quality issue. | K31: Server/Host | L31: Server/Host | M31: S | N31: 4 | O31: 2 | P31: Backlog | Q31: In Review | T31: Monitor | U31: No | V31: Open in Main Tab | X31: SEO | Y31: =IFERROR(HYPERLINK("#'Main'!B"&MATCH(TRIM(H31),Main!B:B,0),"Open"),HYPERLINK("#'Main'!B1","Open")) -> Open | Z31: =IFERROR(INDEX('Content Optimisation Hub'!C:C,MATCH(H31,'Content Optimisation Hub'!F:F,0)),"Not in Hub") -> Not in Hub
A32: No Question Headings | B32: Observation | C32: 37 | D32: 20 | E32: SEE DETAILS IN Content & AI Readiness | F32: Content & AI Readiness | G32: Global Template | H32: https://africanmarketingconfederation.org/amc-awards-2024 | I32: Rewrite priority H2/H3 headings into natural-language questions (Who/What/How) so the following paragraph can serve as a direct extractable answer. | J32: Headings are not phrased as user questions. | K32: Copy Writer | L32: Copy Writer | M32: S | N32: 4 | O32: 2 | P32: Backlog | Q32: In Review | T32: Monitor | U32: No | V32: Open in Main Tab | X32: AEO | Y32: =IFERROR(HYPERLINK("#'Main'!B"&MATCH(TRIM(H32),Main!B:B,0),"Open"),HYPERLINK("#'Main'!B1","Open")) -> Open | Z32: =IFERROR(INDEX('Content Optimisation Hub'!C:C,MATCH(H32,'Content Optimisation Hub'!F:F,0)),"Not in Hub") -> Not in Hub
A33: No 40-60 Word Answer Paragraphs | B33: Observation | C33: 37 | D33: 20 | E33: SEE DETAILS IN Content & AI Readiness | F33: Content & AI Readiness | G33: Global Template | H33: https://africanmarketingconfederation.org/amc-awards-2024 | I33: Refactor each target section to lead with a ~45-word factual definition (no fluff) immediately under the question heading to improve LLM Position Zero retrieval. | J33: No 40–60 word definitional paragraph directly under a question-style H2/H3. | K33: Copy Writer | L33: Copy Writer | M33: S | N33: 4 | O33: 2 | P33: Backlog | Q33: In Review | T33: Monitor | U33: No | V33: Open in Main Tab | X33: AEO | Y33: =IFERROR(HYPERLINK("#'Main'!B"&MATCH(TRIM(H33),Main!B:B,0),"Open"),HYPERLINK("#'Main'!B1","Open")) -> Open | Z33: =IFERROR(INDEX('Content Optimisation Hub'!C:C,MATCH(H33,'Content Optimisation Hub'!F:F,0)),"Not in Hub") -> Not in Hub
A34: AI Crawlers Not Explicitly Allowed | B34: Observation | C34: 37 | D34: 20 | E34: SEE DETAILS IN Technical Diagnostics | F34: Technical Diagnostics | G34: Global Template | H34: https://africanmarketingconfederation.org/amc-awards-2024 | I34: Apply fix based on issue type and re-run audit. | J34: Template/technical implementation quality issue. | K34: Copy Writer | L34: Copy Writer | M34: S | N34: 4 | O34: 2 | P34: Backlog | Q34: In Review | T34: Monitor | U34: No | V34: Open in Main Tab | X34: SEO | Y34: =IFERROR(HYPERLINK("#'Main'!B"&MATCH(TRIM(H34),Main!B:B,0),"Open"),HYPERLINK("#'Main'!B1","Open")) -> Open | Z34: =IFERROR(INDEX('Content Optimisation Hub'!C:C,MATCH(H34,'Content Optimisation Hub'!F:F,0)),"Not in Hub") -> Not in Hub
A35: Image Filename Quality Issues | B35: Observation | C35: 37 | D35: 1 | E35: https://africanmarketingconfederation.org/amc-conference-2025-highlights | F35: Technical Diagnostics | G35: Manual Content | H35: https://africanmarketingconfederation.org/amc-conference-2025-highlights | I35: Apply fix based on issue type and re-run audit. | J35: Template/technical implementation quality issue. | K35: Copy Writer | L35: Copy Writer | M35: S | N35: 4 | O35: 2 | P35: Backlog | Q35: In Review | T35: Monitor | U35: No | V35: Open in Main Tab | X35: SEO | Y35: =IFERROR(HYPERLINK("#'Main'!B"&MATCH(TRIM(H35),Main!B:B,0),"Open"),HYPERLINK("#'Main'!B1","Open")) -> Open | Z35: =IFERROR(INDEX('Content Optimisation Hub'!C:C,MATCH(H35,'Content Optimisation Hub'!F:F,0)),"Not in Hub") -> Not in Hub

Sheet Priority URLs
A1: URL | B1: Business Risk Score | C1: Severity Badge | D1: SEO Health Score | E1: GSC Impressions | F1: GSC CTR | G1: Revenue Intent | H1: Critical Issues Count | I1: Warning Issues Count | J1: Action Needed | K1: Why Prioritized | L1: Owner | M1: Status | N1: Sprint | O1: Indexability Reason | P1: Broken Internal Links Count | Q1: Canonical Type | R1: Open in Main | S1: Open in Technical | T1: BACK TO DASHBOARD
A2: https://africanmarketingconfederation.org/amc-conference-2023/amc-awards-book-now | B2: 90 | C2: Warning | D2: 50 | E2: 0 | F2: 0 | G2: Standard | H2: 0 | I2: 4 | J2: Yes | K2: Monitor | L2: Copy Writer | M2: Open | O2: Indexable | Q2: self | R2: =IFERROR(HYPERLINK("#'Main'!B"&MATCH(TRIM(A2),Main!B:B,0),"Open"),HYPERLINK("#'Main'!B1","Open")) -> Open | S2: =IFERROR(HYPERLINK("#'Technical Diagnostics'!A"&MATCH(A2,'Technical Diagnostics'!A:A,0),"Open"),HYPERLINK("#'Technical Diagnostics'!A1","Open")) -> Open
A3: https://africanmarketingconfederation.org/amc-awards-2024 | B3: 70 | C3: Warning | D3: 60 | E3: 0 | F3: 0 | G3: Standard | H3: 0 | I3: 3 | J3: Yes | K3: Monitor | L3: Copy Writer | M3: Open | O3: Indexable | Q3: self | R3: =IFERROR(HYPERLINK("#'Main'!B"&MATCH(TRIM(A3),Main!B:B,0),"Open"),HYPERLINK("#'Main'!B1","Open")) -> Open | S3: =IFERROR(HYPERLINK("#'Technical Diagnostics'!A"&MATCH(A3,'Technical Diagnostics'!A:A,0),"Open"),HYPERLINK("#'Technical Diagnostics'!A1","Open")) -> Open
A4: https://africanmarketingconfederation.org/ | B4: 70 | C4: Warning | D4: 60 | E4: 1257 | F4: 0.058074781 | G4: Standard | H4: 0 | I4: 3 | J4: Yes | K4: Monitor | L4: Copy Writer | M4: Open | O4: Indexable | Q4: self | R4: =IFERROR(HYPERLINK("#'Main'!B"&MATCH(TRIM(A4),Main!B:B,0),"Open"),HYPERLINK("#'Main'!B1","Open")) -> Open | S4: =IFERROR(HYPERLINK("#'Technical Diagnostics'!A"&MATCH(A4,'Technical Diagnostics'!A:A,0),"Open"),HYPERLINK("#'Technical Diagnostics'!A1","Open")) -> Open
A5: https://africanmarketingconfederation.org/amc-conference-2022-prospectus | B5: 70 | C5: Warning | D5: 60 | E5: 0 | F5: 0 | G5: Standard | H5: 0 | I5: 3 | J5: Yes | K5: Monitor | L5: Copy Writer | M5: Open | O5: Indexable | Q5: self | R5: =IFERROR(HYPERLINK("#'Main'!B"&MATCH(TRIM(A5),Main!B:B,0),"Open"),HYPERLINK("#'Main'!B1","Open")) -> Open | S5: =IFERROR(HYPERLINK("#'Technical Diagnostics'!A"&MATCH(A5,'Technical Diagnostics'!A:A,0),"Open"),HYPERLINK("#'Technical Diagnostics'!A1","Open")) -> Open
A6: https://africanmarketingconfederation.org/amc-conference-2022-thank-you | B6: 70 | C6: Warning | D6: 60 | E6: 0 | F6: 0 | G6: Standard | H6: 0 | I6: 3 | J6: Yes | K6: Monitor | L6: Copy Writer | M6: Open | O6: Indexable | Q6: self | R6: =IFERROR(HYPERLINK("#'Main'!B"&MATCH(TRIM(A6),Main!B:B,0),"Open"),HYPERLINK("#'Main'!B1","Open")) -> Open | S6: =IFERROR(HYPERLINK("#'Technical Diagnostics'!A"&MATCH(A6,'Technical Diagnostics'!A:A,0),"Open"),HYPERLINK("#'Technical Diagnostics'!A1","Open")) -> Open
A7: https://africanmarketingconfederation.org/amc-conference-2022 | B7: 70 | C7: Warning | D7: 60 | E7: 11 | F7: 0 | G7: Standard | H7: 0 | I7: 3 | J7: Yes | K7: Monitor | L7: Copy Writer | M7: Open | O7: Indexable | Q7: self | R7: =IFERROR(HYPERLINK("#'Main'!B"&MATCH(TRIM(A7),Main!B:B,0),"Open"),HYPERLINK("#'Main'!B1","Open")) -> Open | S7: =IFERROR(HYPERLINK("#'Technical Diagnostics'!A"&MATCH(A7,'Technical Diagnostics'!A:A,0),"Open"),HYPERLINK("#'Technical Diagnostics'!A1","Open")) -> Open
A8: https://africanmarketingconfederation.org/amc-conference-2025-highlights | B8: 70 | C8: Warning | D8: 60 | E8: 32 | F8: 0 | G8: Standard | H8: 0 | I8: 3 | J8: Yes | K8: Monitor | L8: Copy Writer | M8: Open | O8: Indexable | Q8: self | R8: =IFERROR(HYPERLINK("#'Main'!B"&MATCH(TRIM(A8),Main!B:B,0),"Open"),HYPERLINK("#'Main'!B1","Open")) -> Open | S8: =IFERROR(HYPERLINK("#'Technical Diagnostics'!A"&MATCH(A8,'Technical Diagnostics'!A:A,0),"Open"),HYPERLINK("#'Technical Diagnostics'!A1","Open")) -> Open
A9: https://africanmarketingconfederation.org/about-us | B9: 50 | C9: Warning | D9: 70 | E9: 235 | F9: 0.042553191 | G9: Standard | H9: 0 | I9: 2 | J9: Yes | K9: Monitor | L9: Copy Writer | M9: Open | O9: Indexable | Q9: self | R9: =IFERROR(HYPERLINK("#'Main'!B"&MATCH(TRIM(A9),Main!B:B,0),"Open"),HYPERLINK("#'Main'!B1","Open")) -> Open | S9: =IFERROR(HYPERLINK("#'Technical Diagnostics'!A"&MATCH(A9,'Technical Diagnostics'!A:A,0),"Open"),HYPERLINK("#'Technical Diagnostics'!A1","Open")) -> Open
A10: https://africanmarketingconfederation.org/african-marketing-confederation-tourism-chapter | B10: 50 | C10: Warning | D10: 70 | E10: 18 | F10: 0 | G10: Standard | H10: 0 | I10: 2 | J10: Yes | K10: Monitor | L10: Copy Writer | M10: Open | O10: Indexable | Q10: self | R10: =IFERROR(HYPERLINK("#'Main'!B"&MATCH(TRIM(A10),Main!B:B,0),"Open"),HYPERLINK("#'Main'!B1","Open")) -> Open | S10: =IFERROR(HYPERLINK("#'Technical Diagnostics'!A"&MATCH(A10,'Technical Diagnostics'!A:A,0),"Open"),HYPERLINK("#'Technical Diagnostics'!A1","Open")) -> Open
A11: https://africanmarketingconfederation.org/amc-conference-2023 | B11: 50 | C11: Warning | D11: 70 | E11: 24 | F11: 0.041666667 | G11: Standard | H11: 0 | I11: 2 | J11: Yes | K11: Monitor | L11: Copy Writer | M11: Open | O11: Indexable | Q11: self | R11: =IFERROR(HYPERLINK("#'Main'!B"&MATCH(TRIM(A11),Main!B:B,0),"Open"),HYPERLINK("#'Main'!B1","Open")) -> Open | S11: =IFERROR(HYPERLINK("#'Technical Diagnostics'!A"&MATCH(A11,'Technical Diagnostics'!A:A,0),"Open"),HYPERLINK("#'Technical Diagnostics'!A1","Open")) -> Open
A12: https://africanmarketingconfederation.org/amc-conference-2023/amc-awards | B12: 50 | C12: Warning | D12: 70 | E12: 30 | F12: 0.033333333 | G12: Standard | H12: 0 | I12: 2 | J12: Yes | K12: Monitor | L12: Copy Writer | M12: Open | O12: Indexable | Q12: self | R12: =IFERROR(HYPERLINK("#'Main'!B"&MATCH(TRIM(A12),Main!B:B,0),"Open"),HYPERLINK("#'Main'!B1","Open")) -> Open | S12: =IFERROR(HYPERLINK("#'Technical Diagnostics'!A"&MATCH(A12,'Technical Diagnostics'!A:A,0),"Open"),HYPERLINK("#'Technical Diagnostics'!A1","Open")) -> Open
A13: https://africanmarketingconfederation.org/amc-conference-2023/book-now-thank-you | B13: 50 | C13: Warning | D13: 70 | E13: 0 | F13: 0 | G13: Standard | H13: 0 | I13: 2 | J13: Yes | K13: Monitor | L13: Copy Writer | M13: Open | O13: Indexable | Q13: self | R13: =IFERROR(HYPERLINK("#'Main'!B"&MATCH(TRIM(A13),Main!B:B,0),"Open"),HYPERLINK("#'Main'!B1","Open")) -> Open | S13: =IFERROR(HYPERLINK("#'Technical Diagnostics'!A"&MATCH(A13,'Technical Diagnostics'!A:A,0),"Open"),HYPERLINK("#'Technical Diagnostics'!A1","Open")) -> Open
... A21: https://africanmarketingconfederation.org/amc-conference-2023/speakers | B21: 30 | C21: Warning | D21: 80 | E21: 29 | F21: 0 | G21: Standard | H21: 0 | I21: 1 | J21: Yes | K21: Monitor | L21: Copy Writer | M21: Open | O21: Indexable | Q21: self | R21: =IFERROR(HYPERLINK("#'Main'!B"&MATCH(TRIM(A21),Main!B:B,0),"Open"),HYPERLINK("#'Main'!B1","Open")) -> Open | S21: =IFERROR(HYPERLINK("#'Technical Diagnostics'!A"&MATCH(A21,'Technical Diagnostics'!A:A,0),"Open"),HYPERLINK("#'Technical Diagnostics'!A1","Open")) -> Open

Sheet Content Optimisation Hub
A1: CONTENT HUB (DIAGNOSTIC): Edit Title, Meta, and H1–H6 in-place; health columns and On-Page score update live. | Use Elementor link for CMS edits. | Set Status to Completed when done. | NOTE: If images show '#BLOCKED!', enable external content in Excel security. | AD1: BACK TO DASHBOARD
A2: Action Required | B2: On-Page Optimization Score | C2: SEO Score | D2: Technical Health | E2: Copy Score | F2: Status | G2: Assigned Owner | H2: URL | I2: URL Slug Normalization | J2: Proposed URL Slug | K2: Current Title | L2: Title Health | M2: Current Meta Desc | N2: Meta Health | O2: H1 | P2: H1 Health | Q2: H2 | R2: H2 Health | S2: H3 | T2: H3 Health | U2: H4 | V2: H4 Health | W2: H5 | X2: H5 Health | Y2: H6 | Z2: H6 Health | AA2: Elementor Builder Link | AB2: Current OG-Image URL | AC2: OG Image Preview | AD2: Open in Main
A3: =IF(B3>=85,"Complete","Needs Copy") -> Needs Copy | B3: =MIN(100,ROUND(0.3*(IF(L3="",0,IF(LEFT(L3,7)="MISSING",0,IF(ISNUMBER(SEARCH("OK",L3)),100,IF(ISNUMBER(SEARCH("SHORT",L3)),65,IF(ISNUMBER(SEARCH("LONG",L3)),50,70))))))+0.25*(IF(N3="",0,IF(LEFT(N3,7)="MISSING",0,IF(ISNUMBER(SEARCH("OK",N3)),100,IF(ISNUMBER(SEARCH("SHORT",N3)),65,IF(ISNUMBER(SEARCH("LONG",N3)),50,70))))))+0.2*(IF(P3="",0,IF(LEFT(P3,2)="OK",100,0)))+0.08*(IF(R3="",0,IF(LEFT(R3,2)="OK",100,0)))+0.06*(IF(T3="",0,IF(LEFT(T3,2)="OK",100,0)))+0.05*(IF(V3="",0,IF(LEFT(V3,2)="OK",100,0)))+0.03*(IF(X3="",0,IF(LEFT(X3,2)="OK",100,0)))+0.03*(IF(Z3="",0,IF(LEFT(Z3,2)="OK",100,0))),0)) -> 68 | C3: 64.52 | D3: 60 | E3: 78.08 | F3: To Do | G3: Copy Writer | H3: =HYPERLINK("https://africanmarketingconfederation.org/","https://africanmarketingconfederation.org/") -> https://africanmarketingconfederation.org/ | I3: =HYPERLINK("https://africanmarketingconfederation.org/","https://africanmarketingconfederation.org/") -> https://africanmarketingconfederation.org/ | K3: African Marketing Confederation - Uniting Marketers for Excellence | L3: =IF(K3="","MISSING",IF(AND(LEN(K3)>=50,LEN(K3)<=60),"OK 50-60 chars",IF(LEN(K3)<50,"SHORT: "&LEN(K3),"LONG: "&LEN(K3)))) -> LONG: 66 | M3: The African Marketing Confederation is the ground-breaking Pan-African body driving the development of top marketing standards across Africa and beyond. | N3: =IF(M3="","MISSING",IF(AND(LEN(M3)>=120,LEN(M3)<=160),"OK 120-160 chars",IF(LEN(M3)<120,"SHORT: "&LEN(M3),"LONG: "&LEN(M3)))) -> OK 120-160 chars | O3: ABOUT The African Marketing Confederation | P3: =IF(OR(ISBLANK(O3),ISNUMBER(SEARCH("|",O3))),"FIX: MULTIPLE/MISSING","OK") -> OK | Q3: The 2026 AMC Conference | Meets the Mighty Victoria Falls | 23-25 September | Livingstone, Zambia | Certified Professional Marketer (Africa) - CPM(A) | The designation where global marketing standards meet African realities | R3: =IF(ISBLANK(Q3),"MISSING","OK") -> OK | T3: =IF(ISBLANK(S3),"MISSING","OK") -> MISSING | V3: =IF(ISBLANK(U3),"MISSING","OK") -> MISSING | X3: =IF(ISBLANK(W3),"MISSING","OK") -> MISSING | Z3: =IF(ISBLANK(Y3),"MISSING","OK") -> MISSING | AA3: =HYPERLINK("https://africanmarketingconfederation.org/wp-admin/post.php?post=8&action=elementor","Open in Elementor") -> Open in Elementor | AB3: =HYPERLINK("https://africanmarketingconfederation.org/wp-content/uploads/2026/03/og-image.png","View Image") -> View Image | AC3: =IF(LEN("https://africanmarketingconfederation.org/wp-content/uploads/2026/03/og-image.png")>0, _xlfn.IMAGE("https://africanmarketingconfederation.org/wp-content/uploads/2026/03/og-image.png"), "") -> #VALUE! | AD3: =IFERROR(HYPERLINK("#'Main'!B"&MATCH(TRIM(H3),Main!B:B,0),"Open in Main"),IFERROR(HYPERLINK("#'Technical Diagnostics'!A"&MATCH(TRIM(H3),'Technical Diagnostics'!A:A,0),"Open in Technical"),"Not Found")) -> Open in Main
A4: =IF(B4>=85,"Complete","Needs Copy") -> Needs Copy | B4: =MIN(100,ROUND(0.3*(IF(L4="",0,IF(LEFT(L4,7)="MISSING",0,IF(ISNUMBER(SEARCH("OK",L4)),100,IF(ISNUMBER(SEARCH("SHORT",L4)),65,IF(ISNUMBER(SEARCH("LONG",L4)),50,70))))))+0.25*(IF(N4="",0,IF(LEFT(N4,7)="MISSING",0,IF(ISNUMBER(SEARCH("OK",N4)),100,IF(ISNUMBER(SEARCH("SHORT",N4)),65,IF(ISNUMBER(SEARCH("LONG",N4)),50,70))))))+0.2*(IF(P4="",0,IF(LEFT(P4,2)="OK",100,0)))+0.08*(IF(R4="",0,IF(LEFT(R4,2)="OK",100,0)))+0.06*(IF(T4="",0,IF(LEFT(T4,2)="OK",100,0)))+0.05*(IF(V4="",0,IF(LEFT(V4,2)="OK",100,0)))+0.03*(IF(X4="",0,IF(LEFT(X4,2)="OK",100,0)))+0.03*(IF(Z4="",0,IF(LEFT(Z4,2)="OK",100,0))),0)) -> 62 | C4: 76.15 | D4: 70 | E4: 94.58 | F4: To Do | G4: Copy Writer | H4: =HYPERLINK("https://africanmarketingconfederation.org/about-us","https://africanmarketingconfederation.org/about-us") -> https://africanmarketingconfederation.org/about-us | I4: =HYPERLINK("https://africanmarketingconfederation.org/about-us","About Us") -> About Us | J4: about-us | K4: African Marketing Confederation – The Leading Marketing Professional Body – African Marketing Confederation | L4: =IF(K4="","MISSING",IF(AND(LEN(K4)>=50,LEN(K4)<=60),"OK 50-60 chars",IF(LEN(K4)<50,"SHORT: "&LEN(K4),"LONG: "&LEN(K4)))) -> LONG: 107 | M4: ABOUT The African Marketing Confederation​ The African Marketing Confederation is the ground-breaking Pan African body of marketing professionals spearheading the ongoing development of the highest possible standards of marketing across Africa. Founded in 2011, the AMC is a collaboration between the African national marketing bodies and associations to exchange expertise and information, and to promote | N4: =IF(M4="","MISSING",IF(AND(LEN(M4)>=120,LEN(M4)<=160),"OK 120-160 chars",IF(LEN(M4)<120,"SHORT: "&LEN(M4),"LONG: "&LEN(M4)))) -> LONG: 405 | O4: ABOUT The African Marketing Confederation​ | P4: =IF(OR(ISBLANK(O4),ISNUMBER(SEARCH("|",O4))),"FIX: MULTIPLE/MISSING","OK") -> OK | Q4: Helen McIntee | President and Co-founder | David Balikuddembe | Secretary General | R4: =IF(ISBLANK(Q4),"MISSING","OK") -> OK | S4: African Marketing Confederation ​ PRESIDENT’S COUNCIL | T4: =IF(ISBLANK(S4),"MISSING","OK") -> OK | V4: =IF(ISBLANK(U4),"MISSING","OK") -> MISSING | X4: =IF(ISBLANK(W4),"MISSING","OK") -> MISSING | Z4: =IF(ISBLANK(Y4),"MISSING","OK") -> MISSING | AA4: =HYPERLINK("https://africanmarketingconfederation.org/wp-admin/post.php?post=84&action=elementor","Open in Elementor") -> Open in Elementor | AB4: =HYPERLINK("https://africanmarketingconfederation.org/wp-content/uploads/2026/03/og-image.png","View Image") -> View Image | AC4: =IF(LEN("https://africanmarketingconfederation.org/wp-content/uploads/2026/03/og-image.png")>0, _xlfn.IMAGE("https://africanmarketingconfederation.org/wp-content/uploads/2026/03/og-image.png"), "") -> #VALUE! | AD4: =IFERROR(HYPERLINK("#'Main'!B"&MATCH(TRIM(H4),Main!B:B,0),"Open in Main"),IFERROR(HYPERLINK("#'Technical Diagnostics'!A"&MATCH(TRIM(H4),'Technical Diagnostics'!A:A,0),"Open in Technical"),"Not Found")) -> Open in Main
A5: =IF(B5>=85,"Complete","Needs Copy") -> Needs Copy | B5: =MIN(100,ROUND(0.3*(IF(L5="",0,IF(LEFT(L5,7)="MISSING",0,IF(ISNUMBER(SEARCH("OK",L5)),100,IF(ISNUMBER(SEARCH("SHORT",L5)),65,IF(ISNUMBER(SEARCH("LONG",L5)),50,70))))))+0.25*(IF(N5="",0,IF(LEFT(N5,7)="MISSING",0,IF(ISNUMBER(SEARCH("OK",N5)),100,IF(ISNUMBER(SEARCH("SHORT",N5)),65,IF(ISNUMBER(SEARCH("LONG",N5)),50,70))))))+0.2*(IF(P5="",0,IF(LEFT(P5,2)="OK",100,0)))+0.08*(IF(R5="",0,IF(LEFT(R5,2)="OK",100,0)))+0.06*(IF(T5="",0,IF(LEFT(T5,2)="OK",100,0)))+0.05*(IF(V5="",0,IF(LEFT(V5,2)="OK",100,0)))+0.03*(IF(X5="",0,IF(LEFT(X5,2)="OK",100,0)))+0.03*(IF(Z5="",0,IF(LEFT(Z5,2)="OK",100,0))),0)) -> 62 | C5: 77.5 | D5: 70 | E5: 100 | F5: To Do | G5: Copy Writer | H5: =HYPERLINK("https://africanmarketingconfederation.org/african-marketing-confederation-tourism-chapter","https://africanmarketingconfederation.org/african-marketing-confederation-tourism-chapter") -> https://africanmarketingconfederation.org/african-marketing-confederation-tourism-chapter | I5: =HYPERLINK("https://africanmarketingconfederation.org/african-marketing-confederation-tourism-chapter","African Marketing Confederation Tourism Chapter") -> African Marketing Confederation Tourism Chapter | J5: african-marketing-confederation-tourism-chapter | K5: African Marketing Confederation Tourism Chapter – African Marketing Confederation | L5: =IF(K5="","MISSING",IF(AND(LEN(K5)>=50,LEN(K5)<=60),"OK 50-60 chars",IF(LEN(K5)<50,"SHORT: "&LEN(K5),"LONG: "&LEN(K5)))) -> LONG: 81 | M5: African Marketing Confederation Tourism Chapter Shaping Africa’s Tourism Narrative Through Strategic Marketing Tourism is one of Africa’s most powerful economic engines - generating jobs, stimulating investment, and fostering cultural exchange.The African Marketing Confederation is proud to launch the Tourism Chapter, a bold initiative to elevate African tourism through the lens of world-class marketing. Launched at the | N5: =IF(M5="","MISSING",IF(AND(LEN(M5)>=120,LEN(M5)<=160),"OK 120-160 chars",IF(LEN(M5)<120,"SHORT: "&LEN(M5),"LONG: "&LEN(M5)))) -> LONG: 423 | O5: African Marketing Confederation Tourism Chapter | P5: =IF(OR(ISBLANK(O5),ISNUMBER(SEARCH("|",O5))),"FIX: MULTIPLE/MISSING","OK") -> OK | Q5: Charting the Course: Purpose, Mission & Vision for Africa’s Tourism Future | Our Goals and Objectives: | R5: =IF(ISBLANK(Q5),"MISSING","OK") -> OK | S5: Shaping Africa’s Tourism Narrative Through Strategic Marketing | T5: =IF(ISBLANK(S5),"MISSING","OK") -> OK | V5: =IF(ISBLANK(U5),"MISSING","OK") -> MISSING | X5: =IF(ISBLANK(W5),"MISSING","OK") -> MISSING | Z5: =IF(ISBLANK(Y5),"MISSING","OK") -> MISSING | AA5: =HYPERLINK("https://africanmarketingconfederation.org/wp-admin/post.php?post=28165&action=elementor","Open in Elementor") -> Open in Elementor | AB5: =HYPERLINK("https://africanmarketingconfederation.org/wp-content/uploads/2026/03/og-image.png","View Image") -> View Image | AC5: =IF(LEN("https://africanmarketingconfederation.org/wp-content/uploads/2026/03/og-image.png")>0, _xlfn.IMAGE("https://africanmarketingconfederation.org/wp-content/uploads/2026/03/og-image.png"), "") -> #VALUE! | AD5: =IFERROR(HYPERLINK("#'Main'!B"&MATCH(TRIM(H5),Main!B:B,0),"Open in Main"),IFERROR(HYPERLINK("#'Technical Diagnostics'!A"&MATCH(TRIM(H5),'Technical Diagnostics'!A:A,0),"Open in Technical"),"Not Found")) -> Open in Main
A6: =IF(B6>=85,"Complete","Needs Copy") -> Needs Copy | B6: =MIN(100,ROUND(0.3*(IF(L6="",0,IF(LEFT(L6,7)="MISSING",0,IF(ISNUMBER(SEARCH("OK",L6)),100,IF(ISNUMBER(SEARCH("SHORT",L6)),65,IF(ISNUMBER(SEARCH("LONG",L6)),50,70))))))+0.25*(IF(N6="",0,IF(LEFT(N6,7)="MISSING",0,IF(ISNUMBER(SEARCH("OK",N6)),100,IF(ISNUMBER(SEARCH("SHORT",N6)),65,IF(ISNUMBER(SEARCH("LONG",N6)),50,70))))))+0.2*(IF(P6="",0,IF(LEFT(P6,2)="OK",100,0)))+0.08*(IF(R6="",0,IF(LEFT(R6,2)="OK",100,0)))+0.06*(IF(T6="",0,IF(LEFT(T6,2)="OK",100,0)))+0.05*(IF(V6="",0,IF(LEFT(V6,2)="OK",100,0)))+0.03*(IF(X6="",0,IF(LEFT(X6,2)="OK",100,0)))+0.03*(IF(Z6="",0,IF(LEFT(Z6,2)="OK",100,0))),0)) -> 60 | C6: 70 | D6: 60 | E6: 100 | F6: To Do | G6: Copy Writer | H6: =HYPERLINK("https://africanmarketingconfederation.org/amc-awards-2024","https://africanmarketingconfederation.org/amc-awards-2024") -> https://africanmarketingconfederation.org/amc-awards-2024 | I6: =HYPERLINK("https://africanmarketingconfederation.org/amc-awards-2024","Amc Awards 2024") -> Amc Awards 2024 | J6: amc-awards-2024 | K6: AMC Awards 2024 – African Marketing Confederation | L6: =IF(K6="","MISSING",IF(AND(LEN(K6)>=50,LEN(K6)<=60),"OK 50-60 chars",IF(LEN(K6)<50,"SHORT: "&LEN(K6),"LONG: "&LEN(K6)))) -> SHORT: 49 | M6: NOMINATIONS are Open ! AMC Awards The African Marketing Confederation Awards event is held annually as part of the African Marketing Confederation Forum. This distinguished event celebrates and acknowledges outstanding marketing campaigns and the visionary individuals behind them. The awards presented honor not only the groundbreaking strategies and creative brilliance that set these campaigns apart but | N6: =IF(M6="","MISSING",IF(AND(LEN(M6)>=120,LEN(M6)<=160),"OK 120-160 chars",IF(LEN(M6)<120,"SHORT: "&LEN(M6),"LONG: "&LEN(M6)))) -> LONG: 406 | O6: NOMINATIONS are Open ! | P6: =IF(OR(ISBLANK(O6),ISNUMBER(SEARCH("|",O6))),"FIX: MULTIPLE/MISSING","OK") -> OK | Q6: Awards Categories | Tourism & Destination Marketing Campaign | of the Year | Best Social Media Campaign | R6: =IF(ISBLANK(Q6),"MISSING","OK") -> OK | T6: =IF(ISBLANK(S6),"MISSING","OK") -> MISSING | V6: =IF(ISBLANK(U6),"MISSING","OK") -> MISSING | X6: =IF(ISBLANK(W6),"MISSING","OK") -> MISSING | Z6: =IF(ISBLANK(Y6),"MISSING","OK") -> MISSING | AA6: =HYPERLINK("https://africanmarketingconfederation.org/wp-admin/post.php?post=16125&action=elementor","Open in Elementor") -> Open in Elementor | AB6: =HYPERLINK("https://africanmarketingconfederation.org/wp-content/uploads/2021/08/amc_faw.png","View Image") -> View Image | AC6: =IF(LEN("https://africanmarketingconfederation.org/wp-content/uploads/2021/08/amc_faw.png")>0, _xlfn.IMAGE("https://africanmarketingconfederation.org/wp-content/uploads/2021/08/amc_faw.png"), "") -> #VALUE! | AD6: =IFERROR(HYPERLINK("#'Main'!B"&MATCH(TRIM(H6),Main!B:B,0),"Open in Main"),IFERROR(HYPERLINK("#'Technical Diagnostics'!A"&MATCH(TRIM(H6),'Technical Diagnostics'!A:A,0),"Open in Technical"),"Not Found")) -> Open in Main
A7: =IF(B7>=85,"Complete","Needs Copy") -> Needs Copy | B7: =MIN(100,ROUND(0.3*(IF(L7="",0,IF(LEFT(L7,7)="MISSING",0,IF(ISNUMBER(SEARCH("OK",L7)),100,IF(ISNUMBER(SEARCH("SHORT",L7)),65,IF(ISNUMBER(SEARCH("LONG",L7)),50,70))))))+0.25*(IF(N7="",0,IF(LEFT(N7,7)="MISSING",0,IF(ISNUMBER(SEARCH("OK",N7)),100,IF(ISNUMBER(SEARCH("SHORT",N7)),65,IF(ISNUMBER(SEARCH("LONG",N7)),50,70))))))+0.2*(IF(P7="",0,IF(LEFT(P7,2)="OK",100,0)))+0.08*(IF(R7="",0,IF(LEFT(R7,2)="OK",100,0)))+0.06*(IF(T7="",0,IF(LEFT(T7,2)="OK",100,0)))+0.05*(IF(V7="",0,IF(LEFT(V7,2)="OK",100,0)))+0.03*(IF(X7="",0,IF(LEFT(X7,2)="OK",100,0)))+0.03*(IF(Z7="",0,IF(LEFT(Z7,2)="OK",100,0))),0)) -> 57 | C7: 56.92 | D7: 60 | E7: 47.67 | F7: To Do | G7: Copy Writer | H7: =HYPERLINK("https://africanmarketingconfederation.org/amc-conference-2022","https://africanmarketingconfederation.org/amc-conference-2022") -> https://africanmarketingconfederation.org/amc-conference-2022 | I7: =HYPERLINK("https://africanmarketingconfederation.org/amc-conference-2022","Amc Conference 2022") -> Amc Conference 2022 | J7: amc-conference-2022 | K7: AMC Conference 2022 – African Marketing Confederation | L7: =IF(K7="","MISSING",IF(AND(LEN(K7)>=50,LEN(K7)<=60),"OK 50-60 chars",IF(LEN(K7)<50,"SHORT: "&LEN(K7),"LONG: "&LEN(K7)))) -> OK 50-60 chars | M7: corinna kopf onlyfans leaks AMC Conference 2022 Thank you for attending19 - 22 October 2022 The African Marketing Confederation's Annual Conference brought together the best collection of marketing leaders from top companies, marketing bodies and associations to share tactics and best practices on how to build the next generation of marketing. Event Highlights Thank you for Attending! | N7: =IF(M7="","MISSING",IF(AND(LEN(M7)>=120,LEN(M7)<=160),"OK 120-160 chars",IF(LEN(M7)<120,"SHORT: "&LEN(M7),"LONG: "&LEN(M7)))) -> LONG: 387 | P7: =IF(OR(ISBLANK(O7),ISNUMBER(SEARCH("|",O7))),"FIX: MULTIPLE/MISSING","OK") -> FIX: MULTIPLE/MISSING | Q7: AMC Conference 2022 | Event Highlights | R7: =IF(ISBLANK(Q7),"MISSING","OK") -> OK | S7: AMC officially welcomes new member associations into the fold | Marketers are placing the ads where consumers don’t want to see them | Time for Africa to control its own narrative and image, delegates told | Excitement as Ghana announced as host of 2025 AMC marketing conference | T7: =IF(ISBLANK(S7),"MISSING","OK") -> OK | V7: =IF(ISBLANK(U7),"MISSING","OK") -> MISSING | X7: =IF(ISBLANK(W7),"MISSING","OK") -> MISSING | Z7: =IF(ISBLANK(Y7),"MISSING","OK") -> MISSING | AA7: =HYPERLINK("https://africanmarketingconfederation.org/wp-admin/post.php?post=4494&action=elementor","Open in Elementor") -> Open in Elementor | AB7: =HYPERLINK("https://africanmarketingconfederation.org/wp-content/uploads/2026/03/og-image.png","View Image") -> View Image | AC7: =IF(LEN("https://africanmarketingconfederation.org/wp-content/uploads/2026/03/og-image.png")>0, _xlfn.IMAGE("https://africanmarketingconfederation.org/wp-content/uploads/2026/03/og-image.png"), "") -> #VALUE! | AD7: =IFERROR(HYPERLINK("#'Main'!B"&MATCH(TRIM(H7),Main!B:B,0),"Open in Main"),IFERROR(HYPERLINK("#'Technical Diagnostics'!A"&MATCH(TRIM(H7),'Technical Diagnostics'!A:A,0),"Open in Technical"),"Not Found")) -> Open in Main
A8: =IF(B8>=85,"Complete","Needs Copy") -> Needs Copy | B8: =MIN(100,ROUND(0.3*(IF(L8="",0,IF(LEFT(L8,7)="MISSING",0,IF(ISNUMBER(SEARCH("OK",L8)),100,IF(ISNUMBER(SEARCH("SHORT",L8)),65,IF(ISNUMBER(SEARCH("LONG",L8)),50,70))))))+0.25*(IF(N8="",0,IF(LEFT(N8,7)="MISSING",0,IF(ISNUMBER(SEARCH("OK",N8)),100,IF(ISNUMBER(SEARCH("SHORT",N8)),65,IF(ISNUMBER(SEARCH("LONG",N8)),50,70))))))+0.2*(IF(P8="",0,IF(LEFT(P8,2)="OK",100,0)))+0.08*(IF(R8="",0,IF(LEFT(R8,2)="OK",100,0)))+0.06*(IF(T8="",0,IF(LEFT(T8,2)="OK",100,0)))+0.05*(IF(V8="",0,IF(LEFT(V8,2)="OK",100,0)))+0.03*(IF(X8="",0,IF(LEFT(X8,2)="OK",100,0)))+0.03*(IF(Z8="",0,IF(LEFT(Z8,2)="OK",100,0))),0)) -> 36 | C8: 58.75 | D8: 60 | E8: 55 | F8: To Do | G8: Copy Writer | H8: =HYPERLINK("https://africanmarketingconfederation.org/amc-conference-2022-prospectus","https://africanmarketingconfederation.org/amc-conference-2022-prospectus") -> https://africanmarketingconfederation.org/amc-conference-2022-prospectus | I8: =HYPERLINK("https://africanmarketingconfederation.org/amc-conference-2022-prospectus","Amc Conference 2022 Prospectus") -> Amc Conference 2022 Prospectus | J8: amc-conference-2022-prospectus | K8: AMC Conference 2022 – Prospectus – African Marketing Confederation | L8: =IF(K8="","MISSING",IF(AND(LEN(K8)>=50,LEN(K8)<=60),"OK 50-60 chars",IF(LEN(K8)<50,"SHORT: "&LEN(K8),"LONG: "&LEN(K8)))) -> LONG: 66 | M8: AMC Conference 2022 23 - 24 March 2022 Navigating Africa's Unique Marketing Mix BOOK NOW Days Hours Minutes Seconds download prospectus To download the AMC 2022 Conference Prospectus please complete the form below: First Name Last Name Email Mobile Company I've read and agree to the Privacy Policy BOOK NOW FOR THE AMC CONFERENCE 2022 | N8: =IF(M8="","MISSING",IF(AND(LEN(M8)>=120,LEN(M8)<=160),"OK 120-160 chars",IF(LEN(M8)<120,"SHORT: "&LEN(M8),"LONG: "&LEN(M8)))) -> LONG: 335 | P8: =IF(OR(ISBLANK(O8),ISNUMBER(SEARCH("|",O8))),"FIX: MULTIPLE/MISSING","OK") -> FIX: MULTIPLE/MISSING | Q8: AMC Conference 2022 | download prospectus | BOOK NOW FOR THE AMC CONFERENCE 2022 | R8: =IF(ISBLANK(Q8),"MISSING","OK") -> OK | T8: =IF(ISBLANK(S8),"MISSING","OK") -> MISSING | V8: =IF(ISBLANK(U8),"MISSING","OK") -> MISSING | X8: =IF(ISBLANK(W8),"MISSING","OK") -> MISSING | Z8: =IF(ISBLANK(Y8),"MISSING","OK") -> MISSING | AA8: =HYPERLINK("https://africanmarketingconfederation.org/wp-admin/post.php?post=5619&action=elementor","Open in Elementor") -> Open in Elementor | AB8: =HYPERLINK("https://africanmarketingconfederation.org/wp-content/uploads/2026/03/og-image.png","View Image") -> View Image | AC8: =IF(LEN("https://africanmarketingconfederation.org/wp-content/uploads/2026/03/og-image.png")>0, _xlfn.IMAGE("https://africanmarketingconfederation.org/wp-content/uploads/2026/03/og-image.png"), "") -> #VALUE! | AD8: =IFERROR(HYPERLINK("#'Main'!B"&MATCH(TRIM(H8),Main!B:B,0),"Open in Main"),IFERROR(HYPERLINK("#'Technical Diagnostics'!A"&MATCH(TRIM(H8),'Technical Diagnostics'!A:A,0),"Open in Technical"),"Not Found")) -> Open in Main
A9: =IF(B9>=85,"Complete","Needs Copy") -> Needs Copy | B9: =MIN(100,ROUND(0.3*(IF(L9="",0,IF(LEFT(L9,7)="MISSING",0,IF(ISNUMBER(SEARCH("OK",L9)),100,IF(ISNUMBER(SEARCH("SHORT",L9)),65,IF(ISNUMBER(SEARCH("LONG",L9)),50,70))))))+0.25*(IF(N9="",0,IF(LEFT(N9,7)="MISSING",0,IF(ISNUMBER(SEARCH("OK",N9)),100,IF(ISNUMBER(SEARCH("SHORT",N9)),65,IF(ISNUMBER(SEARCH("LONG",N9)),50,70))))))+0.2*(IF(P9="",0,IF(LEFT(P9,2)="OK",100,0)))+0.08*(IF(R9="",0,IF(LEFT(R9,2)="OK",100,0)))+0.06*(IF(T9="",0,IF(LEFT(T9,2)="OK",100,0)))+0.05*(IF(V9="",0,IF(LEFT(V9,2)="OK",100,0)))+0.03*(IF(X9="",0,IF(LEFT(X9,2)="OK",100,0)))+0.03*(IF(Z9="",0,IF(LEFT(Z9,2)="OK",100,0))),0)) -> 42 | C9: 62.5 | D9: 60 | E9: 70 | F9: To Do | G9: Copy Writer | H9: =HYPERLINK("https://africanmarketingconfederation.org/amc-conference-2022-thank-you","https://africanmarketingconfederation.org/amc-conference-2022-thank-you") -> https://africanmarketingconfederation.org/amc-conference-2022-thank-you | I9: =HYPERLINK("https://africanmarketingconfederation.org/amc-conference-2022-thank-you","Amc Conference 2022 Thank You") -> Amc Conference 2022 Thank You | J9: amc-conference-2022-thank-you | K9: AMC Conference 2022 – Thank You – African Marketing Confederation | L9: =IF(K9="","MISSING",IF(AND(LEN(K9)>=50,LEN(K9)<=60),"OK 50-60 chars",IF(LEN(K9)<50,"SHORT: "&LEN(K9),"LONG: "&LEN(K9)))) -> LONG: 65 | M9: AMC Conference 2022 23 - 24 March 2022 Navigating Africa's Unique Marketing Mix ENQUIRE NOW Days Hours Minutes Seconds Success! Thank you for completing the enquiry form. Our team will contact you shortly! × Dismiss alert The AMC Conference is the must attend Pan African event for marketing professionals. It will focus on solutions for | N9: =IF(M9="","MISSING",IF(AND(LEN(M9)>=120,LEN(M9)<=160),"OK 120-160 chars",IF(LEN(M9)<120,"SHORT: "&LEN(M9),"LONG: "&LEN(M9)))) -> LONG: 337 | P9: =IF(OR(ISBLANK(O9),ISNUMBER(SEARCH("|",O9))),"FIX: MULTIPLE/MISSING","OK") -> FIX: MULTIPLE/MISSING | Q9: AMC Conference 2022 | WHO SHOULD ATTEND | Countries Participating | R9: =IF(ISBLANK(Q9),"MISSING","OK") -> OK | S9: South Africa | Nigeria | Morocco | T9: =IF(ISBLANK(S9),"MISSING","OK") -> OK | V9: =IF(ISBLANK(U9),"MISSING","OK") -> MISSING | X9: =IF(ISBLANK(W9),"MISSING","OK") -> MISSING | Z9: =IF(ISBLANK(Y9),"MISSING","OK") -> MISSING | AA9: =HYPERLINK("https://africanmarketingconfederation.org/wp-admin/post.php?post=4941&action=elementor","Open in Elementor") -> Open in Elementor | AB9: =HYPERLINK("https://africanmarketingconfederation.org/wp-content/uploads/2026/03/og-image.png","View Image") -> View Image | AC9: =IF(LEN("https://africanmarketingconfederation.org/wp-content/uploads/2026/03/og-image.png")>0, _xlfn.IMAGE("https://africanmarketingconfederation.org/wp-content/uploads/2026/03/og-image.png"), "") -> #VALUE! | AD9: =IFERROR(HYPERLINK("#'Main'!B"&MATCH(TRIM(H9),Main!B:B,0),"Open in Main"),IFERROR(HYPERLINK("#'Technical Diagnostics'!A"&MATCH(TRIM(H9),'Technical Diagnostics'!A:A,0),"Open in Technical"),"Not Found")) -> Open in Main
A10: =IF(B10>=85,"Complete","Needs Copy") -> Needs Copy | B10: =MIN(100,ROUND(0.3*(IF(L10="",0,IF(LEFT(L10,7)="MISSING",0,IF(ISNUMBER(SEARCH("OK",L10)),100,IF(ISNUMBER(SEARCH("SHORT",L10)),65,IF(ISNUMBER(SEARCH("LONG",L10)),50,70))))))+0.25*(IF(N10="",0,IF(LEFT(N10,7)="MISSING",0,IF(ISNUMBER(SEARCH("OK",N10)),100,IF(ISNUMBER(SEARCH("SHORT",N10)),65,IF(ISNUMBER(SEARCH("LONG",N10)),50,70))))))+0.2*(IF(P10="",0,IF(LEFT(P10,2)="OK",100,0)))+0.08*(IF(R10="",0,IF(LEFT(R10,2)="OK",100,0)))+0.06*(IF(T10="",0,IF(LEFT(T10,2)="OK",100,0)))+0.05*(IF(V10="",0,IF(LEFT(V10,2)="OK",100,0)))+0.03*(IF(X10="",0,IF(LEFT(X10,2)="OK",100,0)))+0.03*(IF(Z10="",0,IF(LEFT(Z10,2)="OK",100,0))),0)) -> 77 | C10: 77.5 | D10: 70 | E10: 100 | F10: To Do | G10: Copy Writer | H10: =HYPERLINK("https://africanmarketingconfederation.org/amc-conference-2023","https://africanmarketingconfederation.org/amc-conference-2023") -> https://africanmarketingconfederation.org/amc-conference-2023 | I10: =HYPERLINK("https://africanmarketingconfederation.org/amc-conference-2023","Amc Conference 2023") -> Amc Conference 2023 | J10: amc-conference-2023 | K10: AMC Conference 2023 – African Marketing Confederation | L10: =IF(K10="","MISSING",IF(AND(LEN(K10)>=50,LEN(K10)<=60),"OK 50-60 chars",IF(LEN(K10)<50,"SHORT: "&LEN(K10),"LONG: "&LEN(K10)))) -> OK 50-60 chars | M10: AMC Conference 6 - 9 September 2023 Imperial Botanical Beach Hotel, Entebbe, Uganda Thank you for joining us! View Presentations 2nd Annual African Marketing Confederation Conference Africa's $3.4 trillion Economy: Opportunities for Marketers Welcome to the Recap of the 2nd Annual African Marketing Conference: Unveiling Africa's $3.4 Trillion EconomyOur conference was a remarkable exploration of | N10: =IF(M10="","MISSING",IF(AND(LEN(M10)>=120,LEN(M10)<=160),"OK 120-160 chars",IF(LEN(M10)<120,"SHORT: "&LEN(M10),"LONG: "&LEN(M10)))) -> LONG: 398 | O10: AMC Conference | P10: =IF(OR(ISBLANK(O10),ISNUMBER(SEARCH("|",O10))),"FIX: MULTIPLE/MISSING","OK") -> OK | Q10: Africa's $3.4 trillion Economy: Opportunities for Marketers | Thank you for joining us! | Topics covered | R10: =IF(ISBLANK(Q10),"MISSING","OK") -> OK | S10: Africa Free Trade Area | Business Intelligence | T10: =IF(ISBLANK(S10),"MISSING","OK") -> OK | V10: =IF(ISBLANK(U10),"MISSING","OK") -> MISSING | X10: =IF(ISBLANK(W10),"MISSING","OK") -> MISSING | Z10: =IF(ISBLANK(Y10),"MISSING","OK") -> MISSING | AA10: =HYPERLINK("https://africanmarketingconfederation.org/wp-admin/post.php?post=12371&action=elementor","Open in Elementor") -> Open in Elementor | AB10: =HYPERLINK("https://africanmarketingconfederation.org/wp-content/uploads/2021/08/amc_faw.png","View Image") -> View Image | AC10: =IF(LEN("https://africanmarketingconfederation.org/wp-content/uploads/2021/08/amc_faw.png")>0, _xlfn.IMAGE("https://africanmarketingconfederation.org/wp-content/uploads/2021/08/amc_faw.png"), "") -> #VALUE! | AD10: =IFERROR(HYPERLINK("#'Main'!B"&MATCH(TRIM(H10),Main!B:B,0),"Open in Main"),IFERROR(HYPERLINK("#'Technical Diagnostics'!A"&MATCH(TRIM(H10),'Technical Diagnostics'!A:A,0),"Open in Technical"),"Not Found")) -> Open in Main
A11: =IF(B11>=85,"Complete","Needs Copy") -> Needs Copy | B11: =MIN(100,ROUND(0.3*(IF(L11="",0,IF(LEFT(L11,7)="MISSING",0,IF(ISNUMBER(SEARCH("OK",L11)),100,IF(ISNUMBER(SEARCH("SHORT",L11)),65,IF(ISNUMBER(SEARCH("LONG",L11)),50,70))))))+0.25*(IF(N11="",0,IF(LEFT(N11,7)="MISSING",0,IF(ISNUMBER(SEARCH("OK",N11)),100,IF(ISNUMBER(SEARCH("SHORT",N11)),65,IF(ISNUMBER(SEARCH("LONG",N11)),50,70))))))+0.2*(IF(P11="",0,IF(LEFT(P11,2)="OK",100,0)))+0.08*(IF(R11="",0,IF(LEFT(R11,2)="OK",100,0)))+0.06*(IF(T11="",0,IF(LEFT(T11,2)="OK",100,0)))+0.05*(IF(V11="",0,IF(LEFT(V11,2)="OK",100,0)))+0.03*(IF(X11="",0,IF(LEFT(X11,2)="OK",100,0)))+0.03*(IF(Z11="",0,IF(LEFT(Z11,2)="OK",100,0))),0)) -> 60 | C11: 77.5 | D11: 70 | E11: 100 | F11: To Do | G11: Copy Writer | H11: =HYPERLINK("https://africanmarketingconfederation.org/amc-conference-2023/amc-awards","https://africanmarketingconfederation.org/amc-conference-2023/amc-awards") -> https://africanmarketingconfederation.org/amc-conference-2023/amc-awards | I11: =HYPERLINK("https://africanmarketingconfederation.org/amc-conference-2023/amc-awards","Amc Awards") -> Amc Awards | J11: amc-awards | K11: AMC Awards – African Marketing Confederation | L11: =IF(K11="","MISSING",IF(AND(LEN(K11)>=50,LEN(K11)<=60),"OK 50-60 chars",IF(LEN(K11)<50,"SHORT: "&LEN(K11),"LONG: "&LEN(K11)))) -> SHORT: 44 | M11: AMC Awards Welcome to the prestigious African Marketing Confederation Awards, a distinguished event that celebrates and acknowledges the remarkable achievements, cutting-edge innovations, and exceptional leadership demonstrated by outstanding individuals within the dynamic realm of marketing across the expansive African region.During the 2nd Annual African Marketing Confederation Conference, held from 6th to 9th September at the | N11: =IF(M11="","MISSING",IF(AND(LEN(M11)>=120,LEN(M11)<=160),"OK 120-160 chars",IF(LEN(M11)<120,"SHORT: "&LEN(M11),"LONG: "&LEN(M11)))) -> LONG: 432 | O11: AMC Awards | P11: =IF(OR(ISBLANK(O11),ISNUMBER(SEARCH("|",O11))),"FIX: MULTIPLE/MISSING","OK") -> OK | Q11: AMC AWARD Winners | R11: =IF(ISBLANK(Q11),"MISSING","OK") -> OK | T11: =IF(ISBLANK(S11),"MISSING","OK") -> MISSING | V11: =IF(ISBLANK(U11),"MISSING","OK") -> MISSING | X11: =IF(ISBLANK(W11),"MISSING","OK") -> MISSING | Z11: =IF(ISBLANK(Y11),"MISSING","OK") -> MISSING | AA11: =HYPERLINK("https://africanmarketingconfederation.org/wp-admin/post.php?post=12954&action=elementor","Open in Elementor") -> Open in Elementor | AB11: =HYPERLINK("https://africanmarketingconfederation.org/wp-content/uploads/2021/08/amc_faw.png","View Image") -> View Image | AC11: =IF(LEN("https://africanmarketingconfederation.org/wp-content/uploads/2021/08/amc_faw.png")>0, _xlfn.IMAGE("https://africanmarketingconfederation.org/wp-content/uploads/2021/08/amc_faw.png"), "") -> #VALUE! | AD11: =IFERROR(HYPERLINK("#'Main'!B"&MATCH(TRIM(H11),Main!B:B,0),"Open in Main"),IFERROR(HYPERLINK("#'Technical Diagnostics'!A"&MATCH(TRIM(H11),'Technical Diagnostics'!A:A,0),"Open in Technical"),"Not Found")) -> Open in Main
A12: =IF(B12>=85,"Complete","Needs Copy") -> Needs Copy | B12: =MIN(100,ROUND(0.3*(IF(L12="",0,IF(LEFT(L12,7)="MISSING",0,IF(ISNUMBER(SEARCH("OK",L12)),100,IF(ISNUMBER(SEARCH("SHORT",L12)),65,IF(ISNUMBER(SEARCH("LONG",L12)),50,70))))))+0.25*(IF(N12="",0,IF(LEFT(N12,7)="MISSING",0,IF(ISNUMBER(SEARCH("OK",N12)),100,IF(ISNUMBER(SEARCH("SHORT",N12)),65,IF(ISNUMBER(SEARCH("LONG",N12)),50,70))))))+0.2*(IF(P12="",0,IF(LEFT(P12,2)="OK",100,0)))+0.08*(IF(R12="",0,IF(LEFT(R12,2)="OK",100,0)))+0.06*(IF(T12="",0,IF(LEFT(T12,2)="OK",100,0)))+0.05*(IF(V12="",0,IF(LEFT(V12,2)="OK",100,0)))+0.03*(IF(X12="",0,IF(LEFT(X12,2)="OK",100,0)))+0.03*(IF(Z12="",0,IF(LEFT(Z12,2)="OK",100,0))),0)) -> 46 | C12: 44.4 | D12: 50 | E12: 27.58 | F12: To Do | G12: Copy Writer | H12: =HYPERLINK("https://africanmarketingconfederation.org/amc-conference-2023/amc-awards-book-now","https://africanmarketingconfederation.org/amc-conference-2023/amc-awards-book-now") -> https://africanmarketingconfederation.org/amc-conference-2023/amc-awards-book-now | I12: =HYPERLINK("https://africanmarketingconfederation.org/amc-conference-2023/amc-awards-book-now","Amc Awards Book Now") -> Amc Awards Book Now | J12: amc-awards-book-now | K12: AMC Awards | Book Now – African Marketing Confederation | L12: =IF(K12="","MISSING",IF(AND(LEN(K12)>=50,LEN(K12)<=60),"OK 50-60 chars",IF(LEN(K12)<50,"SHORT: "&LEN(K12),"LONG: "&LEN(K12)))) -> OK 50-60 chars | M12: MISSING DESCRIPTION | N12: =IF(M12="","MISSING",IF(AND(LEN(M12)>=120,LEN(M12)<=160),"OK 120-160 chars",IF(LEN(M12)<120,"SHORT: "&LEN(M12),"LONG: "&LEN(M12)))) -> SHORT: 19 | P12: =IF(OR(ISBLANK(O12),ISNUMBER(SEARCH("|",O12))),"FIX: MULTIPLE/MISSING","OK") -> FIX: MULTIPLE/MISSING | R12: =IF(ISBLANK(Q12),"MISSING","OK") -> MISSING | T12: =IF(ISBLANK(S12),"MISSING","OK") -> MISSING | V12: =IF(ISBLANK(U12),"MISSING","OK") -> MISSING | X12: =IF(ISBLANK(W12),"MISSING","OK") -> MISSING | Z12: =IF(ISBLANK(Y12),"MISSING","OK") -> MISSING | AA12: =HYPERLINK("https://africanmarketingconfederation.org/wp-admin/post.php?post=13164&action=elementor","Open in Elementor") -> Open in Elementor | AB12: =HYPERLINK("https://africanmarketingconfederation.org/wp-content/uploads/2021/08/amc_faw.png","View Image") -> View Image | AC12: =IF(LEN("https://africanmarketingconfederation.org/wp-content/uploads/2021/08/amc_faw.png")>0, _xlfn.IMAGE("https://africanmarketingconfederation.org/wp-content/uploads/2021/08/amc_faw.png"), "") -> #VALUE! | AD12: =IFERROR(HYPERLINK("#'Main'!B"&MATCH(TRIM(H12),Main!B:B,0),"Open in Main"),IFERROR(HYPERLINK("#'Technical Diagnostics'!A"&MATCH(TRIM(H12),'Technical Diagnostics'!A:A,0),"Open in Technical"),"Not Found")) -> Open in Main
A13: =IF(B13>=85,"Complete","Needs Copy") -> Needs Copy | B13: =MIN(100,ROUND(0.3*(IF(L13="",0,IF(LEFT(L13,7)="MISSING",0,IF(ISNUMBER(SEARCH("OK",L13)),100,IF(ISNUMBER(SEARCH("SHORT",L13)),65,IF(ISNUMBER(SEARCH("LONG",L13)),50,70))))))+0.25*(IF(N13="",0,IF(LEFT(N13,7)="MISSING",0,IF(ISNUMBER(SEARCH("OK",N13)),100,IF(ISNUMBER(SEARCH("SHORT",N13)),65,IF(ISNUMBER(SEARCH("LONG",N13)),50,70))))))+0.2*(IF(P13="",0,IF(LEFT(P13,2)="OK",100,0)))+0.08*(IF(R13="",0,IF(LEFT(R13,2)="OK",100,0)))+0.06*(IF(T13="",0,IF(LEFT(T13,2)="OK",100,0)))+0.05*(IF(V13="",0,IF(LEFT(V13,2)="OK",100,0)))+0.03*(IF(X13="",0,IF(LEFT(X13,2)="OK",100,0)))+0.03*(IF(Z13="",0,IF(LEFT(Z13,2)="OK",100,0))),0)) -> 58 | C13: 75.31 | D13: 70 | E13: 91.25 | F13: To Do | G13: Copy Writer | H13: =HYPERLINK("https://africanmarketingconfederation.org/amc-conference-2023/book-now","https://africanmarketingconfederation.org/amc-conference-2023/book-now") -> https://africanmarketingconfederation.org/amc-conference-2023/book-now | I13: =HYPERLINK("https://africanmarketingconfederation.org/amc-conference-2023/book-now","Book Now") -> Book Now | J13: book-now | K13: Book Now – African Marketing Confederation | L13: =IF(K13="","MISSING",IF(AND(LEN(K13)>=50,LEN(K13)<=60),"OK 50-60 chars",IF(LEN(K13)<50,"SHORT: "&LEN(K13),"LONG: "&LEN(K13)))) -> SHORT: 42 | M13: Book Now Individual Booking Package Options 1: Full Conference + Accommodation 5 - 9 September 2023 890 USD 3 Day Conference Including Excursions: 5 Sept - Networking evening and light dinner 6 Sept - Official opening and barbecue dinner 7 Sept - Sunset Cruise on Lake Victoria 8 Sept - Cultural Gala dinner at Ndere | N13: =IF(M13="","MISSING",IF(AND(LEN(M13)>=120,LEN(M13)<=160),"OK 120-160 chars",IF(LEN(M13)<120,"SHORT: "&LEN(M13),"LONG: "&LEN(M13)))) -> LONG: 316 | O13: Book Now | P13: =IF(OR(ISBLANK(O13),ISNUMBER(SEARCH("|",O13))),"FIX: MULTIPLE/MISSING","OK") -> OK | R13: =IF(ISBLANK(Q13),"MISSING","OK") -> MISSING | S13: Individual Booking | Group Bookings | T13: =IF(ISBLANK(S13),"MISSING","OK") -> OK | V13: =IF(ISBLANK(U13),"MISSING","OK") -> MISSING | X13: =IF(ISBLANK(W13),"MISSING","OK") -> MISSING | Z13: =IF(ISBLANK(Y13),"MISSING","OK") -> MISSING | AA13: =HYPERLINK("https://africanmarketingconfederation.org/wp-admin/post.php?post=12407&action=elementor","Open in Elementor") -> Open in Elementor | AB13: =HYPERLINK("https://africanmarketingconfederation.org/wp-content/uploads/2021/08/amc_faw.png","View Image") -> View Image | AC13: =IF(LEN("https://africanmarketingconfederation.org/wp-content/uploads/2021/08/amc_faw.png")>0, _xlfn.IMAGE("https://africanmarketingconfederation.org/wp-content/uploads/2021/08/amc_faw.png"), "") -> #VALUE! | AD13: =IFERROR(HYPERLINK("#'Main'!B"&MATCH(TRIM(H13),Main!B:B,0),"Open in Main"),IFERROR(HYPERLINK("#'Technical Diagnostics'!A"&MATCH(TRIM(H13),'Technical Diagnostics'!A:A,0),"Open in Technical"),"Not Found")) -> Open in Main
A14: =IF(B14>=85,"Complete","Needs Copy") -> Needs Copy | B14: =MIN(100,ROUND(0.3*(IF(L14="",0,IF(LEFT(L14,7)="MISSING",0,IF(ISNUMBER(SEARCH("OK",L14)),100,IF(ISNUMBER(SEARCH("SHORT",L14)),65,IF(ISNUMBER(SEARCH("LONG",L14)),50,70))))))+0.25*(IF(N14="",0,IF(LEFT(N14,7)="MISSING",0,IF(ISNUMBER(SEARCH("OK",N14)),100,IF(ISNUMBER(SEARCH("SHORT",N14)),65,IF(ISNUMBER(SEARCH("LONG",N14)),50,70))))))+0.2*(IF(P14="",0,IF(LEFT(P14,2)="OK",100,0)))+0.08*(IF(R14="",0,IF(LEFT(R14,2)="OK",100,0)))+0.06*(IF(T14="",0,IF(LEFT(T14,2)="OK",100,0)))+0.05*(IF(V14="",0,IF(LEFT(V14,2)="OK",100,0)))+0.03*(IF(X14="",0,IF(LEFT(X14,2)="OK",100,0)))+0.03*(IF(Z14="",0,IF(LEFT(Z14,2)="OK",100,0))),0)) -> 51 | C14: 65.77 | D14: 70 | E14: 53.08 | F14: To Do | G14: Copy Writer | H14: =HYPERLINK("https://africanmarketingconfederation.org/amc-conference-2023/book-now-thank-you","https://africanmarketingconfederation.org/amc-conference-2023/book-now-thank-you") -> https://africanmarketingconfederation.org/amc-conference-2023/book-now-thank-you | I14: =HYPERLINK("https://africanmarketingconfederation.org/amc-conference-2023/book-now-thank-you","Book Now Thank You") -> Book Now Thank You | J14: book-now-thank-you | K14: Book Now | Thank you – African Marketing Confederation | L14: =IF(K14="","MISSING",IF(AND(LEN(K14)>=50,LEN(K14)<=60),"OK 50-60 chars",IF(LEN(K14)<50,"SHORT: "&LEN(K14),"LONG: "&LEN(K14)))) -> OK 50-60 chars | M14: Thank you for completing your booking! Congratulations on booking your seat to the 2023 AfricaPro Conference presenting the 2nd Annual African Marketing Confederation Conference and Inaugural Technology Information Confederation Africa Conference! You will receive your email confirmation shortly with more event information. Be sure to keep an eye on the event website for up to | N14: =IF(M14="","MISSING",IF(AND(LEN(M14)>=120,LEN(M14)<=160),"OK 120-160 chars",IF(LEN(M14)<120,"SHORT: "&LEN(M14),"LONG: "&LEN(M14)))) -> LONG: 379 | P14: =IF(OR(ISBLANK(O14),ISNUMBER(SEARCH("|",O14))),"FIX: MULTIPLE/MISSING","OK") -> FIX: MULTIPLE/MISSING | Q14: Thank you for completing your booking! | R14: =IF(ISBLANK(Q14),"MISSING","OK") -> OK | T14: =IF(ISBLANK(S14),"MISSING","OK") -> MISSING | V14: =IF(ISBLANK(U14),"MISSING","OK") -> MISSING | X14: =IF(ISBLANK(W14),"MISSING","OK") -> MISSING | Z14: =IF(ISBLANK(Y14),"MISSING","OK") -> MISSING | AA14: =HYPERLINK("https://africanmarketingconfederation.org/wp-admin/post.php?post=12497&action=elementor","Open in Elementor") -> Open in Elementor | AB14: =HYPERLINK("https://africanmarketingconfederation.org/wp-content/uploads/2021/08/amc_faw.png","View Image") -> View Image | AC14: =IF(LEN("https://africanmarketingconfederation.org/wp-content/uploads/2021/08/amc_faw.png")>0, _xlfn.IMAGE("https://africanmarketingconfederation.org/wp-content/uploads/2021/08/amc_faw.png"), "") -> #VALUE! | AD14: =IFERROR(HYPERLINK("#'Main'!B"&MATCH(TRIM(H14),Main!B:B,0),"Open in Main"),IFERROR(HYPERLINK("#'Technical Diagnostics'!A"&MATCH(TRIM(H14),'Technical Diagnostics'!A:A,0),"Open in Technical"),"Not Found")) -> Open in Main
A15: =IF(B15>=85,"Complete","Needs Copy") -> Needs Copy | B15: =MIN(100,ROUND(0.3*(IF(L15="",0,IF(LEFT(L15,7)="MISSING",0,IF(ISNUMBER(SEARCH("OK",L15)),100,IF(ISNUMBER(SEARCH("SHORT",L15)),65,IF(ISNUMBER(SEARCH("LONG",L15)),50,70))))))+0.25*(IF(N15="",0,IF(LEFT(N15,7)="MISSING",0,IF(ISNUMBER(SEARCH("OK",N15)),100,IF(ISNUMBER(SEARCH("SHORT",N15)),65,IF(ISNUMBER(SEARCH("LONG",N15)),50,70))))))+0.2*(IF(P15="",0,IF(LEFT(P15,2)="OK",100,0)))+0.08*(IF(R15="",0,IF(LEFT(R15,2)="OK",100,0)))+0.06*(IF(T15="",0,IF(LEFT(T15,2)="OK",100,0)))+0.05*(IF(V15="",0,IF(LEFT(V15,2)="OK",100,0)))+0.03*(IF(X15="",0,IF(LEFT(X15,2)="OK",100,0)))+0.03*(IF(Z15="",0,IF(LEFT(Z15,2)="OK",100,0))),0)) -> 71 | C15: 73.56 | D15: 70 | E15: 84.25 | F15: To Do | G15: Copy Writer | H15: =HYPERLINK("https://africanmarketingconfederation.org/amc-conference-2023/download-prospectus","https://africanmarketingconfederation.org/amc-conference-2023/download-prospectus") -> https://africanmarketingconfederation.org/amc-conference-2023/download-prospectus | I15: =HYPERLINK("https://africanmarketingconfederation.org/amc-conference-2023/download-prospectus","Download Prospectus") -> Download Prospectus | J15: download-prospectus | K15: Download Prospectus – African Marketing Confederation | L15: =IF(K15="","MISSING",IF(AND(LEN(K15)>=50,LEN(K15)<=60),"OK 50-60 chars",IF(LEN(K15)<50,"SHORT: "&LEN(K15),"LONG: "&LEN(K15)))) -> OK 50-60 chars | M15: BOOK NOW Prospectus Download the African Marketing Confederation Prospectus Learn more about the available sponsorship and exhibitor packages and how you can be a part of this exciting event First Name Last Name Email Position Are you a member of a country member body?--Select--Yes No I would like to receive monthly updates from AMCYes No | N15: =IF(M15="","MISSING",IF(AND(LEN(M15)>=120,LEN(M15)<=160),"OK 120-160 chars",IF(LEN(M15)<120,"SHORT: "&LEN(M15),"LONG: "&LEN(M15)))) -> LONG: 340 | O15: Prospectus | P15: =IF(OR(ISBLANK(O15),ISNUMBER(SEARCH("|",O15))),"FIX: MULTIPLE/MISSING","OK") -> OK | Q15: Prospectus | R15: =IF(ISBLANK(Q15),"MISSING","OK") -> OK | T15: =IF(ISBLANK(S15),"MISSING","OK") -> MISSING | V15: =IF(ISBLANK(U15),"MISSING","OK") -> MISSING | X15: =IF(ISBLANK(W15),"MISSING","OK") -> MISSING | Z15: =IF(ISBLANK(Y15),"MISSING","OK") -> MISSING | AA15: =HYPERLINK("https://africanmarketingconfederation.org/wp-admin/post.php?post=13098&action=elementor","Open in Elementor") -> Open in Elementor | AB15: =HYPERLINK("https://africanmarketingconfederation.org/wp-content/uploads/2023/08/AMC-Logo-03.png","View Image") -> View Image | AC15: =IF(LEN("https://africanmarketingconfederation.org/wp-content/uploads/2023/08/AMC-Logo-03.png")>0, _xlfn.IMAGE("https://africanmarketingconfederation.org/wp-content/uploads/2023/08/AMC-Logo-03.png"), "") -> #VALUE! | AD15: =IFERROR(HYPERLINK("#'Main'!B"&MATCH(TRIM(H15),Main!B:B,0),"Open in Main"),IFERROR(HYPERLINK("#'Technical Diagnostics'!A"&MATCH(TRIM(H15),'Technical Diagnostics'!A:A,0),"Open in Technical"),"Not Found")) -> Open in Main
A16: =IF(B16>=85,"Complete","Needs Copy") -> Needs Copy | B16: =MIN(100,ROUND(0.3*(IF(L16="",0,IF(LEFT(L16,7)="MISSING",0,IF(ISNUMBER(SEARCH("OK",L16)),100,IF(ISNUMBER(SEARCH("SHORT",L16)),65,IF(ISNUMBER(SEARCH("LONG",L16)),50,70))))))+0.25*(IF(N16="",0,IF(LEFT(N16,7)="MISSING",0,IF(ISNUMBER(SEARCH("OK",N16)),100,IF(ISNUMBER(SEARCH("SHORT",N16)),65,IF(ISNUMBER(SEARCH("LONG",N16)),50,70))))))+0.2*(IF(P16="",0,IF(LEFT(P16,2)="OK",100,0)))+0.08*(IF(R16="",0,IF(LEFT(R16,2)="OK",100,0)))+0.06*(IF(T16="",0,IF(LEFT(T16,2)="OK",100,0)))+0.05*(IF(V16="",0,IF(LEFT(V16,2)="OK",100,0)))+0.03*(IF(X16="",0,IF(LEFT(X16,2)="OK",100,0)))+0.03*(IF(Z16="",0,IF(LEFT(Z16,2)="OK",100,0))),0)) -> 56 | C16: 72.21 | D16: 70 | E16: 78.83 | F16: To Do | G16: Copy Writer | H16: =HYPERLINK("https://africanmarketingconfederation.org/amc-conference-2023/gallery","https://africanmarketingconfederation.org/amc-conference-2023/gallery") -> https://africanmarketingconfederation.org/amc-conference-2023/gallery | I16: =HYPERLINK("https://africanmarketingconfederation.org/amc-conference-2023/gallery","Gallery") -> Gallery | J16: gallery | K16: Gallery – African Marketing Confederation | L16: =IF(K16="","MISSING",IF(AND(LEN(K16)>=50,LEN(K16)<=60),"OK 50-60 chars",IF(LEN(K16)<50,"SHORT: "&LEN(K16),"LONG: "&LEN(K16)))) -> SHORT: 41 | M16: Conference Gallery sydney sweeney met gala All Day 1 Day 2 Day 3 Night 1 Night 2 Night 3 | N16: =IF(M16="","MISSING",IF(AND(LEN(M16)>=120,LEN(M16)<=160),"OK 120-160 chars",IF(LEN(M16)<120,"SHORT: "&LEN(M16),"LONG: "&LEN(M16)))) -> SHORT: 88 | O16: Conference Gallery | P16: =IF(OR(ISBLANK(O16),ISNUMBER(SEARCH("|",O16))),"FIX: MULTIPLE/MISSING","OK") -> OK | R16: =IF(ISBLANK(Q16),"MISSING","OK") -> MISSING | T16: =IF(ISBLANK(S16),"MISSING","OK") -> MISSING | V16: =IF(ISBLANK(U16),"MISSING","OK") -> MISSING | X16: =IF(ISBLANK(W16),"MISSING","OK") -> MISSING | Z16: =IF(ISBLANK(Y16),"MISSING","OK") -> MISSING | AA16: =HYPERLINK("https://africanmarketingconfederation.org/wp-admin/post.php?post=13549&action=elementor","Open in Elementor") -> Open in Elementor | AB16: =HYPERLINK("https://africanmarketingconfederation.org/wp-content/uploads/2021/08/amc_faw.png","View Image") -> View Image | AC16: =IF(LEN("https://africanmarketingconfederation.org/wp-content/uploads/2021/08/amc_faw.png")>0, _xlfn.IMAGE("https://africanmarketingconfederation.org/wp-content/uploads/2021/08/amc_faw.png"), "") -> #VALUE! | AD16: =IFERROR(HYPERLINK("#'Main'!B"&MATCH(TRIM(H16),Main!B:B,0),"Open in Main"),IFERROR(HYPERLINK("#'Technical Diagnostics'!A"&MATCH(TRIM(H16),'Technical Diagnostics'!A:A,0),"Open in Technical"),"Not Found")) -> Open in Main
A17: =IF(B17>=85,"Complete","Needs Copy") -> Needs Copy | B17: =MIN(100,ROUND(0.3*(IF(L17="",0,IF(LEFT(L17,7)="MISSING",0,IF(ISNUMBER(SEARCH("OK",L17)),100,IF(ISNUMBER(SEARCH("SHORT",L17)),65,IF(ISNUMBER(SEARCH("LONG",L17)),50,70))))))+0.25*(IF(N17="",0,IF(LEFT(N17,7)="MISSING",0,IF(ISNUMBER(SEARCH("OK",N17)),100,IF(ISNUMBER(SEARCH("SHORT",N17)),65,IF(ISNUMBER(SEARCH("LONG",N17)),50,70))))))+0.2*(IF(P17="",0,IF(LEFT(P17,2)="OK",100,0)))+0.08*(IF(R17="",0,IF(LEFT(R17,2)="OK",100,0)))+0.06*(IF(T17="",0,IF(LEFT(T17,2)="OK",100,0)))+0.05*(IF(V17="",0,IF(LEFT(V17,2)="OK",100,0)))+0.03*(IF(X17="",0,IF(LEFT(X17,2)="OK",100,0)))+0.03*(IF(Z17="",0,IF(LEFT(Z17,2)="OK",100,0))),0)) -> 56 | C17: 72 | D17: 70 | E17: 78 | F17: To Do | G17: Copy Writer | H17: =HYPERLINK("https://africanmarketingconfederation.org/amc-conference-2023/partners","https://africanmarketingconfederation.org/amc-conference-2023/partners") -> https://africanmarketingconfederation.org/amc-conference-2023/partners | I17: =HYPERLINK("https://africanmarketingconfederation.org/amc-conference-2023/partners","Partners") -> Partners | J17: partners | K17: Partners – African Marketing Confederation | L17: =IF(K17="","MISSING",IF(AND(LEN(K17)>=50,LEN(K17)<=60),"OK 50-60 chars",IF(LEN(K17)<50,"SHORT: "&LEN(K17),"LONG: "&LEN(K17)))) -> SHORT: 42 | M17: Conference Partners AMC Member Bodies | N17: =IF(M17="","MISSING",IF(AND(LEN(M17)>=120,LEN(M17)<=160),"OK 120-160 chars",IF(LEN(M17)<120,"SHORT: "&LEN(M17),"LONG: "&LEN(M17)))) -> SHORT: 37 | O17: Conference Partners | P17: =IF(OR(ISBLANK(O17),ISNUMBER(SEARCH("|",O17))),"FIX: MULTIPLE/MISSING","OK") -> OK | R17: =IF(ISBLANK(Q17),"MISSING","OK") -> MISSING | T17: =IF(ISBLANK(S17),"MISSING","OK") -> MISSING | V17: =IF(ISBLANK(U17),"MISSING","OK") -> MISSING | X17: =IF(ISBLANK(W17),"MISSING","OK") -> MISSING | Z17: =IF(ISBLANK(Y17),"MISSING","OK") -> MISSING | AA17: =HYPERLINK("https://africanmarketingconfederation.org/wp-admin/post.php?post=13282&action=elementor","Open in Elementor") -> Open in Elementor | AB17: =HYPERLINK("https://africanmarketingconfederation.org/wp-content/uploads/2021/08/amc_faw.png","View Image") -> View Image | AC17: =IF(LEN("https://africanmarketingconfederation.org/wp-content/uploads/2021/08/amc_faw.png")>0, _xlfn.IMAGE("https://africanmarketingconfederation.org/wp-content/uploads/2021/08/amc_faw.png"), "") -> #VALUE! | AD17: =IFERROR(HYPERLINK("#'Main'!B"&MATCH(TRIM(H17),Main!B:B,0),"Open in Main"),IFERROR(HYPERLINK("#'Technical Diagnostics'!A"&MATCH(TRIM(H17),'Technical Diagnostics'!A:A,0),"Open in Technical"),"Not Found")) -> Open in Main
A18: =IF(B18>=85,"Complete","Needs Copy") -> Needs Copy | B18: =MIN(100,ROUND(0.3*(IF(L18="",0,IF(LEFT(L18,7)="MISSING",0,IF(ISNUMBER(SEARCH("OK",L18)),100,IF(ISNUMBER(SEARCH("SHORT",L18)),65,IF(ISNUMBER(SEARCH("LONG",L18)),50,70))))))+0.25*(IF(N18="",0,IF(LEFT(N18,7)="MISSING",0,IF(ISNUMBER(SEARCH("OK",N18)),100,IF(ISNUMBER(SEARCH("SHORT",N18)),65,IF(ISNUMBER(SEARCH("LONG",N18)),50,70))))))+0.2*(IF(P18="",0,IF(LEFT(P18,2)="OK",100,0)))+0.08*(IF(R18="",0,IF(LEFT(R18,2)="OK",100,0)))+0.06*(IF(T18="",0,IF(LEFT(T18,2)="OK",100,0)))+0.05*(IF(V18="",0,IF(LEFT(V18,2)="OK",100,0)))+0.03*(IF(X18="",0,IF(LEFT(X18,2)="OK",100,0)))+0.03*(IF(Z18="",0,IF(LEFT(Z18,2)="OK",100,0))),0)) -> 66 | C18: 77.5 | D18: 70 | E18: 100 | F18: To Do | G18: Copy Writer | H18: =HYPERLINK("https://africanmarketingconfederation.org/amc-conference-2023/programme","https://africanmarketingconfederation.org/amc-conference-2023/programme") -> https://africanmarketingconfederation.org/amc-conference-2023/programme | I18: =HYPERLINK("https://africanmarketingconfederation.org/amc-conference-2023/programme","Programme") -> Programme | J18: programme | K18: Programme – African Marketing Confederation | L18: =IF(K18="","MISSING",IF(AND(LEN(K18)>=50,LEN(K18)<=60),"OK 50-60 chars",IF(LEN(K18)<50,"SHORT: "&LEN(K18),"LONG: "&LEN(K18)))) -> SHORT: 43 | M18: Programme Download Conference Presentations Are Marketers Intelligent Enough For AI - Fred Kithinzi Taking Africa to the world and bringing the world to Africa - Nondumiso Mabece| Next Media DGCEO Presentation Strategy and Technology: Expanding the Success of Pan-African Brands - Prof. Robert Ebo Hinson Winning African Markets - Simon Harvey Culture as the New | N18: =IF(M18="","MISSING",IF(AND(LEN(M18)>=120,LEN(M18)<=160),"OK 120-160 chars",IF(LEN(M18)<120,"SHORT: "&LEN(M18),"LONG: "&LEN(M18)))) -> LONG: 362 | O18: Programme | P18: =IF(OR(ISBLANK(O18),ISNUMBER(SEARCH("|",O18))),"FIX: MULTIPLE/MISSING","OK") -> OK | Q18: Download Conference Presentations | Conference Day 1 | Conference Day 2 | R18: =IF(ISBLANK(Q18),"MISSING","OK") -> OK | S18: WEDNESDAY | 6 SEPTEMBER 2023 | THURSDAY | 7 SEPTEMBER 2023 | T18: =IF(ISBLANK(S18),"MISSING","OK") -> OK | V18: =IF(ISBLANK(U18),"MISSING","OK") -> MISSING | X18: =IF(ISBLANK(W18),"MISSING","OK") -> MISSING | Z18: =IF(ISBLANK(Y18),"MISSING","OK") -> MISSING | AA18: =HYPERLINK("https://africanmarketingconfederation.org/wp-admin/post.php?post=12945&action=elementor","Open in Elementor") -> Open in Elementor | AB18: =HYPERLINK("https://africanmarketingconfederation.org/wp-content/uploads/2021/08/amc_faw.png","View Image") -> View Image | AC18: =IF(LEN("https://africanmarketingconfederation.org/wp-content/uploads/2021/08/amc_faw.png")>0, _xlfn.IMAGE("https://africanmarketingconfederation.org/wp-content/uploads/2021/08/amc_faw.png"), "") -> #VALUE! | AD18: =IFERROR(HYPERLINK("#'Main'!B"&MATCH(TRIM(H18),Main!B:B,0),"Open in Main"),IFERROR(HYPERLINK("#'Technical Diagnostics'!A"&MATCH(TRIM(H18),'Technical Diagnostics'!A:A,0),"Open in Technical"),"Not Found")) -> Open in Main
A19: =IF(B19>=85,"Complete","Needs Copy") -> Needs Copy | B19: =MIN(100,ROUND(0.3*(IF(L19="",0,IF(LEFT(L19,7)="MISSING",0,IF(ISNUMBER(SEARCH("OK",L19)),100,IF(ISNUMBER(SEARCH("SHORT",L19)),65,IF(ISNUMBER(SEARCH("LONG",L19)),50,70))))))+0.25*(IF(N19="",0,IF(LEFT(N19,7)="MISSING",0,IF(ISNUMBER(SEARCH("OK",N19)),100,IF(ISNUMBER(SEARCH("SHORT",N19)),65,IF(ISNUMBER(SEARCH("LONG",N19)),50,70))))))+0.2*(IF(P19="",0,IF(LEFT(P19,2)="OK",100,0)))+0.08*(IF(R19="",0,IF(LEFT(R19,2)="OK",100,0)))+0.06*(IF(T19="",0,IF(LEFT(T19,2)="OK",100,0)))+0.05*(IF(V19="",0,IF(LEFT(V19,2)="OK",100,0)))+0.03*(IF(X19="",0,IF(LEFT(X19,2)="OK",100,0)))+0.03*(IF(Z19="",0,IF(LEFT(Z19,2)="OK",100,0))),0)) -> 66 | C19: 82.77 | D19: 80 | E19: 91.08 | F19: To Do | G19: Copy Writer | H19: =HYPERLINK("https://africanmarketingconfederation.org/amc-conference-2023/speakers","https://africanmarketingconfederation.org/amc-conference-2023/speakers") -> https://africanmarketingconfederation.org/amc-conference-2023/speakers | I19: =HYPERLINK("https://africanmarketingconfederation.org/amc-conference-2023/speakers","Speakers") -> Speakers | J19: speakers | K19: Speakers – African Marketing Confederation | L19: =IF(K19="","MISSING",IF(AND(LEN(K19)>=50,LEN(K19)<=60),"OK 50-60 chars",IF(LEN(K19)<50,"SHORT: "&LEN(K19),"LONG: "&LEN(K19)))) -> SHORT: 42 | M19: Speakers Ali Hussein Kassim Kenya CEO - AHK Corp View Bio Cathy Adengo Uganda Head of Sustainability, Stanbic Bank Uganda View Bio Doreen Asaasira Muhangazi Uganda Chief Human Resource Officer View Bio James Sutton United Kingdom Strategy and Commercial Director - CIM-UK View Bio Juliet Ziswa Zimbabwe Marketing Director - OK Zimbabwe Limited Group View | N19: =IF(M19="","MISSING",IF(AND(LEN(M19)>=120,LEN(M19)<=160),"OK 120-160 chars",IF(LEN(M19)<120,"SHORT: "&LEN(M19),"LONG: "&LEN(M19)))) -> LONG: 354 | O19: Speakers | P19: =IF(OR(ISBLANK(O19),ISNUMBER(SEARCH("|",O19))),"FIX: MULTIPLE/MISSING","OK") -> OK | Q19: Ali Hussein Kassim | Cathy Adengo | Doreen Asaasira Muhangazi | R19: =IF(ISBLANK(Q19),"MISSING","OK") -> OK | S19: Kenya | Uganda | T19: =IF(ISBLANK(S19),"MISSING","OK") -> OK | V19: =IF(ISBLANK(U19),"MISSING","OK") -> MISSING | X19: =IF(ISBLANK(W19),"MISSING","OK") -> MISSING | Z19: =IF(ISBLANK(Y19),"MISSING","OK") -> MISSING | AA19: =HYPERLINK("https://africanmarketingconfederation.org/wp-admin/post.php?post=13179&action=elementor","Open in Elementor") -> Open in Elementor | AB19: =HYPERLINK("https://africanmarketingconfederation.org/wp-content/uploads/2021/08/amc_faw.png","View Image") -> View Image | AC19: =IF(LEN("https://africanmarketingconfederation.org/wp-content/uploads/2021/08/amc_faw.png")>0, _xlfn.IMAGE("https://africanmarketingconfederation.org/wp-content/uploads/2021/08/amc_faw.png"), "") -> #VALUE! | AD19: =IFERROR(HYPERLINK("#'Main'!B"&MATCH(TRIM(H19),Main!B:B,0),"Open in Main"),IFERROR(HYPERLINK("#'Technical Diagnostics'!A"&MATCH(TRIM(H19),'Technical Diagnostics'!A:A,0),"Open in Technical"),"Not Found")) -> Open in Main
A20: =IF(B20>=85,"Complete","Needs Copy") -> Needs Copy | B20: =MIN(100,ROUND(0.3*(IF(L20="",0,IF(LEFT(L20,7)="MISSING",0,IF(ISNUMBER(SEARCH("OK",L20)),100,IF(ISNUMBER(SEARCH("SHORT",L20)),65,IF(ISNUMBER(SEARCH("LONG",L20)),50,70))))))+0.25*(IF(N20="",0,IF(LEFT(N20,7)="MISSING",0,IF(ISNUMBER(SEARCH("OK",N20)),100,IF(ISNUMBER(SEARCH("SHORT",N20)),65,IF(ISNUMBER(SEARCH("LONG",N20)),50,70))))))+0.2*(IF(P20="",0,IF(LEFT(P20,2)="OK",100,0)))+0.08*(IF(R20="",0,IF(LEFT(R20,2)="OK",100,0)))+0.06*(IF(T20="",0,IF(LEFT(T20,2)="OK",100,0)))+0.05*(IF(V20="",0,IF(LEFT(V20,2)="OK",100,0)))+0.03*(IF(X20="",0,IF(LEFT(X20,2)="OK",100,0)))+0.03*(IF(Z20="",0,IF(LEFT(Z20,2)="OK",100,0))),0)) -> 69 | C20: 77.5 | D20: 70 | E20: 100 | F20: To Do | G20: Copy Writer | H20: =HYPERLINK("https://africanmarketingconfederation.org/amc-conference-2024-recap","https://africanmarketingconfederation.org/amc-conference-2024-recap") -> https://africanmarketingconfederation.org/amc-conference-2024-recap | I20: =HYPERLINK("https://africanmarketingconfederation.org/amc-conference-2024-recap","Amc Conference 2024 Recap") -> Amc Conference 2024 Recap | J20: amc-conference-2024-recap | K20: AMC Conference 2024 Recap – African Marketing Confederation | L20: =IF(K20="","MISSING",IF(AND(LEN(K20)>=50,LEN(K20)<=60),"OK 50-60 chars",IF(LEN(K20)<50,"SHORT: "&LEN(K20),"LONG: "&LEN(K20)))) -> OK 50-60 chars | M20: Event Highlights AMC Marketing Conference 2024 Shaping the Future of African Marketing Get 2025 Conference Updates Share Your Experience Conference Day 1 The conference kicked off with insightful addresses, including a keynote from marketing expert Hermawan Kartajaya. Dr Philip Kotler, the Father of Modern Marketing, delivered a welcome address live from Chicago and we ended | N20: =IF(M20="","MISSING",IF(AND(LEN(M20)>=120,LEN(M20)<=160),"OK 120-160 chars",IF(LEN(M20)<120,"SHORT: "&LEN(M20),"LONG: "&LEN(M20)))) -> LONG: 377 | O20: Event Highlights | P20: =IF(OR(ISBLANK(O20),ISNUMBER(SEARCH("|",O20))),"FIX: MULTIPLE/MISSING","OK") -> OK | R20: =IF(ISBLANK(Q20),"MISSING","OK") -> MISSING | S20: Conference Day 1 | Conference Day 2 | Conference Day 3 | Did you attend the 2024 AMC Conference? We’d love to hear about your experience! | Countries Represented | T20: =IF(ISBLANK(S20),"MISSING","OK") -> OK | V20: =IF(ISBLANK(U20),"MISSING","OK") -> MISSING | X20: =IF(ISBLANK(W20),"MISSING","OK") -> MISSING | Z20: =IF(ISBLANK(Y20),"MISSING","OK") -> MISSING | AA20: =HYPERLINK("https://africanmarketingconfederation.org/wp-admin/post.php?post=22401&action=elementor","Open in Elementor") -> Open in Elementor | AB20: =HYPERLINK("https://africanmarketingconfederation.org/wp-content/uploads/2021/08/amc_faw.png","View Image") -> View Image | AC20: =IF(LEN("https://africanmarketingconfederation.org/wp-content/uploads/2021/08/amc_faw.png")>0, _xlfn.IMAGE("https://africanmarketingconfederation.org/wp-content/uploads/2021/08/amc_faw.png"), "") -> #VALUE! | AD20: =IFERROR(HYPERLINK("#'Main'!B"&MATCH(TRIM(H20),Main!B:B,0),"Open in Main"),IFERROR(HYPERLINK("#'Technical Diagnostics'!A"&MATCH(TRIM(H20),'Technical Diagnostics'!A:A,0),"Open in Technical"),"Not Found")) -> Open in Main
A21: =IF(B21>=85,"Complete","Needs Copy") -> Needs Copy | B21: =MIN(100,ROUND(0.3*(IF(L21="",0,IF(LEFT(L21,7)="MISSING",0,IF(ISNUMBER(SEARCH("OK",L21)),100,IF(ISNUMBER(SEARCH("SHORT",L21)),65,IF(ISNUMBER(SEARCH("LONG",L21)),50,70))))))+0.25*(IF(N21="",0,IF(LEFT(N21,7)="MISSING",0,IF(ISNUMBER(SEARCH("OK",N21)),100,IF(ISNUMBER(SEARCH("SHORT",N21)),65,IF(ISNUMBER(SEARCH("LONG",N21)),50,70))))))+0.2*(IF(P21="",0,IF(LEFT(P21,2)="OK",100,0)))+0.08*(IF(R21="",0,IF(LEFT(R21,2)="OK",100,0)))+0.06*(IF(T21="",0,IF(LEFT(T21,2)="OK",100,0)))+0.05*(IF(V21="",0,IF(LEFT(V21,2)="OK",100,0)))+0.03*(IF(X21="",0,IF(LEFT(X21,2)="OK",100,0)))+0.03*(IF(Z21="",0,IF(LEFT(Z21,2)="OK",100,0))),0)) -> 77 | C21: 73.88 | D21: 70 | E21: 85.5 | F21: To Do | G21: Copy Writer | H21: =HYPERLINK("https://africanmarketingconfederation.org/amc-conference-2024-sponsors-packages","https://africanmarketingconfederation.org/amc-conference-2024-sponsors-packages") -> https://africanmarketingconfederation.org/amc-conference-2024-sponsors-packages | I21: =HYPERLINK("https://africanmarketingconfederation.org/amc-conference-2024-sponsors-packages","Amc Conference 2024 Sponsors Packages") -> Amc Conference 2024 Sponsors Packages | J21: amc-conference-2024-sponsors-packages | K21: Sponsors Packages – African Marketing Confederation | L21: =IF(K21="","MISSING",IF(AND(LEN(K21)>=50,LEN(K21)<=60),"OK 50-60 chars",IF(LEN(K21)<50,"SHORT: "&LEN(K21),"LONG: "&LEN(K21)))) -> OK 50-60 chars | M21: SPONSORSHIP PACKAGES Diamond Package Overall Anchor and Title Sponsor $50000,00 View Product Platinum Package Industry Leader Sponsor / per Professional Body Stream $20000,00 View Product Silver Package Full Day (Option to Choose Day 1, 2, or 3) Provision of Delegates Apparel in the Form of Golf Shirts and Caps (Day 2 & 3) $12000,00 View | N21: =IF(M21="","MISSING",IF(AND(LEN(M21)>=120,LEN(M21)<=160),"OK 120-160 chars",IF(LEN(M21)<120,"SHORT: "&LEN(M21),"LONG: "&LEN(M21)))) -> LONG: 339 | O21: SPONSORSHIP PACKAGES | P21: =IF(OR(ISBLANK(O21),ISNUMBER(SEARCH("|",O21))),"FIX: MULTIPLE/MISSING","OK") -> OK | Q21: AMC Full-Conference Package Labadi Beach Hotel | AMC Full-Conference Package La Palm Royal Beach Hotel | AMC Day Attendance Package | R21: =IF(ISBLANK(Q21),"MISSING","OK") -> OK | S21: $ 1550 | $ 1330 | T21: =IF(ISBLANK(S21),"MISSING","OK") -> OK | V21: =IF(ISBLANK(U21),"MISSING","OK") -> MISSING | X21: =IF(ISBLANK(W21),"MISSING","OK") -> MISSING | Z21: =IF(ISBLANK(Y21),"MISSING","OK") -> MISSING | AA21: =HYPERLINK("https://africanmarketingconfederation.org/wp-admin/post.php?post=18318&action=elementor","Open in Elementor") -> Open in Elementor | AB21: =HYPERLINK("https://africanmarketingconfederation.org/wp-content/uploads/2021/08/amc_faw.png","View Image") -> View Image | AC21: =IF(LEN("https://africanmarketingconfederation.org/wp-content/uploads/2021/08/amc_faw.png")>0, _xlfn.IMAGE("https://africanmarketingconfederation.org/wp-content/uploads/2021/08/amc_faw.png"), "") -> #VALUE! | AD21: =IFERROR(HYPERLINK("#'Main'!B"&MATCH(TRIM(H21),Main!B:B,0),"Open in Main"),IFERROR(HYPERLINK("#'Technical Diagnostics'!A"&MATCH(TRIM(H21),'Technical Diagnostics'!A:A,0),"Open in Technical"),"Not Found")) -> Open in Main
A22: =IF(B22>=85,"Complete","Needs Copy") -> Needs Copy | B22: =MIN(100,ROUND(0.3*(IF(L22="",0,IF(LEFT(L22,7)="MISSING",0,IF(ISNUMBER(SEARCH("OK",L22)),100,IF(ISNUMBER(SEARCH("SHORT",L22)),65,IF(ISNUMBER(SEARCH("LONG",L22)),50,70))))))+0.25*(IF(N22="",0,IF(LEFT(N22,7)="MISSING",0,IF(ISNUMBER(SEARCH("OK",N22)),100,IF(ISNUMBER(SEARCH("SHORT",N22)),65,IF(ISNUMBER(SEARCH("LONG",N22)),50,70))))))+0.2*(IF(P22="",0,IF(LEFT(P22,2)="OK",100,0)))+0.08*(IF(R22="",0,IF(LEFT(R22,2)="OK",100,0)))+0.06*(IF(T22="",0,IF(LEFT(T22,2)="OK",100,0)))+0.05*(IF(V22="",0,IF(LEFT(V22,2)="OK",100,0)))+0.03*(IF(X22="",0,IF(LEFT(X22,2)="OK",100,0)))+0.03*(IF(Z22="",0,IF(LEFT(Z22,2)="OK",100,0))),0)) -> 56 | C22: 70 | D22: 60 | E22: 100 | F22: To Do | G22: Copy Writer | H22: =HYPERLINK("https://africanmarketingconfederation.org/amc-conference-2025-highlights","https://africanmarketingconfederation.org/amc-conference-2025-highlights") -> https://africanmarketingconfederation.org/amc-conference-2025-highlights | I22: =HYPERLINK("https://africanmarketingconfederation.org/amc-conference-2025-highlights","Amc Conference 2025 Highlights") -> Amc Conference 2025 Highlights | J22: amc-conference-2025-highlights | K22: AMC Conference 2025 Highlights – African Marketing Confederation | L22: =IF(K22="","MISSING",IF(AND(LEN(K22)>=50,LEN(K22)<=60),"OK 50-60 chars",IF(LEN(K22)<50,"SHORT: "&LEN(K22),"LONG: "&LEN(K22)))) -> LONG: 64 | M22: 2025 Event Highlights AMC Marketing Conference AMC Marketing Conference 250+ Delegates. 29 Countries. One Pan-African Voice.250+ Delegates. 29 Countries.One Pan-African Marketing Voice. Get 2026 Conference Updates Share Your Experience 2025 Event Highlights AMC Marketing Conference 400+ Delegates. 29 Countries.One Pan-African Voice. Get 2026 Conference Updates 2025 Event Highlights AMC Marketing Conference Get 2026 Conference Updates | N22: =IF(M22="","MISSING",IF(AND(LEN(M22)>=120,LEN(M22)<=160),"OK 120-160 chars",IF(LEN(M22)<120,"SHORT: "&LEN(M22),"LONG: "&LEN(M22)))) -> LONG: 437 | O22: 2025 | P22: =IF(OR(ISBLANK(O22),ISNUMBER(SEARCH("|",O22))),"FIX: MULTIPLE/MISSING","OK") -> OK | Q22: Moments that Shaped the 2025 AMC Conference | Wednesday, 20 August | Opening Keynote | Back to Basics – Thriving in Tough Times | Creating Authentic Connections Through User-Generated & Short-Form Video | R22: =IF(ISBLANK(Q22),"MISSING","OK") -> OK | T22: =IF(ISBLANK(S22),"MISSING","OK") -> MISSING | V22: =IF(ISBLANK(U22),"MISSING","OK") -> MISSING | X22: =IF(ISBLANK(W22),"MISSING","OK") -> MISSING | Z22: =IF(ISBLANK(Y22),"MISSING","OK") -> MISSING | AA22: =HYPERLINK("https://africanmarketingconfederation.org/wp-admin/post.php?post=30257&action=elementor","Open in Elementor") -> Open in Elementor | AB22: =HYPERLINK("https://africanmarketingconfederation.org/wp-content/uploads/2021/08/amc_faw.png","View Image") -> View Image | AC22: =IF(LEN("https://africanmarketingconfederation.org/wp-content/uploads/2021/08/amc_faw.png")>0, _xlfn.IMAGE("https://africanmarketingconfederation.org/wp-content/uploads/2021/08/amc_faw.png"), "") -> #VALUE! | AD22: =IFERROR(HYPERLINK("#'Main'!B"&MATCH(TRIM(H22),Main!B:B,0),"Open in Main"),IFERROR(HYPERLINK("#'Technical Diagnostics'!A"&MATCH(TRIM(H22),'Technical Diagnostics'!A:A,0),"Open in Technical"),"Not Found")) -> Open in Main

Sheet Issue Register
A1: URL | B1: Section | C1: Issue | D1: Severity | E1: Affected URL Count | F1: Reference Area | G1: Stable Issue ID | H1: Owner | I1: Sprint | J1: Status | K1: Affected URLs Sample | L1: Source Legacy Tab | M1: Source Row ID | N1: Open in Main | O1: Open in Reference | P1: BACK TO DASHBOARD
B2: AEO Opportunities | C2: Low AEO Readiness Score | D2: Warning | E2: 20 | F2: Content & AI Readiness | J2: Open | K2: https://africanmarketingconfederation.org/amc-awards-2024 | https://africanmarketingconfederation.org/about-us | https://africanmarketingconfederation.org/ | https://africanmarketingconfederation.org/african-marketing-confederation-tourism-chapter | https://africanmarketingconfederation.org/amc-conference-2022-prospectus | https://africanmarketingconfederation.org/amc-conference-2022-thank-you | https://africanmarketingconfederation.org/amc-conference-2022 | https://africanmarketingconfederation.org/amc-conference-2023 | https://africanmarketingconfederation.org/amc-conference-2023/amc-awards-book-now | https://africanmarketingconfederation.org/amc-conference-2023/amc-awards | https://africanmarketingconfederation.org/amc-conference-2023/book-now-thank-you | https://africanmarketingconfederation.org/amc-conference-2023/book-now | https://africanmarketingconfederation.org/amc-conference-2023/download-prospectus | https://africanmarketingconfederation.org/amc-conference-2023/gallery | https://africanmarketingconfederation.org/amc-conference-2023/partners | https://africanmarketingconfederation.org/amc-conference-2024-recap | https://africanmarketingconfederation.org/amc-conference-2023/programme | https://africanmarketingconfederation.org/amc-conference-2023/speakers | https://africanmarketingconfederation.org/amc-conference-2024-sponsors-packages | https://africanmarketingconfederation.org/amc-conference-2025-highlights || Full list: see Content & AI Readiness tab | L2: Summary | M2: 2 | N2: =IFERROR(HYPERLINK("#'Main'!B"&MATCH(TRIM(A2),Main!B:B,0),"Open"),HYPERLINK("#'Main'!B1","Open")) -> Open | O2: =IFERROR(HYPERLINK("#"&F2&"!A"&MATCH(A2,INDIRECT("'"&F2&"'!A:A"),0),"Open"),HYPERLINK("#"&F2&"!A1","Open")) -> Open
B3: AEO Opportunities | C3: Missing FAQ/QA Schema | D3: Warning | E3: 0 | F3: Content & AI Readiness | J3: Open | K3: || Full list: see Content & AI Readiness tab | L3: Summary | M3: 3 | N3: =IFERROR(HYPERLINK("#'Main'!B"&MATCH(TRIM(A3),Main!B:B,0),"Open"),HYPERLINK("#'Main'!B1","Open")) -> Open | O3: =IFERROR(HYPERLINK("#"&F3&"!A"&MATCH(A3,INDIRECT("'"&F3&"'!A:A"),0),"Open"),HYPERLINK("#"&F3&"!A1","Open")) -> Open
B4: AEO Opportunities | C4: No 40-60 Word Answer Paragraphs | D4: Observation | E4: 20 | F4: Content & AI Readiness | J4: Open | K4: https://africanmarketingconfederation.org/amc-awards-2024 | https://africanmarketingconfederation.org/about-us | https://africanmarketingconfederation.org/ | https://africanmarketingconfederation.org/african-marketing-confederation-tourism-chapter | https://africanmarketingconfederation.org/amc-conference-2022-prospectus | https://africanmarketingconfederation.org/amc-conference-2022-thank-you | https://africanmarketingconfederation.org/amc-conference-2022 | https://africanmarketingconfederation.org/amc-conference-2023 | https://africanmarketingconfederation.org/amc-conference-2023/amc-awards-book-now | https://africanmarketingconfederation.org/amc-conference-2023/amc-awards | https://africanmarketingconfederation.org/amc-conference-2023/book-now-thank-you | https://africanmarketingconfederation.org/amc-conference-2023/book-now | https://africanmarketingconfederation.org/amc-conference-2023/download-prospectus | https://africanmarketingconfederation.org/amc-conference-2023/gallery | https://africanmarketingconfederation.org/amc-conference-2023/partners | https://africanmarketingconfederation.org/amc-conference-2024-recap | https://africanmarketingconfederation.org/amc-conference-2023/programme | https://africanmarketingconfederation.org/amc-conference-2023/speakers | https://africanmarketingconfederation.org/amc-conference-2024-sponsors-packages | https://africanmarketingconfederation.org/amc-conference-2025-highlights || Full list: see Content & AI Readiness tab | L4: Summary | M4: 4 | N4: =IFERROR(HYPERLINK("#'Main'!B"&MATCH(TRIM(A4),Main!B:B,0),"Open"),HYPERLINK("#'Main'!B1","Open")) -> Open | O4: =IFERROR(HYPERLINK("#"&F4&"!A"&MATCH(A4,INDIRECT("'"&F4&"'!A:A"),0),"Open"),HYPERLINK("#"&F4&"!A1","Open")) -> Open
B5: AEO Opportunities | C5: No Question Headings | D5: Observation | E5: 20 | F5: Content & AI Readiness | J5: Open | K5: https://africanmarketingconfederation.org/amc-awards-2024 | https://africanmarketingconfederation.org/about-us | https://africanmarketingconfederation.org/ | https://africanmarketingconfederation.org/african-marketing-confederation-tourism-chapter | https://africanmarketingconfederation.org/amc-conference-2022-prospectus | https://africanmarketingconfederation.org/amc-conference-2022-thank-you | https://africanmarketingconfederation.org/amc-conference-2022 | https://africanmarketingconfederation.org/amc-conference-2023 | https://africanmarketingconfederation.org/amc-conference-2023/amc-awards-book-now | https://africanmarketingconfederation.org/amc-conference-2023/amc-awards | https://africanmarketingconfederation.org/amc-conference-2023/book-now-thank-you | https://africanmarketingconfederation.org/amc-conference-2023/book-now | https://africanmarketingconfederation.org/amc-conference-2023/download-prospectus | https://africanmarketingconfederation.org/amc-conference-2023/gallery | https://africanmarketingconfederation.org/amc-conference-2023/partners | https://africanmarketingconfederation.org/amc-conference-2024-recap | https://africanmarketingconfederation.org/amc-conference-2023/programme | https://africanmarketingconfederation.org/amc-conference-2023/speakers | https://africanmarketingconfederation.org/amc-conference-2024-sponsors-packages | https://africanmarketingconfederation.org/amc-conference-2025-highlights || Full list: see Content & AI Readiness tab | L5: Summary | M5: 5 | N5: =IFERROR(HYPERLINK("#'Main'!B"&MATCH(TRIM(A5),Main!B:B,0),"Open"),HYPERLINK("#'Main'!B1","Open")) -> Open | O5: =IFERROR(HYPERLINK("#"&F5&"!A"&MATCH(A5,INDIRECT("'"&F5&"'!A:A"),0),"Open"),HYPERLINK("#"&F5&"!A1","Open")) -> Open
B6: AEO Opportunities | C6: No Answer-Friendly Structure | D6: Observation | E6: 0 | F6: Content & AI Readiness | J6: Open | K6: || Full list: see Content & AI Readiness tab | L6: Summary | M6: 6 | N6: =IFERROR(HYPERLINK("#'Main'!B"&MATCH(TRIM(A6),Main!B:B,0),"Open"),HYPERLINK("#'Main'!B1","Open")) -> Open | O6: =IFERROR(HYPERLINK("#"&F6&"!A"&MATCH(A6,INDIRECT("'"&F6&"'!A:A"),0),"Open"),HYPERLINK("#"&F6&"!A1","Open")) -> Open
B7: AEO Opportunities | E7: 0 | J7: Open | K7: Detailed rows: see Content & AI Readiness tab | L7: Summary | M7: 7 | N7: =IFERROR(HYPERLINK("#'Main'!B"&MATCH(TRIM(A7),Main!B:B,0),"Open"),HYPERLINK("#'Main'!B1","Open")) -> Open | O7: =IFERROR(HYPERLINK("#"&F7&"!A"&MATCH(A7,INDIRECT("'"&F7&"'!A:A"),0),"Open"),HYPERLINK("#"&F7&"!A1","Open")) -> Open
B8: Issue Counts | C8: Broken Internal Links | D8: Critical | E8: 0 | F8: Link Intelligence | J8: Open | K8: || Full list: see Technical Diagnostics / Link Intelligence tabs | L8: Summary | M8: 8 | N8: =IFERROR(HYPERLINK("#'Main'!B"&MATCH(TRIM(A8),Main!B:B,0),"Open"),HYPERLINK("#'Main'!B1","Open")) -> Open | O8: =IFERROR(HYPERLINK("#"&F8&"!A"&MATCH(A8,INDIRECT("'"&F8&"'!A:A"),0),"Open"),HYPERLINK("#"&F8&"!A1","Open")) -> Open
B9: Issue Counts | C9: CWV LCP Above 4.0s | D9: Critical | E9: 0 | F9: Technical Diagnostics | J9: Open | K9: || Full list: see Technical Diagnostics / Link Intelligence tabs | L9: Summary | M9: 9 | N9: =IFERROR(HYPERLINK("#'Main'!B"&MATCH(TRIM(A9),Main!B:B,0),"Open"),HYPERLINK("#'Main'!B1","Open")) -> Open | O9: =IFERROR(HYPERLINK("#"&F9&"!A"&MATCH(A9,INDIRECT("'"&F9&"'!A:A"),0),"Open"),HYPERLINK("#"&F9&"!A1","Open")) -> Open
B10: Issue Counts | C10: Canonical Points Elsewhere | D10: Critical | E10: 0 | F10: Technical Diagnostics | J10: Open | K10: || Full list: see Technical Diagnostics / Link Intelligence tabs | L10: Summary | M10: 10 | N10: =IFERROR(HYPERLINK("#'Main'!B"&MATCH(TRIM(A10),Main!B:B,0),"Open"),HYPERLINK("#'Main'!B1","Open")) -> Open | O10: =IFERROR(HYPERLINK("#"&F10&"!A"&MATCH(A10,INDIRECT("'"&F10&"'!A:A"),0),"Open"),HYPERLINK("#"&F10&"!A1","Open")) -> Open
B11: Issue Counts | C11: Missing Title | D11: Critical | E11: 0 | F11: Technical Diagnostics | J11: Open | K11: || Full list: see Technical Diagnostics / Link Intelligence tabs | L11: Summary | M11: 11 | N11: =IFERROR(HYPERLINK("#'Main'!B"&MATCH(TRIM(A11),Main!B:B,0),"Open"),HYPERLINK("#'Main'!B1","Open")) -> Open | O11: =IFERROR(HYPERLINK("#"&F11&"!A"&MATCH(A11,INDIRECT("'"&F11&"'!A:A"),0),"Open"),HYPERLINK("#"&F11&"!A1","Open")) -> Open
B12: Issue Counts | C12: Noindex Directive | D12: Critical | E12: 0 | F12: Technical Diagnostics | J12: Open | K12: || Full list: see Technical Diagnostics / Link Intelligence tabs | L12: Summary | M12: 12 | N12: =IFERROR(HYPERLINK("#'Main'!B"&MATCH(TRIM(A12),Main!B:B,0),"Open"),HYPERLINK("#'Main'!B1","Open")) -> Open | O12: =IFERROR(HYPERLINK("#"&F12&"!A"&MATCH(A12,INDIRECT("'"&F12&"'!A:A"),0),"Open"),HYPERLINK("#"&F12&"!A1","Open")) -> Open
B13: Issue Counts | C13: Non-200 Status | D13: Critical | E13: 0 | F13: Technical Diagnostics | J13: Open | K13: || Full list: see Technical Diagnostics / Link Intelligence tabs | L13: Summary | M13: 13 | N13: =IFERROR(HYPERLINK("#'Main'!B"&MATCH(TRIM(A13),Main!B:B,0),"Open"),HYPERLINK("#'Main'!B1","Open")) -> Open | O13: =IFERROR(HYPERLINK("#"&F13&"!A"&MATCH(A13,INDIRECT("'"&F13&"'!A:A"),0),"Open"),HYPERLINK("#"&F13&"!A1","Open")) -> Open
B14: Issue Counts | C14: Robots.txt Disallow Root | D14: Critical | E14: 0 | F14: Technical Diagnostics | J14: Open | K14: || Full list: see Technical Diagnostics / Link Intelligence tabs | L14: Summary | M14: 14 | N14: =IFERROR(HYPERLINK("#'Main'!B"&MATCH(TRIM(A14),Main!B:B,0),"Open"),HYPERLINK("#'Main'!B1","Open")) -> Open | O14: =IFERROR(HYPERLINK("#"&F14&"!A"&MATCH(A14,INDIRECT("'"&F14&"'!A:A"),0),"Open"),HYPERLINK("#"&F14&"!A1","Open")) -> Open
B15: Issue Counts | C15: Low AEO Readiness Score | D15: Warning | E15: 20 | F15: Content & AI Readiness | J15: Open | K15: https://africanmarketingconfederation.org/amc-awards-2024 | https://africanmarketingconfederation.org/about-us | https://africanmarketingconfederation.org/ | https://africanmarketingconfederation.org/african-marketing-confederation-tourism-chapter | https://africanmarketingconfederation.org/amc-conference-2022-prospectus | https://africanmarketingconfederation.org/amc-conference-2022-thank-you | https://africanmarketingconfederation.org/amc-conference-2022 | https://africanmarketingconfederation.org/amc-conference-2023 | https://africanmarketingconfederation.org/amc-conference-2023/amc-awards-book-now | https://africanmarketingconfederation.org/amc-conference-2023/amc-awards | https://africanmarketingconfederation.org/amc-conference-2023/book-now-thank-you | https://africanmarketingconfederation.org/amc-conference-2023/book-now | https://africanmarketingconfederation.org/amc-conference-2023/download-prospectus | https://africanmarketingconfederation.org/amc-conference-2023/gallery | https://africanmarketingconfederation.org/amc-conference-2023/partners | https://africanmarketingconfederation.org/amc-conference-2024-recap | https://africanmarketingconfederation.org/amc-conference-2023/programme | https://africanmarketingconfederation.org/amc-conference-2023/speakers | https://africanmarketingconfederation.org/amc-conference-2024-sponsors-packages | https://africanmarketingconfederation.org/amc-conference-2025-highlights || Full list: see Technical Diagnostics / Link Intelligence tabs | L15: Summary | M15: 15 | N15: =IFERROR(HYPERLINK("#'Main'!B"&MATCH(TRIM(A15),Main!B:B,0),"Open"),HYPERLINK("#'Main'!B1","Open")) -> Open | O15: =IFERROR(HYPERLINK("#"&F15&"!A"&MATCH(A15,INDIRECT("'"&F15&"'!A:A"),0),"Open"),HYPERLINK("#"&F15&"!A1","Open")) -> Open
B16: Issue Counts | C16: Low Image Alt Coverage | D16: Warning | E16: 16 | F16: Technical Diagnostics | J16: Open | K16: https://africanmarketingconfederation.org/amc-awards-2024 | https://africanmarketingconfederation.org/about-us | https://africanmarketingconfederation.org/ | https://africanmarketingconfederation.org/amc-conference-2022-prospectus | https://africanmarketingconfederation.org/amc-conference-2022-thank-you | https://africanmarketingconfederation.org/amc-conference-2022 | https://africanmarketingconfederation.org/amc-conference-2023 | https://africanmarketingconfederation.org/amc-conference-2023/amc-awards-book-now | https://africanmarketingconfederation.org/amc-conference-2023/amc-awards | https://africanmarketingconfederation.org/amc-conference-2023/book-now | https://africanmarketingconfederation.org/amc-conference-2023/download-prospectus | https://africanmarketingconfederation.org/amc-conference-2023/gallery | https://africanmarketingconfederation.org/amc-conference-2023/partners | https://africanmarketingconfederation.org/amc-conference-2023/programme | https://africanmarketingconfederation.org/amc-conference-2024-sponsors-packages | https://africanmarketingconfederation.org/amc-conference-2025-highlights || Full list: see Technical Diagnostics / Link Intelligence tabs | L16: Summary | M16: 16 | N16: =IFERROR(HYPERLINK("#'Main'!B"&MATCH(TRIM(A16),Main!B:B,0),"Open"),HYPERLINK("#'Main'!B1","Open")) -> Open | O16: =IFERROR(HYPERLINK("#"&F16&"!A"&MATCH(A16,INDIRECT("'"&F16&"'!A:A"),0),"Open"),HYPERLINK("#"&F16&"!A1","Open")) -> Open
B17: Issue Counts | C17: Missing H1 | D17: Warning | E17: 5 | F17: Technical Diagnostics | J17: Open | K17: https://africanmarketingconfederation.org/amc-conference-2022-prospectus | https://africanmarketingconfederation.org/amc-conference-2022-thank-you | https://africanmarketingconfederation.org/amc-conference-2022 | https://africanmarketingconfederation.org/amc-conference-2023/amc-awards-book-now | https://africanmarketingconfederation.org/amc-conference-2023/book-now-thank-you || Full list: see Technical Diagnostics / Link Intelligence tabs | L17: Summary | M17: 17 | N17: =IFERROR(HYPERLINK("#'Main'!B"&MATCH(TRIM(A17),Main!B:B,0),"Open"),HYPERLINK("#'Main'!B1","Open")) -> Open | O17: =IFERROR(HYPERLINK("#"&F17&"!A"&MATCH(A17,INDIRECT("'"&F17&"'!A:A"),0),"Open"),HYPERLINK("#"&F17&"!A1","Open")) -> Open
B18: Issue Counts | C18: Multiple H1 | D18: Warning | E18: 5 | F18: Technical Diagnostics | J18: Open | K18: https://africanmarketingconfederation.org/amc-awards-2024 | https://africanmarketingconfederation.org/ | https://africanmarketingconfederation.org/african-marketing-confederation-tourism-chapter | https://africanmarketingconfederation.org/amc-conference-2024-recap | https://africanmarketingconfederation.org/amc-conference-2025-highlights || Full list: see Technical Diagnostics / Link Intelligence tabs | L18: Summary | M18: 18 | N18: =IFERROR(HYPERLINK("#'Main'!B"&MATCH(TRIM(A18),Main!B:B,0),"Open"),HYPERLINK("#'Main'!B1","Open")) -> Open | O18: =IFERROR(HYPERLINK("#"&F18&"!A"&MATCH(A18,INDIRECT("'"&F18&"'!A:A"),0),"Open"),HYPERLINK("#"&F18&"!A1","Open")) -> Open
B19: Issue Counts | C19: Missing Meta Description | D19: Warning | E19: 1 | F19: Technical Diagnostics | J19: Open | K19: https://africanmarketingconfederation.org/amc-conference-2023/amc-awards-book-now || Full list: see Technical Diagnostics / Link Intelligence tabs | L19: Summary | M19: 19 | N19: =IFERROR(HYPERLINK("#'Main'!B"&MATCH(TRIM(A19),Main!B:B,0),"Open"),HYPERLINK("#'Main'!B1","Open")) -> Open | O19: =IFERROR(HYPERLINK("#"&F19&"!A"&MATCH(A19,INDIRECT("'"&F19&"'!A:A"),0),"Open"),HYPERLINK("#"&F19&"!A1","Open")) -> Open
... B41: Issue Counts | C41: llms.txt Missing | D41: Observation | E41: 0 | F41: Technical Diagnostics | J41: Open | K41: || Full list: see Technical Diagnostics / Link Intelligence tabs | L41: Summary | M41: 41 | N41: =IFERROR(HYPERLINK("#'Main'!B"&MATCH(TRIM(A41),Main!B:B,0),"Open"),HYPERLINK("#'Main'!B1","Open")) -> Open | O41: =IFERROR(HYPERLINK("#"&F41&"!A"&MATCH(A41,INDIRECT("'"&F41&"'!A:A"),0),"Open"),HYPERLINK("#"&F41&"!A1","Open")) -> Open
B42: Issue Counts | E42: 0 | J42: Open | L42: Summary | M42: 42 | N42: =IFERROR(HYPERLINK("#'Main'!B"&MATCH(TRIM(A42),Main!B:B,0),"Open"),HYPERLINK("#'Main'!B1","Open")) -> Open | O42: =IFERROR(HYPERLINK("#"&F42&"!A"&MATCH(A42,INDIRECT("'"&F42&"'!A:A"),0),"Open"),HYPERLINK("#"&F42&"!A1","Open")) -> Open
B43: Top 10 Critical URLs | E43: 0 | J43: Open | L43: Summary | M43: 43 | N43: =IFERROR(HYPERLINK("#'Main'!B"&MATCH(TRIM(A43),Main!B:B,0),"Open"),HYPERLINK("#'Main'!B1","Open")) -> Open | O43: =IFERROR(HYPERLINK("#"&F43&"!A"&MATCH(A43,INDIRECT("'"&F43&"'!A:A"),0),"Open"),HYPERLINK("#"&F43&"!A1","Open")) -> Open
B44: Top Issues by Template | E44: 0 | J44: Open | L44: Summary | M44: 44 | N44: =IFERROR(HYPERLINK("#'Main'!B"&MATCH(TRIM(A44),Main!B:B,0),"Open"),HYPERLINK("#'Main'!B1","Open")) -> Open | O44: =IFERROR(HYPERLINK("#"&F44&"!A"&MATCH(A44,INDIRECT("'"&F44&"'!A:A"),0),"Open"),HYPERLINK("#"&F44&"!A1","Open")) -> Open
B45: Top Issues by Template | C45: /amc-conference-2023/ -> Low AEO Readiness Score | D45: Observation | E45: 10 | F45: Template & Duplication Risks | J45: Open | L45: Summary | M45: 45 | N45: =IFERROR(HYPERLINK("#'Main'!B"&MATCH(TRIM(A45),Main!B:B,0),"Open"),HYPERLINK("#'Main'!B1","Open")) -> Open | O45: =IFERROR(HYPERLINK("#"&F45&"!A"&MATCH(A45,INDIRECT("'"&F45&"'!A:A"),0),"Open"),HYPERLINK("#"&F45&"!A1","Open")) -> Open
B46: Top Issues by Template | C46: /amc-conference-2023/ -> No ETag Header | D46: Observation | E46: 10 | F46: Template & Duplication Risks | J46: Open | L46: Summary | M46: 46 | N46: =IFERROR(HYPERLINK("#'Main'!B"&MATCH(TRIM(A46),Main!B:B,0),"Open"),HYPERLINK("#'Main'!B1","Open")) -> Open | O46: =IFERROR(HYPERLINK("#"&F46&"!A"&MATCH(A46,INDIRECT("'"&F46&"'!A:A"),0),"Open"),HYPERLINK("#"&F46&"!A1","Open")) -> Open
B47: Top Issues by Template | C47: /amc-conference-2023/ -> No Question Headings | D47: Observation | E47: 10 | F47: Template & Duplication Risks | J47: Open | L47: Summary | M47: 47 | N47: =IFERROR(HYPERLINK("#'Main'!B"&MATCH(TRIM(A47),Main!B:B,0),"Open"),HYPERLINK("#'Main'!B1","Open")) -> Open | O47: =IFERROR(HYPERLINK("#"&F47&"!A"&MATCH(A47,INDIRECT("'"&F47&"'!A:A"),0),"Open"),HYPERLINK("#"&F47&"!A1","Open")) -> Open
B48: Top Issues by Template | C48: /amc-conference-2023/ -> No 40-60 Word Answer Paragraphs | D48: Observation | E48: 10 | F48: Template & Duplication Risks | J48: Open | L48: Summary | M48: 48 | N48: =IFERROR(HYPERLINK("#'Main'!B"&MATCH(TRIM(A48),Main!B:B,0),"Open"),HYPERLINK("#'Main'!B1","Open")) -> Open | O48: =IFERROR(HYPERLINK("#"&F48&"!A"&MATCH(A48,INDIRECT("'"&F48&"'!A:A"),0),"Open"),HYPERLINK("#"&F48&"!A1","Open")) -> Open
B49: Top Issues by Template | C49: /amc-conference-2023/ -> AI Crawlers Not Explicitly Allowed | D49: Observation | E49: 10 | F49: Template & Duplication Risks | J49: Open | L49: Summary | M49: 49 | N49: =IFERROR(HYPERLINK("#'Main'!B"&MATCH(TRIM(A49),Main!B:B,0),"Open"),HYPERLINK("#'Main'!B1","Open")) -> Open | O49: =IFERROR(HYPERLINK("#"&F49&"!A"&MATCH(A49,INDIRECT("'"&F49&"'!A:A"),0),"Open"),HYPERLINK("#"&F49&"!A1","Open")) -> Open
B50: Top Issues by Template | C50: /amc-conference-2023/ -> Low Image Alt Coverage | D50: Observation | E50: 8 | F50: Template & Duplication Risks | J50: Open | L50: Summary | M50: 50 | N50: =IFERROR(HYPERLINK("#'Main'!B"&MATCH(TRIM(A50),Main!B:B,0),"Open"),HYPERLINK("#'Main'!B1","Open")) -> Open | O50: =IFERROR(HYPERLINK("#"&F50&"!A"&MATCH(A50,INDIRECT("'"&F50&"'!A:A"),0),"Open"),HYPERLINK("#"&F50&"!A1","Open")) -> Open
B51: Top Issues by Template | C51: /amc-conference-2023/ -> Thin Content | D51: Observation | E51: 7 | F51: Template & Duplication Risks | J51: Open | L51: Summary | M51: 51 | N51: =IFERROR(HYPERLINK("#'Main'!B"&MATCH(TRIM(A51),Main!B:B,0),"Open"),HYPERLINK("#'Main'!B1","Open")) -> Open | O51: =IFERROR(HYPERLINK("#"&F51&"!A"&MATCH(A51,INDIRECT("'"&F51&"'!A:A"),0),"Open"),HYPERLINK("#"&F51&"!A1","Open")) -> Open
B52: Top Issues by Template | C52: /amc-conference-2023/ -> Missing H1 | D52: Observation | E52: 2 | F52: Template & Duplication Risks | J52: Open | L52: Summary | M52: 52 | N52: =IFERROR(HYPERLINK("#'Main'!B"&MATCH(TRIM(A52),Main!B:B,0),"Open"),HYPERLINK("#'Main'!B1","Open")) -> Open | O52: =IFERROR(HYPERLINK("#"&F52&"!A"&MATCH(A52,INDIRECT("'"&F52&"'!A:A"),0),"Open"),HYPERLINK("#"&F52&"!A1","Open")) -> Open
B53: Top Issues by Template | C53: /amc-conference-2023/ -> Missing Meta Description | D53: Observation | E53: 1 | F53: Template & Duplication Risks | J53: Open | L53: Summary | M53: 53 | N53: =IFERROR(HYPERLINK("#'Main'!B"&MATCH(TRIM(A53),Main!B:B,0),"Open"),HYPERLINK("#'Main'!B1","Open")) -> Open | O53: =IFERROR(HYPERLINK("#"&F53&"!A"&MATCH(A53,INDIRECT("'"&F53&"'!A:A"),0),"Open"),HYPERLINK("#"&F53&"!A1","Open")) -> Open
B54: Top Issues by Template | C54: /amc-awards-2024/ -> Multiple H1 | D54: Observation | E54: 1 | F54: Template & Duplication Risks | J54: Open | L54: Summary | M54: 54 | N54: =IFERROR(HYPERLINK("#'Main'!B"&MATCH(TRIM(A54),Main!B:B,0),"Open"),HYPERLINK("#'Main'!B1","Open")) -> Open | O54: =IFERROR(HYPERLINK("#"&F54&"!A"&MATCH(A54,INDIRECT("'"&F54&"'!A:A"),0),"Open"),HYPERLINK("#"&F54&"!A1","Open")) -> Open
B55: Top Issues by Template | C55: /amc-awards-2024/ -> Low Image Alt Coverage | D55: Observation | E55: 1 | F55: Template & Duplication Risks | J55: Open | L55: Summary | M55: 55 | N55: =IFERROR(HYPERLINK("#'Main'!B"&MATCH(TRIM(A55),Main!B:B,0),"Open"),HYPERLINK("#'Main'!B1","Open")) -> Open | O55: =IFERROR(HYPERLINK("#"&F55&"!A"&MATCH(A55,INDIRECT("'"&F55&"'!A:A"),0),"Open"),HYPERLINK("#"&F55&"!A1","Open")) -> Open
B56: Top Issues by Template | C56: /amc-awards-2024/ -> Low AEO Readiness Score | D56: Observation | E56: 1 | F56: Template & Duplication Risks | J56: Open | L56: Summary | M56: 56 | N56: =IFERROR(HYPERLINK("#'Main'!B"&MATCH(TRIM(A56),Main!B:B,0),"Open"),HYPERLINK("#'Main'!B1","Open")) -> Open | O56: =IFERROR(HYPERLINK("#"&F56&"!A"&MATCH(A56,INDIRECT("'"&F56&"'!A:A"),0),"Open"),HYPERLINK("#"&F56&"!A1","Open")) -> Open
... B64: Top Issues by Template | C64: /about-us/ -> Thin Content | D64: Observation | E64: 1 | F64: Template & Duplication Risks | J64: Open | L64: Summary | M64: 64 | N64: =IFERROR(HYPERLINK("#'Main'!B"&MATCH(TRIM(A64),Main!B:B,0),"Open"),HYPERLINK("#'Main'!B1","Open")) -> Open | O64: =IFERROR(HYPERLINK("#"&F64&"!A"&MATCH(A64,INDIRECT("'"&F64&"'!A:A"),0),"Open"),HYPERLINK("#"&F64&"!A1","Open")) -> Open
A65: https://africanmarketingconfederation.org/amc-awards-2024 | B65: Issue Inventory | C65: Multiple H1 | D65: Warning | E65: 1 | F65: Technical Diagnostics | G65: https://africanmarketingconfederation.org/amc-awards-2024::multiple_h1 | H65: Copy Writer | J65: Open | K65: https://africanmarketingconfederation.org/amc-awards-2024 | L65: IssueInventory | M65: 2 | N65: =IFERROR(HYPERLINK("#'Main'!B"&MATCH(TRIM(A65),Main!B:B,0),"Open"),HYPERLINK("#'Main'!B1","Open")) -> Open | O65: =IFERROR(HYPERLINK("#"&F65&"!A"&MATCH(A65,INDIRECT("'"&F65&"'!A:A"),0),"Open"),HYPERLINK("#"&F65&"!A1","Open")) -> Open
A66: https://africanmarketingconfederation.org/amc-awards-2024 | B66: Issue Inventory | C66: Low Image Alt Coverage | D66: Warning | E66: 1 | F66: Technical Diagnostics | G66: https://africanmarketingconfederation.org/amc-awards-2024::low_image_alt_coverage | H66: Copy Writer | J66: Open | K66: https://africanmarketingconfederation.org/amc-awards-2024 | L66: IssueInventory | M66: 3 | N66: =IFERROR(HYPERLINK("#'Main'!B"&MATCH(TRIM(A66),Main!B:B,0),"Open"),HYPERLINK("#'Main'!B1","Open")) -> Open | O66: =IFERROR(HYPERLINK("#"&F66&"!A"&MATCH(A66,INDIRECT("'"&F66&"'!A:A"),0),"Open"),HYPERLINK("#"&F66&"!A1","Open")) -> Open
A67: https://africanmarketingconfederation.org/amc-awards-2024 | B67: Issue Inventory | C67: Low AEO Readiness Score | D67: Warning | E67: 1 | F67: Content & AI Readiness | G67: https://africanmarketingconfederation.org/amc-awards-2024::low_aeo_readiness_score | H67: Copy Writer | J67: Open | K67: https://africanmarketingconfederation.org/amc-awards-2024 | L67: IssueInventory | M67: 4 | N67: =IFERROR(HYPERLINK("#'Main'!B"&MATCH(TRIM(A67),Main!B:B,0),"Open"),HYPERLINK("#'Main'!B1","Open")) -> Open | O67: =IFERROR(HYPERLINK("#"&F67&"!A"&MATCH(A67,INDIRECT("'"&F67&"'!A:A"),0),"Open"),HYPERLINK("#"&F67&"!A1","Open")) -> Open
A68: https://africanmarketingconfederation.org/amc-awards-2024 | B68: Issue Inventory | C68: No ETag Header | D68: Observation | E68: 1 | F68: Technical Diagnostics | G68: https://africanmarketingconfederation.org/amc-awards-2024::no_etag_header | H68: Server/Host | J68: Open | K68: https://africanmarketingconfederation.org/amc-awards-2024 | L68: IssueInventory | M68: 5 | N68: =IFERROR(HYPERLINK("#'Main'!B"&MATCH(TRIM(A68),Main!B:B,0),"Open"),HYPERLINK("#'Main'!B1","Open")) -> Open | O68: =IFERROR(HYPERLINK("#"&F68&"!A"&MATCH(A68,INDIRECT("'"&F68&"'!A:A"),0),"Open"),HYPERLINK("#"&F68&"!A1","Open")) -> Open
A69: https://africanmarketingconfederation.org/amc-awards-2024 | B69: Issue Inventory | C69: No Question Headings | D69: Observation | E69: 1 | F69: Content & AI Readiness | G69: https://africanmarketingconfederation.org/amc-awards-2024::no_question_headings | H69: Copy Writer | J69: Open | K69: https://africanmarketingconfederation.org/amc-awards-2024 | L69: IssueInventory | M69: 6 | N69: =IFERROR(HYPERLINK("#'Main'!B"&MATCH(TRIM(A69),Main!B:B,0),"Open"),HYPERLINK("#'Main'!B1","Open")) -> Open | O69: =IFERROR(HYPERLINK("#"&F69&"!A"&MATCH(A69,INDIRECT("'"&F69&"'!A:A"),0),"Open"),HYPERLINK("#"&F69&"!A1","Open")) -> Open
A70: https://africanmarketingconfederation.org/amc-awards-2024 | B70: Issue Inventory | C70: No 40-60 Word Answer Paragraphs | D70: Observation | E70: 1 | F70: Technical Diagnostics | G70: https://africanmarketingconfederation.org/amc-awards-2024::no_40-60_word_answer_paragraphs | H70: Copy Writer | J70: Open | K70: https://africanmarketingconfederation.org/amc-awards-2024 | L70: IssueInventory | M70: 7 | N70: =IFERROR(HYPERLINK("#'Main'!B"&MATCH(TRIM(A70),Main!B:B,0),"Open"),HYPERLINK("#'Main'!B1","Open")) -> Open | O70: =IFERROR(HYPERLINK("#"&F70&"!A"&MATCH(A70,INDIRECT("'"&F70&"'!A:A"),0),"Open"),HYPERLINK("#"&F70&"!A1","Open")) -> Open
A71: https://africanmarketingconfederation.org/amc-awards-2024 | B71: Issue Inventory | C71: AI Crawlers Not Explicitly Allowed | D71: Observation | E71: 1 | F71: Technical Diagnostics | G71: https://africanmarketingconfederation.org/amc-awards-2024::ai_crawlers_not_explicitly_allowed | H71: Copy Writer | J71: Open | K71: https://africanmarketingconfederation.org/amc-awards-2024 | L71: IssueInventory | M71: 8 | N71: =IFERROR(HYPERLINK("#'Main'!B"&MATCH(TRIM(A71),Main!B:B,0),"Open"),HYPERLINK("#'Main'!B1","Open")) -> Open | O71: =IFERROR(HYPERLINK("#"&F71&"!A"&MATCH(A71,INDIRECT("'"&F71&"'!A:A"),0),"Open"),HYPERLINK("#"&F71&"!A1","Open")) -> Open
A72: https://africanmarketingconfederation.org/about-us | B72: Issue Inventory | C72: Low Image Alt Coverage | D72: Warning | E72: 1 | F72: Technical Diagnostics | G72: https://africanmarketingconfederation.org/about-us::low_image_alt_coverage | H72: Copy Writer | J72: Open | K72: https://africanmarketingconfederation.org/about-us | L72: IssueInventory | M72: 9 | N72: =IFERROR(HYPERLINK("#'Main'!B"&MATCH(TRIM(A72),Main!B:B,0),"Open"),HYPERLINK("#'Main'!B1","Open")) -> Open | O72: =IFERROR(HYPERLINK("#"&F72&"!A"&MATCH(A72,INDIRECT("'"&F72&"'!A:A"),0),"Open"),HYPERLINK("#"&F72&"!A1","Open")) -> Open
A73: https://africanmarketingconfederation.org/about-us | B73: Issue Inventory | C73: Low AEO Readiness Score | D73: Warning | E73: 1 | F73: Content & AI Readiness | G73: https://africanmarketingconfederation.org/about-us::low_aeo_readiness_score | H73: Copy Writer | J73: Open | K73: https://africanmarketingconfederation.org/about-us | L73: IssueInventory | M73: 10 | N73: =IFERROR(HYPERLINK("#'Main'!B"&MATCH(TRIM(A73),Main!B:B,0),"Open"),HYPERLINK("#'Main'!B1","Open")) -> Open | O73: =IFERROR(HYPERLINK("#"&F73&"!A"&MATCH(A73,INDIRECT("'"&F73&"'!A:A"),0),"Open"),HYPERLINK("#"&F73&"!A1","Open")) -> Open
A74: https://africanmarketingconfederation.org/about-us | B74: Issue Inventory | C74: No ETag Header | D74: Observation | E74: 1 | F74: Technical Diagnostics | G74: https://africanmarketingconfederation.org/about-us::no_etag_header | H74: Server/Host | J74: Open | K74: https://africanmarketingconfederation.org/about-us | L74: IssueInventory | M74: 11 | N74: =IFERROR(HYPERLINK("#'Main'!B"&MATCH(TRIM(A74),Main!B:B,0),"Open"),HYPERLINK("#'Main'!B1","Open")) -> Open | O74: =IFERROR(HYPERLINK("#"&F74&"!A"&MATCH(A74,INDIRECT("'"&F74&"'!A:A"),0),"Open"),HYPERLINK("#"&F74&"!A1","Open")) -> Open
A75: https://africanmarketingconfederation.org/about-us | B75: Issue Inventory | C75: Thin Content | D75: Observation | E75: 1 | F75: Technical Diagnostics | G75: https://africanmarketingconfederation.org/about-us::thin_content | H75: Copy Writer | J75: Open | K75: https://africanmarketingconfederation.org/about-us | L75: IssueInventory | M75: 12 | N75: =IFERROR(HYPERLINK("#'Main'!B"&MATCH(TRIM(A75),Main!B:B,0),"Open"),HYPERLINK("#'Main'!B1","Open")) -> Open | O75: =IFERROR(HYPERLINK("#"&F75&"!A"&MATCH(A75,INDIRECT("'"&F75&"'!A:A"),0),"Open"),HYPERLINK("#"&F75&"!A1","Open")) -> Open
A76: https://africanmarketingconfederation.org/about-us | B76: Issue Inventory | C76: No Question Headings | D76: Observation | E76: 1 | F76: Content & AI Readiness | G76: https://africanmarketingconfederation.org/about-us::no_question_headings | H76: Copy Writer | J76: Open | K76: https://africanmarketingconfederation.org/about-us | L76: IssueInventory | M76: 13 | N76: =IFERROR(HYPERLINK("#'Main'!B"&MATCH(TRIM(A76),Main!B:B,0),"Open"),HYPERLINK("#'Main'!B1","Open")) -> Open | O76: =IFERROR(HYPERLINK("#"&F76&"!A"&MATCH(A76,INDIRECT("'"&F76&"'!A:A"),0),"Open"),HYPERLINK("#"&F76&"!A1","Open")) -> Open
... A205: https://africanmarketingconfederation.org/amc-conference-2025-highlights | B205: Issue Inventory | C205: AI Crawlers Not Explicitly Allowed | D205: Observation | E205: 1 | F205: Technical Diagnostics | G205: https://africanmarketingconfederation.org/amc-conference-2025-highlights::ai_crawlers_not_explicitly_allowed | H205: Copy Writer | J205: Open | K205: https://africanmarketingconfederation.org/amc-conference-2025-highlights | L205: IssueInventory | M205: 142 | N205: =IFERROR(HYPERLINK("#'Main'!B"&MATCH(TRIM(A205),Main!B:B,0),"Open"),HYPERLINK("#'Main'!B1","Open")) -> Open | O205: =IFERROR(HYPERLINK("#"&F205&"!A"&MATCH(A205,INDIRECT("'"&F205&"'!A:A"),0),"Open"),HYPERLINK("#"&F205&"!A1","Open")) -> Open

Sheet Technical Diagnostics
A1: URL | B1: Diagnostic Category | C1: Status Code | D1: Severity Badge | E1: SEO Health Score | F1: Pass Flag | G1: Critical Issues Count | H1: Warning Issues Count | I1: Extraction State | J1: Extraction Source | K1: Indexability Reason | L1: Canonical Type | M1: Redirect Chain Length | N1: Redirect Loop Flag | O1: Strict-Transport-Security | P1: Content-Security-Policy | Q1: X-Content-Type-Options | R1: Desktop PSI Score | S1: Mobile PSI Score | T1: Mobile LCP (s) | U1: Mobile CLS | V1: Mobile TTFB (s) | W1: Final URL | X1: Canonical URL | Y1: Meta Robots Raw | Z1: X-Robots-Tag | AA1: Source Legacy Tab | AB1: Open in Main | AC1: BACK TO DASHBOARD
A2: https://africanmarketingconfederation.org/amc-awards-2024 | B2: Technical | Indexability | C2: 200 | D2: Warning | E2: 60 | F2: Non-Pass | G2: 0 | H2: 3 | I2: partial | J2: rendered_browser | K2: Indexable | L2: self | M2: 0 | N2: FALSE | R2: 0 | S2: 0 | T2: 0 | U2: 0 | V2: 0 | W2: https://africanmarketingconfederation.org/amc-awards-2024 | X2: https://africanmarketingconfederation.org/amc-awards-2024 | Y2: max-image-preview:large | AA2: Technical | Indexability | AB2: =IFERROR(HYPERLINK("#'Main'!B"&MATCH(TRIM(A2),Main!B:B,0),"Open"),HYPERLINK("#'Main'!B1","Open")) -> Open
A3: https://africanmarketingconfederation.org/about-us | B3: Technical | Indexability | C3: 200 | D3: Warning | E3: 70 | F3: Non-Pass | G3: 0 | H3: 2 | I3: partial | J3: rendered_browser | K3: Indexable | L3: self | M3: 0 | N3: FALSE | R3: 0 | S3: 0 | T3: 0 | U3: 0 | V3: 0 | W3: https://africanmarketingconfederation.org/about-us | X3: https://africanmarketingconfederation.org/about-us | Y3: max-image-preview:large | AA3: Technical | Indexability | AB3: =IFERROR(HYPERLINK("#'Main'!B"&MATCH(TRIM(A3),Main!B:B,0),"Open"),HYPERLINK("#'Main'!B1","Open")) -> Open
A4: https://africanmarketingconfederation.org/ | B4: Technical | Indexability | C4: 200 | D4: Warning | E4: 60 | F4: Non-Pass | G4: 0 | H4: 3 | I4: partial | J4: rendered_browser | K4: Indexable | L4: self | M4: 0 | N4: FALSE | R4: 0 | S4: 0 | T4: 0 | U4: 0 | V4: 0 | W4: https://africanmarketingconfederation.org/ | X4: https://africanmarketingconfederation.org/ | Y4: max-image-preview:large | AA4: Technical | Indexability | AB4: =IFERROR(HYPERLINK("#'Main'!B"&MATCH(TRIM(A4),Main!B:B,0),"Open"),HYPERLINK("#'Main'!B1","Open")) -> Open
A5: https://africanmarketingconfederation.org/african-marketing-confederation-tourism-chapter | B5: Technical | Indexability | C5: 200 | D5: Warning | E5: 70 | F5: Non-Pass | G5: 0 | H5: 2 | I5: partial | J5: rendered_browser | K5: Indexable | L5: self | M5: 0 | N5: FALSE | R5: 0 | S5: 0 | T5: 0 | U5: 0 | V5: 0 | W5: https://africanmarketingconfederation.org/african-marketing-confederation-tourism-chapter | X5: https://africanmarketingconfederation.org/african-marketing-confederation-tourism-chapter | Y5: max-image-preview:large | AA5: Technical | Indexability | AB5: =IFERROR(HYPERLINK("#'Main'!B"&MATCH(TRIM(A5),Main!B:B,0),"Open"),HYPERLINK("#'Main'!B1","Open")) -> Open
A6: https://africanmarketingconfederation.org/amc-conference-2022-prospectus | B6: Technical | Indexability | C6: 200 | D6: Warning | E6: 60 | F6: Non-Pass | G6: 0 | H6: 3 | I6: partial | J6: rendered_browser | K6: Indexable | L6: self | M6: 0 | N6: FALSE | R6: 0 | S6: 0 | T6: 0 | U6: 0 | V6: 0 | W6: https://africanmarketingconfederation.org/amc-conference-2022-prospectus | X6: https://africanmarketingconfederation.org/amc-conference-2022-prospectus | Y6: max-image-preview:large | AA6: Technical | Indexability | AB6: =IFERROR(HYPERLINK("#'Main'!B"&MATCH(TRIM(A6),Main!B:B,0),"Open"),HYPERLINK("#'Main'!B1","Open")) -> Open
A7: https://africanmarketingconfederation.org/amc-conference-2022-thank-you | B7: Technical | Indexability | C7: 200 | D7: Warning | E7: 60 | F7: Non-Pass | G7: 0 | H7: 3 | I7: partial | J7: rendered_browser | K7: Indexable | L7: self | M7: 0 | N7: FALSE | R7: 0 | S7: 0 | T7: 0 | U7: 0 | V7: 0 | W7: https://africanmarketingconfederation.org/amc-conference-2022-thank-you | X7: https://africanmarketingconfederation.org/amc-conference-2022-thank-you | Y7: max-image-preview:large | AA7: Technical | Indexability | AB7: =IFERROR(HYPERLINK("#'Main'!B"&MATCH(TRIM(A7),Main!B:B,0),"Open"),HYPERLINK("#'Main'!B1","Open")) -> Open
A8: https://africanmarketingconfederation.org/amc-conference-2022 | B8: Technical | Indexability | C8: 200 | D8: Warning | E8: 60 | F8: Non-Pass | G8: 0 | H8: 3 | I8: partial | J8: rendered_browser | K8: Indexable | L8: self | M8: 0 | N8: FALSE | R8: 0 | S8: 0 | T8: 0 | U8: 0 | V8: 0 | W8: https://africanmarketingconfederation.org/amc-conference-2022 | X8: https://africanmarketingconfederation.org/amc-conference-2022 | Y8: max-image-preview:large | AA8: Technical | Indexability | AB8: =IFERROR(HYPERLINK("#'Main'!B"&MATCH(TRIM(A8),Main!B:B,0),"Open"),HYPERLINK("#'Main'!B1","Open")) -> Open
A9: https://africanmarketingconfederation.org/amc-conference-2023 | B9: Technical | Indexability | C9: 200 | D9: Warning | E9: 70 | F9: Non-Pass | G9: 0 | H9: 2 | I9: partial | J9: rendered_browser | K9: Indexable | L9: self | M9: 0 | N9: FALSE | R9: 0 | S9: 0 | T9: 0 | U9: 0 | V9: 0 | W9: https://africanmarketingconfederation.org/amc-conference-2023 | X9: https://africanmarketingconfederation.org/amc-conference-2023 | Y9: max-image-preview:large | AA9: Technical | Indexability | AB9: =IFERROR(HYPERLINK("#'Main'!B"&MATCH(TRIM(A9),Main!B:B,0),"Open"),HYPERLINK("#'Main'!B1","Open")) -> Open
A10: https://africanmarketingconfederation.org/amc-conference-2023/amc-awards-book-now | B10: Technical | Indexability | C10: 200 | D10: Warning | E10: 50 | F10: Non-Pass | G10: 0 | H10: 4 | I10: partial | J10: rendered_browser | K10: Indexable | L10: self | M10: 0 | N10: FALSE | R10: 0 | S10: 0 | T10: 0 | U10: 0 | V10: 0 | W10: https://africanmarketingconfederation.org/amc-conference-2023/amc-awards-book-now | X10: https://africanmarketingconfederation.org/amc-conference-2023/amc-awards-book-now | Y10: max-image-preview:large | AA10: Technical | Indexability | AB10: =IFERROR(HYPERLINK("#'Main'!B"&MATCH(TRIM(A10),Main!B:B,0),"Open"),HYPERLINK("#'Main'!B1","Open")) -> Open
A11: https://africanmarketingconfederation.org/amc-conference-2023/amc-awards | B11: Technical | Indexability | C11: 200 | D11: Warning | E11: 70 | F11: Non-Pass | G11: 0 | H11: 2 | I11: partial | J11: rendered_browser | K11: Indexable | L11: self | M11: 0 | N11: FALSE | R11: 0 | S11: 0 | T11: 0 | U11: 0 | V11: 0 | W11: https://africanmarketingconfederation.org/amc-conference-2023/amc-awards | X11: https://africanmarketingconfederation.org/amc-conference-2023/amc-awards | Y11: max-image-preview:large | AA11: Technical | Indexability | AB11: =IFERROR(HYPERLINK("#'Main'!B"&MATCH(TRIM(A11),Main!B:B,0),"Open"),HYPERLINK("#'Main'!B1","Open")) -> Open
A12: https://africanmarketingconfederation.org/amc-conference-2023/book-now-thank-you | B12: Technical | Indexability | C12: 200 | D12: Warning | E12: 70 | F12: Non-Pass | G12: 0 | H12: 2 | I12: partial | J12: rendered_browser | K12: Indexable | L12: self | M12: 0 | N12: FALSE | R12: 0 | S12: 0 | T12: 0 | U12: 0 | V12: 0 | W12: https://africanmarketingconfederation.org/amc-conference-2023/book-now-thank-you | X12: https://africanmarketingconfederation.org/amc-conference-2023/book-now-thank-you | Y12: max-image-preview:large | AA12: Technical | Indexability | AB12: =IFERROR(HYPERLINK("#'Main'!B"&MATCH(TRIM(A12),Main!B:B,0),"Open"),HYPERLINK("#'Main'!B1","Open")) -> Open
A13: https://africanmarketingconfederation.org/amc-conference-2023/book-now | B13: Technical | Indexability | C13: 200 | D13: Warning | E13: 70 | F13: Non-Pass | G13: 0 | H13: 2 | I13: partial | J13: rendered_browser | K13: Indexable | L13: self | M13: 0 | N13: FALSE | R13: 0 | S13: 0 | T13: 0 | U13: 0 | V13: 0 | W13: https://africanmarketingconfederation.org/amc-conference-2023/book-now | X13: https://africanmarketingconfederation.org/amc-conference-2023/book-now | Y13: max-image-preview:large | AA13: Technical | Indexability | AB13: =IFERROR(HYPERLINK("#'Main'!B"&MATCH(TRIM(A13),Main!B:B,0),"Open"),HYPERLINK("#'Main'!B1","Open")) -> Open
... A21: https://africanmarketingconfederation.org/amc-conference-2025-highlights | B21: Technical | Indexability | C21: 200 | D21: Warning | E21: 60 | F21: Non-Pass | G21: 0 | H21: 3 | I21: partial | J21: rendered_browser | K21: Indexable | L21: self | M21: 0 | N21: FALSE | R21: 0 | S21: 0 | T21: 0 | U21: 0 | V21: 0 | W21: https://africanmarketingconfederation.org/amc-conference-2025-highlights | X21: https://africanmarketingconfederation.org/amc-conference-2025-highlights | Y21: max-image-preview:large | AA21: Technical | Indexability | AB21: =IFERROR(HYPERLINK("#'Main'!B"&MATCH(TRIM(A21),Main!B:B,0),"Open"),HYPERLINK("#'Main'!B1","Open")) -> Open

Sheet Content & AI Readiness
A1: URL | B1: Content Category | C1: Word Count | D1: Readability (Rough Flesch) | E1: Flesch-Kincaid Grade (Est.) | F1: Thin Content Flag | G1: H1 Count | H1: Missing H1 Flag | I1: Meta Description Missing | J1: AEO Readiness Score | K1: AEO Badge | L1: Schema Types Count | M1: Schema Types Found | N1: Schema Parse Errors | O1: Question Heading Count | P1: Answer Blocks | Q1: FAQ Section Count | R1: Image Count | S1: Images Missing Alt | T1: Image Alt Coverage (%) | U1: AEO Extractability Score | V1: Title Missing | W1: Media Mixed Content Detected | X1: Source Legacy Tab | Y1: Open in Main | Z1: BACK TO DASHBOARD
A2: https://africanmarketingconfederation.org/amc-awards-2024 | B2: Content | AEO | Media | C2: 1668 | D2: 178.62 | E2: 19.13 | F2: FALSE | G2: 2 | H2: FALSE | I2: FALSE | J2: 15 | K2: Needs Work | L2: 0 | N2: 0 | O2: 0 | P2: 0 | Q2: 0 | R2: 93 | S2: 25 | T2: 73.12 | U2: 55 | V2: FALSE | W2: FALSE | X2: Content | AEO | Media | Y2: =IFERROR(HYPERLINK("#'Main'!B"&MATCH(TRIM(A2),Main!B:B,0),"Open"),HYPERLINK("#'Main'!B1","Open")) -> Open
A3: https://africanmarketingconfederation.org/about-us | B3: Content | AEO | Media | C3: 235 | D3: 172.76 | E3: 21.55 | F3: TRUE | G3: 1 | H3: FALSE | I3: FALSE | J3: 15 | K3: Needs Work | L3: 0 | N3: 0 | O3: 0 | P3: 0 | Q3: 0 | R3: 44 | S3: 12 | T3: 72.73 | U3: 55 | V3: FALSE | W3: FALSE | X3: Content | AEO | Media | Y3: =IFERROR(HYPERLINK("#'Main'!B"&MATCH(TRIM(A3),Main!B:B,0),"Open"),HYPERLINK("#'Main'!B1","Open")) -> Open
A4: https://africanmarketingconfederation.org/ | B4: Content | AEO | Media | C4: 37 | D4: 188.06 | E4: 11.08 | F4: TRUE | G4: 5 | H4: FALSE | I4: FALSE | J4: 31.76 | K4: Needs Work | L4: 0 | N4: 0 | O4: 0 | P4: 0 | Q4: 0 | R4: 63 | S4: 13 | T4: 79.37 | U4: 55 | V4: FALSE | W4: FALSE | X4: Content | AEO | Media | Y4: =IFERROR(HYPERLINK("#'Main'!B"&MATCH(TRIM(A4),Main!B:B,0),"Open"),HYPERLINK("#'Main'!B1","Open")) -> Open
A5: https://africanmarketingconfederation.org/african-marketing-confederation-tourism-chapter | B5: Content | AEO | Media | C5: 355 | D5: 179.12 | E5: 18.96 | F5: FALSE | G5: 2 | H5: FALSE | I5: FALSE | J5: 15 | K5: Needs Work | L5: 0 | N5: 0 | O5: 0 | P5: 0 | Q5: 0 | R5: 48 | S5: 9 | T5: 81.25 | U5: 55 | V5: FALSE | W5: FALSE | X5: Content | AEO | Media | Y5: =IFERROR(HYPERLINK("#'Main'!B"&MATCH(TRIM(A5),Main!B:B,0),"Open"),HYPERLINK("#'Main'!B1","Open")) -> Open
A6: https://africanmarketingconfederation.org/amc-conference-2022-prospectus | B6: Content | AEO | Media | C6: 120 | D6: 145.94 | E6: 26.1 | F6: TRUE | G6: 0 | H6: TRUE | I6: FALSE | J6: 15 | K6: Needs Work | L6: 0 | N6: 0 | O6: 0 | P6: 0 | Q6: 0 | R6: 23 | S6: 8 | T6: 65.22 | U6: 55 | V6: FALSE | W6: FALSE | X6: Content | AEO | Media | Y6: =IFERROR(HYPERLINK("#'Main'!B"&MATCH(TRIM(A6),Main!B:B,0),"Open"),HYPERLINK("#'Main'!B1","Open")) -> Open
A7: https://africanmarketingconfederation.org/amc-conference-2022-thank-you | B7: Content | AEO | Media | C7: 367 | D7: 178.18 | E7: 18.28 | F7: FALSE | G7: 0 | H7: TRUE | I7: FALSE | J7: 15 | K7: Needs Work | L7: 0 | N7: 0 | O7: 0 | P7: 0 | Q7: 0 | R7: 30 | S7: 15 | T7: 50 | U7: 55 | V7: FALSE | W7: FALSE | X7: Content | AEO | Media | Y7: =IFERROR(HYPERLINK("#'Main'!B"&MATCH(TRIM(A7),Main!B:B,0),"Open"),HYPERLINK("#'Main'!B1","Open")) -> Open
A8: https://africanmarketingconfederation.org/amc-conference-2022 | B8: Content | AEO | Media | C8: 32 | D8: 196.01 | E8: 10.7 | F8: TRUE | G8: 0 | H8: TRUE | I8: FALSE | J8: 32.9 | K8: Needs Work | L8: 0 | N8: 0 | O8: 0 | P8: 0 | Q8: 0 | R8: 28 | S8: 13 | T8: 53.57 | U8: 55 | V8: FALSE | W8: FALSE | X8: Content | AEO | Media | Y8: =IFERROR(HYPERLINK("#'Main'!B"&MATCH(TRIM(A8),Main!B:B,0),"Open"),HYPERLINK("#'Main'!B1","Open")) -> Open
A9: https://africanmarketingconfederation.org/amc-conference-2023 | B9: Content | AEO | Media | C9: 415 | D9: 168.54 | E9: 23.18 | F9: FALSE | G9: 1 | H9: FALSE | I9: FALSE | J9: 15 | K9: Needs Work | L9: 0 | N9: 0 | O9: 0 | P9: 0 | Q9: 0 | R9: 56 | S9: 37 | T9: 33.93 | U9: 55 | V9: FALSE | W9: FALSE | X9: Content | AEO | Media | Y9: =IFERROR(HYPERLINK("#'Main'!B"&MATCH(TRIM(A9),Main!B:B,0),"Open"),HYPERLINK("#'Main'!B1","Open")) -> Open
A10: https://africanmarketingconfederation.org/amc-conference-2023/amc-awards-book-now | B10: Content | AEO | Media | C10: 31 | D10: 175.37 | E10: 15.91 | F10: TRUE | G10: 0 | H10: TRUE | I10: TRUE | J10: 17.27 | K10: Needs Work | L10: 0 | N10: 0 | O10: 0 | P10: 0 | Q10: 0 | R10: 20 | S10: 5 | T10: 75 | U10: 55 | V10: FALSE | W10: FALSE | X10: Content | AEO | Media | Y10: =IFERROR(HYPERLINK("#'Main'!B"&MATCH(TRIM(A10),Main!B:B,0),"Open"),HYPERLINK("#'Main'!B1","Open")) -> Open
A11: https://africanmarketingconfederation.org/amc-conference-2023/amc-awards | B11: Content | AEO | Media | C11: 326 | D11: 176.75 | E11: 19.64 | F11: FALSE | G11: 1 | H11: FALSE | I11: FALSE | J11: 15 | K11: Needs Work | L11: 0 | N11: 0 | O11: 0 | P11: 0 | Q11: 0 | R11: 25 | S11: 7 | T11: 72 | U11: 55 | V11: FALSE | W11: FALSE | X11: Content | AEO | Media | Y11: =IFERROR(HYPERLINK("#'Main'!B"&MATCH(TRIM(A11),Main!B:B,0),"Open"),HYPERLINK("#'Main'!B1","Open")) -> Open
A12: https://africanmarketingconfederation.org/amc-conference-2023/book-now-thank-you | B12: Content | AEO | Media | C12: 97 | D12: 174.02 | E12: 18.31 | F12: TRUE | G12: 0 | H12: TRUE | I12: FALSE | J12: 15 | K12: Needs Work | L12: 0 | N12: 0 | O12: 0 | P12: 0 | Q12: 0 | R12: 17 | S12: 2 | T12: 88.24 | U12: 55 | V12: FALSE | W12: FALSE | X12: Content | AEO | Media | Y12: =IFERROR(HYPERLINK("#'Main'!B"&MATCH(TRIM(A12),Main!B:B,0),"Open"),HYPERLINK("#'Main'!B1","Open")) -> Open
A13: https://africanmarketingconfederation.org/amc-conference-2023/book-now | B13: Content | AEO | Media | C13: 195 | D13: 8.91 | E13: 77.65 | F13: TRUE | G13: 1 | H13: FALSE | I13: FALSE | J13: 15 | K13: Needs Work | L13: 0 | N13: 0 | O13: 0 | P13: 0 | Q13: 0 | R13: 20 | S13: 5 | T13: 75 | U13: 55 | V13: FALSE | W13: FALSE | X13: Content | AEO | Media | Y13: =IFERROR(HYPERLINK("#'Main'!B"&MATCH(TRIM(A13),Main!B:B,0),"Open"),HYPERLINK("#'Main'!B1","Open")) -> Open
... A21: https://africanmarketingconfederation.org/amc-conference-2025-highlights | B21: Content | AEO | Media | C21: 1869 | D21: 183.98 | E21: 16.8 | F21: FALSE | G21: 10 | H21: FALSE | I21: FALSE | J21: 15 | K21: Needs Work | L21: 0 | N21: 0 | O21: 0 | P21: 0 | Q21: 0 | R21: 109 | S21: 94 | T21: 13.76 | U21: 55 | V21: FALSE | W21: FALSE | X21: Content | AEO | Media | Y21: =IFERROR(HYPERLINK("#'Main'!B"&MATCH(TRIM(A21),Main!B:B,0),"Open"),HYPERLINK("#'Main'!B1","Open")) -> Open

Sheet Link Intelligence
A1: URL | B1: Record Type | C1: Target URL | D1: Anchor Text | E1: Target Status (if crawled) | F1: Crawlable | G1: Internal Links Count | H1: Broken Internal Links Count | I1: Unresolved Internal Links Count | J1: External Links Count | K1: Inlinks Count | L1: Orphan Candidate | M1: Click Depth | N1: Internal PageRank | O1: Generic Anchor Text Count | P1: Nofollow Internal Links Count | Q1: Nofollow External Links Count | R1: Internal Link Statuses | S1: Actionable Fixes | T1: Source Legacy Tab | U1: Open in Main | V1: BACK TO DASHBOARD
A2: https://africanmarketingconfederation.org/amc-awards-2024 | B2: Summary | G2: 16 | H2: =COUNTIFS('Link Inventory'!$A:$A,$A2,'Link Inventory'!$E:$E,"Internal",'Link Inventory'!$F:$F,404)+COUNTIFS('Link Inventory'!$A:$A,$A2,'Link Inventory'!$E:$E,"Internal",'Link Inventory'!$F:$F,"404") -> 4 | I2: 0 | J2: 4 | K2: 0 | L2: TRUE | M2: 0 | N2: 0.011213 | O2: 0 | P2: 0 | Q2: 0 | R2: https://africanmarketingconfederation.org/amc-conference-2025 => 200 | https://africanmarketingconfederation.org/amc-conference-2025-delegate-packages => 404 | https://africanmarketingconfederation.org/amc-marketing-conference-2024/amc-programme-2025 => 200 | https://africanmarketingconfederation.org/amc-marketing-conference-2024/awards-2025 => 200 | https://africanmarketingconfederation.org/amc-sponsors-2025 => 200 | https://africanmarketingconfederation.org/conference-faq-2025 => 200 | https://africanmarketingconfederation.org/privacy-policy => 200 | https://africanmarketingconfederation.org/publications-2 => 200 | https://africanmarketingconfederation.org/speakers-2025 => 200 | S2: =IF(H2>0,"Fix "&H2&" broken links (See Link Inventory tab for details).","") -> Fix 4 broken links (See Link Inventory tab for details). | T2: Links | U2: =IFERROR(HYPERLINK("#'Main'!B"&MATCH(TRIM(A2),Main!B:B,0),"Open"),HYPERLINK("#'Main'!B1","Open")) -> Open
A3: https://africanmarketingconfederation.org/about-us | B3: Summary | G3: 32 | H3: =COUNTIFS('Link Inventory'!$A:$A,$A3,'Link Inventory'!$E:$E,"Internal",'Link Inventory'!$F:$F,404)+COUNTIFS('Link Inventory'!$A:$A,$A3,'Link Inventory'!$E:$E,"Internal",'Link Inventory'!$F:$F,"404") -> 4 | I3: 0 | J3: 7 | K3: 6 | L3: FALSE | M3: 1 | N3: 0.147311 | O3: 0 | P3: 0 | Q3: 0 | R3: https://africanmarketingconfederation.org/ => 200 | https://africanmarketingconfederation.org/about-us => 200 | https://africanmarketingconfederation.org/african-marketing-confederation-tourism-chapter => 200 | https://africanmarketingconfederation.org/amc-conference-2025-delegate-packages => 404 | https://africanmarketingconfederation.org/amc-conference-2026 => 200 | https://africanmarketingconfederation.org/certified-professional-marketer-africa => 200 | https://africanmarketingconfederation.org/chartered-marketer-africa => 200 | https://africanmarketingconfederation.org/contact-us => 200 | https://africanmarketingconfederation.org/education => 200 | https://africanmarketingconfederation.org/members => 200 | https://africanmarketingconfederation.org/news-articles => 200 | https://africanmarketingconfederation.org/privacy-policy => 200 | https://africanmarketingconfederation.org/publications-2 => 200 | https://africanmarketingconfederation.org/sub-committees => 200 | S3: =IF(H3>0,"Fix "&H3&" broken links (See Link Inventory tab for details).","") -> Fix 4 broken links (See Link Inventory tab for details). | T3: Links | U3: =IFERROR(HYPERLINK("#'Main'!B"&MATCH(TRIM(A3),Main!B:B,0),"Open"),HYPERLINK("#'Main'!B1","Open")) -> Open
A4: https://africanmarketingconfederation.org/ | B4: Summary | G4: 62 | H4: =COUNTIFS('Link Inventory'!$A:$A,$A4,'Link Inventory'!$E:$E,"Internal",'Link Inventory'!$F:$F,404)+COUNTIFS('Link Inventory'!$A:$A,$A4,'Link Inventory'!$E:$E,"Internal",'Link Inventory'!$F:$F,"404") -> 4 | I4: 0 | J4: 2 | K4: 14 | L4: FALSE | M4: 0 | N4: 0.188917 | O4: 2 | P4: 0 | Q4: 0 | R4: https://africanmarketingconfederation.org/ => 200 | https://africanmarketingconfederation.org/about-us => 200 | https://africanmarketingconfederation.org/african-marketing-confederation-tourism-chapter => 200 | https://africanmarketingconfederation.org/amc-conference-2025 => 200 | https://africanmarketingconfederation.org/amc-conference-2025-delegate-packages => 404 | https://africanmarketingconfederation.org/amc-conference-2026 => 200 | https://africanmarketingconfederation.org/certified-professional-marketer-africa => 200 | https://africanmarketingconfederation.org/chartered-marketer-africa => 200 | https://africanmarketingconfederation.org/contact-us => 200 | https://africanmarketingconfederation.org/cost-of-groceries-the-primary-worry-for-almost-half-of-sa-consumers => 200 | https://africanmarketingconfederation.org/cracking-the-africa-code-the-functional-path-to-market-leadership => 200 | https://africanmarketingconfederation.org/education => 200 | https://africanmarketingconfederation.org/lays-world-cup-marketing-strategy-focuses-on-fan-fun-and-togetherness => 200 | https://africanmarketingconfederation.org/members => 200 | https://africanmarketingconfederation.org/national-foods-holdings-expands-food-processing-capacity-in-zimbabwe => 200 | https://africanmarketingconfederation.org/news-articles => 200 | https://africanmarketingconfederation.org/privacy-policy => 200 | https://africanmarketingconfederation.org/publications-2 => 200 | https://africanmarketingconfederation.org/social-media-overtakes-television-as-main-source-of-news-for-kenyans => 200 | https://africanmarketingconfederation.org/sub-committees => 200 | https://africanmarketingconfederation.org/subscribe => 200 | https://africanmarketingconfederation.org/traceability-giving-africa-a-marketing-edge-the-world-can-audit => 200 | S4: =IF(H4>0,"Fix "&H4&" broken links (See Link Inventory tab for details).","") -> Fix 4 broken links (See Link Inventory tab for details). | T4: Links | U4: =IFERROR(HYPERLINK("#'Main'!B"&MATCH(TRIM(A4),Main!B:B,0),"Open"),HYPERLINK("#'Main'!B1","Open")) -> Open
A5: https://africanmarketingconfederation.org/african-marketing-confederation-tourism-chapter | B5: Summary | G5: 58 | H5: =COUNTIFS('Link Inventory'!$A:$A,$A5,'Link Inventory'!$E:$E,"Internal",'Link Inventory'!$F:$F,404)+COUNTIFS('Link Inventory'!$A:$A,$A5,'Link Inventory'!$E:$E,"Internal",'Link Inventory'!$F:$F,"404") -> 4 | I5: 0 | J5: 3 | K5: 6 | L5: FALSE | M5: 1 | N5: 0.147311 | O5: 0 | P5: 0 | Q5: 0 | R5: https://africanmarketingconfederation.org/ => 200 | https://africanmarketingconfederation.org/about-us => 200 | https://africanmarketingconfederation.org/african-marketing-confederation-tourism-chapter => 200 | https://africanmarketingconfederation.org/amc-conference-2025-delegate-packages => 404 | https://africanmarketingconfederation.org/amc-conference-2025-highlights => 200 | https://africanmarketingconfederation.org/amc-conference-2026 => 200 | https://africanmarketingconfederation.org/certified-professional-marketer-africa => 200 | https://africanmarketingconfederation.org/chartered-marketer-africa => 200 | https://africanmarketingconfederation.org/contact-us => 200 | https://africanmarketingconfederation.org/education => 200 | https://africanmarketingconfederation.org/members => 200 | https://africanmarketingconfederation.org/news-articles => 200 | https://africanmarketingconfederation.org/privacy-policy => 200 | https://africanmarketingconfederation.org/publications-2 => 200 | https://africanmarketingconfederation.org/sub-committees => 200 | S5: =IF(H5>0,"Fix "&H5&" broken links (See Link Inventory tab for details).","") -> Fix 4 broken links (See Link Inventory tab for details). | T5: Links | U5: =IFERROR(HYPERLINK("#'Main'!B"&MATCH(TRIM(A5),Main!B:B,0),"Open"),HYPERLINK("#'Main'!B1","Open")) -> Open
A6: https://africanmarketingconfederation.org/amc-conference-2022-prospectus | B6: Summary | G6: 32 | H6: =COUNTIFS('Link Inventory'!$A:$A,$A6,'Link Inventory'!$E:$E,"Internal",'Link Inventory'!$F:$F,404)+COUNTIFS('Link Inventory'!$A:$A,$A6,'Link Inventory'!$E:$E,"Internal",'Link Inventory'!$F:$F,"404") -> 4 | I6: 0 | J6: 4 | K6: 0 | L6: TRUE | M6: 0 | N6: 0.011213 | O6: 0 | P6: 0 | Q6: 0 | R6: https://africanmarketingconfederation.org/ => 200 | https://africanmarketingconfederation.org/about-us => 200 | https://africanmarketingconfederation.org/african-marketing-confederation-tourism-chapter => 200 | https://africanmarketingconfederation.org/amc-conference-2025-delegate-packages => 404 | https://africanmarketingconfederation.org/amc-conference-2026 => 200 | https://africanmarketingconfederation.org/certified-professional-marketer-africa => 200 | https://africanmarketingconfederation.org/chartered-marketer-africa => 200 | https://africanmarketingconfederation.org/contact-us => 200 | https://africanmarketingconfederation.org/education => 200 | https://africanmarketingconfederation.org/members => 200 | https://africanmarketingconfederation.org/news-articles => 200 | https://africanmarketingconfederation.org/privacy-policy => 200 | https://africanmarketingconfederation.org/publications-2 => 200 | https://africanmarketingconfederation.org/sub-committees => 200 | S6: =IF(H6>0,"Fix "&H6&" broken links (See Link Inventory tab for details).","") -> Fix 4 broken links (See Link Inventory tab for details). | T6: Links | U6: =IFERROR(HYPERLINK("#'Main'!B"&MATCH(TRIM(A6),Main!B:B,0),"Open"),HYPERLINK("#'Main'!B1","Open")) -> Open
A7: https://africanmarketingconfederation.org/amc-conference-2022-thank-you | B7: Summary | G7: 32 | H7: =COUNTIFS('Link Inventory'!$A:$A,$A7,'Link Inventory'!$E:$E,"Internal",'Link Inventory'!$F:$F,404)+COUNTIFS('Link Inventory'!$A:$A,$A7,'Link Inventory'!$E:$E,"Internal",'Link Inventory'!$F:$F,"404") -> 6 | I7: 0 | J7: 2 | K7: 0 | L7: TRUE | M7: 0 | N7: 0.011213 | O7: 0 | P7: 0 | Q7: 0 | R7: https://africanmarketingconfederation.org/ => 200 | https://africanmarketingconfederation.org/about-us => 200 | https://africanmarketingconfederation.org/african-marketing-confederation-tourism-chapter => 200 | https://africanmarketingconfederation.org/amc-conference-2025-delegate-packages => 404 | https://africanmarketingconfederation.org/amc-conference-2026 => 200 | https://africanmarketingconfederation.org/certified-professional-marketer-africa => 200 | https://africanmarketingconfederation.org/chartered-marketer-africa => 200 | https://africanmarketingconfederation.org/contact-us => 200 | https://africanmarketingconfederation.org/education => 200 | https://africanmarketingconfederation.org/members => 200 | https://africanmarketingconfederation.org/news-articles => 200 | https://africanmarketingconfederation.org/privacy-policy => 200 | https://africanmarketingconfederation.org/publications-2 => 200 | https://africanmarketingconfederation.org/sub-committees => 200 | https://africanmarketingconfederation.org/wp-content/uploads/2021/11/AMC-2022_Prospectus-low-res.pdf => 404 | S7: =IF(H7>0,"Fix "&H7&" broken links (See Link Inventory tab for details).","") -> Fix 6 broken links (See Link Inventory tab for details). | T7: Links | U7: =IFERROR(HYPERLINK("#'Main'!B"&MATCH(TRIM(A7),Main!B:B,0),"Open"),HYPERLINK("#'Main'!B1","Open")) -> Open
A8: https://africanmarketingconfederation.org/amc-conference-2022 | B8: Summary | G8: 99 | H8: =COUNTIFS('Link Inventory'!$A:$A,$A8,'Link Inventory'!$E:$E,"Internal",'Link Inventory'!$F:$F,404)+COUNTIFS('Link Inventory'!$A:$A,$A8,'Link Inventory'!$E:$E,"Internal",'Link Inventory'!$F:$F,"404") -> 4 | I8: 0 | J8: 3 | K8: 0 | L8: TRUE | M8: 0 | N8: 0.011213 | O8: 0 | P8: 0 | Q8: 0 | R8: https://africanmarketingconfederation.org/ => 200 | https://africanmarketingconfederation.org/2024-amc-awards-recognise-marketing-excellence-from-the-continent => 200 | https://africanmarketingconfederation.org/about-us => 200 | https://africanmarketingconfederation.org/african-marketing-confederation-tourism-chapter => 200 | https://africanmarketingconfederation.org/amc-conference-2025 => 200 | https://africanmarketingconfederation.org/amc-conference-2025-delegate-packages => 404 | https://africanmarketingconfederation.org/amc-conference-2026 => 200 | https://africanmarketingconfederation.org/amc-marketing-conference-2024/amc-programme-2025 => 200 | https://africanmarketingconfederation.org/amc-marketing-conference-2024/awards-2025 => 200 | https://africanmarketingconfederation.org/amc-officially-welcomes-new-member-associations-into-the-fold => 200 | https://africanmarketingconfederation.org/amc-sponsors-2025 => 200 | https://africanmarketingconfederation.org/certified-professional-marketer-africa => 200 | https://africanmarketingconfederation.org/chartered-marketer-africa => 200 | https://africanmarketingconfederation.org/conference-faq-2025 => 200 | https://africanmarketingconfederation.org/contact-us => 200 | https://africanmarketingconfederation.org/education => 200 | https://africanmarketingconfederation.org/excitement-as-ghana-announced-as-host-of-2025-amc-marketing-conference => 200 | https://africanmarketingconfederation.org/how-a-bold-strategy-saved-kiwi-marketing-association-from-extinction => 200 | https://africanmarketingconfederation.org/marketers-are-placing-the-ads-where-consumers-dont-want-to-see-them => 200 | https://africanmarketingconfederation.org/members => 200 | https://africanmarketingconfederation.org/news-articles => 200 | https://africanmarketingconfederation.org/privacy-policy => 200 | https://africanmarketingconfederation.org/publications-2 => 200 | https://africanmarketingconfederation.org/speakers-2025 => 200 | https://africanmarketingconfederation.org/sub-committees => 200 | https://africanmarketingconfederation.org/time-for-africa-to-control-its-own-narrative-and-image-delegates-told => 200 | https://africanmarketingconfederation.org/wp-content/uploads/2022/10/EA2A2394-scaled.jpg => 200 | https://africanmarketingconfederation.org/wp-content/uploads/2022/10/EA2A2427-scaled.jpg => 200 | https://africanmarketingconfederation.org/wp-content/uploads/2022/10/EA2A2487-scaled.jpg => 200 | https://africanmarketingconfederation.org/wp-content/uploads/2022/10/EA2A2512-scaled.jpg => 200 | https://africanmarketingconfederation.org/wp-content/uploads/2022/10/EA2A2525-scaled.jpg => 200 | https://africanmarketingconfederation.org/wp-content/uploads/2022/10/EA2A2527-scaled.jpg => 200 | https://africanmarketingconfederation.org/wp-content/uploads/2022/10/EA2A2536-scaled.jpg => 200 | https://africanmarketingconfederation.org/wp-content/uploads/2022/10/EA2A2999-scaled.jpg => 200 | https://africanmarketingconfederation.org/wp-content/uploads/2022/10/EA2A3057-scaled.jpg => 200 | https://africanmarketingconfederation.org/wp-content/uploads/2022/10/EA2A3111-scaled.jpg => 200 | https://africanmarketingconfederation.org/wp-content/uploads/2022/10/EA2A3195-scaled.jpg => 200 | https://africanmarketingconfederation.org/wp-content/uploads/2022/10/EA2A3198-scaled.jpg => 200 | https://africanmarketingconfederation.org/wp-content/uploads/2022/10/EA2A3217-scaled.jpg => 200 | https://africanmarketingconfederation.org/wp-content/uploads/2022/10/EA2A3254-scaled.jpg => 200 | https://africanmarketingconfederation.org/wp-content/uploads/2022/10/EA2A3268-scaled.jpg => 200 | https://africanmarketingconfederation.org/wp-content/uploads/2022/10/EA2A3293-scaled.jpg => 200 | https://africanmarketingconfederation.org/wp-content/uploads/2022/10/EA2A3369-scaled.jpg => 200 | https://africanmarketingconfederation.org/wp-content/uploads/2022/10/EA2A3396-scaled.jpg => 200 | https://africanmarketingconfederation.org/wp-content/uploads/2022/10/EA2A3485-scaled.jpg => 200 | https://africanmarketingconfederation.org/wp-content/uploads/2022/10/EA2A3505-scaled.jpg => 200 | https://africanmarketingconfederation.org/wp-content/uploads/2022/10/EA2A3816-scaled.jpg => 200 | https://africanmarketingconfederation.org/wp-content/uploads/2022/10/EA2A3869-scaled.jpg => 200 | https://africanmarketingconfederation.org/wp-content/uploads/2022/10/EA2A3879-scaled.jpg => 200 | https://africanmarketingconfederation.org/wp-content/uploads/2022/10/EA2A3892-scaled.jpg => 200 | https://africanmarketingconfederation.org/wp-content/uploads/2022/10/EA2A3922-scaled.jpg => 200 | https://africanmarketingconfederation.org/wp-content/uploads/2022/10/EA2A3930-scaled.jpg => 200 | https://africanmarketingconfederation.org/wp-content/uploads/2022/10/EA2A3936-scaled.jpg => 200 | https://africanmarketingconfederation.org/wp-content/uploads/2022/10/EA2A4027-scaled.jpg => 200 | https://africanmarketingconfederation.org/wp-content/uploads/2022/10/EA2A4067-scaled.jpg => 200 | https://africanmarketingconfederation.org/wp-content/uploads/2022/10/EA2A4121-scaled.jpg => 200 | https://africanmarketingconfederation.org/wp-content/uploads/2022/10/EA2A4137-scaled.jpg => 200 | https://africanmarketingconfederation.org/wp-content/uploads/2022/10/IMG_0031-scaled.jpg => 200 | https://africanmarketingconfederation.org/wp-content/uploads/2022/10/IMG_9698-scaled.jpg => 200 | https://africanmarketingconfederation.org/wp-content/uploads/2022/10/IMG_9719-scaled.jpg => 200 | https://africanmarketingconfederation.org/wp-content/uploads/2022/10/IMG_9758-scaled.jpg => 200 | https://africanmarketingconfederation.org/wp-content/uploads/2022/10/IMG_9953-scaled.jpg => 200 | https://africanmarketingconfederation.org/wp-content/uploads/2022/10/IMG_9964-scaled.jpg => 200 | https://africanmarketingconfederation.org/wp-content/uploads/2022/10/IMG_9985-scaled.jpg => 200 | S8: =IF(H8>0,"Fix "&H8&" broken links (See Link Inventory tab for details).","") -> Fix 4 broken links (See Link Inventory tab for details). | T8: Links | U8: =IFERROR(HYPERLINK("#'Main'!B"&MATCH(TRIM(A8),Main!B:B,0),"Open"),HYPERLINK("#'Main'!B1","Open")) -> Open
A9: https://africanmarketingconfederation.org/amc-conference-2023 | B9: Summary | G9: 41 | H9: =COUNTIFS('Link Inventory'!$A:$A,$A9,'Link Inventory'!$E:$E,"Internal",'Link Inventory'!$F:$F,404)+COUNTIFS('Link Inventory'!$A:$A,$A9,'Link Inventory'!$E:$E,"Internal",'Link Inventory'!$F:$F,"404") -> 8 | I9: 0 | J9: 13 | K9: 8 | L9: FALSE | M9: 0 | N9: 0.052819 | O9: 0 | P9: 0 | Q9: 0 | R9: https://africanmarketingconfederation.org/amc-conference-2023/gallery => 200 | https://africanmarketingconfederation.org/amc-conference-2023/programme => 200 | https://africanmarketingconfederation.org/amc-conference-2023/speakers => 200 | https://africanmarketingconfederation.org/amc-conference-2025 => 200 | https://africanmarketingconfederation.org/amc-conference-2025-delegate-packages => 404 | https://africanmarketingconfederation.org/amc-marketing-conference-2024/amc-programme-2025 => 200 | https://africanmarketingconfederation.org/amc-marketing-conference-2024/awards-2025 => 200 | https://africanmarketingconfederation.org/amc-sponsors-2025 => 200 | https://africanmarketingconfederation.org/calendar_events => 404 | https://africanmarketingconfederation.org/conference-faq-2025 => 200 | https://africanmarketingconfederation.org/privacy-policy => 200 | https://africanmarketingconfederation.org/publications-2 => 200 | https://africanmarketingconfederation.org/speakers-2025 => 200 | https://africanmarketingconfederation.org/wp-content/uploads/2023/09/AMC-TICON-0164.jpg => 200 | https://africanmarketingconfederation.org/wp-content/uploads/2023/09/AMC-TICON-1113.jpg => 200 | https://africanmarketingconfederation.org/wp-content/uploads/2023/09/AMC-TICON-1127.jpg => 200 | https://africanmarketingconfederation.org/wp-content/uploads/2023/09/AMC-Ticon-00246.jpg => 200 | https://africanmarketingconfederation.org/wp-content/uploads/2023/09/AMC-Ticon-00449.jpg => 200 | https://africanmarketingconfederation.org/wp-content/uploads/2023/09/AMC-Ticon-00481.jpg => 200 | https://africanmarketingconfederation.org/wp-content/uploads/2023/09/AMC-Ticon-00638.jpg => 200 | https://africanmarketingconfederation.org/wp-content/uploads/2023/09/AMC-Ticon-00682.jpg => 200 | https://africanmarketingconfederation.org/wp-content/uploads/2023/09/AMC-Ticon-00742.jpg => 200 | https://africanmarketingconfederation.org/wp-content/uploads/2023/09/AMC-Ticon-01128.jpg => 200 | https://africanmarketingconfederation.org/wp-content/uploads/2023/09/AMC-Ticon-01363.jpg => 200 | https://africanmarketingconfederation.org/wp-content/uploads/2023/09/AMC-Ticon-01409.jpg => 200 | https://africanmarketingconfederation.org/wp-content/uploads/2023/09/AMC-Ticon-01476.jpg => 200 | https://africanmarketingconfederation.org/wp-content/uploads/2023/09/AMC-Ticon-01530.jpg => 200 | https://africanmarketingconfederation.org/wp-content/uploads/2023/09/AMC-Ticon-01616.jpg => 200 | https://africanmarketingconfederation.org/wp-content/uploads/2023/09/AMC-Ticon-02950-1.jpg => 200 | https://africanmarketingconfederation.org/wp-content/uploads/2023/09/AMC-Ticon-03063.jpg => 200 | https://africanmarketingconfederation.org/wp-content/uploads/2023/09/AMC-Ticon-09823.jpg => 200 | https://africanmarketingconfederation.org/wp-content/uploads/2023/09/AMC-Ticon-09825.jpg => 200 | https://africanmarketingconfederation.org/wp-content/uploads/2023/09/AMC-Ticon-09953.jpg => 200 | S9: =IF(H9>0,"Fix "&H9&" broken links (See Link Inventory tab for details).","") -> Fix 8 broken links (See Link Inventory tab for details). | T9: Links | U9: =IFERROR(HYPERLINK("#'Main'!B"&MATCH(TRIM(A9),Main!B:B,0),"Open"),HYPERLINK("#'Main'!B1","Open")) -> Open
A10: https://africanmarketingconfederation.org/amc-conference-2023/amc-awards-book-now | B10: Summary | G10: 19 | H10: =COUNTIFS('Link Inventory'!$A:$A,$A10,'Link Inventory'!$E:$E,"Internal",'Link Inventory'!$F:$F,404)+COUNTIFS('Link Inventory'!$A:$A,$A10,'Link Inventory'!$E:$E,"Internal",'Link Inventory'!$F:$F,"404") -> 4 | I10: 0 | J10: 2 | K10: 0 | L10: TRUE | M10: 0 | N10: 0.011213 | O10: 0 | P10: 0 | Q10: 0 | R10: https://africanmarketingconfederation.org/ => 200 | https://africanmarketingconfederation.org/amc-conference-2023 => 200 | https://africanmarketingconfederation.org/amc-conference-2023/amc-awards => 200 | https://africanmarketingconfederation.org/amc-conference-2023/gallery => 200 | https://africanmarketingconfederation.org/amc-conference-2023/partners => 200 | https://africanmarketingconfederation.org/amc-conference-2023/programme => 200 | https://africanmarketingconfederation.org/amc-conference-2023/speakers => 200 | https://africanmarketingconfederation.org/amc-conference-2025-delegate-packages => 404 | https://africanmarketingconfederation.org/privacy-policy => 200 | https://africanmarketingconfederation.org/publications-2 => 200 | S10: =IF(H10>0,"Fix "&H10&" broken links (See Link Inventory tab for details).","") -> Fix 4 broken links (See Link Inventory tab for details). | T10: Links | U10: =IFERROR(HYPERLINK("#'Main'!B"&MATCH(TRIM(A10),Main!B:B,0),"Open"),HYPERLINK("#'Main'!B1","Open")) -> Open
A11: https://africanmarketingconfederation.org/amc-conference-2023/amc-awards | B11: Summary | G11: 19 | H11: =COUNTIFS('Link Inventory'!$A:$A,$A11,'Link Inventory'!$E:$E,"Internal",'Link Inventory'!$F:$F,404)+COUNTIFS('Link Inventory'!$A:$A,$A11,'Link Inventory'!$E:$E,"Internal",'Link Inventory'!$F:$F,"404") -> 4 | I11: 0 | J11: 2 | K11: 8 | L11: FALSE | M11: 0 | N11: 0.052819 | O11: 0 | P11: 0 | Q11: 0 | R11: https://africanmarketingconfederation.org/ => 200 | https://africanmarketingconfederation.org/amc-conference-2023 => 200 | https://africanmarketingconfederation.org/amc-conference-2023/amc-awards => 200 | https://africanmarketingconfederation.org/amc-conference-2023/gallery => 200 | https://africanmarketingconfederation.org/amc-conference-2023/partners => 200 | https://africanmarketingconfederation.org/amc-conference-2023/programme => 200 | https://africanmarketingconfederation.org/amc-conference-2023/speakers => 200 | https://africanmarketingconfederation.org/amc-conference-2025-delegate-packages => 404 | https://africanmarketingconfederation.org/privacy-policy => 200 | https://africanmarketingconfederation.org/publications-2 => 200 | S11: =IF(H11>0,"Fix "&H11&" broken links (See Link Inventory tab for details).","") -> Fix 4 broken links (See Link Inventory tab for details). | T11: Links | U11: =IFERROR(HYPERLINK("#'Main'!B"&MATCH(TRIM(A11),Main!B:B,0),"Open"),HYPERLINK("#'Main'!B1","Open")) -> Open
A12: https://africanmarketingconfederation.org/amc-conference-2023/book-now-thank-you | B12: Summary | G12: 2 | H12: =COUNTIFS('Link Inventory'!$A:$A,$A12,'Link Inventory'!$E:$E,"Internal",'Link Inventory'!$F:$F,404)+COUNTIFS('Link Inventory'!$A:$A,$A12,'Link Inventory'!$E:$E,"Internal",'Link Inventory'!$F:$F,"404") -> 4 | I12: 0 | J12: 0 | K12: 0 | L12: TRUE | M12: 0 | N12: 0.011213 | O12: 0 | P12: 0 | Q12: 0 | R12: https://africanmarketingconfederation.org/amc-conference-2025-delegate-packages => 404 | S12: =IF(H12>0,"Fix "&H12&" broken links (See Link Inventory tab for details).","") -> Fix 4 broken links (See Link Inventory tab for details). | T12: Links | U12: =IFERROR(HYPERLINK("#'Main'!B"&MATCH(TRIM(A12),Main!B:B,0),"Open"),HYPERLINK("#'Main'!B1","Open")) -> Open
A13: https://africanmarketingconfederation.org/amc-conference-2023/book-now | B13: Summary | G13: 19 | H13: =COUNTIFS('Link Inventory'!$A:$A,$A13,'Link Inventory'!$E:$E,"Internal",'Link Inventory'!$F:$F,404)+COUNTIFS('Link Inventory'!$A:$A,$A13,'Link Inventory'!$E:$E,"Internal",'Link Inventory'!$F:$F,"404") -> 4 | I13: 0 | J13: 2 | K13: 0 | L13: TRUE | M13: 0 | N13: 0.011213 | O13: 0 | P13: 0 | Q13: 0 | R13: https://africanmarketingconfederation.org/ => 200 | https://africanmarketingconfederation.org/amc-conference-2023 => 200 | https://africanmarketingconfederation.org/amc-conference-2023/amc-awards => 200 | https://africanmarketingconfederation.org/amc-conference-2023/gallery => 200 | https://africanmarketingconfederation.org/amc-conference-2023/partners => 200 | https://africanmarketingconfederation.org/amc-conference-2023/programme => 200 | https://africanmarketingconfederation.org/amc-conference-2023/speakers => 200 | https://africanmarketingconfederation.org/amc-conference-2025-delegate-packages => 404 | https://africanmarketingconfederation.org/privacy-policy => 200 | https://africanmarketingconfederation.org/publications-2 => 200 | S13: =IF(H13>0,"Fix "&H13&" broken links (See Link Inventory tab for details).","") -> Fix 4 broken links (See Link Inventory tab for details). | T13: Links | U13: =IFERROR(HYPERLINK("#'Main'!B"&MATCH(TRIM(A13),Main!B:B,0),"Open"),HYPERLINK("#'Main'!B1","Open")) -> Open
... A21: https://africanmarketingconfederation.org/amc-conference-2025-highlights | B21: Summary | G21: 16 | H21: =COUNTIFS('Link Inventory'!$A:$A,$A21,'Link Inventory'!$E:$E,"Internal",'Link Inventory'!$F:$F,404)+COUNTIFS('Link Inventory'!$A:$A,$A21,'Link Inventory'!$E:$E,"Internal",'Link Inventory'!$F:$F,"404") -> 4 | I21: 0 | J21: 49 | K21: 1 | L21: FALSE | M21: 2 | N21: 0.042516 | O21: 0 | P21: 0 | Q21: 0 | R21: https://africanmarketingconfederation.org/amc-conference-2025 => 200 | https://africanmarketingconfederation.org/amc-conference-2025-delegate-packages => 404 | https://africanmarketingconfederation.org/amc-marketing-conference-2024/amc-programme-2025 => 200 | https://africanmarketingconfederation.org/amc-marketing-conference-2024/awards-2025 => 200 | https://africanmarketingconfederation.org/amc-sponsors-2025 => 200 | https://africanmarketingconfederation.org/conference-faq-2025 => 200 | https://africanmarketingconfederation.org/privacy-policy => 200 | https://africanmarketingconfederation.org/publications-2 => 200 | https://africanmarketingconfederation.org/speakers-2025 => 200 | S21: =IF(H21>0,"Fix "&H21&" broken links (See Link Inventory tab for details).","") -> Fix 4 broken links (See Link Inventory tab for details). | T21: Links | U21: =IFERROR(HYPERLINK("#'Main'!B"&MATCH(TRIM(A21),Main!B:B,0),"Open"),HYPERLINK("#'Main'!B1","Open")) -> Open
A22: https://africanmarketingconfederation.org/amc-awards-2024 | B22: Detail | C22: http://www.africanmarketingconfederation.org/ | E22: 200 | F22: TRUE | G22: 0 | H22: 0 | I22: 0 | J22: 0 | K22: 0 | L22: FALSE | M22: 0 | N22: 0 | O22: 0 | P22: 0 | Q22: 0 | T22: LinksDetail | U22: =IFERROR(HYPERLINK("#'Main'!B"&MATCH(TRIM(A22),Main!B:B,0),"Open"),HYPERLINK("#'Main'!B1","Open")) -> Open
A23: https://africanmarketingconfederation.org/amc-awards-2024 | B23: Detail | C23: https://africanmarketingconfederation.org/amc-conference-2025 | D23: GHANA 2025 | E23: 200 | F23: TRUE | G23: 0 | H23: 0 | I23: 0 | J23: 0 | K23: 0 | L23: FALSE | M23: 0 | N23: 0 | O23: 0 | P23: 0 | Q23: 0 | T23: LinksDetail | U23: =IFERROR(HYPERLINK("#'Main'!B"&MATCH(TRIM(A23),Main!B:B,0),"Open"),HYPERLINK("#'Main'!B1","Open")) -> Open
A24: https://africanmarketingconfederation.org/amc-awards-2024 | B24: Detail | C24: https://africanmarketingconfederation.org/speakers-2025 | D24: SPEAKERS 2025 | E24: 200 | F24: TRUE | G24: 0 | H24: 0 | I24: 0 | J24: 0 | K24: 0 | L24: FALSE | M24: 0 | N24: 0 | O24: 0 | P24: 0 | Q24: 0 | T24: LinksDetail | U24: =IFERROR(HYPERLINK("#'Main'!B"&MATCH(TRIM(A24),Main!B:B,0),"Open"),HYPERLINK("#'Main'!B1","Open")) -> Open
A25: https://africanmarketingconfederation.org/amc-awards-2024 | B25: Detail | C25: https://africanmarketingconfederation.org/amc-marketing-conference-2024/amc-programme-2025 | D25: AMC PROGRAMME 2025 | E25: 200 | F25: TRUE | G25: 0 | H25: 0 | I25: 0 | J25: 0 | K25: 0 | L25: FALSE | M25: 0 | N25: 0 | O25: 0 | P25: 0 | Q25: 0 | T25: LinksDetail | U25: =IFERROR(HYPERLINK("#'Main'!B"&MATCH(TRIM(A25),Main!B:B,0),"Open"),HYPERLINK("#'Main'!B1","Open")) -> Open
A26: https://africanmarketingconfederation.org/amc-awards-2024 | B26: Detail | C26: https://africanmarketingconfederation.org/amc-marketing-conference-2024/awards-2025 | D26: AWARDS 2025 | E26: 200 | F26: TRUE | G26: 0 | H26: 0 | I26: 0 | J26: 0 | K26: 0 | L26: FALSE | M26: 0 | N26: 0 | O26: 0 | P26: 0 | Q26: 0 | T26: LinksDetail | U26: =IFERROR(HYPERLINK("#'Main'!B"&MATCH(TRIM(A26),Main!B:B,0),"Open"),HYPERLINK("#'Main'!B1","Open")) -> Open
A27: https://africanmarketingconfederation.org/amc-awards-2024 | B27: Detail | C27: https://africanmarketingconfederation.org/amc-sponsors-2025 | D27: SPONSORS 2025 | E27: 200 | F27: TRUE | G27: 0 | H27: 0 | I27: 0 | J27: 0 | K27: 0 | L27: FALSE | M27: 0 | N27: 0 | O27: 0 | P27: 0 | Q27: 0 | T27: LinksDetail | U27: =IFERROR(HYPERLINK("#'Main'!B"&MATCH(TRIM(A27),Main!B:B,0),"Open"),HYPERLINK("#'Main'!B1","Open")) -> Open
A28: https://africanmarketingconfederation.org/amc-awards-2024 | B28: Detail | C28: https://africanmarketingconfederation.org/conference-faq-2025 | D28: FAQ 2025 | E28: 200 | F28: TRUE | G28: 0 | H28: 0 | I28: 0 | J28: 0 | K28: 0 | L28: FALSE | M28: 0 | N28: 0 | O28: 0 | P28: 0 | Q28: 0 | T28: LinksDetail | U28: =IFERROR(HYPERLINK("#'Main'!B"&MATCH(TRIM(A28),Main!B:B,0),"Open"),HYPERLINK("#'Main'!B1","Open")) -> Open
A29: https://africanmarketingconfederation.org/amc-awards-2024 | B29: Detail | C29: https://africanmarketingconfederation.org/amc-conference-2025 | D29: GHANA 2025 | E29: 200 | F29: TRUE | G29: 0 | H29: 0 | I29: 0 | J29: 0 | K29: 0 | L29: FALSE | M29: 0 | N29: 0 | O29: 0 | P29: 0 | Q29: 0 | T29: LinksDetail | U29: =IFERROR(HYPERLINK("#'Main'!B"&MATCH(TRIM(A29),Main!B:B,0),"Open"),HYPERLINK("#'Main'!B1","Open")) -> Open
A30: https://africanmarketingconfederation.org/amc-awards-2024 | B30: Detail | C30: https://africanmarketingconfederation.org/speakers-2025 | D30: SPEAKERS 2025 | E30: 200 | F30: TRUE | G30: 0 | H30: 0 | I30: 0 | J30: 0 | K30: 0 | L30: FALSE | M30: 0 | N30: 0 | O30: 0 | P30: 0 | Q30: 0 | T30: LinksDetail | U30: =IFERROR(HYPERLINK("#'Main'!B"&MATCH(TRIM(A30),Main!B:B,0),"Open"),HYPERLINK("#'Main'!B1","Open")) -> Open
A31: https://africanmarketingconfederation.org/amc-awards-2024 | B31: Detail | C31: https://africanmarketingconfederation.org/amc-marketing-conference-2024/amc-programme-2025 | D31: AMC PROGRAMME 2025 | E31: 200 | F31: TRUE | G31: 0 | H31: 0 | I31: 0 | J31: 0 | K31: 0 | L31: FALSE | M31: 0 | N31: 0 | O31: 0 | P31: 0 | Q31: 0 | T31: LinksDetail | U31: =IFERROR(HYPERLINK("#'Main'!B"&MATCH(TRIM(A31),Main!B:B,0),"Open"),HYPERLINK("#'Main'!B1","Open")) -> Open
A32: https://africanmarketingconfederation.org/amc-awards-2024 | B32: Detail | C32: https://africanmarketingconfederation.org/amc-marketing-conference-2024/awards-2025 | D32: AWARDS 2025 | E32: 200 | F32: TRUE | G32: 0 | H32: 0 | I32: 0 | J32: 0 | K32: 0 | L32: FALSE | M32: 0 | N32: 0 | O32: 0 | P32: 0 | Q32: 0 | T32: LinksDetail | U32: =IFERROR(HYPERLINK("#'Main'!B"&MATCH(TRIM(A32),Main!B:B,0),"Open"),HYPERLINK("#'Main'!B1","Open")) -> Open
A33: https://africanmarketingconfederation.org/amc-awards-2024 | B33: Detail | C33: https://africanmarketingconfederation.org/amc-sponsors-2025 | D33: SPONSORS 2025 | E33: 200 | F33: TRUE | G33: 0 | H33: 0 | I33: 0 | J33: 0 | K33: 0 | L33: FALSE | M33: 0 | N33: 0 | O33: 0 | P33: 0 | Q33: 0 | T33: LinksDetail | U33: =IFERROR(HYPERLINK("#'Main'!B"&MATCH(TRIM(A33),Main!B:B,0),"Open"),HYPERLINK("#'Main'!B1","Open")) -> Open
A34: https://africanmarketingconfederation.org/amc-awards-2024 | B34: Detail | C34: https://africanmarketingconfederation.org/conference-faq-2025 | D34: FAQ 2025 | E34: 200 | F34: TRUE | G34: 0 | H34: 0 | I34: 0 | J34: 0 | K34: 0 | L34: FALSE | M34: 0 | N34: 0 | O34: 0 | P34: 0 | Q34: 0 | T34: LinksDetail | U34: =IFERROR(HYPERLINK("#'Main'!B"&MATCH(TRIM(A34),Main!B:B,0),"Open"),HYPERLINK("#'Main'!B1","Open")) -> Open
A35: https://africanmarketingconfederation.org/amc-awards-2024 | B35: Detail | C35: https://africanmarketingconfederation.org/publications-2 | D35: Strategic Marketing for Africa Magazine | E35: 200 | F35: TRUE | G35: 0 | H35: 0 | I35: 0 | J35: 0 | K35: 0 | L35: FALSE | M35: 0 | N35: 0 | O35: 0 | P35: 0 | Q35: 0 | T35: LinksDetail | U35: =IFERROR(HYPERLINK("#'Main'!B"&MATCH(TRIM(A35),Main!B:B,0),"Open"),HYPERLINK("#'Main'!B1","Open")) -> Open
A36: https://africanmarketingconfederation.org/amc-awards-2024 | B36: Detail | C36: https://www.facebook.com/The-African-Marketing-Confederation-108980418182403 | E36: 200 | F36: TRUE | G36: 0 | H36: 0 | I36: 0 | J36: 0 | K36: 0 | L36: FALSE | M36: 0 | N36: 0 | O36: 0 | P36: 0 | Q36: 0 | T36: LinksDetail | U36: =IFERROR(HYPERLINK("#'Main'!B"&MATCH(TRIM(A36),Main!B:B,0),"Open"),HYPERLINK("#'Main'!B1","Open")) -> Open
A37: https://africanmarketingconfederation.org/amc-awards-2024 | B37: Detail | C37: https://www.linkedin.com/company/african-marketing-confederation | E37: 200 | F37: TRUE | G37: 0 | H37: 0 | I37: 0 | J37: 0 | K37: 0 | L37: FALSE | M37: 0 | N37: 0 | O37: 0 | P37: 0 | Q37: 0 | T37: LinksDetail | U37: =IFERROR(HYPERLINK("#'Main'!B"&MATCH(TRIM(A37),Main!B:B,0),"Open"),HYPERLINK("#'Main'!B1","Open")) -> Open
A38: https://africanmarketingconfederation.org/amc-awards-2024 | B38: Detail | C38: https://twitter.com/connect_amc | E38: 403 | F38: FALSE | G38: 0 | H38: 0 | I38: 0 | J38: 0 | K38: 0 | L38: FALSE | M38: 0 | N38: 0 | O38: 0 | P38: 0 | Q38: 0 | T38: LinksDetail | U38: =IFERROR(HYPERLINK("#'Main'!B"&MATCH(TRIM(A38),Main!B:B,0),"Open"),HYPERLINK("#'Main'!B1","Open")) -> Open
A39: https://africanmarketingconfederation.org/amc-awards-2024 | B39: Detail | C39: https://africanmarketingconfederation.org/privacy-policy | D39: © 2021 by African Marketing Confederation | Privacy Policy | E39: 200 | F39: TRUE | G39: 0 | H39: 0 | I39: 0 | J39: 0 | K39: 0 | L39: FALSE | M39: 0 | N39: 0 | O39: 0 | P39: 0 | Q39: 0 | T39: LinksDetail | U39: =IFERROR(HYPERLINK("#'Main'!B"&MATCH(TRIM(A39),Main!B:B,0),"Open"),HYPERLINK("#'Main'!B1","Open")) -> Open
A40: https://africanmarketingconfederation.org/amc-awards-2024 | B40: Detail | C40: https://africanmarketingconfederation.org/amc-conference-2025-delegate-packages | D40: Return to Shop | E40: 404 | F40: FALSE | G40: 0 | H40: 0 | I40: 0 | J40: 0 | K40: 0 | L40: FALSE | M40: 0 | N40: 0 | O40: 0 | P40: 0 | Q40: 0 | T40: LinksDetail | U40: =IFERROR(HYPERLINK("#'Main'!B"&MATCH(TRIM(A40),Main!B:B,0),"Open"),HYPERLINK("#'Main'!B1","Open")) -> Open
A41: https://africanmarketingconfederation.org/amc-awards-2024 | B41: Detail | C41: https://africanmarketingconfederation.org/amc-conference-2025-delegate-packages | D41: Continue Shopping | E41: 404 | F41: FALSE | G41: 0 | H41: 0 | I41: 0 | J41: 0 | K41: 0 | L41: FALSE | M41: 0 | N41: 0 | O41: 0 | P41: 0 | Q41: 0 | T41: LinksDetail | U41: =IFERROR(HYPERLINK("#'Main'!B"&MATCH(TRIM(A41),Main!B:B,0),"Open"),HYPERLINK("#'Main'!B1","Open")) -> Open
A42: https://africanmarketingconfederation.org/about-us | B42: Detail | C42: https://africanmarketingconfederation.org/ | E42: 200 | F42: TRUE | G42: 0 | H42: 0 | I42: 0 | J42: 0 | K42: 0 | L42: FALSE | M42: 0 | N42: 0 | O42: 0 | P42: 0 | Q42: 0 | T42: LinksDetail | U42: =IFERROR(HYPERLINK("#'Main'!B"&MATCH(TRIM(A42),Main!B:B,0),"Open"),HYPERLINK("#'Main'!B1","Open")) -> Open
A43: https://africanmarketingconfederation.org/about-us | B43: Detail | C43: https://africanmarketingconfederation.org/ | D43: HOME | E43: 200 | F43: TRUE | G43: 0 | H43: 0 | I43: 0 | J43: 0 | K43: 0 | L43: FALSE | M43: 0 | N43: 0 | O43: 0 | P43: 0 | Q43: 0 | T43: LinksDetail | U43: =IFERROR(HYPERLINK("#'Main'!B"&MATCH(TRIM(A43),Main!B:B,0),"Open"),HYPERLINK("#'Main'!B1","Open")) -> Open
A44: https://africanmarketingconfederation.org/about-us | B44: Detail | C44: https://africanmarketingconfederation.org/about-us | D44: ABOUT US | E44: 200 | F44: TRUE | G44: 0 | H44: 0 | I44: 0 | J44: 0 | K44: 0 | L44: FALSE | M44: 0 | N44: 0 | O44: 0 | P44: 0 | Q44: 0 | T44: LinksDetail | U44: =IFERROR(HYPERLINK("#'Main'!B"&MATCH(TRIM(A44),Main!B:B,0),"Open"),HYPERLINK("#'Main'!B1","Open")) -> Open
A45: https://africanmarketingconfederation.org/about-us | B45: Detail | C45: https://africanmarketingconfederation.org/sub-committees | D45: AMC COMMITTEES | E45: 200 | F45: TRUE | G45: 0 | H45: 0 | I45: 0 | J45: 0 | K45: 0 | L45: FALSE | M45: 0 | N45: 0 | O45: 0 | P45: 0 | Q45: 0 | T45: LinksDetail | U45: =IFERROR(HYPERLINK("#'Main'!B"&MATCH(TRIM(A45),Main!B:B,0),"Open"),HYPERLINK("#'Main'!B1","Open")) -> Open
A46: https://africanmarketingconfederation.org/about-us | B46: Detail | C46: https://africanmarketingconfederation.org/members | D46: MEMBERS | E46: 200 | F46: TRUE | G46: 0 | H46: 0 | I46: 0 | J46: 0 | K46: 0 | L46: FALSE | M46: 0 | N46: 0 | O46: 0 | P46: 0 | Q46: 0 | T46: LinksDetail | U46: =IFERROR(HYPERLINK("#'Main'!B"&MATCH(TRIM(A46),Main!B:B,0),"Open"),HYPERLINK("#'Main'!B1","Open")) -> Open
A47: https://africanmarketingconfederation.org/about-us | B47: Detail | C47: https://africanmarketingconfederation.org/african-marketing-confederation-tourism-chapter | D47: TOURISM CHAPTER | E47: 200 | F47: TRUE | G47: 0 | H47: 0 | I47: 0 | J47: 0 | K47: 0 | L47: FALSE | M47: 0 | N47: 0 | O47: 0 | P47: 0 | Q47: 0 | T47: LinksDetail | U47: =IFERROR(HYPERLINK("#'Main'!B"&MATCH(TRIM(A47),Main!B:B,0),"Open"),HYPERLINK("#'Main'!B1","Open")) -> Open
A48: https://africanmarketingconfederation.org/about-us | B48: Detail | C48: https://africanmarketingconfederation.org/education | D48: EDUCATION | E48: 200 | F48: TRUE | G48: 0 | H48: 0 | I48: 0 | J48: 0 | K48: 0 | L48: FALSE | M48: 0 | N48: 0 | O48: 0 | P48: 0 | Q48: 0 | T48: LinksDetail | U48: =IFERROR(HYPERLINK("#'Main'!B"&MATCH(TRIM(A48),Main!B:B,0),"Open"),HYPERLINK("#'Main'!B1","Open")) -> Open
A49: https://africanmarketingconfederation.org/about-us | B49: Detail | C49: https://africanmarketingconfederation.org/chartered-marketer-africa | D49: CHARTERED MARKETER (AFRICA) | E49: 200 | F49: TRUE | G49: 0 | H49: 0 | I49: 0 | J49: 0 | K49: 0 | L49: FALSE | M49: 0 | N49: 0 | O49: 0 | P49: 0 | Q49: 0 | T49: LinksDetail | U49: =IFERROR(HYPERLINK("#'Main'!B"&MATCH(TRIM(A49),Main!B:B,0),"Open"),HYPERLINK("#'Main'!B1","Open")) -> Open
A50: https://africanmarketingconfederation.org/about-us | B50: Detail | C50: https://africanmarketingconfederation.org/certified-professional-marketer-africa | D50: CPM(A) | E50: 200 | F50: TRUE | G50: 0 | H50: 0 | I50: 0 | J50: 0 | K50: 0 | L50: FALSE | M50: 0 | N50: 0 | O50: 0 | P50: 0 | Q50: 0 | T50: LinksDetail | U50: =IFERROR(HYPERLINK("#'Main'!B"&MATCH(TRIM(A50),Main!B:B,0),"Open"),HYPERLINK("#'Main'!B1","Open")) -> Open
A51: https://africanmarketingconfederation.org/about-us | B51: Detail | C51: https://africanmarketingconfederation.org/news-articles | D51: NEWS & PUBLICATIONS | E51: 200 | F51: TRUE | G51: 0 | H51: 0 | I51: 0 | J51: 0 | K51: 0 | L51: FALSE | M51: 0 | N51: 0 | O51: 0 | P51: 0 | Q51: 0 | T51: LinksDetail | U51: =IFERROR(HYPERLINK("#'Main'!B"&MATCH(TRIM(A51),Main!B:B,0),"Open"),HYPERLINK("#'Main'!B1","Open")) -> Open
A52: https://africanmarketingconfederation.org/about-us | B52: Detail | C52: https://africanmarketingconfederation.org/news-articles | D52: NEWS ARTICLES | E52: 200 | F52: TRUE | G52: 0 | H52: 0 | I52: 0 | J52: 0 | K52: 0 | L52: FALSE | M52: 0 | N52: 0 | O52: 0 | P52: 0 | Q52: 0 | T52: LinksDetail | U52: =IFERROR(HYPERLINK("#'Main'!B"&MATCH(TRIM(A52),Main!B:B,0),"Open"),HYPERLINK("#'Main'!B1","Open")) -> Open
A53: https://africanmarketingconfederation.org/about-us | B53: Detail | C53: https://africanmarketingconfederation.org/publications-2 | D53: PUBLICATIONS | E53: 200 | F53: TRUE | G53: 0 | H53: 0 | I53: 0 | J53: 0 | K53: 0 | L53: FALSE | M53: 0 | N53: 0 | O53: 0 | P53: 0 | Q53: 0 | T53: LinksDetail | U53: =IFERROR(HYPERLINK("#'Main'!B"&MATCH(TRIM(A53),Main!B:B,0),"Open"),HYPERLINK("#'Main'!B1","Open")) -> Open
A54: https://africanmarketingconfederation.org/about-us | B54: Detail | C54: https://africanmarketingconfederation.org/amc-conference-2026 | D54: AMC Conference | E54: 200 | F54: TRUE | G54: 0 | H54: 0 | I54: 0 | J54: 0 | K54: 0 | L54: FALSE | M54: 0 | N54: 0 | O54: 0 | P54: 0 | Q54: 0 | T54: LinksDetail | U54: =IFERROR(HYPERLINK("#'Main'!B"&MATCH(TRIM(A54),Main!B:B,0),"Open"),HYPERLINK("#'Main'!B1","Open")) -> Open
... A75: https://africanmarketingconfederation.org/about-us | B75: Detail | C75: https://africanmarketingconfederation.org/publications-2 | D75: Strategic Marketing for Africa Magazine | E75: 200 | F75: TRUE | G75: 0 | H75: 0 | I75: 0 | J75: 0 | K75: 0 | L75: FALSE | M75: 0 | N75: 0 | O75: 0 | P75: 0 | Q75: 0 | T75: LinksDetail | U75: =IFERROR(HYPERLINK("#'Main'!B"&MATCH(TRIM(A75),Main!B:B,0),"Open"),HYPERLINK("#'Main'!B1","Open")) -> Open
A76: https://africanmarketingconfederation.org/about-us | B76: Detail | C76: https://www.facebook.com/The-African-Marketing-Confederation-108980418182403 | E76: 200 | F76: TRUE | G76: 0 | H76: 0 | I76: 0 | J76: 0 | K76: 0 | L76: FALSE | M76: 0 | N76: 0 | O76: 0 | P76: 0 | Q76: 0 | T76: LinksDetail | U76: =IFERROR(HYPERLINK("#'Main'!B"&MATCH(TRIM(A76),Main!B:B,0),"Open"),HYPERLINK("#'Main'!B1","Open")) -> Open
A77: https://africanmarketingconfederation.org/about-us | B77: Detail | C77: https://www.linkedin.com/company/african-marketing-confederation | E77: 200 | F77: TRUE | G77: 0 | H77: 0 | I77: 0 | J77: 0 | K77: 0 | L77: FALSE | M77: 0 | N77: 0 | O77: 0 | P77: 0 | Q77: 0 | T77: LinksDetail | U77: =IFERROR(HYPERLINK("#'Main'!B"&MATCH(TRIM(A77),Main!B:B,0),"Open"),HYPERLINK("#'Main'!B1","Open")) -> Open
A78: https://africanmarketingconfederation.org/about-us | B78: Detail | C78: https://africanmarketingconfederation.org/privacy-policy | D78: © 2026 by African Marketing Confederation | Privacy Policy | E78: 200 | F78: TRUE | G78: 0 | H78: 0 | I78: 0 | J78: 0 | K78: 0 | L78: FALSE | M78: 0 | N78: 0 | O78: 0 | P78: 0 | Q78: 0 | T78: LinksDetail | U78: =IFERROR(HYPERLINK("#'Main'!B"&MATCH(TRIM(A78),Main!B:B,0),"Open"),HYPERLINK("#'Main'!B1","Open")) -> Open
A79: https://africanmarketingconfederation.org/about-us | B79: Detail | C79: https://africanmarketingconfederation.org/amc-conference-2025-delegate-packages | D79: Return to Shop | E79: 404 | F79: FALSE | G79: 0 | H79: 0 | I79: 0 | J79: 0 | K79: 0 | L79: FALSE | M79: 0 | N79: 0 | O79: 0 | P79: 0 | Q79: 0 | T79: LinksDetail | U79: =IFERROR(HYPERLINK("#'Main'!B"&MATCH(TRIM(A79),Main!B:B,0),"Open"),HYPERLINK("#'Main'!B1","Open")) -> Open
A80: https://africanmarketingconfederation.org/about-us | B80: Detail | C80: https://africanmarketingconfederation.org/amc-conference-2025-delegate-packages | D80: Continue Shopping | E80: 404 | F80: FALSE | G80: 0 | H80: 0 | I80: 0 | J80: 0 | K80: 0 | L80: FALSE | M80: 0 | N80: 0 | O80: 0 | P80: 0 | Q80: 0 | T80: LinksDetail | U80: =IFERROR(HYPERLINK("#'Main'!B"&MATCH(TRIM(A80),Main!B:B,0),"Open"),HYPERLINK("#'Main'!B1","Open")) -> Open
A81: https://africanmarketingconfederation.org/ | B81: Detail | C81: https://africanmarketingconfederation.org/ | E81: 200 | F81: TRUE | G81: 0 | H81: 0 | I81: 0 | J81: 0 | K81: 0 | L81: FALSE | M81: 0 | N81: 0 | O81: 0 | P81: 0 | Q81: 0 | T81: LinksDetail | U81: =IFERROR(HYPERLINK("#'Main'!B"&MATCH(TRIM(A81),Main!B:B,0),"Open"),HYPERLINK("#'Main'!B1","Open")) -> Open
A82: https://africanmarketingconfederation.org/ | B82: Detail | C82: https://africanmarketingconfederation.org/ | D82: HOME | E82: 200 | F82: TRUE | G82: 0 | H82: 0 | I82: 0 | J82: 0 | K82: 0 | L82: FALSE | M82: 0 | N82: 0 | O82: 0 | P82: 0 | Q82: 0 | T82: LinksDetail | U82: =IFERROR(HYPERLINK("#'Main'!B"&MATCH(TRIM(A82),Main!B:B,0),"Open"),HYPERLINK("#'Main'!B1","Open")) -> Open
A83: https://africanmarketingconfederation.org/ | B83: Detail | C83: https://africanmarketingconfederation.org/about-us | D83: ABOUT US | E83: 200 | F83: TRUE | G83: 0 | H83: 0 | I83: 0 | J83: 0 | K83: 0 | L83: FALSE | M83: 0 | N83: 0 | O83: 0 | P83: 0 | Q83: 0 | T83: LinksDetail | U83: =IFERROR(HYPERLINK("#'Main'!B"&MATCH(TRIM(A83),Main!B:B,0),"Open"),HYPERLINK("#'Main'!B1","Open")) -> Open
A84: https://africanmarketingconfederation.org/ | B84: Detail | C84: https://africanmarketingconfederation.org/sub-committees | D84: AMC COMMITTEES | E84: 200 | F84: TRUE | G84: 0 | H84: 0 | I84: 0 | J84: 0 | K84: 0 | L84: FALSE | M84: 0 | N84: 0 | O84: 0 | P84: 0 | Q84: 0 | T84: LinksDetail | U84: =IFERROR(HYPERLINK("#'Main'!B"&MATCH(TRIM(A84),Main!B:B,0),"Open"),HYPERLINK("#'Main'!B1","Open")) -> Open
A85: https://africanmarketingconfederation.org/ | B85: Detail | C85: https://africanmarketingconfederation.org/members | D85: MEMBERS | E85: 200 | F85: TRUE | G85: 0 | H85: 0 | I85: 0 | J85: 0 | K85: 0 | L85: FALSE | M85: 0 | N85: 0 | O85: 0 | P85: 0 | Q85: 0 | T85: LinksDetail | U85: =IFERROR(HYPERLINK("#'Main'!B"&MATCH(TRIM(A85),Main!B:B,0),"Open"),HYPERLINK("#'Main'!B1","Open")) -> Open
A86: https://africanmarketingconfederation.org/ | B86: Detail | C86: https://africanmarketingconfederation.org/african-marketing-confederation-tourism-chapter | D86: TOURISM CHAPTER | E86: 200 | F86: TRUE | G86: 0 | H86: 0 | I86: 0 | J86: 0 | K86: 0 | L86: FALSE | M86: 0 | N86: 0 | O86: 0 | P86: 0 | Q86: 0 | T86: LinksDetail | U86: =IFERROR(HYPERLINK("#'Main'!B"&MATCH(TRIM(A86),Main!B:B,0),"Open"),HYPERLINK("#'Main'!B1","Open")) -> Open
A87: https://africanmarketingconfederation.org/ | B87: Detail | C87: https://africanmarketingconfederation.org/education | D87: EDUCATION | E87: 200 | F87: TRUE | G87: 0 | H87: 0 | I87: 0 | J87: 0 | K87: 0 | L87: FALSE | M87: 0 | N87: 0 | O87: 0 | P87: 0 | Q87: 0 | T87: LinksDetail | U87: =IFERROR(HYPERLINK("#'Main'!B"&MATCH(TRIM(A87),Main!B:B,0),"Open"),HYPERLINK("#'Main'!B1","Open")) -> Open
A88: https://africanmarketingconfederation.org/ | B88: Detail | C88: https://africanmarketingconfederation.org/chartered-marketer-africa | D88: CHARTERED MARKETER (AFRICA) | E88: 200 | F88: TRUE | G88: 0 | H88: 0 | I88: 0 | J88: 0 | K88: 0 | L88: FALSE | M88: 0 | N88: 0 | O88: 0 | P88: 0 | Q88: 0 | T88: LinksDetail | U88: =IFERROR(HYPERLINK("#'Main'!B"&MATCH(TRIM(A88),Main!B:B,0),"Open"),HYPERLINK("#'Main'!B1","Open")) -> Open
A89: https://africanmarketingconfederation.org/ | B89: Detail | C89: https://africanmarketingconfederation.org/certified-professional-marketer-africa | D89: CPM(A) | E89: 200 | F89: TRUE | G89: 0 | H89: 0 | I89: 0 | J89: 0 | K89: 0 | L89: FALSE | M89: 0 | N89: 0 | O89: 0 | P89: 0 | Q89: 0 | T89: LinksDetail | U89: =IFERROR(HYPERLINK("#'Main'!B"&MATCH(TRIM(A89),Main!B:B,0),"Open"),HYPERLINK("#'Main'!B1","Open")) -> Open
A90: https://africanmarketingconfederation.org/ | B90: Detail | C90: https://africanmarketingconfederation.org/news-articles | D90: NEWS & PUBLICATIONS | E90: 200 | F90: TRUE | G90: 0 | H90: 0 | I90: 0 | J90: 0 | K90: 0 | L90: FALSE | M90: 0 | N90: 0 | O90: 0 | P90: 0 | Q90: 0 | T90: LinksDetail | U90: =IFERROR(HYPERLINK("#'Main'!B"&MATCH(TRIM(A90),Main!B:B,0),"Open"),HYPERLINK("#'Main'!B1","Open")) -> Open
A91: https://africanmarketingconfederation.org/ | B91: Detail | C91: https://africanmarketingconfederation.org/news-articles | D91: NEWS ARTICLES | E91: 200 | F91: TRUE | G91: 0 | H91: 0 | I91: 0 | J91: 0 | K91: 0 | L91: FALSE | M91: 0 | N91: 0 | O91: 0 | P91: 0 | Q91: 0 | T91: LinksDetail | U91: =IFERROR(HYPERLINK("#'Main'!B"&MATCH(TRIM(A91),Main!B:B,0),"Open"),HYPERLINK("#'Main'!B1","Open")) -> Open
A92: https://africanmarketingconfederation.org/ | B92: Detail | C92: https://africanmarketingconfederation.org/publications-2 | D92: PUBLICATIONS | E92: 200 | F92: TRUE | G92: 0 | H92: 0 | I92: 0 | J92: 0 | K92: 0 | L92: FALSE | M92: 0 | N92: 0 | O92: 0 | P92: 0 | Q92: 0 | T92: LinksDetail | U92: =IFERROR(HYPERLINK("#'Main'!B"&MATCH(TRIM(A92),Main!B:B,0),"Open"),HYPERLINK("#'Main'!B1","Open")) -> Open
A93: https://africanmarketingconfederation.org/ | B93: Detail | C93: https://africanmarketingconfederation.org/amc-conference-2026 | D93: AMC Conference | E93: 200 | F93: TRUE | G93: 0 | H93: 0 | I93: 0 | J93: 0 | K93: 0 | L93: FALSE | M93: 0 | N93: 0 | O93: 0 | P93: 0 | Q93: 0 | T93: LinksDetail | U93: =IFERROR(HYPERLINK("#'Main'!B"&MATCH(TRIM(A93),Main!B:B,0),"Open"),HYPERLINK("#'Main'!B1","Open")) -> Open
... A119: https://africanmarketingconfederation.org/ | B119: Detail | C119: https://africanmarketingconfederation.org/subscribe | D119: Subscribe | E119: 200 | F119: TRUE | G119: 0 | H119: 0 | I119: 0 | J119: 0 | K119: 0 | L119: FALSE | M119: 0 | N119: 0 | O119: 0 | P119: 0 | Q119: 0 | T119: LinksDetail | U119: =IFERROR(HYPERLINK("#'Main'!B"&MATCH(TRIM(A119),Main!B:B,0),"Open"),HYPERLINK("#'Main'!B1","Open")) -> Open
A120: https://africanmarketingconfederation.org/ | B120: Detail | C120: https://africanmarketingconfederation.org/lays-world-cup-marketing-strategy-focuses-on-fan-fun-and-togetherness | E120: 200 | F120: TRUE | G120: 0 | H120: 0 | I120: 0 | J120: 0 | K120: 0 | L120: FALSE | M120: 0 | N120: 0 | O120: 0 | P120: 0 | Q120: 0 | T120: LinksDetail | U120: =IFERROR(HYPERLINK("#'Main'!B"&MATCH(TRIM(A120),Main!B:B,0),"Open"),HYPERLINK("#'Main'!B1","Open")) -> Open
